class_version major=61 minor=0
this_class    InputKt
super_class   java/lang/Object
access_flags  0x0031
method        double (I)I 0x0019
  code        max_stack=2 max_locals=2
    0000 iconst_0
    0001 istore_1
    0002 iload_0
    0003 iconst_2
    0004 imul
    0005 op_0xAC
method        isType (Ljava/lang/Object;)Z 0x1019
  code        max_stack=3 max_locals=2
    0000 aload_0
    0001 ldc "value"
    0003 invokestatic Method(kotlin/jvm/internal/Intrinsics.checkNotNullParameter:(Ljava/lang/Object;Ljava/lang/String;)V)
    0006 iconst_0
    0007 istore_1
    0008 aload_0
    0009 iconst_3
    0010 ldc "T"
    0012 invokestatic Method(kotlin/jvm/internal/Intrinsics.reifiedOperationMarker:(ILjava/lang/String;)V)
    0015 instanceof Class(java/lang/Object)
    0018 op_0xAC
  attr        Signature (2 bytes)
method        main ()V 0x0019
  code        max_stack=2 max_locals=2
    0000 ldc "hello"
    0002 astore_0
    0003 iconst_0
    0004 istore_1
    0005 iconst_1
    0006 istore_0
    0007 getstatic Field(java/lang/System.out:Ljava/io/PrintStream;)
    0010 iload_0
    0011 invokevirtual Method(java/io/PrintStream.println:(Z)V)
    0014 ldc "hello"
    0016 astore_0
    0017 iconst_0
    0018 istore_1
    0019 aload_0
    0020 instanceof Class(java/lang/Integer)
    0023 istore_0
    0024 getstatic Field(java/lang/System.out:Ljava/io/PrintStream;)
    0027 iload_0
    0028 invokevirtual Method(java/io/PrintStream.println:(Z)V)
    0031 bipush 21
    0033 istore_0
    0034 iconst_0
    0035 istore_1
    0036 iload_0
    0037 iconst_2
    0038 imul
    0039 istore_0
    0040 getstatic Field(java/lang/System.out:Ljava/io/PrintStream;)
    0043 iload_0
    0044 invokevirtual Method(java/io/PrintStream.println:(I)V)
    0047 return
method        main ([Ljava/lang/String;)V 0x1009
  code        max_stack=0 max_locals=1
    0000 invokestatic Method(InputKt.main:()V)
    0003 return
class_attr    SourceDebugExtension (154 bytes)
class_attr    RuntimeInvisibleAnnotations (14 bytes)
