class_version major=61 minor=0
this_class    InputKt
super_class   java/lang/Object
access_flags  0x0031
method        main ()V 0x0019
  code        max_stack=2 max_locals=1
    0000 iconst_1
    0001 invokestatic Method(InputKt.pick:(Z)LTag;)
    0004 invokeinterface InterfaceMethod(Tag.id:()I)
    0009 istore_0
    0010 getstatic Field(java/lang/System.out:Ljava/io/PrintStream;)
    0013 iload_0
    0014 invokevirtual Method(java/io/PrintStream.println:(I)V)
    0017 iconst_0
    0018 invokestatic Method(InputKt.pick:(Z)LTag;)
    0021 invokeinterface InterfaceMethod(Tag.id:()I)
    0026 istore_0
    0027 getstatic Field(java/lang/System.out:Ljava/io/PrintStream;)
    0030 iload_0
    0031 invokevirtual Method(java/io/PrintStream.println:(I)V)
    0034 return
method        main ([Ljava/lang/String;)V 0x1009
  code        max_stack=0 max_locals=1
    0000 invokestatic Method(InputKt.main:()V)
    0003 return
method        pick (Z)LTag; 0x0019
  code        max_stack=2 max_locals=2
    0000 iload_0
    0001 ifeq 15
    0004 new Class(A)
    0007 dup
    0008 invokespecial Method(A.<init>:()V)
    0011 astore_1
    0012 goto 23
    0015 new Class(B)
    0018 dup
    0019 invokespecial Method(B.<init>:()V)
    0022 astore_1
    0023 aload_1
    0024 checkcast Class(Tag)
    0027 areturn
    sub_attr  StackMapTable (9 bytes)
  attr        RuntimeInvisibleAnnotations (6 bytes)
