class_version major=61 minor=0
this_class    InputKt
super_class   java/lang/Object
access_flags  0x0031
method        main ()V 0x0019
  code        max_stack=3 max_locals=2
    0000 getstatic Field(Op.ADD:LOp;)
    0003 checkcast Class(Calc)
    0006 astore_0
    0007 getstatic Field(Op.MUL:LOp;)
    0010 checkcast Class(Calc)
    0013 astore_1
    0014 aload_0
    0015 iconst_2
    0016 iconst_3
    0017 invokestatic Method(InputKt.runIt:(LCalc;II)Ljava/lang/String;)
    0020 getstatic Field(java/lang/System.out:Ljava/io/PrintStream;)
    0023 swap
    0024 invokevirtual Method(java/io/PrintStream.println:(Ljava/lang/Object;)V)
    0027 aload_1
    0028 iconst_4
    0029 iconst_5
    0030 invokestatic Method(InputKt.runIt:(LCalc;II)Ljava/lang/String;)
    0033 getstatic Field(java/lang/System.out:Ljava/io/PrintStream;)
    0036 swap
    0037 invokevirtual Method(java/io/PrintStream.println:(Ljava/lang/Object;)V)
    0040 return
method        main ([Ljava/lang/String;)V 0x1009
  code        max_stack=0 max_locals=1
    0000 invokestatic Method(InputKt.main:()V)
    0003 return
method        runIt (LCalc;II)Ljava/lang/String; 0x0019
  code        max_stack=4 max_locals=4
    0000 aload_0
    0001 ldc "c"
    0003 invokestatic Method(kotlin/jvm/internal/Intrinsics.checkNotNullParameter:(Ljava/lang/Object;Ljava/lang/String;)V)
    0006 aload_0
    0007 invokeinterface InterfaceMethod(Calc.label:()Ljava/lang/String;)
    0012 aload_0
    0013 iload_1
    0014 iload_2
    0015 invokeinterface InterfaceMethod(Calc.apply:(II)I)
    0020 istore_3
    0021 iload_1
    0022 iload_2
    0023 iload_3
    0024 invokedynamic InvokeDynamic(makeConcatWithConstants:(Ljava/lang/String;III)Ljava/lang/String;)
    0029 areturn
  attr        RuntimeInvisibleAnnotations (6 bytes)
  attr        RuntimeInvisibleParameterAnnotations (11 bytes)
class_attr    BootstrapMethods (8 bytes)
