class_version major=61 minor=0
this_class    InputKt$Lambda$0
super_class   java/lang/Object
access_flags  0x0021
interfaces    [kotlin/jvm/functions/Function1]
method        <init> ()V 0x0001
  code        max_stack=1 max_locals=1
    0000 aload_0
    0001 invokespecial Method(java/lang/Object.<init>:()V)
    0004 return
method        invoke (Ljava/lang/Object;)Ljava/lang/Object; 0x0001
  code        max_stack=3 max_locals=2
    0000 aload_1
    0001 checkcast Class(java/lang/String)
    0004 getstatic Field(java/util/Locale.ROOT:Ljava/util/Locale;)
    0007 invokevirtual Method(java/lang/String.toUpperCase:(Ljava/util/Locale;)Ljava/lang/String;)
    0010 dup
    0011 ldc "toUpperCase(...)"
    0013 invokestatic Method(kotlin/jvm/internal/Intrinsics.checkNotNullExpressionValue:(Ljava/lang/Object;Ljava/lang/String;)V)
    0016 areturn
