class_version major=61 minor=0
this_class    InputKt
super_class   java/lang/Object
access_flags  0x0031
method        M (Lkotlin/jvm/functions/Function0;Lkotlin/jvm/functions/Function0;Lkotlin/jvm/functions/Function0;Lkotlin/jvm/functions/Function0;Lkotlin/jvm/functions/Function0;Landroidx/compose/runtime/Composer;I)V 0x0019
  code        max_stack=2 max_locals=8
    0000 aload_0
    0001 ldc "c1"
    0003 invokestatic Method(kotlin/jvm/internal/Intrinsics.checkNotNullParameter:(Ljava/lang/Object;Ljava/lang/String;)V)
    0006 aload_1
    0007 ldc "c2"
    0009 invokestatic Method(kotlin/jvm/internal/Intrinsics.checkNotNullParameter:(Ljava/lang/Object;Ljava/lang/String;)V)
    0012 aload_2
    0013 ldc "c3"
    0015 invokestatic Method(kotlin/jvm/internal/Intrinsics.checkNotNullParameter:(Ljava/lang/Object;Ljava/lang/String;)V)
    0018 aload_3
    0019 ldc "c4"
    0021 invokestatic Method(kotlin/jvm/internal/Intrinsics.checkNotNullParameter:(Ljava/lang/Object;Ljava/lang/String;)V)
    0024 aload 4
    0026 ldc "c5"
    0028 invokestatic Method(kotlin/jvm/internal/Intrinsics.checkNotNullParameter:(Ljava/lang/Object;Ljava/lang/String;)V)
    0031 iconst_0
    0032 istore 7
    0034 aload_0
    0035 invokeinterface InterfaceMethod(kotlin/jvm/functions/Function0.invoke:()Ljava/lang/Object;)
    0040 pop
    0041 aload_1
    0042 invokeinterface InterfaceMethod(kotlin/jvm/functions/Function0.invoke:()Ljava/lang/Object;)
    0047 pop
    0048 aload_2
    0049 invokeinterface InterfaceMethod(kotlin/jvm/functions/Function0.invoke:()Ljava/lang/Object;)
    0054 pop
    0055 aload_3
    0056 invokeinterface InterfaceMethod(kotlin/jvm/functions/Function0.invoke:()Ljava/lang/Object;)
    0061 pop
    0062 aload 4
    0064 invokeinterface InterfaceMethod(kotlin/jvm/functions/Function0.invoke:()Ljava/lang/Object;)
    0069 pop
    0070 return
  attr        Signature (2 bytes)
  attr        RuntimeInvisibleAnnotations (6 bytes)
  attr        RuntimeInvisibleParameterAnnotations (39 bytes)
