class_version major=61 minor=0
this_class    InputKt
super_class   java/lang/Object
access_flags  0x0031
method        first (Ljava/util/List;)I 0x0019
  code        max_stack=2 max_locals=1
    0000 aload_0
    0001 ldc "actions"
    0003 invokestatic Method(kotlin/jvm/internal/Intrinsics.checkNotNullParameter:(Ljava/lang/Object;Ljava/lang/String;)V)
    0006 aload_0
    0007 iconst_0
    0008 invokeinterface InterfaceMethod(java/util/List.get:(I)Ljava/lang/Object;)
    0013 checkcast Class(Action)
    0016 invokeinterface InterfaceMethod(Action.run:()I)
    0021 ireturn
  attr        Signature (2 bytes)
  attr        RuntimeInvisibleParameterAnnotations (7 bytes)
method        main ()V 0x0019
  code        max_stack=3 max_locals=2
    0000 new Class(IncAction)
    0003 dup
    0004 iconst_5
    0005 invokespecial Method(IncAction.<init>:(I)V)
    0008 invokestatic Method(kotlin/collections/CollectionsKt.listOf:(Ljava/lang/Object;)Ljava/util/List;)
    0011 astore_0
    0012 aload_0
    0013 invokestatic Method(InputKt.first:(Ljava/util/List;)I)
    0016 istore_1
    0017 getstatic Field(java/lang/System.out:Ljava/io/PrintStream;)
    0020 iload_1
    0021 invokevirtual Method(java/io/PrintStream.println:(I)V)
    0024 return
method        main ([Ljava/lang/String;)V 0x1009
  code        max_stack=0 max_locals=1
    0000 invokestatic Method(InputKt.main:()V)
    0003 return
