class_version major=61 minor=0
this_class    Logger
super_class   java/lang/Object
access_flags  0x0021
field         tag : Ljava/lang/String; 0x0001
method        <init> (Ljava/lang/String;)V 0x0001
  code        max_stack=2 max_locals=2
    0000 aload_0
    0001 invokespecial Method(java/lang/Object.<init>:()V)
    0004 aload_0
    0005 aload_1
    0006 putfield Field(Logger.tag:Ljava/lang/String;)
    0009 aload_1
    0010 invokedynamic InvokeDynamic(makeConcatWithConstants:(Ljava/lang/String;)Ljava/lang/String;)
    0015 getstatic Field(java/lang/System.out:Ljava/io/PrintStream;)
    0018 swap
    0019 invokevirtual Method(java/io/PrintStream.println:(Ljava/lang/Object;)V)
    0022 return
method        getTag ()Ljava/lang/String; 0x0001
  code        max_stack=1 max_locals=1
    0000 aload_0
    0001 getfield Field(Logger.tag:Ljava/lang/String;)
    0004 areturn
  attr        RuntimeInvisibleAnnotations (6 bytes)
method        log (Ljava/lang/String;)V 0x0001
  code        max_stack=2 max_locals=3
    0000 aload_0
    0001 getfield Field(Logger.tag:Ljava/lang/String;)
    0004 astore_2
    0005 aload_2
    0006 aload_1
    0007 invokedynamic InvokeDynamic(makeConcatWithConstants:(Ljava/lang/String;Ljava/lang/String;)Ljava/lang/String;)
    0012 getstatic Field(java/lang/System.out:Ljava/io/PrintStream;)
    0015 swap
    0016 invokevirtual Method(java/io/PrintStream.println:(Ljava/lang/Object;)V)
    0019 aload_0
    0020 aload_2
    0021 putfield Field(Logger.tag:Ljava/lang/String;)
    0024 return
class_attr    BootstrapMethods (14 bytes)
