class_version major=61 minor=0
this_class    InputKt
super_class   java/lang/Object
access_flags  0x0031
method        main ()V 0x0019
  code        max_stack=3 max_locals=6
    0000 ldc "APP"
    0002 astore_0
    0003 new Class(Logger)
    0006 dup
    0007 aload_0
    0008 invokespecial Method(Logger.<init>:(Ljava/lang/String;)V)
    0011 checkcast Class(Logger)
    0014 astore_2
    0015 ldc "started"
    0017 astore_3
    0018 aload_2
    0019 checkcast Class(Logger)
    0022 astore 4
    0024 ldc "started"
    0026 astore 5
    0028 aload 4
    0030 aload 5
    0032 invokevirtual Method(Logger.log:(Ljava/lang/String;)V)
    0035 return
method        main ([Ljava/lang/String;)V 0x1009
  code        max_stack=0 max_locals=1
    0000 invokestatic Method(InputKt.main:()V)
    0003 return
