class_version major=61 minor=0
this_class    Password
super_class   java/lang/Object
access_flags  0x0021
field         value : Ljava/lang/String; 0x0001
method        <init> (Ljava/lang/String;)V 0x0001
  code        max_stack=2 max_locals=2
    0000 aload_0
    0001 invokespecial Method(java/lang/Object.<init>:()V)
    0004 aload_0
    0005 aload_1
    0006 putfield Field(Password.value:Ljava/lang/String;)
    0009 return
method        component1 ()Ljava/lang/String; 0x0001
  code        max_stack=1 max_locals=1
    0000 aload_0
    0001 getfield Field(Password.value:Ljava/lang/String;)
    0004 areturn
  attr        RuntimeInvisibleAnnotations (6 bytes)
method        copy (Ljava/lang/String;)LPassword; 0x0001
  code        max_stack=3 max_locals=2
    0000 new Class(Password)
    0003 dup
    0004 aload_1
    0005 invokespecial Method(Password.<init>:(Ljava/lang/String;)V)
    0008 areturn
  attr        RuntimeInvisibleAnnotations (6 bytes)
method        equals (Ljava/lang/Object;)Z 0x0001
  code        max_stack=2 max_locals=11
    0000 aload_0
    0001 astore_2
    0002 aload_2
    0003 aload_1
    0004 if_acmpne 13
    0007 iconst_1
    0008 istore 4
    0010 iload 4
    0012 ireturn
    0013 aload_1
    0014 instanceof Class(Password)
    0017 istore 5
    0019 iload 5
    0021 ifne 30
    0024 iconst_0
    0025 istore 6
    0027 iload 6
    0029 ireturn
    0030 aload_1
    0031 checkcast Class(Password)
    0034 astore 7
    0036 aload_0
    0037 getfield Field(Password.value:Ljava/lang/String;)
    0040 astore 8
    0042 aload 7
    0044 getfield Field(Password.value:Ljava/lang/String;)
    0047 astore 9
    0049 aload 8
    0051 aload 9
    0053 invokevirtual Method(java/lang/String.equals:(Ljava/lang/Object;)Z)
    0056 istore 10
    0058 iload 10
    0060 ireturn
    sub_attr  StackMapTable (14 bytes)
method        getValue ()Ljava/lang/String; 0x0001
  code        max_stack=1 max_locals=1
    0000 aload_0
    0001 getfield Field(Password.value:Ljava/lang/String;)
    0004 areturn
  attr        RuntimeInvisibleAnnotations (6 bytes)
method        hashCode ()I 0x0001
  code        max_stack=1 max_locals=1
    0000 aload_0
    0001 getfield Field(Password.value:Ljava/lang/String;)
    0004 invokevirtual Method(java/lang/String.hashCode:()I)
    0007 ireturn
method        toString ()Ljava/lang/String; 0x0001
  code        max_stack=2 max_locals=2
    0000 ldc "Password("
    0002 invokedynamic InvokeDynamic(makeConcatWithConstants:(Ljava/lang/String;)Ljava/lang/String;)
    0007 astore_1
    0008 aload_1
    0009 aload_0
    0010 getfield Field(Password.value:Ljava/lang/String;)
    0013 invokedynamic InvokeDynamic(makeConcatWithConstants:(Ljava/lang/String;Ljava/lang/String;)Ljava/lang/String;)
    0018 invokedynamic InvokeDynamic(makeConcatWithConstants:(Ljava/lang/String;)Ljava/lang/String;)
    0023 areturn
  attr        RuntimeInvisibleAnnotations (6 bytes)
class_attr    BootstrapMethods (20 bytes)
