class_version major=61 minor=0
this_class    InputKt
super_class   java/lang/Object
access_flags  0x0031
method        describe (LOp;)Ljava/lang/String; 0x0019
  code        max_stack=2 max_locals=1
    0000 aload_0
    0001 ldc "op"
    0003 invokestatic Method(kotlin/jvm/internal/Intrinsics.checkNotNullParameter:(Ljava/lang/Object;Ljava/lang/String;)V)
    0006 aload_0
    0007 getstatic Field(InputKt$WhenMappings.$EnumSwitchMapping$0:[I)
    0010 swap
    0011 invokevirtual Method(Op.ordinal:()I)
    0014 iaload
    0015 tableswitch default=64 low=1 high=4 1=44 2=49 3=54 4=59
    0044 ldc "plus"
    0046 goto 72
    0049 ldc "minus"
    0051 goto 72
    0054 ldc "times"
    0056 goto 72
    0059 ldc "div"
    0061 goto 72
    0064 new Class(kotlin/NoWhenBranchMatchedException)
    0067 dup
    0068 invokespecial Method(kotlin/NoWhenBranchMatchedException.<init>:()V)
    0071 athrow
    0072 areturn
    sub_attr  StackMapTable (11 bytes)
  attr        RuntimeInvisibleAnnotations (6 bytes)
  attr        RuntimeInvisibleParameterAnnotations (7 bytes)
method        main ()V 0x0019
  code        max_stack=2 max_locals=0
    0000 getstatic Field(Op.PLUS:LOp;)
    0003 invokestatic Method(InputKt.describe:(LOp;)Ljava/lang/String;)
    0006 getstatic Field(java/lang/System.out:Ljava/io/PrintStream;)
    0009 swap
    0010 invokevirtual Method(java/io/PrintStream.println:(Ljava/lang/Object;)V)
    0013 getstatic Field(Op.DIV:LOp;)
    0016 invokestatic Method(InputKt.describe:(LOp;)Ljava/lang/String;)
    0019 getstatic Field(java/lang/System.out:Ljava/io/PrintStream;)
    0022 swap
    0023 invokevirtual Method(java/io/PrintStream.println:(Ljava/lang/Object;)V)
    0026 return
method        main ([Ljava/lang/String;)V 0x1009
  code        max_stack=0 max_locals=1
    0000 invokestatic Method(InputKt.main:()V)
    0003 return
class_attr    InnerClasses (10 bytes)
