class_version major=61 minor=0
this_class    InputKt
super_class   java/lang/Object
access_flags  0x0031
method        main ()V 0x0019
  code        max_stack=0 max_locals=0
    0000 invokestatic Method(InputKt.useIntBox:()V)
    0003 invokestatic Method(InputKt.useStringBox:()V)
    0006 return
method        main ([Ljava/lang/String;)V 0x1009
  code        max_stack=0 max_locals=1
    0000 invokestatic Method(InputKt.main:()V)
    0003 return
method        useIntBox ()V 0x0019
  code        max_stack=3 max_locals=2
    0000 new Class(Box)
    0003 dup
    0004 bipush 42
    0006 invokestatic Method(java/lang/Integer.valueOf:(I)Ljava/lang/Integer;)
    0009 invokespecial Method(Box.<init>:(Ljava/lang/Object;)V)
    0012 astore_0
    0013 aload_0
    0014 invokevirtual Method(Box.unwrap:()Ljava/lang/Object;)
    0017 checkcast Class(java/lang/Number)
    0020 invokevirtual Method(java/lang/Number.intValue:()I)
    0023 istore_1
    0024 getstatic Field(java/lang/System.out:Ljava/io/PrintStream;)
    0027 iload_1
    0028 invokevirtual Method(java/io/PrintStream.println:(I)V)
    0031 return
method        useStringBox ()V 0x0019
  code        max_stack=3 max_locals=2
    0000 new Class(Box)
    0003 dup
    0004 ldc "hello"
    0006 invokespecial Method(Box.<init>:(Ljava/lang/Object;)V)
    0009 astore_0
    0010 aload_0
    0011 invokevirtual Method(Box.unwrap:()Ljava/lang/Object;)
    0014 checkcast Class(java/lang/String)
    0017 astore_1
    0018 getstatic Field(java/lang/System.out:Ljava/io/PrintStream;)
    0021 aload_1
    0022 invokevirtual Method(java/io/PrintStream.println:(Ljava/lang/Object;)V)
    0025 return
