class_version major=61 minor=0
this_class    InputKt
super_class   java/lang/Object
access_flags  0x0031
method        main ()V 0x0019
  code        max_stack=4 max_locals=9
    0000 ldc "hello from coroutine"
    0002 astore_1
    0003 new Class(InputKt$Lambda$0)
    0006 dup
    0007 aconst_null
    0008 astore_3
    0009 aload_1
    0010 aload_3
    0011 invokespecial Method(InputKt$Lambda$0.<init>:(Ljava/lang/String;Lkotlin/coroutines/Continuation;)V)
    0014 astore_2
    0015 aconst_null
    0016 astore 4
    0018 aload_2
    0019 checkcast Class(kotlin/jvm/functions/Function2)
    0022 astore 5
    0024 iconst_1
    0025 istore 6
    0027 aconst_null
    0028 astore 7
    0030 aload 4
    0032 aload 5
    0034 iload 6
    0036 aload 7
    0038 invokestatic Method(kotlinx/coroutines/BuildersKt.runBlocking$default:(Lkotlin/coroutines/CoroutineContext;Lkotlin/jvm/functions/Function2;ILjava/lang/Object;)Ljava/lang/Object;)
    0041 astore 8
    0043 return
method        main ([Ljava/lang/String;)V 0x1009
  code        max_stack=0 max_locals=1
    0000 invokestatic Method(InputKt.main:()V)
    0003 return
