class_version major=61 minor=0
this_class    InputKt
super_class   java/lang/Object
access_flags  0x0031
method        main ()V 0x0019
  code        max_stack=3 max_locals=5
    0000 new Class(FormalGreeter)
    0003 dup
    0004 ldc "Alice"
    0006 invokespecial Method(FormalGreeter.<init>:(Ljava/lang/String;)V)
    0009 checkcast Class(Greeter)
    0012 astore_0
    0013 new Class(LoudGreeter)
    0016 dup
    0017 aload_0
    0018 invokespecial Method(LoudGreeter.<init>:(LGreeter;)V)
    0021 checkcast Class(Greeter)
    0024 astore_1
    0025 new Class(QuietGreeter)
    0028 dup
    0029 aload_0
    0030 invokespecial Method(QuietGreeter.<init>:(LGreeter;)V)
    0033 checkcast Class(Greeter)
    0036 astore_2
    0037 new Class(QuietGreeter)
    0040 dup
    0041 aload_0
    0042 invokespecial Method(QuietGreeter.<init>:(LGreeter;)V)
    0045 astore_3
    0046 new Class(LoudGreeter)
    0049 dup
    0050 aload_3
    0051 checkcast Class(Greeter)
    0054 invokespecial Method(LoudGreeter.<init>:(LGreeter;)V)
    0057 checkcast Class(Greeter)
    0060 astore 4
    0062 aload_1
    0063 invokeinterface InterfaceMethod(Greeter.greet:()Ljava/lang/String;)
    0068 getstatic Field(java/lang/System.out:Ljava/io/PrintStream;)
    0071 swap
    0072 invokevirtual Method(java/io/PrintStream.println:(Ljava/lang/Object;)V)
    0075 aload_1
    0076 invokeinterface InterfaceMethod(Greeter.farewell:()Ljava/lang/String;)
    0081 getstatic Field(java/lang/System.out:Ljava/io/PrintStream;)
    0084 swap
    0085 invokevirtual Method(java/io/PrintStream.println:(Ljava/lang/Object;)V)
    0088 aload_2
    0089 invokeinterface InterfaceMethod(Greeter.greet:()Ljava/lang/String;)
    0094 getstatic Field(java/lang/System.out:Ljava/io/PrintStream;)
    0097 swap
    0098 invokevirtual Method(java/io/PrintStream.println:(Ljava/lang/Object;)V)
    0101 aload_2
    0102 invokeinterface InterfaceMethod(Greeter.farewell:()Ljava/lang/String;)
    0107 getstatic Field(java/lang/System.out:Ljava/io/PrintStream;)
    0110 swap
    0111 invokevirtual Method(java/io/PrintStream.println:(Ljava/lang/Object;)V)
    0114 aload 4
    0116 invokeinterface InterfaceMethod(Greeter.greet:()Ljava/lang/String;)
    0121 getstatic Field(java/lang/System.out:Ljava/io/PrintStream;)
    0124 swap
    0125 invokevirtual Method(java/io/PrintStream.println:(Ljava/lang/Object;)V)
    0128 aload 4
    0130 invokeinterface InterfaceMethod(Greeter.farewell:()Ljava/lang/String;)
    0135 getstatic Field(java/lang/System.out:Ljava/io/PrintStream;)
    0138 swap
    0139 invokevirtual Method(java/io/PrintStream.println:(Ljava/lang/Object;)V)
    0142 return
method        main ([Ljava/lang/String;)V 0x1009
  code        max_stack=0 max_locals=1
    0000 invokestatic Method(InputKt.main:()V)
    0003 return
