class_version major=61 minor=0
this_class    InputKt
super_class   java/lang/Object
access_flags  0x0031
method        gliderInitial ()[I 0x0019
  code        max_stack=3 max_locals=3
    0000 bipush 100
    0002 newarray int
    0004 astore_0
    0005 iconst_1
    0006 istore_1
    0007 iconst_1
    0008 istore_2
    0009 aload_0
    0010 iload_1
    0011 iload_2
    0012 iastore
    0013 bipush 12
    0015 istore_1
    0016 iconst_1
    0017 istore_2
    0018 aload_0
    0019 iload_1
    0020 iload_2
    0021 iastore
    0022 bipush 20
    0024 istore_1
    0025 iconst_1
    0026 istore_2
    0027 aload_0
    0028 iload_1
    0029 iload_2
    0030 iastore
    0031 bipush 21
    0033 istore_1
    0034 iconst_1
    0035 istore_2
    0036 aload_0
    0037 iload_1
    0038 iload_2
    0039 iastore
    0040 bipush 22
    0042 istore_1
    0043 iconst_1
    0044 istore_2
    0045 aload_0
    0046 iload_1
    0047 iload_2
    0048 iastore
    0049 aload_0
    0050 areturn
method        main ()V 0x0019
  code        max_stack=5 max_locals=3
    0000 invokestatic Method(InputKt.gliderInitial:()[I)
    0003 astore_0
    0004 new Class(Generation)
    0007 dup
    0008 bipush 10
    0010 bipush 10
    0012 aload_0
    0013 invokespecial Method(Generation.<init>:(II[I)V)
    0016 astore_1
    0017 iconst_0
    0018 istore_2
    0019 iload_2
    0020 iconst_4
    0021 if_icmpgt 59
    0024 iload_2
    0025 invokedynamic InvokeDynamic(makeConcatWithConstants:(I)Ljava/lang/String;)
    0030 getstatic Field(java/lang/System.out:Ljava/io/PrintStream;)
    0033 swap
    0034 invokevirtual Method(java/io/PrintStream.println:(Ljava/lang/Object;)V)
    0037 aload_1
    0038 invokevirtual Method(Generation.show:()Ljava/lang/String;)
    0041 getstatic Field(java/lang/System.out:Ljava/io/PrintStream;)
    0044 swap
    0045 invokevirtual Method(java/io/PrintStream.print:(Ljava/lang/Object;)V)
    0048 aload_1
    0049 invokevirtual Method(Generation.step:()LGeneration;)
    0052 astore_1
    0053 iinc 2 1
    0056 goto 19
    0059 return
    sub_attr  StackMapTable (13 bytes)
method        main ([Ljava/lang/String;)V 0x1009
  code        max_stack=0 max_locals=1
    0000 invokestatic Method(InputKt.main:()V)
    0003 return
class_attr    BootstrapMethods (8 bytes)
