class_version major=61 minor=0
this_class    InputKt
super_class   java/lang/Object
access_flags  0x0031
method        describe (LLruCache;Ljava/lang/String;)V 0x0019
  code        max_stack=3 max_locals=4
    0000 aload_0
    0001 ldc "cache"
    0003 invokestatic Method(kotlin/jvm/internal/Intrinsics.checkNotNullParameter:(Ljava/lang/Object;Ljava/lang/String;)V)
    0006 aload_1
    0007 ldc "label"
    0009 invokestatic Method(kotlin/jvm/internal/Intrinsics.checkNotNullParameter:(Ljava/lang/Object;Ljava/lang/String;)V)
    0012 aload_0
    0013 invokevirtual Method(LruCache.keys:()Ljava/util/List;)
    0016 astore_2
    0017 aload_0
    0018 invokevirtual Method(LruCache.size:()I)
    0021 istore_3
    0022 aload_1
    0023 aload_2
    0024 iload_3
    0025 invokedynamic InvokeDynamic(makeConcatWithConstants:(Ljava/lang/String;Ljava/util/List;I)Ljava/lang/String;)
    0030 getstatic Field(java/lang/System.out:Ljava/io/PrintStream;)
    0033 swap
    0034 invokevirtual Method(java/io/PrintStream.println:(Ljava/lang/Object;)V)
    0037 return
  attr        Signature (2 bytes)
  attr        RuntimeInvisibleParameterAnnotations (13 bytes)
method        main ()V 0x0019
  code        max_stack=3 max_locals=5
    0000 new Class(LruCache)
    0003 dup
    0004 iconst_3
    0005 invokespecial Method(LruCache.<init>:(I)V)
    0008 astore_0
    0009 iconst_1
    0010 invokestatic Method(java/lang/Integer.valueOf:(I)Ljava/lang/Integer;)
    0013 astore_1
    0014 aload_0
    0015 ldc "a"
    0017 aload_1
    0018 invokevirtual Method(LruCache.put:(Ljava/lang/Object;Ljava/lang/Object;)V)
    0021 iconst_2
    0022 invokestatic Method(java/lang/Integer.valueOf:(I)Ljava/lang/Integer;)
    0025 astore_1
    0026 aload_0
    0027 ldc "b"
    0029 aload_1
    0030 invokevirtual Method(LruCache.put:(Ljava/lang/Object;Ljava/lang/Object;)V)
    0033 iconst_3
    0034 invokestatic Method(java/lang/Integer.valueOf:(I)Ljava/lang/Integer;)
    0037 astore_1
    0038 aload_0
    0039 ldc "c"
    0041 aload_1
    0042 invokevirtual Method(LruCache.put:(Ljava/lang/Object;Ljava/lang/Object;)V)
    0045 aload_0
    0046 ldc "initial fill"
    0048 invokestatic Method(InputKt.describe:(LLruCache;Ljava/lang/String;)V)
    0051 aload_0
    0052 ldc "a"
    0054 invokevirtual Method(LruCache.get:(Ljava/lang/Object;)Ljava/lang/Object;)
    0057 astore 4
    0059 aload 4
    0061 invokedynamic InvokeDynamic(makeConcatWithConstants:(Ljava/lang/Object;)Ljava/lang/String;)
    0066 getstatic Field(java/lang/System.out:Ljava/io/PrintStream;)
    0069 swap
    0070 invokevirtual Method(java/io/PrintStream.println:(Ljava/lang/Object;)V)
    0073 aload_0
    0074 ldc "after get(a)"
    0076 invokestatic Method(InputKt.describe:(LLruCache;Ljava/lang/String;)V)
    0079 iconst_4
    0080 invokestatic Method(java/lang/Integer.valueOf:(I)Ljava/lang/Integer;)
    0083 astore_1
    0084 aload_0
    0085 ldc "d"
    0087 aload_1
    0088 invokevirtual Method(LruCache.put:(Ljava/lang/Object;Ljava/lang/Object;)V)
    0091 aload_0
    0092 ldc "after put(d)"
    0094 invokestatic Method(InputKt.describe:(LLruCache;Ljava/lang/String;)V)
    0097 aload_0
    0098 ldc "b"
    0100 invokevirtual Method(LruCache.get:(Ljava/lang/Object;)Ljava/lang/Object;)
    0103 invokedynamic InvokeDynamic(makeConcatWithConstants:(Ljava/lang/Object;)Ljava/lang/String;)
    0108 getstatic Field(java/lang/System.out:Ljava/io/PrintStream;)
    0111 swap
    0112 invokevirtual Method(java/io/PrintStream.println:(Ljava/lang/Object;)V)
    0115 aload_0
    0116 ldc "d"
    0118 invokevirtual Method(LruCache.get:(Ljava/lang/Object;)Ljava/lang/Object;)
    0121 invokedynamic InvokeDynamic(makeConcatWithConstants:(Ljava/lang/Object;)Ljava/lang/String;)
    0126 getstatic Field(java/lang/System.out:Ljava/io/PrintStream;)
    0129 swap
    0130 invokevirtual Method(java/io/PrintStream.println:(Ljava/lang/Object;)V)
    0133 bipush 99
    0135 invokestatic Method(java/lang/Integer.valueOf:(I)Ljava/lang/Integer;)
    0138 astore_1
    0139 aload_0
    0140 ldc "a"
    0142 aload_1
    0143 invokevirtual Method(LruCache.put:(Ljava/lang/Object;Ljava/lang/Object;)V)
    0146 aload_0
    0147 ldc "after put(a=99)"
    0149 invokestatic Method(InputKt.describe:(LLruCache;Ljava/lang/String;)V)
    0152 aload_0
    0153 ldc "a"
    0155 invokevirtual Method(LruCache.get:(Ljava/lang/Object;)Ljava/lang/Object;)
    0158 invokedynamic InvokeDynamic(makeConcatWithConstants:(Ljava/lang/Object;)Ljava/lang/String;)
    0163 getstatic Field(java/lang/System.out:Ljava/io/PrintStream;)
    0166 swap
    0167 invokevirtual Method(java/io/PrintStream.println:(Ljava/lang/Object;)V)
    0170 return
method        main ([Ljava/lang/String;)V 0x1009
  code        max_stack=0 max_locals=1
    0000 invokestatic Method(InputKt.main:()V)
    0003 return
class_attr    BootstrapMethods (26 bytes)
