class_version major=61 minor=0
this_class    InputKt
super_class   java/lang/Object
access_flags  0x0031
method        doubleBox (LBox;)I 0x0019
  code        max_stack=2 max_locals=1
    0000 aload_0
    0001 ldc "b"
    0003 invokestatic Method(kotlin/jvm/internal/Intrinsics.checkNotNullParameter:(Ljava/lang/Object;Ljava/lang/String;)V)
    0006 aload_0
    0007 invokevirtual Method(Box.getValue:()I)
    0010 iconst_2
    0011 imul
    0012 op_0xAC
  attr        RuntimeInvisibleParameterAnnotations (7 bytes)
method        main ()V 0x0019
  code        max_stack=3 max_locals=2
    0000 new Class(Box)
    0003 dup
    0004 bipush 21
    0006 invokespecial Method(Box.<init>:(I)V)
    0009 astore_0
    0010 aload_0
    0011 invokestatic Method(InputKt.unbox:(LBox;)I)
    0014 istore_1
    0015 getstatic Field(java/lang/System.out:Ljava/io/PrintStream;)
    0018 iload_1
    0019 invokevirtual Method(java/io/PrintStream.println:(I)V)
    0022 aload_0
    0023 invokestatic Method(InputKt.doubleBox:(LBox;)I)
    0026 istore_1
    0027 getstatic Field(java/lang/System.out:Ljava/io/PrintStream;)
    0030 iload_1
    0031 invokevirtual Method(java/io/PrintStream.println:(I)V)
    0034 return
method        main ([Ljava/lang/String;)V 0x1009
  code        max_stack=0 max_locals=1
    0000 invokestatic Method(InputKt.main:()V)
    0003 return
method        unbox (LBox;)I 0x0019
  code        max_stack=2 max_locals=1
    0000 aload_0
    0001 ldc "b"
    0003 invokestatic Method(kotlin/jvm/internal/Intrinsics.checkNotNullParameter:(Ljava/lang/Object;Ljava/lang/String;)V)
    0006 aload_0
    0007 invokevirtual Method(Box.getValue:()I)
    0010 op_0xAC
  attr        RuntimeInvisibleParameterAnnotations (7 bytes)
