class_version major=61 minor=0
this_class    InputKt
super_class   java/lang/Object
access_flags  0x0031
method        main ()V 0x0019
  code        max_stack=3 max_locals=1
    0000 new Class(DbConn)
    0003 dup
    0004 invokespecial Method(DbConn.<init>:()V)
    0007 astore_0
    0008 new Class(InputKt$main$1)
    0011 dup
    0012 aload_0
    0013 invokespecial Method(InputKt$main$1.<init>:(LDbConn;)V)
    0016 pop
    0017 new Class(InputKt$main$2)
    0020 dup
    0021 aload_0
    0022 invokespecial Method(InputKt$main$2.<init>:(LDbConn;)V)
    0025 invokevirtual Method(InputKt$main$2.invoke:()Ljava/lang/Object;)
    0028 pop
    0029 aload_0
    0030 invokevirtual Method(DbConn.close:()V)
    0033 ldc "done"
    0035 getstatic Field(java/lang/System.out:Ljava/io/PrintStream;)
    0038 swap
    0039 invokevirtual Method(java/io/PrintStream.println:(Ljava/lang/Object;)V)
    0042 return
method        main ([Ljava/lang/String;)V 0x1009
  code        max_stack=0 max_locals=1
    0000 invokestatic Method(InputKt.main:()V)
    0003 return
method        process (LDbConn;)Ljava/lang/String; 0x0019
  code        max_stack=2 max_locals=1
    0000 aload_0
    0001 ldc "conn"
    0003 invokestatic Method(kotlin/jvm/internal/Intrinsics.checkNotNullParameter:(Ljava/lang/Object;Ljava/lang/String;)V)
    0006 ldc "processed"
    0008 areturn
  attr        RuntimeInvisibleAnnotations (6 bytes)
  attr        RuntimeInvisibleParameterAnnotations (7 bytes)
class_attr    InnerClasses (18 bytes)
