class_version major=61 minor=0
this_class    InputKt
super_class   java/lang/Object
access_flags  0x0031
method        main ()V 0x0019
  code        max_stack=2 max_locals=1
    0000 iconst_3
    0001 invokestatic Method(java/lang/Integer.valueOf:(I)Ljava/lang/Integer;)
    0004 op_0xC0
    0005 nop
    0006 op_0x14
    0007 bipush 7
    0009 invokestatic Method(java/lang/Integer.valueOf:(I)Ljava/lang/Integer;)
    0012 op_0xC0
    0013 nop
    0014 op_0x14
    0015 invokestatic Method(InputKt.maxOf:(Ljava/lang/Comparable;Ljava/lang/Comparable;)Ljava/lang/Comparable;)
    0018 op_0xC0
    0019 nop
    0020 op_0x25
    0021 invokevirtual Method(java/lang/Number.intValue:()I)
    0024 op_0x3B
    0025 getstatic Field(java/lang/System.out:Ljava/io/PrintStream;)
    0028 op_0x1A
    0029 invokevirtual Method(java/io/PrintStream.println:(I)V)
    0032 bipush 10
    0034 invokestatic Method(java/lang/Integer.valueOf:(I)Ljava/lang/Integer;)
    0037 op_0xC0
    0038 nop
    0039 op_0x14
    0040 iconst_2
    0041 invokestatic Method(java/lang/Integer.valueOf:(I)Ljava/lang/Integer;)
    0044 op_0xC0
    0045 nop
    0046 op_0x14
    0047 invokestatic Method(InputKt.maxOf:(Ljava/lang/Comparable;Ljava/lang/Comparable;)Ljava/lang/Comparable;)
    0050 op_0xC0
    0051 nop
    0052 op_0x25
    0053 invokevirtual Method(java/lang/Number.intValue:()I)
    0056 op_0x3B
    0057 getstatic Field(java/lang/System.out:Ljava/io/PrintStream;)
    0060 op_0x1A
    0061 invokevirtual Method(java/io/PrintStream.println:(I)V)
    0064 return
method        main ([Ljava/lang/String;)V 0x1009
  code        max_stack=0 max_locals=1
    0000 invokestatic Method(InputKt.main:()V)
    0003 return
method        maxOf (Ljava/lang/Comparable;Ljava/lang/Comparable;)Ljava/lang/Comparable; 0x0019
  code        max_stack=2 max_locals=2
    0000 op_0x2A
    0001 ldc "a"
    0003 invokestatic Method(kotlin/jvm/internal/Intrinsics.checkNotNullParameter:(Ljava/lang/Object;Ljava/lang/String;)V)
    0006 op_0x2B
    0007 ldc "b"
    0009 invokestatic Method(kotlin/jvm/internal/Intrinsics.checkNotNullParameter:(Ljava/lang/Object;Ljava/lang/String;)V)
    0012 op_0x2A
    0013 op_0x2B
    0014 op_0xB9
    0015 nop
    0016 op_0x18
    0017 iconst_m1
    0018 nop
    0019 op_0x9E
    0020 nop
    0021 iconst_4
    0022 op_0x2A
    0023 op_0xA7
    0024 nop
    0025 iconst_1
    0026 op_0x2B
    0027 op_0xB0
    sub_attr  StackMapTable (7 bytes)
  attr        Signature (2 bytes)
  attr        RuntimeInvisibleAnnotations (6 bytes)
  attr        RuntimeInvisibleParameterAnnotations (13 bytes)
