class_version major=61 minor=0
this_class    InputKt
super_class   java/lang/Object
access_flags  0x0031
method        main ([Ljava/lang/String;)V 0x0009
  code        max_stack=1 max_locals=5
    0000 iconst_1
    0001 istore 1
    0003 iload 1
    0005 invokestatic Method(InputKt.printMonth:(I)V)
    0008 iconst_3
    0009 istore 2
    0011 iload 2
    0013 invokestatic Method(InputKt.printMonth:(I)V)
    0016 bipush 6
    0018 istore 3
    0020 iload 3
    0022 invokestatic Method(InputKt.printMonth:(I)V)
    0025 bipush 12
    0027 istore 4
    0029 iload 4
    0031 invokestatic Method(InputKt.printMonth:(I)V)
    0034 return
method        printMonth (I)V 0x0009
  code        max_stack=2 max_locals=21
    0000 iload 0
    0002 istore 1
    0004 op_0xA7
    0005 nop
    0006 iconst_0
    0007 iconst_1
    0008 istore 2
    0010 iload 1
    0012 iload 2
    0014 op_0x9F
    0015 nop
    0016 iconst_4
    0017 iconst_0
    0018 op_0xA7
    0019 nop
    0020 iconst_1
    0021 iconst_1
    0022 istore 3
    0024 iload 3
    0026 op_0x99
    0027 nop
    0028 ldc "java/io/PrintStream"
    0030 op_0x0B
    0031 astore 4
    0033 getstatic Field(java/lang/System.out:Ljava/io/PrintStream;)
    0036 aload 4
    0038 invokevirtual Method(java/io/PrintStream.println:(Ljava/lang/String;)V)
    0041 op_0xA7
    0042 nop
    0043 op_0xCC
    0044 iconst_2
    0045 istore 5
    0047 iload 1
    0049 iload 5
    0051 op_0x9F
    0052 nop
    0053 iconst_4
    0054 iconst_0
    0055 op_0xA7
    0056 nop
    0057 iconst_1
    0058 iconst_1
    0059 istore 6
    0061 iload 6
    0063 op_0x99
    0064 nop
    0065 ldc "java/io/PrintStream"
    0067 aload 58
    0069 iconst_4
    0070 getstatic Field(java/lang/System.out:Ljava/io/PrintStream;)
    0073 aload 7
    0075 invokevirtual Method(java/io/PrintStream.println:(Ljava/lang/String;)V)
    0078 op_0xA7
    0079 nop
    0080 op_0xA7
    0081 iconst_3
    0082 istore 8
    0084 iload 1
    0086 iload 8
    0088 op_0x9F
    0089 nop
    0090 iconst_4
    0091 iconst_0
    0092 op_0xA7
    0093 nop
    0094 iconst_1
    0095 iconst_1
    0096 istore 9
    0098 iload 9
    0100 op_0x99
    0101 nop
    0102 ldc "java/io/PrintStream"
    0104 op_0x1B
    0105 astore 10
    0107 getstatic Field(java/lang/System.out:Ljava/io/PrintStream;)
    0110 aload 10
    0112 invokevirtual Method(java/io/PrintStream.println:(Ljava/lang/String;)V)
    0115 op_0xA7
    0116 nop
    0117 op_0x82
    0118 iconst_4
    0119 istore 11
    0121 iload 1
    0123 iload 11
    0125 op_0x9F
    0126 nop
    0127 iconst_4
    0128 iconst_0
    0129 op_0xA7
    0130 nop
    0131 iconst_1
    0132 iconst_1
    0133 istore 12
    0135 iload 12
    0137 op_0x99
    0138 nop
    0139 ldc "java/io/PrintStream"
    0141 op_0x1D
    0142 astore 13
    0144 getstatic Field(java/lang/System.out:Ljava/io/PrintStream;)
    0147 aload 13
    0149 invokevirtual Method(java/io/PrintStream.println:(Ljava/lang/String;)V)
    0152 op_0xA7
    0153 nop
    0154 op_0x5D
    0155 iconst_5
    0156 istore 14
    0158 iload 1
    0160 iload 14
    0162 op_0x9F
    0163 nop
    0164 iconst_4
    0165 iconst_0
    0166 op_0xA7
    0167 nop
    0168 iconst_1
    0169 iconst_1
    0170 istore 15
    0172 iload 15
    0174 op_0x99
    0175 nop
    0176 ldc "java/io/PrintStream"
    0178 op_0x1F
    0179 astore 16
    0181 getstatic Field(java/lang/System.out:Ljava/io/PrintStream;)
    0184 aload 16
    0186 invokevirtual Method(java/io/PrintStream.println:(Ljava/lang/String;)V)
    0189 op_0xA7
    0190 nop
    0191 op_0x38
    0192 bipush 6
    0194 istore 17
    0196 iload 1
    0198 iload 17
    0200 op_0x9F
    0201 nop
    0202 iconst_4
    0203 iconst_0
    0204 op_0xA7
    0205 nop
    0206 iconst_1
    0207 iconst_1
    0208 istore 18
    0210 iload 18
    0212 op_0x99
    0213 nop
    0214 ldc "java/io/PrintStream"
    0216 op_0x21
    0217 astore 19
    0219 getstatic Field(java/lang/System.out:Ljava/io/PrintStream;)
    0222 aload 19
    0224 invokevirtual Method(java/io/PrintStream.println:(Ljava/lang/String;)V)
    0227 op_0xA7
    0228 nop
    0229 ldc "java/io/PrintStream"
    0231 op_0x23
    0232 astore 20
    0234 getstatic Field(java/lang/System.out:Ljava/io/PrintStream;)
    0237 aload 20
    0239 invokevirtual Method(java/io/PrintStream.println:(Ljava/lang/String;)V)
    0242 op_0xA7
    0243 nop
    0244 iconst_0
    0245 return
    sub_attr  StackMapTable (349 bytes)
