class_version major=61 minor=0
this_class    InputKt
super_class   java/lang/Object
access_flags  0x0031
method        main ()V 0x0019
  code        max_stack=1 max_locals=0
    0000 iconst_1
    0001 invokestatic Method(InputKt.printMonth:(I)V)
    0004 iconst_3
    0005 invokestatic Method(InputKt.printMonth:(I)V)
    0008 bipush 6
    0010 invokestatic Method(InputKt.printMonth:(I)V)
    0013 bipush 12
    0015 invokestatic Method(InputKt.printMonth:(I)V)
    0018 return
method        main ([Ljava/lang/String;)V 0x1009
  code        max_stack=0 max_locals=1
    0000 invokestatic Method(InputKt.main:()V)
    0003 return
method        printMonth (I)V 0x0019
<<<<<<< Updated upstream
  code        max_stack=2 max_locals=14
    0000 iload_0
    0001 iconst_1
    0002 if_icmpne 9
    0005 iconst_1
    0006 goto 10
    0009 iconst_0
    0010 istore_1
    0011 iload_1
    0012 ifeq 28
    0015 ldc "January"
    0017 astore_2
    0018 getstatic Field(java/lang/System.out:Ljava/io/PrintStream;)
    0021 aload_2
    0022 invokevirtual Method(java/io/PrintStream.println:(Ljava/lang/Object;)V)
    0025 goto 199
    0028 iload_0
    0029 iconst_2
    0030 if_icmpne 37
    0033 iconst_1
    0034 goto 38
    0037 iconst_0
    0038 istore_3
    0039 iload_3
    0040 ifeq 58
    0043 ldc "February"
    0045 astore 4
    0047 getstatic Field(java/lang/System.out:Ljava/io/PrintStream;)
    0050 aload 4
    0052 invokevirtual Method(java/io/PrintStream.println:(Ljava/lang/Object;)V)
    0055 goto 199
    0058 iload_0
    0059 iconst_3
    0060 if_icmpne 67
    0063 iconst_1
    0064 goto 68
    0067 iconst_0
    0068 istore 5
    0070 iload 5
    0072 ifeq 90
    0075 ldc "March"
    0077 astore 6
    0079 getstatic Field(java/lang/System.out:Ljava/io/PrintStream;)
    0082 aload 6
    0084 invokevirtual Method(java/io/PrintStream.println:(Ljava/lang/Object;)V)
    0087 goto 199
    0090 iload_0
    0091 iconst_4
    0092 if_icmpne 99
    0095 iconst_1
    0096 goto 100
    0099 iconst_0
    0100 istore 7
    0102 iload 7
    0104 ifeq 122
    0107 ldc "April"
    0109 astore 8
    0111 getstatic Field(java/lang/System.out:Ljava/io/PrintStream;)
    0114 aload 8
    0116 invokevirtual Method(java/io/PrintStream.println:(Ljava/lang/Object;)V)
    0119 goto 199
    0122 iload_0
    0123 iconst_5
    0124 if_icmpne 131
    0127 iconst_1
    0128 goto 132
    0131 iconst_0
    0132 istore 9
    0134 iload 9
    0136 ifeq 154
    0139 ldc "May"
    0141 astore 10
    0143 getstatic Field(java/lang/System.out:Ljava/io/PrintStream;)
    0146 aload 10
    0148 invokevirtual Method(java/io/PrintStream.println:(Ljava/lang/Object;)V)
    0151 goto 199
    0154 iload_0
    0155 bipush 6
    0157 if_icmpne 164
    0160 iconst_1
    0161 goto 165
    0164 iconst_0
    0165 istore 11
    0167 iload 11
    0169 ifeq 187
    0172 ldc "June"
    0174 astore 12
    0176 getstatic Field(java/lang/System.out:Ljava/io/PrintStream;)
    0179 aload 12
    0181 invokevirtual Method(java/io/PrintStream.println:(Ljava/lang/Object;)V)
    0184 goto 199
    0187 ldc "Other"
    0189 astore 13
    0191 getstatic Field(java/lang/System.out:Ljava/io/PrintStream;)
    0194 aload 13
    0196 invokevirtual Method(java/io/PrintStream.println:(Ljava/lang/Object;)V)
    0199 return
    sub_attr  StackMapTable (58 bytes)
=======
  code        max_stack=2 max_locals=20
    0000 iconst_1
    0001 istore_1
    0002 iload_0
    0003 iload_1
    0004 if_icmpne 20
    0007 ldc "January"
    0009 astore_3
    0010 getstatic Field(java/lang/System.out:Ljava/io/PrintStream;)
    0013 aload_3
    0014 invokevirtual Method(java/io/PrintStream.println:(Ljava/lang/Object;)V)
    0017 goto 153
    0020 iconst_2
    0021 istore 4
    0023 iload_0
    0024 iload 4
    0026 if_icmpne 44
    0029 ldc "February"
    0031 astore 6
    0033 getstatic Field(java/lang/System.out:Ljava/io/PrintStream;)
    0036 aload 6
    0038 invokevirtual Method(java/io/PrintStream.println:(Ljava/lang/Object;)V)
    0041 goto 153
    0044 iconst_3
    0045 istore 7
    0047 iload_0
    0048 iload 7
    0050 if_icmpne 68
    0053 ldc "March"
    0055 astore 9
    0057 getstatic Field(java/lang/System.out:Ljava/io/PrintStream;)
    0060 aload 9
    0062 invokevirtual Method(java/io/PrintStream.println:(Ljava/lang/Object;)V)
    0065 goto 153
    0068 iconst_4
    0069 istore 10
    0071 iload_0
    0072 iload 10
    0074 if_icmpne 92
    0077 ldc "April"
    0079 astore 12
    0081 getstatic Field(java/lang/System.out:Ljava/io/PrintStream;)
    0084 aload 12
    0086 invokevirtual Method(java/io/PrintStream.println:(Ljava/lang/Object;)V)
    0089 goto 153
    0092 iconst_5
    0093 istore 13
    0095 iload_0
    0096 iload 13
    0098 if_icmpne 116
    0101 ldc "May"
    0103 astore 15
    0105 getstatic Field(java/lang/System.out:Ljava/io/PrintStream;)
    0108 aload 15
    0110 invokevirtual Method(java/io/PrintStream.println:(Ljava/lang/Object;)V)
    0113 goto 153
    0116 bipush 6
    0118 istore 16
    0120 iload_0
    0121 iload 16
    0123 if_icmpne 141
    0126 ldc "June"
    0128 astore 18
    0130 getstatic Field(java/lang/System.out:Ljava/io/PrintStream;)
    0133 aload 18
    0135 invokevirtual Method(java/io/PrintStream.println:(Ljava/lang/Object;)V)
    0138 goto 153
    0141 ldc "Other"
    0143 astore 19
    0145 getstatic Field(java/lang/System.out:Ljava/io/PrintStream;)
    0148 aload 19
    0150 invokevirtual Method(java/io/PrintStream.println:(Ljava/lang/Object;)V)
    0153 return
    sub_attr  StackMapTable (45 bytes)
>>>>>>> Stashed changes
