class_version major=61 minor=0
this_class    InputKt
super_class   java/lang/Object
access_flags  0x0031
method        main ()V 0x0019
  code        max_stack=2 max_locals=0
    0000 getstatic Field(Dir.NORTH:LDir;)
    0003 invokestatic Method(InputKt.move:(LDir;)Ljava/lang/String;)
    0006 getstatic Field(java/lang/System.out:Ljava/io/PrintStream;)
    0009 op_0x5F
    0010 invokevirtual Method(java/io/PrintStream.println:(Ljava/lang/Object;)V)
    0013 getstatic Field(Dir.WEST:LDir;)
    0016 invokestatic Method(InputKt.move:(LDir;)Ljava/lang/String;)
    0019 getstatic Field(java/lang/System.out:Ljava/io/PrintStream;)
    0022 op_0x5F
    0023 invokevirtual Method(java/io/PrintStream.println:(Ljava/lang/Object;)V)
    0026 return
method        main ([Ljava/lang/String;)V 0x1009
  code        max_stack=0 max_locals=1
    0000 invokestatic Method(InputKt.main:()V)
    0003 return
method        move (LDir;)Ljava/lang/String; 0x0019
  code        max_stack=2 max_locals=1
    0000 op_0x2A
    0001 ldc "d"
    0003 invokestatic Method(kotlin/jvm/internal/Intrinsics.checkNotNullParameter:(Ljava/lang/Object;Ljava/lang/String;)V)
    0006 op_0x2A
    0007 getstatic Field(InputKt$WhenMappings.$EnumSwitchMapping$0:[I)
    0010 op_0x5F
    0011 invokevirtual Method(Dir.ordinal:()I)
    0014 op_0x2E
    0015 op_0xAA
    0016 nop
    0017 nop
    0018 nop
    0019 op_0x31
    0020 nop
    0021 nop
    0022 nop
    0023 aconst_null
    0024 nop
    0025 nop
    0026 nop
    0027 iconst_1
    0028 nop
    0029 nop
    0030 nop
    0031 op_0x1D
    0032 nop
    0033 nop
    0034 nop
    0035 op_0x22
    0036 nop
    0037 nop
    0038 nop
    0039 op_0x27
    0040 nop
    0041 nop
    0042 nop
    0043 op_0x2C
    0044 ldc "up"
    0046 op_0xA7
    0047 nop
    0048 op_0x14
    0049 ldc "down"
    0051 op_0xA7
    0052 nop
    0053 op_0x0F
    0054 ldc "right"
    0056 op_0xA7
    0057 nop
    0058 op_0x0A
    0059 ldc "left"
    0061 op_0xA7
    0062 nop
    0063 iconst_2
    0064 ldc "?"
    0066 op_0xB0
    sub_attr  StackMapTable (11 bytes)
  attr        RuntimeInvisibleAnnotations (6 bytes)
  attr        RuntimeInvisibleParameterAnnotations (7 bytes)
class_attr    InnerClasses (10 bytes)
