class_version major=61 minor=0
this_class    InputKt
super_class   java/lang/Object
access_flags  0x0031
method        Dir$valueOf (Ljava/lang/String;)LDir; 0x0009
  code        max_stack=5 max_locals=14
    0000 ldc "NORTH"
    0002 astore 1
    0004 aload 0
    0006 aload 1
    0008 invokevirtual Method(java/lang/String.equals:(Ljava/lang/Object;)Z)
    0011 istore 2
    0013 iload 2
    0015 op_0x99
    0016 nop
    0017 op_0x42
    0018 op_0xA7
    0019 nop
    0020 op_0x59
    0021 invokestatic Method(InputKt.NORTH:()LDir;)
    0024 astore 3
    0026 aload 3
    0028 op_0xB0
    0029 ldc "WEST"
    0031 astore 4
    0033 aload 0
    0035 aload 4
    0037 invokevirtual Method(java/lang/String.equals:(Ljava/lang/Object;)Z)
    0040 istore 5
    0042 iload 5
    0044 op_0x99
    0045 op_0xFF
    0046 op_0xE9
    0047 invokestatic Method(InputKt.WEST:()LDir;)
    0050 astore 6
    0052 aload 6
    0054 op_0xB0
    0055 ldc "EAST"
    0057 astore 7
    0059 aload 0
    0061 aload 7
    0063 invokevirtual Method(java/lang/String.equals:(Ljava/lang/Object;)Z)
    0066 istore 8
    0068 iload 8
    0070 op_0x99
    0071 op_0xFF
    0072 op_0xD7
    0073 invokestatic Method(InputKt.EAST:()LDir;)
    0076 astore 9
    0078 aload 9
    0080 op_0xB0
    0081 ldc "SOUTH"
    0083 astore 10
    0085 aload 0
    0087 aload 10
    0089 invokevirtual Method(java/lang/String.equals:(Ljava/lang/Object;)Z)
    0092 istore 11
    0094 iload 11
    0096 op_0x99
    0097 op_0xFF
    0098 op_0xD7
    0099 invokestatic Method(InputKt.SOUTH:()LDir;)
    0102 astore 12
    0104 aload 12
    0106 op_0xB0
    0107 invokestatic Method(InputKt.NORTH:()LDir;)
    0110 astore 13
    0112 aload 13
    0114 op_0xB0
    sub_attr  StackMapTable (111 bytes)
method        Dir$values ()Ljava/util/ArrayList; 0x0009
  code        max_stack=2 max_locals=9
    0000 op_0xBB
    0001 nop
    0002 op_0x48
    0003 op_0x59
    0004 invokespecial Method(java/util/ArrayList.<init>:()V)
    0007 astore 0
    0009 invokestatic Method(InputKt.NORTH:()LDir;)
    0012 astore 1
    0014 aload 0
    0016 aload 1
    0018 invokevirtual Method(java/util/ArrayList.add:(Ljava/lang/Object;)Z)
    0021 istore 2
    0023 invokestatic Method(InputKt.SOUTH:()LDir;)
    0026 astore 3
    0028 aload 0
    0030 aload 3
    0032 invokevirtual Method(java/util/ArrayList.add:(Ljava/lang/Object;)Z)
    0035 istore 4
    0037 invokestatic Method(InputKt.EAST:()LDir;)
    0040 astore 5
    0042 aload 0
    0044 aload 5
    0046 invokevirtual Method(java/util/ArrayList.add:(Ljava/lang/Object;)Z)
    0049 istore 6
    0051 invokestatic Method(InputKt.WEST:()LDir;)
    0054 astore 7
    0056 aload 0
    0058 aload 7
    0060 invokevirtual Method(java/util/ArrayList.add:(Ljava/lang/Object;)Z)
    0063 istore 8
    0065 aload 0
    0067 op_0xB0
method        EAST ()LDir; 0x0009
  code        max_stack=3 max_locals=2
    0000 op_0xBB
    0001 nop
    0002 op_0x0B
    0003 op_0x59
    0004 ldc "EAST"
    0006 astore 1
    0008 aload 1
    0010 invokespecial Method(Dir.<init>:(Ljava/lang/String;)V)
    0013 astore 0
    0015 aload 0
    0017 op_0xB0
method        NORTH ()LDir; 0x0009
  code        max_stack=3 max_locals=2
    0000 op_0xBB
    0001 nop
    0002 op_0x0B
    0003 op_0x59
    0004 ldc "NORTH"
    0006 astore 1
    0008 aload 1
    0010 invokespecial Method(Dir.<init>:(Ljava/lang/String;)V)
    0013 astore 0
    0015 aload 0
    0017 op_0xB0
method        SOUTH ()LDir; 0x0009
  code        max_stack=3 max_locals=2
    0000 op_0xBB
    0001 nop
    0002 op_0x0B
    0003 op_0x59
    0004 ldc "SOUTH"
    0006 astore 1
    0008 aload 1
    0010 invokespecial Method(Dir.<init>:(Ljava/lang/String;)V)
    0013 astore 0
    0015 aload 0
    0017 op_0xB0
method        WEST ()LDir; 0x0009
  code        max_stack=3 max_locals=2
    0000 op_0xBB
    0001 nop
    0002 op_0x0B
    0003 op_0x59
    0004 ldc "WEST"
    0006 astore 1
    0008 aload 1
    0010 invokespecial Method(Dir.<init>:(Ljava/lang/String;)V)
    0013 astore 0
    0015 aload 0
    0017 op_0xB0
method        main ([Ljava/lang/String;)V 0x0009
  code        max_stack=2 max_locals=5
    0000 invokestatic Method(InputKt.NORTH:()LDir;)
    0003 astore 1
    0005 aload 1
    0007 invokestatic Method(InputKt.move:(LDir;)Ljava/lang/String;)
    0010 astore 2
    0012 getstatic Field(java/lang/System.out:Ljava/io/PrintStream;)
    0015 aload 2
    0017 invokevirtual Method(java/io/PrintStream.println:(Ljava/lang/String;)V)
    0020 invokestatic Method(InputKt.WEST:()LDir;)
    0023 astore 3
    0025 aload 3
    0027 invokestatic Method(InputKt.move:(LDir;)Ljava/lang/String;)
    0030 astore 4
    0032 getstatic Field(java/lang/System.out:Ljava/io/PrintStream;)
    0035 aload 4
    0037 invokevirtual Method(java/io/PrintStream.println:(Ljava/lang/String;)V)
    0040 return
method        move (LDir;)Ljava/lang/String; 0x0009
  code        max_stack=2 max_locals=16
    0000 aload 0
    0002 op_0xC0
    0003 nop
    0004 op_0x0B
    0005 astore 1
    0007 op_0xA7
    0008 nop
    0009 iconst_0
    0010 invokestatic Method(InputKt.NORTH:()LDir;)
    0013 astore 2
    0015 aload 1
    0017 aload 2
    0019 op_0x5F
    0020 invokevirtual Method(java/lang/Object.toString:()Ljava/lang/String;)
    0023 op_0x5F
    0024 invokevirtual Method(java/lang/Object.toString:()Ljava/lang/String;)
    0027 invokevirtual Method(java/lang/String.equals:(Ljava/lang/Object;)Z)
    0030 istore 3
    0032 iload 3
    0034 op_0x99
    0035 nop
    0036 op_0x0E
    0037 ldc "up"
    0039 astore 4
    0041 aload 4
    0043 astore 5
    0045 op_0xA7
    0046 nop
    0047 op_0x80
    0048 invokestatic Method(InputKt.SOUTH:()LDir;)
    0051 astore 6
    0053 aload 1
    0055 aload 6
    0057 op_0x5F
    0058 invokevirtual Method(java/lang/Object.toString:()Ljava/lang/String;)
    0061 op_0x5F
    0062 invokevirtual Method(java/lang/Object.toString:()Ljava/lang/String;)
    0065 invokevirtual Method(java/lang/String.equals:(Ljava/lang/Object;)Z)
    0068 istore 7
    0070 iload 7
    0072 op_0x99
    0073 nop
    0074 op_0x0E
    0075 ldc "down"
    0077 astore 8
    0079 aload 8
    0081 astore 5
    0083 op_0xA7
    0084 nop
    0085 op_0x5A
    0086 invokestatic Method(InputKt.EAST:()LDir;)
    0089 astore 9
    0091 aload 1
    0093 aload 9
    0095 op_0x5F
    0096 invokevirtual Method(java/lang/Object.toString:()Ljava/lang/String;)
    0099 op_0x5F
    0100 invokevirtual Method(java/lang/Object.toString:()Ljava/lang/String;)
    0103 invokevirtual Method(java/lang/String.equals:(Ljava/lang/Object;)Z)
    0106 istore 10
    0108 iload 10
    0110 op_0x99
    0111 nop
    0112 op_0x0E
    0113 ldc "right"
    0115 astore 11
    0117 aload 11
    0119 astore 5
    0121 op_0xA7
    0122 nop
    0123 op_0x34
    0124 invokestatic Method(InputKt.WEST:()LDir;)
    0127 astore 12
    0129 aload 1
    0131 aload 12
    0133 op_0x5F
    0134 invokevirtual Method(java/lang/Object.toString:()Ljava/lang/String;)
    0137 op_0x5F
    0138 invokevirtual Method(java/lang/Object.toString:()Ljava/lang/String;)
    0141 invokevirtual Method(java/lang/String.equals:(Ljava/lang/Object;)Z)
    0144 istore 13
    0146 iload 13
    0148 op_0x99
    0149 nop
    0150 op_0x0E
    0151 ldc "left"
    0153 astore 14
    0155 aload 14
    0157 astore 5
    0159 op_0xA7
    0160 nop
    0161 op_0x0E
    0162 ldc "?"
    0164 astore 15
    0166 aload 15
    0168 astore 5
    0170 op_0xA7
    0171 nop
    0172 iconst_0
    0173 aload 5
    0175 op_0xB0
    sub_attr  StackMapTable (137 bytes)
