class_version major=61 minor=0
this_class    InputKt
super_class   java/lang/Object
access_flags  0x0031
method        Dir$valueOf (Ljava/lang/String;)LDir; 0x0019
  code        max_stack=5 max_locals=14
    0000 aload_0
    0001 ldc "name"
    0003 invokestatic Method(kotlin/jvm/internal/Intrinsics.checkNotNullParameter:(Ljava/lang/Object;Ljava/lang/String;)V)
    0006 ldc "NORTH"
    0008 astore_1
    0009 aload_0
    0010 aload_1
    0011 invokestatic Method(kotlin/jvm/internal/Intrinsics.areEqual:(Ljava/lang/Object;Ljava/lang/Object;)Z)
    0014 istore_2
    0015 iload_2
    0016 ifeq 78
    0019 goto 103
    0022 invokestatic Method(InputKt.NORTH:()LDir;)
    0025 astore_3
    0026 aload_3
    0027 areturn
    0028 ldc "WEST"
    0030 astore 4
    0032 aload_0
    0033 aload 4
    0035 invokestatic Method(kotlin/jvm/internal/Intrinsics.areEqual:(Ljava/lang/Object;Ljava/lang/Object;)Z)
    0038 istore 5
    0040 iload 5
    0042 ifeq 22
    0045 invokestatic Method(InputKt.WEST:()LDir;)
    0048 astore 6
    0050 aload 6
    0052 areturn
    0053 ldc "EAST"
    0055 astore 7
    0057 aload_0
    0058 aload 7
    0060 invokestatic Method(kotlin/jvm/internal/Intrinsics.areEqual:(Ljava/lang/Object;Ljava/lang/Object;)Z)
    0063 istore 8
    0065 iload 8
    0067 ifeq 28
    0070 invokestatic Method(InputKt.EAST:()LDir;)
    0073 astore 9
    0075 aload 9
    0077 areturn
    0078 ldc "SOUTH"
    0080 astore 10
    0082 aload_0
    0083 aload 10
    0085 invokestatic Method(kotlin/jvm/internal/Intrinsics.areEqual:(Ljava/lang/Object;Ljava/lang/Object;)Z)
    0088 istore 11
    0090 iload 11
    0092 ifeq 53
    0095 invokestatic Method(InputKt.SOUTH:()LDir;)
    0098 astore 12
    0100 aload 12
    0102 areturn
    0103 invokestatic Method(InputKt.NORTH:()LDir;)
    0106 astore 13
    0108 aload 13
    0110 areturn
    sub_attr  StackMapTable (98 bytes)
  attr        RuntimeInvisibleAnnotations (6 bytes)
  attr        RuntimeInvisibleParameterAnnotations (7 bytes)
method        Dir$values ()Ljava/util/ArrayList; 0x0019
  code        max_stack=2 max_locals=1
    0000 new Class(java/util/ArrayList)
    0003 dup
    0004 invokespecial Method(java/util/ArrayList.<init>:()V)
    0007 astore_0
    0008 invokestatic Method(InputKt.NORTH:()LDir;)
    0011 aload_0
    0012 swap
    0013 invokevirtual Method(java/util/ArrayList.add:(Ljava/lang/Object;)Z)
    0016 pop
    0017 invokestatic Method(InputKt.SOUTH:()LDir;)
    0020 aload_0
    0021 swap
    0022 invokevirtual Method(java/util/ArrayList.add:(Ljava/lang/Object;)Z)
    0025 pop
    0026 invokestatic Method(InputKt.EAST:()LDir;)
    0029 aload_0
    0030 swap
    0031 invokevirtual Method(java/util/ArrayList.add:(Ljava/lang/Object;)Z)
    0034 pop
    0035 invokestatic Method(InputKt.WEST:()LDir;)
    0038 aload_0
    0039 swap
    0040 invokevirtual Method(java/util/ArrayList.add:(Ljava/lang/Object;)Z)
    0043 pop
    0044 aload_0
    0045 areturn
  attr        RuntimeInvisibleAnnotations (6 bytes)
method        EAST ()LDir; 0x0019
  code        max_stack=3 max_locals=0
    0000 new Class(Dir)
    0003 dup
    0004 ldc "EAST"
    0006 invokespecial Method(Dir.<init>:(Ljava/lang/String;)V)
    0009 areturn
  attr        RuntimeInvisibleAnnotations (6 bytes)
method        NORTH ()LDir; 0x0019
  code        max_stack=3 max_locals=0
    0000 new Class(Dir)
    0003 dup
    0004 ldc "NORTH"
    0006 invokespecial Method(Dir.<init>:(Ljava/lang/String;)V)
    0009 areturn
  attr        RuntimeInvisibleAnnotations (6 bytes)
method        SOUTH ()LDir; 0x0019
  code        max_stack=3 max_locals=0
    0000 new Class(Dir)
    0003 dup
    0004 ldc "SOUTH"
    0006 invokespecial Method(Dir.<init>:(Ljava/lang/String;)V)
    0009 areturn
  attr        RuntimeInvisibleAnnotations (6 bytes)
method        WEST ()LDir; 0x0019
  code        max_stack=3 max_locals=0
    0000 new Class(Dir)
    0003 dup
    0004 ldc "WEST"
    0006 invokespecial Method(Dir.<init>:(Ljava/lang/String;)V)
    0009 areturn
  attr        RuntimeInvisibleAnnotations (6 bytes)
method        main ()V 0x0019
  code        max_stack=2 max_locals=0
    0000 invokestatic Method(InputKt.NORTH:()LDir;)
    0003 invokestatic Method(InputKt.move:(LDir;)Ljava/lang/String;)
    0006 getstatic Field(java/lang/System.out:Ljava/io/PrintStream;)
    0009 swap
    0010 invokevirtual Method(java/io/PrintStream.println:(Ljava/lang/Object;)V)
    0013 invokestatic Method(InputKt.WEST:()LDir;)
    0016 invokestatic Method(InputKt.move:(LDir;)Ljava/lang/String;)
    0019 getstatic Field(java/lang/System.out:Ljava/io/PrintStream;)
    0022 swap
    0023 invokevirtual Method(java/io/PrintStream.println:(Ljava/lang/Object;)V)
    0026 return
method        main ([Ljava/lang/String;)V 0x1009
  code        max_stack=0 max_locals=1
    0000 invokestatic Method(InputKt.main:()V)
    0003 return
method        move (LDir;)Ljava/lang/String; 0x0019
  code        max_stack=2 max_locals=15
    0000 aload_0
    0001 ldc "d"
    0003 invokestatic Method(kotlin/jvm/internal/Intrinsics.checkNotNullParameter:(Ljava/lang/Object;Ljava/lang/String;)V)
    0006 goto 9
    0009 invokestatic Method(InputKt.NORTH:()LDir;)
    0012 astore_1
    0013 aload_0
    0014 aload_1
    0015 swap
    0016 invokevirtual Method(java/lang/Object.toString:()Ljava/lang/String;)
    0019 swap
    0020 invokevirtual Method(java/lang/Object.toString:()Ljava/lang/String;)
    0023 invokevirtual Method(java/lang/String.equals:(Ljava/lang/Object;)Z)
    0026 istore_2
    0027 iload_2
    0028 ifeq 40
    0031 ldc "up"
    0033 astore_3
    0034 aload_3
    0035 astore 4
    0037 goto 162
    0040 invokestatic Method(InputKt.SOUTH:()LDir;)
    0043 astore 5
    0045 aload_0
    0046 aload 5
    0048 swap
    0049 invokevirtual Method(java/lang/Object.toString:()Ljava/lang/String;)
    0052 swap
    0053 invokevirtual Method(java/lang/Object.toString:()Ljava/lang/String;)
    0056 invokevirtual Method(java/lang/String.equals:(Ljava/lang/Object;)Z)
    0059 istore 6
    0061 iload 6
    0063 ifeq 77
    0066 ldc "down"
    0068 astore 7
    0070 aload 7
    0072 astore 4
    0074 goto 162
    0077 invokestatic Method(InputKt.EAST:()LDir;)
    0080 astore 8
    0082 aload_0
    0083 aload 8
    0085 swap
    0086 invokevirtual Method(java/lang/Object.toString:()Ljava/lang/String;)
    0089 swap
    0090 invokevirtual Method(java/lang/Object.toString:()Ljava/lang/String;)
    0093 invokevirtual Method(java/lang/String.equals:(Ljava/lang/Object;)Z)
    0096 istore 9
    0098 iload 9
    0100 ifeq 114
    0103 ldc "right"
    0105 astore 10
    0107 aload 10
    0109 astore 4
    0111 goto 162
    0114 invokestatic Method(InputKt.WEST:()LDir;)
    0117 astore 11
    0119 aload_0
    0120 aload 11
    0122 swap
    0123 invokevirtual Method(java/lang/Object.toString:()Ljava/lang/String;)
    0126 swap
    0127 invokevirtual Method(java/lang/Object.toString:()Ljava/lang/String;)
    0130 invokevirtual Method(java/lang/String.equals:(Ljava/lang/Object;)Z)
    0133 istore 12
    0135 iload 12
    0137 ifeq 151
    0140 ldc "left"
    0142 astore 13
    0144 aload 13
    0146 astore 4
    0148 goto 162
    0151 ldc "?"
    0153 astore 14
    0155 aload 14
    0157 astore 4
    0159 goto 162
    0162 aload 4
    0164 areturn
    sub_attr  StackMapTable (64 bytes)
  attr        RuntimeInvisibleAnnotations (6 bytes)
  attr        RuntimeInvisibleParameterAnnotations (7 bytes)
