class_version major=61 minor=0
this_class    InputKt
super_class   java/lang/Object
access_flags  0x0031
method        isSafe ([III)Z 0x0019
  code        max_stack=3 max_locals=6
    0000 aload_0
    0001 ldc "cols"
    0003 invokestatic Method(kotlin/jvm/internal/Intrinsics.checkNotNullParameter:(Ljava/lang/Object;Ljava/lang/String;)V)
    0006 iconst_0
    0007 istore_3
    0008 iload_3
    0009 iload_1
    0010 if_icmpge 59
    0013 aload_0
    0014 iload_3
    0015 iaload
    0016 iload_2
    0017 if_icmpne 22
    0020 iconst_0
    0021 ireturn
    0022 iload_2
    0023 aload_0
    0024 iload_3
    0025 iaload
    0026 isub
    0027 istore 4
    0029 iload_1
    0030 iload_3
    0031 isub
    0032 istore 5
    0034 iload 4
    0036 iload 5
    0038 if_icmpne 43
    0041 iconst_0
    0042 ireturn
    0043 iload 4
    0045 iload 5
    0047 ineg
    0048 if_icmpne 53
    0051 iconst_0
    0052 ireturn
    0053 iinc 3 1
    0056 goto 8
    0059 iconst_1
    0060 ireturn
    sub_attr  StackMapTable (16 bytes)
  attr        RuntimeInvisibleParameterAnnotations (11 bytes)
method        main ()V 0x0019
  code        max_stack=2 max_locals=1
    0000 iconst_1
    0001 istore_0
    0002 iload_0
    0003 bipush 9
    0005 if_icmpgt 31
    0008 iload_0
    0009 iload_0
    0010 invokestatic Method(InputKt.solveNQueens:(I)I)
    0013 invokedynamic InvokeDynamic(makeConcatWithConstants:(II)Ljava/lang/String;)
    0018 getstatic Field(java/lang/System.out:Ljava/io/PrintStream;)
    0021 swap
    0022 invokevirtual Method(java/io/PrintStream.println:(Ljava/lang/Object;)V)
    0025 iinc 0 1
    0028 goto 2
    0031 return
    sub_attr  StackMapTable (7 bytes)
method        main ([Ljava/lang/String;)V 0x1009
  code        max_stack=0 max_locals=1
    0000 invokestatic Method(InputKt.main:()V)
    0003 return
method        place ([III[I)V 0x0019
  code        max_stack=4 max_locals=5
    0000 aload_0
    0001 ldc "cols"
    0003 invokestatic Method(kotlin/jvm/internal/Intrinsics.checkNotNullParameter:(Ljava/lang/Object;Ljava/lang/String;)V)
    0006 aload_3
    0007 ldc "counter"
    0009 invokestatic Method(kotlin/jvm/internal/Intrinsics.checkNotNullParameter:(Ljava/lang/Object;Ljava/lang/String;)V)
    0012 iload_2
    0013 iload_1
    0014 if_icmpne 26
    0017 aload_3
    0018 iconst_0
    0019 aload_3
    0020 iconst_0
    0021 iaload
    0022 iconst_1
    0023 iadd
    0024 iastore
    0025 return
    0026 iconst_0
    0027 istore 4
    0029 iload 4
    0031 iload_1
    0032 if_icmpge 65
    0035 aload_0
    0036 iload_2
    0037 iload 4
    0039 invokestatic Method(InputKt.isSafe:([III)Z)
    0042 ifeq 59
    0045 aload_0
    0046 iload_2
    0047 iload 4
    0049 iastore
    0050 aload_0
    0051 iload_1
    0052 iload_2
    0053 iconst_1
    0054 iadd
    0055 aload_3
    0056 invokestatic Method(InputKt.place:([III[I)V)
    0059 iinc 4 1
    0062 goto 29
    0065 return
    sub_attr  StackMapTable (9 bytes)
  attr        RuntimeInvisibleParameterAnnotations (17 bytes)
method        solveNQueens (I)I 0x0019
  code        max_stack=4 max_locals=3
    0000 iload_0
    0001 newarray int
    0003 astore_1
    0004 iconst_1
    0005 newarray int
    0007 astore_2
    0008 aload_1
    0009 iload_0
    0010 iconst_0
    0011 aload_2
    0012 invokestatic Method(InputKt.place:([III[I)V)
    0015 aload_2
    0016 iconst_0
    0017 iaload
    0018 ireturn
class_attr    BootstrapMethods (8 bytes)
