class_version major=61 minor=0
this_class    InputKt
super_class   java/lang/Object
access_flags  0x0031
method        emptyCatch ()V 0x0019
  code        max_stack=1 max_locals=1
    0000 nop
    0001 goto 7
    0004 astore_0
    0005 aload_0
    0006 athrow
    0007 return
    sub_attr  StackMapTable (7 bytes)
method        emptyCatchFinally ()V 0x0019
  code        max_stack=2 max_locals=1
    0000 nop
    0001 ldc "cf finally ran"
    0003 getstatic Field(java/lang/System.out:Ljava/io/PrintStream;)
    0006 swap
    0007 invokevirtual Method(java/io/PrintStream.println:(Ljava/lang/Object;)V)
    0010 goto 28
    0013 astore_0
    0014 aload_0
    0015 athrow
    0016 astore_0
    0017 ldc "cf finally ran"
    0019 getstatic Field(java/lang/System.out:Ljava/io/PrintStream;)
    0022 swap
    0023 invokevirtual Method(java/io/PrintStream.println:(Ljava/lang/Object;)V)
    0026 aload_0
    0027 athrow
    0028 return
    sub_attr  StackMapTable (11 bytes)
method        emptyFinally ()V 0x0019
  code        max_stack=2 max_locals=1
    0000 nop
    0001 ldc "finally ran"
    0003 getstatic Field(java/lang/System.out:Ljava/io/PrintStream;)
    0006 swap
    0007 invokevirtual Method(java/io/PrintStream.println:(Ljava/lang/Object;)V)
    0010 goto 25
    0013 astore_0
    0014 ldc "finally ran"
    0016 getstatic Field(java/lang/System.out:Ljava/io/PrintStream;)
    0019 swap
    0020 invokevirtual Method(java/io/PrintStream.println:(Ljava/lang/Object;)V)
    0023 aload_0
    0024 athrow
    0025 return
    sub_attr  StackMapTable (7 bytes)
method        main ()V 0x0019
  code        max_stack=2 max_locals=0
    0000 invokestatic Method(InputKt.emptyCatch:()V)
    0003 invokestatic Method(InputKt.emptyFinally:()V)
    0006 invokestatic Method(InputKt.emptyCatchFinally:()V)
    0009 ldc "ok"
    0011 getstatic Field(java/lang/System.out:Ljava/io/PrintStream;)
    0014 swap
    0015 invokevirtual Method(java/io/PrintStream.println:(Ljava/lang/Object;)V)
    0018 return
method        main ([Ljava/lang/String;)V 0x1009
  code        max_stack=0 max_locals=1
    0000 invokestatic Method(InputKt.main:()V)
    0003 return
