class_version major=61 minor=0
this_class    Secret
super_class   java/lang/Object
access_flags  0x0021
field         code : I 0x0001
method        <init> (I)V 0x0001
  code        max_stack=2 max_locals=2
    0000 aload_0
    0001 invokespecial Method(java/lang/Object.<init>:()V)
    0004 aload_0
    0005 iload_1
    0006 putfield Field(Secret.code:I)
    0009 return
method        check (I)Z 0x0001
  code        max_stack=3 max_locals=3
    0000 aload_0
    0001 getfield Field(Secret.code:I)
    0004 istore_2
    0005 iload_1
    0006 iload_2
    0007 if_icmpne 14
    0010 iconst_1
    0011 goto 15
    0014 iconst_0
    0015 aload_0
    0016 iload_2
    0017 putfield Field(Secret.code:I)
    0020 ireturn
    sub_attr  StackMapTable (8 bytes)
method        getCode ()I 0x0001
  code        max_stack=1 max_locals=1
    0000 aload_0
    0001 getfield Field(Secret.code:I)
    0004 ireturn
method        reveal ()I 0x0001
  code        max_stack=2 max_locals=2
    0000 aload_0
    0001 getfield Field(Secret.code:I)
    0004 istore_1
    0005 aload_0
    0006 iload_1
    0007 putfield Field(Secret.code:I)
    0010 iload_1
    0011 ireturn
