class_version major=61 minor=0
this_class    InputKt
super_class   java/lang/Object
access_flags  0x0031
field         b : LBox; 0x001A
method        <clinit> ()V 0x001A
  code        max_stack=1 max_locals=0
    0000 bipush 42
    0002 invokestatic Method(InputKt.Box:(I)LBox;)
    0005 putstatic Field(InputKt.b:LBox;)
    0008 return
method        Box (I)LBox; 0x0019
  code        max_stack=3 max_locals=2
    0000 iload_0
    0001 invokestatic Method(java/lang/String.valueOf:(I)Ljava/lang/String;)
    0004 astore_1
    0005 new Class(Box)
    0008 dup
    0009 aload_1
    0010 invokespecial Method(Box.<init>:(Ljava/lang/String;)V)
    0013 areturn
  attr        RuntimeInvisibleAnnotations (6 bytes)
method        getB ()LBox; 0x0019
  code        max_stack=1 max_locals=0
    0000 getstatic Field(InputKt.b:LBox;)
    0003 areturn
  attr        RuntimeInvisibleAnnotations (6 bytes)
method        main ()V 0x0019
  code        max_stack=2 max_locals=0
    0000 getstatic Field(InputKt.b:LBox;)
    0003 invokevirtual Method(Box.getS:()Ljava/lang/String;)
    0006 getstatic Field(java/lang/System.out:Ljava/io/PrintStream;)
    0009 swap
    0010 invokevirtual Method(java/io/PrintStream.println:(Ljava/lang/Object;)V)
    0013 return
method        main ([Ljava/lang/String;)V 0x1009
  code        max_stack=0 max_locals=1
    0000 invokestatic Method(InputKt.main:()V)
    0003 return
