class_version major=61 minor=0
this_class    InputKt
super_class   java/lang/Object
access_flags  0x0031
method        abs (I)I 0x0019
  code        max_stack=1 max_locals=1
    0000 op_0x1A
    0001 op_0x9C
    0002 nop
    0003 iconst_5
    0004 op_0x1A
    0005 op_0x74
    0006 op_0xA7
    0007 nop
    0008 iconst_1
    0009 op_0x1A
    0010 op_0xAC
    sub_attr  StackMapTable (5 bytes)
method        gcd (II)I 0x0019
  code        max_stack=2 max_locals=5
    0000 op_0x1A
    0001 invokestatic Method(InputKt.abs:(I)I)
    0004 op_0x3D
    0005 op_0x1B
    0006 invokestatic Method(InputKt.abs:(I)I)
    0009 op_0x3E
    0010 op_0x1D
    0011 op_0x99
    0012 nop
    0013 bipush 29
    0015 istore 4
    0017 op_0x1C
    0018 op_0x1D
    0019 irem
    0020 op_0x3E
    0021 iload 4
    0023 op_0x3D
    0024 op_0xA7
    0025 op_0xFF
    0026 op_0xF2
    0027 op_0x1C
    0028 op_0xAC
    sub_attr  StackMapTable (8 bytes)
method        lcm (II)I 0x0019
  code        max_stack=3 max_locals=2
    0000 op_0x1A
    0001 op_0x1A
    0002 op_0x1B
    0003 invokestatic Method(InputKt.gcd:(II)I)
    0006 idiv
    0007 op_0x1B
    0008 imul
    0009 op_0xAC
method        main ()V 0x0019
  code        max_stack=2 max_locals=1
    0000 bipush -42
    0002 invokestatic Method(InputKt.abs:(I)I)
    0005 op_0x3B
    0006 getstatic Field(java/lang/System.out:Ljava/io/PrintStream;)
    0009 op_0x1A
    0010 invokevirtual Method(java/io/PrintStream.println:(I)V)
    0013 iconst_3
    0014 bipush 7
    0016 invokestatic Method(InputKt.min:(II)I)
    0019 op_0x3B
    0020 getstatic Field(java/lang/System.out:Ljava/io/PrintStream;)
    0023 op_0x1A
    0024 invokevirtual Method(java/io/PrintStream.println:(I)V)
    0027 iconst_3
    0028 bipush 7
    0030 invokestatic Method(InputKt.max:(II)I)
    0033 op_0x3B
    0034 getstatic Field(java/lang/System.out:Ljava/io/PrintStream;)
    0037 op_0x1A
    0038 invokevirtual Method(java/io/PrintStream.println:(I)V)
    0041 bipush 12
    0043 bipush 8
    0045 invokestatic Method(InputKt.gcd:(II)I)
    0048 op_0x3B
    0049 getstatic Field(java/lang/System.out:Ljava/io/PrintStream;)
    0052 op_0x1A
    0053 invokevirtual Method(java/io/PrintStream.println:(I)V)
    0056 iconst_4
    0057 bipush 6
    0059 invokestatic Method(InputKt.lcm:(II)I)
    0062 op_0x3B
    0063 getstatic Field(java/lang/System.out:Ljava/io/PrintStream;)
    0066 op_0x1A
    0067 invokevirtual Method(java/io/PrintStream.println:(I)V)
    0070 return
method        main ([Ljava/lang/String;)V 0x1009
  code        max_stack=0 max_locals=1
    0000 invokestatic Method(InputKt.main:()V)
    0003 return
method        max (II)I 0x0019
  code        max_stack=2 max_locals=2
    0000 op_0x1A
    0001 op_0x1B
    0002 op_0xA4
    0003 nop
    0004 iconst_4
    0005 op_0x1A
    0006 op_0xA7
    0007 nop
    0008 iconst_1
    0009 op_0x1B
    0010 op_0xAC
    sub_attr  StackMapTable (5 bytes)
method        min (II)I 0x0019
  code        max_stack=2 max_locals=2
    0000 op_0x1A
    0001 op_0x1B
    0002 op_0xA2
    0003 nop
    0004 iconst_4
    0005 op_0x1A
    0006 op_0xA7
    0007 nop
    0008 iconst_1
    0009 op_0x1B
    0010 op_0xAC
    sub_attr  StackMapTable (5 bytes)
