class_version major=61 minor=0
this_class    InputKt
super_class   java/lang/Object
access_flags  0x0031
method        abs (I)I 0x0009
  code        max_stack=2 max_locals=9
    0000 iload 0
    0002 istore 1
    0004 iconst_0
    0005 istore 2
    0007 iload 1
    0009 iload 2
    0011 op_0xA1
    0012 nop
    0013 iconst_4
    0014 iconst_0
    0015 op_0xA7
    0016 nop
    0017 iconst_1
    0018 iconst_1
    0019 istore 3
    0021 iload 3
    0023 op_0x99
    0024 nop
    0025 op_0x18
    0026 iload 0
    0028 istore 4
    0030 iconst_0
    0031 istore 5
    0033 iload 5
    0035 iload 4
    0037 isub
    0038 istore 6
    0040 iload 6
    0042 istore 7
    0044 op_0xA7
    0045 nop
    0046 op_0x0E
    0047 iload 0
    0049 istore 8
    0051 iload 8
    0053 istore 7
    0055 op_0xA7
    0056 nop
    0057 iconst_0
    0058 iload 7
    0060 op_0xAC
    sub_attr  StackMapTable (49 bytes)
method        gcd (II)I 0x0009
  code        max_stack=2 max_locals=18
    0000 iload 0
    0002 istore 2
    0004 iload 2
    0006 invokestatic Method(InputKt.abs:(I)I)
    0009 istore 3
    0011 iload 3
    0013 istore 4
    0015 iload 1
    0017 istore 5
    0019 iload 5
    0021 invokestatic Method(InputKt.abs:(I)I)
    0024 istore 6
    0026 iload 6
    0028 istore 7
    0030 op_0xA7
    0031 nop
    0032 iconst_0
    0033 iload 7
    0035 istore 8
    0037 iconst_0
    0038 istore 9
    0040 iload 8
    0042 iload 9
    0044 op_0xA0
    0045 nop
    0046 iconst_4
    0047 iconst_0
    0048 op_0xA7
    0049 nop
    0050 iconst_1
    0051 iconst_1
    0052 istore 10
    0054 iload 10
    0056 op_0x99
    0057 nop
    0058 op_0x29
    0059 iload 7
    0061 istore 11
    0063 iload 11
    0065 istore 12
    0067 iload 4
    0069 istore 13
    0071 iload 7
    0073 istore 14
    0075 iload 13
    0077 iload 14
    0079 irem
    0080 istore 15
    0082 iload 15
    0084 istore 7
    0086 iload 12
    0088 istore 16
    0090 iload 16
    0092 istore 4
    0094 op_0xA7
    0095 op_0xFF
    0096 op_0xC3
    0097 iload 4
    0099 istore 17
    0101 iload 17
    0103 op_0xAC
    sub_attr  StackMapTable (70 bytes)
method        lcm (II)I 0x0009
  code        max_stack=2 max_locals=9
    0000 iload 0
    0002 istore 2
    0004 iload 0
    0006 istore 3
    0008 iload 1
    0010 istore 4
    0012 iload 3
    0014 iload 4
    0016 invokestatic Method(InputKt.gcd:(II)I)
    0019 istore 5
    0021 iload 2
    0023 iload 5
    0025 idiv
    0026 istore 6
    0028 iload 1
    0030 istore 7
    0032 iload 6
    0034 iload 7
    0036 imul
    0037 istore 8
    0039 iload 8
    0041 op_0xAC
method        main ([Ljava/lang/String;)V 0x0009
  code        max_stack=2 max_locals=15
    0000 bipush -42
    0002 istore 1
    0004 iload 1
    0006 invokestatic Method(InputKt.abs:(I)I)
    0009 istore 2
    0011 getstatic Field(java/lang/System.out:Ljava/io/PrintStream;)
    0014 iload 2
    0016 invokevirtual Method(java/io/PrintStream.println:(I)V)
    0019 iconst_3
    0020 istore 3
    0022 bipush 7
    0024 istore 4
    0026 iload 3
    0028 iload 4
    0030 invokestatic Method(InputKt.min:(II)I)
    0033 istore 5
    0035 getstatic Field(java/lang/System.out:Ljava/io/PrintStream;)
    0038 iload 5
    0040 invokevirtual Method(java/io/PrintStream.println:(I)V)
    0043 iconst_3
    0044 istore 6
    0046 bipush 7
    0048 istore 7
    0050 iload 6
    0052 iload 7
    0054 invokestatic Method(InputKt.max:(II)I)
    0057 istore 8
    0059 getstatic Field(java/lang/System.out:Ljava/io/PrintStream;)
    0062 iload 8
    0064 invokevirtual Method(java/io/PrintStream.println:(I)V)
    0067 bipush 12
    0069 istore 9
    0071 bipush 8
    0073 istore 10
    0075 iload 9
    0077 iload 10
    0079 invokestatic Method(InputKt.gcd:(II)I)
    0082 istore 11
    0084 getstatic Field(java/lang/System.out:Ljava/io/PrintStream;)
    0087 iload 11
    0089 invokevirtual Method(java/io/PrintStream.println:(I)V)
    0092 iconst_4
    0093 istore 12
    0095 bipush 6
    0097 istore 13
    0099 iload 12
    0101 iload 13
    0103 invokestatic Method(InputKt.lcm:(II)I)
    0106 istore 14
    0108 getstatic Field(java/lang/System.out:Ljava/io/PrintStream;)
    0111 iload 14
    0113 invokevirtual Method(java/io/PrintStream.println:(I)V)
    0116 return
method        max (II)I 0x0009
  code        max_stack=2 max_locals=8
    0000 iload 0
    0002 istore 2
    0004 iload 1
    0006 istore 3
    0008 iload 2
    0010 iload 3
    0012 op_0xA3
    0013 nop
    0014 iconst_4
    0015 iconst_0
    0016 op_0xA7
    0017 nop
    0018 iconst_1
    0019 iconst_1
    0020 istore 4
    0022 iload 4
    0024 op_0x99
    0025 nop
    0026 op_0x0E
    0027 iload 0
    0029 istore 5
    0031 iload 5
    0033 istore 6
    0035 op_0xA7
    0036 nop
    0037 op_0x0E
    0038 iload 1
    0040 istore 7
    0042 iload 7
    0044 istore 6
    0046 op_0xA7
    0047 nop
    0048 iconst_0
    0049 iload 6
    0051 op_0xAC
    sub_attr  StackMapTable (51 bytes)
method        min (II)I 0x0009
  code        max_stack=2 max_locals=8
    0000 iload 0
    0002 istore 2
    0004 iload 1
    0006 istore 3
    0008 iload 2
    0010 iload 3
    0012 op_0xA1
    0013 nop
    0014 iconst_4
    0015 iconst_0
    0016 op_0xA7
    0017 nop
    0018 iconst_1
    0019 iconst_1
    0020 istore 4
    0022 iload 4
    0024 op_0x99
    0025 nop
    0026 op_0x0E
    0027 iload 0
    0029 istore 5
    0031 iload 5
    0033 istore 6
    0035 op_0xA7
    0036 nop
    0037 op_0x0E
    0038 iload 1
    0040 istore 7
    0042 iload 7
    0044 istore 6
    0046 op_0xA7
    0047 nop
    0048 iconst_0
    0049 iload 6
    0051 op_0xAC
    sub_attr  StackMapTable (51 bytes)
