class_version major=61 minor=0
this_class    InputKt
super_class   java/lang/Object
access_flags  0x0031
method        greet (Ljava/lang/String;)Ljava/lang/String; 0x0009
  code        max_stack=2 max_locals=6
    0000 ldc "Hello, "
    0002 astore 1
    0004 aload 0
    0006 astore 2
    0008 aload 1
    0010 aload 2
    0012 invokevirtual Method(java/lang/String.concat:(Ljava/lang/String;)Ljava/lang/String;)
    0015 astore 3
    0017 ldc "!"
    0019 astore 4
    0021 aload 3
    0023 aload 4
    0025 invokevirtual Method(java/lang/String.concat:(Ljava/lang/String;)Ljava/lang/String;)
    0028 astore 5
    0030 aload 5
    0032 areturn
method        main ([Ljava/lang/String;)V 0x0009
  code        max_stack=9 max_locals=58
    0000 iconst_1
    0001 istore 1
    0003 iconst_2
    0004 istore 2
    0006 iconst_3
    0007 istore 3
    0009 iconst_4
    0010 istore 4
    0012 iconst_5
    0013 istore 5
    0015 iconst_5
    0016 istore 6
    0018 iload 6
    0020 op_0xBD
    0021 nop
    0022 iconst_1
    0023 astore 7
    0025 iconst_0
    0026 istore 8
    0028 iload 1
    0030 invokestatic Method(java/lang/Integer.valueOf:(I)Ljava/lang/Integer;)
    0033 astore 9
    0035 aload 7
    0037 iload 8
    0039 aload 9
    0041 op_0x53
    0042 iconst_1
    0043 istore 10
    0045 iload 2
    0047 invokestatic Method(java/lang/Integer.valueOf:(I)Ljava/lang/Integer;)
    0050 astore 11
    0052 aload 7
    0054 iload 10
    0056 aload 11
    0058 op_0x53
    0059 iconst_2
    0060 istore 12
    0062 iload 3
    0064 invokestatic Method(java/lang/Integer.valueOf:(I)Ljava/lang/Integer;)
    0067 astore 13
    0069 aload 7
    0071 iload 12
    0073 aload 13
    0075 op_0x53
    0076 iconst_3
    0077 istore 14
    0079 iload 4
    0081 invokestatic Method(java/lang/Integer.valueOf:(I)Ljava/lang/Integer;)
    0084 astore 15
    0086 aload 7
    0088 iload 14
    0090 aload 15
    0092 op_0x53
    0093 iconst_4
    0094 istore 16
    0096 iload 5
    0098 invokestatic Method(java/lang/Integer.valueOf:(I)Ljava/lang/Integer;)
    0101 astore 17
    0103 aload 7
    0105 iload 16
    0107 aload 17
    0109 op_0x53
    0110 aload 7
    0112 invokestatic Method(kotlin/collections/CollectionsKt.listOf:([Ljava/lang/Object;)Ljava/util/List;)
    0115 astore 18
    0117 aload 18
    0119 checkcast Class(java/util/List)
    0122 astore 19
    0124 ldc "Count: "
    0126 astore 20
    0128 aload 19
    0130 checkcast Class(java/util/List)
    0133 astore 21
    0135 aload 21
    0137 invokeinterface InterfaceMethod(java/util/List.size:()I)
    0142 istore 22
    0144 getstatic Field(java/lang/System.out:Ljava/io/PrintStream;)
    0147 new Class(java/lang/StringBuilder)
    0150 dup
    0151 invokespecial Method(java/lang/StringBuilder.<init>:()V)
    0154 aload 20
    0156 invokevirtual Method(java/lang/StringBuilder.append:(Ljava/lang/String;)Ljava/lang/StringBuilder;)
    0159 iload 22
    0161 invokevirtual Method(java/lang/StringBuilder.append:(I)Ljava/lang/StringBuilder;)
    0164 invokevirtual Method(java/lang/StringBuilder.toString:()Ljava/lang/String;)
    0167 invokevirtual Method(java/io/PrintStream.println:(Ljava/lang/String;)V)
    0170 ldc "Greeting: "
    0172 astore 23
    0174 ldc "World"
    0176 astore 24
    0178 aload 24
    0180 invokestatic Method(InputKt.greet:(Ljava/lang/String;)Ljava/lang/String;)
    0183 astore 25
    0185 getstatic Field(java/lang/System.out:Ljava/io/PrintStream;)
    0188 new Class(java/lang/StringBuilder)
    0191 dup
    0192 invokespecial Method(java/lang/StringBuilder.<init>:()V)
    0195 aload 23
    0197 invokevirtual Method(java/lang/StringBuilder.append:(Ljava/lang/String;)Ljava/lang/StringBuilder;)
    0200 aload 25
    0202 invokevirtual Method(java/lang/StringBuilder.append:(Ljava/lang/String;)Ljava/lang/StringBuilder;)
    0205 invokevirtual Method(java/lang/StringBuilder.toString:()Ljava/lang/String;)
    0208 invokevirtual Method(java/io/PrintStream.println:(Ljava/lang/String;)V)
    0211 bipush 10
    0213 istore 26
    0215 iload 26
    0217 istore 27
    0219 bipush 20
    0221 istore 28
    0223 iload 28
    0225 istore 29
    0227 ldc "Sum: "
    0229 astore 30
    0231 iload 27
    0233 istore 31
    0235 iload 29
    0237 istore 32
    0239 iload 31
    0241 iload 32
    0243 iadd
    0244 istore 33
    0246 ldc ", Product: "
    0248 astore 34
    0250 iload 27
    0252 istore 35
    0254 iload 29
    0256 istore 36
    0258 iload 35
    0260 iload 36
    0262 imul
    0263 istore 37
    0265 getstatic Field(java/lang/System.out:Ljava/io/PrintStream;)
    0268 new Class(java/lang/StringBuilder)
    0271 dup
    0272 invokespecial Method(java/lang/StringBuilder.<init>:()V)
    0275 aload 30
    0277 invokevirtual Method(java/lang/StringBuilder.append:(Ljava/lang/String;)Ljava/lang/StringBuilder;)
    0280 iload 33
    0282 invokevirtual Method(java/lang/StringBuilder.append:(I)Ljava/lang/StringBuilder;)
    0285 aload 34
    0287 invokevirtual Method(java/lang/StringBuilder.append:(Ljava/lang/String;)Ljava/lang/StringBuilder;)
    0290 iload 37
    0292 invokevirtual Method(java/lang/StringBuilder.append:(I)Ljava/lang/StringBuilder;)
    0295 invokevirtual Method(java/lang/StringBuilder.toString:()Ljava/lang/String;)
    0298 invokevirtual Method(java/io/PrintStream.println:(Ljava/lang/String;)V)
    0301 ldc "Items: "
    0303 astore 38
    0305 ldc ", "
    0307 astore 39
    0309 aload 19
    0311 checkcast Class(java/util/List)
    0314 astore 40
    0316 ldc ", "
    0318 astore 41
    0320 aconst_null
    0321 astore 42
    0323 aconst_null
    0324 astore 43
    0326 iconst_0
    0327 istore 44
    0329 aconst_null
    0330 astore 45
    0332 aconst_null
    0333 astore 46
    0335 bipush 62
    0337 istore 47
    0339 aconst_null
    0340 astore 48
    0342 aload 40
    0344 aload 41
    0346 aload 42
    0348 aload 43
    0350 iload 44
    0352 aload 45
    0354 aload 46
    0356 iload 47
    0358 aload 48
    0360 invokestatic Method(kotlin/collections/CollectionsKt.joinToString$default:(Ljava/lang/Iterable;Ljava/lang/CharSequence;Ljava/lang/CharSequence;Ljava/lang/CharSequence;ILjava/lang/CharSequence;Lkotlin/jvm/functions/Function1;ILjava/lang/Object;)Ljava/lang/String;)
    0363 astore 49
    0365 getstatic Field(java/lang/System.out:Ljava/io/PrintStream;)
    0368 new Class(java/lang/StringBuilder)
    0371 dup
    0372 invokespecial Method(java/lang/StringBuilder.<init>:()V)
    0375 aload 38
    0377 invokevirtual Method(java/lang/StringBuilder.append:(Ljava/lang/String;)Ljava/lang/StringBuilder;)
    0380 aload 49
    0382 invokevirtual Method(java/lang/StringBuilder.append:(Ljava/lang/Object;)Ljava/lang/StringBuilder;)
    0385 invokevirtual Method(java/lang/StringBuilder.toString:()Ljava/lang/String;)
    0388 invokevirtual Method(java/io/PrintStream.println:(Ljava/lang/String;)V)
    0391 ldc "Reversed: "
    0393 astore 50
    0395 aload 19
    0397 checkcast Class(java/util/List)
    0400 astore 51
    0402 aload 51
    0404 invokestatic Method(kotlin/collections/CollectionsKt.reversed:(Ljava/lang/Iterable;)Ljava/util/List;)
    0407 astore 52
    0409 getstatic Field(java/lang/System.out:Ljava/io/PrintStream;)
    0412 new Class(java/lang/StringBuilder)
    0415 dup
    0416 invokespecial Method(java/lang/StringBuilder.<init>:()V)
    0419 aload 50
    0421 invokevirtual Method(java/lang/StringBuilder.append:(Ljava/lang/String;)Ljava/lang/StringBuilder;)
    0424 aload 52
    0426 invokevirtual Method(java/lang/StringBuilder.append:(Ljava/lang/Object;)Ljava/lang/StringBuilder;)
    0429 invokevirtual Method(java/lang/StringBuilder.toString:()Ljava/lang/String;)
    0432 invokevirtual Method(java/io/PrintStream.println:(Ljava/lang/String;)V)
    0435 ldc "First three: "
    0437 astore 53
    0439 iconst_3
    0440 istore 54
    0442 aload 19
    0444 checkcast Class(java/util/List)
    0447 astore 55
    0449 iconst_3
    0450 istore 56
    0452 aload 55
    0454 iload 56
    0456 invokestatic Method(kotlin/collections/CollectionsKt.take:(Ljava/lang/Iterable;I)Ljava/util/List;)
    0459 astore 57
    0461 getstatic Field(java/lang/System.out:Ljava/io/PrintStream;)
    0464 new Class(java/lang/StringBuilder)
    0467 dup
    0468 invokespecial Method(java/lang/StringBuilder.<init>:()V)
    0471 aload 53
    0473 invokevirtual Method(java/lang/StringBuilder.append:(Ljava/lang/String;)Ljava/lang/StringBuilder;)
    0476 aload 57
    0478 invokevirtual Method(java/lang/StringBuilder.append:(Ljava/lang/Object;)Ljava/lang/StringBuilder;)
    0481 invokevirtual Method(java/lang/StringBuilder.toString:()Ljava/lang/String;)
    0484 invokevirtual Method(java/io/PrintStream.println:(Ljava/lang/String;)V)
    0487 return
