class_version major=61 minor=0
this_class    InputKt
super_class   java/lang/Object
access_flags  0x0031
method        main ()V 0x0019
  code        max_stack=4 max_locals=0
    0000 aconst_null
    0001 new Class(InputKt$main$1)
    0004 dup
    0005 aconst_null
    0006 invokespecial Method(InputKt$main$1.<init>:(Lkotlin/coroutines/Continuation;)V)
    0009 checkcast Class(kotlin/jvm/functions/Function2)
    0012 iconst_1
    0013 aconst_null
    0014 invokestatic Method(kotlinx/coroutines/BuildersKt.runBlocking$default:(Lkotlin/coroutines/CoroutineContext;Lkotlin/jvm/functions/Function2;ILjava/lang/Object;)Ljava/lang/Object;)
    0017 pop
    0018 return
method        main ([Ljava/lang/String;)V 0x1009
  code        max_stack=0 max_locals=1
    0000 invokestatic Method(InputKt.main:()V)
    0003 return
method        sumWithScope (Lkotlin/coroutines/Continuation;)Ljava/lang/Object; 0x0019
  code        max_stack=3 max_locals=1
    0000 new Class(InputKt$sumWithScope$2)
    0003 dup
    0004 aconst_null
    0005 invokespecial Method(InputKt$sumWithScope$2.<init>:(Lkotlin/coroutines/Continuation;)V)
    0008 checkcast Class(kotlin/jvm/functions/Function2)
    0011 aload_0
    0012 invokestatic Method(kotlinx/coroutines/CoroutineScopeKt.coroutineScope:(Lkotlin/jvm/functions/Function2;Lkotlin/coroutines/Continuation;)Ljava/lang/Object;)
    0015 areturn
  attr        Signature (2 bytes)
  attr        RuntimeInvisibleAnnotations (6 bytes)
  attr        RuntimeInvisibleParameterAnnotations (7 bytes)
class_attr    InnerClasses (18 bytes)
