class_version major=61 minor=0
this_class    InputKt
super_class   java/lang/Object
access_flags  0x0031
method        binarySearch (II)I 0x0009
  code        max_stack=4 max_locals=33
    0000 iconst_0
    0001 istore 2
    0003 iload 2
    0005 istore 3
    0007 iload 1
    0009 istore 4
    0011 iconst_1
    0012 istore 5
    0014 iload 4
    0016 iload 5
    0018 isub
    0019 istore 6
    0021 iload 6
    0023 istore 7
    0025 op_0xA7
    0026 nop
    0027 iconst_0
    0028 iload 3
    0030 istore 8
    0032 iload 7
    0034 istore 9
    0036 iload 8
    0038 iload 9
    0040 op_0xA4
    0041 nop
    0042 iconst_4
    0043 iconst_0
    0044 op_0xA7
    0045 nop
    0046 iconst_1
    0047 iconst_1
    0048 istore 10
    0050 iload 10
    0052 op_0x99
    0053 nop
    0054 op_0x41
    0055 iload 3
    0057 istore 11
    0059 iload 7
    0061 istore 12
    0063 iload 11
    0065 iload 12
    0067 iadd
    0068 istore 13
    0070 iconst_2
    0071 istore 14
    0073 iload 13
    0075 iload 14
    0077 idiv
    0078 istore 15
    0080 iload 15
    0082 istore 16
    0084 iload 16
    0086 istore 17
    0088 iload 0
    0090 istore 18
    0092 iload 17
    0094 iload 18
    0096 op_0x9F
    0097 nop
    0098 iconst_4
    0099 iconst_0
    0100 op_0xA7
    0101 nop
    0102 iconst_1
    0103 iconst_1
    0104 istore 19
    0106 iconst_0
    0107 istore 20
    0109 iload 19
    0111 op_0x99
    0112 nop
    0113 ldc_w #42752
    0116 op_0x09
    0117 iconst_m1
    0118 istore 21
    0120 iload 21
    0122 op_0xAC
    0123 iload 16
    0125 istore 22
    0127 iload 22
    0129 op_0xAC
    0130 op_0xA7
    0131 nop
    0132 iconst_0
    0133 iload 16
    0135 istore 23
    0137 iload 0
    0139 istore 24
    0141 iload 23
    0143 iload 24
    0145 op_0xA1
    0146 nop
    0147 iconst_4
    0148 iconst_0
    0149 op_0xA7
    0150 nop
    0151 iconst_1
    0152 iconst_1
    0153 istore 25
    0155 iconst_0
    0156 istore 26
    0158 iload 25
    0160 op_0x99
    0161 nop
    0162 op_0x18
    0163 iload 16
    0165 istore 27
    0167 iconst_1
    0168 istore 28
    0170 iload 27
    0172 iload 28
    0174 iadd
    0175 istore 29
    0177 iload 29
    0179 istore 3
    0181 op_0xA7
    0182 nop
    0183 op_0x18
    0184 iload 16
    0186 istore 30
    0188 iconst_1
    0189 istore 31
    0191 iload 30
    0193 iload 31
    0195 isub
    0196 istore 32
    0198 iload 32
    0200 istore 7
    0202 op_0xA7
    0203 nop
    0204 iconst_0
    0205 op_0xA7
    0206 op_0xFF
    0207 op_0x4F
    sub_attr  StackMapTable (340 bytes)
method        main ([Ljava/lang/String;)V 0x0009
  code        max_stack=2 max_locals=13
    0000 bipush 7
    0002 istore 1
    0004 bipush 20
    0006 istore 2
    0008 iload 1
    0010 iload 2
    0012 invokestatic Method(InputKt.binarySearch:(II)I)
    0015 istore 3
    0017 getstatic Field(java/lang/System.out:Ljava/io/PrintStream;)
    0020 iload 3
    0022 invokevirtual Method(java/io/PrintStream.println:(I)V)
    0025 iconst_0
    0026 istore 4
    0028 bipush 20
    0030 istore 5
    0032 iload 4
    0034 iload 5
    0036 invokestatic Method(InputKt.binarySearch:(II)I)
    0039 istore 6
    0041 getstatic Field(java/lang/System.out:Ljava/io/PrintStream;)
    0044 iload 6
    0046 invokevirtual Method(java/io/PrintStream.println:(I)V)
    0049 bipush 19
    0051 istore 7
    0053 bipush 20
    0055 istore 8
    0057 iload 7
    0059 iload 8
    0061 invokestatic Method(InputKt.binarySearch:(II)I)
    0064 istore 9
    0066 getstatic Field(java/lang/System.out:Ljava/io/PrintStream;)
    0069 iload 9
    0071 invokevirtual Method(java/io/PrintStream.println:(I)V)
    0074 bipush 25
    0076 istore 10
    0078 bipush 20
    0080 istore 11
    0082 iload 10
    0084 iload 11
    0086 invokestatic Method(InputKt.binarySearch:(II)I)
    0089 istore 12
    0091 getstatic Field(java/lang/System.out:Ljava/io/PrintStream;)
    0094 iload 12
    0096 invokevirtual Method(java/io/PrintStream.println:(I)V)
    0099 return
