class_version major=61 minor=0
this_class    InputKt
super_class   java/lang/Object
access_flags  0x0031
method        eval (LExpr;)I 0x0019
  code        max_stack=2 max_locals=18
    0000 aload_0
    0001 checkcast Class(Expr)
    0004 astore_1
    0005 goto 8
    0008 aload_0
    0009 checkcast Class(Expr)
    0012 astore_2
    0013 aload_2
    0014 instanceof Class(Num)
    0017 istore_3
    0018 iload_3
    0019 ifeq 49
    0022 aload_0
    0023 checkcast Class(Num)
    0026 astore 4
    0028 aload 4
    0030 checkcast Class(Num)
    0033 astore 5
    0035 aload 5
    0037 getfield Field(Num.value:I)
    0040 istore 6
    0042 iload 6
    0044 istore 7
    0046 goto 135
    0049 aload_0
    0050 checkcast Class(Expr)
    0053 astore 8
    0055 aload 8
    0057 instanceof Class(Sum)
    0060 istore 9
    0062 iload 9
    0064 ifeq 129
    0067 aload_0
    0068 checkcast Class(Sum)
    0071 astore 10
    0073 aload 10
    0075 checkcast Class(Sum)
    0078 astore 11
    0080 aload 11
    0082 getfield Field(Sum.left:LExpr;)
    0085 astore 12
    0087 aload 12
    0089 invokestatic Method(InputKt.eval:(LExpr;)I)
    0092 istore 13
    0094 aload 10
    0096 checkcast Class(Sum)
    0099 astore 14
    0101 aload 14
    0103 getfield Field(Sum.right:LExpr;)
    0106 astore 15
    0108 aload 15
    0110 invokestatic Method(InputKt.eval:(LExpr;)I)
    0113 istore 16
    0115 iload 13
    0117 iload 16
    0119 iadd
    0120 istore 17
    0122 iload 17
    0124 istore 7
    0126 goto 135
    0129 iconst_0
    0130 istore 7
    0132 goto 135
    0135 iload 7
    0137 op_0xAC
    sub_attr  StackMapTable (77 bytes)
method        main ()V 0x0019
  code        max_stack=4 max_locals=11
    0000 iconst_1
    0001 istore_0
    0002 new Class(Num)
    0005 dup
    0006 iload_0
    0007 invokespecial Method(Num.<init>:(I)V)
    0010 astore_1
    0011 iconst_2
    0012 istore_2
    0013 new Class(Num)
    0016 dup
    0017 iload_2
    0018 invokespecial Method(Num.<init>:(I)V)
    0021 astore_3
    0022 iconst_3
    0023 istore 4
    0025 new Class(Num)
    0028 dup
    0029 iload 4
    0031 invokespecial Method(Num.<init>:(I)V)
    0034 astore 5
    0036 new Class(Sum)
    0039 dup
    0040 aload_3
    0041 aload 5
    0043 invokespecial Method(Sum.<init>:(LExpr;LExpr;)V)
    0046 astore 6
    0048 new Class(Sum)
    0051 dup
    0052 aload_1
    0053 aload 6
    0055 invokespecial Method(Sum.<init>:(LExpr;LExpr;)V)
    0058 checkcast Class(Sum)
    0061 checkcast Class(Sum)
    0064 invokestatic Method(InputKt.eval:(LExpr;)I)
    0067 istore 10
    0069 getstatic Field(java/lang/System.out:Ljava/io/PrintStream;)
    0072 iload 10
    0074 invokevirtual Method(java/io/PrintStream.println:(I)V)
    0077 return
method        main ([Ljava/lang/String;)V 0x1009
  code        max_stack=0 max_locals=1
    0000 invokestatic Method(InputKt.main:()V)
    0003 return
