class_version major=61 minor=0
this_class    InputKt
super_class   java/lang/Object
access_flags  0x0031
method        main ()V 0x0019
  code        max_stack=2 max_locals=3
    0000 new Class(kotlin/jvm/internal/Ref$IntRef)
    0003 dup
    0004 invokespecial Method(kotlin/jvm/internal/Ref$IntRef.<init>:()V)
    0007 astore_0
    0008 aload_0
    0009 op_0xBA
    0010 nop
    0011 op_0x1F
    0012 nop
    0013 nop
    0014 astore_1
    0015 aload_1
    0016 invokeinterface InterfaceMethod(kotlin/jvm/functions/Function0.invoke:()Ljava/lang/Object;)
    0021 pop
    0022 aload_1
    0023 invokeinterface InterfaceMethod(kotlin/jvm/functions/Function0.invoke:()Ljava/lang/Object;)
    0028 pop
    0029 aload_1
    0030 invokeinterface InterfaceMethod(kotlin/jvm/functions/Function0.invoke:()Ljava/lang/Object;)
    0035 pop
    0036 aload_0
    0037 getfield Field(kotlin/jvm/internal/Ref$IntRef.element:I)
    0040 istore_2
    0041 getstatic Field(java/lang/System.out:Ljava/io/PrintStream;)
    0044 iload_2
    0045 invokevirtual Method(java/io/PrintStream.println:(I)V)
    0048 return
method        main ([Ljava/lang/String;)V 0x1009
  code        max_stack=0 max_locals=1
    0000 invokestatic Method(InputKt.main:()V)
    0003 return
method        main$lambda$0 (Lkotlin/jvm/internal/Ref$IntRef;)Lkotlin/Unit; 0x001A
  code        max_stack=3 max_locals=1
    0000 aload_0
    0001 aload_0
    0002 getfield Field(kotlin/jvm/internal/Ref$IntRef.element:I)
    0005 iconst_1
    0006 iadd
    0007 putfield Field(kotlin/jvm/internal/Ref$IntRef.element:I)
    0010 getstatic Field(kotlin/Unit.INSTANCE:Lkotlin/Unit;)
    0013 areturn
class_attr    InnerClasses (10 bytes)
class_attr    BootstrapMethods (12 bytes)
