class_version major=61 minor=0
this_class    InputKt
super_class   java/lang/Object
access_flags  0x0031
method        starts (Ljava/lang/String;Lkotlin/coroutines/Continuation;)Ljava/lang/Object; 0x0019
  code        max_stack=5 max_locals=2
    0000 aload_0
    0001 ldc ""
    0003 iconst_0
    0004 iconst_2
    0005 aconst_null
    0006 invokestatic Method(kotlin/text/StringsKt.startsWith$default:(Ljava/lang/String;Ljava/lang/String;ZILjava/lang/Object;)Z)
    0009 invokestatic Method(kotlin/coroutines/jvm/internal/Boxing.boxBoolean:(Z)Ljava/lang/Boolean;)
    0012 areturn
  attr        Signature (2 bytes)
  attr        RuntimeInvisibleAnnotations (6 bytes)
  attr        RuntimeInvisibleParameterAnnotations (13 bytes)
