class_version major=61 minor=0
this_class    InputKt
super_class   java/lang/Object
access_flags  0x0031
method        main ([Ljava/lang/String;)V 0x0009
  code        max_stack=4 max_locals=27
    0000 iconst_1
    0001 istore 1
    0003 ldc "one"
    0005 astore 2
    0007 iload 1
    0009 invokestatic Method(java/lang/Integer.valueOf:(I)Ljava/lang/Integer;)
    0012 astore 3
    0014 op_0xBB
    0015 nop
    0016 ldc_w #22809
    0019 iconst_0
    0020 aload 2
    0022 invokespecial Method(kotlin/Pair.<init>:(Ljava/lang/Object;Ljava/lang/Object;)V)
    0025 astore 4
    0027 iconst_2
    0028 istore 5
    0030 ldc "two"
    0032 astore 6
    0034 iload 5
    0036 invokestatic Method(java/lang/Integer.valueOf:(I)Ljava/lang/Integer;)
    0039 astore 7
    0041 op_0xBB
    0042 nop
    0043 ldc_w #22809
    0046 iconst_4
    0047 aload 6
    0049 invokespecial Method(kotlin/Pair.<init>:(Ljava/lang/Object;Ljava/lang/Object;)V)
    0052 astore 8
    0054 iconst_3
    0055 istore 9
    0057 ldc "three"
    0059 astore 10
    0061 iload 9
    0063 invokestatic Method(java/lang/Integer.valueOf:(I)Ljava/lang/Integer;)
    0066 astore 11
    0068 op_0xBB
    0069 nop
    0070 ldc_w #22809
    0073 op_0x0B
    0074 aload 10
    0076 invokespecial Method(kotlin/Pair.<init>:(Ljava/lang/Object;Ljava/lang/Object;)V)
    0079 astore 12
    0081 iconst_3
    0082 istore 13
    0084 iload 13
    0086 op_0xBD
    0087 nop
    0088 ldc_w #14862
    0091 iconst_0
    0092 istore 15
    0094 aload 14
    0096 iload 15
    0098 aload 4
    0100 op_0x53
    0101 iconst_1
    0102 istore 16
    0104 aload 14
    0106 iload 16
    0108 aload 8
    0110 op_0x53
    0111 iconst_2
    0112 istore 17
    0114 aload 14
    0116 iload 17
    0118 aload 12
    0120 op_0x53
    0121 aload 14
    0123 invokestatic Method(kotlin/collections/MapsKt.mapOf:([Lkotlin/Pair;)Ljava/util/Map;)
    0126 astore 18
    0128 aload 18
    0130 op_0xC0
    0131 nop
    0132 op_0x23
    0133 astore 19
    0135 aload 19
    0137 op_0xC0
    0138 nop
    0139 op_0x23
    0140 astore 20
    0142 getstatic Field(java/lang/System.out:Ljava/io/PrintStream;)
    0145 aload 20
    0147 invokevirtual Method(java/io/PrintStream.println:(Ljava/lang/Object;)V)
    0150 aload 19
    0152 op_0xC0
    0153 nop
    0154 op_0x23
    0155 astore 21
    0157 iconst_2
    0158 istore 22
    0160 iload 22
    0162 invokestatic Method(java/lang/Integer.valueOf:(I)Ljava/lang/Integer;)
    0165 astore 23
    0167 aload 21
    0169 aload 23
    0171 op_0xB9
    0172 nop
    0173 op_0x33
    0174 iconst_m1
    0175 nop
    0176 astore 24
    0178 getstatic Field(java/lang/System.out:Ljava/io/PrintStream;)
    0181 aload 24
    0183 invokevirtual Method(java/io/PrintStream.println:(Ljava/lang/Object;)V)
    0186 aload 19
    0188 op_0xC0
    0189 nop
    0190 op_0x23
    0191 astore 25
    0193 aload 25
    0195 op_0xB9
    0196 nop
    0197 op_0x37
    0198 aconst_null
    0199 nop
    0200 istore 26
    0202 getstatic Field(java/lang/System.out:Ljava/io/PrintStream;)
    0205 iload 26
    0207 invokevirtual Method(java/io/PrintStream.println:(I)V)
    0210 return
