class_version major=61 minor=0
this_class    InputKt
super_class   java/lang/Object
access_flags  0x0031
method        fail (Ljava/lang/String;)Ljava/lang/Void; 0x0019
  code        max_stack=3 max_locals=1
    0000 aload_0
    0001 ldc "msg"
    0003 invokestatic Method(kotlin/jvm/internal/Intrinsics.checkNotNullParameter:(Ljava/lang/Object;Ljava/lang/String;)V)
    0006 new Class(java/lang/IllegalStateException)
    0009 dup
    0010 aload_0
    0011 invokespecial Method(java/lang/IllegalStateException.<init>:(Ljava/lang/String;)V)
    0014 athrow
  attr        RuntimeInvisibleAnnotations (6 bytes)
  attr        RuntimeInvisibleParameterAnnotations (7 bytes)
method        main ()V 0x0019
  code        max_stack=2 max_locals=1
    0000 nop
    0001 ldc "test error"
    0003 invokestatic Method(InputKt.fail:(Ljava/lang/String;)Ljava/lang/Void;)
    0006 pop
    0007 new Class(kotlin/KotlinNothingValueException)
    0010 dup
    0011 invokespecial Method(kotlin/KotlinNothingValueException.<init>:()V)
    0014 athrow
    0015 astore_0
    0016 aload_0
    0017 invokevirtual Method(java/lang/IllegalStateException.getMessage:()Ljava/lang/String;)
    0020 op_0xBA
    0021 nop
    0022 op_0x30
    0023 nop
    0024 nop
    0025 getstatic Field(java/lang/System.out:Ljava/io/PrintStream;)
    0028 op_0x5F
    0029 invokevirtual Method(java/io/PrintStream.println:(Ljava/lang/Object;)V)
    0032 return
    sub_attr  StackMapTable (6 bytes)
method        main ([Ljava/lang/String;)V 0x1009
  code        max_stack=0 max_locals=1
    0000 invokestatic Method(InputKt.main:()V)
    0003 return
class_attr    BootstrapMethods (8 bytes)
