class_version major=61 minor=0
this_class    InputKt
super_class   java/lang/Object
access_flags  0x0031
method        main ()V 0x0019
  code        max_stack=3 max_locals=1
    0000 new Class(G)
    0003 dup
    0004 invokespecial Method(G.<init>:()V)
    0007 astore_0
    0008 aload_0
    0009 ldc "A"
    0011 ldc "B"
    0013 invokevirtual Method(G.add:(Ljava/lang/String;Ljava/lang/String;)V)
    0016 aload_0
    0017 ldc "A"
    0019 ldc "C"
    0021 invokevirtual Method(G.add:(Ljava/lang/String;Ljava/lang/String;)V)
    0024 aload_0
    0025 ldc "A"
    0027 ldc "D"
    0029 invokevirtual Method(G.add:(Ljava/lang/String;Ljava/lang/String;)V)
    0032 aload_0
    0033 ldc "A"
    0035 invokevirtual Method(G.size:(Ljava/lang/String;)I)
    0038 invokedynamic InvokeDynamic(makeConcatWithConstants:(I)Ljava/lang/String;)
    0043 getstatic Field(java/lang/System.out:Ljava/io/PrintStream;)
    0046 swap
    0047 invokevirtual Method(java/io/PrintStream.println:(Ljava/lang/Object;)V)
    0050 aload_0
    0051 ldc "B"
    0053 invokevirtual Method(G.size:(Ljava/lang/String;)I)
    0056 invokedynamic InvokeDynamic(makeConcatWithConstants:(I)Ljava/lang/String;)
    0061 getstatic Field(java/lang/System.out:Ljava/io/PrintStream;)
    0064 swap
    0065 invokevirtual Method(java/io/PrintStream.println:(Ljava/lang/Object;)V)
    0068 return
method        main ([Ljava/lang/String;)V 0x1009
  code        max_stack=0 max_locals=1
    0000 invokestatic Method(InputKt.main:()V)
    0003 return
class_attr    BootstrapMethods (14 bytes)
