class_version major=61 minor=0
this_class    InputKt
super_class   java/lang/Object
access_flags  0x0031
method        describe (Ljava/lang/Object;)Ljava/lang/String; 0x0009
  code        max_stack=3 max_locals=20
    0000 aload 0
    0002 astore 1
    0004 aload 1
    0006 instanceof Class(java/lang/String)
    0009 istore 2
    0011 iconst_0
    0012 istore 3
    0014 iload 2
    0016 ifeq 61
    0019 aload 0
    0021 checkcast Class(java/lang/String)
    0024 astore 4
    0026 aload 4
    0028 astore 5
    0030 aload 5
    0032 invokevirtual Method(java/lang/String.length:()I)
    0035 istore 6
    0037 iconst_3
    0038 istore 7
    0040 iload 6
    0042 iload 7
    0044 op_0xA3
    0045 nop
    0046 iconst_4
    0047 iconst_0
    0048 goto 52
    0051 iconst_1
    0052 istore 8
    0054 iload 8
    0056 istore 3
    0058 goto 61
    0061 iload 3
    0063 ifeq 93
    0066 aload 0
    0068 checkcast Class(java/lang/String)
    0071 astore 9
    0073 ldc "long string: "
    0075 astore 10
    0077 aload 9
    0079 astore 11
    0081 aload 10
    0083 aload 11
    0085 invokevirtual Method(java/lang/String.concat:(Ljava/lang/String;)Ljava/lang/String;)
    0088 astore 12
    0090 aload 12
    0092 areturn
    0093 goto 96
    0096 aload 0
    0098 astore 13
    0100 aload 13
    0102 instanceof Class(java/lang/Integer)
    0105 istore 14
    0107 iload 14
    0109 ifeq 145
    0112 aload 0
    0114 checkcast Class(java/lang/Integer)
    0117 invokevirtual Method(java/lang/Integer.intValue:()I)
    0120 istore 15
    0122 ldc "integer: "
    0124 astore 16
    0126 iload 15
    0128 istore 17
    0130 aload 16
    0132 iload 17
    0134 invokestatic Method(java/lang/String.valueOf:(I)Ljava/lang/String;)
    0137 invokevirtual Method(java/lang/String.concat:(Ljava/lang/String;)Ljava/lang/String;)
    0140 astore 18
    0142 aload 18
    0144 areturn
    0145 goto 148
    0148 ldc "other"
    0150 astore 19
    0152 aload 19
    0154 areturn
    sub_attr  StackMapTable (150 bytes)
method        main ([Ljava/lang/String;)V 0x0009
  code        max_stack=2 max_locals=11
    0000 ldc "hello"
    0002 astore 1
    0004 aload 1
    0006 invokestatic Method(InputKt.describe:(Ljava/lang/Object;)Ljava/lang/String;)
    0009 astore 2
    0011 getstatic Field(java/lang/System.out:Ljava/io/PrintStream;)
    0014 aload 2
    0016 invokevirtual Method(java/io/PrintStream.println:(Ljava/lang/String;)V)
    0019 ldc "hi"
    0021 astore 3
    0023 aload 3
    0025 invokestatic Method(InputKt.describe:(Ljava/lang/Object;)Ljava/lang/String;)
    0028 astore 4
    0030 getstatic Field(java/lang/System.out:Ljava/io/PrintStream;)
    0033 aload 4
    0035 invokevirtual Method(java/io/PrintStream.println:(Ljava/lang/String;)V)
    0038 bipush 42
    0040 istore 5
    0042 iload 5
    0044 invokestatic Method(java/lang/Integer.valueOf:(I)Ljava/lang/Integer;)
    0047 astore 6
    0049 aload 6
    0051 invokestatic Method(InputKt.describe:(Ljava/lang/Object;)Ljava/lang/String;)
    0054 astore 7
    0056 getstatic Field(java/lang/System.out:Ljava/io/PrintStream;)
    0059 aload 7
    0061 invokevirtual Method(java/io/PrintStream.println:(Ljava/lang/String;)V)
    0064 iconst_1
    0065 istore 8
    0067 iload 8
    0069 invokestatic Method(java/lang/Boolean.valueOf:(Z)Ljava/lang/Boolean;)
    0072 astore 9
    0074 aload 9
    0076 invokestatic Method(InputKt.describe:(Ljava/lang/Object;)Ljava/lang/String;)
    0079 astore 10
    0081 getstatic Field(java/lang/System.out:Ljava/io/PrintStream;)
    0084 aload 10
    0086 invokevirtual Method(java/io/PrintStream.println:(Ljava/lang/String;)V)
    0089 return
