class_version major=61 minor=0
this_class    InputKt
super_class   java/lang/Object
access_flags  0x0031
method        describe (Ljava/lang/Object;)Ljava/lang/String; 0x0019
  code        max_stack=2 max_locals=12
    0000 aload_0
    0001 ldc "value"
    0003 invokestatic Method(kotlin/jvm/internal/Intrinsics.checkNotNullParameter:(Ljava/lang/Object;Ljava/lang/String;)V)
    0006 aload_0
    0007 instanceof Class(java/lang/String)
    0010 istore_1
    0011 iconst_0
    0012 istore_2
    0013 iload_1
<<<<<<< Updated upstream
    0014 ifeq 44
=======
    0014 ifeq 48
>>>>>>> Stashed changes
    0017 aload_0
    0018 checkcast Class(java/lang/String)
    0021 astore_3
    0022 aload_3
    0023 invokevirtual Method(java/lang/String.length:()I)
    0026 istore 4
<<<<<<< Updated upstream
    0028 iload 4
    0030 iconst_3
    0031 if_icmple 38
    0034 iconst_1
    0035 goto 39
    0038 iconst_0
    0039 istore 5
    0041 iload 5
    0043 istore_2
    0044 iload_2
    0045 ifeq 66
    0048 aload_0
    0049 checkcast Class(java/lang/String)
    0052 astore 6
    0054 aload 6
    0056 op_0xBA
    0057 nop
    0058 lload_3
    0059 nop
    0060 nop
    0061 astore 7
    0063 aload 7
    0065 areturn
    0066 aload_0
    0067 instanceof Class(java/lang/Integer)
    0070 istore 8
    0072 iload 8
    0074 ifeq 98
    0077 aload_0
    0078 checkcast Class(java/lang/Integer)
    0081 invokevirtual Method(java/lang/Integer.intValue:()I)
    0084 istore 9
    0086 iload 9
    0088 op_0xBA
    0089 nop
    0090 aload_1
    0091 nop
    0092 nop
    0093 astore 10
    0095 aload 10
    0097 areturn
    0098 ldc "other"
    0100 astore 11
    0102 aload 11
    0104 areturn
    sub_attr  StackMapTable (40 bytes)
=======
    0028 iconst_3
    0029 istore 5
    0031 iload 4
    0033 iload 5
    0035 if_icmple 42
    0038 iconst_1
    0039 goto 43
    0042 iconst_0
    0043 istore 6
    0045 iload 6
    0047 istore_2
    0048 iload_2
    0049 ifeq 70
    0052 aload_0
    0053 checkcast Class(java/lang/String)
    0056 astore 7
    0058 aload 7
    0060 op_0xBA
    0061 nop
    0062 lload_3
    0063 nop
    0064 nop
    0065 astore 8
    0067 aload 8
    0069 areturn
    0070 aload_0
    0071 instanceof Class(java/lang/Integer)
    0074 istore 9
    0076 iload 9
    0078 ifeq 102
    0081 aload_0
    0082 checkcast Class(java/lang/Integer)
    0085 invokevirtual Method(java/lang/Integer.intValue:()I)
    0088 istore 10
    0090 iload 10
    0092 op_0xBA
    0093 nop
    0094 aload_1
    0095 nop
    0096 nop
    0097 astore 11
    0099 aload 11
    0101 areturn
    0102 ldc "other"
    0104 astore 12
    0106 aload 12
    0108 areturn
    sub_attr  StackMapTable (42 bytes)
>>>>>>> Stashed changes
  attr        RuntimeInvisibleAnnotations (6 bytes)
  attr        RuntimeInvisibleParameterAnnotations (7 bytes)
method        main ()V 0x0019
  code        max_stack=2 max_locals=0
    0000 ldc "hello"
    0002 invokestatic Method(InputKt.describe:(Ljava/lang/Object;)Ljava/lang/String;)
    0005 getstatic Field(java/lang/System.out:Ljava/io/PrintStream;)
    0008 swap
    0009 invokevirtual Method(java/io/PrintStream.println:(Ljava/lang/Object;)V)
    0012 ldc "hi"
    0014 invokestatic Method(InputKt.describe:(Ljava/lang/Object;)Ljava/lang/String;)
    0017 getstatic Field(java/lang/System.out:Ljava/io/PrintStream;)
    0020 swap
    0021 invokevirtual Method(java/io/PrintStream.println:(Ljava/lang/Object;)V)
    0024 bipush 42
    0026 invokestatic Method(java/lang/Integer.valueOf:(I)Ljava/lang/Integer;)
    0029 invokestatic Method(InputKt.describe:(Ljava/lang/Object;)Ljava/lang/String;)
    0032 getstatic Field(java/lang/System.out:Ljava/io/PrintStream;)
    0035 swap
    0036 invokevirtual Method(java/io/PrintStream.println:(Ljava/lang/Object;)V)
    0039 iconst_1
    0040 invokestatic Method(java/lang/Boolean.valueOf:(Z)Ljava/lang/Boolean;)
    0043 invokestatic Method(InputKt.describe:(Ljava/lang/Object;)Ljava/lang/String;)
    0046 getstatic Field(java/lang/System.out:Ljava/io/PrintStream;)
    0049 swap
    0050 invokevirtual Method(java/io/PrintStream.println:(Ljava/lang/Object;)V)
    0053 return
method        main ([Ljava/lang/String;)V 0x1009
  code        max_stack=0 max_locals=1
    0000 invokestatic Method(InputKt.main:()V)
    0003 return
class_attr    BootstrapMethods (14 bytes)
