class_version major=61 minor=0
this_class    InputKt
super_class   java/lang/Object
access_flags  0x0031
method        greet (Ljava/lang/String;Lkotlin/coroutines/Continuation;)Ljava/lang/Object; 0x0019
  code        max_stack=1 max_locals=2
    0000 aload_0
    0001 areturn
  attr        Signature (2 bytes)
  attr        RuntimeInvisibleAnnotations (6 bytes)
  attr        RuntimeInvisibleParameterAnnotations (13 bytes)
method        greet$default (Ljava/lang/String;Lkotlin/coroutines/Continuation;ILjava/lang/Object;)Ljava/lang/Object; 0x1009
  code        max_stack=2 max_locals=4
    0000 iload_2
    0001 iconst_1
    0002 iand
    0003 ifeq 9
    0006 ldc "World"
    0008 astore_0
    0009 aload_0
    0010 aload_1
    0011 invokestatic Method(InputKt.greet:(Ljava/lang/String;Lkotlin/coroutines/Continuation;)Ljava/lang/Object;)
    0014 areturn
    sub_attr  StackMapTable (3 bytes)
