class_version major=61 minor=0
this_class    InputKt
super_class   java/lang/Object
access_flags  0x0031
method        main ()V 0x0019
  code        max_stack=4 max_locals=2
    0000 new Class(kotlin/ranges/IntRange)
    0003 dup
    0004 iconst_1
    0005 bipush 10
    0007 invokespecial Method(kotlin/ranges/IntRange.<init>:(II)V)
    0010 astore_0
    0011 aload_0
    0012 invokevirtual Method(kotlin/ranges/IntRange.getFirst:()I)
    0015 istore_1
    0016 iconst_5
    0017 aload_0
    0018 invokevirtual Method(kotlin/ranges/IntRange.getLast:()I)
    0021 op_0xA3
    0022 nop
    0023 bipush 27
    0025 iconst_5
    0026 op_0xA3
    0027 nop
    0028 iconst_4
    0029 iconst_1
    0030 goto 38
    0033 iconst_0
    0034 goto 38
    0037 iconst_0
    0038 istore_1
    0039 getstatic Field(java/lang/System.out:Ljava/io/PrintStream;)
    0042 iload_1
    0043 invokevirtual Method(java/io/PrintStream.println:(Z)V)
    0046 aload_0
    0047 invokevirtual Method(kotlin/ranges/IntRange.getFirst:()I)
    0050 istore_1
    0051 bipush 11
    0053 aload_0
    0054 invokevirtual Method(kotlin/ranges/IntRange.getLast:()I)
    0057 op_0xA3
    0058 nop
    0059 sipush 6928
    0062 op_0x0B
    0063 op_0xA3
    0064 nop
    0065 iconst_4
    0066 iconst_1
    0067 goto 75
    0070 iconst_0
    0071 goto 75
    0074 iconst_0
    0075 istore_1
    0076 getstatic Field(java/lang/System.out:Ljava/io/PrintStream;)
    0079 iload_1
    0080 invokevirtual Method(java/io/PrintStream.println:(Z)V)
    0083 aload_0
    0084 invokevirtual Method(kotlin/ranges/IntRange.getFirst:()I)
    0087 istore_1
    0088 getstatic Field(java/lang/System.out:Ljava/io/PrintStream;)
    0091 iload_1
    0092 invokevirtual Method(java/io/PrintStream.println:(I)V)
    0095 aload_0
    0096 invokevirtual Method(kotlin/ranges/IntRange.getLast:()I)
    0099 istore_1
    0100 getstatic Field(java/lang/System.out:Ljava/io/PrintStream;)
    0103 iload_1
    0104 invokevirtual Method(java/io/PrintStream.println:(I)V)
    0107 return
    sub_attr  StackMapTable (16 bytes)
method        main ([Ljava/lang/String;)V 0x1009
  code        max_stack=0 max_locals=1
    0000 invokestatic Method(InputKt.main:()V)
    0003 return
