class_version major=61 minor=0
this_class    InputKt
super_class   java/lang/Object
access_flags  0x0031
method        show (IJDLjava/lang/String;Lkotlin/coroutines/Continuation;)Ljava/lang/Object; 0x0019
  code        max_stack=3 max_locals=7
    0000 getstatic Field(java/lang/System.out:Ljava/io/PrintStream;)
    0003 iload_0
    0004 invokevirtual Method(java/io/PrintStream.println:(I)V)
    0007 getstatic Field(java/lang/System.out:Ljava/io/PrintStream;)
    0010 lload_1
    0011 invokevirtual Method(java/io/PrintStream.println:(J)V)
    0014 getstatic Field(java/lang/System.out:Ljava/io/PrintStream;)
    0017 dload_3
    0018 invokevirtual Method(java/io/PrintStream.println:(D)V)
    0021 getstatic Field(java/lang/System.out:Ljava/io/PrintStream;)
    0024 aload 5
    0026 invokevirtual Method(java/io/PrintStream.println:(Ljava/lang/Object;)V)
    0029 getstatic Field(kotlin/Unit.INSTANCE:Lkotlin/Unit;)
    0032 areturn
  attr        Signature (2 bytes)
  attr        RuntimeInvisibleAnnotations (6 bytes)
  attr        RuntimeInvisibleParameterAnnotations (19 bytes)
