class_version major=61 minor=0
this_class    Planet
super_class   java/lang/Object
access_flags  0x0021
field         mass : D 0x0001
field         name : Ljava/lang/String; 0x0001
method        <init> (Ljava/lang/String;D)V 0x0001
  code        max_stack=3 max_locals=4
    0000 aload_0
    0001 invokespecial Method(java/lang/Object.<init>:()V)
    0004 aload_0
    0005 aload_1
    0006 putfield Field(Planet.name:Ljava/lang/String;)
    0009 aload_0
    0010 dload_2
    0011 putfield Field(Planet.mass:D)
    0014 return
method        toString ()Ljava/lang/String; 0x0001
  code        max_stack=1 max_locals=1
    0000 aload_0
    0001 getfield Field(Planet.name:Ljava/lang/String;)
    0004 areturn
  attr        RuntimeInvisibleAnnotations (6 bytes)
