class_version major=61 minor=0
this_class    InputKt
super_class   java/lang/Object
access_flags  0x0031
method        EARTH ()LPlanet; 0x0009
  code        max_stack=5 max_locals=4
    0000 new Class(Planet)
    0003 dup
    0004 ldc "EARTH"
    0006 astore 1
    0008 op_0x14
    0009 nop
    0010 op_0x2E
    0011 op_0x39
    0012 iconst_m1
    0013 aload 1
    0015 op_0x18
    0016 iconst_m1
    0017 invokespecial Method(Planet.<init>:(Ljava/lang/String;D)V)
    0020 astore 0
    0022 aload 0
    0024 areturn
method        JUPITER ()LPlanet; 0x0009
  code        max_stack=5 max_locals=4
    0000 new Class(Planet)
    0003 dup
    0004 ldc "JUPITER"
    0006 astore 1
    0008 op_0x14
    0009 nop
    0010 op_0x38
    0011 op_0x39
    0012 iconst_m1
    0013 aload 1
    0015 op_0x18
    0016 iconst_m1
    0017 invokespecial Method(Planet.<init>:(Ljava/lang/String;D)V)
    0020 astore 0
    0022 aload 0
    0024 areturn
method        MARS ()LPlanet; 0x0009
  code        max_stack=5 max_locals=4
    0000 new Class(Planet)
    0003 dup
    0004 ldc "MARS"
    0006 astore 1
    0008 op_0x14
    0009 nop
    0010 op_0x35
    0011 op_0x39
    0012 iconst_m1
    0013 aload 1
    0015 op_0x18
    0016 iconst_m1
    0017 invokespecial Method(Planet.<init>:(Ljava/lang/String;D)V)
    0020 astore 0
    0022 aload 0
    0024 areturn
method        Planet$valueOf (Ljava/lang/String;)LPlanet; 0x0009
  code        max_stack=4 max_locals=11
    0000 ldc "EARTH"
    0002 astore 1
    0004 aload 0
    0006 aload 1
    0008 invokevirtual Method(java/lang/String.equals:(Ljava/lang/Object;)Z)
    0011 istore 2
    0013 iload 2
    0015 ifeq 55
    0018 goto 81
    0021 invokestatic Method(InputKt.EARTH:()LPlanet;)
    0024 astore 3
    0026 aload 3
    0028 areturn
    0029 ldc "JUPITER"
    0031 astore 4
    0033 aload 0
    0035 aload 4
    0037 invokevirtual Method(java/lang/String.equals:(Ljava/lang/Object;)Z)
    0040 istore 5
    0042 iload 5
    0044 ifeq 21
    0047 invokestatic Method(InputKt.JUPITER:()LPlanet;)
    0050 astore 6
    0052 aload 6
    0054 areturn
    0055 ldc "MARS"
    0057 astore 7
    0059 aload 0
    0061 aload 7
    0063 invokevirtual Method(java/lang/String.equals:(Ljava/lang/Object;)Z)
    0066 istore 8
    0068 iload 8
    0070 ifeq 29
    0073 invokestatic Method(InputKt.MARS:()LPlanet;)
    0076 astore 9
    0078 aload 9
    0080 areturn
    0081 invokestatic Method(InputKt.EARTH:()LPlanet;)
    0084 astore 10
    0086 aload 10
    0088 areturn
    sub_attr  StackMapTable (76 bytes)
method        Planet$values ()Ljava/util/ArrayList; 0x0009
  code        max_stack=2 max_locals=7
    0000 new Class(java/util/ArrayList)
    0003 dup
    0004 invokespecial Method(java/util/ArrayList.<init>:()V)
    0007 astore 0
    0009 invokestatic Method(InputKt.EARTH:()LPlanet;)
    0012 astore 1
    0014 aload 0
    0016 aload 1
    0018 invokevirtual Method(java/util/ArrayList.add:(Ljava/lang/Object;)Z)
    0021 istore 2
    0023 invokestatic Method(InputKt.MARS:()LPlanet;)
    0026 astore 3
    0028 aload 0
    0030 aload 3
    0032 invokevirtual Method(java/util/ArrayList.add:(Ljava/lang/Object;)Z)
    0035 istore 4
    0037 invokestatic Method(InputKt.JUPITER:()LPlanet;)
    0040 astore 5
    0042 aload 0
    0044 aload 5
    0046 invokevirtual Method(java/util/ArrayList.add:(Ljava/lang/Object;)Z)
    0049 istore 6
    0051 aload 0
    0053 areturn
method        main ([Ljava/lang/String;)V 0x0009
  code        max_stack=5 max_locals=9
    0000 invokestatic Method(InputKt.EARTH:()LPlanet;)
    0003 astore 1
    0005 aload 1
    0007 getfield Field(Planet.mass:D)
    0010 op_0x39
    0011 iconst_m1
    0012 getstatic Field(java/lang/System.out:Ljava/io/PrintStream;)
    0015 op_0x18
    0016 iconst_m1
    0017 invokevirtual Method(java/io/PrintStream.println:(D)V)
    0020 invokestatic Method(InputKt.MARS:()LPlanet;)
    0023 astore 4
    0025 aload 4
    0027 getfield Field(Planet.name:Ljava/lang/String;)
    0030 astore 5
    0032 getstatic Field(java/lang/System.out:Ljava/io/PrintStream;)
    0035 aload 5
    0037 invokevirtual Method(java/io/PrintStream.println:(Ljava/lang/String;)V)
    0040 invokestatic Method(InputKt.JUPITER:()LPlanet;)
    0043 astore 6
    0045 aload 6
    0047 getfield Field(Planet.mass:D)
    0050 op_0x39
    0051 iconst_4
    0052 getstatic Field(java/lang/System.out:Ljava/io/PrintStream;)
    0055 op_0x18
    0056 iconst_4
    0057 invokevirtual Method(java/io/PrintStream.println:(D)V)
    0060 return
