class_version major=61 minor=0
this_class    InputKt
super_class   java/lang/Object
access_flags  0x0031
method        main ()V 0x0019
  code        max_stack=5 max_locals=2
    0000 ldc "Hello, World!"
    0002 astore_0
    0003 aload_0
    0004 invokevirtual Method(java/lang/String.length:()I)
    0007 istore_1
    0008 getstatic Field(java/lang/System.out:Ljava/io/PrintStream;)
    0011 iload_1
    0012 invokevirtual Method(java/io/PrintStream.println:(I)V)
    0015 aload_0
    0016 getstatic Field(java/util/Locale.ROOT:Ljava/util/Locale;)
    0019 invokevirtual Method(java/lang/String.toUpperCase:(Ljava/util/Locale;)Ljava/lang/String;)
    0022 dup
    0023 ldc "toUpperCase(...)"
    0025 invokestatic Method(kotlin/jvm/internal/Intrinsics.checkNotNullExpressionValue:(Ljava/lang/Object;Ljava/lang/String;)V)
    0028 astore_1
    0029 getstatic Field(java/lang/System.out:Ljava/io/PrintStream;)
    0032 aload_1
    0033 invokevirtual Method(java/io/PrintStream.println:(Ljava/lang/Object;)V)
    0036 aload_0
    0037 getstatic Field(java/util/Locale.ROOT:Ljava/util/Locale;)
    0040 invokevirtual Method(java/lang/String.toLowerCase:(Ljava/util/Locale;)Ljava/lang/String;)
    0043 dup
    0044 ldc "toLowerCase(...)"
    0046 invokestatic Method(kotlin/jvm/internal/Intrinsics.checkNotNullExpressionValue:(Ljava/lang/Object;Ljava/lang/String;)V)
    0049 astore_1
    0050 getstatic Field(java/lang/System.out:Ljava/io/PrintStream;)
    0053 aload_1
    0054 invokevirtual Method(java/io/PrintStream.println:(Ljava/lang/Object;)V)
    0057 aload_0
    0058 iconst_0
    0059 iconst_5
    0060 invokevirtual Method(java/lang/String.substring:(II)Ljava/lang/String;)
    0063 dup
    0064 ldc "substring(...)"
    0066 invokestatic Method(kotlin/jvm/internal/Intrinsics.checkNotNullExpressionValue:(Ljava/lang/Object;Ljava/lang/String;)V)
    0069 astore_1
    0070 getstatic Field(java/lang/System.out:Ljava/io/PrintStream;)
    0073 aload_1
    0074 invokevirtual Method(java/io/PrintStream.println:(Ljava/lang/Object;)V)
    0077 aload_0
    0078 checkcast Class(java/lang/CharSequence)
    0081 ldc "World"
    0083 checkcast Class(java/lang/CharSequence)
    0086 iconst_0
    0087 iconst_2
    0088 aconst_null
    0089 invokestatic Method(kotlin/text/StringsKt.contains$default:(Ljava/lang/CharSequence;Ljava/lang/CharSequence;ZILjava/lang/Object;)Z)
    0092 istore_1
    0093 getstatic Field(java/lang/System.out:Ljava/io/PrintStream;)
    0096 iload_1
    0097 invokevirtual Method(java/io/PrintStream.println:(Z)V)
    0100 aload_0
    0101 ldc "Hello"
    0103 iconst_0
    0104 iconst_2
    0105 aconst_null
    0106 invokestatic Method(kotlin/text/StringsKt.startsWith$default:(Ljava/lang/String;Ljava/lang/String;ZILjava/lang/Object;)Z)
    0109 istore_1
    0110 getstatic Field(java/lang/System.out:Ljava/io/PrintStream;)
    0113 iload_1
    0114 invokevirtual Method(java/io/PrintStream.println:(Z)V)
    0117 aload_0
    0118 ldc "!"
    0120 iconst_0
    0121 iconst_2
    0122 aconst_null
    0123 invokestatic Method(kotlin/text/StringsKt.endsWith$default:(Ljava/lang/String;Ljava/lang/String;ZILjava/lang/Object;)Z)
    0126 istore_1
    0127 getstatic Field(java/lang/System.out:Ljava/io/PrintStream;)
    0130 iload_1
    0131 invokevirtual Method(java/io/PrintStream.println:(Z)V)
    0134 return
method        main ([Ljava/lang/String;)V 0x1009
  code        max_stack=0 max_locals=1
    0000 invokestatic Method(InputKt.main:()V)
    0003 return
