class_version major=61 minor=0
this_class    Wrapper
super_class   java/lang/Object
access_flags  0x0021
field         items : [I 0x0001
method        <init> ([I)V 0x0001
  code        max_stack=2 max_locals=2
    0000 aload_0
    0001 invokespecial Method(java/lang/Object.<init>:()V)
    0004 aload_0
    0005 aload_1
    0006 putfield Field(Wrapper.items:[I)
    0009 return
method        get (I)I 0x0001
  code        max_stack=3 max_locals=3
    0000 aload_0
    0001 getfield Field(Wrapper.items:[I)
    0004 astore_2
    0005 aload_2
    0006 iload_1
    0007 iaload
    0008 aload_0
    0009 aload_2
    0010 putfield Field(Wrapper.items:[I)
    0013 ireturn
method        getItems ()[I 0x0001
  code        max_stack=1 max_locals=1
    0000 aload_0
    0001 getfield Field(Wrapper.items:[I)
    0004 areturn
method        set (II)V 0x0001
  code        max_stack=3 max_locals=4
    0000 aload_0
    0001 getfield Field(Wrapper.items:[I)
    0004 astore_3
    0005 aload_3
    0006 iload_1
    0007 iload_2
    0008 iastore
    0009 aload_0
    0010 aload_3
    0011 putfield Field(Wrapper.items:[I)
    0014 return
