class_version major=61 minor=0
this_class    MathUtils
super_class   java/lang/Object
access_flags  0x0031
field         INSTANCE : LMathUtils; 0x0019
method        <clinit> ()V 0x0008
  code        max_stack=2 max_locals=0
    0000 op_0xBB
    0001 nop
    0002 iconst_m1
    0003 op_0x59
    0004 invokespecial Method(MathUtils.<init>:()V)
    0007 op_0xB3
    0008 nop
    0009 op_0x14
    0010 return
method        <init> ()V 0x0002
  code        max_stack=1 max_locals=1
    0000 op_0x2A
    0001 invokespecial Method(java/lang/Object.<init>:()V)
    0004 return
method        cube (I)I 0x0011
  code        max_stack=2 max_locals=2
    0000 op_0x1B
    0001 op_0x1B
    0002 imul
    0003 op_0x1B
    0004 imul
    0005 op_0xAC
method        square (I)I 0x0011
  code        max_stack=2 max_locals=2
    0000 op_0x1B
    0001 op_0x1B
    0002 imul
    0003 op_0xAC
