class_version major=61 minor=0
this_class    InputKt
super_class   java/lang/Object
access_flags  0x0031
method        main ()V 0x0019
  code        max_stack=4 max_locals=3
    0000 iconst_3
    0001 anewarray Class(java/lang/String)
    0004 astore_0
    0005 aload_0
    0006 iconst_0
    0007 ldc "a"
    0009 aastore
    0010 aload_0
    0011 iconst_1
    0012 ldc "b"
    0014 aastore
    0015 aload_0
    0016 iconst_2
    0017 ldc "c"
    0019 aastore
    0020 aload_0
    0021 invokestatic Method(kotlin/collections/CollectionsKt.listOf:([Ljava/lang/Object;)Ljava/util/List;)
    0024 astore_0
    0025 new Class(Box)
    0028 dup
    0029 ldc "hi"
    0031 aload_0
    0032 invokespecial Method(Box.<init>:(Ljava/lang/String;Ljava/util/List;)V)
    0035 astore_2
    0036 aload_2
    0037 invokevirtual Method(Box.getName:()Ljava/lang/String;)
    0040 getstatic Field(java/lang/System.out:Ljava/io/PrintStream;)
    0043 swap
    0044 invokevirtual Method(java/io/PrintStream.println:(Ljava/lang/Object;)V)
    0047 aload_2
    0048 invokevirtual Method(Box.getItems:()Ljava/util/List;)
    0051 invokeinterface InterfaceMethod(java/util/List.size:()I)
    0056 istore_0
    0057 getstatic Field(java/lang/System.out:Ljava/io/PrintStream;)
    0060 iload_0
    0061 invokevirtual Method(java/io/PrintStream.println:(I)V)
    0064 return
method        main ([Ljava/lang/String;)V 0x1009
  code        max_stack=0 max_locals=1
    0000 invokestatic Method(InputKt.main:()V)
    0003 return
