class_version major=61 minor=0
this_class    InputKt
super_class   java/lang/Object
access_flags  0x0031
method        describe (LJsonValue;)Ljava/lang/String; 0x0019
  code        max_stack=2 max_locals=2
    0000 aload_0
    0001 ldc "v"
    0003 invokestatic Method(kotlin/jvm/internal/Intrinsics.checkNotNullParameter:(Ljava/lang/Object;Ljava/lang/String;)V)
    0006 aload_0
    0007 astore_1
    0008 aload_1
    0009 instanceof Class(JsonNull)
    0012 ifeq 20
    0015 ldc "null"
    0017 goto 118
    0020 aload_1
    0021 instanceof Class(JsonBool)
    0024 ifeq 32
    0027 ldc "bool"
    0029 goto 118
    0032 aload_1
    0033 instanceof Class(JsonNum)
    0036 ifeq 44
    0039 ldc "num"
    0041 goto 118
    0044 aload_1
    0045 instanceof Class(JsonStr)
    0048 ifeq 56
    0051 ldc "str"
    0053 goto 118
    0056 aload_1
    0057 instanceof Class(JsonArr)
    0060 ifeq 83
    0063 aload_0
    0064 checkcast Class(JsonArr)
    0067 invokevirtual Method(JsonArr.getItems:()Ljava/util/List;)
    0070 invokeinterface InterfaceMethod(java/util/List.size:()I)
    0075 invokedynamic InvokeDynamic(makeConcatWithConstants:(I)Ljava/lang/String;)
    0080 goto 118
    0083 aload_1
    0084 instanceof Class(JsonObj)
    0087 ifeq 110
    0090 aload_0
    0091 checkcast Class(JsonObj)
    0094 invokevirtual Method(JsonObj.getKeys:()Ljava/util/List;)
    0097 invokeinterface InterfaceMethod(java/util/List.size:()I)
    0102 invokedynamic InvokeDynamic(makeConcatWithConstants:(I)Ljava/lang/String;)
    0107 goto 118
    0110 new Class(kotlin/NoWhenBranchMatchedException)
    0113 dup
    0114 invokespecial Method(kotlin/NoWhenBranchMatchedException.<init>:()V)
    0117 athrow
    0118 areturn
    sub_attr  StackMapTable (17 bytes)
  attr        RuntimeInvisibleAnnotations (6 bytes)
  attr        RuntimeInvisibleParameterAnnotations (7 bytes)
method        escapeString (Ljava/lang/String;)Ljava/lang/String; 0x0019
  code        max_stack=3 max_locals=5
    0000 aload_0
    0001 ldc "s"
    0003 invokestatic Method(kotlin/jvm/internal/Intrinsics.checkNotNullParameter:(Ljava/lang/Object;Ljava/lang/String;)V)
    0006 new Class(java/lang/StringBuilder)
    0009 dup
    0010 invokespecial Method(java/lang/StringBuilder.<init>:()V)
    0013 astore_1
    0014 aload_1
    0015 bipush 34
    0017 invokevirtual Method(java/lang/StringBuilder.append:(C)Ljava/lang/StringBuilder;)
    0020 pop
    0021 iconst_0
    0022 istore_2
    0023 aload_0
    0024 invokevirtual Method(java/lang/String.length:()I)
    0027 istore_3
    0028 iload_2
    0029 iload_3
    0030 if_icmpge 43
    0033 aload_0
    0034 iload_2
    0035 invokevirtual Method(java/lang/String.charAt:(I)C)
    0038 istore 4
    0040 goto 61
    0043 aload_1
    0044 bipush 34
    0046 invokevirtual Method(java/lang/StringBuilder.append:(C)Ljava/lang/StringBuilder;)
    0049 pop
    0050 aload_1
    0051 invokevirtual Method(java/lang/StringBuilder.toString:()Ljava/lang/String;)
    0054 dup
    0055 ldc "toString(...)"
    0057 invokestatic Method(kotlin/jvm/internal/Intrinsics.checkNotNullExpressionValue:(Ljava/lang/Object;Ljava/lang/String;)V)
    0060 areturn
    0061 iload 4
    0063 bipush 34
    0065 if_icmpne 78
    0068 aload_1
    0069 ldc "\""
    0071 invokevirtual Method(java/lang/StringBuilder.append:(Ljava/lang/String;)Ljava/lang/StringBuilder;)
    0074 pop
    0075 goto 153
    0078 iload 4
    0080 bipush 92
    0082 if_icmpne 95
    0085 aload_1
    0086 ldc "\\"
    0088 invokevirtual Method(java/lang/StringBuilder.append:(Ljava/lang/String;)Ljava/lang/StringBuilder;)
    0091 pop
    0092 goto 153
    0095 iload 4
    0097 bipush 10
    0099 if_icmpne 112
    0102 aload_1
    0103 ldc "\n"
    0105 invokevirtual Method(java/lang/StringBuilder.append:(Ljava/lang/String;)Ljava/lang/StringBuilder;)
    0108 pop
    0109 goto 153
    0112 iload 4
    0114 bipush 9
    0116 if_icmpne 129
    0119 aload_1
    0120 ldc "\t"
    0122 invokevirtual Method(java/lang/StringBuilder.append:(Ljava/lang/String;)Ljava/lang/StringBuilder;)
    0125 pop
    0126 goto 153
    0129 iload 4
    0131 bipush 13
    0133 if_icmpne 146
    0136 aload_1
    0137 ldc "\r"
    0139 invokevirtual Method(java/lang/StringBuilder.append:(Ljava/lang/String;)Ljava/lang/StringBuilder;)
    0142 pop
    0143 goto 153
    0146 aload_1
    0147 iload 4
    0149 invokevirtual Method(java/lang/StringBuilder.append:(C)Ljava/lang/StringBuilder;)
    0152 pop
    0153 iinc 2 1
    0156 goto 23
    sub_attr  StackMapTable (23 bytes)
  attr        RuntimeInvisibleAnnotations (6 bytes)
  attr        RuntimeInvisibleParameterAnnotations (7 bytes)
method        indent (Ljava/lang/StringBuilder;I)V 0x0019
  code        max_stack=2 max_locals=3
    0000 aload_0
    0001 ldc "sb"
    0003 invokestatic Method(kotlin/jvm/internal/Intrinsics.checkNotNullParameter:(Ljava/lang/Object;Ljava/lang/String;)V)
    0006 iconst_0
    0007 istore_2
    0008 iload_2
    0009 iload_1
    0010 if_icmpge 26
    0013 aload_0
    0014 ldc "  "
    0016 invokevirtual Method(java/lang/StringBuilder.append:(Ljava/lang/String;)Ljava/lang/StringBuilder;)
    0019 pop
    0020 iinc 2 1
    0023 goto 8
    0026 return
    sub_attr  StackMapTable (7 bytes)
  attr        RuntimeInvisibleParameterAnnotations (9 bytes)
method        main ()V 0x0019
  code        max_stack=2 max_locals=3
    0000 ldc "{"name":"Ada","langs":["Kotlin","Rust","Swift"],"active":true,"manager":null}"
    0002 astore_0
    0003 aload_0
    0004 invokestatic Method(InputKt.parseJson:(Ljava/lang/String;)LJsonValue;)
    0007 astore_1
    0008 aload_1
    0009 invokestatic Method(InputKt.describe:(LJsonValue;)Ljava/lang/String;)
    0012 invokedynamic InvokeDynamic(makeConcatWithConstants:(Ljava/lang/String;)Ljava/lang/String;)
    0017 getstatic Field(java/lang/System.out:Ljava/io/PrintStream;)
    0020 swap
    0021 invokevirtual Method(java/io/PrintStream.println:(Ljava/lang/Object;)V)
    0024 aload_1
    0025 checkcast Class(JsonObj)
    0028 astore_2
    0029 aload_2
    0030 invokevirtual Method(JsonObj.getKeys:()Ljava/util/List;)
    0033 invokeinterface InterfaceMethod(java/util/List.size:()I)
    0038 invokedynamic InvokeDynamic(makeConcatWithConstants:(I)Ljava/lang/String;)
    0043 getstatic Field(java/lang/System.out:Ljava/io/PrintStream;)
    0046 swap
    0047 invokevirtual Method(java/io/PrintStream.println:(Ljava/lang/Object;)V)
    0050 ldc "--- round-trip ---"
    0052 getstatic Field(java/lang/System.out:Ljava/io/PrintStream;)
    0055 swap
    0056 invokevirtual Method(java/io/PrintStream.println:(Ljava/lang/Object;)V)
    0059 aload_1
    0060 invokestatic Method(InputKt.pretty:(LJsonValue;)Ljava/lang/String;)
    0063 getstatic Field(java/lang/System.out:Ljava/io/PrintStream;)
    0066 swap
    0067 invokevirtual Method(java/io/PrintStream.println:(Ljava/lang/Object;)V)
    0070 return
method        main ([Ljava/lang/String;)V 0x1009
  code        max_stack=0 max_locals=1
    0000 invokestatic Method(InputKt.main:()V)
    0003 return
method        parseJson (Ljava/lang/String;)LJsonValue; 0x0019
  code        max_stack=3 max_locals=3
    0000 aload_0
    0001 ldc "src"
    0003 invokestatic Method(kotlin/jvm/internal/Intrinsics.checkNotNullParameter:(Ljava/lang/Object;Ljava/lang/String;)V)
    0006 new Class(Parser)
    0009 dup
    0010 aload_0
    0011 invokespecial Method(Parser.<init>:(Ljava/lang/String;)V)
    0014 astore_1
    0015 aload_1
    0016 invokevirtual Method(Parser.parseValue:()LJsonValue;)
    0019 astore_2
    0020 aload_1
    0021 invokevirtual Method(Parser.skipWs:()V)
    0024 aload_2
    0025 areturn
  attr        RuntimeInvisibleAnnotations (6 bytes)
  attr        RuntimeInvisibleParameterAnnotations (7 bytes)
method        pretty (LJsonValue;)Ljava/lang/String; 0x0019
  code        max_stack=3 max_locals=2
    0000 aload_0
    0001 ldc "v"
    0003 invokestatic Method(kotlin/jvm/internal/Intrinsics.checkNotNullParameter:(Ljava/lang/Object;Ljava/lang/String;)V)
    0006 new Class(java/lang/StringBuilder)
    0009 dup
    0010 invokespecial Method(java/lang/StringBuilder.<init>:()V)
    0013 astore_1
    0014 aload_0
    0015 aload_1
    0016 iconst_0
    0017 invokestatic Method(InputKt.prettyInto:(LJsonValue;Ljava/lang/StringBuilder;I)V)
    0020 aload_1
    0021 invokevirtual Method(java/lang/StringBuilder.toString:()Ljava/lang/String;)
    0024 dup
    0025 ldc "toString(...)"
    0027 invokestatic Method(kotlin/jvm/internal/Intrinsics.checkNotNullExpressionValue:(Ljava/lang/Object;Ljava/lang/String;)V)
    0030 areturn
  attr        RuntimeInvisibleAnnotations (6 bytes)
  attr        RuntimeInvisibleParameterAnnotations (7 bytes)
method        prettyInto (LJsonValue;Ljava/lang/StringBuilder;I)V 0x0019
  code        max_stack=3 max_locals=27
    0000 aload_0
    0001 ldc "v"
    0003 invokestatic Method(kotlin/jvm/internal/Intrinsics.checkNotNullParameter:(Ljava/lang/Object;Ljava/lang/String;)V)
    0006 aload_1
    0007 ldc "sb"
    0009 invokestatic Method(kotlin/jvm/internal/Intrinsics.checkNotNullParameter:(Ljava/lang/Object;Ljava/lang/String;)V)
    0012 aload_0
    0013 astore_3
    0014 aload_3
    0015 instanceof Class(JsonNull)
    0018 ifeq 31
    0021 aload_1
    0022 ldc "null"
    0024 invokevirtual Method(java/lang/StringBuilder.append:(Ljava/lang/String;)Ljava/lang/StringBuilder;)
    0027 pop
    0028 goto 167
    0031 aload_3
    0032 instanceof Class(JsonBool)
    0035 ifeq 51
    0038 aload_0
    0039 checkcast Class(JsonBool)
    0042 invokevirtual Method(JsonBool.getValue:()Z)
    0045 ifeq 175
    0048 goto 168
    0051 aload_3
    0052 instanceof Class(JsonNum)
    0055 ifeq 76
    0058 aload_1
    0059 aload_0
    0060 checkcast Class(JsonNum)
    0063 invokevirtual Method(JsonNum.getValue:()I)
    0066 invokestatic Method(java/lang/String.valueOf:(I)Ljava/lang/String;)
    0069 invokevirtual Method(java/lang/StringBuilder.append:(Ljava/lang/String;)Ljava/lang/StringBuilder;)
    0072 pop
    0073 goto 167
    0076 aload_3
    0077 instanceof Class(JsonStr)
    0080 ifeq 101
    0083 aload_1
    0084 aload_0
    0085 checkcast Class(JsonStr)
    0088 invokevirtual Method(JsonStr.getValue:()Ljava/lang/String;)
    0091 invokestatic Method(InputKt.escapeString:(Ljava/lang/String;)Ljava/lang/String;)
    0094 invokevirtual Method(java/lang/StringBuilder.append:(Ljava/lang/String;)Ljava/lang/StringBuilder;)
    0097 pop
    0098 goto 167
    0101 aload_3
    0102 instanceof Class(JsonArr)
    0105 ifeq 130
    0108 aload_0
    0109 checkcast Class(JsonArr)
    0112 astore 4
    0114 aload 4
    0116 invokevirtual Method(JsonArr.getItems:()Ljava/util/List;)
    0119 invokeinterface InterfaceMethod(java/util/List.isEmpty:()Z)
    0124 ifeq 197
    0127 goto 189
    0130 aload_3
    0131 instanceof Class(JsonObj)
    0134 ifeq 159
    0137 aload_0
    0138 checkcast Class(JsonObj)
    0141 astore 5
    0143 aload 5
    0145 invokevirtual Method(JsonObj.getKeys:()Ljava/util/List;)
    0148 invokeinterface InterfaceMethod(java/util/List.isEmpty:()Z)
    0153 ifeq 344
    0156 goto 336
    0159 new Class(kotlin/NoWhenBranchMatchedException)
    0162 dup
    0163 invokespecial Method(kotlin/NoWhenBranchMatchedException.<init>:()V)
    0166 athrow
    0167 return
    0168 ldc "true"
    0170 astore 6
    0172 goto 179
    0175 ldc "false"
    0177 astore 6
    0179 aload_1
    0180 aload 6
    0182 invokevirtual Method(java/lang/StringBuilder.append:(Ljava/lang/String;)Ljava/lang/StringBuilder;)
    0185 pop
    0186 goto 167
    0189 aload_1
    0190 ldc "[]"
    0192 invokevirtual Method(java/lang/StringBuilder.append:(Ljava/lang/String;)Ljava/lang/StringBuilder;)
    0195 pop
    0196 return
    0197 aload_1
    0198 ldc "[
"
    0200 invokevirtual Method(java/lang/StringBuilder.append:(Ljava/lang/String;)Ljava/lang/StringBuilder;)
    0203 pop
    0204 iconst_0
    0205 istore 7
    0207 iload 7
    0209 istore 8
    0211 aload 4
    0213 invokevirtual Method(JsonArr.getItems:()Ljava/util/List;)
    0216 invokeinterface InterfaceMethod(java/util/List.size:()I)
    0221 istore 9
    0223 iload 8
    0225 iload 9
    0227 if_icmpge 303
    0230 aload_1
    0231 iload_2
    0232 iconst_1
    0233 iadd
    0234 invokestatic Method(InputKt.indent:(Ljava/lang/StringBuilder;I)V)
    0237 aload 4
    0239 invokevirtual Method(JsonArr.getItems:()Ljava/util/List;)
    0242 astore 10
    0244 iload 7
    0246 istore 11
    0248 aload 10
    0250 iload 11
    0252 invokeinterface InterfaceMethod(java/util/List.get:(I)Ljava/lang/Object;)
    0257 astore 12
    0259 iload_2
    0260 iconst_1
    0261 iadd
    0262 istore 13
    0264 aload 12
    0266 checkcast Class(JsonValue)
    0269 aload_1
    0270 iload 13
    0272 invokestatic Method(InputKt.prettyInto:(LJsonValue;Ljava/lang/StringBuilder;I)V)
    0275 iload 7
    0277 iconst_1
    0278 iadd
    0279 istore 14
    0281 aload 4
    0283 invokevirtual Method(JsonArr.getItems:()Ljava/util/List;)
    0286 invokeinterface InterfaceMethod(java/util/List.size:()I)
    0291 istore 15
    0293 iload 14
    0295 iload 15
    0297 if_icmpge 323
    0300 goto 316
    0303 aload_1
    0304 iload_2
    0305 invokestatic Method(InputKt.indent:(Ljava/lang/StringBuilder;I)V)
    0308 aload_1
    0309 ldc "]"
    0311 invokevirtual Method(java/lang/StringBuilder.append:(Ljava/lang/String;)Ljava/lang/StringBuilder;)
    0314 pop
    0315 return
    0316 aload_1
    0317 ldc ","
    0319 invokevirtual Method(java/lang/StringBuilder.append:(Ljava/lang/String;)Ljava/lang/StringBuilder;)
    0322 pop
    0323 aload_1
    0324 ldc "
"
    0326 invokevirtual Method(java/lang/StringBuilder.append:(Ljava/lang/String;)Ljava/lang/StringBuilder;)
    0329 pop
    0330 iinc 7 1
    0333 goto 207
    0336 aload_1
    0337 ldc "{}"
    0339 invokevirtual Method(java/lang/StringBuilder.append:(Ljava/lang/String;)Ljava/lang/StringBuilder;)
    0342 pop
    0343 return
    0344 aload_1
    0345 ldc "{
"
    0347 invokevirtual Method(java/lang/StringBuilder.append:(Ljava/lang/String;)Ljava/lang/StringBuilder;)
    0350 pop
    0351 iconst_0
    0352 istore 16
    0354 iload 16
    0356 istore 17
    0358 aload 5
    0360 invokevirtual Method(JsonObj.getKeys:()Ljava/util/List;)
    0363 invokeinterface InterfaceMethod(java/util/List.size:()I)
    0368 istore 18
    0370 iload 17
    0372 iload 18
    0374 if_icmpge 488
    0377 aload_1
    0378 iload_2
    0379 iconst_1
    0380 iadd
    0381 invokestatic Method(InputKt.indent:(Ljava/lang/StringBuilder;I)V)
    0384 aload 5
    0386 invokevirtual Method(JsonObj.getKeys:()Ljava/util/List;)
    0389 astore 19
    0391 iload 16
    0393 istore 20
    0395 aload_1
    0396 aload 19
    0398 iload 20
    0400 invokeinterface InterfaceMethod(java/util/List.get:(I)Ljava/lang/Object;)
    0405 checkcast Class(java/lang/String)
    0408 invokestatic Method(InputKt.escapeString:(Ljava/lang/String;)Ljava/lang/String;)
    0411 invokevirtual Method(java/lang/StringBuilder.append:(Ljava/lang/String;)Ljava/lang/StringBuilder;)
    0414 pop
    0415 aload_1
    0416 ldc ": "
    0418 invokevirtual Method(java/lang/StringBuilder.append:(Ljava/lang/String;)Ljava/lang/StringBuilder;)
    0421 pop
    0422 aload 5
    0424 invokevirtual Method(JsonObj.getValues:()Ljava/util/List;)
    0427 astore 21
    0429 iload 16
    0431 istore 22
    0433 aload 21
    0435 iload 22
    0437 invokeinterface InterfaceMethod(java/util/List.get:(I)Ljava/lang/Object;)
    0442 astore 23
    0444 iload_2
    0445 iconst_1
    0446 iadd
    0447 istore 24
    0449 aload 23
    0451 checkcast Class(JsonValue)
    0454 aload_1
    0455 iload 24
    0457 invokestatic Method(InputKt.prettyInto:(LJsonValue;Ljava/lang/StringBuilder;I)V)
    0460 iload 16
    0462 iconst_1
    0463 iadd
    0464 istore 25
    0466 aload 5
    0468 invokevirtual Method(JsonObj.getKeys:()Ljava/util/List;)
    0471 invokeinterface InterfaceMethod(java/util/List.size:()I)
    0476 istore 26
    0478 iload 25
    0480 iload 26
    0482 if_icmpge 508
    0485 goto 501
    0488 aload_1
    0489 iload_2
    0490 invokestatic Method(InputKt.indent:(Ljava/lang/StringBuilder;I)V)
    0493 aload_1
    0494 ldc "}"
    0496 invokevirtual Method(java/lang/StringBuilder.append:(Ljava/lang/String;)Ljava/lang/StringBuilder;)
    0499 pop
    0500 return
    0501 aload_1
    0502 ldc ","
    0504 invokevirtual Method(java/lang/StringBuilder.append:(Ljava/lang/String;)Ljava/lang/StringBuilder;)
    0507 pop
    0508 aload_1
    0509 ldc "
"
    0511 invokevirtual Method(java/lang/StringBuilder.append:(Ljava/lang/String;)Ljava/lang/StringBuilder;)
    0514 pop
    0515 iinc 16 1
    0518 goto 354
    sub_attr  StackMapTable (200 bytes)
  attr        RuntimeInvisibleParameterAnnotations (15 bytes)
class_attr    BootstrapMethods (26 bytes)
