class_version major=61 minor=0
this_class    Validated
super_class   java/lang/Object
access_flags  0x0021
field         value : I 0x0001
method        <init> (I)V 0x0001
  code        max_stack=2 max_locals=2
    0000 aload_0
    0001 invokespecial Method(java/lang/Object.<init>:()V)
    0004 aload_0
    0005 iload_1
    0006 putfield Field(Validated.value:I)
    0009 iload_1
    0010 ifgt 21
    0013 new Class(java/lang/IllegalArgumentException)
    0016 dup
    0017 invokespecial Method(java/lang/IllegalArgumentException.<init>:()V)
    0020 athrow
    0021 return
    sub_attr  StackMapTable (3 bytes)
method        getValue ()I 0x0001
  code        max_stack=1 max_locals=1
    0000 aload_0
    0001 getfield Field(Validated.value:I)
    0004 ireturn
