class_version major=61 minor=0
this_class    InputKt
super_class   java/lang/Object
access_flags  0x0031
method        classify (II)Ljava/lang/String; 0x0009
  code        max_stack=3 max_locals=37
    0000 iconst_1
    0001 istore 2
    0003 op_0xA7
    0004 nop
    0005 iconst_0
    0006 iload 0
    0008 istore 3
    0010 iconst_0
    0011 istore 4
    0013 iload 3
    0015 iload 4
    0017 op_0xA3
    0018 nop
    0019 iconst_4
    0020 iconst_0
    0021 op_0xA7
    0022 nop
    0023 iconst_1
    0024 iconst_1
    0025 istore 5
    0027 iconst_0
    0028 istore 6
    0030 iload 5
    0032 op_0x99
    0033 nop
    0034 op_0xBC
    0035 op_0xA7
    0036 nop
    0037 op_0x9D
    0038 ldc "Q1"
    0040 astore 7
    0042 aload 7
    0044 astore 8
    0046 op_0xA7
    0047 nop
    0048 op_0x8F
    0049 iload 0
    0051 istore 9
    0053 iconst_0
    0054 istore 10
    0056 iload 9
    0058 iload 10
    0060 op_0xA1
    0061 nop
    0062 iconst_4
    0063 iconst_0
    0064 op_0xA7
    0065 nop
    0066 iconst_1
    0067 iconst_1
    0068 istore 11
    0070 iconst_0
    0071 istore 12
    0073 iload 11
    0075 op_0x99
    0076 nop
    0077 op_0xB5
    0078 op_0xA7
    0079 nop
    0080 op_0x96
    0081 ldc "Q2"
    0083 astore 13
    0085 aload 13
    0087 astore 8
    0089 op_0xA7
    0090 nop
    0091 isub
    0092 iload 0
    0094 istore 14
    0096 iconst_0
    0097 istore 15
    0099 iload 14
    0101 iload 15
    0103 op_0xA1
    0104 nop
    0105 iconst_4
    0106 iconst_0
    0107 op_0xA7
    0108 nop
    0109 iconst_1
    0110 iconst_1
    0111 istore 16
    0113 iconst_0
    0114 istore 17
    0116 iload 16
    0118 op_0x99
    0119 nop
    0120 op_0xAE
    0121 op_0xA7
    0122 nop
    0123 op_0x8F
    0124 ldc "Q3"
    0126 astore 18
    0128 aload 18
    0130 astore 8
    0132 op_0xA7
    0133 nop
    0134 op_0x39
    0135 iload 0
    0137 istore 19
    0139 iconst_0
    0140 istore 20
    0142 iload 19
    0144 iload 20
    0146 op_0xA3
    0147 nop
    0148 iconst_4
    0149 iconst_0
    0150 op_0xA7
    0151 nop
    0152 iconst_1
    0153 iconst_1
    0154 istore 21
    0156 iconst_0
    0157 istore 22
    0159 iload 21
    0161 op_0x99
    0162 nop
    0163 op_0xA7
    0164 op_0xA7
    0165 nop
    0166 op_0x88
    0167 ldc "Q4"
    0169 astore 23
    0171 aload 23
    0173 astore 8
    0175 op_0xA7
    0176 nop
    0177 op_0x0E
    0178 ldc "axis"
    0180 astore 24
    0182 aload 24
    0184 astore 8
    0186 op_0xA7
    0187 nop
    0188 iconst_0
    0189 aload 8
    0191 op_0xB0
    0192 iload 1
    0194 istore 25
    0196 iconst_0
    0197 istore 26
    0199 iload 25
    0201 iload 26
    0203 op_0xA3
    0204 nop
    0205 iconst_4
    0206 iconst_0
    0207 op_0xA7
    0208 nop
    0209 iconst_1
    0210 iconst_1
    0211 istore 27
    0213 iload 27
    0215 istore 6
    0217 op_0xA7
    0218 nop
    0219 iconst_0
    0220 iload 6
    0222 op_0x99
    0223 op_0xFF
    0224 op_0x53
    0225 op_0xA7
    0226 op_0xFF
    0227 op_0x45
    0228 iload 1
    0230 istore 28
    0232 iconst_0
    0233 istore 29
    0235 iload 28
    0237 iload 29
    0239 op_0xA3
    0240 nop
    0241 iconst_4
    0242 iconst_0
    0243 op_0xA7
    0244 nop
    0245 iconst_1
    0246 iconst_1
    0247 istore 30
    0249 iload 30
    0251 istore 12
    0253 op_0xA7
    0254 nop
    0255 iconst_0
    0256 iload 12
    0258 op_0x99
    0259 op_0xFF
    0260 op_0x5A
    0261 op_0xA7
    0262 op_0xFF
    0263 op_0x4C
    0264 iload 1
    0266 istore 31
    0268 iconst_0
    0269 istore 32
    0271 iload 31
    0273 iload 32
    0275 op_0xA1
    0276 nop
    0277 iconst_4
    0278 iconst_0
    0279 op_0xA7
    0280 nop
    0281 iconst_1
    0282 iconst_1
    0283 istore 33
    0285 iload 33
    0287 istore 17
    0289 op_0xA7
    0290 nop
    0291 iconst_0
    0292 iload 17
    0294 op_0x99
    0295 op_0xFF
    0296 op_0x61
    0297 op_0xA7
    0298 op_0xFF
    0299 op_0x53
    0300 iload 1
    0302 istore 34
    0304 iconst_0
    0305 istore 35
    0307 iload 34
    0309 iload 35
    0311 op_0xA1
    0312 nop
    0313 iconst_4
    0314 iconst_0
    0315 op_0xA7
    0316 nop
    0317 iconst_1
    0318 iconst_1
    0319 istore 36
    0321 iload 36
    0323 istore 22
    0325 op_0xA7
    0326 nop
    0327 iconst_0
    0328 iload 22
    0330 op_0x99
    0331 op_0xFF
    0332 imul
    0333 op_0xA7
    0334 op_0xFF
    0335 op_0x5A
    sub_attr  StackMapTable (864 bytes)
method        main ([Ljava/lang/String;)V 0x0009
  code        max_stack=2 max_locals=16
    0000 iconst_1
    0001 istore 1
    0003 iconst_1
    0004 istore 2
    0006 iload 1
    0008 iload 2
    0010 invokestatic Method(InputKt.classify:(II)Ljava/lang/String;)
    0013 astore 3
    0015 getstatic Field(java/lang/System.out:Ljava/io/PrintStream;)
    0018 aload 3
    0020 invokevirtual Method(java/io/PrintStream.println:(Ljava/lang/String;)V)
    0023 iconst_m1
    0024 istore 4
    0026 iconst_1
    0027 istore 5
    0029 iload 4
    0031 iload 5
    0033 invokestatic Method(InputKt.classify:(II)Ljava/lang/String;)
    0036 astore 6
    0038 getstatic Field(java/lang/System.out:Ljava/io/PrintStream;)
    0041 aload 6
    0043 invokevirtual Method(java/io/PrintStream.println:(Ljava/lang/String;)V)
    0046 iconst_m1
    0047 istore 7
    0049 iconst_m1
    0050 istore 8
    0052 iload 7
    0054 iload 8
    0056 invokestatic Method(InputKt.classify:(II)Ljava/lang/String;)
    0059 astore 9
    0061 getstatic Field(java/lang/System.out:Ljava/io/PrintStream;)
    0064 aload 9
    0066 invokevirtual Method(java/io/PrintStream.println:(Ljava/lang/String;)V)
    0069 iconst_1
    0070 istore 10
    0072 iconst_m1
    0073 istore 11
    0075 iload 10
    0077 iload 11
    0079 invokestatic Method(InputKt.classify:(II)Ljava/lang/String;)
    0082 astore 12
    0084 getstatic Field(java/lang/System.out:Ljava/io/PrintStream;)
    0087 aload 12
    0089 invokevirtual Method(java/io/PrintStream.println:(Ljava/lang/String;)V)
    0092 iconst_0
    0093 istore 13
    0095 iconst_5
    0096 istore 14
    0098 iload 13
    0100 iload 14
    0102 invokestatic Method(InputKt.classify:(II)Ljava/lang/String;)
    0105 astore 15
    0107 getstatic Field(java/lang/System.out:Ljava/io/PrintStream;)
    0110 aload 15
    0112 invokevirtual Method(java/io/PrintStream.println:(Ljava/lang/String;)V)
    0115 return
