class_version major=61 minor=0
this_class    test/InputKt
super_class   java/lang/Object
access_flags  0x0031
method        main ()V 0x0019
  code        max_stack=2 max_locals=0
    0000 new Class(test/Receiver)
    0003 dup
    0004 invokespecial Method(test/Receiver.<init>:()V)
    0007 invokestatic Method(test/InputKt.useReceiver:(Ltest/Receiver;)Ljava/lang/String;)
    0010 getstatic Field(java/lang/System.out:Ljava/io/PrintStream;)
    0013 swap
    0014 invokevirtual Method(java/io/PrintStream.println:(Ljava/lang/Object;)V)
    0017 return
method        main ([Ljava/lang/String;)V 0x1009
  code        max_stack=0 max_locals=1
    0000 invokestatic Method(test/InputKt.main:()V)
    0003 return
method        useReceiver (Ltest/Receiver;)Ljava/lang/String; 0x0019
  code        max_stack=7 max_locals=2
    0000 aload_0
    0001 ldc "r"
    0003 invokestatic Method(kotlin/jvm/internal/Intrinsics.checkNotNullParameter:(Ljava/lang/Object;Ljava/lang/String;)V)
    0006 new Class(test/InputKt$Lambda$1)
    0009 dup
    0010 invokespecial Method(test/InputKt$Lambda$1.<init>:()V)
    0013 pop
    0014 new Class(test/InputKt$Lambda$2)
    0017 dup
    0018 invokespecial Method(test/InputKt$Lambda$2.<init>:()V)
    0021 astore_1
    0022 aload_0
    0023 bipush 100
    0025 bipush 50
    0027 ldc ""
    0029 aload_1
    0030 checkcast Class(kotlin/jvm/functions/Function0)
    0033 iconst_4
    0034 aconst_null
    0035 invokestatic Method(test/Receiver.layout$default:(Ltest/Receiver;IILjava/lang/String;Lkotlin/jvm/functions/Function0;ILjava/lang/Object;)Ljava/lang/String;)
    0038 areturn
  attr        RuntimeInvisibleAnnotations (6 bytes)
  attr        RuntimeInvisibleParameterAnnotations (7 bytes)
class_attr    InnerClasses (18 bytes)
