class_version major=61 minor=0
this_class    InputKt
super_class   java/lang/Object
access_flags  0x0031
method        main ()V 0x0019
  code        max_stack=4 max_locals=0
    0000 getstatic Field(Color.Companion:LColor$Companion;)
    0003 invokevirtual Method(Color$Companion.white:()LColor;)
    0006 getstatic Field(java/lang/System.out:Ljava/io/PrintStream;)
    0009 swap
    0010 invokevirtual Method(java/io/PrintStream.println:(Ljava/lang/Object;)V)
    0013 getstatic Field(Color.Companion:LColor$Companion;)
    0016 invokevirtual Method(Color$Companion.black:()LColor;)
    0019 getstatic Field(java/lang/System.out:Ljava/io/PrintStream;)
    0022 swap
    0023 invokevirtual Method(java/io/PrintStream.println:(Ljava/lang/Object;)V)
    0026 getstatic Field(Color.Companion:LColor$Companion;)
    0029 sipush 128
    0032 invokevirtual Method(Color$Companion.gray:(I)LColor;)
    0035 getstatic Field(java/lang/System.out:Ljava/io/PrintStream;)
    0038 swap
    0039 invokevirtual Method(java/io/PrintStream.println:(Ljava/lang/Object;)V)
    0042 getstatic Field(Color.Companion:LColor$Companion;)
    0045 sipush 255
    0048 bipush 100
    0050 bipush 50
    0052 invokevirtual Method(Color$Companion.rgb:(III)LColor;)
    0055 getstatic Field(java/lang/System.out:Ljava/io/PrintStream;)
    0058 swap
    0059 invokevirtual Method(java/io/PrintStream.println:(Ljava/lang/Object;)V)
    0062 return
method        main ([Ljava/lang/String;)V 0x1009
  code        max_stack=0 max_locals=1
    0000 invokestatic Method(InputKt.main:()V)
    0003 return
class_attr    InnerClasses (10 bytes)
