class_version major=61 minor=0
this_class    InputKt
super_class   java/lang/Object
access_flags  0x0031
method        fetchData (Lkotlin/coroutines/Continuation;)Ljava/lang/Object; 0x0019
  code        max_stack=16 max_locals=32
    0000 aload_0
    0001 instanceof Class(InputKt$fetchData$1)
    0004 ifeq 40
    0007 aload_0
    0008 checkcast Class(InputKt$fetchData$1)
    0011 astore 6
    0013 aload 6
    0015 getfield Field(InputKt$fetchData$1.label:I)
    0018 ldc int(-2147483648)
    0020 iand
    0021 ifeq 40
    0024 aload 6
    0026 aload 6
    0028 getfield Field(InputKt$fetchData$1.label:I)
    0031 ldc int(-2147483648)
    0033 isub
    0034 putfield Field(InputKt$fetchData$1.label:I)
    0037 goto 50
    0040 new Class(InputKt$fetchData$1)
    0043 dup
    0044 aload_0
    0045 invokespecial Method(InputKt$fetchData$1.<init>:(Lkotlin/coroutines/Continuation;)V)
    0048 astore 6
    0050 aload 6
    0052 getfield Field(InputKt$fetchData$1.result:Ljava/lang/Object;)
    0055 astore 5
    0057 invokestatic Method(kotlin/coroutines/intrinsics/IntrinsicsKt.getCOROUTINE_SUSPENDED:()Ljava/lang/Object;)
    0060 astore 7
    0062 aload 6
    0064 getfield Field(InputKt$fetchData$1.label:I)
    0067 tableswitch default=135 low=0 high=1 0=88 1=118
    0088 aload 5
    0090 invokestatic Method(kotlin/ResultKt.throwOnFailure:(Ljava/lang/Object;)V)
    0093 ldc2_w long(10)
    0096 lstore_1
    0097 lload_1
    0098 aload 6
    0100 iconst_1
    0101 putfield Field(InputKt$fetchData$1.label:I)
    0104 aload 6
    0106 invokestatic Method(kotlinx/coroutines/DelayKt.delay:(JLkotlin/coroutines/Continuation;)Ljava/lang/Object;)
    0109 dup
    0110 aload 7
    0112 if_acmpne 125
    0115 aload 7
    0117 areturn
    0118 aload 5
    0120 invokestatic Method(kotlin/ResultKt.throwOnFailure:(Ljava/lang/Object;)V)
    0123 aload 5
    0125 pop
    0126 aconst_null
    0127 astore_3
    0128 ldc "data"
    0130 astore 4
    0132 aload 4
    0134 areturn
    0135 new Class(java/lang/IllegalStateException)
    0138 dup
    0139 ldc "call to 'resume' before 'invoke' with coroutine"
    0141 invokespecial Method(java/lang/IllegalStateException.<init>:(Ljava/lang/String;)V)
    0144 athrow
    sub_attr  StackMapTable (125 bytes)
  attr        Signature (2 bytes)
  attr        RuntimeInvisibleAnnotations (6 bytes)
  attr        RuntimeInvisibleParameterAnnotations (7 bytes)
method        main ()V 0x0019
  code        max_stack=4 max_locals=1
    0000 new Class(InputKt$Lambda$0)
    0003 dup
    0004 aconst_null
    0005 invokespecial Method(InputKt$Lambda$0.<init>:(Lkotlin/coroutines/Continuation;)V)
    0008 checkcast Class(kotlin/jvm/functions/Function2)
    0011 aconst_null
    0012 swap
    0013 iconst_1
    0014 aconst_null
    0015 invokestatic Method(kotlinx/coroutines/BuildersKt.runBlocking$default:(Lkotlin/coroutines/CoroutineContext;Lkotlin/jvm/functions/Function2;ILjava/lang/Object;)Ljava/lang/Object;)
    0018 astore_0
    0019 return
method        main ([Ljava/lang/String;)V 0x1009
  code        max_stack=0 max_locals=1
    0000 invokestatic Method(InputKt.main:()V)
    0003 return
method        processData (Lkotlin/coroutines/Continuation;)Ljava/lang/Object; 0x0019
  code        max_stack=16 max_locals=32
    0000 aload_0
    0001 instanceof Class(InputKt$processData$1)
    0004 ifeq 40
    0007 aload_0
    0008 checkcast Class(InputKt$processData$1)
    0011 astore 5
    0013 aload 5
    0015 getfield Field(InputKt$processData$1.label:I)
    0018 ldc int(-2147483648)
    0020 iand
    0021 ifeq 40
    0024 aload 5
    0026 aload 5
    0028 getfield Field(InputKt$processData$1.label:I)
    0031 ldc int(-2147483648)
    0033 isub
    0034 putfield Field(InputKt$processData$1.label:I)
    0037 goto 50
    0040 new Class(InputKt$processData$1)
    0043 dup
    0044 aload_0
    0045 invokespecial Method(InputKt$processData$1.<init>:(Lkotlin/coroutines/Continuation;)V)
    0048 astore 5
    0050 aload 5
    0052 getfield Field(InputKt$processData$1.result:Ljava/lang/Object;)
    0055 astore 4
    0057 invokestatic Method(kotlin/coroutines/intrinsics/IntrinsicsKt.getCOROUTINE_SUSPENDED:()Ljava/lang/Object;)
    0060 astore 6
    0062 aload 5
    0064 getfield Field(InputKt$processData$1.label:I)
    0067 tableswitch default=141 low=0 high=1 0=88 1=113
    0088 aload 4
    0090 invokestatic Method(kotlin/ResultKt.throwOnFailure:(Ljava/lang/Object;)V)
    0093 aload 5
    0095 iconst_1
    0096 putfield Field(InputKt$processData$1.label:I)
    0099 aload 5
    0101 invokestatic Method(InputKt.fetchData:(Lkotlin/coroutines/Continuation;)Ljava/lang/Object;)
    0104 dup
    0105 aload 6
    0107 if_acmpne 120
    0110 aload 6
    0112 areturn
    0113 aload 4
    0115 invokestatic Method(kotlin/ResultKt.throwOnFailure:(Ljava/lang/Object;)V)
    0118 aload 4
    0120 checkcast Class(java/lang/String)
    0123 astore_1
    0124 ldc "processed: "
    0126 astore_2
    0127 aload_2
    0128 checkcast Class(java/lang/String)
    0131 aload_1
    0132 invokestatic Method(java/lang/String.valueOf:(Ljava/lang/Object;)Ljava/lang/String;)
    0135 invokevirtual Method(java/lang/String.concat:(Ljava/lang/String;)Ljava/lang/String;)
    0138 astore_3
    0139 aload_3
    0140 areturn
    0141 new Class(java/lang/IllegalStateException)
    0144 dup
    0145 ldc "call to 'resume' before 'invoke' with coroutine"
    0147 invokespecial Method(java/lang/IllegalStateException.<init>:(Ljava/lang/String;)V)
    0150 athrow
    sub_attr  StackMapTable (120 bytes)
  attr        Signature (2 bytes)
  attr        RuntimeInvisibleAnnotations (6 bytes)
  attr        RuntimeInvisibleParameterAnnotations (7 bytes)
class_attr    InnerClasses (26 bytes)
