class_version major=61 minor=0
this_class    Rect
super_class   Shape
access_flags  0x0021
field         h : I 0x0001
field         w : I 0x0001
method        <init> (II)V 0x0001
  code        max_stack=2 max_locals=3
    0000 aload_0
    0001 invokespecial Method(Shape.<init>:()V)
    0004 aload_0
    0005 iload_1
    0006 putfield Field(Rect.w:I)
    0009 aload_0
    0010 iload_2
    0011 putfield Field(Rect.h:I)
    0014 return
method        area ()I 0x0001
  code        max_stack=3 max_locals=3
    0000 aload_0
    0001 getfield Field(Rect.w:I)
    0004 istore_1
    0005 aload_0
    0006 getfield Field(Rect.h:I)
    0009 istore_2
    0010 iload_1
    0011 iload_2
    0012 imul
    0013 aload_0
    0014 iload_1
    0015 putfield Field(Rect.w:I)
    0018 aload_0
    0019 iload_2
    0020 putfield Field(Rect.h:I)
    0023 ireturn
method        getH ()I 0x0001
  code        max_stack=1 max_locals=1
    0000 aload_0
    0001 getfield Field(Rect.h:I)
    0004 ireturn
method        getW ()I 0x0001
  code        max_stack=1 max_locals=1
    0000 aload_0
    0001 getfield Field(Rect.w:I)
    0004 ireturn
