class_version major=61 minor=0
this_class    Failure
super_class   Result
access_flags  0x0021
field         error : Ljava/lang/String; 0x0001
method        <init> (Ljava/lang/String;)V 0x0001
  code        max_stack=2 max_locals=2
    0000 aload_0
    0001 invokespecial Method(Result.<init>:()V)
    0004 aload_0
    0005 aload_1
    0006 putfield Field(Failure.error:Ljava/lang/String;)
    0009 return
method        getError ()Ljava/lang/String; 0x0001
  code        max_stack=1 max_locals=1
    0000 aload_0
    0001 getfield Field(Failure.error:Ljava/lang/String;)
    0004 areturn
  attr        RuntimeInvisibleAnnotations (6 bytes)
