class_version major=61 minor=0
this_class    InputKt
super_class   java/lang/Object
access_flags  0x0031
method        main ([Ljava/lang/String;)V 0x0009
  code        max_stack=5 max_locals=21
    0000 bipush -5
    0002 istore 1
    0004 iload 1
    0006 invokestatic Method(java/lang/Math.abs:(I)I)
    0009 istore 2
    0011 getstatic Field(java/lang/System.out:Ljava/io/PrintStream;)
    0014 iload 2
    0016 invokevirtual Method(java/io/PrintStream.println:(I)V)
    0019 op_0x14
    0020 nop
    0021 iload_2
    0022 op_0x39
    0023 iconst_0
    0024 op_0x18
    0025 iconst_0
    0026 invokestatic Method(java/lang/Math.sqrt:(D)D)
    0029 op_0x39
    0030 iconst_2
    0031 getstatic Field(java/lang/System.out:Ljava/io/PrintStream;)
    0034 op_0x18
    0035 iconst_2
    0036 invokevirtual Method(java/io/PrintStream.println:(D)V)
    0039 op_0x14
    0040 nop
    0041 op_0x25
    0042 op_0x39
    0043 iconst_4
    0044 op_0x18
    0045 iconst_4
    0046 invokestatic Method(java/lang/Math.ceil:(D)D)
    0049 op_0x39
    0050 op_0x09
    0051 getstatic Field(java/lang/System.out:Ljava/io/PrintStream;)
    0054 op_0x18
    0055 op_0x09
    0056 invokevirtual Method(java/io/PrintStream.println:(D)V)
    0059 op_0x14
    0060 nop
    0061 aload_0
    0062 op_0x39
    0063 op_0x0B
    0064 op_0x18
    0065 op_0x0B
    0066 invokestatic Method(java/lang/Math.floor:(D)D)
    0069 op_0x39
    0070 op_0x0D
    0071 getstatic Field(java/lang/System.out:Ljava/io/PrintStream;)
    0074 op_0x18
    0075 op_0x0D
    0076 invokevirtual Method(java/io/PrintStream.println:(D)V)
    0079 bipush 10
    0081 istore 15
    0083 bipush 20
    0085 istore 16
    0087 iload 15
    0089 iload 16
    0091 invokestatic Method(java/lang/Math.max:(II)I)
    0094 istore 17
    0096 getstatic Field(java/lang/System.out:Ljava/io/PrintStream;)
    0099 iload 17
    0101 invokevirtual Method(java/io/PrintStream.println:(I)V)
    0104 bipush 10
    0106 istore 18
    0108 bipush 20
    0110 istore 19
    0112 iload 18
    0114 iload 19
    0116 invokestatic Method(java/lang/Math.min:(II)I)
    0119 istore 20
    0121 getstatic Field(java/lang/System.out:Ljava/io/PrintStream;)
    0124 iload 20
    0126 invokevirtual Method(java/io/PrintStream.println:(I)V)
    0129 return
