class_version major=61 minor=0
this_class    InputKt
super_class   java/lang/Object
access_flags  0x0031
method        factorial (I)I 0x0009
  code        max_stack=2 max_locals=13
    0000 iconst_1
    0001 istore 1
    0003 iload 1
    0005 istore 2
    0007 iconst_2
    0008 istore 3
    0010 iload 0
    0012 istore 4
    0014 iload 3
    0016 istore 5
    0018 op_0xA7
    0019 nop
    0020 iconst_0
    0021 iload 5
    0023 iload 4
    0025 op_0xA4
    0026 nop
    0027 iconst_4
    0028 iconst_0
    0029 op_0xA7
    0030 nop
    0031 iconst_1
    0032 iconst_1
    0033 istore 6
    0035 iload 6
    0037 op_0x99
    0038 nop
    0039 op_0x2A
    0040 iload 2
    0042 istore 7
    0044 iload 5
    0046 istore 8
    0048 iload 7
    0050 iload 8
    0052 imul
    0053 istore 9
    0055 iload 9
    0057 istore 2
    0059 op_0xA7
    0060 nop
    0061 iconst_0
    0062 iconst_1
    0063 istore 10
    0065 iload 5
    0067 iload 10
    0069 iadd
    0070 istore 11
    0072 iload 11
    0074 istore 5
    0076 op_0xA7
    0077 op_0xFF
    0078 op_0xC9
    0079 iload 2
    0081 istore 12
    0083 iload 12
    0085 op_0xAC
    sub_attr  StackMapTable (73 bytes)
method        isPrime (I)Z 0x0009
  code        max_stack=5 max_locals=22
    0000 iload 0
    0002 istore 1
    0004 iconst_2
    0005 istore 2
    0007 iload 1
    0009 iload 2
    0011 op_0xA1
    0012 nop
    0013 iconst_4
    0014 iconst_0
    0015 op_0xA7
    0016 nop
    0017 iconst_1
    0018 iconst_1
    0019 istore 3
    0021 iload 3
    0023 op_0x99
    0024 nop
    0025 op_0x09
    0026 iconst_0
    0027 istore 4
    0029 iload 4
    0031 op_0xAC
    0032 op_0xA7
    0033 nop
    0034 iconst_0
    0035 iconst_2
    0036 istore 5
    0038 iload 5
    0040 istore 6
    0042 op_0xA7
    0043 nop
    0044 iconst_0
    0045 iload 6
    0047 istore 7
    0049 iload 6
    0051 istore 8
    0053 iload 7
    0055 iload 8
    0057 imul
    0058 istore 9
    0060 iload 0
    0062 istore 10
    0064 iload 9
    0066 iload 10
    0068 op_0xA4
    0069 nop
    0070 iconst_4
    0071 iconst_0
    0072 op_0xA7
    0073 nop
    0074 iconst_1
    0075 iconst_1
    0076 istore 11
    0078 iload 11
    0080 op_0x99
    0081 nop
    0082 op_0x2B
    0083 iload 0
    0085 istore 12
    0087 iload 6
    0089 istore 13
    0091 iload 12
    0093 iload 13
    0095 irem
    0096 istore 14
    0098 iconst_0
    0099 istore 15
    0101 iload 14
    0103 iload 15
    0105 op_0x9F
    0106 nop
    0107 iconst_4
    0108 iconst_0
    0109 op_0xA7
    0110 nop
    0111 iconst_1
    0112 iconst_1
    0113 istore 16
    0115 iload 16
    0117 op_0x99
    0118 nop
    0119 ldc #167
    0121 nop
    0122 op_0x09
    0123 iconst_1
    0124 istore 17
    0126 iload 17
    0128 op_0xAC
    0129 iconst_0
    0130 istore 18
    0132 iload 18
    0134 op_0xAC
    0135 op_0xA7
    0136 nop
    0137 iconst_0
    0138 iload 6
    0140 istore 19
    0142 iconst_1
    0143 istore 20
    0145 iload 19
    0147 iload 20
    0149 iadd
    0150 istore 21
    0152 iload 21
    0154 istore 6
    0156 op_0xA7
    0157 op_0xFF
    0158 op_0x91
    sub_attr  StackMapTable (234 bytes)
method        main ([Ljava/lang/String;)V 0x0009
  code        max_stack=2 max_locals=18
    0000 iconst_2
    0001 istore 1
    0003 bipush 20
    0005 istore 2
    0007 iload 1
    0009 istore 3
    0011 op_0xA7
    0012 nop
    0013 iconst_0
    0014 iload 3
    0016 iload 2
    0018 op_0xA4
    0019 nop
    0020 iconst_4
    0021 iconst_0
    0022 op_0xA7
    0023 nop
    0024 iconst_1
    0025 iconst_1
    0026 istore 4
    0028 iload 4
    0030 op_0x99
    0031 nop
    0032 op_0x27
    0033 iload 3
    0035 istore 5
    0037 iload 5
    0039 invokestatic Method(InputKt.isPrime:(I)Z)
    0042 istore 6
    0044 iload 6
    0046 op_0x99
    0047 nop
    0048 astore 167
    0050 nop
    0051 op_0x28
    0052 iconst_1
    0053 istore 7
    0055 iload 3
    0057 iload 7
    0059 iadd
    0060 istore 8
    0062 iload 8
    0064 istore 3
    0066 op_0xA7
    0067 op_0xFF
    0068 op_0xCC
    0069 getstatic Field(java/lang/System.out:Ljava/io/PrintStream;)
    0072 invokevirtual Method(java/io/PrintStream.println:()V)
    0075 iconst_1
    0076 istore 9
    0078 bipush 7
    0080 istore 10
    0082 iload 9
    0084 istore 11
    0086 op_0xA7
    0087 nop
    0088 op_0x18
    0089 iload 3
    0091 istore 12
    0093 getstatic Field(java/lang/System.out:Ljava/io/PrintStream;)
    0096 iload 12
    0098 invokevirtual Method(java/io/PrintStream.println:(I)V)
    0101 op_0xA7
    0102 nop
    0103 iconst_3
    0104 op_0xA7
    0105 nop
    0106 iconst_0
    0107 op_0xA7
    0108 op_0xFF
    0109 op_0xC9
    0110 iload 11
    0112 iload 10
    0114 op_0xA4
    0115 nop
    0116 iconst_4
    0117 iconst_0
    0118 op_0xA7
    0119 nop
    0120 iconst_1
    0121 iconst_1
    0122 istore 13
    0124 iload 13
    0126 op_0x99
    0127 nop
    0128 op_0x2A
    0129 iload 11
    0131 istore 14
    0133 iload 14
    0135 invokestatic Method(InputKt.factorial:(I)I)
    0138 istore 15
    0140 getstatic Field(java/lang/System.out:Ljava/io/PrintStream;)
    0143 iload 15
    0145 invokevirtual Method(java/io/PrintStream.println:(I)V)
    0148 op_0xA7
    0149 nop
    0150 iconst_0
    0151 iconst_1
    0152 istore 16
    0154 iload 11
    0156 iload 16
    0158 iadd
    0159 istore 17
    0161 iload 17
    0163 istore 11
    0165 op_0xA7
    0166 op_0xFF
    0167 op_0xC9
    0168 return
    sub_attr  StackMapTable (232 bytes)
