class_version major=61 minor=0
this_class    InputKt
super_class   java/lang/Object
access_flags  0x0031
method        main ()V 0x0019
<<<<<<< Updated upstream
  code        max_stack=3 max_locals=3
    0000 goto 3
    0003 new Class(java/lang/IllegalArgumentException)
    0006 dup
    0007 ldc "test"
    0009 invokespecial Method(java/lang/IllegalArgumentException.<init>:(Ljava/lang/String;)V)
    0012 astore_0
    0013 aload_0
    0014 athrow
    0015 astore_1
    0016 aconst_null
    0017 invokevirtual Method(java/lang/IllegalArgumentException.getMessage:()Ljava/lang/String;)
    0020 astore_2
    0021 aload_2
    0022 op_0xBA
    0023 nop
    0024 lload_0
    0025 nop
    0026 nop
    0027 getstatic Field(java/lang/System.out:Ljava/io/PrintStream;)
    0030 swap
    0031 invokevirtual Method(java/io/PrintStream.println:(Ljava/lang/Object;)V)
    0034 goto 37
    0037 return
    sub_attr  StackMapTable (17 bytes)
=======
  code        max_stack=3 max_locals=5
    0000 ldc "test"
    0002 astore_0
    0003 new Class(java/lang/IllegalArgumentException)
    0006 dup
    0007 aload_0
    0008 invokespecial Method(java/lang/IllegalArgumentException.<init>:(Ljava/lang/String;)V)
    0011 astore_1
    0012 aload_1
    0013 athrow
    0014 astore_2
    0015 ldc "caught IAE: "
    0017 astore_3
    0018 aload_2
    0019 invokevirtual Method(java/lang/IllegalArgumentException.getMessage:()Ljava/lang/String;)
    0022 astore 4
    0024 aload_3
    0025 aload 4
    0027 op_0xBA
    0028 nop
    0029 lload_2
    0030 nop
    0031 nop
    0032 getstatic Field(java/lang/System.out:Ljava/io/PrintStream;)
    0035 swap
    0036 invokevirtual Method(java/io/PrintStream.println:(Ljava/lang/Object;)V)
    0039 return
    sub_attr  StackMapTable (6 bytes)
>>>>>>> Stashed changes
method        main ([Ljava/lang/String;)V 0x1009
  code        max_stack=0 max_locals=1
    0000 invokestatic Method(InputKt.main:()V)
    0003 return
class_attr    BootstrapMethods (8 bytes)
