class_version major=61 minor=0
this_class    InputKt
super_class   java/lang/Object
access_flags  0x0031
field         items : Ljava/util/List; 0x001A
field         tags : Ljava/util/Set; 0x001A
method        <clinit> ()V 0x0008
  code        max_stack=3 max_locals=2
    0000 iconst_3
    0001 anewarray Class(java/lang/String)
    0004 astore_0
    0005 aload_0
    0006 iconst_0
    0007 ldc "x"
    0009 aastore
    0010 aload_0
    0011 iconst_1
    0012 ldc "y"
    0014 aastore
    0015 aload_0
    0016 iconst_2
    0017 ldc "z"
    0019 aastore
    0020 aload_0
    0021 invokestatic Method(kotlin/collections/CollectionsKt.listOf:([Ljava/lang/Object;)Ljava/util/List;)
    0024 putstatic Field(InputKt.items:Ljava/util/List;)
    0027 iconst_2
    0028 anewarray Class(java/lang/Integer)
    0031 astore_0
    0032 iconst_1
    0033 invokestatic Method(java/lang/Integer.valueOf:(I)Ljava/lang/Integer;)
    0036 astore_1
    0037 aload_0
    0038 iconst_0
    0039 aload_1
    0040 aastore
    0041 iconst_2
    0042 invokestatic Method(java/lang/Integer.valueOf:(I)Ljava/lang/Integer;)
    0045 astore_1
    0046 aload_0
    0047 iconst_1
    0048 aload_1
    0049 aastore
    0050 aload_0
    0051 invokestatic Method(kotlin/collections/SetsKt.setOf:([Ljava/lang/Object;)Ljava/util/Set;)
    0054 putstatic Field(InputKt.tags:Ljava/util/Set;)
    0057 return
method        getItems ()Ljava/util/List; 0x0019
  code        max_stack=1 max_locals=0
    0000 getstatic Field(InputKt.items:Ljava/util/List;)
    0003 areturn
  attr        Signature (2 bytes)
  attr        RuntimeInvisibleAnnotations (6 bytes)
method        getTags ()Ljava/util/Set; 0x0019
  code        max_stack=1 max_locals=0
    0000 getstatic Field(InputKt.tags:Ljava/util/Set;)
    0003 areturn
  attr        Signature (2 bytes)
  attr        RuntimeInvisibleAnnotations (6 bytes)
method        main ()V 0x0019
  code        max_stack=2 max_locals=0
    0000 getstatic Field(InputKt.items:Ljava/util/List;)
    0003 getstatic Field(java/lang/System.out:Ljava/io/PrintStream;)
    0006 swap
    0007 invokevirtual Method(java/io/PrintStream.println:(Ljava/lang/Object;)V)
    0010 getstatic Field(InputKt.tags:Ljava/util/Set;)
    0013 getstatic Field(java/lang/System.out:Ljava/io/PrintStream;)
    0016 swap
    0017 invokevirtual Method(java/io/PrintStream.println:(Ljava/lang/Object;)V)
    0020 return
method        main ([Ljava/lang/String;)V 0x1009
  code        max_stack=0 max_locals=1
    0000 invokestatic Method(InputKt.main:()V)
    0003 return
