class_version major=61 minor=0
this_class    InputKt
super_class   java/lang/Object
access_flags  0x0031
method        main ()V 0x0019
  code        max_stack=3 max_locals=2
    0000 new Class(Add)
    0003 dup
    0004 iconst_3
    0005 invokespecial Method(Add.<init>:(I)V)
    0008 checkcast Class(Op)
    0011 astore_0
    0012 new Class(Sub)
    0015 dup
    0016 bipush 7
    0018 invokespecial Method(Sub.<init>:(I)V)
    0021 checkcast Class(Op)
    0024 astore_1
    0025 aload_0
    0026 invokestatic Method(InputKt.negate:(LOp;)LOp;)
    0029 invokeinterface InterfaceMethod(Op.label:()Ljava/lang/String;)
    0034 getstatic Field(java/lang/System.out:Ljava/io/PrintStream;)
    0037 swap
    0038 invokevirtual Method(java/io/PrintStream.println:(Ljava/lang/Object;)V)
    0041 aload_1
    0042 invokestatic Method(InputKt.negate:(LOp;)LOp;)
    0045 invokeinterface InterfaceMethod(Op.label:()Ljava/lang/String;)
    0050 getstatic Field(java/lang/System.out:Ljava/io/PrintStream;)
    0053 swap
    0054 invokevirtual Method(java/io/PrintStream.println:(Ljava/lang/Object;)V)
    0057 getstatic Field(Noop.INSTANCE:LNoop;)
    0060 checkcast Class(Op)
    0063 invokestatic Method(InputKt.negate:(LOp;)LOp;)
    0066 invokeinterface InterfaceMethod(Op.label:()Ljava/lang/String;)
    0071 getstatic Field(java/lang/System.out:Ljava/io/PrintStream;)
    0074 swap
    0075 invokevirtual Method(java/io/PrintStream.println:(Ljava/lang/Object;)V)
    0078 iconst_1
    0079 bipush 9
    0081 invokestatic Method(InputKt.pickIfElse:(ZI)LOp;)
    0084 invokeinterface InterfaceMethod(Op.label:()Ljava/lang/String;)
    0089 getstatic Field(java/lang/System.out:Ljava/io/PrintStream;)
    0092 swap
    0093 invokevirtual Method(java/io/PrintStream.println:(Ljava/lang/Object;)V)
    0096 iconst_0
    0097 bipush 9
    0099 invokestatic Method(InputKt.pickIfElse:(ZI)LOp;)
    0102 invokeinterface InterfaceMethod(Op.label:()Ljava/lang/String;)
    0107 getstatic Field(java/lang/System.out:Ljava/io/PrintStream;)
    0110 swap
    0111 invokevirtual Method(java/io/PrintStream.println:(Ljava/lang/Object;)V)
    0114 return
method        main ([Ljava/lang/String;)V 0x1009
  code        max_stack=0 max_locals=1
    0000 invokestatic Method(InputKt.main:()V)
    0003 return
method        negate (LOp;)LOp; 0x0019
  code        max_stack=3 max_locals=2
    0000 aload_0
    0001 ldc "o"
    0003 invokestatic Method(kotlin/jvm/internal/Intrinsics.checkNotNullParameter:(Ljava/lang/Object;Ljava/lang/String;)V)
    0006 aload_0
    0007 astore_1
    0008 aload_1
    0009 instanceof Class(Add)
    0012 ifeq 35
    0015 new Class(Sub)
    0018 dup
    0019 aload_0
    0020 checkcast Class(Add)
    0023 invokevirtual Method(Add.getV:()I)
    0026 invokespecial Method(Sub.<init>:(I)V)
    0029 checkcast Class(Op)
    0032 goto 86
    0035 aload_1
    0036 instanceof Class(Sub)
    0039 ifeq 62
    0042 new Class(Add)
    0045 dup
    0046 aload_0
    0047 checkcast Class(Sub)
    0050 invokevirtual Method(Sub.getV:()I)
    0053 invokespecial Method(Add.<init>:(I)V)
    0056 checkcast Class(Op)
    0059 goto 86
    0062 aload_1
    0063 instanceof Class(Noop)
    0066 ifeq 78
    0069 getstatic Field(Noop.INSTANCE:LNoop;)
    0072 checkcast Class(Op)
    0075 goto 86
    0078 new Class(kotlin/NoWhenBranchMatchedException)
    0081 dup
    0082 invokespecial Method(kotlin/NoWhenBranchMatchedException.<init>:()V)
    0085 athrow
    0086 areturn
    sub_attr  StackMapTable (14 bytes)
  attr        RuntimeInvisibleAnnotations (6 bytes)
  attr        RuntimeInvisibleParameterAnnotations (7 bytes)
method        pickIfElse (ZI)LOp; 0x0019
  code        max_stack=3 max_locals=2
    0000 iload_0
    0001 ifeq 18
    0004 new Class(Add)
    0007 dup
    0008 iload_1
    0009 invokespecial Method(Add.<init>:(I)V)
    0012 checkcast Class(Op)
    0015 goto 24
    0018 getstatic Field(Noop.INSTANCE:LNoop;)
    0021 checkcast Class(Op)
    0024 areturn
    sub_attr  StackMapTable (7 bytes)
  attr        RuntimeInvisibleAnnotations (6 bytes)
