class_version major=61 minor=0
this_class    InputKt
super_class   java/lang/Object
access_flags  0x0031
method        describe (LResult;)Ljava/lang/String; 0x0019
  code        max_stack=2 max_locals=9
    0000 aload_0
    0001 ldc "r"
    0003 invokestatic Method(kotlin/jvm/internal/Intrinsics.checkNotNullParameter:(Ljava/lang/Object;Ljava/lang/String;)V)
    0006 aload_0
    0007 instanceof Class(Ok)
    0010 istore_1
    0011 iload_1
    0012 ifeq 29
    0015 aload_0
    0016 checkcast Class(Ok)
    0019 astore_2
    0020 ldc "ok"
    0022 astore_3
    0023 aload_3
    0024 astore 4
    0026 goto 65
    0029 aload_0
    0030 instanceof Class(Err)
    0033 istore 5
    0035 iload 5
    0037 ifeq 57
    0040 aload_0
    0041 checkcast Class(Err)
    0044 astore 6
    0046 ldc "err"
    0048 astore 7
    0050 aload 7
    0052 astore 4
    0054 goto 65
    0057 ldc "unknown"
    0059 astore 8
    0061 aload 8
    0063 astore 4
    0065 aload 4
    0067 areturn
    sub_attr  StackMapTable (20 bytes)
  attr        RuntimeInvisibleAnnotations (6 bytes)
  attr        RuntimeInvisibleParameterAnnotations (7 bytes)
method        main ()V 0x0019
  code        max_stack=3 max_locals=0
    0000 new Class(Ok)
    0003 dup
    0004 bipush 42
    0006 invokespecial Method(Ok.<init>:(I)V)
    0009 checkcast Class(Result)
    0012 invokestatic Method(InputKt.describe:(LResult;)Ljava/lang/String;)
    0015 getstatic Field(java/lang/System.out:Ljava/io/PrintStream;)
    0018 swap
    0019 invokevirtual Method(java/io/PrintStream.println:(Ljava/lang/Object;)V)
    0022 new Class(Err)
    0025 dup
    0026 ldc "fail"
    0028 invokespecial Method(Err.<init>:(Ljava/lang/String;)V)
    0031 checkcast Class(Result)
    0034 invokestatic Method(InputKt.describe:(LResult;)Ljava/lang/String;)
    0037 getstatic Field(java/lang/System.out:Ljava/io/PrintStream;)
    0040 swap
    0041 invokevirtual Method(java/io/PrintStream.println:(Ljava/lang/Object;)V)
    0044 return
method        main ([Ljava/lang/String;)V 0x1009
  code        max_stack=0 max_locals=1
    0000 invokestatic Method(InputKt.main:()V)
    0003 return
