class_version major=61 minor=0
this_class    InputKt
super_class   java/lang/Object
access_flags  0x0031
method        greetByLang (Ljava/lang/String;)Ljava/lang/String; 0x0019
  code        max_stack=2 max_locals=2
    0000 op_0x2A
    0001 ldc "lang"
    0003 invokestatic Method(kotlin/jvm/internal/Intrinsics.checkNotNullParameter:(Ljava/lang/Object;Ljava/lang/String;)V)
    0006 op_0x2A
    0007 op_0x4C
    0008 op_0x2B
    0009 invokevirtual Method(java/lang/String.hashCode:()I)
    0012 op_0xAB
    0013 nop
    0014 nop
    0015 nop
    0016 nop
    0017 nop
    0018 nop
    0019 irem
    0020 nop
    0021 nop
    0022 nop
    0023 iconst_1
    0024 nop
    0025 nop
    0026 op_0x0C
    0027 op_0x81
    0028 nop
    0029 nop
    0030 nop
    0031 op_0x2C
    0032 nop
    0033 nop
    0034 op_0x0C
    0035 op_0xA9
    0036 nop
    0037 nop
    0038 nop
    0039 op_0x38
    0040 nop
    0041 nop
    0042 op_0x0C
    0043 op_0xAE
    0044 nop
    0045 nop
    0046 nop
    0047 op_0x50
    0048 nop
    0049 nop
    0050 op_0x0C
    0051 op_0xCC
    0052 nop
    0053 nop
    0054 nop
    0055 op_0x44
    0056 op_0x2B
    0057 ldc "de"
    0059 invokevirtual Method(java/lang/String.equals:(Ljava/lang/Object;)Z)
    0062 op_0x9A
    0063 nop
    0064 op_0x39
    0065 op_0xA7
    0066 nop
    0067 op_0x3B
    0068 op_0x2B
    0069 ldc "en"
    0071 invokevirtual Method(java/lang/String.equals:(Ljava/lang/Object;)Z)
    0074 op_0x9A
    0075 nop
    0076 op_0x1E
    0077 op_0xA7
    0078 nop
    0079 op_0x2F
    0080 op_0x2B
    0081 ldc "fr"
    0083 invokevirtual Method(java/lang/String.equals:(Ljava/lang/Object;)Z)
    0086 op_0x9A
    0087 nop
    0088 op_0x1C
    0089 op_0xA7
    0090 nop
    0091 op_0x23
    0092 op_0x2B
    0093 ldc "es"
    0095 invokevirtual Method(java/lang/String.equals:(Ljava/lang/Object;)Z)
    0098 op_0x9A
    0099 nop
    0100 op_0x0B
    0101 op_0xA7
    0102 nop
    0103 op_0x17
    0104 ldc "Hello"
    0106 op_0xA7
    0107 nop
    0108 op_0x14
    0109 ldc "Hola"
    0111 op_0xA7
    0112 nop
    0113 op_0x0F
    0114 ldc "Bonjour"
    0116 op_0xA7
    0117 nop
    0118 op_0x0A
    0119 ldc "Hallo"
    0121 op_0xA7
    0122 nop
    0123 iconst_2
    0124 ldc "Hi"
    0126 op_0xB0
    sub_attr  StackMapTable (20 bytes)
  attr        RuntimeInvisibleAnnotations (6 bytes)
  attr        RuntimeInvisibleParameterAnnotations (7 bytes)
method        main ()V 0x0019
  code        max_stack=2 max_locals=0
    0000 ldc "en"
    0002 invokestatic Method(InputKt.greetByLang:(Ljava/lang/String;)Ljava/lang/String;)
    0005 getstatic Field(java/lang/System.out:Ljava/io/PrintStream;)
    0008 op_0x5F
    0009 invokevirtual Method(java/io/PrintStream.println:(Ljava/lang/Object;)V)
    0012 ldc "es"
    0014 invokestatic Method(InputKt.greetByLang:(Ljava/lang/String;)Ljava/lang/String;)
    0017 getstatic Field(java/lang/System.out:Ljava/io/PrintStream;)
    0020 op_0x5F
    0021 invokevirtual Method(java/io/PrintStream.println:(Ljava/lang/Object;)V)
    0024 ldc "fr"
    0026 invokestatic Method(InputKt.greetByLang:(Ljava/lang/String;)Ljava/lang/String;)
    0029 getstatic Field(java/lang/System.out:Ljava/io/PrintStream;)
    0032 op_0x5F
    0033 invokevirtual Method(java/io/PrintStream.println:(Ljava/lang/Object;)V)
    0036 ldc "de"
    0038 invokestatic Method(InputKt.greetByLang:(Ljava/lang/String;)Ljava/lang/String;)
    0041 getstatic Field(java/lang/System.out:Ljava/io/PrintStream;)
    0044 op_0x5F
    0045 invokevirtual Method(java/io/PrintStream.println:(Ljava/lang/Object;)V)
    0048 ldc "ja"
    0050 invokestatic Method(InputKt.greetByLang:(Ljava/lang/String;)Ljava/lang/String;)
    0053 getstatic Field(java/lang/System.out:Ljava/io/PrintStream;)
    0056 op_0x5F
    0057 invokevirtual Method(java/io/PrintStream.println:(Ljava/lang/Object;)V)
    0060 return
method        main ([Ljava/lang/String;)V 0x1009
  code        max_stack=0 max_locals=1
    0000 invokestatic Method(InputKt.main:()V)
    0003 return
