class_version major=61 minor=0
this_class    InputKt
super_class   java/lang/Object
access_flags  0x0031
method        greetByLang (Ljava/lang/String;)Ljava/lang/String; 0x0019
  code        max_stack=2 max_locals=11
    0000 aload_0
    0001 ldc "lang"
    0003 invokestatic Method(kotlin/jvm/internal/Intrinsics.checkNotNullParameter:(Ljava/lang/Object;Ljava/lang/String;)V)
<<<<<<< Updated upstream
    0006 aload_0
    0007 ldc "en"
    0009 invokestatic Method(kotlin/jvm/internal/Intrinsics.areEqual:(Ljava/lang/Object;Ljava/lang/Object;)Z)
    0012 istore_1
    0013 iload_1
    0014 ifeq 25
    0017 ldc "Hello"
    0019 astore_2
    0020 aload_2
    0021 astore_3
    0022 goto 101
    0025 aload_0
    0026 ldc "es"
    0028 invokestatic Method(kotlin/jvm/internal/Intrinsics.areEqual:(Ljava/lang/Object;Ljava/lang/Object;)Z)
    0031 istore 4
    0033 iload 4
    0035 ifeq 48
    0038 ldc "Hola"
    0040 astore 5
    0042 aload 5
    0044 astore_3
    0045 goto 101
    0048 aload_0
    0049 ldc "fr"
    0051 invokestatic Method(kotlin/jvm/internal/Intrinsics.areEqual:(Ljava/lang/Object;Ljava/lang/Object;)Z)
    0054 istore 6
    0056 iload 6
    0058 ifeq 71
    0061 ldc "Bonjour"
    0063 astore 7
    0065 aload 7
    0067 astore_3
    0068 goto 101
    0071 aload_0
    0072 ldc "de"
    0074 invokestatic Method(kotlin/jvm/internal/Intrinsics.areEqual:(Ljava/lang/Object;Ljava/lang/Object;)Z)
    0077 istore 8
    0079 iload 8
    0081 ifeq 94
    0084 ldc "Hallo"
    0086 astore 9
    0088 aload 9
    0090 astore_3
    0091 goto 101
    0094 ldc "Hi"
    0096 astore 10
    0098 aload 10
    0100 astore_3
    0101 aload_3
    0102 areturn
    sub_attr  StackMapTable (37 bytes)
=======
    0006 ldc "en"
    0008 astore_1
    0009 aload_0
    0010 aload_1
    0011 invokestatic Method(kotlin/jvm/internal/Intrinsics.areEqual:(Ljava/lang/Object;Ljava/lang/Object;)Z)
    0014 istore_2
    0015 iload_2
    0016 ifeq 28
    0019 ldc "Hello"
    0021 astore_3
    0022 aload_3
    0023 astore 4
    0025 goto 120
    0028 ldc "es"
    0030 astore 5
    0032 aload_0
    0033 aload 5
    0035 invokestatic Method(kotlin/jvm/internal/Intrinsics.areEqual:(Ljava/lang/Object;Ljava/lang/Object;)Z)
    0038 istore 6
    0040 iload 6
    0042 ifeq 56
    0045 ldc "Hola"
    0047 astore 7
    0049 aload 7
    0051 astore 4
    0053 goto 120
    0056 ldc "fr"
    0058 astore 8
    0060 aload_0
    0061 aload 8
    0063 invokestatic Method(kotlin/jvm/internal/Intrinsics.areEqual:(Ljava/lang/Object;Ljava/lang/Object;)Z)
    0066 istore 9
    0068 iload 9
    0070 ifeq 84
    0073 ldc "Bonjour"
    0075 astore 10
    0077 aload 10
    0079 astore 4
    0081 goto 120
    0084 ldc "de"
    0086 astore 11
    0088 aload_0
    0089 aload 11
    0091 invokestatic Method(kotlin/jvm/internal/Intrinsics.areEqual:(Ljava/lang/Object;Ljava/lang/Object;)Z)
    0094 istore 12
    0096 iload 12
    0098 ifeq 112
    0101 ldc "Hallo"
    0103 astore 13
    0105 aload 13
    0107 astore 4
    0109 goto 120
    0112 ldc "Hi"
    0114 astore 14
    0116 aload 14
    0118 astore 4
    0120 aload 4
    0122 areturn
    sub_attr  StackMapTable (63 bytes)
>>>>>>> Stashed changes
  attr        RuntimeInvisibleAnnotations (6 bytes)
  attr        RuntimeInvisibleParameterAnnotations (7 bytes)
method        main ()V 0x0019
  code        max_stack=2 max_locals=0
    0000 ldc "en"
    0002 invokestatic Method(InputKt.greetByLang:(Ljava/lang/String;)Ljava/lang/String;)
    0005 getstatic Field(java/lang/System.out:Ljava/io/PrintStream;)
    0008 swap
    0009 invokevirtual Method(java/io/PrintStream.println:(Ljava/lang/Object;)V)
    0012 ldc "es"
    0014 invokestatic Method(InputKt.greetByLang:(Ljava/lang/String;)Ljava/lang/String;)
    0017 getstatic Field(java/lang/System.out:Ljava/io/PrintStream;)
    0020 swap
    0021 invokevirtual Method(java/io/PrintStream.println:(Ljava/lang/Object;)V)
    0024 ldc "fr"
    0026 invokestatic Method(InputKt.greetByLang:(Ljava/lang/String;)Ljava/lang/String;)
    0029 getstatic Field(java/lang/System.out:Ljava/io/PrintStream;)
    0032 swap
    0033 invokevirtual Method(java/io/PrintStream.println:(Ljava/lang/Object;)V)
    0036 ldc "de"
    0038 invokestatic Method(InputKt.greetByLang:(Ljava/lang/String;)Ljava/lang/String;)
    0041 getstatic Field(java/lang/System.out:Ljava/io/PrintStream;)
    0044 swap
    0045 invokevirtual Method(java/io/PrintStream.println:(Ljava/lang/Object;)V)
    0048 ldc "ja"
    0050 invokestatic Method(InputKt.greetByLang:(Ljava/lang/String;)Ljava/lang/String;)
    0053 getstatic Field(java/lang/System.out:Ljava/io/PrintStream;)
    0056 swap
    0057 invokevirtual Method(java/io/PrintStream.println:(Ljava/lang/Object;)V)
    0060 return
method        main ([Ljava/lang/String;)V 0x1009
  code        max_stack=0 max_locals=1
    0000 invokestatic Method(InputKt.main:()V)
    0003 return
