class_version major=61 minor=0
this_class    InputKt
super_class   java/lang/Object
access_flags  0x0031
method        build (Lkotlin/jvm/functions/Function1;Ljava/lang/Object;)LBox; 0x0019
  code        max_stack=3 max_locals=3
    0000 aload_0
    0001 ldc "init"
    0003 invokestatic Method(kotlin/jvm/internal/Intrinsics.checkNotNullParameter:(Ljava/lang/Object;Ljava/lang/String;)V)
    0006 new Class(Box)
    0009 dup
    0010 aload_1
    0011 invokespecial Method(Box.<init>:(Ljava/lang/Object;)V)
    0014 astore_2
    0015 aload_0
    0016 aload_2
    0017 invokeinterface InterfaceMethod(kotlin/jvm/functions/Function1.invoke:(Ljava/lang/Object;)Ljava/lang/Object;)
    0022 pop
    0023 aload_2
    0024 areturn
  attr        Signature (2 bytes)
  attr        RuntimeInvisibleAnnotations (6 bytes)
  attr        RuntimeInvisibleParameterAnnotations (9 bytes)
method        main ()V 0x0019
  code        max_stack=2 max_locals=2
    0000 invokedynamic InvokeDynamic(invoke:()Lkotlin/jvm/functions/Function1;)
    0005 iconst_0
    0006 invokestatic Method(java/lang/Integer.valueOf:(I)Ljava/lang/Integer;)
    0009 invokestatic Method(InputKt.build:(Lkotlin/jvm/functions/Function1;Ljava/lang/Object;)LBox;)
    0012 astore_0
    0013 aload_0
    0014 invokevirtual Method(Box.getSum:()I)
    0017 istore_1
    0018 getstatic Field(java/lang/System.out:Ljava/io/PrintStream;)
    0021 iload_1
    0022 invokevirtual Method(java/io/PrintStream.println:(I)V)
    0025 return
method        main ([Ljava/lang/String;)V 0x1009
  code        max_stack=0 max_locals=1
    0000 invokestatic Method(InputKt.main:()V)
    0003 return
method        main$lambda$0 (LBox;)Lkotlin/Unit; 0x001A
  code        max_stack=2 max_locals=1
    0000 aload_0
    0001 ldc "$this$build"
    0003 invokestatic Method(kotlin/jvm/internal/Intrinsics.checkNotNullParameter:(Ljava/lang/Object;Ljava/lang/String;)V)
    0006 aload_0
    0007 iconst_1
    0008 invokevirtual Method(Box.add:(I)V)
    0011 aload_0
    0012 iconst_2
    0013 invokevirtual Method(Box.add:(I)V)
    0016 aload_0
    0017 iconst_3
    0018 invokevirtual Method(Box.add:(I)V)
    0021 getstatic Field(kotlin/Unit.INSTANCE:Lkotlin/Unit;)
    0024 areturn
class_attr    BootstrapMethods (12 bytes)
