class_version major=61 minor=0
this_class    InputKt$Lambda$0
super_class   kotlin/coroutines/jvm/internal/SuspendLambda
access_flags  0x0021
interfaces    [kotlin/jvm/functions/Function2]
field         L$0 : Ljava/lang/Object; 0x0001
field         L$1 : Ljava/lang/Object; 0x0001
field         L$2 : Ljava/lang/Object; 0x0001
field         L$3 : Ljava/lang/Object; 0x0001
field         label : I 0x0001
field         p$0 : Ljava/lang/Object; 0x0001
method        <init> (Lkotlin/coroutines/Continuation;)V 0x0001
  code        max_stack=3 max_locals=2
    0000 aload_0
    0001 iconst_2
    0002 aload_1
    0003 invokespecial Method(kotlin/coroutines/jvm/internal/SuspendLambda.<init>:(ILkotlin/coroutines/Continuation;)V)
    0006 return
method        create (Ljava/lang/Object;Lkotlin/coroutines/Continuation;)Lkotlin/coroutines/Continuation; 0x0011
  code        max_stack=4 max_locals=3
    0000 new Class(InputKt$Lambda$0)
    0003 dup
    0004 aload_2
    0005 invokespecial Method(InputKt$Lambda$0.<init>:(Lkotlin/coroutines/Continuation;)V)
    0008 dup
    0009 aload_1
    0010 putfield Field(InputKt$Lambda$0.p$0:Ljava/lang/Object;)
    0013 checkcast Class(kotlin/coroutines/Continuation)
    0016 areturn
method        invoke (Ljava/lang/Object;Ljava/lang/Object;)Ljava/lang/Object; 0x1051
  code        max_stack=3 max_locals=3
    0000 aload_0
    0001 aload_1
    0002 aload_2
    0003 checkcast Class(kotlin/coroutines/Continuation)
    0006 invokevirtual Method(InputKt$Lambda$0.invoke:(Ljava/lang/Object;Lkotlin/coroutines/Continuation;)Ljava/lang/Object;)
    0009 areturn
method        invoke (Ljava/lang/Object;Lkotlin/coroutines/Continuation;)Ljava/lang/Object; 0x0011
  code        max_stack=3 max_locals=3
    0000 aload_0
    0001 aload_1
    0002 aload_2
    0003 invokevirtual Method(InputKt$Lambda$0.create:(Ljava/lang/Object;Lkotlin/coroutines/Continuation;)Lkotlin/coroutines/Continuation;)
    0006 checkcast Class(InputKt$Lambda$0)
    0009 getstatic Field(kotlin/Unit.INSTANCE:Lkotlin/Unit;)
    0012 invokevirtual Method(InputKt$Lambda$0.invokeSuspend:(Ljava/lang/Object;)Ljava/lang/Object;)
    0015 areturn
method        invokeSuspend (Ljava/lang/Object;)Ljava/lang/Object; 0x0011
  code        max_stack=16 max_locals=60
    0000 invokestatic Method(kotlin/coroutines/intrinsics/IntrinsicsKt.getCOROUTINE_SUSPENDED:()Ljava/lang/Object;)
    0003 astore_2
    0004 aconst_null
    0005 astore 29
    0007 aconst_null
    0008 astore 11
    0010 aconst_null
    0011 astore 50
    0013 iconst_0
    0014 istore 35
    0016 aconst_null
    0017 astore 17
    0019 lconst_0
    0020 lstore 56
    0022 aconst_null
    0023 astore 38
    0025 aconst_null
    0026 astore 22
    0028 aconst_null
    0029 astore 44
    0031 aconst_null
    0032 astore 28
    0034 aconst_null
    0035 astore 10
    0037 aconst_null
    0038 astore 49
    0040 aconst_null
    0041 astore 34
    0043 aconst_null
    0044 astore 16
    0046 aconst_null
    0047 astore 55
    0049 aconst_null
    0050 astore 6
    0052 aconst_null
    0053 astore 21
    0055 aconst_null
    0056 astore 43
    0058 aconst_null
    0059 astore 27
    0061 iconst_0
    0062 istore 9
    0064 aconst_null
    0065 astore 48
    0067 aconst_null
    0068 astore 33
    0070 iconst_0
    0071 istore 15
    0073 aconst_null
    0074 astore 54
    0076 aconst_null
    0077 astore 37
    0079 aconst_null
    0080 astore 20
    0082 iconst_0
    0083 istore 42
    0085 aconst_null
    0086 astore 26
    0088 aconst_null
    0089 astore 3
    0091 aconst_null
    0092 astore 47
    0094 aconst_null
    0095 astore 32
    0097 iconst_0
    0098 istore 14
    0100 iconst_0
    0101 istore 53
    0103 aconst_null
    0104 astore 5
    0106 aconst_null
    0107 astore 19
    0109 iconst_0
    0110 istore 41
    0112 iconst_0
    0113 istore 25
    0115 aconst_null
    0116 astore 8
    0118 aconst_null
    0119 astore 46
    0121 aconst_null
    0122 astore 31
    0124 iconst_0
    0125 istore 13
    0127 aconst_null
    0128 astore 52
    0130 aconst_null
    0131 astore 4
    0133 aconst_null
    0134 astore 18
    0136 aconst_null
    0137 astore 59
    0139 iconst_0
    0140 istore 40
    0142 aconst_null
    0143 astore 24
    0145 iconst_0
    0146 istore 7
    0148 aconst_null
    0149 astore 45
    0151 aconst_null
    0152 astore 30
    0154 aconst_null
    0155 astore 12
    0157 aconst_null
    0158 astore 51
    0160 aconst_null
    0161 astore 36
    0163 aconst_null
    0164 astore 58
    0166 aconst_null
    0167 astore 39
    0169 aconst_null
    0170 astore 23
    0172 aload_0
    0173 getfield Field(InputKt$Lambda$0.label:I)
    0176 tableswitch default=801 low=0 high=5 0=216 1=247 2=290 3=539 4=608 5=789
    0216 aload_1
    0217 invokestatic Method(kotlin/ResultKt.throwOnFailure:(Ljava/lang/Object;)V)
    0220 iconst_5
    0221 istore 7
    0223 aconst_null
    0224 astore 8
    0226 iload 7
    0228 aload_0
    0229 checkcast Class(kotlin/coroutines/Continuation)
    0232 aload_0
    0233 iconst_1
    0234 putfield Field(InputKt$Lambda$0.label:I)
    0237 invokestatic Method(InputKt.doubleAfterDelay:(ILkotlin/coroutines/Continuation;)Ljava/lang/Object;)
    0240 dup
    0241 aload_2
    0242 if_acmpne 252
    0245 aload_2
    0246 areturn
    0247 aload_1
    0248 invokestatic Method(kotlin/ResultKt.throwOnFailure:(Ljava/lang/Object;)V)
    0251 aload_1
    0252 checkcast Class(java/lang/Integer)
    0255 astore_3
    0256 bipush 10
    0258 istore 9
    0260 aconst_null
    0261 astore 10
    0263 iload 9
    0265 aload_0
    0266 checkcast Class(kotlin/coroutines/Continuation)
    0269 aload_0
    0270 aload 3
    0272 putfield Field(InputKt$Lambda$0.L$0:Ljava/lang/Object;)
    0275 aload_0
    0276 iconst_2
    0277 putfield Field(InputKt$Lambda$0.label:I)
    0280 invokestatic Method(InputKt.doubleAfterDelay:(ILkotlin/coroutines/Continuation;)Ljava/lang/Object;)
    0283 dup
    0284 aload_2
    0285 if_acmpne 301
    0288 aload_2
    0289 areturn
    0290 aload_0
    0291 getfield Field(InputKt$Lambda$0.L$0:Ljava/lang/Object;)
    0294 astore 3
    0296 aload_1
    0297 invokestatic Method(kotlin/ResultKt.throwOnFailure:(Ljava/lang/Object;)V)
    0300 aload_1
    0301 checkcast Class(java/lang/Integer)
    0304 astore 11
    0306 ldc "sequential: "
    0308 astore 12
    0310 aload_3
    0311 checkcast Class(java/lang/Integer)
    0314 invokevirtual Method(java/lang/Integer.intValue:()I)
    0317 istore 13
    0319 aload 11
    0321 checkcast Class(java/lang/Integer)
    0324 invokevirtual Method(java/lang/Integer.intValue:()I)
    0327 istore 14
    0329 iload 13
    0331 iload 14
    0333 iadd
    0334 istore 15
    0336 iload 15
    0338 invokestatic Method(java/lang/String.valueOf:(I)Ljava/lang/String;)
    0341 astore 16
    0343 aload 12
    0345 checkcast Class(java/lang/String)
    0348 aload 16
    0350 checkcast Class(java/lang/String)
    0353 invokevirtual Method(java/lang/String.concat:(Ljava/lang/String;)Ljava/lang/String;)
    0356 astore 17
    0358 getstatic Field(java/lang/System.out:Ljava/io/PrintStream;)
    0361 aload 17
    0363 invokevirtual Method(java/io/PrintStream.println:(Ljava/lang/Object;)V)
    0366 new Class(InputKt$Lambda$1)
    0369 astore 18
    0371 aconst_null
    0372 astore 19
    0374 aload 18
    0376 aload 19
    0378 invokespecial Method(InputKt$Lambda$1.<init>:(Lkotlin/coroutines/Continuation;)V)
    0381 aload_0
    0382 getfield Field(InputKt$Lambda$0.p$0:Ljava/lang/Object;)
    0385 astore 20
    0387 aload 20
    0389 checkcast Class(kotlinx/coroutines/CoroutineScope)
    0392 astore 21
    0394 aconst_null
    0395 astore 22
    0397 aconst_null
    0398 astore 23
    0400 aload 18
    0402 checkcast Class(kotlin/jvm/functions/Function2)
    0405 astore 24
    0407 iconst_3
    0408 istore 25
    0410 aconst_null
    0411 astore 26
    0413 aload 21
    0415 aload 22
    0417 aload 23
    0419 aload 24
    0421 iload 25
    0423 aload 26
    0425 invokestatic Method(kotlinx/coroutines/BuildersKt.async$default:(Lkotlinx/coroutines/CoroutineScope;Lkotlin/coroutines/CoroutineContext;Lkotlinx/coroutines/CoroutineStart;Lkotlin/jvm/functions/Function2;ILjava/lang/Object;)Lkotlinx/coroutines/Deferred;)
    0428 astore 27
    0430 new Class(InputKt$Lambda$2)
    0433 astore 28
    0435 aconst_null
    0436 astore 29
    0438 aload 28
    0440 aload 29
    0442 invokespecial Method(InputKt$Lambda$2.<init>:(Lkotlin/coroutines/Continuation;)V)
    0445 aload_0
    0446 getfield Field(InputKt$Lambda$0.p$0:Ljava/lang/Object;)
    0449 astore 30
    0451 aload 30
    0453 checkcast Class(kotlinx/coroutines/CoroutineScope)
    0456 astore 31
    0458 aconst_null
    0459 astore 32
    0461 aconst_null
    0462 astore 33
    0464 aload 28
    0466 checkcast Class(kotlin/jvm/functions/Function2)
    0469 astore 34
    0471 iconst_3
    0472 istore 35
    0474 aconst_null
    0475 astore 36
    0477 aload 31
    0479 aload 32
    0481 aload 33
    0483 aload 34
    0485 iload 35
    0487 aload 36
    0489 invokestatic Method(kotlinx/coroutines/BuildersKt.async$default:(Lkotlinx/coroutines/CoroutineScope;Lkotlin/coroutines/CoroutineContext;Lkotlinx/coroutines/CoroutineStart;Lkotlin/jvm/functions/Function2;ILjava/lang/Object;)Lkotlinx/coroutines/Deferred;)
    0492 astore 4
    0494 ldc "parallel: "
    0496 astore 5
    0498 aconst_null
    0499 astore 37
    0501 aload 27
    0503 checkcast Class(kotlinx/coroutines/Deferred)
    0506 aload_0
    0507 checkcast Class(kotlin/coroutines/Continuation)
    0510 aload_0
    0511 aload 4
    0513 putfield Field(InputKt$Lambda$0.L$1:Ljava/lang/Object;)
    0516 aload_0
    0517 aload 5
    0519 putfield Field(InputKt$Lambda$0.L$2:Ljava/lang/Object;)
    0522 aload_0
    0523 iconst_3
    0524 putfield Field(InputKt$Lambda$0.label:I)
    0527 invokeinterface InterfaceMethod(kotlinx/coroutines/Deferred.await:(Lkotlin/coroutines/Continuation;)Ljava/lang/Object;)
    0532 dup
    0533 aload_2
    0534 if_acmpne 562
    0537 aload_2
    0538 areturn
    0539 aload_0
    0540 getfield Field(InputKt$Lambda$0.L$2:Ljava/lang/Object;)
    0543 checkcast Class(java/lang/String)
    0546 astore 5
    0548 aload_0
    0549 getfield Field(InputKt$Lambda$0.L$1:Ljava/lang/Object;)
    0552 checkcast Class(kotlinx/coroutines/Deferred)
    0555 astore 4
    0557 aload_1
    0558 invokestatic Method(kotlin/ResultKt.throwOnFailure:(Ljava/lang/Object;)V)
    0561 aload_1
    0562 checkcast Class(java/lang/Object)
    0565 astore 6
    0567 aconst_null
    0568 astore 38
    0570 aload 4
    0572 checkcast Class(kotlinx/coroutines/Deferred)
    0575 aload_0
    0576 checkcast Class(kotlin/coroutines/Continuation)
    0579 aload_0
    0580 aload 5
    0582 putfield Field(InputKt$Lambda$0.L$2:Ljava/lang/Object;)
    0585 aload_0
    0586 aload 6
    0588 putfield Field(InputKt$Lambda$0.L$3:Ljava/lang/Object;)
    0591 aload_0
    0592 iconst_4
    0593 putfield Field(InputKt$Lambda$0.label:I)
    0596 invokeinterface InterfaceMethod(kotlinx/coroutines/Deferred.await:(Lkotlin/coroutines/Continuation;)Ljava/lang/Object;)
    0601 dup
    0602 aload_2
    0603 if_acmpne 628
    0606 aload_2
    0607 areturn
    0608 aload_0
    0609 getfield Field(InputKt$Lambda$0.L$3:Ljava/lang/Object;)
    0612 astore 6
    0614 aload_0
    0615 getfield Field(InputKt$Lambda$0.L$2:Ljava/lang/Object;)
    0618 checkcast Class(java/lang/String)
    0621 astore 5
    0623 aload_1
    0624 invokestatic Method(kotlin/ResultKt.throwOnFailure:(Ljava/lang/Object;)V)
    0627 aload_1
    0628 checkcast Class(java/lang/Object)
    0631 astore 39
    0633 aload 6
    0635 checkcast Class(java/lang/Integer)
    0638 invokevirtual Method(java/lang/Integer.intValue:()I)
    0641 istore 40
    0643 aload 39
    0645 checkcast Class(java/lang/Integer)
    0648 invokevirtual Method(java/lang/Integer.intValue:()I)
    0651 istore 41
    0653 iload 40
    0655 iload 41
    0657 iadd
    0658 istore 42
    0660 iload 42
    0662 invokestatic Method(java/lang/String.valueOf:(I)Ljava/lang/String;)
    0665 astore 43
    0667 aload 5
    0669 checkcast Class(java/lang/String)
    0672 aload 43
    0674 checkcast Class(java/lang/String)
    0677 invokevirtual Method(java/lang/String.concat:(Ljava/lang/String;)Ljava/lang/String;)
    0680 astore 44
    0682 getstatic Field(java/lang/System.out:Ljava/io/PrintStream;)
    0685 aload 44
    0687 invokevirtual Method(java/io/PrintStream.println:(Ljava/lang/Object;)V)
    0690 ldc "launched"
    0692 astore 45
    0694 new Class(InputKt$Lambda$3)
    0697 astore 46
    0699 aconst_null
    0700 astore 47
    0702 aload 46
    0704 aload 45
    0706 aload 47
    0708 invokespecial Method(InputKt$Lambda$3.<init>:(Ljava/lang/String;Lkotlin/coroutines/Continuation;)V)
    0711 aload_0
    0712 getfield Field(InputKt$Lambda$0.p$0:Ljava/lang/Object;)
    0715 astore 48
    0717 aload 48
    0719 checkcast Class(kotlinx/coroutines/CoroutineScope)
    0722 astore 49
    0724 aconst_null
    0725 astore 50
    0727 aconst_null
    0728 astore 51
    0730 aload 46
    0732 checkcast Class(kotlin/jvm/functions/Function2)
    0735 astore 52
    0737 iconst_3
    0738 istore 53
    0740 aconst_null
    0741 astore 54
    0743 aload 49
    0745 aload 50
    0747 aload 51
    0749 aload 52
    0751 iload 53
    0753 aload 54
    0755 invokestatic Method(kotlinx/coroutines/BuildersKt.launch$default:(Lkotlinx/coroutines/CoroutineScope;Lkotlin/coroutines/CoroutineContext;Lkotlinx/coroutines/CoroutineStart;Lkotlin/jvm/functions/Function2;ILjava/lang/Object;)Lkotlinx/coroutines/Job;)
    0758 astore 55
    0760 ldc2_w long(100)
    0763 lstore 56
    0765 aconst_null
    0766 astore 58
    0768 lload 56
    0770 aload_0
    0771 checkcast Class(kotlin/coroutines/Continuation)
    0774 aload_0
    0775 iconst_5
    0776 putfield Field(InputKt$Lambda$0.label:I)
    0779 invokestatic Method(kotlinx/coroutines/DelayKt.delay:(JLkotlin/coroutines/Continuation;)Ljava/lang/Object;)
    0782 dup
    0783 aload_2
    0784 if_acmpne 794
    0787 aload_2
    0788 areturn
    0789 aload_1
    0790 invokestatic Method(kotlin/ResultKt.throwOnFailure:(Ljava/lang/Object;)V)
    0793 aload_1
    0794 pop
    0795 aconst_null
    0796 astore 59
    0798 aload 59
    0800 areturn
    0801 new Class(java/lang/IllegalStateException)
    0804 dup
    0805 ldc "call to 'resume' before 'invoke' with coroutine"
    0807 invokespecial Method(java/lang/IllegalStateException.<init>:(Ljava/lang/String;)V)
    0810 athrow
    sub_attr  StackMapTable (192 bytes)
