class_version major=61 minor=0
this_class    InputKt
super_class   java/lang/Object
access_flags  0x0031
method        main ()V 0x0019
  code        max_stack=2 max_locals=0
    0000 ldc "hello"
    0002 invokestatic Method(InputKt.reverse:(Ljava/lang/String;)Ljava/lang/String;)
    0005 getstatic Field(java/lang/System.out:Ljava/io/PrintStream;)
    0008 swap
    0009 invokevirtual Method(java/io/PrintStream.println:(Ljava/lang/Object;)V)
    0012 ldc "kotlin"
    0014 invokestatic Method(InputKt.reverse:(Ljava/lang/String;)Ljava/lang/String;)
    0017 getstatic Field(java/lang/System.out:Ljava/io/PrintStream;)
    0020 swap
    0021 invokevirtual Method(java/io/PrintStream.println:(Ljava/lang/Object;)V)
    0024 return
method        main ([Ljava/lang/String;)V 0x1009
  code        max_stack=0 max_locals=1
    0000 invokestatic Method(InputKt.main:()V)
    0003 return
method        reverse (Ljava/lang/String;)Ljava/lang/String; 0x0019
  code        max_stack=3 max_locals=3
    0000 aload_0
    0001 ldc "s"
    0003 invokestatic Method(kotlin/jvm/internal/Intrinsics.checkNotNullParameter:(Ljava/lang/Object;Ljava/lang/String;)V)
    0006 new Class(java/lang/StringBuilder)
    0009 dup
    0010 invokespecial Method(java/lang/StringBuilder.<init>:()V)
    0013 astore_1
    0014 aload_0
    0015 invokevirtual Method(java/lang/String.length:()I)
    0018 iconst_1
    0019 isub
    0020 istore_2
    0021 aload_1
    0022 aload_0
    0023 iload_2
    0024 invokestatic Method(InputKt.reverse$helper:(Ljava/lang/StringBuilder;Ljava/lang/String;I)V)
    0027 aload_1
    0028 invokevirtual Method(java/lang/StringBuilder.toString:()Ljava/lang/String;)
    0031 dup
    0032 ldc "toString(...)"
    0034 invokestatic Method(kotlin/jvm/internal/Intrinsics.checkNotNullExpressionValue:(Ljava/lang/Object;Ljava/lang/String;)V)
    0037 areturn
  attr        RuntimeInvisibleAnnotations (6 bytes)
  attr        RuntimeInvisibleParameterAnnotations (7 bytes)
method        reverse$helper (Ljava/lang/StringBuilder;Ljava/lang/String;I)V 0x001A
  code        max_stack=3 max_locals=4
    0000 aload_0
    0001 ldc "builder"
    0003 invokestatic Method(kotlin/jvm/internal/Intrinsics.checkNotNullParameter:(Ljava/lang/Object;Ljava/lang/String;)V)
    0006 aload_1
    0007 ldc "s"
    0009 invokestatic Method(kotlin/jvm/internal/Intrinsics.checkNotNullParameter:(Ljava/lang/Object;Ljava/lang/String;)V)
    0012 iload_2
    0013 ifge 17
    0016 return
    0017 aload_0
    0018 aload_1
    0019 iload_2
    0020 invokevirtual Method(java/lang/String.charAt:(I)C)
    0023 invokevirtual Method(java/lang/StringBuilder.append:(C)Ljava/lang/StringBuilder;)
    0026 pop
    0027 iload_2
    0028 iconst_1
    0029 isub
    0030 invokestatic Method(java/lang/Integer.valueOf:(I)Ljava/lang/Integer;)
    0033 astore_3
    0034 aload_0
    0035 aload_1
    0036 aload_3
    0037 checkcast Class(java/lang/Integer)
    0040 invokevirtual Method(java/lang/Integer.intValue:()I)
    0043 invokestatic Method(InputKt.reverse$helper:(Ljava/lang/StringBuilder;Ljava/lang/String;I)V)
    0046 return
    sub_attr  StackMapTable (3 bytes)
  attr        RuntimeInvisibleParameterAnnotations (15 bytes)
