class_version major=61 minor=0
this_class    InputKt
super_class   java/lang/Object
access_flags  0x0031
method        main ()V 0x0019
  code        max_stack=3 max_locals=9
    0000 iconst_5
    0001 anewarray Class(java/lang/Object)
    0004 astore_0
    0005 iconst_1
    0006 invokestatic Method(java/lang/Integer.valueOf:(I)Ljava/lang/Integer;)
    0009 astore_1
    0010 aload_0
    0011 iconst_0
    0012 aload_1
    0013 aastore
    0014 iconst_2
    0015 invokestatic Method(java/lang/Integer.valueOf:(I)Ljava/lang/Integer;)
    0018 astore_2
    0019 aload_0
    0020 iconst_1
    0021 aload_2
    0022 aastore
    0023 iconst_3
    0024 invokestatic Method(java/lang/Integer.valueOf:(I)Ljava/lang/Integer;)
    0027 astore_3
    0028 aload_0
    0029 iconst_2
    0030 aload_3
    0031 aastore
    0032 iconst_4
    0033 invokestatic Method(java/lang/Integer.valueOf:(I)Ljava/lang/Integer;)
    0036 astore 4
    0038 aload_0
    0039 iconst_3
    0040 aload 4
    0042 aastore
    0043 iconst_5
    0044 invokestatic Method(java/lang/Integer.valueOf:(I)Ljava/lang/Integer;)
    0047 astore 5
    0049 aload_0
    0050 iconst_4
    0051 aload 5
    0053 aastore
    0054 aload_0
    0055 invokestatic Method(kotlin/collections/CollectionsKt.listOf:([Ljava/lang/Object;)Ljava/util/List;)
    0058 astore 6
    0060 invokedynamic InvokeDynamic(invoke:()Lkotlin/jvm/functions/Function1;)
    0065 astore 7
    0067 aload 6
    0069 invokeinterface InterfaceMethod(java/lang/Iterable.iterator:()Ljava/util/Iterator;)
    0074 astore 8
    0076 aload 8
    0078 invokeinterface InterfaceMethod(java/util/Iterator.hasNext:()Z)
    0083 ifeq 105
    0086 aload 8
    0088 invokeinterface InterfaceMethod(java/util/Iterator.next:()Ljava/lang/Object;)
    0093 aload 7
    0095 swap
    0096 invokeinterface InterfaceMethod(kotlin/jvm/functions/Function1.invoke:(Ljava/lang/Object;)Ljava/lang/Object;)
    0101 pop
    0102 goto 76
    0105 ldc "done"
    0107 getstatic Field(java/lang/System.out:Ljava/io/PrintStream;)
    0110 swap
    0111 invokevirtual Method(java/io/PrintStream.println:(Ljava/lang/Object;)V)
    0114 return
    sub_attr  StackMapTable (37 bytes)
method        main ([Ljava/lang/String;)V 0x1009
  code        max_stack=0 max_locals=1
    0000 invokestatic Method(InputKt.main:()V)
    0003 return
method        main$lambda$0 (I)Lkotlin/Unit; 0x0019
  code        max_stack=2 max_locals=1
    0000 iload_0
    0001 iconst_3
    0002 if_icmpne 9
    0005 getstatic Field(kotlin/Unit.INSTANCE:Lkotlin/Unit;)
    0008 areturn
    0009 getstatic Field(java/lang/System.out:Ljava/io/PrintStream;)
    0012 iload_0
    0013 invokevirtual Method(java/io/PrintStream.println:(I)V)
    0016 getstatic Field(kotlin/Unit.INSTANCE:Lkotlin/Unit;)
    0019 areturn
    sub_attr  StackMapTable (3 bytes)
  attr        RuntimeInvisibleAnnotations (6 bytes)
class_attr    BootstrapMethods (12 bytes)
