class_version major=61 minor=0
this_class    InputKt
super_class   java/lang/Object
access_flags  0x0031
method        cents (I)LMoney; 0x0019
  code        max_stack=4 max_locals=3
    0000 iload_0
    0001 i2l
    0002 lstore_1
    0003 new Class(Money)
    0006 dup
    0007 lload_1
    0008 invokespecial Method(Money.<init>:(J)V)
    0011 areturn
  attr        RuntimeInvisibleAnnotations (6 bytes)
method        main ()V 0x0019
  code        max_stack=4 max_locals=4
    0000 new Class(Money)
    0003 dup
    0004 ldc2_w long(10)
    0007 invokespecial Method(Money.<init>:(J)V)
    0010 astore_0
    0011 new Class(Money)
    0014 dup
    0015 ldc2_w long(20)
    0018 invokespecial Method(Money.<init>:(J)V)
    0021 astore_1
    0022 aload_0
    0023 aload_1
    0024 invokevirtual Method(Money.add:(LMoney;)LMoney;)
    0027 invokevirtual Method(Money.getCents:()J)
    0030 lstore_2
    0031 getstatic Field(java/lang/System.out:Ljava/io/PrintStream;)
    0034 lload_2
    0035 invokevirtual Method(java/io/PrintStream.println:(J)V)
    0038 bipush 30
    0040 invokestatic Method(InputKt.cents:(I)LMoney;)
    0043 invokevirtual Method(Money.getCents:()J)
    0046 lstore_2
    0047 getstatic Field(java/lang/System.out:Ljava/io/PrintStream;)
    0050 lload_2
    0051 invokevirtual Method(java/io/PrintStream.println:(J)V)
    0054 return
method        main ([Ljava/lang/String;)V 0x1009
  code        max_stack=0 max_locals=1
    0000 invokestatic Method(InputKt.main:()V)
    0003 return
