class_version major=61 minor=0
this_class    Greeter
super_class   java/lang/Object
access_flags  0x0021
field         greet : Ljava/lang/Object; 0x0001
method        <init> (Ljava/lang/Object;)V 0x0001
  code        max_stack=2 max_locals=2
    0000 aload_0
    0001 invokespecial Method(java/lang/Object.<init>:()V)
    0004 aload_0
    0005 aload_1
    0006 putfield Field(Greeter.greet:Ljava/lang/Object;)
    0009 return
method        getGreet ()Ljava/lang/Object; 0x0001
  code        max_stack=1 max_locals=1
    0000 aload_0
    0001 getfield Field(Greeter.greet:Ljava/lang/Object;)
    0004 areturn
method        run ()V 0x0001
  code        max_stack=2 max_locals=3
    0000 aload_0
    0001 getfield Field(Greeter.greet:Ljava/lang/Object;)
    0004 astore_1
    0005 aload_1
    0006 invokeinterface InterfaceMethod(kotlin/jvm/functions/Function0.invoke:()Ljava/lang/Object;)
    0011 astore_2
    0012 getstatic Field(java/lang/System.out:Ljava/io/PrintStream;)
    0015 aload_2
    0016 invokevirtual Method(java/io/PrintStream.println:(Ljava/lang/Object;)V)
    0019 aload_0
    0020 aload_1
    0021 putfield Field(Greeter.greet:Ljava/lang/Object;)
    0024 return
