class_version major=61 minor=0
this_class    InputKt
super_class   java/lang/Object
access_flags  0x0031
method        main ()V 0x0019
  code        max_stack=3 max_locals=1
    0000 new Class(Greeter)
    0003 dup
    0004 op_0xBA
    0005 nop
    0006 iload_1
    0007 nop
    0008 nop
    0009 invokespecial Method(Greeter.<init>:(Lkotlin/jvm/functions/Function0;)V)
    0012 astore_0
    0013 aload_0
    0014 invokevirtual Method(Greeter.run:()V)
    0017 return
method        main ([Ljava/lang/String;)V 0x1009
  code        max_stack=0 max_locals=1
    0000 invokestatic Method(InputKt.main:()V)
    0003 return
method        main$lambda$0 ()Ljava/lang/String; 0x001A
  code        max_stack=1 max_locals=0
    0000 ldc "Hello from callable field!"
    0002 areturn
class_attr    BootstrapMethods (12 bytes)
