class_version major=61 minor=0
this_class    InputKt
super_class   java/lang/Object
access_flags  0x0031
method        countWhere (Ljava/lang/Iterable;Lkotlin/jvm/functions/Function1;)I 0x0019
  code        max_stack=2 max_locals=6
    0000 aload_0
    0001 ldc "<this>"
    0003 invokestatic Method(kotlin/jvm/internal/Intrinsics.checkNotNullParameter:(Ljava/lang/Object;Ljava/lang/String;)V)
    0006 aload_1
    0007 ldc "predicate"
    0009 invokestatic Method(kotlin/jvm/internal/Intrinsics.checkNotNullParameter:(Ljava/lang/Object;Ljava/lang/String;)V)
    0012 iconst_0
    0013 istore_2
    0014 iconst_0
    0015 istore_3
    0016 aload_0
    0017 invokeinterface InterfaceMethod(java/lang/Iterable.iterator:()Ljava/util/Iterator;)
    0022 astore 4
    0024 aload 4
    0026 invokeinterface InterfaceMethod(java/util/Iterator.hasNext:()Z)
    0031 ifeq 66
    0034 aload 4
    0036 invokeinterface InterfaceMethod(java/util/Iterator.next:()Ljava/lang/Object;)
    0041 astore 5
    0043 aload_1
    0044 aload 5
    0046 invokeinterface InterfaceMethod(kotlin/jvm/functions/Function1.invoke:(Ljava/lang/Object;)Ljava/lang/Object;)
    0051 checkcast Class(java/lang/Boolean)
    0054 invokevirtual Method(java/lang/Boolean.booleanValue:()Z)
    0057 ifeq 24
    0060 iinc 3 1
    0063 goto 24
    0066 iload_3
    0067 ireturn
    sub_attr  StackMapTable (11 bytes)
  attr        Signature (2 bytes)
  attr        RuntimeInvisibleParameterAnnotations (13 bytes)
method        firstOrNullByPredicate (Ljava/lang/Iterable;Lkotlin/jvm/functions/Function1;)Ljava/lang/Object; 0x0019
  code        max_stack=2 max_locals=4
    0000 aload_0
    0001 ldc "<this>"
    0003 invokestatic Method(kotlin/jvm/internal/Intrinsics.checkNotNullParameter:(Ljava/lang/Object;Ljava/lang/String;)V)
    0006 aload_1
    0007 ldc "predicate"
    0009 invokestatic Method(kotlin/jvm/internal/Intrinsics.checkNotNullParameter:(Ljava/lang/Object;Ljava/lang/String;)V)
    0012 aload_0
    0013 invokeinterface InterfaceMethod(java/lang/Iterable.iterator:()Ljava/util/Iterator;)
    0018 astore_2
    0019 aload_2
    0020 invokeinterface InterfaceMethod(java/util/Iterator.hasNext:()Z)
    0025 ifeq 53
    0028 aload_2
    0029 invokeinterface InterfaceMethod(java/util/Iterator.next:()Ljava/lang/Object;)
    0034 astore_3
    0035 aload_1
    0036 aload_3
    0037 invokeinterface InterfaceMethod(kotlin/jvm/functions/Function1.invoke:(Ljava/lang/Object;)Ljava/lang/Object;)
    0042 checkcast Class(java/lang/Boolean)
    0045 invokevirtual Method(java/lang/Boolean.booleanValue:()Z)
    0048 ifeq 19
    0051 aload_3
    0052 areturn
    0053 aconst_null
    0054 areturn
    sub_attr  StackMapTable (9 bytes)
  attr        Signature (2 bytes)
  attr        RuntimeInvisibleAnnotations (6 bytes)
  attr        RuntimeInvisibleParameterAnnotations (13 bytes)
method        main ()V 0x0019
  code        max_stack=3 max_locals=8
    0000 bipush 10
    0002 anewarray Class(java/lang/Integer)
    0005 astore_1
    0006 aload_1
    0007 iconst_0
    0008 iconst_1
    0009 invokestatic Method(java/lang/Integer.valueOf:(I)Ljava/lang/Integer;)
    0012 aastore
    0013 aload_1
    0014 iconst_1
    0015 iconst_2
    0016 invokestatic Method(java/lang/Integer.valueOf:(I)Ljava/lang/Integer;)
    0019 aastore
    0020 aload_1
    0021 iconst_2
    0022 iconst_3
    0023 invokestatic Method(java/lang/Integer.valueOf:(I)Ljava/lang/Integer;)
    0026 aastore
    0027 aload_1
    0028 iconst_3
    0029 iconst_4
    0030 invokestatic Method(java/lang/Integer.valueOf:(I)Ljava/lang/Integer;)
    0033 aastore
    0034 aload_1
    0035 iconst_4
    0036 iconst_5
    0037 invokestatic Method(java/lang/Integer.valueOf:(I)Ljava/lang/Integer;)
    0040 aastore
    0041 aload_1
    0042 iconst_5
    0043 bipush 6
    0045 invokestatic Method(java/lang/Integer.valueOf:(I)Ljava/lang/Integer;)
    0048 aastore
    0049 aload_1
    0050 bipush 6
    0052 bipush 7
    0054 invokestatic Method(java/lang/Integer.valueOf:(I)Ljava/lang/Integer;)
    0057 aastore
    0058 aload_1
    0059 bipush 7
    0061 bipush 8
    0063 invokestatic Method(java/lang/Integer.valueOf:(I)Ljava/lang/Integer;)
    0066 aastore
    0067 aload_1
    0068 bipush 8
    0070 bipush 9
    0072 invokestatic Method(java/lang/Integer.valueOf:(I)Ljava/lang/Integer;)
    0075 aastore
    0076 aload_1
    0077 bipush 9
    0079 bipush 10
    0081 invokestatic Method(java/lang/Integer.valueOf:(I)Ljava/lang/Integer;)
    0084 aastore
    0085 aload_1
    0086 invokestatic Method(kotlin/collections/CollectionsKt.listOf:([Ljava/lang/Object;)Ljava/util/List;)
    0089 astore_0
    0090 aload_0
    0091 checkcast Class(java/lang/Iterable)
    0094 astore_1
    0095 iconst_0
    0096 istore_2
    0097 iconst_0
    0098 istore_3
    0099 aload_1
    0100 invokeinterface InterfaceMethod(java/lang/Iterable.iterator:()Ljava/util/Iterator;)
    0105 astore 4
    0107 aload 4
    0109 invokeinterface InterfaceMethod(java/util/Iterator.hasNext:()Z)
    0114 ifeq 160
    0117 aload 4
    0119 invokeinterface InterfaceMethod(java/util/Iterator.next:()Ljava/lang/Object;)
    0124 astore 5
    0126 aload 5
    0128 checkcast Class(java/lang/Number)
    0131 invokevirtual Method(java/lang/Number.intValue:()I)
    0134 istore 6
    0136 iconst_0
    0137 istore 7
    0139 iload 6
    0141 iconst_2
    0142 irem
    0143 ifne 150
    0146 iconst_1
    0147 goto 151
    0150 iconst_0
    0151 ifeq 107
    0154 iinc 3 1
    0157 goto 107
    0160 iload_3
    0161 istore_1
    0162 getstatic Field(java/lang/System.out:Ljava/io/PrintStream;)
    0165 iload_1
    0166 invokevirtual Method(java/io/PrintStream.println:(I)V)
    0169 aload_0
    0170 checkcast Class(java/lang/Iterable)
    0173 invokedynamic InvokeDynamic(invoke:()Lkotlin/jvm/functions/Function1;)
    0178 invokestatic Method(InputKt.firstOrNullByPredicate:(Ljava/lang/Iterable;Lkotlin/jvm/functions/Function1;)Ljava/lang/Object;)
    0181 getstatic Field(java/lang/System.out:Ljava/io/PrintStream;)
    0184 swap
    0185 invokevirtual Method(java/io/PrintStream.println:(Ljava/lang/Object;)V)
    0188 return
    sub_attr  StackMapTable (33 bytes)
method        main ([Ljava/lang/String;)V 0x1009
  code        max_stack=0 max_locals=1
    0000 invokestatic Method(InputKt.main:()V)
    0003 return
method        main$lambda$1 (I)Z 0x001A
  code        max_stack=2 max_locals=1
    0000 iload_0
    0001 iconst_5
    0002 if_icmple 9
    0005 iconst_1
    0006 goto 10
    0009 iconst_0
    0010 ireturn
    sub_attr  StackMapTable (5 bytes)
class_attr    SourceDebugExtension (132 bytes)
class_attr    RuntimeInvisibleAnnotations (14 bytes)
class_attr    BootstrapMethods (12 bytes)
