class_version major=61 minor=0
this_class    InputKt
super_class   java/lang/Object
access_flags  0x0031
method        main ()V 0x0019
  code        max_stack=3 max_locals=9
    0000 iconst_5
    0001 anewarray Class(java/lang/Object)
    0004 astore_0
    0005 iconst_1
    0006 invokestatic Method(java/lang/Integer.valueOf:(I)Ljava/lang/Integer;)
    0009 astore_1
    0010 aload_0
    0011 iconst_0
    0012 aload_1
    0013 aastore
    0014 iconst_2
    0015 invokestatic Method(java/lang/Integer.valueOf:(I)Ljava/lang/Integer;)
    0018 astore_1
    0019 aload_0
    0020 iconst_1
    0021 aload_1
    0022 aastore
    0023 iconst_3
    0024 invokestatic Method(java/lang/Integer.valueOf:(I)Ljava/lang/Integer;)
    0027 astore_1
    0028 aload_0
    0029 iconst_2
    0030 aload_1
    0031 aastore
    0032 iconst_4
    0033 invokestatic Method(java/lang/Integer.valueOf:(I)Ljava/lang/Integer;)
    0036 astore_1
    0037 aload_0
    0038 iconst_3
    0039 aload_1
    0040 aastore
    0041 iconst_5
    0042 invokestatic Method(java/lang/Integer.valueOf:(I)Ljava/lang/Integer;)
    0045 astore_1
    0046 aload_0
    0047 iconst_4
    0048 aload_1
    0049 aastore
    0050 aload_0
    0051 invokestatic Method(kotlin/collections/CollectionsKt.listOf:([Ljava/lang/Object;)Ljava/util/List;)
    0054 astore 6
    0056 iconst_3
    0057 anewarray Class(java/lang/String)
    0060 astore_0
    0061 aload_0
    0062 iconst_0
    0063 ldc "a"
    0065 aastore
    0066 aload_0
    0067 iconst_1
    0068 ldc "b"
    0070 aastore
    0071 aload_0
    0072 iconst_2
    0073 ldc "c"
    0075 aastore
    0076 aload_0
    0077 invokestatic Method(kotlin/collections/CollectionsKt.listOf:([Ljava/lang/Object;)Ljava/util/List;)
    0080 astore 8
    0082 aload 6
    0084 invokestatic Method(InputKt.sizeTimesTwo:(Ljava/util/List;)I)
    0087 istore_0
    0088 getstatic Field(java/lang/System.out:Ljava/io/PrintStream;)
    0091 iload_0
    0092 invokevirtual Method(java/io/PrintStream.println:(I)V)
    0095 aload 8
    0097 invokestatic Method(InputKt.sizeTimesTwo:(Ljava/util/List;)I)
    0100 istore_0
    0101 getstatic Field(java/lang/System.out:Ljava/io/PrintStream;)
    0104 iload_0
    0105 invokevirtual Method(java/io/PrintStream.println:(I)V)
    0108 aload 6
    0110 invokestatic Method(InputKt.starSizePlusOne:(Ljava/util/List;)I)
    0113 istore_0
    0114 getstatic Field(java/lang/System.out:Ljava/io/PrintStream;)
    0117 iload_0
    0118 invokevirtual Method(java/io/PrintStream.println:(I)V)
    0121 aload 8
    0123 invokestatic Method(InputKt.starSizePlusOne:(Ljava/util/List;)I)
    0126 istore_0
    0127 getstatic Field(java/lang/System.out:Ljava/io/PrintStream;)
    0130 iload_0
    0131 invokevirtual Method(java/io/PrintStream.println:(I)V)
    0134 return
method        main ([Ljava/lang/String;)V 0x1009
  code        max_stack=0 max_locals=1
    0000 invokestatic Method(InputKt.main:()V)
    0003 return
method        sizeTimesTwo (Ljava/util/List;)I 0x0019
  code        max_stack=2 max_locals=1
    0000 aload_0
    0001 ldc "<this>"
    0003 invokestatic Method(kotlin/jvm/internal/Intrinsics.checkNotNullParameter:(Ljava/lang/Object;Ljava/lang/String;)V)
    0006 aload_0
    0007 invokeinterface InterfaceMethod(java/util/List.size:()I)
    0012 iconst_2
    0013 imul
    0014 ireturn
  attr        Signature (2 bytes)
  attr        RuntimeInvisibleParameterAnnotations (7 bytes)
method        starSizePlusOne (Ljava/util/List;)I 0x0019
  code        max_stack=2 max_locals=1
    0000 aload_0
    0001 ldc "<this>"
    0003 invokestatic Method(kotlin/jvm/internal/Intrinsics.checkNotNullParameter:(Ljava/lang/Object;Ljava/lang/String;)V)
    0006 aload_0
    0007 invokeinterface InterfaceMethod(java/util/List.size:()I)
    0012 iconst_1
    0013 iadd
    0014 ireturn
  attr        Signature (2 bytes)
  attr        RuntimeInvisibleParameterAnnotations (7 bytes)
