class_version major=61 minor=0
this_class    InputKt
super_class   java/lang/Object
access_flags  0x0031
method        MINUS ()LOp; 0x0019
  code        max_stack=3 max_locals=0
    0000 new Class(Op)
    0003 dup
    0004 ldc "MINUS"
    0006 invokespecial Method(Op.<init>:(Ljava/lang/String;)V)
    0009 areturn
  attr        RuntimeInvisibleAnnotations (6 bytes)
method        Op$apply (LOp;II)I 0x0019
  code        max_stack=3 max_locals=11
    0000 aload_0
    0001 getfield Field(Op.name:Ljava/lang/String;)
    0004 astore_3
    0005 ldc "PLUS"
    0007 astore 4
    0009 aload_3
    0010 aload 4
    0012 invokestatic Method(kotlin/jvm/internal/Intrinsics.areEqual:(Ljava/lang/Object;Ljava/lang/Object;)Z)
    0015 istore 5
    0017 iload 5
    0019 ifeq 30
    0022 iload_1
    0023 iload_2
    0024 iadd
    0025 istore 6
    0027 iload 6
    0029 ireturn
    0030 ldc "MINUS"
    0032 astore 7
    0034 aload_3
    0035 aload 7
    0037 invokestatic Method(kotlin/jvm/internal/Intrinsics.areEqual:(Ljava/lang/Object;Ljava/lang/Object;)Z)
    0040 istore 8
    0042 iload 8
    0044 ifeq 55
    0047 iload_1
    0048 iload_2
    0049 isub
    0050 istore 9
    0052 iload 9
    0054 ireturn
    0055 iconst_0
    0056 istore 10
    0058 iload 10
    0060 ireturn
    sub_attr  StackMapTable (20 bytes)
method        Op$valueOf (Ljava/lang/String;)LOp; 0x0019
  code        max_stack=3 max_locals=8
    0000 aload_0
    0001 ldc "name"
    0003 invokestatic Method(kotlin/jvm/internal/Intrinsics.checkNotNullParameter:(Ljava/lang/Object;Ljava/lang/String;)V)
    0006 ldc "PLUS"
    0008 astore_1
    0009 aload_0
    0010 aload_1
    0011 invokestatic Method(kotlin/jvm/internal/Intrinsics.areEqual:(Ljava/lang/Object;Ljava/lang/Object;)Z)
    0014 istore_2
    0015 iload_2
    0016 ifeq 28
    0019 goto 53
    0022 invokestatic Method(InputKt.PLUS:()LOp;)
    0025 astore_3
    0026 aload_3
    0027 areturn
    0028 ldc "MINUS"
    0030 astore 4
    0032 aload_0
    0033 aload 4
    0035 invokestatic Method(kotlin/jvm/internal/Intrinsics.areEqual:(Ljava/lang/Object;Ljava/lang/Object;)Z)
    0038 istore 5
    0040 iload 5
    0042 ifeq 22
    0045 invokestatic Method(InputKt.MINUS:()LOp;)
    0048 astore 6
    0050 aload 6
    0052 areturn
    0053 invokestatic Method(InputKt.PLUS:()LOp;)
    0056 astore 7
    0058 aload 7
    0060 areturn
    sub_attr  StackMapTable (25 bytes)
  attr        RuntimeInvisibleAnnotations (6 bytes)
  attr        RuntimeInvisibleParameterAnnotations (7 bytes)
method        Op$values ()Ljava/util/ArrayList; 0x0019
  code        max_stack=2 max_locals=1
    0000 new Class(java/util/ArrayList)
    0003 dup
    0004 invokespecial Method(java/util/ArrayList.<init>:()V)
    0007 astore_0
    0008 invokestatic Method(InputKt.PLUS:()LOp;)
    0011 aload_0
    0012 swap
    0013 invokevirtual Method(java/util/ArrayList.add:(Ljava/lang/Object;)Z)
    0016 pop
    0017 invokestatic Method(InputKt.MINUS:()LOp;)
    0020 aload_0
    0021 swap
    0022 invokevirtual Method(java/util/ArrayList.add:(Ljava/lang/Object;)Z)
    0025 pop
    0026 aload_0
    0027 areturn
  attr        RuntimeInvisibleAnnotations (6 bytes)
method        PLUS ()LOp; 0x0019
  code        max_stack=3 max_locals=0
    0000 new Class(Op)
    0003 dup
    0004 ldc "PLUS"
    0006 invokespecial Method(Op.<init>:(Ljava/lang/String;)V)
    0009 areturn
  attr        RuntimeInvisibleAnnotations (6 bytes)
method        main ()V 0x0019
  code        max_stack=3 max_locals=1
    0000 invokestatic Method(InputKt.PLUS:()LOp;)
    0003 iconst_3
    0004 iconst_2
    0005 invokestatic Method(InputKt.Op$apply:(LOp;II)I)
    0008 istore_0
    0009 getstatic Field(java/lang/System.out:Ljava/io/PrintStream;)
    0012 iload_0
    0013 invokevirtual Method(java/io/PrintStream.println:(I)V)
    0016 invokestatic Method(InputKt.MINUS:()LOp;)
    0019 iconst_3
    0020 iconst_2
    0021 invokestatic Method(InputKt.Op$apply:(LOp;II)I)
    0024 istore_0
    0025 getstatic Field(java/lang/System.out:Ljava/io/PrintStream;)
    0028 iload_0
    0029 invokevirtual Method(java/io/PrintStream.println:(I)V)
    0032 return
method        main ([Ljava/lang/String;)V 0x1009
  code        max_stack=0 max_locals=1
    0000 invokestatic Method(InputKt.main:()V)
    0003 return
