class_version major=61 minor=0
this_class    InputKt
super_class   java/lang/Object
access_flags  0x0031
method        apply (L$Function1;I)I 0x0009
  code        max_stack=2 max_locals=6
    0000 iload 1
    0002 istore 2
    0004 iload 2
    0006 invokestatic Method(java/lang/Integer.valueOf:(I)Ljava/lang/Integer;)
    0009 astore 3
    0011 aload 0
    0013 aload 3
    0015 op_0xB9
    0016 nop
    0017 iload 2
    0019 nop
    0020 astore 4
    0022 aload 4
    0024 op_0xC0
    0025 nop
    0026 op_0x0B
    0027 invokevirtual Method(java/lang/Integer.intValue:()I)
    0030 istore 5
    0032 iload 5
    0034 op_0xAC
method        combine (L$Function1;L$Function1;I)I 0x0009
  code        max_stack=2 max_locals=10
    0000 iload 2
    0002 istore 3
    0004 iload 3
    0006 invokestatic Method(java/lang/Integer.valueOf:(I)Ljava/lang/Integer;)
    0009 astore 4
    0011 aload 0
    0013 aload 4
    0015 op_0xB9
    0016 nop
    0017 iload 2
    0019 nop
    0020 astore 5
    0022 aload 5
    0024 op_0xC0
    0025 nop
    0026 op_0x0B
    0027 invokevirtual Method(java/lang/Integer.intValue:()I)
    0030 istore 6
    0032 iload 6
    0034 invokestatic Method(java/lang/Integer.valueOf:(I)Ljava/lang/Integer;)
    0037 astore 7
    0039 aload 1
    0041 aload 7
    0043 op_0xB9
    0044 nop
    0045 iload 2
    0047 nop
    0048 astore 8
    0050 aload 8
    0052 op_0xC0
    0053 nop
    0054 op_0x0B
    0055 invokevirtual Method(java/lang/Integer.intValue:()I)
    0058 istore 9
    0060 iload 9
    0062 op_0xAC
method        main ([Ljava/lang/String;)V 0x0009
  code        max_stack=3 max_locals=14
    0000 op_0xBB
    0001 nop
    0002 op_0x20
    0003 op_0x59
    0004 invokespecial Method($Lambda$1.<init>:()V)
    0007 astore 1
    0009 iconst_5
    0010 istore 2
    0012 aload 1
    0014 iload 2
    0016 invokestatic Method(InputKt.apply:(L$Function1;I)I)
    0019 istore 3
    0021 getstatic Field(java/lang/System.out:Ljava/io/PrintStream;)
    0024 iload 3
    0026 invokevirtual Method(java/io/PrintStream.println:(I)V)
    0029 op_0xBB
    0030 nop
    0031 op_0x34
    0032 op_0x59
    0033 invokespecial Method($Lambda$2.<init>:()V)
    0036 astore 4
    0038 bipush 10
    0040 istore 5
    0042 aload 4
    0044 iload 5
    0046 invokestatic Method(InputKt.transform:(L$Function1;I)I)
    0049 istore 6
    0051 getstatic Field(java/lang/System.out:Ljava/io/PrintStream;)
    0054 iload 6
    0056 invokevirtual Method(java/io/PrintStream.println:(I)V)
    0059 op_0xBB
    0060 nop
    0061 op_0x39
    0062 op_0x59
    0063 invokespecial Method($Lambda$3.<init>:()V)
    0066 astore 7
    0068 bipush 10
    0070 istore 8
    0072 aload 7
    0074 iload 8
    0076 invokestatic Method(InputKt.transform:(L$Function1;I)I)
    0079 istore 9
    0081 getstatic Field(java/lang/System.out:Ljava/io/PrintStream;)
    0084 iload 9
    0086 invokevirtual Method(java/io/PrintStream.println:(I)V)
    0089 op_0xBB
    0090 nop
    0091 op_0x3C
    0092 op_0x59
    0093 invokespecial Method($Lambda$4.<init>:()V)
    0096 astore 10
    0098 op_0xBB
    0099 nop
    0100 op_0x3F
    0101 op_0x59
    0102 invokespecial Method($Lambda$5.<init>:()V)
    0105 astore 11
    0107 iconst_5
    0108 istore 12
    0110 aload 10
    0112 aload 11
    0114 iload 12
    0116 invokestatic Method(InputKt.combine:(L$Function1;L$Function1;I)I)
    0119 istore 13
    0121 getstatic Field(java/lang/System.out:Ljava/io/PrintStream;)
    0124 iload 13
    0126 invokevirtual Method(java/io/PrintStream.println:(I)V)
    0129 return
method        transform (L$Function1;I)I 0x0009
  code        max_stack=2 max_locals=6
    0000 iload 1
    0002 istore 2
    0004 iload 2
    0006 invokestatic Method(java/lang/Integer.valueOf:(I)Ljava/lang/Integer;)
    0009 astore 3
    0011 aload 0
    0013 aload 3
    0015 op_0xB9
    0016 nop
    0017 iload 2
    0019 nop
    0020 astore 4
    0022 aload 4
    0024 op_0xC0
    0025 nop
    0026 op_0x0B
    0027 invokevirtual Method(java/lang/Integer.intValue:()I)
    0030 istore 5
    0032 iload 5
    0034 op_0xAC
