class_version major=61 minor=0
this_class    InputKt
super_class   java/lang/Object
access_flags  0x0031
method        apply (Lkotlin/jvm/functions/Function1;I)I 0x0019
  code        max_stack=2 max_locals=2
    0000 aload_0
    0001 ldc "f"
    0003 invokestatic Method(kotlin/jvm/internal/Intrinsics.checkNotNullParameter:(Ljava/lang/Object;Ljava/lang/String;)V)
    0006 aload_0
    0007 iload_1
    0008 invokestatic Method(java/lang/Integer.valueOf:(I)Ljava/lang/Integer;)
    0011 invokeinterface InterfaceMethod(kotlin/jvm/functions/Function1.invoke:(Ljava/lang/Object;)Ljava/lang/Object;)
    0016 checkcast Class(java/lang/Number)
    0019 invokevirtual Method(java/lang/Number.intValue:()I)
    0022 ireturn
  attr        Signature (2 bytes)
  attr        RuntimeInvisibleParameterAnnotations (9 bytes)
method        combine (Lkotlin/jvm/functions/Function1;Lkotlin/jvm/functions/Function1;I)I 0x0019
  code        max_stack=2 max_locals=3
    0000 aload_0
    0001 ldc "f"
    0003 invokestatic Method(kotlin/jvm/internal/Intrinsics.checkNotNullParameter:(Ljava/lang/Object;Ljava/lang/String;)V)
    0006 aload_1
    0007 ldc "g"
    0009 invokestatic Method(kotlin/jvm/internal/Intrinsics.checkNotNullParameter:(Ljava/lang/Object;Ljava/lang/String;)V)
    0012 aload_0
    0013 iload_2
    0014 invokestatic Method(java/lang/Integer.valueOf:(I)Ljava/lang/Integer;)
    0017 invokeinterface InterfaceMethod(kotlin/jvm/functions/Function1.invoke:(Ljava/lang/Object;)Ljava/lang/Object;)
    0022 aload_1
    0023 swap
    0024 invokeinterface InterfaceMethod(kotlin/jvm/functions/Function1.invoke:(Ljava/lang/Object;)Ljava/lang/Object;)
    0029 checkcast Class(java/lang/Number)
    0032 invokevirtual Method(java/lang/Number.intValue:()I)
    0035 ireturn
  attr        Signature (2 bytes)
  attr        RuntimeInvisibleParameterAnnotations (15 bytes)
method        main ()V 0x0019
  code        max_stack=3 max_locals=1
    0000 invokedynamic InvokeDynamic(invoke:()Lkotlin/jvm/functions/Function1;)
    0005 iconst_5
    0006 invokestatic Method(InputKt.apply:(Lkotlin/jvm/functions/Function1;I)I)
    0009 istore_0
    0010 getstatic Field(java/lang/System.out:Ljava/io/PrintStream;)
    0013 iload_0
    0014 invokevirtual Method(java/io/PrintStream.println:(I)V)
    0017 invokedynamic InvokeDynamic(invoke:()Lkotlin/jvm/functions/Function1;)
    0022 bipush 10
    0024 invokestatic Method(InputKt.transform:(Lkotlin/jvm/functions/Function1;I)I)
    0027 istore_0
    0028 getstatic Field(java/lang/System.out:Ljava/io/PrintStream;)
    0031 iload_0
    0032 invokevirtual Method(java/io/PrintStream.println:(I)V)
    0035 invokedynamic InvokeDynamic(invoke:()Lkotlin/jvm/functions/Function1;)
    0040 bipush 10
    0042 invokestatic Method(InputKt.transform:(Lkotlin/jvm/functions/Function1;I)I)
    0045 istore_0
    0046 getstatic Field(java/lang/System.out:Ljava/io/PrintStream;)
    0049 iload_0
    0050 invokevirtual Method(java/io/PrintStream.println:(I)V)
    0053 invokedynamic InvokeDynamic(invoke:()Lkotlin/jvm/functions/Function1;)
    0058 astore_0
    0059 invokedynamic InvokeDynamic(invoke:()Lkotlin/jvm/functions/Function1;)
    0064 aload_0
    0065 swap
    0066 iconst_5
    0067 invokestatic Method(InputKt.combine:(Lkotlin/jvm/functions/Function1;Lkotlin/jvm/functions/Function1;I)I)
    0070 istore_0
    0071 getstatic Field(java/lang/System.out:Ljava/io/PrintStream;)
    0074 iload_0
    0075 invokevirtual Method(java/io/PrintStream.println:(I)V)
    0078 return
method        main ([Ljava/lang/String;)V 0x1009
  code        max_stack=0 max_locals=1
    0000 invokestatic Method(InputKt.main:()V)
    0003 return
method        main$lambda$0 (I)I 0x001A
  code        max_stack=2 max_locals=1
    0000 iload_0
    0001 iconst_2
    0002 imul
    0003 ireturn
method        main$lambda$1 (I)I 0x001A
  code        max_stack=2 max_locals=1
    0000 iload_0
    0001 iconst_1
    0002 iadd
    0003 ireturn
method        main$lambda$2 (I)I 0x001A
  code        max_stack=2 max_locals=1
    0000 iload_0
    0001 iconst_3
    0002 imul
    0003 ireturn
method        main$lambda$3 (I)I 0x001A
  code        max_stack=2 max_locals=1
    0000 iload_0
    0001 iconst_1
    0002 iadd
    0003 ireturn
method        main$lambda$4 (I)I 0x001A
  code        max_stack=2 max_locals=1
    0000 iload_0
    0001 iconst_2
    0002 imul
    0003 ireturn
method        transform (Lkotlin/jvm/functions/Function1;I)I 0x0019
  code        max_stack=2 max_locals=2
    0000 aload_0
    0001 ldc "f"
    0003 invokestatic Method(kotlin/jvm/internal/Intrinsics.checkNotNullParameter:(Ljava/lang/Object;Ljava/lang/String;)V)
    0006 aload_0
    0007 iload_1
    0008 invokestatic Method(java/lang/Integer.valueOf:(I)Ljava/lang/Integer;)
    0011 invokeinterface InterfaceMethod(kotlin/jvm/functions/Function1.invoke:(Ljava/lang/Object;)Ljava/lang/Object;)
    0016 checkcast Class(java/lang/Number)
    0019 invokevirtual Method(java/lang/Number.intValue:()I)
    0022 ireturn
  attr        Signature (2 bytes)
  attr        RuntimeInvisibleParameterAnnotations (9 bytes)
class_attr    BootstrapMethods (52 bytes)
