class_version major=61 minor=0
this_class    InputKt
super_class   java/lang/Object
access_flags  0x0031
method        main ()V 0x0019
  code        max_stack=2 max_locals=1
    0000 new Class(InputKt$main$1)
    0003 dup
    0004 invokespecial Method(InputKt$main$1.<init>:()V)
    0007 checkcast Class(Action)
    0010 invokestatic Method(InputKt.runAction:(LAction;)V)
    0013 new Class(InputKt$main$2)
    0016 dup
    0017 invokespecial Method(InputKt$main$2.<init>:()V)
    0020 checkcast Class(Transform)
    0023 bipush 7
    0025 invokestatic Method(InputKt.process:(LTransform;I)I)
    0028 istore_0
    0029 getstatic Field(java/lang/System.out:Ljava/io/PrintStream;)
    0032 iload_0
    0033 invokevirtual Method(java/io/PrintStream.println:(I)V)
    0036 return
method        main ([Ljava/lang/String;)V 0x1009
  code        max_stack=0 max_locals=1
    0000 invokestatic Method(InputKt.main:()V)
    0003 return
method        process (LTransform;I)I 0x0019
  code        max_stack=2 max_locals=2
    0000 aload_0
    0001 ldc "t"
    0003 invokestatic Method(kotlin/jvm/internal/Intrinsics.checkNotNullParameter:(Ljava/lang/Object;Ljava/lang/String;)V)
    0006 aload_0
    0007 iload_1
    0008 invokeinterface InterfaceMethod(Transform.apply:(I)I)
    0013 ireturn
  attr        RuntimeInvisibleParameterAnnotations (9 bytes)
method        runAction (LAction;)V 0x0019
  code        max_stack=2 max_locals=1
    0000 aload_0
    0001 ldc "a"
    0003 invokestatic Method(kotlin/jvm/internal/Intrinsics.checkNotNullParameter:(Ljava/lang/Object;Ljava/lang/String;)V)
    0006 aload_0
    0007 invokeinterface InterfaceMethod(Action.execute:()V)
    0012 return
  attr        RuntimeInvisibleParameterAnnotations (7 bytes)
class_attr    InnerClasses (18 bytes)
