class_version major=61 minor=0
this_class    Calculator
super_class   java/lang/Object
access_flags  0x0021
method        <init> ()V 0x0001
  code        max_stack=1 max_locals=1
    0000 aload_0
    0001 invokespecial Method(java/lang/Object.<init>:()V)
    0004 return
method        add (II)I 0x0001
  code        max_stack=2 max_locals=3
    0000 iload_1
    0001 iload_2
    0002 iadd
    0003 ireturn
method        isPositive (I)Z 0x0001
  code        max_stack=1 max_locals=2
    0000 iload_1
    0001 ifle 8
    0004 iconst_1
    0005 goto 9
    0008 iconst_0
    0009 ireturn
    sub_attr  StackMapTable (5 bytes)
method        multiply (II)I 0x0001
  code        max_stack=2 max_locals=3
    0000 iload_1
    0001 iload_2
    0002 imul
    0003 ireturn
