class_version major=61 minor=0
this_class    InputKt
super_class   java/lang/Object
access_flags  0x0031
method        main ()V 0x0019
  code        max_stack=3 max_locals=15
    0000 new Class(Push)
    0003 dup
    0004 iconst_5
    0005 invokespecial Method(Push.<init>:(I)V)
    0008 astore_0
    0009 new Class(JumpIfZero)
    0012 dup
    0013 bipush 9
    0015 invokespecial Method(JumpIfZero.<init>:(I)V)
    0018 astore_1
    0019 new Class(Push)
    0022 dup
    0023 iconst_1
    0024 invokespecial Method(Push.<init>:(I)V)
    0027 astore_2
    0028 new Class(Jump)
    0031 dup
    0032 iconst_1
    0033 invokespecial Method(Jump.<init>:(I)V)
    0036 astore_3
    0037 bipush 10
    0039 anewarray Class(java/lang/Object)
    0042 astore 4
    0044 aload 4
    0046 iconst_0
    0047 aload_0
    0048 aastore
    0049 aload 4
    0051 iconst_1
    0052 getstatic Field(Dup.INSTANCE:LDup;)
    0055 aastore
    0056 aload 4
    0058 iconst_2
    0059 aload_1
    0060 aastore
    0061 aload 4
    0063 iconst_3
    0064 getstatic Field(Dup.INSTANCE:LDup;)
    0067 aastore
    0068 aload 4
    0070 iconst_4
    0071 getstatic Field(Print.INSTANCE:LPrint;)
    0074 aastore
    0075 aload 4
    0077 iconst_5
    0078 aload_2
    0079 aastore
    0080 aload 4
    0082 bipush 6
    0084 getstatic Field(Sub.INSTANCE:LSub;)
    0087 aastore
    0088 aload 4
    0090 bipush 7
    0092 aload_3
    0093 aastore
    0094 aload 4
    0096 bipush 8
    0098 getstatic Field(Halt.INSTANCE:LHalt;)
    0101 aastore
    0102 aload 4
    0104 bipush 9
    0106 getstatic Field(Halt.INSTANCE:LHalt;)
    0109 aastore
    0110 aload 4
    0112 invokestatic Method(kotlin/collections/CollectionsKt.listOf:([Ljava/lang/Object;)Ljava/util/List;)
    0115 astore 5
    0117 new Class(Vm)
    0120 dup
    0121 aload 5
    0123 invokespecial Method(Vm.<init>:(Ljava/util/List;)V)
    0126 invokevirtual Method(Vm.run:()V)
    0129 ldc "---"
    0131 getstatic Field(java/lang/System.out:Ljava/io/PrintStream;)
    0134 swap
    0135 invokevirtual Method(java/io/PrintStream.println:(Ljava/lang/Object;)V)
    0138 new Class(Push)
    0141 dup
    0142 iconst_2
    0143 invokespecial Method(Push.<init>:(I)V)
    0146 astore_0
    0147 new Class(Push)
    0150 dup
    0151 iconst_3
    0152 invokespecial Method(Push.<init>:(I)V)
    0155 astore_1
    0156 new Class(Push)
    0159 dup
    0160 iconst_4
    0161 invokespecial Method(Push.<init>:(I)V)
    0164 astore_2
    0165 bipush 7
    0167 anewarray Class(java/lang/Object)
    0170 astore_3
    0171 aload_3
    0172 iconst_0
    0173 aload_0
    0174 aastore
    0175 aload_3
    0176 iconst_1
    0177 aload_1
    0178 aastore
    0179 aload_3
    0180 iconst_2
    0181 getstatic Field(Add.INSTANCE:LAdd;)
    0184 aastore
    0185 aload_3
    0186 iconst_3
    0187 aload_2
    0188 aastore
    0189 aload_3
    0190 iconst_4
    0191 getstatic Field(Mul.INSTANCE:LMul;)
    0194 aastore
    0195 aload_3
    0196 iconst_5
    0197 getstatic Field(Print.INSTANCE:LPrint;)
    0200 aastore
    0201 aload_3
    0202 bipush 6
    0204 getstatic Field(Halt.INSTANCE:LHalt;)
    0207 aastore
    0208 aload_3
    0209 invokestatic Method(kotlin/collections/CollectionsKt.listOf:([Ljava/lang/Object;)Ljava/util/List;)
    0212 astore 10
    0214 new Class(Vm)
    0217 dup
    0218 aload 10
    0220 invokespecial Method(Vm.<init>:(Ljava/util/List;)V)
    0223 invokevirtual Method(Vm.run:()V)
    0226 ldc "---"
    0228 getstatic Field(java/lang/System.out:Ljava/io/PrintStream;)
    0231 swap
    0232 invokevirtual Method(java/io/PrintStream.println:(Ljava/lang/Object;)V)
    0235 new Class(Push)
    0238 dup
    0239 bipush 10
    0241 invokespecial Method(Push.<init>:(I)V)
    0244 astore_0
    0245 new Class(Push)
    0248 dup
    0249 bipush 20
    0251 invokespecial Method(Push.<init>:(I)V)
    0254 astore_1
    0255 iconst_5
    0256 anewarray Class(java/lang/Object)
    0259 astore_2
    0260 aload_2
    0261 iconst_0
    0262 aload_0
    0263 aastore
    0264 aload_2
    0265 iconst_1
    0266 aload_1
    0267 aastore
    0268 aload_2
    0269 iconst_2
    0270 getstatic Field(Swap.INSTANCE:LSwap;)
    0273 aastore
    0274 aload_2
    0275 iconst_3
    0276 getstatic Field(Print.INSTANCE:LPrint;)
    0279 aastore
    0280 aload_2
    0281 iconst_4
    0282 getstatic Field(Halt.INSTANCE:LHalt;)
    0285 aastore
    0286 aload_2
    0287 invokestatic Method(kotlin/collections/CollectionsKt.listOf:([Ljava/lang/Object;)Ljava/util/List;)
    0290 astore 14
    0292 new Class(Vm)
    0295 dup
    0296 aload 14
    0298 invokespecial Method(Vm.<init>:(Ljava/util/List;)V)
    0301 invokevirtual Method(Vm.run:()V)
    0304 return
method        main ([Ljava/lang/String;)V 0x1009
  code        max_stack=0 max_locals=1
    0000 invokestatic Method(InputKt.main:()V)
    0003 return
