class_version major=61 minor=0
this_class    Person
super_class   java/lang/Object
access_flags  0x0021
field         age : I 0x0001
field         name : Ljava/lang/String; 0x0001
method        <init> (Ljava/lang/String;I)V 0x0001
  code        max_stack=2 max_locals=3
    0000 aload_0
    0001 invokespecial Method(java/lang/Object.<init>:()V)
    0004 aload_0
    0005 aload_1
    0006 putfield Field(Person.name:Ljava/lang/String;)
    0009 aload_0
    0010 iload_2
    0011 putfield Field(Person.age:I)
    0014 return
method        getAge ()I 0x0001
  code        max_stack=1 max_locals=1
    0000 aload_0
    0001 getfield Field(Person.age:I)
    0004 ireturn
method        getName ()Ljava/lang/String; 0x0001
  code        max_stack=1 max_locals=1
    0000 aload_0
    0001 getfield Field(Person.name:Ljava/lang/String;)
    0004 areturn
  attr        RuntimeInvisibleAnnotations (6 bytes)
