class_version major=61 minor=0
this_class    InputKt
super_class   java/lang/Object
access_flags  0x0031
method        joinNodes (Ljava/util/List;)Ljava/lang/String; 0x0019
  code        max_stack=3 max_locals=4
    0000 aload_0
    0001 ldc "xs"
    0003 invokestatic Method(kotlin/jvm/internal/Intrinsics.checkNotNullParameter:(Ljava/lang/Object;Ljava/lang/String;)V)
    0006 new Class(java/lang/StringBuilder)
    0009 dup
    0010 invokespecial Method(java/lang/StringBuilder.<init>:()V)
    0013 astore_1
    0014 iconst_0
    0015 istore_2
    0016 aload_0
    0017 invokeinterface InterfaceMethod(java/util/List.size:()I)
    0022 istore_3
    0023 iload_2
    0024 iload_3
    0025 if_icmpge 35
    0028 iload_2
    0029 ifle 53
    0032 goto 46
    0035 aload_1
    0036 invokevirtual Method(java/lang/StringBuilder.toString:()Ljava/lang/String;)
    0039 dup
    0040 ldc "toString(...)"
    0042 invokestatic Method(kotlin/jvm/internal/Intrinsics.checkNotNullExpressionValue:(Ljava/lang/Object;Ljava/lang/String;)V)
    0045 areturn
    0046 aload_1
    0047 ldc ", "
    0049 invokevirtual Method(java/lang/StringBuilder.append:(Ljava/lang/String;)Ljava/lang/StringBuilder;)
    0052 pop
    0053 aload_0
    0054 iload_2
    0055 invokeinterface InterfaceMethod(java/util/List.get:(I)Ljava/lang/Object;)
    0060 aload_1
    0061 swap
    0062 invokevirtual Method(java/lang/StringBuilder.append:(Ljava/lang/Object;)Ljava/lang/StringBuilder;)
    0065 pop
    0066 iinc 2 1
    0069 goto 16
    sub_attr  StackMapTable (15 bytes)
  attr        Signature (2 bytes)
  attr        RuntimeInvisibleAnnotations (6 bytes)
  attr        RuntimeInvisibleParameterAnnotations (7 bytes)
method        main ()V 0x0019
  code        max_stack=3 max_locals=4
    0000 new Class(Graph)
    0003 dup
    0004 iconst_0
    0005 invokespecial Method(Graph.<init>:(Z)V)
    0008 astore_0
    0009 aload_0
    0010 ldc "A"
    0012 ldc "B"
    0014 invokevirtual Method(Graph.addEdge:(Ljava/lang/Object;Ljava/lang/Object;)V)
    0017 aload_0
    0018 ldc "A"
    0020 ldc "C"
    0022 invokevirtual Method(Graph.addEdge:(Ljava/lang/Object;Ljava/lang/Object;)V)
    0025 aload_0
    0026 ldc "B"
    0028 ldc "D"
    0030 invokevirtual Method(Graph.addEdge:(Ljava/lang/Object;Ljava/lang/Object;)V)
    0033 aload_0
    0034 ldc "C"
    0036 ldc "E"
    0038 invokevirtual Method(Graph.addEdge:(Ljava/lang/Object;Ljava/lang/Object;)V)
    0041 aload_0
    0042 ldc "D"
    0044 ldc "E"
    0046 invokevirtual Method(Graph.addEdge:(Ljava/lang/Object;Ljava/lang/Object;)V)
    0049 aload_0
    0050 ldc "A"
    0052 invokevirtual Method(Graph.bfs:(Ljava/lang/Object;)Ljava/util/List;)
    0055 astore_1
    0056 aload_1
    0057 invokestatic Method(InputKt.joinNodes:(Ljava/util/List;)Ljava/lang/String;)
    0060 invokedynamic InvokeDynamic(makeConcatWithConstants:(Ljava/lang/String;)Ljava/lang/String;)
    0065 getstatic Field(java/lang/System.out:Ljava/io/PrintStream;)
    0068 swap
    0069 invokevirtual Method(java/io/PrintStream.println:(Ljava/lang/Object;)V)
    0072 aload_0
    0073 ldc "E"
    0075 invokevirtual Method(Graph.bfs:(Ljava/lang/Object;)Ljava/util/List;)
    0078 astore_2
    0079 aload_2
    0080 invokestatic Method(InputKt.joinNodes:(Ljava/util/List;)Ljava/lang/String;)
    0083 invokedynamic InvokeDynamic(makeConcatWithConstants:(Ljava/lang/String;)Ljava/lang/String;)
    0088 getstatic Field(java/lang/System.out:Ljava/io/PrintStream;)
    0091 swap
    0092 invokevirtual Method(java/io/PrintStream.println:(Ljava/lang/Object;)V)
    0095 new Class(Graph)
    0098 dup
    0099 iconst_1
    0100 invokespecial Method(Graph.<init>:(Z)V)
    0103 astore_3
    0104 aload_3
    0105 ldc "A"
    0107 ldc "B"
    0109 invokevirtual Method(Graph.addEdge:(Ljava/lang/Object;Ljava/lang/Object;)V)
    0112 aload_3
    0113 ldc "A"
    0115 ldc "C"
    0117 invokevirtual Method(Graph.addEdge:(Ljava/lang/Object;Ljava/lang/Object;)V)
    0120 aload_3
    0121 ldc "B"
    0123 ldc "D"
    0125 invokevirtual Method(Graph.addEdge:(Ljava/lang/Object;Ljava/lang/Object;)V)
    0128 aload_3
    0129 ldc "C"
    0131 ldc "E"
    0133 invokevirtual Method(Graph.addEdge:(Ljava/lang/Object;Ljava/lang/Object;)V)
    0136 aload_3
    0137 ldc "D"
    0139 ldc "E"
    0141 invokevirtual Method(Graph.addEdge:(Ljava/lang/Object;Ljava/lang/Object;)V)
    0144 aload_3
    0145 ldc "A"
    0147 invokevirtual Method(Graph.bfs:(Ljava/lang/Object;)Ljava/util/List;)
    0150 invokestatic Method(InputKt.joinNodes:(Ljava/util/List;)Ljava/lang/String;)
    0153 invokedynamic InvokeDynamic(makeConcatWithConstants:(Ljava/lang/String;)Ljava/lang/String;)
    0158 getstatic Field(java/lang/System.out:Ljava/io/PrintStream;)
    0161 swap
    0162 invokevirtual Method(java/io/PrintStream.println:(Ljava/lang/Object;)V)
    0165 aload_3
    0166 ldc "D"
    0168 invokevirtual Method(Graph.bfs:(Ljava/lang/Object;)Ljava/util/List;)
    0171 invokestatic Method(InputKt.joinNodes:(Ljava/util/List;)Ljava/lang/String;)
    0174 invokedynamic InvokeDynamic(makeConcatWithConstants:(Ljava/lang/String;)Ljava/lang/String;)
    0179 getstatic Field(java/lang/System.out:Ljava/io/PrintStream;)
    0182 swap
    0183 invokevirtual Method(java/io/PrintStream.println:(Ljava/lang/Object;)V)
    0186 return
method        main ([Ljava/lang/String;)V 0x1009
  code        max_stack=0 max_locals=1
    0000 invokestatic Method(InputKt.main:()V)
    0003 return
class_attr    BootstrapMethods (26 bytes)
