class_version major=61 minor=0
this_class    InputKt
super_class   java/lang/Object
access_flags  0x0031
method        main ()V 0x0019
  code        max_stack=6 max_locals=0
    0000 new Class(Circle)
    0003 dup
    0004 op_0x14
    0005 nop
    0006 op_0x27
    0007 invokespecial Method(Circle.<init>:(D)V)
    0010 checkcast Class(Shape)
    0013 invokestatic Method(InputKt.printArea:(LShape;)V)
    0016 new Class(Rectangle)
    0019 dup
    0020 op_0x14
    0021 nop
    0022 op_0x30
    0023 op_0x14
    0024 nop
    0025 op_0x32
    0026 invokespecial Method(Rectangle.<init>:(DD)V)
    0029 checkcast Class(Shape)
    0032 invokestatic Method(InputKt.printArea:(LShape;)V)
    0035 return
method        main ([Ljava/lang/String;)V 0x1009
  code        max_stack=0 max_locals=1
    0000 invokestatic Method(InputKt.main:()V)
    0003 return
method        printArea (LShape;)V 0x0019
  code        max_stack=3 max_locals=3
    0000 aload_0
    0001 ldc "shape"
    0003 invokestatic Method(kotlin/jvm/internal/Intrinsics.checkNotNullParameter:(Ljava/lang/Object;Ljava/lang/String;)V)
    0006 aload_0
    0007 invokeinterface InterfaceMethod(Shape.area:()D)
    0012 op_0x48
    0013 getstatic Field(java/lang/System.out:Ljava/io/PrintStream;)
    0016 op_0x27
    0017 invokevirtual Method(java/io/PrintStream.println:(D)V)
    0020 return
  attr        RuntimeInvisibleParameterAnnotations (7 bytes)
