class_version major=61 minor=0
this_class    InputKt
super_class   java/lang/Object
access_flags  0x0031
method        html (Lkotlin/jvm/functions/Function1;)V 0x0019
  code        max_stack=2 max_locals=2
    0000 aload_0
    0001 ldc "init"
    0003 invokestatic Method(kotlin/jvm/internal/Intrinsics.checkNotNullParameter:(Ljava/lang/Object;Ljava/lang/String;)V)
    0006 new Class(HTML)
    0009 dup
    0010 invokespecial Method(HTML.<init>:()V)
    0013 astore_1
    0014 aload_0
    0015 aload_1
    0016 invokeinterface InterfaceMethod(kotlin/jvm/functions/Function1.invoke:(Ljava/lang/Object;)Ljava/lang/Object;)
    0021 pop
    0022 return
  attr        Signature (2 bytes)
  attr        RuntimeInvisibleParameterAnnotations (7 bytes)
method        main ()V 0x0019
  code        max_stack=1 max_locals=0
    0000 invokedynamic InvokeDynamic(invoke:()Lkotlin/jvm/functions/Function1;)
    0005 invokestatic Method(InputKt.html:(Lkotlin/jvm/functions/Function1;)V)
    0008 return
method        main ([Ljava/lang/String;)V 0x1009
  code        max_stack=0 max_locals=1
    0000 invokestatic Method(InputKt.main:()V)
    0003 return
method        main$lambda$0 (LHTML;)Lkotlin/Unit; 0x001A
  code        max_stack=2 max_locals=1
    0000 aload_0
    0001 ldc "$this$html"
    0003 invokestatic Method(kotlin/jvm/internal/Intrinsics.checkNotNullParameter:(Ljava/lang/Object;Ljava/lang/String;)V)
    0006 aload_0
    0007 invokevirtual Method(HTML.foo:()V)
    0010 getstatic Field(kotlin/Unit.INSTANCE:Lkotlin/Unit;)
    0013 areturn
class_attr    BootstrapMethods (12 bytes)
