class_version major=61 minor=0
this_class    Point
super_class   java/lang/Object
access_flags  0x0021
field         x : I 0x0001
field         y : I 0x0001
method        <init> (II)V 0x0001
  code        max_stack=2 max_locals=3
    0000 aload_0
    0001 invokespecial Method(java/lang/Object.<init>:()V)
    0004 aload_0
    0005 iload_1
    0006 putfield Field(Point.x:I)
    0009 aload_0
    0010 iload_2
    0011 putfield Field(Point.y:I)
    0014 return
method        distFromOriginSquared ()I 0x0001
  code        max_stack=3 max_locals=3
    0000 aload_0
    0001 getfield Field(Point.x:I)
    0004 istore_1
    0005 aload_0
    0006 getfield Field(Point.y:I)
    0009 istore_2
    0010 iload_1
    0011 iload_1
    0012 imul
    0013 iload_2
    0014 iload_2
    0015 imul
    0016 iadd
    0017 aload_0
    0018 iload_1
    0019 putfield Field(Point.x:I)
    0022 aload_0
    0023 iload_2
    0024 putfield Field(Point.y:I)
    0027 ireturn
method        getX ()I 0x0001
  code        max_stack=1 max_locals=1
    0000 aload_0
    0001 getfield Field(Point.x:I)
    0004 ireturn
method        getY ()I 0x0001
  code        max_stack=1 max_locals=1
    0000 aload_0
    0001 getfield Field(Point.y:I)
    0004 ireturn
