Compiled from "com/example/compose/jetchat/components/AnimatingFabContent.kt"
public final class com.example.compose.jetchat.components.AnimatingFabContentKt {
  public static final int transitionDuration;

  public static final <T> void AnimatingFabContent(kotlin.jvm.functions.Function2, kotlin.jvm.functions.Function2, androidx.compose.ui.Modifier, boolean, androidx.compose.runtime.Composer, int);
    Code:
         0: aload_0
         1: ldc           #13                 // String icon
         3: invokestatic  #19                 // Method kotlin/jvm/internal/Intrinsics.checkNotNullParameter:(Ljava/lang/Object;Ljava/lang/String;)V
         6: aload_1
         7: ldc           #21                 // String text
         9: invokestatic  #19                 // Method kotlin/jvm/internal/Intrinsics.checkNotNullParameter:(Ljava/lang/Object;Ljava/lang/String;)V
        12: aload_2
        13: ldc           #23                 // String modifier
        15: invokestatic  #19                 // Method kotlin/jvm/internal/Intrinsics.checkNotNullParameter:(Ljava/lang/Object;Ljava/lang/String;)V
        18: iload_3
        19: ifeq          31
        22: aconst_null
        23: getfield      #29                 // Field com/example/compose/jetchat/components/ExpandableFabStates.Extended:Ljava/lang/Object;
        26: astore        6
        28: goto          37
        31: aconst_null
        32: getfield      #32                 // Field com/example/compose/jetchat/components/ExpandableFabStates.Collapsed:Ljava/lang/Object;
        35: astore        6
        37: aload         6
        39: checkcast     #34                 // class androidx/compose/animation/core/MutableTransitionState
        42: ldc           #36                 // String fab_transition
        44: aload         4
        46: iload         5
        48: iconst_0
        49: invokestatic  #42                 // Method androidx/compose/animation/core/TransitionKt.updateTransition:(Landroidx/compose/animation/core/MutableTransitionState;Ljava/lang/String;Landroidx/compose/runtime/Composer;II)Landroidx/compose/animation/core/Transition;
        52: astore        7
        54: new           #44                 // class com/example/compose/jetchat/components/AnimatingFabContentKt$Lambda$23
        57: dup
        58: invokespecial #48                 // Method com/example/compose/jetchat/components/AnimatingFabContentKt$Lambda$23."<init>":()V
        61: pop
        62: invokedynamic #68,  0             // InvokeDynamic #0:invoke:()Lkotlin/jvm/functions/Function1;
        67: astore        8
        69: new           #70                 // class com/example/compose/jetchat/components/AnimatingFabContentKt$Lambda$24
        72: dup
        73: invokespecial #71                 // Method com/example/compose/jetchat/components/AnimatingFabContentKt$Lambda$24."<init>":()V
        76: pop
        77: invokedynamic #76,  0             // InvokeDynamic #1:invoke:()Lkotlin/jvm/functions/Function1;
        82: astore        9
        84: aconst_null
        85: astore        10
        87: new           #78                 // class com/example/compose/jetchat/components/AnimatingFabContentKt$Lambda$25
        90: dup
        91: invokespecial #79                 // Method com/example/compose/jetchat/components/AnimatingFabContentKt$Lambda$25."<init>":()V
        94: pop
        95: invokedynamic #84,  0             // InvokeDynamic #2:invoke:()Lkotlin/jvm/functions/Function1;
       100: astore        11
       102: new           #86                 // class com/example/compose/jetchat/components/AnimatingFabContentKt$Lambda$26
       105: dup
       106: invokespecial #87                 // Method com/example/compose/jetchat/components/AnimatingFabContentKt$Lambda$26."<init>":()V
       109: pop
       110: invokedynamic #92,  0             // InvokeDynamic #3:invoke:()Lkotlin/jvm/functions/Function1;
       115: astore        12
       117: aconst_null
       118: astore        13
       120: new           #94                 // class com/example/compose/jetchat/components/AnimatingFabContentKt$Lambda$27
       123: dup
       124: aload         10
       126: invokespecial #97                 // Method com/example/compose/jetchat/components/AnimatingFabContentKt$Lambda$27."<init>":(Ljava/lang/Object;)V
       129: astore        14
       131: new           #99                 // class com/example/compose/jetchat/components/AnimatingFabContentKt$Lambda$28
       134: dup
       135: aload         13
       137: invokespecial #100                // Method com/example/compose/jetchat/components/AnimatingFabContentKt$Lambda$28."<init>":(Ljava/lang/Object;)V
       140: astore        15
       142: aload_0
       143: aload_1
       144: aload         14
       146: checkcast     #102                // class kotlin/jvm/functions/Function0
       149: aload         15
       151: checkcast     #102                // class kotlin/jvm/functions/Function0
       154: aload_2
       155: aload         4
       157: iconst_0
       158: invokestatic  #106                // Method IconAndTextRow:(Lkotlin/jvm/functions/Function2;Lkotlin/jvm/functions/Function2;Lkotlin/jvm/functions/Function0;Lkotlin/jvm/functions/Function0;Landroidx/compose/ui/Modifier;Landroidx/compose/runtime/Composer;I)V
       161: return

  private static final kotlin.Unit AnimatingFabContent$lambda$0(kotlin.jvm.functions.Function2, kotlin.jvm.functions.Function2, androidx.compose.ui.Modifier, boolean, int, androidx.compose.runtime.Composer, int);
    Code:
         0: aload_0
         1: aload_1
         2: aload_2
         3: iload_3
         4: aload         5
         6: iload         4
         8: iconst_1
         9: ior
        10: invokestatic  #125                // Method androidx/compose/runtime/RecomposeScopeImplKt.updateChangedFlags:(I)I
        13: invokestatic  #127                // Method AnimatingFabContent:(Lkotlin/jvm/functions/Function2;Lkotlin/jvm/functions/Function2;Landroidx/compose/ui/Modifier;ZLandroidx/compose/runtime/Composer;I)V
        16: getstatic     #133                // Field kotlin/Unit.INSTANCE:Lkotlin/Unit;
        19: areturn

  public static void AnimatingFabContent$default(kotlin.jvm.functions.Function2, kotlin.jvm.functions.Function2, androidx.compose.ui.Modifier, boolean, androidx.compose.runtime.Composer, int, int, java.lang.Object);
    Code:
         0: iload         6
         2: bipush        8
         4: iand
         5: ifeq          10
         8: iconst_1
         9: istore_3
        10: aload_0
        11: aload_1
        12: aload_2
        13: iload_3
        14: aload         4
        16: iload         5
        18: invokestatic  #127                // Method AnimatingFabContent:(Lkotlin/jvm/functions/Function2;Lkotlin/jvm/functions/Function2;Landroidx/compose/ui/Modifier;ZLandroidx/compose/runtime/Composer;I)V
        21: return

  public static final <T> void IconAndTextRow(kotlin.jvm.functions.Function2, kotlin.jvm.functions.Function2, kotlin.jvm.functions.Function0, kotlin.jvm.functions.Function0, androidx.compose.ui.Modifier, androidx.compose.runtime.Composer, int);
    Code:
         0: aload         5
         2: ldc           #159                // int -2022106602
         4: invokeinterface #143,  2          // InterfaceMethod androidx/compose/runtime/Composer.startRestartGroup:(I)Landroidx/compose/runtime/Composer;
         9: astore        5
        11: aload         5
        13: iload         6
        15: ifeq          22
        18: iconst_1
        19: goto          23
        22: iconst_0
        23: iload         6
        25: iconst_1
        26: iand
        27: invokeinterface #147,  3          // InterfaceMethod androidx/compose/runtime/Composer.shouldExecute:(ZI)Z
        32: ifne          45
        35: aload         5
        37: invokeinterface #150,  1          // InterfaceMethod androidx/compose/runtime/Composer.skipToGroupEnd:()V
        42: goto          85
        45: new           #161                // class com/example/compose/jetchat/components/AnimatingFabContentKt$Lambda$29
        48: dup
        49: aload_0
        50: aload_2
        51: aload_1
        52: invokespecial #164                // Method com/example/compose/jetchat/components/AnimatingFabContentKt$Lambda$29."<init>":(Lkotlin/jvm/functions/Function2;Lkotlin/jvm/functions/Function0;Lkotlin/jvm/functions/Function2;)V
        55: astore        7
        57: new           #166                // class com/example/compose/jetchat/components/AnimatingFabContentKt$Lambda$33
        60: dup
        61: aload_3
        62: invokespecial #169                // Method com/example/compose/jetchat/components/AnimatingFabContentKt$Lambda$33."<init>":(Lkotlin/jvm/functions/Function0;)V
        65: astore        8
        67: aload         4
        69: aload         7
        71: checkcast     #171                // class androidx/compose/ui/layout/MeasurePolicy
        74: aload         8
        76: checkcast     #112                // class androidx/compose/runtime/Composer
        79: iload         6
        81: iconst_0
        82: invokestatic  #177                // Method androidx/compose/ui/layout/LayoutKt.Layout:(Landroidx/compose/ui/Modifier;Landroidx/compose/ui/layout/MeasurePolicy;Landroidx/compose/runtime/Composer;II)V
        85: aload         5
        87: invokeinterface #154,  1          // InterfaceMethod androidx/compose/runtime/Composer.endRestartGroup:()Landroidx/compose/runtime/ScopeUpdateScope;
        92: dup
        93: ifnull        117
        96: aload_0
        97: aload_1
        98: aload_2
        99: aload_3
       100: aload         4
       102: iload         6
       104: invokedynamic #189,  0            // InvokeDynamic #4:invoke:(Lkotlin/jvm/functions/Function2;Lkotlin/jvm/functions/Function2;Lkotlin/jvm/functions/Function0;Lkotlin/jvm/functions/Function0;Landroidx/compose/ui/Modifier;I)Lkotlin/jvm/functions/Function2;
       109: invokeinterface #158,  2          // InterfaceMethod androidx/compose/runtime/ScopeUpdateScope.updateScope:(Lkotlin/jvm/functions/Function2;)V
       114: goto          118
       117: pop
       118: return

  private static final kotlin.Unit IconAndTextRow$lambda$0(kotlin.jvm.functions.Function2, kotlin.jvm.functions.Function2, kotlin.jvm.functions.Function0, kotlin.jvm.functions.Function0, androidx.compose.ui.Modifier, int, androidx.compose.runtime.Composer, int);
    Code:
         0: aload_0
         1: aload_1
         2: aload_2
         3: aload_3
         4: aload         4
         6: aload         6
         8: iload         5
        10: iconst_1
        11: ior
        12: invokestatic  #125                // Method androidx/compose/runtime/RecomposeScopeImplKt.updateChangedFlags:(I)I
        15: invokestatic  #106                // Method IconAndTextRow:(Lkotlin/jvm/functions/Function2;Lkotlin/jvm/functions/Function2;Lkotlin/jvm/functions/Function0;Lkotlin/jvm/functions/Function0;Landroidx/compose/ui/Modifier;Landroidx/compose/runtime/Composer;I)V
        18: getstatic     #133                // Field kotlin/Unit.INSTANCE:Lkotlin/Unit;
        21: areturn

  public static final float AnimatingFabContent$lambda$0(java.lang.Object);
    Code:
         0: aconst_null
         1: getfield      #32                 // Field com/example/compose/jetchat/components/ExpandableFabStates.Collapsed:Ljava/lang/Object;
         4: aload_0
         5: swap
         6: if_acmpne     14
         9: fconst_0
        10: fstore_1
        11: goto          16
        14: fconst_1
        15: fstore_1
        16: fload_1
        17: freturn

  public static final float AnimatingFabContent$lambda$1(java.lang.Object);
    Code:
         0: aconst_null
         1: getfield      #32                 // Field com/example/compose/jetchat/components/ExpandableFabStates.Collapsed:Ljava/lang/Object;
         4: aload_0
         5: swap
         6: if_acmpne     14
         9: fconst_0
        10: fstore_1
        11: goto          16
        14: fconst_1
        15: fstore_1
        16: fload_1
        17: freturn

  public static final float AnimatingFabContent$lambda$2(java.lang.Object);
    Code:
         0: aconst_null
         1: getfield      #32                 // Field com/example/compose/jetchat/components/ExpandableFabStates.Collapsed:Ljava/lang/Object;
         4: aload_0
         5: swap
         6: if_acmpne     14
         9: fconst_0
        10: fstore_1
        11: goto          16
        14: fconst_1
        15: fstore_1
        16: fload_1
        17: freturn

  public static final float AnimatingFabContent$lambda$3(java.lang.Object);
    Code:
         0: aconst_null
         1: getfield      #32                 // Field com/example/compose/jetchat/components/ExpandableFabStates.Collapsed:Ljava/lang/Object;
         4: aload_0
         5: swap
         6: if_acmpne     14
         9: fconst_0
        10: fstore_1
        11: goto          16
        14: fconst_1
        15: fstore_1
        16: fload_1
        17: freturn

  public static final com.example.compose.jetchat.components.ExpandableFabStates Collapsed();
    Code:
         0: getstatic     #194                // Field com/example/compose/jetchat/components/ExpandableFabStates.Collapsed:LExpandableFabStates;
         3: areturn

  public static final com.example.compose.jetchat.components.ExpandableFabStates Extended();
    Code:
         0: getstatic     #196                // Field com/example/compose/jetchat/components/ExpandableFabStates.Extended:LExpandableFabStates;
         3: areturn

  public static final java.util.ArrayList ExpandableFabStates$values();
    Code:
         0: new           #200                // class java/util/ArrayList
         3: dup
         4: invokespecial #201                // Method java/util/ArrayList."<init>":()V
         7: astore_0
         8: aload_0
         9: invokestatic  #203                // Method Collapsed:()Lcom/example/compose/jetchat/components/ExpandableFabStates;
        12: invokevirtual #207                // Method java/util/ArrayList.add:(Ljava/lang/Object;)Z
        15: pop
        16: aload_0
        17: invokestatic  #209                // Method Extended:()Lcom/example/compose/jetchat/components/ExpandableFabStates;
        20: invokevirtual #207                // Method java/util/ArrayList.add:(Ljava/lang/Object;)Z
        23: pop
        24: aload_0
        25: areturn

  public static final com.example.compose.jetchat.components.ExpandableFabStates ExpandableFabStates$valueOf(java.lang.String);
    Code:
         0: aload_0
         1: ldc           #213                // String name
         3: invokestatic  #19                 // Method kotlin/jvm/internal/Intrinsics.checkNotNullParameter:(Ljava/lang/Object;Ljava/lang/String;)V
         6: aload_0
         7: ldc           #214                // String Collapsed
         9: invokestatic  #218                // Method kotlin/jvm/internal/Intrinsics.areEqual:(Ljava/lang/Object;Ljava/lang/Object;)Z
        12: ifeq          22
        15: goto          35
        18: invokestatic  #203                // Method Collapsed:()Lcom/example/compose/jetchat/components/ExpandableFabStates;
        21: areturn
        22: aload_0
        23: ldc           #219                // String Extended
        25: invokestatic  #218                // Method kotlin/jvm/internal/Intrinsics.areEqual:(Ljava/lang/Object;Ljava/lang/Object;)Z
        28: ifeq          18
        31: invokestatic  #209                // Method Extended:()Lcom/example/compose/jetchat/components/ExpandableFabStates;
        34: areturn
        35: invokestatic  #203                // Method Collapsed:()Lcom/example/compose/jetchat/components/ExpandableFabStates;
        38: areturn
}
