Compiled from "com/example/compose/jetchat/components/ExpandableFabStates.kt"
public final class com.example.compose.jetchat.components.ExpandableFabStates {
  public java.lang.String name;

  public static final ExpandableFabStates Collapsed;

  public static final ExpandableFabStates Extended;

  public static final int $stable;

  static {};
    Code:
         0: new           #18                 // class ExpandableFabStates
         3: dup
         4: ldc           #19                 // String Collapsed
         6: invokespecial #23                 // Method ExpandableFabStates."<init>":(Ljava/lang/String;)V
         9: putstatic     #25                 // Field ExpandableFabStates.Collapsed:LExpandableFabStates;
        12: new           #18                 // class ExpandableFabStates
        15: dup
        16: ldc           #26                 // String Extended
        18: invokespecial #23                 // Method ExpandableFabStates."<init>":(Ljava/lang/String;)V
        21: putstatic     #28                 // Field ExpandableFabStates.Extended:LExpandableFabStates;
        24: return

  public com.example.compose.jetchat.components.ExpandableFabStates(java.lang.String);
    Code:
         0: aload_0
         1: invokespecial #30                 // Method java/lang/Object."<init>":()V
         4: aload_0
         5: aload_1
         6: putfield      #32                 // Field name:Ljava/lang/String;
         9: return

  public java.lang.String toString();
    Code:
         0: aload_0
         1: getfield      #32                 // Field name:Ljava/lang/String;
         4: areturn

  public final java.lang.String getName();
    Code:
         0: aload_0
         1: getfield      #32                 // Field name:Ljava/lang/String;
         4: areturn
}
