Compiled from "com/example/compose/jetchat/conversation/SymbolAnnotationType.kt"
public final class com.example.compose.jetchat.conversation.SymbolAnnotationType {
  public java.lang.String name;

  public static final SymbolAnnotationType PERSON;

  public static final SymbolAnnotationType LINK;

  public static final int $stable;

  static {};
    Code:
         0: new           #18                 // class SymbolAnnotationType
         3: dup
         4: ldc           #19                 // String PERSON
         6: invokespecial #23                 // Method SymbolAnnotationType."<init>":(Ljava/lang/String;)V
         9: putstatic     #25                 // Field SymbolAnnotationType.PERSON:LSymbolAnnotationType;
        12: new           #18                 // class SymbolAnnotationType
        15: dup
        16: ldc           #26                 // String LINK
        18: invokespecial #23                 // Method SymbolAnnotationType."<init>":(Ljava/lang/String;)V
        21: putstatic     #28                 // Field SymbolAnnotationType.LINK:LSymbolAnnotationType;
        24: return

  public com.example.compose.jetchat.conversation.SymbolAnnotationType(java.lang.String);
    Code:
         0: aload_0
         1: invokespecial #30                 // Method java/lang/Object."<init>":()V
         4: aload_0
         5: aload_1
         6: putfield      #32                 // Field name:Ljava/lang/String;
         9: return

  public java.lang.String toString();
    Code:
         0: aload_0
         1: getfield      #32                 // Field name:Ljava/lang/String;
         4: areturn

  public final java.lang.String getName();
    Code:
         0: aload_0
         1: getfield      #32                 // Field name:Ljava/lang/String;
         4: areturn
}
