Compiled from "com/example/compose/jetchat/conversation/UserInput.kt"
public final class com.example.compose.jetchat.conversation.UserInputKt {
  public static final int EMOJI_COLUMNS;

  private static final androidx.compose.ui.semantics.SemanticsPropertyKey KeyboardShownKey;

  private static final java.lang.Object emojis;

  public static final androidx.compose.ui.semantics.SemanticsPropertyKey getKeyboardShownKey();
    Code:
         0: getstatic     #16                 // Field KeyboardShownKey:Landroidx/compose/ui/semantics/SemanticsPropertyKey;
         3: areturn

  public static final java.lang.Object getEmojis();
    Code:
         0: getstatic     #22                 // Field emojis:Ljava/lang/Object;
         3: areturn

  public static final void UserInputPreview(androidx.compose.runtime.Composer, int);
    Code:
         0: aload_0
         1: ldc           #51                 // int 435691402
         3: invokeinterface #34,  2           // InterfaceMethod androidx/compose/runtime/Composer.startRestartGroup:(I)Landroidx/compose/runtime/Composer;
         8: astore_0
         9: aload_0
        10: iload_1
        11: ifeq          18
        14: iconst_1
        15: goto          19
        18: iconst_0
        19: iload_1
        20: iconst_1
        21: iand
        22: invokeinterface #38,  3           // InterfaceMethod androidx/compose/runtime/Composer.shouldExecute:(ZI)Z
        27: ifne          39
        30: aload_0
        31: invokeinterface #42,  1           // InterfaceMethod androidx/compose/runtime/Composer.skipToGroupEnd:()V
        36: goto          55
        39: new           #53                 // class com/example/compose/jetchat/conversation/UserInputKt$Lambda$25
        42: dup
        43: invokespecial #56                 // Method com/example/compose/jetchat/conversation/UserInputKt$Lambda$25."<init>":()V
        46: astore_2
        47: aload_2
        48: aconst_null
        49: iconst_0
        50: aload_0
        51: iconst_0
        52: invokestatic  #60                 // Method UserInput:(Lkotlin/jvm/functions/Function1;Lcom/example/compose/jetchat/conversation/Modifier;Lkotlin/jvm/functions/Function0;Landroidx/compose/runtime/Composer;I)V
        55: aload_0
        56: invokeinterface #46,  1           // InterfaceMethod androidx/compose/runtime/Composer.endRestartGroup:()Landroidx/compose/runtime/ScopeUpdateScope;
        61: dup
        62: ifnull        79
        65: iload_1
        66: invokedynamic #80,  0             // InvokeDynamic #0:invoke:(I)Lkotlin/jvm/functions/Function2;
        71: invokeinterface #50,  2           // InterfaceMethod androidx/compose/runtime/ScopeUpdateScope.updateScope:(Lkotlin/jvm/functions/Function2;)V
        76: goto          80
        79: pop
        80: return

  private static final kotlin.Unit UserInputPreview$lambda$0(int, androidx.compose.runtime.Composer, int);
    Code:
         0: aload_1
         1: iload_0
         2: iconst_1
         3: ior
         4: invokestatic  #92                 // Method androidx/compose/runtime/RecomposeScopeImplKt.updateChangedFlags:(I)I
         7: invokestatic  #94                 // Method UserInputPreview:(Landroidx/compose/runtime/Composer;I)V
        10: getstatic     #100                // Field kotlin/Unit.INSTANCE:Lkotlin/Unit;
        13: areturn

  public static final void UserInput(kotlin.jvm.functions.Function1, com.example.compose.jetchat.conversation.Modifier, kotlin.jvm.functions.Function0, androidx.compose.runtime.Composer, int);
    Code:
         0: aload_3
         1: ldc           #101                // int 1847406486
         3: invokeinterface #34,  2           // InterfaceMethod androidx/compose/runtime/Composer.startRestartGroup:(I)Landroidx/compose/runtime/Composer;
         8: astore_3
         9: aload_3
        10: iload         4
        12: ifeq          19
        15: iconst_1
        16: goto          20
        19: iconst_0
        20: iload         4
        22: iconst_1
        23: iand
        24: invokeinterface #38,  3           // InterfaceMethod androidx/compose/runtime/Composer.shouldExecute:(ZI)Z
        29: ifne          38
        32: aload_3
        33: invokeinterface #42,  1           // InterfaceMethod androidx/compose/runtime/Composer.skipToGroupEnd:()V
        38: aload_3
        39: invokeinterface #46,  1           // InterfaceMethod androidx/compose/runtime/Composer.endRestartGroup:()Landroidx/compose/runtime/ScopeUpdateScope;
        44: dup
        45: ifnull        66
        48: aload_0
        49: aload_1
        50: aload_2
        51: iload         4
        53: invokedynamic #109,  0            // InvokeDynamic #1:invoke:(Lkotlin/jvm/functions/Function1;Lcom/example/compose/jetchat/conversation/Modifier;Lkotlin/jvm/functions/Function0;I)Lkotlin/jvm/functions/Function2;
        58: invokeinterface #50,  2           // InterfaceMethod androidx/compose/runtime/ScopeUpdateScope.updateScope:(Lkotlin/jvm/functions/Function2;)V
        63: goto          67
        66: pop
        67: return

  private static final kotlin.Unit UserInput$lambda$0(kotlin.jvm.functions.Function1, com.example.compose.jetchat.conversation.Modifier, kotlin.jvm.functions.Function0, int, androidx.compose.runtime.Composer, int);
    Code:
         0: aload_0
         1: aload_1
         2: aload_2
         3: aload         4
         5: iload_3
         6: iconst_1
         7: ior
         8: invokestatic  #92                 // Method androidx/compose/runtime/RecomposeScopeImplKt.updateChangedFlags:(I)I
        11: invokestatic  #60                 // Method UserInput:(Lkotlin/jvm/functions/Function1;Lcom/example/compose/jetchat/conversation/Modifier;Lkotlin/jvm/functions/Function0;Landroidx/compose/runtime/Composer;I)V
        14: getstatic     #100                // Field kotlin/Unit.INSTANCE:Lkotlin/Unit;
        17: areturn

  private static final com.example.compose.jetchat.conversation.TextFieldValue addText(java.lang.Object, com.example.compose.jetchat.conversation.TextFieldValue);
    Code:
         0: aload_0
         1: ldc           #119                // String <this>
         3: invokestatic  #125                // Method kotlin/jvm/internal/Intrinsics.checkNotNullParameter:(Ljava/lang/Object;Ljava/lang/String;)V
         6: aload_1
         7: ldc           #127                // String newString
         9: invokestatic  #125                // Method kotlin/jvm/internal/Intrinsics.checkNotNullParameter:(Ljava/lang/Object;Ljava/lang/String;)V
        12: aconst_null
        13: areturn

  private static final <T> void SelectorExpanded(com.example.compose.jetchat.conversation.InputSelector, kotlin.jvm.functions.Function0, kotlin.jvm.functions.Function1, androidx.compose.runtime.Composer, int);
    Code:
         0: aload_0
         1: ldc           #133                // String currentSelector
         3: invokestatic  #125                // Method kotlin/jvm/internal/Intrinsics.checkNotNullParameter:(Ljava/lang/Object;Ljava/lang/String;)V
         6: aload_1
         7: ldc           #135                // String onCloseRequested
         9: invokestatic  #125                // Method kotlin/jvm/internal/Intrinsics.checkNotNullParameter:(Ljava/lang/Object;Ljava/lang/String;)V
        12: aload_2
        13: ldc           #137                // String onTextAdded
        15: invokestatic  #125                // Method kotlin/jvm/internal/Intrinsics.checkNotNullParameter:(Ljava/lang/Object;Ljava/lang/String;)V
        18: invokestatic  #141                // Method NONE:()Lcom/example/compose/jetchat/conversation/InputSelector;
        21: aload_0
        22: swap
        23: swap
        24: invokevirtual #145                // Method java/lang/Object.toString:()Ljava/lang/String;
        27: swap
        28: invokevirtual #145                // Method java/lang/Object.toString:()Ljava/lang/String;
        31: invokevirtual #151                // Method java/lang/String.equals:(Ljava/lang/Object;)Z
        34: ifeq          38
        37: return
        38: new           #153                // class com/example/compose/jetchat/conversation/UserInputKt$Lambda$30
        41: dup
        42: invokespecial #154                // Method com/example/compose/jetchat/conversation/UserInputKt$Lambda$30."<init>":()V
        45: checkcast     #115                // class kotlin/jvm/functions/Function0
        48: aload_3
        49: iload         4
        51: invokestatic  #160                // Method androidx/compose/runtime/ComposablesKt.remember:(Lkotlin/jvm/functions/Function0;Landroidx/compose/runtime/Composer;I)Ljava/lang/Object;
        54: astore        5
        56: new           #162                // class com/example/compose/jetchat/conversation/UserInputKt$Lambda$31
        59: dup
        60: aload_0
        61: aload         5
        63: invokespecial #165                // Method com/example/compose/jetchat/conversation/UserInputKt$Lambda$31."<init>":(Lcom/example/compose/jetchat/conversation/InputSelector;Ljava/lang/Object;)V
        66: checkcast     #115                // class kotlin/jvm/functions/Function0
        69: aload_3
        70: iload         4
        72: invokestatic  #171                // Method androidx/compose/runtime/EffectsKt.SideEffect:(Lkotlin/jvm/functions/Function0;Landroidx/compose/runtime/Composer;I)V
        75: bipush        8
        77: i2f
        78: fstore        6
        80: new           #173                // class com/example/compose/jetchat/conversation/UserInputKt$Lambda$32
        83: dup
        84: aload_0
        85: aload_2
        86: aload         5
        88: aload_1
        89: invokespecial #176                // Method com/example/compose/jetchat/conversation/UserInputKt$Lambda$32."<init>":(Lcom/example/compose/jetchat/conversation/InputSelector;Lkotlin/jvm/functions/Function1;Ljava/lang/Object;Lkotlin/jvm/functions/Function0;)V
        92: pop
        93: return

  private static final kotlin.Unit SelectorExpanded$lambda$0(com.example.compose.jetchat.conversation.InputSelector, kotlin.jvm.functions.Function0, kotlin.jvm.functions.Function1, int, androidx.compose.runtime.Composer, int);
    Code:
         0: aload_0
         1: aload_1
         2: aload_2
         3: aload         4
         5: iload_3
         6: iconst_1
         7: ior
         8: invokestatic  #92                 // Method androidx/compose/runtime/RecomposeScopeImplKt.updateChangedFlags:(I)I
        11: invokestatic  #183                // Method SelectorExpanded:(Lcom/example/compose/jetchat/conversation/InputSelector;Lkotlin/jvm/functions/Function0;Lkotlin/jvm/functions/Function1;Landroidx/compose/runtime/Composer;I)V
        14: getstatic     #100                // Field kotlin/Unit.INSTANCE:Lkotlin/Unit;
        17: areturn

  public static final void FunctionalityNotAvailablePanel(androidx.compose.runtime.Composer, int);
    Code:
         0: return

  private static final kotlin.Unit FunctionalityNotAvailablePanel$lambda$0(int, androidx.compose.runtime.Composer, int);
    Code:
         0: aload_1
         1: iload_0
         2: iconst_1
         3: ior
         4: invokestatic  #92                 // Method androidx/compose/runtime/RecomposeScopeImplKt.updateChangedFlags:(I)I
         7: invokestatic  #187                // Method FunctionalityNotAvailablePanel:(Landroidx/compose/runtime/Composer;I)V
        10: getstatic     #100                // Field kotlin/Unit.INSTANCE:Lkotlin/Unit;
        13: areturn

  public static final <T> void UserInputSelector(kotlin.jvm.functions.Function1, boolean, kotlin.jvm.functions.Function0, com.example.compose.jetchat.conversation.InputSelector, androidx.compose.ui.Modifier, androidx.compose.runtime.Composer, int);
    Code:
         0: aload         5
         2: ldc           #190                // int -1179243053
         4: invokeinterface #34,  2           // InterfaceMethod androidx/compose/runtime/Composer.startRestartGroup:(I)Landroidx/compose/runtime/Composer;
         9: astore        5
        11: aload         5
        13: iload         6
        15: ifeq          22
        18: iconst_1
        19: goto          23
        22: iconst_0
        23: iload         6
        25: iconst_1
        26: iand
        27: invokeinterface #38,  3           // InterfaceMethod androidx/compose/runtime/Composer.shouldExecute:(ZI)Z
        32: ifne          45
        35: aload         5
        37: invokeinterface #42,  1           // InterfaceMethod androidx/compose/runtime/Composer.skipToGroupEnd:()V
        42: goto          96
        45: bipush        72
        47: i2f
        48: fstore        7
        50: bipush        72
        52: i2f
        53: fstore        8
        55: aload         4
        57: fload         8
        59: invokevirtual #196                // Method androidx/compose/ui/Modifier.height:(F)V
        62: bipush        16
        64: i2f
        65: fstore        9
        67: bipush        16
        69: i2f
        70: fstore        10
        72: bipush        16
        74: i2f
        75: fstore        11
        77: getstatic     #202                // Field androidx/compose/ui/Alignment.Companion:Landroidx/compose/ui/Alignment$Companion;
        80: invokevirtual #208                // Method androidx/compose/ui/Alignment$Companion.getCenterVertically:()Landroidx/compose/ui/Alignment$Vertical;
        83: pop
        84: new           #210                // class com/example/compose/jetchat/conversation/UserInputKt$Lambda$37
        87: dup
        88: aload_0
        89: aload_3
        90: iload_1
        91: aload_2
        92: invokespecial #213                // Method com/example/compose/jetchat/conversation/UserInputKt$Lambda$37."<init>":(Lkotlin/jvm/functions/Function1;Lcom/example/compose/jetchat/conversation/InputSelector;ZLkotlin/jvm/functions/Function0;)V
        95: pop
        96: aload         5
        98: invokeinterface #46,  1           // InterfaceMethod androidx/compose/runtime/Composer.endRestartGroup:()Landroidx/compose/runtime/ScopeUpdateScope;
       103: dup
       104: ifnull        128
       107: aload_0
       108: iload_1
       109: aload_2
       110: aload_3
       111: aload         4
       113: iload         6
       115: invokedynamic #221,  0            // InvokeDynamic #2:invoke:(Lkotlin/jvm/functions/Function1;ZLkotlin/jvm/functions/Function0;Lcom/example/compose/jetchat/conversation/InputSelector;Landroidx/compose/ui/Modifier;I)Lkotlin/jvm/functions/Function2;
       120: invokeinterface #50,  2           // InterfaceMethod androidx/compose/runtime/ScopeUpdateScope.updateScope:(Lkotlin/jvm/functions/Function2;)V
       125: goto          129
       128: pop
       129: return

  private static final kotlin.Unit UserInputSelector$lambda$0(kotlin.jvm.functions.Function1, boolean, kotlin.jvm.functions.Function0, com.example.compose.jetchat.conversation.InputSelector, androidx.compose.ui.Modifier, int, androidx.compose.runtime.Composer, int);
    Code:
         0: aload_0
         1: iload_1
         2: aload_2
         3: aload_3
         4: aload         4
         6: aload         6
         8: iload         5
        10: iconst_1
        11: ior
        12: invokestatic  #92                 // Method androidx/compose/runtime/RecomposeScopeImplKt.updateChangedFlags:(I)I
        15: invokestatic  #224                // Method UserInputSelector:(Lkotlin/jvm/functions/Function1;ZLkotlin/jvm/functions/Function0;Lcom/example/compose/jetchat/conversation/InputSelector;Landroidx/compose/ui/Modifier;Landroidx/compose/runtime/Composer;I)V
        18: getstatic     #100                // Field kotlin/Unit.INSTANCE:Lkotlin/Unit;
        21: areturn

  private static final <T> void InputSelectorButton(kotlin.jvm.functions.Function0, com.example.compose.jetchat.conversation.Painter, java.lang.String, boolean, androidx.compose.ui.Modifier, androidx.compose.runtime.Composer, int);
    Code:
         0: aload_0
         1: ldc           #228                // String onClick
         3: invokestatic  #125                // Method kotlin/jvm/internal/Intrinsics.checkNotNullParameter:(Ljava/lang/Object;Ljava/lang/String;)V
         6: aload_1
         7: ldc           #230                // String icon
         9: invokestatic  #125                // Method kotlin/jvm/internal/Intrinsics.checkNotNullParameter:(Ljava/lang/Object;Ljava/lang/String;)V
        12: aload_2
        13: ldc           #232                // String description
        15: invokestatic  #125                // Method kotlin/jvm/internal/Intrinsics.checkNotNullParameter:(Ljava/lang/Object;Ljava/lang/String;)V
        18: aload         4
        20: ldc           #234                // String modifier
        22: invokestatic  #125                // Method kotlin/jvm/internal/Intrinsics.checkNotNullParameter:(Ljava/lang/Object;Ljava/lang/String;)V
        25: iload_3
        26: ifeq          57
        29: aconst_null
        30: getfield      #239                // Field androidx/compose/material3/LocalContentColor.current:Ljava/lang/Object;
        33: astore        7
        35: bipush        14
        37: i2f
        38: fstore        8
        40: aconst_null
        41: getfield      #239                // Field androidx/compose/material3/LocalContentColor.current:Ljava/lang/Object;
        44: astore        9
        46: bipush        14
        48: i2f
        49: fstore        10
        51: aconst_null
        52: astore        11
        54: goto          60
        57: aconst_null
        58: astore        11
        60: aload         4
        62: aload         11
        64: invokeinterface #243,  2          // InterfaceMethod androidx/compose/ui/Modifier.then:(Landroidx/compose/ui/Modifier;)Landroidx/compose/ui/Modifier;
        69: pop
        70: new           #245                // class com/example/compose/jetchat/conversation/UserInputKt$Lambda$44
        73: dup
        74: iload_3
        75: aload_1
        76: aload_2
        77: invokespecial #248                // Method com/example/compose/jetchat/conversation/UserInputKt$Lambda$44."<init>":(ZLcom/example/compose/jetchat/conversation/Painter;Ljava/lang/String;)V
        80: pop
        81: return

  private static final kotlin.Unit InputSelectorButton$lambda$0(kotlin.jvm.functions.Function0, com.example.compose.jetchat.conversation.Painter, java.lang.String, boolean, androidx.compose.ui.Modifier, int, androidx.compose.runtime.Composer, int);
    Code:
         0: aload_0
         1: aload_1
         2: aload_2
         3: iload_3
         4: aload         4
         6: aload         6
         8: iload         5
        10: iconst_1
        11: ior
        12: invokestatic  #92                 // Method androidx/compose/runtime/RecomposeScopeImplKt.updateChangedFlags:(I)I
        15: invokestatic  #255                // Method InputSelectorButton:(Lkotlin/jvm/functions/Function0;Lcom/example/compose/jetchat/conversation/Painter;Ljava/lang/String;ZLandroidx/compose/ui/Modifier;Landroidx/compose/runtime/Composer;I)V
        18: getstatic     #100                // Field kotlin/Unit.INSTANCE:Lkotlin/Unit;
        21: areturn

  public static final <T> void NotAvailablePopup(kotlin.jvm.functions.Function0, androidx.compose.runtime.Composer, int);
    Code:
         0: aload_1
         1: ldc_w         #257                // int 2008796409
         4: invokeinterface #34,  2           // InterfaceMethod androidx/compose/runtime/Composer.startRestartGroup:(I)Landroidx/compose/runtime/Composer;
         9: astore_1
        10: aload_1
        11: iload_2
        12: ifeq          19
        15: iconst_1
        16: goto          20
        19: iconst_0
        20: iload_2
        21: iconst_1
        22: iand
        23: invokeinterface #38,  3           // InterfaceMethod androidx/compose/runtime/Composer.shouldExecute:(ZI)Z
        28: ifne          40
        31: aload_1
        32: invokeinterface #42,  1           // InterfaceMethod androidx/compose/runtime/Composer.skipToGroupEnd:()V
        37: goto          46
        40: aload_0
        41: aload_1
        42: iload_2
        43: invokestatic  #262                // Method com/example/compose/jetchat/UiExtrasKt.FunctionalityNotAvailablePopup:(Lkotlin/jvm/functions/Function0;Landroidx/compose/runtime/Composer;I)V
        46: aload_1
        47: invokeinterface #46,  1           // InterfaceMethod androidx/compose/runtime/Composer.endRestartGroup:()Landroidx/compose/runtime/ScopeUpdateScope;
        52: dup
        53: ifnull        71
        56: aload_0
        57: iload_2
        58: invokedynamic #270,  0            // InvokeDynamic #3:invoke:(Lkotlin/jvm/functions/Function0;I)Lkotlin/jvm/functions/Function2;
        63: invokeinterface #50,  2           // InterfaceMethod androidx/compose/runtime/ScopeUpdateScope.updateScope:(Lkotlin/jvm/functions/Function2;)V
        68: goto          72
        71: pop
        72: return

  private static final kotlin.Unit NotAvailablePopup$lambda$0(kotlin.jvm.functions.Function0, int, androidx.compose.runtime.Composer, int);
    Code:
         0: aload_0
         1: aload_2
         2: iload_1
         3: iconst_1
         4: ior
         5: invokestatic  #92                 // Method androidx/compose/runtime/RecomposeScopeImplKt.updateChangedFlags:(I)I
         8: invokestatic  #273                // Method NotAvailablePopup:(Lkotlin/jvm/functions/Function0;Landroidx/compose/runtime/Composer;I)V
        11: getstatic     #100                // Field kotlin/Unit.INSTANCE:Lkotlin/Unit;
        14: areturn

  public static final void getKeyboardShownProperty(androidx.compose.ui.semantics.SemanticsPropertyReceiver);
    Code:
         0: aload_0
         1: ldc           #119                // String <this>
         3: invokestatic  #125                // Method kotlin/jvm/internal/Intrinsics.checkNotNullParameter:(Ljava/lang/Object;Ljava/lang/String;)V
         6: return

  public static final <T> void UserInputText(androidx.compose.ui.text.input.KeyboardType, kotlin.jvm.functions.Function1, androidx.compose.ui.text.input.TextFieldValue, boolean, kotlin.jvm.functions.Function1, kotlin.jvm.functions.Function1, boolean, androidx.compose.runtime.Composer, int);
    Code:
         0: aload         7
         2: ldc_w         #280                // int 82125285
         5: invokeinterface #34,  2           // InterfaceMethod androidx/compose/runtime/Composer.startRestartGroup:(I)Landroidx/compose/runtime/Composer;
        10: astore        7
        12: aload         7
        14: iload         8
        16: ifeq          23
        19: iconst_1
        20: goto          24
        23: iconst_0
        24: iload         8
        26: iconst_1
        27: iand
        28: invokeinterface #38,  3           // InterfaceMethod androidx/compose/runtime/Composer.shouldExecute:(ZI)Z
        33: ifne          46
        36: aload         7
        38: invokeinterface #42,  1           // InterfaceMethod androidx/compose/runtime/Composer.skipToGroupEnd:()V
        43: goto          156
        46: new           #282                // class com/example/compose/jetchat/conversation/UserInputKt$Lambda$45
        49: dup
        50: invokespecial #283                // Method com/example/compose/jetchat/conversation/UserInputKt$Lambda$45."<init>":()V
        53: astore        9
        55: aload         9
        57: checkcast     #115                // class kotlin/jvm/functions/Function0
        60: aload         7
        62: iload         8
        64: invokestatic  #160                // Method androidx/compose/runtime/ComposablesKt.remember:(Lkotlin/jvm/functions/Function0;Landroidx/compose/runtime/Composer;I)Ljava/lang/Object;
        67: astore        10
        69: new           #285                // class com/example/compose/jetchat/conversation/UserInputKt$Lambda$46
        72: dup
        73: invokespecial #286                // Method com/example/compose/jetchat/conversation/UserInputKt$Lambda$46."<init>":()V
        76: astore        11
        78: aload         11
        80: checkcast     #115                // class kotlin/jvm/functions/Function0
        83: aload         7
        85: iload         8
        87: invokestatic  #160                // Method androidx/compose/runtime/ComposablesKt.remember:(Lkotlin/jvm/functions/Function0;Landroidx/compose/runtime/Composer;I)Ljava/lang/Object;
        90: astore        12
        92: aconst_null
        93: astore        13
        95: aload         13
        97: astore        14
        99: getstatic     #291                // Field com/example/compose/jetchat/R$string.textfield_desc:I
       102: aload         7
       104: iload         8
       106: invokestatic  #297                // Method androidx/compose/ui/res/StringResources_androidKt.stringResource:(ILandroidx/compose/runtime/Composer;I)Ljava/lang/String;
       109: astore        15
       111: bipush        64
       113: i2f
       114: fstore        16
       116: aconst_null
       117: invokevirtual #303                // Method androidx/compose/foundation/layout/Arrangement.getEnd:()Landroidx/compose/foundation/layout/Arrangement$Horizontal;
       120: pop
       121: new           #305                // class com/example/compose/jetchat/conversation/$Ref$47
       124: dup
       125: aload         14
       127: invokespecial #308                // Method com/example/compose/jetchat/conversation/$Ref$47."<init>":(Ljava/lang/Object;)V
       130: astore        17
       132: new           #310                // class com/example/compose/jetchat/conversation/UserInputKt$Lambda$48
       135: dup
       136: aload         17
       138: aload         10
       140: aload_2
       141: aload_1
       142: aload         4
       144: aload_0
       145: iload         6
       147: aload         5
       149: aload         15
       151: iload_3
       152: invokespecial #313                // Method com/example/compose/jetchat/conversation/UserInputKt$Lambda$48."<init>":(Lcom/example/compose/jetchat/conversation/$Ref$47;Ljava/lang/Object;Landroidx/compose/ui/text/input/TextFieldValue;Lkotlin/jvm/functions/Function1;Lkotlin/jvm/functions/Function1;Landroidx/compose/ui/text/input/KeyboardType;ZLkotlin/jvm/functions/Function1;Ljava/lang/String;Z)V
       155: pop
       156: aload         7
       158: invokeinterface #46,  1           // InterfaceMethod androidx/compose/runtime/Composer.endRestartGroup:()Landroidx/compose/runtime/ScopeUpdateScope;
       163: dup
       164: ifnull        192
       167: aload_0
       168: aload_1
       169: aload_2
       170: iload_3
       171: aload         4
       173: aload         5
       175: iload         6
       177: iload         8
       179: invokedynamic #321,  0            // InvokeDynamic #4:invoke:(Landroidx/compose/ui/text/input/KeyboardType;Lkotlin/jvm/functions/Function1;Landroidx/compose/ui/text/input/TextFieldValue;ZLkotlin/jvm/functions/Function1;Lkotlin/jvm/functions/Function1;ZI)Lkotlin/jvm/functions/Function2;
       184: invokeinterface #50,  2           // InterfaceMethod androidx/compose/runtime/ScopeUpdateScope.updateScope:(Lkotlin/jvm/functions/Function2;)V
       189: goto          193
       192: pop
       193: return

  private static final kotlin.Unit UserInputText$lambda$0(androidx.compose.ui.text.input.KeyboardType, kotlin.jvm.functions.Function1, androidx.compose.ui.text.input.TextFieldValue, boolean, kotlin.jvm.functions.Function1, kotlin.jvm.functions.Function1, boolean, int, androidx.compose.runtime.Composer, int);
    Code:
         0: aload_0
         1: aload_1
         2: aload_2
         3: iload_3
         4: aload         4
         6: aload         5
         8: iload         6
        10: aload         8
        12: iload         7
        14: iconst_1
        15: ior
        16: invokestatic  #92                 // Method androidx/compose/runtime/RecomposeScopeImplKt.updateChangedFlags:(I)I
        19: invokestatic  #329                // Method UserInputText:(Landroidx/compose/ui/text/input/KeyboardType;Lkotlin/jvm/functions/Function1;Landroidx/compose/ui/text/input/TextFieldValue;ZLkotlin/jvm/functions/Function1;Lkotlin/jvm/functions/Function1;ZLandroidx/compose/runtime/Composer;I)V
        22: getstatic     #100                // Field kotlin/Unit.INSTANCE:Lkotlin/Unit;
        25: areturn

  public static final void UserInputTextField(java.lang.Object, com.example.compose.jetchat.conversation.BoxScope, com.example.compose.jetchat.conversation.TextFieldValue, kotlin.jvm.functions.Function1, kotlin.jvm.functions.Function1, com.example.compose.jetchat.conversation.KeyboardType, boolean, kotlin.jvm.functions.Function1, androidx.compose.runtime.Composer, int);
    Code:
         0: aload         8
         2: ldc_w         #332                // int -2116358553
         5: invokeinterface #34,  2           // InterfaceMethod androidx/compose/runtime/Composer.startRestartGroup:(I)Landroidx/compose/runtime/Composer;
        10: astore        8
        12: aload         8
        14: iload         9
        16: ifeq          23
        19: iconst_1
        20: goto          24
        23: iconst_0
        24: iload         9
        26: iconst_1
        27: iand
        28: invokeinterface #38,  3           // InterfaceMethod androidx/compose/runtime/Composer.shouldExecute:(ZI)Z
        33: ifne          43
        36: aload         8
        38: invokeinterface #42,  1           // InterfaceMethod androidx/compose/runtime/Composer.skipToGroupEnd:()V
        43: aload         8
        45: invokeinterface #46,  1           // InterfaceMethod androidx/compose/runtime/Composer.endRestartGroup:()Landroidx/compose/runtime/ScopeUpdateScope;
        50: dup
        51: ifnull        81
        54: aload_0
        55: aload_1
        56: aload_2
        57: aload_3
        58: aload         4
        60: aload         5
        62: iload         6
        64: aload         7
        66: iload         9
        68: invokedynamic #340,  0            // InvokeDynamic #5:invoke:(Ljava/lang/Object;Lcom/example/compose/jetchat/conversation/BoxScope;Lcom/example/compose/jetchat/conversation/TextFieldValue;Lkotlin/jvm/functions/Function1;Lkotlin/jvm/functions/Function1;Lcom/example/compose/jetchat/conversation/KeyboardType;ZLkotlin/jvm/functions/Function1;I)Lkotlin/jvm/functions/Function2;
        73: invokeinterface #50,  2           // InterfaceMethod androidx/compose/runtime/ScopeUpdateScope.updateScope:(Lkotlin/jvm/functions/Function2;)V
        78: goto          82
        81: pop
        82: return

  private static final kotlin.Unit UserInputTextField$lambda$0(java.lang.Object, com.example.compose.jetchat.conversation.BoxScope, com.example.compose.jetchat.conversation.TextFieldValue, kotlin.jvm.functions.Function1, kotlin.jvm.functions.Function1, com.example.compose.jetchat.conversation.KeyboardType, boolean, kotlin.jvm.functions.Function1, int, androidx.compose.runtime.Composer, int);
    Code:
         0: aload_0
         1: aload_1
         2: aload_2
         3: aload_3
         4: aload         4
         6: aload         5
         8: iload         6
        10: aload         7
        12: aload         9
        14: iload         8
        16: iconst_1
        17: ior
        18: invokestatic  #92                 // Method androidx/compose/runtime/RecomposeScopeImplKt.updateChangedFlags:(I)I
        21: invokestatic  #346                // Method UserInputTextField:(Ljava/lang/Object;Lcom/example/compose/jetchat/conversation/BoxScope;Lcom/example/compose/jetchat/conversation/TextFieldValue;Lkotlin/jvm/functions/Function1;Lkotlin/jvm/functions/Function1;Lcom/example/compose/jetchat/conversation/KeyboardType;ZLkotlin/jvm/functions/Function1;Landroidx/compose/runtime/Composer;I)V
        24: getstatic     #100                // Field kotlin/Unit.INSTANCE:Lkotlin/Unit;
        27: areturn

  public static final <T> void RecordingIndicator(kotlin.jvm.functions.Function0, androidx.compose.runtime.Composer, int);
    Code:
         0: aload_1
         1: ldc_w         #348                // int -1730157611
         4: invokeinterface #34,  2           // InterfaceMethod androidx/compose/runtime/Composer.startRestartGroup:(I)Landroidx/compose/runtime/Composer;
         9: astore_1
        10: aload_1
        11: iload_2
        12: ifeq          19
        15: iconst_1
        16: goto          20
        19: iconst_0
        20: iload_2
        21: iconst_1
        22: iand
        23: invokeinterface #38,  3           // InterfaceMethod androidx/compose/runtime/Composer.shouldExecute:(ZI)Z
        28: ifne          40
        31: aload_1
        32: invokeinterface #42,  1           // InterfaceMethod androidx/compose/runtime/Composer.skipToGroupEnd:()V
        37: goto          115
        40: new           #350                // class com/example/compose/jetchat/conversation/UserInputKt$Lambda$62
        43: dup
        44: invokespecial #351                // Method com/example/compose/jetchat/conversation/UserInputKt$Lambda$62."<init>":()V
        47: astore_3
        48: aload_3
        49: checkcast     #115                // class kotlin/jvm/functions/Function0
        52: aload_1
        53: iload_2
        54: invokestatic  #160                // Method androidx/compose/runtime/ComposablesKt.remember:(Lkotlin/jvm/functions/Function0;Landroidx/compose/runtime/Composer;I)Ljava/lang/Object;
        57: astore        4
        59: aconst_null
        60: astore        5
        62: aload         5
        64: astore        6
        66: new           #353                // class com/example/compose/jetchat/conversation/UserInputKt$Lambda$63
        69: dup
        70: invokespecial #354                // Method com/example/compose/jetchat/conversation/UserInputKt$Lambda$63."<init>":()V
        73: astore        7
        75: aconst_null
        76: aload         7
        78: checkcast     #356                // class kotlin/jvm/functions/Function2
        81: aload_1
        82: iload_2
        83: invokestatic  #360                // Method androidx/compose/runtime/EffectsKt.LaunchedEffect:([Ljava/lang/Object;Lkotlin/jvm/functions/Function2;Landroidx/compose/runtime/Composer;I)V
        86: getstatic     #202                // Field androidx/compose/ui/Alignment.Companion:Landroidx/compose/ui/Alignment$Companion;
        89: invokevirtual #208                // Method androidx/compose/ui/Alignment$Companion.getCenterVertically:()Landroidx/compose/ui/Alignment$Vertical;
        92: pop
        93: new           #362                // class com/example/compose/jetchat/conversation/$Ref$64
        96: dup
        97: aload         6
        99: invokespecial #363                // Method com/example/compose/jetchat/conversation/$Ref$64."<init>":(Ljava/lang/Object;)V
       102: astore        8
       104: new           #365                // class com/example/compose/jetchat/conversation/UserInputKt$Lambda$65
       107: dup
       108: aload         8
       110: aload_0
       111: invokespecial #368                // Method com/example/compose/jetchat/conversation/UserInputKt$Lambda$65."<init>":(Lcom/example/compose/jetchat/conversation/$Ref$64;Lkotlin/jvm/functions/Function0;)V
       114: pop
       115: aload_1
       116: invokeinterface #46,  1           // InterfaceMethod androidx/compose/runtime/Composer.endRestartGroup:()Landroidx/compose/runtime/ScopeUpdateScope;
       121: dup
       122: ifnull        140
       125: aload_0
       126: iload_2
       127: invokedynamic #373,  0            // InvokeDynamic #6:invoke:(Lkotlin/jvm/functions/Function0;I)Lkotlin/jvm/functions/Function2;
       132: invokeinterface #50,  2           // InterfaceMethod androidx/compose/runtime/ScopeUpdateScope.updateScope:(Lkotlin/jvm/functions/Function2;)V
       137: goto          141
       140: pop
       141: return

  private static final kotlin.Unit RecordingIndicator$lambda$0(kotlin.jvm.functions.Function0, int, androidx.compose.runtime.Composer, int);
    Code:
         0: aload_0
         1: aload_2
         2: iload_1
         3: iconst_1
         4: ior
         5: invokestatic  #92                 // Method androidx/compose/runtime/RecomposeScopeImplKt.updateChangedFlags:(I)I
         8: invokestatic  #375                // Method RecordingIndicator:(Lkotlin/jvm/functions/Function0;Landroidx/compose/runtime/Composer;I)V
        11: getstatic     #100                // Field kotlin/Unit.INSTANCE:Lkotlin/Unit;
        14: areturn

  public static final <T> void EmojiSelector(kotlin.jvm.functions.Function1, androidx.compose.ui.focus.FocusRequester, androidx.compose.runtime.Composer, int);
    Code:
         0: aload_0
         1: ldc           #137                // String onTextAdded
         3: invokestatic  #125                // Method kotlin/jvm/internal/Intrinsics.checkNotNullParameter:(Ljava/lang/Object;Ljava/lang/String;)V
         6: aload_1
         7: ldc_w         #379                // String focusRequester
        10: invokestatic  #125                // Method kotlin/jvm/internal/Intrinsics.checkNotNullParameter:(Ljava/lang/Object;Ljava/lang/String;)V
        13: new           #381                // class com/example/compose/jetchat/conversation/UserInputKt$Lambda$70
        16: dup
        17: invokespecial #382                // Method com/example/compose/jetchat/conversation/UserInputKt$Lambda$70."<init>":()V
        20: checkcast     #115                // class kotlin/jvm/functions/Function0
        23: aload_2
        24: iload_3
        25: invokestatic  #160                // Method androidx/compose/runtime/ComposablesKt.remember:(Lkotlin/jvm/functions/Function0;Landroidx/compose/runtime/Composer;I)Ljava/lang/Object;
        28: astore        4
        30: aconst_null
        31: astore        5
        33: getstatic     #385                // Field com/example/compose/jetchat/R$string.emoji_selector_desc:I
        36: aload_2
        37: iload_3
        38: invokestatic  #297                // Method androidx/compose/ui/res/StringResources_androidKt.stringResource:(ILandroidx/compose/runtime/Composer;I)Ljava/lang/String;
        41: astore        6
        43: new           #387                // class com/example/compose/jetchat/conversation/UserInputKt$Lambda$71
        46: dup
        47: aload         6
        49: invokespecial #390                // Method com/example/compose/jetchat/conversation/UserInputKt$Lambda$71."<init>":(Ljava/lang/String;)V
        52: pop
        53: new           #392                // class com/example/compose/jetchat/conversation/UserInputKt$Lambda$72
        56: dup
        57: aload_0
        58: invokespecial #395                // Method com/example/compose/jetchat/conversation/UserInputKt$Lambda$72."<init>":(Lkotlin/jvm/functions/Function1;)V
        61: pop
        62: aload         5
        64: astore        7
        66: invokestatic  #399                // Method STICKER:()Lcom/example/compose/jetchat/conversation/EmojiStickerSelector;
        69: aload         7
        71: swap
        72: if_acmpne     90
        75: new           #401                // class com/example/compose/jetchat/conversation/UserInputKt$Lambda$77
        78: dup
        79: invokespecial #402                // Method com/example/compose/jetchat/conversation/UserInputKt$Lambda$77."<init>":()V
        82: checkcast     #115                // class kotlin/jvm/functions/Function0
        85: aload_2
        86: iconst_0
        87: invokestatic  #273                // Method NotAvailablePopup:(Lkotlin/jvm/functions/Function0;Landroidx/compose/runtime/Composer;I)V
        90: return

  private static final kotlin.Unit EmojiSelector$lambda$0(kotlin.jvm.functions.Function1, androidx.compose.ui.focus.FocusRequester, int, androidx.compose.runtime.Composer, int);
    Code:
         0: aload_0
         1: aload_1
         2: aload_3
         3: iload_2
         4: iconst_1
         5: ior
         6: invokestatic  #92                 // Method androidx/compose/runtime/RecomposeScopeImplKt.updateChangedFlags:(I)I
         9: invokestatic  #409                // Method EmojiSelector:(Lkotlin/jvm/functions/Function1;Landroidx/compose/ui/focus/FocusRequester;Landroidx/compose/runtime/Composer;I)V
        12: getstatic     #100                // Field kotlin/Unit.INSTANCE:Lkotlin/Unit;
        15: areturn

  public static final <T> void ExtendedSelectorInnerButton(java.lang.String, kotlin.jvm.functions.Function0, boolean, androidx.compose.ui.Modifier, androidx.compose.runtime.Composer, int);
    Code:
         0: aload_0
         1: ldc_w         #413                // String text
         4: invokestatic  #125                // Method kotlin/jvm/internal/Intrinsics.checkNotNullParameter:(Ljava/lang/Object;Ljava/lang/String;)V
         7: aload_1
         8: ldc           #228                // String onClick
        10: invokestatic  #125                // Method kotlin/jvm/internal/Intrinsics.checkNotNullParameter:(Ljava/lang/Object;Ljava/lang/String;)V
        13: aload_3
        14: ldc           #234                // String modifier
        16: invokestatic  #125                // Method kotlin/jvm/internal/Intrinsics.checkNotNullParameter:(Ljava/lang/Object;Ljava/lang/String;)V
        19: iload_2
        20: ifeq          26
        23: goto          33
        26: getstatic     #418                // Field androidx/compose/ui/graphics/Color.Companion:Landroidx/compose/ui/graphics/Color$Companion;
        29: invokevirtual #424                // Method androidx/compose/ui/graphics/Color$Companion."getTransparent-0d7_KjU":()J
        32: pop2
        33: getstatic     #418                // Field androidx/compose/ui/graphics/Color.Companion:Landroidx/compose/ui/graphics/Color$Companion;
        36: invokevirtual #424                // Method androidx/compose/ui/graphics/Color$Companion."getTransparent-0d7_KjU":()J
        39: pop2
        40: aconst_null
        41: aload         4
        43: iconst_0
        44: invokevirtual #430                // Method androidx/compose/material3/MaterialTheme.getColorScheme:(Landroidx/compose/runtime/Composer;I)Landroidx/compose/material3/ColorScheme;
        47: pop
        48: iload_2
        49: ifeq          55
        52: goto          62
        55: getstatic     #418                // Field androidx/compose/ui/graphics/Color.Companion:Landroidx/compose/ui/graphics/Color$Companion;
        58: invokevirtual #424                // Method androidx/compose/ui/graphics/Color$Companion."getTransparent-0d7_KjU":()J
        61: pop2
        62: getstatic     #418                // Field androidx/compose/ui/graphics/Color.Companion:Landroidx/compose/ui/graphics/Color$Companion;
        65: invokevirtual #424                // Method androidx/compose/ui/graphics/Color$Companion."getTransparent-0d7_KjU":()J
        68: pop2
        69: aconst_null
        70: aload         4
        72: iconst_0
        73: invokevirtual #430                // Method androidx/compose/material3/MaterialTheme.getColorScheme:(Landroidx/compose/runtime/Composer;I)Landroidx/compose/material3/ColorScheme;
        76: pop
        77: aconst_null
        78: astore        6
        80: bipush        8
        82: i2f
        83: fstore        7
        85: bipush        8
        87: i2f
        88: fstore        8
        90: aload_3
        91: fload         8
        93: invokevirtual #433                // Method androidx/compose/ui/Modifier.padding:(F)V
        96: bipush        36
        98: i2f
        99: fstore        9
       101: iconst_0
       102: i2f
       103: invokestatic  #439                // Method androidx/compose/foundation/layout/PaddingKt."PaddingValues-0680j_4":(F)Landroidx/compose/foundation/layout/PaddingValues;
       106: astore        10
       108: new           #441                // class com/example/compose/jetchat/conversation/UserInputKt$Lambda$78
       111: dup
       112: aload_0
       113: invokespecial #442                // Method com/example/compose/jetchat/conversation/UserInputKt$Lambda$78."<init>":(Ljava/lang/String;)V
       116: pop
       117: return

  private static final kotlin.Unit ExtendedSelectorInnerButton$lambda$0(java.lang.String, kotlin.jvm.functions.Function0, boolean, androidx.compose.ui.Modifier, int, androidx.compose.runtime.Composer, int);
    Code:
         0: aload_0
         1: aload_1
         2: iload_2
         3: aload_3
         4: aload         5
         6: iload         4
         8: iconst_1
         9: ior
        10: invokestatic  #92                 // Method androidx/compose/runtime/RecomposeScopeImplKt.updateChangedFlags:(I)I
        13: invokestatic  #447                // Method ExtendedSelectorInnerButton:(Ljava/lang/String;Lkotlin/jvm/functions/Function0;ZLandroidx/compose/ui/Modifier;Landroidx/compose/runtime/Composer;I)V
        16: getstatic     #100                // Field kotlin/Unit.INSTANCE:Lkotlin/Unit;
        19: areturn

  public static final <T> void EmojiTable(kotlin.jvm.functions.Function1, androidx.compose.ui.Modifier, androidx.compose.runtime.Composer, int);
    Code:
         0: aload_2
         1: ldc_w         #450                // int 1903484279
         4: invokeinterface #34,  2           // InterfaceMethod androidx/compose/runtime/Composer.startRestartGroup:(I)Landroidx/compose/runtime/Composer;
         9: astore_2
        10: aload_2
        11: iload_3
        12: ifeq          19
        15: iconst_1
        16: goto          20
        19: iconst_0
        20: iload_3
        21: iconst_1
        22: iand
        23: invokeinterface #38,  3           // InterfaceMethod androidx/compose/runtime/Composer.shouldExecute:(ZI)Z
        28: ifne          40
        31: aload_2
        32: invokeinterface #42,  1           // InterfaceMethod androidx/compose/runtime/Composer.skipToGroupEnd:()V
        37: goto          68
        40: aload_1
        41: invokevirtual #453                // Method androidx/compose/ui/Modifier.fillMaxWidth:()V
        44: new           #455                // class com/example/compose/jetchat/conversation/UserInputKt$Lambda$79
        47: dup
        48: aload_0
        49: invokespecial #456                // Method com/example/compose/jetchat/conversation/UserInputKt$Lambda$79."<init>":(Lkotlin/jvm/functions/Function1;)V
        52: astore        4
        54: aconst_null
        55: aconst_null
        56: aload         4
        58: checkcast     #458                // class kotlin/jvm/functions/Function3
        61: aload_2
        62: iload_3
        63: bipush        6
        65: invokestatic  #464                // Method androidx/compose/foundation/layout/ColumnKt.Column:(Landroidx/compose/ui/Modifier;Landroidx/compose/foundation/layout/Arrangement$Vertical;Landroidx/compose/ui/Alignment$Horizontal;Lkotlin/jvm/functions/Function3;Landroidx/compose/runtime/Composer;II)V
        68: aload_2
        69: invokeinterface #46,  1           // InterfaceMethod androidx/compose/runtime/Composer.endRestartGroup:()Landroidx/compose/runtime/ScopeUpdateScope;
        74: dup
        75: ifnull        94
        78: aload_0
        79: aload_1
        80: iload_3
        81: invokedynamic #472,  0            // InvokeDynamic #7:invoke:(Lkotlin/jvm/functions/Function1;Landroidx/compose/ui/Modifier;I)Lkotlin/jvm/functions/Function2;
        86: invokeinterface #50,  2           // InterfaceMethod androidx/compose/runtime/ScopeUpdateScope.updateScope:(Lkotlin/jvm/functions/Function2;)V
        91: goto          95
        94: pop
        95: return

  private static final kotlin.Unit EmojiTable$lambda$0(kotlin.jvm.functions.Function1, androidx.compose.ui.Modifier, int, androidx.compose.runtime.Composer, int);
    Code:
         0: aload_0
         1: aload_1
         2: aload_3
         3: iload_2
         4: iconst_1
         5: ior
         6: invokestatic  #92                 // Method androidx/compose/runtime/RecomposeScopeImplKt.updateChangedFlags:(I)I
         9: invokestatic  #475                // Method EmojiTable:(Lkotlin/jvm/functions/Function1;Landroidx/compose/ui/Modifier;Landroidx/compose/runtime/Composer;I)V
        12: getstatic     #100                // Field kotlin/Unit.INSTANCE:Lkotlin/Unit;
        15: areturn

  public static final com.example.compose.jetchat.conversation.InputSelector NONE();
    Code:
         0: getstatic     #478                // Field com/example/compose/jetchat/conversation/InputSelector.NONE:LInputSelector;
         3: areturn

  public static final com.example.compose.jetchat.conversation.InputSelector MAP();
    Code:
         0: getstatic     #481                // Field com/example/compose/jetchat/conversation/InputSelector.MAP:LInputSelector;
         3: areturn

  public static final com.example.compose.jetchat.conversation.InputSelector DM();
    Code:
         0: getstatic     #484                // Field com/example/compose/jetchat/conversation/InputSelector.DM:LInputSelector;
         3: areturn

  public static final com.example.compose.jetchat.conversation.InputSelector EMOJI();
    Code:
         0: getstatic     #487                // Field com/example/compose/jetchat/conversation/InputSelector.EMOJI:LInputSelector;
         3: areturn

  public static final com.example.compose.jetchat.conversation.InputSelector PHONE();
    Code:
         0: getstatic     #490                // Field com/example/compose/jetchat/conversation/InputSelector.PHONE:LInputSelector;
         3: areturn

  public static final com.example.compose.jetchat.conversation.InputSelector PICTURE();
    Code:
         0: getstatic     #493                // Field com/example/compose/jetchat/conversation/InputSelector.PICTURE:LInputSelector;
         3: areturn

  public static final java.util.ArrayList InputSelector$values();
    Code:
         0: new           #497                // class java/util/ArrayList
         3: dup
         4: invokespecial #498                // Method java/util/ArrayList."<init>":()V
         7: astore_0
         8: aload_0
         9: invokestatic  #141                // Method NONE:()Lcom/example/compose/jetchat/conversation/InputSelector;
        12: invokevirtual #501                // Method java/util/ArrayList.add:(Ljava/lang/Object;)Z
        15: pop
        16: aload_0
        17: invokestatic  #503                // Method MAP:()Lcom/example/compose/jetchat/conversation/InputSelector;
        20: invokevirtual #501                // Method java/util/ArrayList.add:(Ljava/lang/Object;)Z
        23: pop
        24: aload_0
        25: invokestatic  #505                // Method DM:()Lcom/example/compose/jetchat/conversation/InputSelector;
        28: invokevirtual #501                // Method java/util/ArrayList.add:(Ljava/lang/Object;)Z
        31: pop
        32: aload_0
        33: invokestatic  #507                // Method EMOJI:()Lcom/example/compose/jetchat/conversation/InputSelector;
        36: invokevirtual #501                // Method java/util/ArrayList.add:(Ljava/lang/Object;)Z
        39: pop
        40: aload_0
        41: invokestatic  #509                // Method PHONE:()Lcom/example/compose/jetchat/conversation/InputSelector;
        44: invokevirtual #501                // Method java/util/ArrayList.add:(Ljava/lang/Object;)Z
        47: pop
        48: aload_0
        49: invokestatic  #511                // Method PICTURE:()Lcom/example/compose/jetchat/conversation/InputSelector;
        52: invokevirtual #501                // Method java/util/ArrayList.add:(Ljava/lang/Object;)Z
        55: pop
        56: aload_0
        57: areturn

  public static final com.example.compose.jetchat.conversation.InputSelector InputSelector$valueOf(java.lang.String);
    Code:
         0: aload_0
         1: ldc_w         #515                // String name
         4: invokestatic  #125                // Method kotlin/jvm/internal/Intrinsics.checkNotNullParameter:(Ljava/lang/Object;Ljava/lang/String;)V
         7: aload_0
         8: ldc_w         #516                // String NONE
        11: invokestatic  #520                // Method kotlin/jvm/internal/Intrinsics.areEqual:(Ljava/lang/Object;Ljava/lang/Object;)Z
        14: ifeq          80
        17: goto          94
        20: invokestatic  #141                // Method NONE:()Lcom/example/compose/jetchat/conversation/InputSelector;
        23: areturn
        24: aload_0
        25: ldc_w         #521                // String PICTURE
        28: invokestatic  #520                // Method kotlin/jvm/internal/Intrinsics.areEqual:(Ljava/lang/Object;Ljava/lang/Object;)Z
        31: ifeq          20
        34: invokestatic  #511                // Method PICTURE:()Lcom/example/compose/jetchat/conversation/InputSelector;
        37: areturn
        38: aload_0
        39: ldc_w         #522                // String PHONE
        42: invokestatic  #520                // Method kotlin/jvm/internal/Intrinsics.areEqual:(Ljava/lang/Object;Ljava/lang/Object;)Z
        45: ifeq          24
        48: invokestatic  #509                // Method PHONE:()Lcom/example/compose/jetchat/conversation/InputSelector;
        51: areturn
        52: aload_0
        53: ldc_w         #523                // String EMOJI
        56: invokestatic  #520                // Method kotlin/jvm/internal/Intrinsics.areEqual:(Ljava/lang/Object;Ljava/lang/Object;)Z
        59: ifeq          38
        62: invokestatic  #507                // Method EMOJI:()Lcom/example/compose/jetchat/conversation/InputSelector;
        65: areturn
        66: aload_0
        67: ldc_w         #524                // String DM
        70: invokestatic  #520                // Method kotlin/jvm/internal/Intrinsics.areEqual:(Ljava/lang/Object;Ljava/lang/Object;)Z
        73: ifeq          52
        76: invokestatic  #505                // Method DM:()Lcom/example/compose/jetchat/conversation/InputSelector;
        79: areturn
        80: aload_0
        81: ldc_w         #525                // String MAP
        84: invokestatic  #520                // Method kotlin/jvm/internal/Intrinsics.areEqual:(Ljava/lang/Object;Ljava/lang/Object;)Z
        87: ifeq          66
        90: invokestatic  #503                // Method MAP:()Lcom/example/compose/jetchat/conversation/InputSelector;
        93: areturn
        94: invokestatic  #141                // Method NONE:()Lcom/example/compose/jetchat/conversation/InputSelector;
        97: areturn

  public static final com.example.compose.jetchat.conversation.EmojiStickerSelector EMOJI();
    Code:
         0: getstatic     #530                // Field com/example/compose/jetchat/conversation/EmojiStickerSelector.EMOJI:LEmojiStickerSelector;
         3: areturn

  public static final com.example.compose.jetchat.conversation.EmojiStickerSelector STICKER();
    Code:
         0: getstatic     #532                // Field com/example/compose/jetchat/conversation/EmojiStickerSelector.STICKER:LEmojiStickerSelector;
         3: areturn

  public static final java.util.ArrayList EmojiStickerSelector$values();
    Code:
         0: new           #497                // class java/util/ArrayList
         3: dup
         4: invokespecial #498                // Method java/util/ArrayList."<init>":()V
         7: astore_0
         8: aload_0
         9: invokestatic  #535                // Method EMOJI:()Lcom/example/compose/jetchat/conversation/EmojiStickerSelector;
        12: invokevirtual #501                // Method java/util/ArrayList.add:(Ljava/lang/Object;)Z
        15: pop
        16: aload_0
        17: invokestatic  #399                // Method STICKER:()Lcom/example/compose/jetchat/conversation/EmojiStickerSelector;
        20: invokevirtual #501                // Method java/util/ArrayList.add:(Ljava/lang/Object;)Z
        23: pop
        24: aload_0
        25: areturn

  public static final com.example.compose.jetchat.conversation.EmojiStickerSelector EmojiStickerSelector$valueOf(java.lang.String);
    Code:
         0: aload_0
         1: ldc_w         #515                // String name
         4: invokestatic  #125                // Method kotlin/jvm/internal/Intrinsics.checkNotNullParameter:(Ljava/lang/Object;Ljava/lang/String;)V
         7: aload_0
         8: ldc_w         #523                // String EMOJI
        11: invokestatic  #520                // Method kotlin/jvm/internal/Intrinsics.areEqual:(Ljava/lang/Object;Ljava/lang/Object;)Z
        14: ifeq          24
        17: goto          38
        20: invokestatic  #535                // Method EMOJI:()Lcom/example/compose/jetchat/conversation/EmojiStickerSelector;
        23: areturn
        24: aload_0
        25: ldc_w         #538                // String STICKER
        28: invokestatic  #520                // Method kotlin/jvm/internal/Intrinsics.areEqual:(Ljava/lang/Object;Ljava/lang/Object;)Z
        31: ifeq          20
        34: invokestatic  #399                // Method STICKER:()Lcom/example/compose/jetchat/conversation/EmojiStickerSelector;
        37: areturn
        38: invokestatic  #535                // Method EMOJI:()Lcom/example/compose/jetchat/conversation/EmojiStickerSelector;
        41: areturn

  public static final kotlin.Unit invoke$lambda$0(java.lang.Object);
    Code:
         0: aconst_null
         1: areturn

  public static final java.lang.String invoke$lambda$1(java.lang.Object, java.lang.Object, java.lang.Object);
    Code:
         0: aload_0
         1: checkcast     #4                  // class java/lang/Object
         4: invokevirtual #145                // Method java/lang/Object.toString:()Ljava/lang/String;
         7: pop
         8: aconst_null
         9: astore_3
        10: aload_1
        11: checkcast     #4                  // class java/lang/Object
        14: invokevirtual #145                // Method java/lang/Object.toString:()Ljava/lang/String;
        17: pop
        18: aconst_null
        19: astore        4
        21: aload_3
        22: aload         4
        24: invokedynamic #554,  0            // InvokeDynamic #8:makeConcatWithConstants:(Ljava/lang/Object;Ljava/lang/Object;)Ljava/lang/String;
        29: areturn

  public static final java.lang.String invoke$lambda$2(java.lang.Object, java.lang.Object, java.lang.Object);
    Code:
         0: aload_0
         1: checkcast     #4                  // class java/lang/Object
         4: invokevirtual #145                // Method java/lang/Object.toString:()Ljava/lang/String;
         7: pop
         8: aconst_null
         9: astore_3
        10: aload_1
        11: checkcast     #4                  // class java/lang/Object
        14: invokevirtual #145                // Method java/lang/Object.toString:()Ljava/lang/String;
        17: pop
        18: aconst_null
        19: astore        4
        21: aload_3
        22: aload         4
        24: invokedynamic #554,  0            // InvokeDynamic #8:makeConcatWithConstants:(Ljava/lang/Object;Ljava/lang/Object;)Ljava/lang/String;
        29: areturn

  private static final {};
    Code:
         0: new           #558                // class androidx/compose/ui/semantics/SemanticsPropertyKey
         3: dup
         4: ldc_w         #559                // String KeyboardShownKey
         7: aconst_null
         8: checkcast     #356                // class kotlin/jvm/functions/Function2
        11: iconst_2
        12: aconst_null
        13: invokespecial #562                // Method androidx/compose/ui/semantics/SemanticsPropertyKey."<init>":(Ljava/lang/String;Lkotlin/jvm/functions/Function2;ILkotlin/jvm/internal/DefaultConstructorMarker;)V
        16: putstatic     #16                 // Field KeyboardShownKey:Landroidx/compose/ui/semantics/SemanticsPropertyKey;
        19: sipush        128
        22: anewarray     #4                  // class java/lang/Object
        25: astore_0
        26: aload_0
        27: iconst_0
        28: ldc_w         #564                // String
        31: aastore
        32: aload_0
        33: iconst_1
        34: ldc_w         #564                // String
        37: aastore
        38: aload_0
        39: iconst_2
        40: ldc_w         #564                // String
        43: aastore
        44: aload_0
        45: iconst_3
        46: ldc_w         #564                // String
        49: aastore
        50: aload_0
        51: iconst_4
        52: ldc_w         #564                // String
        55: aastore
        56: aload_0
        57: iconst_5
        58: ldc_w         #564                // String
        61: aastore
        62: aload_0
        63: bipush        6
        65: ldc_w         #564                // String
        68: aastore
        69: aload_0
        70: bipush        7
        72: ldc_w         #564                // String
        75: aastore
        76: aload_0
        77: bipush        8
        79: ldc_w         #564                // String
        82: aastore
        83: aload_0
        84: bipush        9
        86: ldc_w         #564                // String
        89: aastore
        90: aload_0
        91: bipush        10
        93: ldc_w         #564                // String
        96: aastore
        97: aload_0
        98: bipush        11
       100: ldc_w         #564                // String
       103: aastore
       104: aload_0
       105: bipush        12
       107: ldc_w         #564                // String
       110: aastore
       111: aload_0
       112: bipush        13
       114: ldc_w         #564                // String
       117: aastore
       118: aload_0
       119: bipush        14
       121: ldc_w         #564                // String
       124: aastore
       125: aload_0
       126: bipush        15
       128: ldc_w         #564                // String
       131: aastore
       132: aload_0
       133: bipush        16
       135: ldc_w         #566                // String ☺
       138: aastore
       139: aload_0
       140: bipush        17
       142: ldc_w         #564                // String
       145: aastore
       146: aload_0
       147: bipush        18
       149: ldc_w         #564                // String
       152: aastore
       153: aload_0
       154: bipush        19
       156: ldc_w         #564                // String
       159: aastore
       160: aload_0
       161: bipush        20
       163: ldc_w         #564                // String
       166: aastore
       167: aload_0
       168: bipush        21
       170: ldc_w         #564                // String
       173: aastore
       174: aload_0
       175: bipush        22
       177: ldc_w         #564                // String
       180: aastore
       181: aload_0
       182: bipush        23
       184: ldc_w         #564                // String
       187: aastore
       188: aload_0
       189: bipush        24
       191: ldc_w         #564                // String
       194: aastore
       195: aload_0
       196: bipush        25
       198: ldc_w         #564                // String
       201: aastore
       202: aload_0
       203: bipush        26
       205: ldc_w         #564                // String
       208: aastore
       209: aload_0
       210: bipush        27
       212: ldc_w         #564                // String
       215: aastore
       216: aload_0
       217: bipush        28
       219: ldc_w         #564                // String
       222: aastore
       223: aload_0
       224: bipush        29
       226: ldc_w         #564                // String
       229: aastore
       230: aload_0
       231: bipush        30
       233: ldc_w         #564                // String
       236: aastore
       237: aload_0
       238: bipush        31
       240: ldc_w         #564                // String
       243: aastore
       244: aload_0
       245: bipush        32
       247: ldc_w         #564                // String
       250: aastore
       251: aload_0
       252: bipush        33
       254: ldc_w         #564                // String
       257: aastore
       258: aload_0
       259: bipush        34
       261: ldc_w         #564                // String
       264: aastore
       265: aload_0
       266: bipush        35
       268: ldc_w         #564                // String
       271: aastore
       272: aload_0
       273: bipush        36
       275: ldc_w         #564                // String
       278: aastore
       279: aload_0
       280: bipush        37
       282: ldc_w         #564                // String
       285: aastore
       286: aload_0
       287: bipush        38
       289: ldc_w         #564                // String
       292: aastore
       293: aload_0
       294: bipush        39
       296: ldc_w         #564                // String
       299: aastore
       300: aload_0
       301: bipush        40
       303: ldc_w         #564                // String
       306: aastore
       307: aload_0
       308: bipush        41
       310: ldc_w         #564                // String
       313: aastore
       314: aload_0
       315: bipush        42
       317: ldc_w         #564                // String
       320: aastore
       321: aload_0
       322: bipush        43
       324: ldc_w         #564                // String
       327: aastore
       328: aload_0
       329: bipush        44
       331: ldc_w         #564                // String
       334: aastore
       335: aload_0
       336: bipush        45
       338: ldc_w         #564                // String
       341: aastore
       342: aload_0
       343: bipush        46
       345: ldc_w         #564                // String
       348: aastore
       349: aload_0
       350: bipush        47
       352: ldc_w         #564                // String
       355: aastore
       356: aload_0
       357: bipush        48
       359: ldc_w         #564                // String
       362: aastore
       363: aload_0
       364: bipush        49
       366: ldc_w         #568                // String ☹
       369: aastore
       370: aload_0
       371: bipush        50
       373: ldc_w         #564                // String
       376: aastore
       377: aload_0
       378: bipush        51
       380: ldc_w         #564                // String
       383: aastore
       384: aload_0
       385: bipush        52
       387: ldc_w         #564                // String
       390: aastore
       391: aload_0
       392: bipush        53
       394: ldc_w         #564                // String
       397: aastore
       398: aload_0
       399: bipush        54
       401: ldc_w         #564                // String
       404: aastore
       405: aload_0
       406: bipush        55
       408: ldc_w         #564                // String
       411: aastore
       412: aload_0
       413: bipush        56
       415: ldc_w         #564                // String
       418: aastore
       419: aload_0
       420: bipush        57
       422: ldc_w         #564                // String
       425: aastore
       426: aload_0
       427: bipush        58
       429: ldc_w         #564                // String
       432: aastore
       433: aload_0
       434: bipush        59
       436: ldc_w         #564                // String
       439: aastore
       440: aload_0
       441: bipush        60
       443: ldc_w         #564                // String
       446: aastore
       447: aload_0
       448: bipush        61
       450: ldc_w         #564                // String
       453: aastore
       454: aload_0
       455: bipush        62
       457: ldc_w         #564                // String
       460: aastore
       461: aload_0
       462: bipush        63
       464: ldc_w         #564                // String
       467: aastore
       468: aload_0
       469: bipush        64
       471: ldc_w         #564                // String
       474: aastore
       475: aload_0
       476: bipush        65
       478: ldc_w         #564                // String
       481: aastore
       482: aload_0
       483: bipush        66
       485: ldc_w         #564                // String
       488: aastore
       489: aload_0
       490: bipush        67
       492: ldc_w         #564                // String
       495: aastore
       496: aload_0
       497: bipush        68
       499: ldc_w         #564                // String
       502: aastore
       503: aload_0
       504: bipush        69
       506: ldc_w         #564                // String
       509: aastore
       510: aload_0
       511: bipush        70
       513: ldc_w         #564                // String
       516: aastore
       517: aload_0
       518: bipush        71
       520: ldc_w         #564                // String
       523: aastore
       524: aload_0
       525: bipush        72
       527: ldc_w         #564                // String
       530: aastore
       531: aload_0
       532: bipush        73
       534: ldc_w         #564                // String
       537: aastore
       538: aload_0
       539: bipush        74
       541: ldc_w         #564                // String
       544: aastore
       545: aload_0
       546: bipush        75
       548: ldc_w         #564                // String
       551: aastore
       552: aload_0
       553: bipush        76
       555: ldc_w         #564                // String
       558: aastore
       559: aload_0
       560: bipush        77
       562: ldc_w         #564                // String
       565: aastore
       566: aload_0
       567: bipush        78
       569: ldc_w         #564                // String
       572: aastore
       573: aload_0
       574: bipush        79
       576: ldc_w         #564                // String
       579: aastore
       580: aload_0
       581: bipush        80
       583: ldc_w         #564                // String
       586: aastore
       587: aload_0
       588: bipush        81
       590: ldc_w         #564                // String
       593: aastore
       594: aload_0
       595: bipush        82
       597: ldc_w         #564                // String
       600: aastore
       601: aload_0
       602: bipush        83
       604: ldc_w         #564                // String
       607: aastore
       608: aload_0
       609: bipush        84
       611: ldc_w         #564                // String
       614: aastore
       615: aload_0
       616: bipush        85
       618: ldc_w         #564                // String
       621: aastore
       622: aload_0
       623: bipush        86
       625: ldc_w         #564                // String
       628: aastore
       629: aload_0
       630: bipush        87
       632: ldc_w         #564                // String
       635: aastore
       636: aload_0
       637: bipush        88
       639: ldc_w         #564                // String
       642: aastore
       643: aload_0
       644: bipush        89
       646: ldc_w         #564                // String
       649: aastore
       650: aload_0
       651: bipush        90
       653: ldc_w         #564                // String
       656: aastore
       657: aload_0
       658: bipush        91
       660: ldc_w         #564                // String
       663: aastore
       664: aload_0
       665: bipush        92
       667: ldc_w         #564                // String
       670: aastore
       671: aload_0
       672: bipush        93
       674: ldc_w         #564                // String
       677: aastore
       678: aload_0
       679: bipush        94
       681: ldc_w         #564                // String
       684: aastore
       685: aload_0
       686: bipush        95
       688: ldc_w         #564                // String
       691: aastore
       692: aload_0
       693: bipush        96
       695: ldc_w         #564                // String
       698: aastore
       699: aload_0
       700: bipush        97
       702: ldc_w         #564                // String
       705: aastore
       706: aload_0
       707: bipush        98
       709: ldc_w         #570                // String ⛑
       712: aastore
       713: aload_0
       714: bipush        99
       716: ldc_w         #564                // String
       719: aastore
       720: aload_0
       721: bipush        100
       723: ldc_w         #564                // String
       726: aastore
       727: aload_0
       728: bipush        101
       730: ldc_w         #564                // String
       733: aastore
       734: aload_0
       735: bipush        102
       737: ldc_w         #564                // String
       740: aastore
       741: aload_0
       742: bipush        103
       744: ldc_w         #564                // String
       747: aastore
       748: aload_0
       749: bipush        104
       751: ldc_w         #564                // String
       754: aastore
       755: aload_0
       756: bipush        105
       758: ldc_w         #564                // String
       761: aastore
       762: aload_0
       763: bipush        106
       765: ldc_w         #564                // String
       768: aastore
       769: aload_0
       770: bipush        107
       772: ldc_w         #564                // String
       775: aastore
       776: aload_0
       777: bipush        108
       779: ldc_w         #564                // String
       782: aastore
       783: aload_0
       784: bipush        109
       786: ldc_w         #564                // String
       789: aastore
       790: aload_0
       791: bipush        110
       793: ldc_w         #564                // String
       796: aastore
       797: aload_0
       798: bipush        111
       800: ldc_w         #564                // String
       803: aastore
       804: aload_0
       805: bipush        112
       807: ldc_w         #564                // String
       810: aastore
       811: aload_0
       812: bipush        113
       814: ldc_w         #564                // String
       817: aastore
       818: aload_0
       819: bipush        114
       821: ldc_w         #564                // String
       824: aastore
       825: aload_0
       826: bipush        115
       828: ldc_w         #564                // String
       831: aastore
       832: aload_0
       833: bipush        116
       835: ldc_w         #564                // String
       838: aastore
       839: aload_0
       840: bipush        117
       842: ldc_w         #564                // String
       845: aastore
       846: aload_0
       847: bipush        118
       849: ldc_w         #564                // String
       852: aastore
       853: aload_0
       854: bipush        119
       856: ldc_w         #564                // String
       859: aastore
       860: aload_0
       861: bipush        120
       863: ldc_w         #564                // String
       866: aastore
       867: aload_0
       868: bipush        121
       870: ldc_w         #564                // String
       873: aastore
       874: aload_0
       875: bipush        122
       877: ldc_w         #564                // String
       880: aastore
       881: aload_0
       882: bipush        123
       884: ldc_w         #564                // String
       887: aastore
       888: aload_0
       889: bipush        124
       891: ldc_w         #564                // String
       894: aastore
       895: aload_0
       896: bipush        125
       898: ldc_w         #564                // String
       901: aastore
       902: aload_0
       903: bipush        126
       905: ldc_w         #564                // String
       908: aastore
       909: aload_0
       910: bipush        127
       912: ldc_w         #564                // String
       915: aastore
       916: aload_0
       917: invokestatic  #576                // Method kotlin/collections/CollectionsKt.listOf:([Ljava/lang/Object;)Ljava/util/List;
       920: putstatic     #22                 // Field emojis:Ljava/lang/Object;
       923: return
}
