class_version major=61 minor=0
this_class    Err
super_class   java/lang/Object
access_flags  0x0021
interfaces    [Result]
field         msg : Ljava/lang/String; 0x0001
method        <init> (Ljava/lang/String;)V 0x0001
  code        max_stack=2 max_locals=2
    0000 aload_0
    0001 invokespecial Method(java/lang/Object.<init>:()V)
    0004 aload_0
    0005 aload_1
    0006 putfield Field(Err.msg:Ljava/lang/String;)
    0009 return
method        getMsg ()Ljava/lang/String; 0x0001
  code        max_stack=1 max_locals=1
    0000 aload_0
    0001 getfield Field(Err.msg:Ljava/lang/String;)
    0004 areturn
  attr        RuntimeInvisibleAnnotations (6 bytes)
