class_version major=61 minor=0
this_class    BankAccount
super_class   java/lang/Object
access_flags  0x0021
field         balance : I 0x0001
method        <init> (I)V 0x0001
  code        max_stack=2 max_locals=2
    0000 aload_0
    0001 invokespecial Method(java/lang/Object.<init>:()V)
    0004 aload_0
    0005 iload_1
    0006 putfield Field(BankAccount.balance:I)
    0009 return
method        deposit (I)V 0x0001
  code        max_stack=2 max_locals=3
    0000 aload_0
    0001 getfield Field(BankAccount.balance:I)
    0004 iload_1
    0005 iadd
    0006 istore_2
    0007 aload_0
    0008 iload_2
    0009 putfield Field(BankAccount.balance:I)
    0012 return
method        getBalance ()I 0x0001
  code        max_stack=1 max_locals=1
    0000 aload_0
    0001 getfield Field(BankAccount.balance:I)
    0004 ireturn
method        setBalance (I)V 0x0001
  code        max_stack=2 max_locals=2
    0000 aload_0
    0001 iload_1
    0002 putfield Field(BankAccount.balance:I)
    0005 return
method        withdraw (I)V 0x0001
  code        max_stack=2 max_locals=3
    0000 aload_0
    0001 getfield Field(BankAccount.balance:I)
    0004 iload_1
    0005 isub
    0006 istore_2
    0007 aload_0
    0008 iload_2
    0009 putfield Field(BankAccount.balance:I)
    0012 return
