class_version major=61 minor=0
this_class    InputKt
super_class   java/lang/Object
access_flags  0x0031
method        safe (Ljava/lang/Double;Lkotlin/coroutines/Continuation;)Ljava/lang/Object; 0x0019
  code        max_stack=2 max_locals=2
    0000 aload_0
    0001 dup
    0002 ifnull 11
    0005 invokevirtual Method(java/lang/Double.doubleValue:()D)
    0008 goto 13
    0011 pop
    0012 dconst_0
    0013 invokestatic Method(kotlin/coroutines/jvm/internal/Boxing.boxDouble:(D)Ljava/lang/Double;)
    0016 areturn
    sub_attr  StackMapTable (8 bytes)
  attr        Signature (2 bytes)
  attr        RuntimeInvisibleAnnotations (6 bytes)
  attr        RuntimeInvisibleParameterAnnotations (13 bytes)
