class_version major=61 minor=0
this_class    Box
super_class   java/lang/Object
access_flags  0x0021
field         value : I 0x0001
method        <init> (I)V 0x0001
  code        max_stack=2 max_locals=2
    0000 aload_0
    0001 invokespecial Method(java/lang/Object.<init>:()V)
    0004 aload_0
    0005 iload_1
    0006 putfield Field(Box.value:I)
    0009 return
method        doubleIt ()V 0x0001
  code        max_stack=2 max_locals=2
    0000 aload_0
    0001 getfield Field(Box.value:I)
    0004 iconst_2
    0005 imul
    0006 istore_1
    0007 aload_0
    0008 iload_1
    0009 putfield Field(Box.value:I)
    0012 return
method        getValue ()I 0x0001
  code        max_stack=1 max_locals=1
    0000 aload_0
    0001 getfield Field(Box.value:I)
    0004 ireturn
method        setValue (I)V 0x0001
  code        max_stack=2 max_locals=2
    0000 aload_0
    0001 iload_1
    0002 putfield Field(Box.value:I)
    0005 return
method        update (I)V 0x0001
  code        max_stack=2 max_locals=3
    0000 aload_0
    0001 getfield Field(Box.value:I)
    0004 istore_2
    0005 iload_1
    0006 istore_2
    0007 aload_0
    0008 iload_2
    0009 putfield Field(Box.value:I)
    0012 return
