class_version major=61 minor=0
this_class    Pair
super_class   java/lang/Object
access_flags  0x0021
field         first : I 0x0001
field         second : I 0x0001
method        <init> (II)V 0x0001
  code        max_stack=2 max_locals=3
    0000 aload_0
    0001 invokespecial Method(java/lang/Object.<init>:()V)
    0004 aload_0
    0005 iload_1
    0006 putfield Field(Pair.first:I)
    0009 aload_0
    0010 iload_2
    0011 putfield Field(Pair.second:I)
    0014 return
method        getFirst ()I 0x0001
  code        max_stack=1 max_locals=1
    0000 aload_0
    0001 getfield Field(Pair.first:I)
    0004 ireturn
method        getSecond ()I 0x0001
  code        max_stack=1 max_locals=1
    0000 aload_0
    0001 getfield Field(Pair.second:I)
    0004 ireturn
