class_version major=61 minor=0
this_class    test/InputKt
super_class   java/lang/Object
access_flags  0x0031
method        halveDp (Ltest/Dp;)Ltest/Dp; 0x0019
  code        max_stack=2 max_locals=1
    0000 aload_0
    0001 ldc "x"
    0003 invokestatic Method(kotlin/jvm/internal/Intrinsics.checkNotNullParameter:(Ljava/lang/Object;Ljava/lang/String;)V)
    0006 aload_0
    0007 fconst_2
    0008 invokevirtual Method(test/Dp.div:(F)Ltest/Dp;)
    0011 areturn
  attr        RuntimeInvisibleAnnotations (6 bytes)
  attr        RuntimeInvisibleParameterAnnotations (7 bytes)
method        main ()V 0x0019
  code        max_stack=3 max_locals=1
    0000 new Class(test/Dp)
    0003 dup
    0004 ldc float(10)
    0006 invokespecial Method(test/Dp.<init>:(F)V)
    0009 invokestatic Method(test/InputKt.halveDp:(Ltest/Dp;)Ltest/Dp;)
    0012 invokevirtual Method(test/Dp.getValue:()F)
    0015 fstore_0
    0016 getstatic Field(java/lang/System.out:Ljava/io/PrintStream;)
    0019 fload_0
    0020 invokevirtual Method(java/io/PrintStream.println:(F)V)
    0023 new Class(test/Dp)
    0026 dup
    0027 ldc float(10)
    0029 invokespecial Method(test/Dp.<init>:(F)V)
    0032 ldc float(3)
    0034 invokestatic Method(test/InputKt.shrinkDp:(Ltest/Dp;F)Ltest/Dp;)
    0037 invokevirtual Method(test/Dp.getValue:()F)
    0040 fstore_0
    0041 getstatic Field(java/lang/System.out:Ljava/io/PrintStream;)
    0044 fload_0
    0045 invokevirtual Method(java/io/PrintStream.println:(F)V)
    0048 return
method        main ([Ljava/lang/String;)V 0x1009
  code        max_stack=0 max_locals=1
    0000 invokestatic Method(test/InputKt.main:()V)
    0003 return
method        shrinkDp (Ltest/Dp;F)Ltest/Dp; 0x0019
  code        max_stack=2 max_locals=2
    0000 aload_0
    0001 ldc "x"
    0003 invokestatic Method(kotlin/jvm/internal/Intrinsics.checkNotNullParameter:(Ljava/lang/Object;Ljava/lang/String;)V)
    0006 aload_0
    0007 fload_1
    0008 invokevirtual Method(test/Dp.minus:(F)Ltest/Dp;)
    0011 areturn
  attr        RuntimeInvisibleAnnotations (6 bytes)
  attr        RuntimeInvisibleParameterAnnotations (9 bytes)
