class_version major=61 minor=0
this_class    InputKt
super_class   java/lang/Object
access_flags  0x0031
method        applyTimes (ILkotlin/jvm/functions/Function0;)V 0x0019
  code        max_stack=2 max_locals=3
    0000 aload_1
    0001 ldc "action"
    0003 invokestatic Method(kotlin/jvm/internal/Intrinsics.checkNotNullParameter:(Ljava/lang/Object;Ljava/lang/String;)V)
    0006 iconst_0
    0007 istore_2
    0008 iload_2
    0009 iload_0
    0010 if_icmpge 26
    0013 aload_1
    0014 invokeinterface InterfaceMethod(kotlin/jvm/functions/Function0.invoke:()Ljava/lang/Object;)
    0019 pop
    0020 iinc 2 1
    0023 goto 8
    0026 return
    sub_attr  StackMapTable (7 bytes)
  attr        Signature (2 bytes)
  attr        RuntimeInvisibleParameterAnnotations (9 bytes)
method        main ()V 0x0019
  code        max_stack=3 max_locals=1
    0000 new Class(Counter)
    0003 dup
    0004 iconst_0
    0005 invokespecial Method(Counter.<init>:(I)V)
    0008 astore_0
    0009 new Class(InputKt$main$1)
    0012 dup
    0013 aload_0
    0014 invokespecial Method(InputKt$main$1.<init>:(LCounter;)V)
    0017 iconst_5
    0018 swap
    0019 checkcast Class(kotlin/jvm/functions/Function0)
    0022 invokestatic Method(InputKt.applyTimes:(ILkotlin/jvm/functions/Function0;)V)
    0025 aload_0
    0026 invokevirtual Method(Counter.value:()I)
    0029 invokedynamic InvokeDynamic(makeConcatWithConstants:(I)Ljava/lang/String;)
    0034 getstatic Field(java/lang/System.out:Ljava/io/PrintStream;)
    0037 swap
    0038 invokevirtual Method(java/io/PrintStream.println:(Ljava/lang/Object;)V)
    0041 return
method        main ([Ljava/lang/String;)V 0x1009
  code        max_stack=0 max_locals=1
    0000 invokestatic Method(InputKt.main:()V)
    0003 return
class_attr    InnerClasses (10 bytes)
class_attr    BootstrapMethods (8 bytes)
