class_version major=61 minor=0
this_class    InputKt
super_class   java/lang/Object
access_flags  0x0031
method        cellValue (Ljava/lang/String;Ljava/lang/String;[IIII)I 0x0019
  code        max_stack=3 max_locals=21
    0000 aload_0
    0001 ldc "s1"
    0003 invokestatic Method(kotlin/jvm/internal/Intrinsics.checkNotNullParameter:(Ljava/lang/Object;Ljava/lang/String;)V)
    0006 aload_1
    0007 ldc "s2"
    0009 invokestatic Method(kotlin/jvm/internal/Intrinsics.checkNotNullParameter:(Ljava/lang/Object;Ljava/lang/String;)V)
    0012 aload_0
    0013 iload 4
    0015 iconst_1
    0016 isub
    0017 invokevirtual Method(java/lang/String.charAt:(I)C)
    0020 istore 6
    0022 aload_1
    0023 iload 5
    0025 iconst_1
    0026 isub
    0027 invokevirtual Method(java/lang/String.charAt:(I)C)
    0030 istore 7
    0032 iload 6
    0034 iload 7
    0036 if_icmpne 65
    0039 iload 4
    0041 iconst_1
    0042 isub
    0043 iload_3
    0044 imul
    0045 istore 8
    0047 iload 5
    0049 iconst_1
    0050 isub
    0051 istore 9
    0053 iload 8
    0055 iload 9
    0057 iadd
    0058 istore 10
    0060 aload_2
    0061 iload 10
    0063 iaload
    0064 ireturn
    0065 iload 4
    0067 iconst_1
    0068 isub
    0069 iload_3
    0070 imul
    0071 iload 5
    0073 iadd
    0074 istore 11
    0076 aload_2
    0077 iload 11
    0079 iaload
    0080 iconst_1
    0081 iadd
    0082 istore 12
    0084 iload 4
    0086 iload_3
    0087 imul
    0088 istore 13
    0090 iload 5
    0092 iconst_1
    0093 isub
    0094 istore 14
    0096 iload 13
    0098 iload 14
    0100 iadd
    0101 istore 15
    0103 aload_2
    0104 iload 15
    0106 iaload
    0107 iconst_1
    0108 iadd
    0109 istore 16
    0111 iload 4
    0113 iconst_1
    0114 isub
    0115 iload_3
    0116 imul
    0117 istore 17
    0119 iload 5
    0121 iconst_1
    0122 isub
    0123 istore 18
    0125 iload 17
    0127 iload 18
    0129 iadd
    0130 istore 19
    0132 aload_2
    0133 iload 19
    0135 iaload
    0136 iconst_1
    0137 iadd
    0138 istore 20
    0140 iload 12
    0142 iload 16
    0144 iload 20
    0146 invokestatic Method(InputKt.min3:(III)I)
    0149 ireturn
    sub_attr  StackMapTable (7 bytes)
  attr        RuntimeInvisibleParameterAnnotations (21 bytes)
method        editDistance (Ljava/lang/String;Ljava/lang/String;)I 0x0019
  code        max_stack=6 max_locals=20
    0000 aload_0
    0001 ldc "s1"
    0003 invokestatic Method(kotlin/jvm/internal/Intrinsics.checkNotNullParameter:(Ljava/lang/Object;Ljava/lang/String;)V)
    0006 aload_1
    0007 ldc "s2"
    0009 invokestatic Method(kotlin/jvm/internal/Intrinsics.checkNotNullParameter:(Ljava/lang/Object;Ljava/lang/String;)V)
    0012 aload_0
    0013 invokevirtual Method(java/lang/String.length:()I)
    0016 istore_2
    0017 aload_1
    0018 invokevirtual Method(java/lang/String.length:()I)
    0021 istore_3
    0022 iload_3
    0023 iconst_1
    0024 iadd
    0025 istore 4
    0027 iload_2
    0028 iconst_1
    0029 iadd
    0030 iload 4
    0032 imul
    0033 newarray int
    0035 astore 5
    0037 iconst_0
    0038 istore 6
    0040 iload 6
    0042 iload_3
    0043 if_icmpgt 67
    0046 iload 6
    0048 istore 7
    0050 iload 6
    0052 istore 8
    0054 aload 5
    0056 iload 7
    0058 iload 8
    0060 iastore
    0061 iinc 6 1
    0064 goto 40
    0067 iconst_0
    0068 istore 9
    0070 iload 9
    0072 iload_2
    0073 if_icmpgt 100
    0076 iload 9
    0078 iload 4
    0080 imul
    0081 istore 10
    0083 iload 9
    0085 istore 11
    0087 aload 5
    0089 iload 10
    0091 iload 11
    0093 iastore
    0094 iinc 9 1
    0097 goto 70
    0100 iconst_1
    0101 istore 9
    0103 iload 9
    0105 iload_2
    0106 if_icmpgt 115
    0109 iconst_1
    0110 istore 12
    0112 goto 129
    0115 iload_2
    0116 iload 4
    0118 imul
    0119 iload_3
    0120 iadd
    0121 istore 13
    0123 aload 5
    0125 iload 13
    0127 iaload
    0128 ireturn
    0129 iload 12
    0131 iload_3
    0132 if_icmpgt 189
    0135 iload 9
    0137 iload 4
    0139 imul
    0140 istore 14
    0142 iload 12
    0144 istore 15
    0146 iload 14
    0148 iload 15
    0150 iadd
    0151 istore 16
    0153 iload 9
    0155 istore 17
    0157 iload 12
    0159 istore 18
    0161 aload_0
    0162 aload_1
    0163 aload 5
    0165 iload 4
    0167 iload 17
    0169 iload 18
    0171 invokestatic Method(InputKt.cellValue:(Ljava/lang/String;Ljava/lang/String;[IIII)I)
    0174 istore 19
    0176 aload 5
    0178 iload 16
    0180 iload 19
    0182 iastore
    0183 iinc 12 1
    0186 goto 129
    0189 iinc 9 1
    0192 goto 103
    sub_attr  StackMapTable (39 bytes)
  attr        RuntimeInvisibleParameterAnnotations (13 bytes)
method        main ()V 0x0019
  code        max_stack=2 max_locals=0
    0000 ldc ""
    0002 ldc ""
    0004 invokestatic Method(InputKt.report:(Ljava/lang/String;Ljava/lang/String;)V)
    0007 ldc "a"
    0009 ldc ""
    0011 invokestatic Method(InputKt.report:(Ljava/lang/String;Ljava/lang/String;)V)
    0014 ldc ""
    0016 ldc "abc"
    0018 invokestatic Method(InputKt.report:(Ljava/lang/String;Ljava/lang/String;)V)
    0021 ldc "abc"
    0023 ldc "abc"
    0025 invokestatic Method(InputKt.report:(Ljava/lang/String;Ljava/lang/String;)V)
    0028 ldc "kitten"
    0030 ldc "sitting"
    0032 invokestatic Method(InputKt.report:(Ljava/lang/String;Ljava/lang/String;)V)
    0035 ldc "flaw"
    0037 ldc "lawn"
    0039 invokestatic Method(InputKt.report:(Ljava/lang/String;Ljava/lang/String;)V)
    0042 ldc "intention"
    0044 ldc "execution"
    0046 invokestatic Method(InputKt.report:(Ljava/lang/String;Ljava/lang/String;)V)
    0049 ldc "Saturday"
    0051 ldc "Sunday"
    0053 invokestatic Method(InputKt.report:(Ljava/lang/String;Ljava/lang/String;)V)
    0056 ldc "rosettacode"
    0058 ldc "raisethysword"
    0060 invokestatic Method(InputKt.report:(Ljava/lang/String;Ljava/lang/String;)V)
    0063 return
method        main ([Ljava/lang/String;)V 0x1009
  code        max_stack=0 max_locals=1
    0000 invokestatic Method(InputKt.main:()V)
    0003 return
method        min3 (III)I 0x0019
  code        max_stack=2 max_locals=4
    0000 iload_0
    0001 istore_3
    0002 iload_1
    0003 iload_3
    0004 if_icmpge 9
    0007 iload_1
    0008 istore_3
    0009 iload_2
    0010 iload_3
    0011 if_icmpge 16
    0014 iload_2
    0015 istore_3
    0016 iload_3
    0017 ireturn
    sub_attr  StackMapTable (7 bytes)
method        report (Ljava/lang/String;Ljava/lang/String;)V 0x0019
  code        max_stack=3 max_locals=3
    0000 aload_0
    0001 ldc "s1"
    0003 invokestatic Method(kotlin/jvm/internal/Intrinsics.checkNotNullParameter:(Ljava/lang/Object;Ljava/lang/String;)V)
    0006 aload_1
    0007 ldc "s2"
    0009 invokestatic Method(kotlin/jvm/internal/Intrinsics.checkNotNullParameter:(Ljava/lang/Object;Ljava/lang/String;)V)
    0012 aload_0
    0013 aload_1
    0014 invokestatic Method(InputKt.editDistance:(Ljava/lang/String;Ljava/lang/String;)I)
    0017 istore_2
    0018 aload_0
    0019 aload_1
    0020 iload_2
    0021 invokedynamic InvokeDynamic(makeConcatWithConstants:(Ljava/lang/String;Ljava/lang/String;I)Ljava/lang/String;)
    0026 getstatic Field(java/lang/System.out:Ljava/io/PrintStream;)
    0029 swap
    0030 invokevirtual Method(java/io/PrintStream.println:(Ljava/lang/Object;)V)
    0033 return
  attr        RuntimeInvisibleParameterAnnotations (13 bytes)
class_attr    BootstrapMethods (8 bytes)
