class_version major=61 minor=0
this_class    InputKt
super_class   java/lang/Object
access_flags  0x0031
method        A ()LV; 0x0019
  code        max_stack=1 max_locals=0
    0000 getstatic Field(V.A:LV;)
    0003 areturn
  attr        RuntimeInvisibleAnnotations (6 bytes)
method        B ()LV; 0x0019
  code        max_stack=1 max_locals=0
    0000 getstatic Field(V.B:LV;)
    0003 areturn
  attr        RuntimeInvisibleAnnotations (6 bytes)
method        Box (Landroidx/compose/runtime/Composer;I)V 0x0019
  code        max_stack=4 max_locals=4
    0000 aload_0
    0001 ldc int(-708084014)
    0003 invokeinterface InterfaceMethod(androidx/compose/runtime/Composer.startRestartGroup:(I)Landroidx/compose/runtime/Composer;)
    0008 astore_0
    0009 aload_0
    0010 iload_1
    0011 ifeq 18
    0014 iconst_1
    0015 goto 19
    0018 iconst_0
    0019 iload_1
    0020 iconst_1
    0021 iand
    0022 invokeinterface InterfaceMethod(androidx/compose/runtime/Composer.shouldExecute:(ZI)Z)
    0027 ifne 39
    0030 aload_0
    0031 invokeinterface InterfaceMethod(androidx/compose/runtime/Composer.skipToGroupEnd:()V)
    0036 goto 50
    0039 invokedynamic InvokeDynamic(invoke:()Lkotlin/jvm/functions/Function1;)
    0044 astore_2
    0045 aload_2
    0046 invokestatic Method(InputKt.pick:(Lkotlin/jvm/functions/Function1;)I)
    0049 istore_3
    0050 aload_0
    0051 invokeinterface InterfaceMethod(androidx/compose/runtime/Composer.endRestartGroup:()Landroidx/compose/runtime/ScopeUpdateScope;)
    0056 dup
    0057 ifnull 74
    0060 iload_1
    0061 invokedynamic InvokeDynamic(invoke:(I)Lkotlin/jvm/functions/Function2;)
    0066 invokeinterface InterfaceMethod(androidx/compose/runtime/ScopeUpdateScope.updateScope:(Lkotlin/jvm/functions/Function2;)V)
    0071 goto 75
    0074 pop
    0075 return
    sub_attr  StackMapTable (28 bytes)
  attr        RuntimeInvisibleAnnotations (6 bytes)
  attr        RuntimeInvisibleParameterAnnotations (9 bytes)
method        Box$lambda$0 (ILandroidx/compose/runtime/Composer;I)Lkotlin/Unit; 0x001A
  code        max_stack=3 max_locals=3
    0000 aload_1
    0001 iload_0
    0002 iconst_1
    0003 ior
    0004 invokestatic Method(androidx/compose/runtime/RecomposeScopeImplKt.updateChangedFlags:(I)I)
    0007 invokestatic Method(InputKt.Box:(Landroidx/compose/runtime/Composer;I)V)
    0010 getstatic Field(kotlin/Unit.INSTANCE:Lkotlin/Unit;)
    0013 areturn
method        Box$lambda$0 (LV;)I 0x001A
  code        max_stack=3 max_locals=1
    0000 aload_0
    0001 aload_0
    0002 ldc "it"
    0004 invokestatic Method(kotlin/jvm/internal/Intrinsics.checkNotNullParameter:(Ljava/lang/Object;Ljava/lang/String;)V)
    0007 invokestatic Method(InputKt.A:()LV;)
    0010 swap
    0011 invokevirtual Method(java/lang/Object.toString:()Ljava/lang/String;)
    0014 swap
    0015 invokevirtual Method(java/lang/Object.toString:()Ljava/lang/String;)
    0018 invokevirtual Method(java/lang/String.equals:(Ljava/lang/Object;)Z)
    0021 ifeq 28
    0024 iconst_1
    0025 goto 29
    0028 iconst_2
    0029 ireturn
    sub_attr  StackMapTable (5 bytes)
method        V$valueOf (Ljava/lang/String;)LV; 0x0019
  code        max_stack=2 max_locals=1
    0000 aload_0
    0001 ldc "name"
    0003 invokestatic Method(kotlin/jvm/internal/Intrinsics.checkNotNullParameter:(Ljava/lang/Object;Ljava/lang/String;)V)
    0006 aload_0
    0007 ldc "A"
    0009 invokestatic Method(kotlin/jvm/internal/Intrinsics.areEqual:(Ljava/lang/Object;Ljava/lang/Object;)Z)
    0012 ifeq 22
    0015 goto 35
    0018 invokestatic Method(InputKt.A:()LV;)
    0021 areturn
    0022 aload_0
    0023 ldc "B"
    0025 invokestatic Method(kotlin/jvm/internal/Intrinsics.areEqual:(Ljava/lang/Object;Ljava/lang/Object;)Z)
    0028 ifeq 18
    0031 invokestatic Method(InputKt.B:()LV;)
    0034 areturn
    0035 invokestatic Method(InputKt.A:()LV;)
    0038 areturn
    sub_attr  StackMapTable (5 bytes)
  attr        RuntimeInvisibleAnnotations (6 bytes)
  attr        RuntimeInvisibleParameterAnnotations (7 bytes)
method        V$values ()Ljava/util/ArrayList; 0x0019
  code        max_stack=2 max_locals=1
    0000 new Class(java/util/ArrayList)
    0003 dup
    0004 invokespecial Method(java/util/ArrayList.<init>:()V)
    0007 astore_0
    0008 aload_0
    0009 invokestatic Method(InputKt.A:()LV;)
    0012 invokevirtual Method(java/util/ArrayList.add:(Ljava/lang/Object;)Z)
    0015 pop
    0016 aload_0
    0017 invokestatic Method(InputKt.B:()LV;)
    0020 invokevirtual Method(java/util/ArrayList.add:(Ljava/lang/Object;)Z)
    0023 pop
    0024 aload_0
    0025 areturn
  attr        RuntimeInvisibleAnnotations (6 bytes)
method        pick (Lkotlin/jvm/functions/Function1;)I 0x0019
  code        max_stack=2 max_locals=1
    0000 aload_0
    0001 ldc "fn"
    0003 invokestatic Method(kotlin/jvm/internal/Intrinsics.checkNotNullParameter:(Ljava/lang/Object;Ljava/lang/String;)V)
    0006 invokestatic Method(InputKt.A:()LV;)
    0009 aload_0
    0010 swap
    0011 invokeinterface InterfaceMethod(kotlin/jvm/functions/Function1.invoke:(Ljava/lang/Object;)Ljava/lang/Object;)
    0016 checkcast Class(java/lang/Number)
    0019 invokevirtual Method(java/lang/Number.intValue:()I)
    0022 ireturn
  attr        Signature (2 bytes)
  attr        RuntimeInvisibleParameterAnnotations (7 bytes)
class_attr    BootstrapMethods (22 bytes)
