class_version major=61 minor=0
this_class    InputKt
super_class   java/lang/Object
access_flags  0x0031
method        fibonacci (I)I 0x0009
  code        max_stack=3 max_locals=22
    0000 iload 0
    0002 istore 1
    0004 iconst_1
    0005 istore 2
    0007 iload 1
    0009 iload 2
    0011 op_0xA4
    0012 nop
    0013 iconst_4
    0014 iconst_0
    0015 op_0xA7
    0016 nop
    0017 iconst_1
    0018 iconst_1
    0019 istore 3
    0021 iload 3
    0023 op_0x99
    0024 nop
    0025 op_0x0A
    0026 iload 0
    0028 istore 4
    0030 iload 4
    0032 op_0xAC
    0033 op_0xA7
    0034 nop
    0035 iconst_0
    0036 iconst_0
    0037 istore 5
    0039 iload 5
    0041 istore 6
    0043 iconst_1
    0044 istore 7
    0046 iload 7
    0048 istore 8
    0050 iconst_2
    0051 istore 9
    0053 iload 0
    0055 istore 10
    0057 iload 9
    0059 istore 11
    0061 op_0xA7
    0062 nop
    0063 iconst_0
    0064 iload 11
    0066 iload 10
    0068 op_0xA4
    0069 nop
    0070 iconst_4
    0071 iconst_0
    0072 op_0xA7
    0073 nop
    0074 iconst_1
    0075 iconst_1
    0076 istore 12
    0078 iload 12
    0080 op_0x99
    0081 nop
    0082 astore 21
    0084 iconst_3
    0085 istore 13
    0087 iload 8
    0089 istore 14
    0091 iload 13
    0093 iload 14
    0095 iadd
    0096 istore 15
    0098 iload 15
    0100 istore 16
    0102 iload 8
    0104 istore 17
    0106 iload 17
    0108 istore 6
    0110 iload 16
    0112 istore 18
    0114 iload 18
    0116 istore 8
    0118 op_0xA7
    0119 nop
    0120 iconst_0
    0121 iconst_1
    0122 istore 19
    0124 iload 11
    0126 iload 19
    0128 iadd
    0129 istore 20
    0131 iload 20
    0133 istore 11
    0135 op_0xA7
    0136 op_0xFF
    0137 op_0xB9
    0138 iload 8
    0140 istore 21
    0142 iload 21
    0144 op_0xAC
    sub_attr  StackMapTable (149 bytes)
method        isEven (I)Z 0x0009
  code        max_stack=2 max_locals=6
    0000 iload 0
    0002 istore 1
    0004 iconst_2
    0005 istore 2
    0007 iload 1
    0009 iload 2
    0011 irem
    0012 istore 3
    0014 iconst_0
    0015 istore 4
    0017 iload 3
    0019 iload 4
    0021 op_0x9F
    0022 nop
    0023 iconst_4
    0024 iconst_0
    0025 op_0xA7
    0026 nop
    0027 iconst_1
    0028 iconst_1
    0029 istore 5
    0031 iload 5
    0033 op_0xAC
    sub_attr  StackMapTable (27 bytes)
method        isOdd (I)Z 0x0009
  code        max_stack=2 max_locals=4
    0000 invokestatic Method(InputKt.isEven:(I)Z)
    0003 istore 1
    0005 iconst_1
    0006 istore 2
    0008 iload 2
    0010 iload 1
    0012 isub
    0013 istore 3
    0015 iload 3
    0017 op_0xAC
method        main ([Ljava/lang/String;)V 0x0009
  code        max_stack=3 max_locals=30
    0000 ldc "Sum of odds 1..10: "
    0002 astore 1
    0004 bipush 10
    0006 istore 2
    0008 iload 2
    0010 invokestatic Method(InputKt.sumOfOdds:(I)I)
    0013 istore 3
    0015 getstatic Field(java/lang/System.out:Ljava/io/PrintStream;)
    0018 op_0xBB
    0019 nop
    0020 op_0x1E
    0021 op_0x59
    0022 invokespecial Method(java/lang/StringBuilder.<init>:()V)
    0025 aload 1
    0027 invokevirtual Method(java/lang/StringBuilder.append:(Ljava/lang/String;)Ljava/lang/StringBuilder;)
    0030 iload 3
    0032 invokevirtual Method(java/lang/StringBuilder.append:(I)Ljava/lang/StringBuilder;)
    0035 invokevirtual Method(java/lang/StringBuilder.toString:()Ljava/lang/String;)
    0038 invokevirtual Method(java/io/PrintStream.println:(Ljava/lang/String;)V)
    0041 ldc "Fib(10): "
    0043 astore 4
    0045 bipush 10
    0047 istore 5
    0049 iload 5
    0051 invokestatic Method(InputKt.fibonacci:(I)I)
    0054 istore 6
    0056 getstatic Field(java/lang/System.out:Ljava/io/PrintStream;)
    0059 op_0xBB
    0060 nop
    0061 op_0x1E
    0062 op_0x59
    0063 invokespecial Method(java/lang/StringBuilder.<init>:()V)
    0066 aload 4
    0068 invokevirtual Method(java/lang/StringBuilder.append:(Ljava/lang/String;)Ljava/lang/StringBuilder;)
    0071 iload 6
    0073 invokevirtual Method(java/lang/StringBuilder.append:(I)Ljava/lang/StringBuilder;)
    0076 invokevirtual Method(java/lang/StringBuilder.toString:()Ljava/lang/String;)
    0079 invokevirtual Method(java/io/PrintStream.println:(Ljava/lang/String;)V)
    0082 iconst_1
    0083 istore 7
    0085 op_0xA7
    0086 nop
    0087 iconst_0
    0088 bipush 10
    0090 istore 8
    0092 iload 8
    0094 invokestatic Method(InputKt.sumOfOdds:(I)I)
    0097 istore 9
    0099 bipush 20
    0101 istore 10
    0103 iload 9
    0105 iload 10
    0107 op_0xA3
    0108 nop
    0109 iconst_4
    0110 iconst_0
    0111 op_0xA7
    0112 nop
    0113 iconst_1
    0114 iconst_1
    0115 istore 11
    0117 iload 11
    0119 op_0x99
    0120 nop
    0121 op_0x0E
    0122 ldc "big"
    0124 astore 12
    0126 aload 12
    0128 astore 13
    0130 op_0xA7
    0131 nop
    0132 op_0x0E
    0133 ldc "small"
    0135 astore 14
    0137 aload 14
    0139 astore 13
    0141 op_0xA7
    0142 nop
    0143 iconst_0
    0144 aload 13
    0146 astore 15
    0148 ldc "Classification: "
    0150 astore 16
    0152 aload 15
    0154 astore 17
    0156 getstatic Field(java/lang/System.out:Ljava/io/PrintStream;)
    0159 op_0xBB
    0160 nop
    0161 op_0x1E
    0162 op_0x59
    0163 invokespecial Method(java/lang/StringBuilder.<init>:()V)
    0166 aload 16
    0168 invokevirtual Method(java/lang/StringBuilder.append:(Ljava/lang/String;)Ljava/lang/StringBuilder;)
    0171 aload 17
    0173 invokevirtual Method(java/lang/StringBuilder.append:(Ljava/lang/String;)Ljava/lang/StringBuilder;)
    0176 invokevirtual Method(java/lang/StringBuilder.toString:()Ljava/lang/String;)
    0179 invokevirtual Method(java/io/PrintStream.println:(Ljava/lang/String;)V)
    0182 iconst_1
    0183 istore 18
    0185 iconst_5
    0186 istore 19
    0188 iload 18
    0190 istore 20
    0192 op_0xA7
    0193 nop
    0194 iconst_0
    0195 iload 20
    0197 iload 19
    0199 op_0xA4
    0200 nop
    0201 iconst_4
    0202 iconst_0
    0203 op_0xA7
    0204 nop
    0205 iconst_1
    0206 iconst_1
    0207 istore 21
    0209 iload 21
    0211 op_0x99
    0212 nop
    0213 op_0x29
    0214 iload 20
    0216 istore 22
    0218 ldc ": "
    0220 astore 23
    0222 invokestatic Method(InputKt.isOdd:(I)Z)
    0225 istore 24
    0227 iload 24
    0229 op_0x99
    0230 nop
    0231 op_0x23
    0232 op_0xA7
    0233 nop
    0234 iload 4
    0236 istore 25
    0238 iload 20
    0240 iload 25
    0242 iadd
    0243 istore 26
    0245 iload 26
    0247 istore 20
    0249 op_0xA7
    0250 op_0xFF
    0251 op_0xCA
    0252 return
    0253 ldc "odd"
    0255 astore 27
    0257 aload 27
    0259 astore 28
    0261 op_0xA7
    0262 nop
    0263 op_0x0E
    0264 ldc "even"
    0266 astore 29
    0268 aload 29
    0270 astore 28
    0272 op_0xA7
    0273 nop
    0274 iconst_0
    0275 getstatic Field(java/lang/System.out:Ljava/io/PrintStream;)
    0278 op_0xBB
    0279 nop
    0280 op_0x1E
    0281 op_0x59
    0282 invokespecial Method(java/lang/StringBuilder.<init>:()V)
    0285 iload 22
    0287 invokevirtual Method(java/lang/StringBuilder.append:(I)Ljava/lang/StringBuilder;)
    0290 aload 23
    0292 invokevirtual Method(java/lang/StringBuilder.append:(Ljava/lang/String;)Ljava/lang/StringBuilder;)
    0295 aload 28
    0297 invokevirtual Method(java/lang/StringBuilder.append:(Ljava/lang/String;)Ljava/lang/StringBuilder;)
    0300 invokevirtual Method(java/lang/StringBuilder.toString:()Ljava/lang/String;)
    0303 invokevirtual Method(java/io/PrintStream.println:(Ljava/lang/String;)V)
    0306 op_0xA7
    0307 op_0xFF
    0308 op_0xB9
    sub_attr  StackMapTable (500 bytes)
method        sumOfOdds (I)I 0x0009
  code        max_stack=3 max_locals=14
    0000 iconst_0
    0001 istore 1
    0003 iload 1
    0005 istore 2
    0007 iconst_1
    0008 istore 3
    0010 iload 0
    0012 istore 4
    0014 iload 3
    0016 istore 5
    0018 op_0xA7
    0019 nop
    0020 iconst_0
    0021 iload 5
    0023 iload 4
    0025 op_0xA4
    0026 nop
    0027 iconst_4
    0028 iconst_0
    0029 op_0xA7
    0030 nop
    0031 iconst_1
    0032 iconst_1
    0033 istore 6
    0035 iload 6
    0037 op_0x99
    0038 nop
    0039 op_0x21
    0040 invokestatic Method(InputKt.isEven:(I)Z)
    0043 istore 7
    0045 iload 7
    0047 op_0x99
    0048 nop
    0049 op_0x21
    0050 op_0xA7
    0051 nop
    0052 op_0x1B
    0053 iconst_1
    0054 istore 8
    0056 iload 5
    0058 iload 8
    0060 iadd
    0061 istore 9
    0063 iload 9
    0065 istore 5
    0067 op_0xA7
    0068 op_0xFF
    0069 op_0xD2
    0070 iload 2
    0072 istore 10
    0074 iload 10
    0076 op_0xAC
    0077 op_0xA7
    0078 op_0xFF
    0079 op_0xE8
    0080 op_0xA7
    0081 nop
    0082 iconst_0
    0083 iload 2
    0085 istore 11
    0087 iload 5
    0089 istore 12
    0091 iload 11
    0093 iload 12
    0095 iadd
    0096 istore 13
    0098 iload 13
    0100 istore 2
    0102 op_0xA7
    0103 op_0xFF
    0104 op_0xCF
    sub_attr  StackMapTable (116 bytes)
