class_version major=61 minor=0
this_class    InputKt
super_class   java/lang/Object
access_flags  0x0031
method        fwd (Ljava/lang/String;Lkotlin/coroutines/Continuation;)Ljava/lang/Object; 0x0019
  code        max_stack=1 max_locals=2
    0000 aload_0
    0001 invokestatic Method(InputKt.greet:(Ljava/lang/String;)Ljava/lang/String;)
    0004 areturn
  attr        Signature (2 bytes)
  attr        RuntimeInvisibleAnnotations (6 bytes)
  attr        RuntimeInvisibleParameterAnnotations (13 bytes)
method        greet (Ljava/lang/String;)Ljava/lang/String; 0x0019
  code        max_stack=2 max_locals=1
    0000 aload_0
    0001 ldc "s"
    0003 invokestatic Method(kotlin/jvm/internal/Intrinsics.checkNotNullParameter:(Ljava/lang/Object;Ljava/lang/String;)V)
    0006 aload_0
    0007 invokedynamic InvokeDynamic(makeConcatWithConstants:(Ljava/lang/String;)Ljava/lang/String;)
    0012 areturn
  attr        RuntimeInvisibleAnnotations (6 bytes)
  attr        RuntimeInvisibleParameterAnnotations (7 bytes)
class_attr    BootstrapMethods (8 bytes)
