class_version major=61 minor=0
this_class    InputKt
super_class   java/lang/Object
access_flags  0x0031
field         xs : Ljava/util/List; 0x001A
method        <clinit> ()V 0x0008
  code        max_stack=3 max_locals=1
    0000 iconst_3
    0001 anewarray Class(java/lang/String)
    0004 astore_0
    0005 aload_0
    0006 iconst_0
    0007 ldc "a"
    0009 aastore
    0010 aload_0
    0011 iconst_1
    0012 ldc "b"
    0014 aastore
    0015 aload_0
    0016 iconst_2
    0017 ldc "c"
    0019 aastore
    0020 aload_0
    0021 invokestatic Method(kotlin/collections/CollectionsKt.listOf:([Ljava/lang/Object;)Ljava/util/List;)
    0024 putstatic Field(InputKt.xs:Ljava/util/List;)
    0027 return
method        getXs ()Ljava/util/List; 0x0019
  code        max_stack=1 max_locals=0
    0000 getstatic Field(InputKt.xs:Ljava/util/List;)
    0003 areturn
method        main ()V 0x0019
  code        max_stack=2 max_locals=1
    0000 getstatic Field(InputKt.xs:Ljava/util/List;)
    0003 invokeinterface InterfaceMethod(java/util/List.size:()I)
    0008 istore_0
    0009 getstatic Field(java/lang/System.out:Ljava/io/PrintStream;)
    0012 iload_0
    0013 invokevirtual Method(java/io/PrintStream.println:(I)V)
    0016 return
method        main ([Ljava/lang/String;)V 0x1009
  code        max_stack=0 max_locals=1
    0000 invokestatic Method(InputKt.main:()V)
    0003 return
