class_version major=61 minor=0
this_class    InputKt
super_class   java/lang/Object
access_flags  0x0031
method        BLUE ()LColor; 0x0019
  code        max_stack=3 max_locals=0
    0000 new Class(Color)
    0003 dup
    0004 ldc "BLUE"
    0006 invokespecial Method(Color.<init>:(Ljava/lang/String;)V)
    0009 areturn
  attr        RuntimeInvisibleAnnotations (6 bytes)
method        Color$valueOf (Ljava/lang/String;)LColor; 0x0019
  code        max_stack=4 max_locals=11
    0000 aload_0
    0001 ldc "name"
    0003 invokestatic Method(kotlin/jvm/internal/Intrinsics.checkNotNullParameter:(Ljava/lang/Object;Ljava/lang/String;)V)
    0006 ldc "RED"
    0008 astore_1
    0009 aload_0
    0010 aload_1
    0011 invokestatic Method(kotlin/jvm/internal/Intrinsics.areEqual:(Ljava/lang/Object;Ljava/lang/Object;)Z)
    0014 istore_2
    0015 iload_2
    0016 ifeq 53
    0019 goto 78
    0022 invokestatic Method(InputKt.RED:()LColor;)
    0025 astore_3
    0026 aload_3
    0027 areturn
    0028 ldc "BLUE"
    0030 astore 4
    0032 aload_0
    0033 aload 4
    0035 invokestatic Method(kotlin/jvm/internal/Intrinsics.areEqual:(Ljava/lang/Object;Ljava/lang/Object;)Z)
    0038 istore 5
    0040 iload 5
    0042 ifeq 22
    0045 invokestatic Method(InputKt.BLUE:()LColor;)
    0048 astore 6
    0050 aload 6
    0052 areturn
    0053 ldc "GREEN"
    0055 astore 7
    0057 aload_0
    0058 aload 7
    0060 invokestatic Method(kotlin/jvm/internal/Intrinsics.areEqual:(Ljava/lang/Object;Ljava/lang/Object;)Z)
    0063 istore 8
    0065 iload 8
    0067 ifeq 28
    0070 invokestatic Method(InputKt.GREEN:()LColor;)
    0073 astore 9
    0075 aload 9
    0077 areturn
    0078 invokestatic Method(InputKt.RED:()LColor;)
    0081 astore 10
    0083 aload 10
    0085 areturn
    sub_attr  StackMapTable (63 bytes)
  attr        RuntimeInvisibleAnnotations (6 bytes)
  attr        RuntimeInvisibleParameterAnnotations (7 bytes)
method        Color$values ()Ljava/util/ArrayList; 0x0019
  code        max_stack=2 max_locals=1
    0000 new Class(java/util/ArrayList)
    0003 dup
    0004 invokespecial Method(java/util/ArrayList.<init>:()V)
    0007 astore_0
    0008 invokestatic Method(InputKt.RED:()LColor;)
    0011 aload_0
    0012 swap
    0013 invokevirtual Method(java/util/ArrayList.add:(Ljava/lang/Object;)Z)
    0016 pop
    0017 invokestatic Method(InputKt.GREEN:()LColor;)
    0020 aload_0
    0021 swap
    0022 invokevirtual Method(java/util/ArrayList.add:(Ljava/lang/Object;)Z)
    0025 pop
    0026 invokestatic Method(InputKt.BLUE:()LColor;)
    0029 aload_0
    0030 swap
    0031 invokevirtual Method(java/util/ArrayList.add:(Ljava/lang/Object;)Z)
    0034 pop
    0035 aload_0
    0036 areturn
  attr        RuntimeInvisibleAnnotations (6 bytes)
method        GREEN ()LColor; 0x0019
  code        max_stack=3 max_locals=0
    0000 new Class(Color)
    0003 dup
    0004 ldc "GREEN"
    0006 invokespecial Method(Color.<init>:(Ljava/lang/String;)V)
    0009 areturn
  attr        RuntimeInvisibleAnnotations (6 bytes)
method        LARGE ()LSize; 0x0019
  code        max_stack=3 max_locals=0
    0000 new Class(Size)
    0003 dup
    0004 ldc "LARGE"
    0006 invokespecial Method(Size.<init>:(Ljava/lang/String;)V)
    0009 areturn
  attr        RuntimeInvisibleAnnotations (6 bytes)
method        MEDIUM ()LSize; 0x0019
  code        max_stack=3 max_locals=0
    0000 new Class(Size)
    0003 dup
    0004 ldc "MEDIUM"
    0006 invokespecial Method(Size.<init>:(Ljava/lang/String;)V)
    0009 areturn
  attr        RuntimeInvisibleAnnotations (6 bytes)
method        RED ()LColor; 0x0019
  code        max_stack=3 max_locals=0
    0000 new Class(Color)
    0003 dup
    0004 ldc "RED"
    0006 invokespecial Method(Color.<init>:(Ljava/lang/String;)V)
    0009 areturn
  attr        RuntimeInvisibleAnnotations (6 bytes)
method        SMALL ()LSize; 0x0019
  code        max_stack=3 max_locals=0
    0000 new Class(Size)
    0003 dup
    0004 ldc "SMALL"
    0006 invokespecial Method(Size.<init>:(Ljava/lang/String;)V)
    0009 areturn
  attr        RuntimeInvisibleAnnotations (6 bytes)
method        Size$valueOf (Ljava/lang/String;)LSize; 0x0019
  code        max_stack=4 max_locals=11
    0000 aload_0
    0001 ldc "name"
    0003 invokestatic Method(kotlin/jvm/internal/Intrinsics.checkNotNullParameter:(Ljava/lang/Object;Ljava/lang/String;)V)
    0006 ldc "SMALL"
    0008 astore_1
    0009 aload_0
    0010 aload_1
    0011 invokestatic Method(kotlin/jvm/internal/Intrinsics.areEqual:(Ljava/lang/Object;Ljava/lang/Object;)Z)
    0014 istore_2
    0015 iload_2
    0016 ifeq 53
    0019 goto 78
    0022 invokestatic Method(InputKt.SMALL:()LSize;)
    0025 astore_3
    0026 aload_3
    0027 areturn
    0028 ldc "LARGE"
    0030 astore 4
    0032 aload_0
    0033 aload 4
    0035 invokestatic Method(kotlin/jvm/internal/Intrinsics.areEqual:(Ljava/lang/Object;Ljava/lang/Object;)Z)
    0038 istore 5
    0040 iload 5
    0042 ifeq 22
    0045 invokestatic Method(InputKt.LARGE:()LSize;)
    0048 astore 6
    0050 aload 6
    0052 areturn
    0053 ldc "MEDIUM"
    0055 astore 7
    0057 aload_0
    0058 aload 7
    0060 invokestatic Method(kotlin/jvm/internal/Intrinsics.areEqual:(Ljava/lang/Object;Ljava/lang/Object;)Z)
    0063 istore 8
    0065 iload 8
    0067 ifeq 28
    0070 invokestatic Method(InputKt.MEDIUM:()LSize;)
    0073 astore 9
    0075 aload 9
    0077 areturn
    0078 invokestatic Method(InputKt.SMALL:()LSize;)
    0081 astore 10
    0083 aload 10
    0085 areturn
    sub_attr  StackMapTable (63 bytes)
  attr        RuntimeInvisibleAnnotations (6 bytes)
  attr        RuntimeInvisibleParameterAnnotations (7 bytes)
method        Size$values ()Ljava/util/ArrayList; 0x0019
  code        max_stack=2 max_locals=1
    0000 new Class(java/util/ArrayList)
    0003 dup
    0004 invokespecial Method(java/util/ArrayList.<init>:()V)
    0007 astore_0
    0008 invokestatic Method(InputKt.SMALL:()LSize;)
    0011 aload_0
    0012 swap
    0013 invokevirtual Method(java/util/ArrayList.add:(Ljava/lang/Object;)Z)
    0016 pop
    0017 invokestatic Method(InputKt.MEDIUM:()LSize;)
    0020 aload_0
    0021 swap
    0022 invokevirtual Method(java/util/ArrayList.add:(Ljava/lang/Object;)Z)
    0025 pop
    0026 invokestatic Method(InputKt.LARGE:()LSize;)
    0029 aload_0
    0030 swap
    0031 invokevirtual Method(java/util/ArrayList.add:(Ljava/lang/Object;)Z)
    0034 pop
    0035 aload_0
    0036 areturn
  attr        RuntimeInvisibleAnnotations (6 bytes)
method        main ()V 0x0019
  code        max_stack=2 max_locals=0
    0000 invokestatic Method(InputKt.RED:()LColor;)
    0003 getstatic Field(java/lang/System.out:Ljava/io/PrintStream;)
    0006 swap
    0007 invokevirtual Method(java/io/PrintStream.println:(Ljava/lang/Object;)V)
    0010 invokestatic Method(InputKt.BLUE:()LColor;)
    0013 getstatic Field(java/lang/System.out:Ljava/io/PrintStream;)
    0016 swap
    0017 invokevirtual Method(java/io/PrintStream.println:(Ljava/lang/Object;)V)
    0020 invokestatic Method(InputKt.SMALL:()LSize;)
    0023 getstatic Field(java/lang/System.out:Ljava/io/PrintStream;)
    0026 swap
    0027 invokevirtual Method(java/io/PrintStream.println:(Ljava/lang/Object;)V)
    0030 invokestatic Method(InputKt.LARGE:()LSize;)
    0033 getstatic Field(java/lang/System.out:Ljava/io/PrintStream;)
    0036 swap
    0037 invokevirtual Method(java/io/PrintStream.println:(Ljava/lang/Object;)V)
    0040 return
method        main ([Ljava/lang/String;)V 0x1009
  code        max_stack=0 max_locals=1
    0000 invokestatic Method(InputKt.main:()V)
    0003 return
