class_version major=61 minor=0
this_class    Square
super_class   Shape
access_flags  0x0021
field         side : I 0x0001
method        <init> (I)V 0x0001
  code        max_stack=2 max_locals=2
    0000 aload_0
    0001 ldc "Square"
    0003 invokespecial Method(Shape.<init>:(Ljava/lang/String;)V)
    0006 aload_0
    0007 iload_1
    0008 putfield Field(Square.side:I)
    0011 return
method        area ()I 0x0001
  code        max_stack=3 max_locals=3
    0000 aload_0
    0001 getfield Field(Square.side:I)
    0004 istore_1
    0005 aload_0
    0006 getfield Field(Shape.name:Ljava/lang/String;)
    0009 astore_2
    0010 iload_1
    0011 iload_1
    0012 imul
    0013 aload_0
    0014 iload_1
    0015 putfield Field(Square.side:I)
    0018 ireturn
method        getSide ()I 0x0001
  code        max_stack=1 max_locals=1
    0000 aload_0
    0001 getfield Field(Square.side:I)
    0004 ireturn
