class_version major=61 minor=0
this_class    InputKt
super_class   java/lang/Object
access_flags  0x0031
method        main ([Ljava/lang/String;)V 0x0009
  code        max_stack=3 max_locals=11
    0000 new Class(ConsoleLogger)
    0003 dup
    0004 invokespecial Method(ConsoleLogger.<init>:()V)
    0007 astore 1
    0009 aload 1
    0011 checkcast Class(ConsoleLogger)
    0014 astore 2
    0016 aload 2
    0018 checkcast Class(ConsoleLogger)
    0021 astore 3
    0023 new Class(PrefixLogger)
    0026 dup
    0027 aload 3
    0029 invokespecial Method(PrefixLogger.<init>:(LLogger;)V)
    0032 astore 4
    0034 aload 4
    0036 checkcast Class(PrefixLogger)
    0039 astore 5
    0041 ldc "hello"
    0043 astore 6
    0045 aload 5
    0047 checkcast Class(PrefixLogger)
    0050 astore 7
    0052 ldc "hello"
    0054 astore 8
    0056 aload 7
    0058 aload 8
    0060 invokevirtual Method(PrefixLogger.log:(Ljava/lang/String;)V)
    0063 aload 5
    0065 checkcast Class(PrefixLogger)
    0068 astore 9
    0070 aload 9
    0072 invokevirtual Method(PrefixLogger.level:()Ljava/lang/String;)
    0075 astore 10
    0077 getstatic Field(java/lang/System.out:Ljava/io/PrintStream;)
    0080 aload 10
    0082 invokevirtual Method(java/io/PrintStream.println:(Ljava/lang/String;)V)
    0085 return
