class_version major=61 minor=0
this_class    InputKt
super_class   java/lang/Object
access_flags  0x0031
method        main ()V 0x0019
  code        max_stack=6 max_locals=2
    0000 new Class(Complex)
    0003 dup
    0004 dconst_1
    0005 ldc2_w double(2)
    0008 invokespecial Method(Complex.<init>:(DD)V)
    0011 astore_0
    0012 new Class(Complex)
    0015 dup
    0016 ldc2_w double(3)
    0019 ldc2_w double(4)
    0022 invokespecial Method(Complex.<init>:(DD)V)
    0025 astore_1
    0026 aload_0
    0027 invokevirtual Method(Complex.show:()Ljava/lang/String;)
    0030 invokedynamic InvokeDynamic(makeConcatWithConstants:(Ljava/lang/String;)Ljava/lang/String;)
    0035 getstatic Field(java/lang/System.out:Ljava/io/PrintStream;)
    0038 swap
    0039 invokevirtual Method(java/io/PrintStream.println:(Ljava/lang/Object;)V)
    0042 aload_1
    0043 invokevirtual Method(Complex.show:()Ljava/lang/String;)
    0046 invokedynamic InvokeDynamic(makeConcatWithConstants:(Ljava/lang/String;)Ljava/lang/String;)
    0051 getstatic Field(java/lang/System.out:Ljava/io/PrintStream;)
    0054 swap
    0055 invokevirtual Method(java/io/PrintStream.println:(Ljava/lang/Object;)V)
    0058 aload_0
    0059 aload_1
    0060 invokevirtual Method(Complex.plus:(LComplex;)LComplex;)
    0063 invokevirtual Method(Complex.show:()Ljava/lang/String;)
    0066 invokedynamic InvokeDynamic(makeConcatWithConstants:(Ljava/lang/String;)Ljava/lang/String;)
    0071 getstatic Field(java/lang/System.out:Ljava/io/PrintStream;)
    0074 swap
    0075 invokevirtual Method(java/io/PrintStream.println:(Ljava/lang/Object;)V)
    0078 aload_0
    0079 aload_1
    0080 invokevirtual Method(Complex.minus:(LComplex;)LComplex;)
    0083 invokevirtual Method(Complex.show:()Ljava/lang/String;)
    0086 invokedynamic InvokeDynamic(makeConcatWithConstants:(Ljava/lang/String;)Ljava/lang/String;)
    0091 getstatic Field(java/lang/System.out:Ljava/io/PrintStream;)
    0094 swap
    0095 invokevirtual Method(java/io/PrintStream.println:(Ljava/lang/Object;)V)
    0098 aload_0
    0099 aload_1
    0100 invokevirtual Method(Complex.times:(LComplex;)LComplex;)
    0103 invokevirtual Method(Complex.show:()Ljava/lang/String;)
    0106 invokedynamic InvokeDynamic(makeConcatWithConstants:(Ljava/lang/String;)Ljava/lang/String;)
    0111 getstatic Field(java/lang/System.out:Ljava/io/PrintStream;)
    0114 swap
    0115 invokevirtual Method(java/io/PrintStream.println:(Ljava/lang/Object;)V)
    0118 aload_0
    0119 invokevirtual Method(Complex.magnitudeSquared:()D)
    0122 invokedynamic InvokeDynamic(makeConcatWithConstants:(D)Ljava/lang/String;)
    0127 getstatic Field(java/lang/System.out:Ljava/io/PrintStream;)
    0130 swap
    0131 invokevirtual Method(java/io/PrintStream.println:(Ljava/lang/Object;)V)
    0134 ldc "---"
    0136 getstatic Field(java/lang/System.out:Ljava/io/PrintStream;)
    0139 swap
    0140 invokevirtual Method(java/io/PrintStream.println:(Ljava/lang/Object;)V)
    0143 bipush 60
    0145 bipush 20
    0147 bipush 50
    0149 invokestatic Method(InputKt.renderViaComplex:(III)Ljava/lang/String;)
    0152 getstatic Field(java/lang/System.out:Ljava/io/PrintStream;)
    0155 swap
    0156 invokevirtual Method(java/io/PrintStream.print:(Ljava/lang/Object;)V)
    0159 return
method        main ([Ljava/lang/String;)V 0x1009
  code        max_stack=0 max_locals=1
    0000 invokestatic Method(InputKt.main:()V)
    0003 return
method        mandelbrotEscape (LComplex;I)I 0x0019
  code        max_stack=6 max_locals=6
    0000 aload_0
    0001 ldc "c"
    0003 invokestatic Method(kotlin/jvm/internal/Intrinsics.checkNotNullParameter:(Ljava/lang/Object;Ljava/lang/String;)V)
    0006 new Class(Complex)
    0009 dup
    0010 dconst_0
    0011 dconst_0
    0012 invokespecial Method(Complex.<init>:(DD)V)
    0015 astore_2
    0016 iconst_0
    0017 istore_3
    0018 iload_3
    0019 iload_1
    0020 if_icmpge 27
    0023 iconst_1
    0024 goto 28
    0027 iconst_0
    0028 istore 4
    0030 iconst_0
    0031 istore 5
    0033 iload 4
    0035 ifeq 77
    0038 goto 59
    0041 aload_2
    0042 aload_2
    0043 invokevirtual Method(Complex.times:(LComplex;)LComplex;)
    0046 aload_0
    0047 invokevirtual Method(Complex.plus:(LComplex;)LComplex;)
    0050 astore_2
    0051 iinc 3 1
    0054 goto 18
    0057 iload_3
    0058 ireturn
    0059 aload_2
    0060 invokevirtual Method(Complex.magnitudeSquared:()D)
    0063 ldc2_w double(4)
    0066 dcmpg
    0067 ifge 74
    0070 iconst_1
    0071 goto 75
    0074 iconst_0
    0075 istore 5
    0077 iload 5
    0079 ifeq 57
    0082 goto 41
    sub_attr  StackMapTable (23 bytes)
  attr        RuntimeInvisibleParameterAnnotations (9 bytes)
method        renderViaComplex (III)Ljava/lang/String; 0x0019
  code        max_stack=6 max_locals=27
    0000 new Class(java/lang/StringBuilder)
    0003 dup
    0004 invokespecial Method(java/lang/StringBuilder.<init>:()V)
    0007 astore_3
    0008 iconst_0
    0009 istore 4
    0011 iload 4
    0013 iload_1
    0014 if_icmpge 23
    0017 iconst_0
    0018 istore 5
    0020 goto 34
    0023 aload_3
    0024 invokevirtual Method(java/lang/StringBuilder.toString:()Ljava/lang/String;)
    0027 dup
    0028 ldc "toString(...)"
    0030 invokestatic Method(kotlin/jvm/internal/Intrinsics.checkNotNullExpressionValue:(Ljava/lang/Object;Ljava/lang/String;)V)
    0033 areturn
    0034 iload 5
    0036 iload_0
    0037 if_icmpge 138
    0040 iload 5
    0042 i2d
    0043 dstore 6
    0045 ldc2_w double(3.5)
    0048 dload 6
    0050 dmul
    0051 dstore 8
    0053 iload_0
    0054 i2d
    0055 dstore 10
    0057 dload 8
    0059 dload 10
    0061 ddiv
    0062 dstore 12
    0064 ldc2_w double(-2.5)
    0067 dload 12
    0069 dadd
    0070 dstore 14
    0072 iload 4
    0074 i2d
    0075 dstore 16
    0077 ldc2_w double(2)
    0080 dload 16
    0082 dmul
    0083 dstore 18
    0085 iload_1
    0086 i2d
    0087 dstore 20
    0089 dload 18
    0091 dload 20
    0093 ddiv
    0094 dstore 22
    0096 ldc2_w double(-1)
    0099 dload 22
    0101 dadd
    0102 dstore 24
    0104 new Class(Complex)
    0107 dup
    0108 dload 14
    0110 dload 24
    0112 invokespecial Method(Complex.<init>:(DD)V)
    0115 iload_2
    0116 invokestatic Method(InputKt.mandelbrotEscape:(LComplex;I)I)
    0119 istore 26
    0121 aload_3
    0122 iload 26
    0124 iload_2
    0125 invokestatic Method(InputKt.shadeFor:(II)C)
    0128 invokevirtual Method(java/lang/StringBuilder.append:(C)Ljava/lang/StringBuilder;)
    0131 pop
    0132 iinc 5 1
    0135 goto 34
    0138 aload_3
    0139 bipush 10
    0141 invokevirtual Method(java/lang/StringBuilder.append:(C)Ljava/lang/StringBuilder;)
    0144 pop
    0145 iinc 4 1
    0148 goto 11
    sub_attr  StackMapTable (17 bytes)
  attr        RuntimeInvisibleAnnotations (6 bytes)
method        shadeFor (II)C 0x0019
  code        max_stack=2 max_locals=2
    0000 iload_0
    0001 iload_1
    0002 if_icmplt 8
    0005 bipush 35
    0007 ireturn
    0008 iload_0
    0009 iconst_2
    0010 imul
    0011 iload_1
    0012 if_icmplt 18
    0015 bipush 42
    0017 ireturn
    0018 iload_0
    0019 iconst_4
    0020 imul
    0021 iload_1
    0022 if_icmplt 28
    0025 bipush 43
    0027 ireturn
    0028 iload_0
    0029 bipush 8
    0031 imul
    0032 iload_1
    0033 if_icmplt 39
    0036 bipush 46
    0038 ireturn
    0039 bipush 32
    0041 ireturn
    sub_attr  StackMapTable (6 bytes)
class_attr    BootstrapMethods (38 bytes)
