class_version major=61 minor=0
this_class    InputKt
super_class   java/lang/Object
access_flags  0x0031
method        main ()V 0x0019
  code        max_stack=5 max_locals=20
    0000 ldc "HOME"
    0002 astore_0
    0003 aload_0
    0004 invokestatic Method(java/lang/System.getenv:(Ljava/lang/String;)Ljava/lang/String;)
    0007 astore_1
    0008 aload_1
    0009 astore_2
    0010 aload_2
    0011 astore_3
    0012 aconst_null
    0013 astore 4
    0015 aload_3
    0016 aload 4
    0018 invokevirtual Method(java/lang/String.equals:(Ljava/lang/Object;)Z)
    0021 iconst_1
    0022 op_0x5F
    0023 isub
    0024 istore 5
    0026 getstatic Field(java/lang/System.out:Ljava/io/PrintStream;)
    0029 iload 5
    0031 invokevirtual Method(java/io/PrintStream.println:(Z)V)
    0034 invokestatic Method(java/lang/System.currentTimeMillis:()J)
    0037 op_0x37
    0038 iconst_3
    0039 op_0x16
    0040 iconst_3
    0041 op_0x37
    0042 iconst_5
    0043 op_0x16
    0044 iconst_5
    0045 op_0x37
    0046 op_0x0A
    0047 iconst_0
    0048 istore 12
    0050 iload 12
    0052 op_0x85
    0053 op_0x37
    0054 op_0x0D
    0055 op_0x16
    0056 op_0x0A
    0057 op_0x16
    0058 op_0x0D
    0059 op_0x94
    0060 op_0x9D
    0061 nop
    0062 iconst_4
    0063 iconst_0
    0064 goto 68
    0067 iconst_1
    0068 istore 15
    0070 getstatic Field(java/lang/System.out:Ljava/io/PrintStream;)
    0073 iload 15
    0075 invokevirtual Method(java/io/PrintStream.println:(Z)V)
    0078 invokestatic Method(java/lang/System.lineSeparator:()Ljava/lang/String;)
    0081 astore 16
    0083 aload 16
    0085 invokevirtual Method(java/lang/String.length:()I)
    0088 istore 17
    0090 iconst_0
    0091 istore 18
    0093 iload 17
    0095 iload 18
    0097 op_0xA3
    0098 nop
    0099 iconst_4
    0100 iconst_0
    0101 goto 105
    0104 iconst_1
    0105 istore 19
    0107 getstatic Field(java/lang/System.out:Ljava/io/PrintStream;)
    0110 iload 19
    0112 invokevirtual Method(java/io/PrintStream.println:(Z)V)
    0115 return
    sub_attr  StackMapTable (128 bytes)
method        main ([Ljava/lang/String;)V 0x1009
  code        max_stack=0 max_locals=1
    0000 invokestatic Method(InputKt.main:()V)
    0003 return
