class_version major=61 minor=0
this_class    InputKt
super_class   java/lang/Object
access_flags  0x0031
method        AUTUMN ()LSeason; 0x0019
  code        max_stack=3 max_locals=0
    0000 new Class(Season)
    0003 dup
    0004 ldc "AUTUMN"
    0006 invokespecial Method(Season.<init>:(Ljava/lang/String;)V)
    0009 areturn
  attr        RuntimeInvisibleAnnotations (6 bytes)
method        SPRING ()LSeason; 0x0019
  code        max_stack=3 max_locals=0
    0000 new Class(Season)
    0003 dup
    0004 ldc "SPRING"
    0006 invokespecial Method(Season.<init>:(Ljava/lang/String;)V)
    0009 areturn
  attr        RuntimeInvisibleAnnotations (6 bytes)
method        SUMMER ()LSeason; 0x0019
  code        max_stack=3 max_locals=0
    0000 new Class(Season)
    0003 dup
    0004 ldc "SUMMER"
    0006 invokespecial Method(Season.<init>:(Ljava/lang/String;)V)
    0009 areturn
  attr        RuntimeInvisibleAnnotations (6 bytes)
method        Season$valueOf (Ljava/lang/String;)LSeason; 0x0019
  code        max_stack=2 max_locals=10
    0000 aload_0
    0001 ldc "name"
    0003 invokestatic Method(kotlin/jvm/internal/Intrinsics.checkNotNullParameter:(Ljava/lang/Object;Ljava/lang/String;)V)
    0006 aload_0
    0007 ldc "SPRING"
    0009 invokestatic Method(kotlin/jvm/internal/Intrinsics.areEqual:(Ljava/lang/Object;Ljava/lang/Object;)Z)
    0012 istore_1
    0013 iload_1
    0014 ifeq 66
    0017 goto 87
    0020 invokestatic Method(InputKt.SPRING:()LSeason;)
    0023 astore_2
    0024 aload_2
    0025 areturn
    0026 aload_0
    0027 ldc "WINTER"
    0029 invokestatic Method(kotlin/jvm/internal/Intrinsics.areEqual:(Ljava/lang/Object;Ljava/lang/Object;)Z)
    0032 istore_3
    0033 iload_3
    0034 ifeq 20
    0037 invokestatic Method(InputKt.WINTER:()LSeason;)
    0040 astore 4
    0042 aload 4
    0044 areturn
    0045 aload_0
    0046 ldc "AUTUMN"
    0048 invokestatic Method(kotlin/jvm/internal/Intrinsics.areEqual:(Ljava/lang/Object;Ljava/lang/Object;)Z)
    0051 istore 5
    0053 iload 5
    0055 ifeq 26
    0058 invokestatic Method(InputKt.AUTUMN:()LSeason;)
    0061 astore 6
    0063 aload 6
    0065 areturn
    0066 aload_0
    0067 ldc "SUMMER"
    0069 invokestatic Method(kotlin/jvm/internal/Intrinsics.areEqual:(Ljava/lang/Object;Ljava/lang/Object;)Z)
    0072 istore 7
    0074 iload 7
    0076 ifeq 45
    0079 invokestatic Method(InputKt.SUMMER:()LSeason;)
    0082 astore 8
    0084 aload 8
    0086 areturn
    0087 invokestatic Method(InputKt.SPRING:()LSeason;)
    0090 astore 9
    0092 aload 9
    0094 areturn
    sub_attr  StackMapTable (65 bytes)
  attr        RuntimeInvisibleAnnotations (6 bytes)
  attr        RuntimeInvisibleParameterAnnotations (7 bytes)
method        Season$values ()Ljava/util/ArrayList; 0x0019
  code        max_stack=2 max_locals=1
    0000 new Class(java/util/ArrayList)
    0003 dup
    0004 invokespecial Method(java/util/ArrayList.<init>:()V)
    0007 astore_0
    0008 invokestatic Method(InputKt.SPRING:()LSeason;)
    0011 aload_0
    0012 swap
    0013 invokevirtual Method(java/util/ArrayList.add:(Ljava/lang/Object;)Z)
    0016 pop
    0017 invokestatic Method(InputKt.SUMMER:()LSeason;)
    0020 aload_0
    0021 swap
    0022 invokevirtual Method(java/util/ArrayList.add:(Ljava/lang/Object;)Z)
    0025 pop
    0026 invokestatic Method(InputKt.AUTUMN:()LSeason;)
    0029 aload_0
    0030 swap
    0031 invokevirtual Method(java/util/ArrayList.add:(Ljava/lang/Object;)Z)
    0034 pop
    0035 invokestatic Method(InputKt.WINTER:()LSeason;)
    0038 aload_0
    0039 swap
    0040 invokevirtual Method(java/util/ArrayList.add:(Ljava/lang/Object;)Z)
    0043 pop
    0044 aload_0
    0045 areturn
  attr        RuntimeInvisibleAnnotations (6 bytes)
method        WINTER ()LSeason; 0x0019
  code        max_stack=3 max_locals=0
    0000 new Class(Season)
    0003 dup
    0004 ldc "WINTER"
    0006 invokespecial Method(Season.<init>:(Ljava/lang/String;)V)
    0009 areturn
  attr        RuntimeInvisibleAnnotations (6 bytes)
method        describe (Ljava/lang/String;)Ljava/lang/String; 0x0019
  code        max_stack=2 max_locals=11
    0000 aload_0
    0001 ldc "s"
    0003 invokestatic Method(kotlin/jvm/internal/Intrinsics.checkNotNullParameter:(Ljava/lang/Object;Ljava/lang/String;)V)
<<<<<<< Updated upstream
    0006 aload_0
    0007 ldc "SPRING"
    0009 invokestatic Method(kotlin/jvm/internal/Intrinsics.areEqual:(Ljava/lang/Object;Ljava/lang/Object;)Z)
    0012 istore_1
    0013 iload_1
    0014 ifeq 25
    0017 ldc "flowers bloom"
    0019 astore_2
    0020 aload_2
    0021 astore_3
    0022 goto 101
    0025 aload_0
    0026 ldc "SUMMER"
    0028 invokestatic Method(kotlin/jvm/internal/Intrinsics.areEqual:(Ljava/lang/Object;Ljava/lang/Object;)Z)
    0031 istore 4
    0033 iload 4
    0035 ifeq 48
    0038 ldc "sun shines"
    0040 astore 5
    0042 aload 5
    0044 astore_3
    0045 goto 101
    0048 aload_0
    0049 ldc "AUTUMN"
    0051 invokestatic Method(kotlin/jvm/internal/Intrinsics.areEqual:(Ljava/lang/Object;Ljava/lang/Object;)Z)
    0054 istore 6
    0056 iload 6
    0058 ifeq 71
    0061 ldc "leaves fall"
    0063 astore 7
    0065 aload 7
    0067 astore_3
    0068 goto 101
    0071 aload_0
    0072 ldc "WINTER"
    0074 invokestatic Method(kotlin/jvm/internal/Intrinsics.areEqual:(Ljava/lang/Object;Ljava/lang/Object;)Z)
    0077 istore 8
    0079 iload 8
    0081 ifeq 94
    0084 ldc "snow falls"
    0086 astore 9
    0088 aload 9
    0090 astore_3
    0091 goto 101
    0094 ldc "unknown"
    0096 astore 10
    0098 aload 10
    0100 astore_3
    0101 aload_3
    0102 areturn
    sub_attr  StackMapTable (37 bytes)
=======
    0006 ldc "SPRING"
    0008 astore_1
    0009 aload_0
    0010 aload_1
    0011 invokestatic Method(kotlin/jvm/internal/Intrinsics.areEqual:(Ljava/lang/Object;Ljava/lang/Object;)Z)
    0014 istore_2
    0015 iload_2
    0016 ifeq 28
    0019 ldc "flowers bloom"
    0021 astore_3
    0022 aload_3
    0023 astore 4
    0025 goto 120
    0028 ldc "SUMMER"
    0030 astore 5
    0032 aload_0
    0033 aload 5
    0035 invokestatic Method(kotlin/jvm/internal/Intrinsics.areEqual:(Ljava/lang/Object;Ljava/lang/Object;)Z)
    0038 istore 6
    0040 iload 6
    0042 ifeq 56
    0045 ldc "sun shines"
    0047 astore 7
    0049 aload 7
    0051 astore 4
    0053 goto 120
    0056 ldc "AUTUMN"
    0058 astore 8
    0060 aload_0
    0061 aload 8
    0063 invokestatic Method(kotlin/jvm/internal/Intrinsics.areEqual:(Ljava/lang/Object;Ljava/lang/Object;)Z)
    0066 istore 9
    0068 iload 9
    0070 ifeq 84
    0073 ldc "leaves fall"
    0075 astore 10
    0077 aload 10
    0079 astore 4
    0081 goto 120
    0084 ldc "WINTER"
    0086 astore 11
    0088 aload_0
    0089 aload 11
    0091 invokestatic Method(kotlin/jvm/internal/Intrinsics.areEqual:(Ljava/lang/Object;Ljava/lang/Object;)Z)
    0094 istore 12
    0096 iload 12
    0098 ifeq 112
    0101 ldc "snow falls"
    0103 astore 13
    0105 aload 13
    0107 astore 4
    0109 goto 120
    0112 ldc "unknown"
    0114 astore 14
    0116 aload 14
    0118 astore 4
    0120 aload 4
    0122 areturn
    sub_attr  StackMapTable (63 bytes)
>>>>>>> Stashed changes
  attr        RuntimeInvisibleAnnotations (6 bytes)
  attr        RuntimeInvisibleParameterAnnotations (7 bytes)
method        main ()V 0x0019
  code        max_stack=2 max_locals=0
    0000 invokestatic Method(InputKt.SPRING:()LSeason;)
    0003 invokestatic Method(InputKt.describe:(Ljava/lang/String;)Ljava/lang/String;)
    0006 getstatic Field(java/lang/System.out:Ljava/io/PrintStream;)
    0009 swap
    0010 invokevirtual Method(java/io/PrintStream.println:(Ljava/lang/Object;)V)
    0013 invokestatic Method(InputKt.WINTER:()LSeason;)
    0016 invokestatic Method(InputKt.describe:(Ljava/lang/String;)Ljava/lang/String;)
    0019 getstatic Field(java/lang/System.out:Ljava/io/PrintStream;)
    0022 swap
    0023 invokevirtual Method(java/io/PrintStream.println:(Ljava/lang/Object;)V)
    0026 return
method        main ([Ljava/lang/String;)V 0x1009
  code        max_stack=0 max_locals=1
    0000 invokestatic Method(InputKt.main:()V)
    0003 return
