class_version major=61 minor=0
this_class    InputKt
super_class   java/lang/Object
access_flags  0x0031
method        identity (Ljava/lang/Object;)Ljava/lang/Object; 0x0019
  code        max_stack=2 max_locals=1
    0000 aload_0
    0001 ldc "x"
    0003 invokestatic Method(kotlin/jvm/internal/Intrinsics.checkNotNullParameter:(Ljava/lang/Object;Ljava/lang/String;)V)
    0006 aload_0
    0007 areturn
  attr        RuntimeInvisibleParameterAnnotations (7 bytes)
method        main ()V 0x0019
  code        max_stack=2 max_locals=1
    0000 bipush 42
    0002 invokestatic Method(java/lang/Integer.valueOf:(I)Ljava/lang/Integer;)
    0005 invokestatic Method(InputKt.identity:(Ljava/lang/Object;)Ljava/lang/Object;)
    0008 getstatic Field(java/lang/System.out:Ljava/io/PrintStream;)
    0011 swap
    0012 invokevirtual Method(java/io/PrintStream.println:(Ljava/lang/Object;)V)
    0015 ldc "hello"
    0017 invokestatic Method(InputKt.identity:(Ljava/lang/Object;)Ljava/lang/Object;)
    0020 getstatic Field(java/lang/System.out:Ljava/io/PrintStream;)
    0023 swap
    0024 invokevirtual Method(java/io/PrintStream.println:(Ljava/lang/Object;)V)
    0027 iconst_1
    0028 invokestatic Method(java/lang/Integer.valueOf:(I)Ljava/lang/Integer;)
    0031 astore_0
    0032 iconst_2
    0033 invokestatic Method(java/lang/Integer.valueOf:(I)Ljava/lang/Integer;)
    0036 aload_0
    0037 swap
    0038 invokestatic Method(InputKt.pair:(Ljava/lang/Object;Ljava/lang/Object;)Ljava/lang/String;)
    0041 getstatic Field(java/lang/System.out:Ljava/io/PrintStream;)
    0044 swap
    0045 invokevirtual Method(java/io/PrintStream.println:(Ljava/lang/Object;)V)
    0048 return
method        main ([Ljava/lang/String;)V 0x1009
  code        max_stack=0 max_locals=1
    0000 invokestatic Method(InputKt.main:()V)
    0003 return
method        pair (Ljava/lang/Object;Ljava/lang/Object;)Ljava/lang/String; 0x0019
  code        max_stack=2 max_locals=2
    0000 aload_0
    0001 ldc "a"
    0003 invokestatic Method(kotlin/jvm/internal/Intrinsics.checkNotNullParameter:(Ljava/lang/Object;Ljava/lang/String;)V)
    0006 aload_1
    0007 ldc "b"
    0009 invokestatic Method(kotlin/jvm/internal/Intrinsics.checkNotNullParameter:(Ljava/lang/Object;Ljava/lang/String;)V)
    0012 aload_0
    0013 invokestatic Method(java/lang/String.valueOf:(Ljava/lang/Object;)Ljava/lang/String;)
    0016 ldc " and "
    0018 invokevirtual Method(java/lang/String.concat:(Ljava/lang/String;)Ljava/lang/String;)
    0021 aload_1
    0022 invokestatic Method(java/lang/String.valueOf:(Ljava/lang/Object;)Ljava/lang/String;)
    0025 invokevirtual Method(java/lang/String.concat:(Ljava/lang/String;)Ljava/lang/String;)
    0028 areturn
  attr        RuntimeInvisibleAnnotations (6 bytes)
  attr        RuntimeInvisibleParameterAnnotations (13 bytes)
