class_version major=61 minor=0
this_class    Cat
super_class   Animal
access_flags  0x0021
method        <init> (Ljava/lang/String;)V 0x0001
  code        max_stack=2 max_locals=2
    0000 aload_0
    0001 aload_1
    0002 invokespecial Method(Animal.<init>:(Ljava/lang/String;)V)
    0005 aload_0
    0006 aload_1
    0007 putfield Field(Cat.name:Ljava/lang/String;)
    0010 return
method        sound ()Ljava/lang/String; 0x0001
  code        max_stack=1 max_locals=2
    0000 aload_0
    0001 getfield Field(Animal.name:Ljava/lang/String;)
    0004 astore_1
    0005 ldc "Meow"
    0007 areturn
  attr        RuntimeInvisibleAnnotations (6 bytes)
