class_version major=61 minor=0
this_class    Derived
super_class   java/lang/Object
access_flags  0x0021
interfaces    [Base]
field         b : LBase; 0x0001
method        <init> (LBase;)V 0x0001
  code        max_stack=2 max_locals=2
    0000 aload_0
    0001 invokespecial Method(java/lang/Object.<init>:()V)
    0004 aload_0
    0005 aload_1
    0006 putfield Field(Derived.b:LBase;)
    0009 return
method        print ()V 0x0001
  code        max_stack=1 max_locals=1
    0000 aload_0
    0001 getfield Field(Derived.b:LBase;)
    0004 invokeinterface InterfaceMethod(Base.print:()V)
    0009 return
