class_version major=61 minor=0
this_class    InputKt
super_class   java/lang/Object
access_flags  0x0031
method        Texts (Ljava/lang/String;Ljava/lang/String;Ljava/lang/String;Ljava/lang/String;Landroidx/compose/runtime/Composer;I)V 0x0019
  code        max_stack=2 max_locals=7
    0000 aload_0
    0001 ldc "a"
    0003 invokestatic Method(kotlin/jvm/internal/Intrinsics.checkNotNullParameter:(Ljava/lang/Object;Ljava/lang/String;)V)
    0006 aload_1
    0007 ldc "b"
    0009 invokestatic Method(kotlin/jvm/internal/Intrinsics.checkNotNullParameter:(Ljava/lang/Object;Ljava/lang/String;)V)
    0012 aload_2
    0013 ldc "c"
    0015 invokestatic Method(kotlin/jvm/internal/Intrinsics.checkNotNullParameter:(Ljava/lang/Object;Ljava/lang/String;)V)
    0018 aload_3
    0019 ldc "d"
    0021 invokestatic Method(kotlin/jvm/internal/Intrinsics.checkNotNullParameter:(Ljava/lang/Object;Ljava/lang/String;)V)
    0024 iconst_0
    0025 istore 6
    0027 return
  attr        RuntimeInvisibleAnnotations (6 bytes)
  attr        RuntimeInvisibleParameterAnnotations (33 bytes)
