class_version major=61 minor=0
this_class    InputKt
super_class   java/lang/Object
access_flags  0x0031
method        Coin$valueOf (Ljava/lang/String;)LCoin; 0x0019
  code        max_stack=5 max_locals=14
    0000 aload_0
    0001 ldc "name"
    0003 invokestatic Method(kotlin/jvm/internal/Intrinsics.checkNotNullParameter:(Ljava/lang/Object;Ljava/lang/String;)V)
    0006 ldc "PENNY"
    0008 astore_1
    0009 aload_0
    0010 aload_1
    0011 invokevirtual Method(java/lang/String.equals:(Ljava/lang/Object;)Z)
    0014 istore_2
    0015 iload_2
    0016 ifeq 78
    0019 goto 103
    0022 invokestatic Method(InputKt.PENNY:()LCoin;)
    0025 astore_3
    0026 aload_3
    0027 areturn
    0028 ldc "QUARTER"
    0030 astore 4
    0032 aload_0
    0033 aload 4
    0035 invokevirtual Method(java/lang/String.equals:(Ljava/lang/Object;)Z)
    0038 istore 5
    0040 iload 5
    0042 ifeq 22
    0045 invokestatic Method(InputKt.QUARTER:()LCoin;)
    0048 astore 6
    0050 aload 6
    0052 areturn
    0053 ldc "DIME"
    0055 astore 7
    0057 aload_0
    0058 aload 7
    0060 invokevirtual Method(java/lang/String.equals:(Ljava/lang/Object;)Z)
    0063 istore 8
    0065 iload 8
    0067 ifeq 28
    0070 invokestatic Method(InputKt.DIME:()LCoin;)
    0073 astore 9
    0075 aload 9
    0077 areturn
    0078 ldc "NICKEL"
    0080 astore 10
    0082 aload_0
    0083 aload 10
    0085 invokevirtual Method(java/lang/String.equals:(Ljava/lang/Object;)Z)
    0088 istore 11
    0090 iload 11
    0092 ifeq 53
    0095 invokestatic Method(InputKt.NICKEL:()LCoin;)
    0098 astore 12
    0100 aload 12
    0102 areturn
    0103 invokestatic Method(InputKt.PENNY:()LCoin;)
    0106 astore 13
    0108 aload 13
    0110 areturn
    sub_attr  StackMapTable (98 bytes)
  attr        RuntimeInvisibleAnnotations (6 bytes)
  attr        RuntimeInvisibleParameterAnnotations (7 bytes)
method        Coin$values ()Ljava/util/ArrayList; 0x0019
  code        max_stack=2 max_locals=1
    0000 new Class(java/util/ArrayList)
    0003 dup
    0004 invokespecial Method(java/util/ArrayList.<init>:()V)
    0007 astore_0
    0008 invokestatic Method(InputKt.PENNY:()LCoin;)
    0011 aload_0
    0012 swap
    0013 invokevirtual Method(java/util/ArrayList.add:(Ljava/lang/Object;)Z)
    0016 pop
    0017 invokestatic Method(InputKt.NICKEL:()LCoin;)
    0020 aload_0
    0021 swap
    0022 invokevirtual Method(java/util/ArrayList.add:(Ljava/lang/Object;)Z)
    0025 pop
    0026 invokestatic Method(InputKt.DIME:()LCoin;)
    0029 aload_0
    0030 swap
    0031 invokevirtual Method(java/util/ArrayList.add:(Ljava/lang/Object;)Z)
    0034 pop
    0035 invokestatic Method(InputKt.QUARTER:()LCoin;)
    0038 aload_0
    0039 swap
    0040 invokevirtual Method(java/util/ArrayList.add:(Ljava/lang/Object;)Z)
    0043 pop
    0044 aload_0
    0045 areturn
  attr        RuntimeInvisibleAnnotations (6 bytes)
method        DIME ()LCoin; 0x0019
  code        max_stack=4 max_locals=0
    0000 new Class(Coin)
    0003 dup
    0004 ldc "DIME"
    0006 bipush 10
    0008 invokespecial Method(Coin.<init>:(Ljava/lang/String;I)V)
    0011 areturn
  attr        RuntimeInvisibleAnnotations (6 bytes)
method        NICKEL ()LCoin; 0x0019
  code        max_stack=4 max_locals=0
    0000 new Class(Coin)
    0003 dup
    0004 ldc "NICKEL"
    0006 iconst_5
    0007 invokespecial Method(Coin.<init>:(Ljava/lang/String;I)V)
    0010 areturn
  attr        RuntimeInvisibleAnnotations (6 bytes)
method        PENNY ()LCoin; 0x0019
  code        max_stack=4 max_locals=0
    0000 new Class(Coin)
    0003 dup
    0004 ldc "PENNY"
    0006 iconst_1
    0007 invokespecial Method(Coin.<init>:(Ljava/lang/String;I)V)
    0010 areturn
  attr        RuntimeInvisibleAnnotations (6 bytes)
method        QUARTER ()LCoin; 0x0019
  code        max_stack=4 max_locals=0
    0000 new Class(Coin)
    0003 dup
    0004 ldc "QUARTER"
    0006 bipush 25
    0008 invokespecial Method(Coin.<init>:(Ljava/lang/String;I)V)
    0011 areturn
  attr        RuntimeInvisibleAnnotations (6 bytes)
method        main ()V 0x0019
  code        max_stack=2 max_locals=1
    0000 invokestatic Method(InputKt.PENNY:()LCoin;)
    0003 invokestatic Method(InputKt.value:(LCoin;)I)
    0006 istore_0
    0007 getstatic Field(java/lang/System.out:Ljava/io/PrintStream;)
    0010 iload_0
    0011 invokevirtual Method(java/io/PrintStream.println:(I)V)
    0014 invokestatic Method(InputKt.QUARTER:()LCoin;)
    0017 invokestatic Method(InputKt.value:(LCoin;)I)
    0020 istore_0
    0021 getstatic Field(java/lang/System.out:Ljava/io/PrintStream;)
    0024 iload_0
    0025 invokevirtual Method(java/io/PrintStream.println:(I)V)
    0028 invokestatic Method(InputKt.DIME:()LCoin;)
    0031 getfield Field(Coin.cents:I)
    0034 istore_0
    0035 getstatic Field(java/lang/System.out:Ljava/io/PrintStream;)
    0038 iload_0
    0039 invokevirtual Method(java/io/PrintStream.println:(I)V)
    0042 return
method        main ([Ljava/lang/String;)V 0x1009
  code        max_stack=0 max_locals=1
    0000 invokestatic Method(InputKt.main:()V)
    0003 return
method        value (LCoin;)I 0x0019
  code        max_stack=2 max_locals=1
    0000 aload_0
    0001 ldc "c"
    0003 invokestatic Method(kotlin/jvm/internal/Intrinsics.checkNotNullParameter:(Ljava/lang/Object;Ljava/lang/String;)V)
    0006 aload_0
    0007 getfield Field(Coin.cents:I)
    0010 ireturn
  attr        RuntimeInvisibleParameterAnnotations (7 bytes)
