class_version major=61 minor=0
this_class    InputKt
super_class   java/lang/Object
access_flags  0x0031
field         GREETING : Ljava/lang/String; 0x001A
field         MAX : I 0x001A
method        <clinit> ()V 0x0008
  code        max_stack=1 max_locals=0
    0000 bipush 100
    0002 op_0xB3
    0003 nop
    0004 op_0x0A
    0005 ldc "Hello"
    0007 op_0xB3
    0008 nop
    0009 op_0x11
    0010 return
method        clamp (I)I 0x0019
  code        max_stack=2 max_locals=1
    0000 op_0x1A
    0001 getstatic Field(InputKt.MAX:I)
    0004 op_0xA4
    0005 nop
    0006 iconst_4
    0007 getstatic Field(InputKt.MAX:I)
    0010 op_0xAC
    0011 op_0x1A
    0012 op_0x9C
    0013 nop
    0014 iconst_2
    0015 iconst_0
    0016 op_0xAC
    0017 op_0x1A
    0018 op_0xAC
    sub_attr  StackMapTable (4 bytes)
method        getGREETING ()Ljava/lang/String; 0x0019
  code        max_stack=1 max_locals=0
    0000 getstatic Field(InputKt.GREETING:Ljava/lang/String;)
    0003 op_0xB0
  attr        RuntimeInvisibleAnnotations (6 bytes)
method        getMAX ()I 0x0019
  code        max_stack=1 max_locals=0
    0000 getstatic Field(InputKt.MAX:I)
    0003 op_0xAC
method        main ()V 0x0019
  code        max_stack=2 max_locals=1
    0000 getstatic Field(InputKt.GREETING:Ljava/lang/String;)
    0003 getstatic Field(java/lang/System.out:Ljava/io/PrintStream;)
    0006 op_0x5F
    0007 invokevirtual Method(java/io/PrintStream.println:(Ljava/lang/Object;)V)
    0010 bipush 50
    0012 invokestatic Method(InputKt.clamp:(I)I)
    0015 op_0x3B
    0016 getstatic Field(java/lang/System.out:Ljava/io/PrintStream;)
    0019 op_0x1A
    0020 invokevirtual Method(java/io/PrintStream.println:(I)V)
    0023 sipush 200
    0026 invokestatic Method(InputKt.clamp:(I)I)
    0029 op_0x3B
    0030 getstatic Field(java/lang/System.out:Ljava/io/PrintStream;)
    0033 op_0x1A
    0034 invokevirtual Method(java/io/PrintStream.println:(I)V)
    0037 bipush -5
    0039 invokestatic Method(InputKt.clamp:(I)I)
    0042 op_0x3B
    0043 getstatic Field(java/lang/System.out:Ljava/io/PrintStream;)
    0046 op_0x1A
    0047 invokevirtual Method(java/io/PrintStream.println:(I)V)
    0050 return
method        main ([Ljava/lang/String;)V 0x1009
  code        max_stack=0 max_locals=1
    0000 invokestatic Method(InputKt.main:()V)
    0003 return
