class_version major=61 minor=0
this_class    InputKt
super_class   java/lang/Object
access_flags  0x0031
method        grow (LShape;)LShape; 0x0019
  code        max_stack=4 max_locals=3
    0000 aload_0
    0001 ldc "s"
    0003 invokestatic Method(kotlin/jvm/internal/Intrinsics.checkNotNullParameter:(Ljava/lang/Object;Ljava/lang/String;)V)
    0006 aload_0
    0007 astore_1
    0008 aload_1
    0009 instanceof Class(Square)
    0012 ifeq 37
    0015 new Class(Square)
    0018 dup
    0019 aload_0
    0020 checkcast Class(Square)
    0023 invokevirtual Method(Square.getSide:()I)
    0026 iconst_1
    0027 iadd
    0028 invokespecial Method(Square.<init>:(I)V)
    0031 checkcast Class(Shape)
    0034 goto 111
    0037 aload_1
    0038 instanceof Class(Rect)
    0041 ifeq 83
    0044 aload_0
    0045 checkcast Class(Rect)
    0048 invokevirtual Method(Rect.getW:()I)
    0051 aload_0
    0052 checkcast Class(Rect)
    0055 invokevirtual Method(Rect.getH:()I)
    0058 iadd
    0059 istore_2
    0060 new Class(Rect)
    0063 dup
    0064 aload_0
    0065 checkcast Class(Rect)
    0068 invokevirtual Method(Rect.getW:()I)
    0071 iconst_1
    0072 iadd
    0073 iload_2
    0074 invokespecial Method(Rect.<init>:(II)V)
    0077 checkcast Class(Shape)
    0080 goto 111
    0083 aload_1
    0084 instanceof Class(Empty)
    0087 ifeq 103
    0090 new Class(Empty)
    0093 dup
    0094 invokespecial Method(Empty.<init>:()V)
    0097 checkcast Class(Shape)
    0100 goto 111
    0103 new Class(kotlin/NoWhenBranchMatchedException)
    0106 dup
    0107 invokespecial Method(kotlin/NoWhenBranchMatchedException.<init>:()V)
    0110 athrow
    0111 areturn
    sub_attr  StackMapTable (14 bytes)
  attr        RuntimeInvisibleAnnotations (6 bytes)
  attr        RuntimeInvisibleParameterAnnotations (7 bytes)
method        main ()V 0x0019
  code        max_stack=4 max_locals=2
    0000 new Class(Square)
    0003 dup
    0004 iconst_2
    0005 invokespecial Method(Square.<init>:(I)V)
    0008 checkcast Class(Shape)
    0011 astore_0
    0012 aload_0
    0013 invokestatic Method(InputKt.grow:(LShape;)LShape;)
    0016 astore_0
    0017 aload_0
    0018 invokeinterface InterfaceMethod(Shape.area:()I)
    0023 istore_1
    0024 getstatic Field(java/lang/System.out:Ljava/io/PrintStream;)
    0027 iload_1
    0028 invokevirtual Method(java/io/PrintStream.println:(I)V)
    0031 new Class(Rect)
    0034 dup
    0035 iconst_3
    0036 iconst_4
    0037 invokespecial Method(Rect.<init>:(II)V)
    0040 checkcast Class(Shape)
    0043 astore_0
    0044 aload_0
    0045 invokestatic Method(InputKt.grow:(LShape;)LShape;)
    0048 astore_0
    0049 aload_0
    0050 invokeinterface InterfaceMethod(Shape.area:()I)
    0055 istore_1
    0056 getstatic Field(java/lang/System.out:Ljava/io/PrintStream;)
    0059 iload_1
    0060 invokevirtual Method(java/io/PrintStream.println:(I)V)
    0063 new Class(Empty)
    0066 dup
    0067 invokespecial Method(Empty.<init>:()V)
    0070 checkcast Class(Shape)
    0073 astore_0
    0074 aload_0
    0075 invokestatic Method(InputKt.grow:(LShape;)LShape;)
    0078 astore_0
    0079 aload_0
    0080 invokeinterface InterfaceMethod(Shape.area:()I)
    0085 istore_1
    0086 getstatic Field(java/lang/System.out:Ljava/io/PrintStream;)
    0089 iload_1
    0090 invokevirtual Method(java/io/PrintStream.println:(I)V)
    0093 return
method        main ([Ljava/lang/String;)V 0x1009
  code        max_stack=0 max_locals=1
    0000 invokestatic Method(InputKt.main:()V)
    0003 return
