class_version major=61 minor=0
this_class    InputKt
super_class   java/lang/Object
access_flags  0x0031
method        grow (LShape;)LShape; 0x0019
  code        max_stack=4 max_locals=9
    0000 aload_0
    0001 ldc "s"
    0003 invokestatic Method(kotlin/jvm/internal/Intrinsics.checkNotNullParameter:(Ljava/lang/Object;Ljava/lang/String;)V)
    0006 aload_0
    0007 astore_1
    0008 aload_1
    0009 instanceof Class(Square)
    0012 ifeq 37
    0015 aload_0
    0016 checkcast Class(Square)
    0019 invokevirtual Method(Square.getSide:()I)
    0022 iconst_1
    0023 iadd
    0024 istore_2
    0025 new Class(Square)
    0028 dup
    0029 iload_2
    0030 invokespecial Method(Square.<init>:(I)V)
    0033 astore_3
    0034 goto 116
    0037 aload_1
    0038 instanceof Class(Rect)
    0041 ifeq 96
    0044 aload_0
    0045 checkcast Class(Rect)
    0048 astore 4
    0050 aload 4
    0052 invokevirtual Method(Rect.getW:()I)
    0055 istore 5
    0057 aload 4
    0059 invokevirtual Method(Rect.getH:()I)
    0062 iload 5
    0064 swap
    0065 iadd
    0066 istore 6
    0068 aload 4
    0070 invokevirtual Method(Rect.getW:()I)
    0073 iconst_1
    0074 iadd
    0075 istore 7
    0077 new Class(Rect)
    0080 dup
    0081 iload 7
    0083 iload 6
    0085 invokespecial Method(Rect.<init>:(II)V)
    0088 astore 8
    0090 aload 8
    0092 astore_3
    0093 aload 8
    0095 areturn
    0096 aload_1
    0097 instanceof Class(Empty)
    0100 ifeq 114
    0103 new Class(Empty)
    0106 dup
    0107 invokespecial Method(Empty.<init>:()V)
    0110 astore_3
    0111 goto 116
    0114 aconst_null
    0115 astore_3
    0116 aload_3
    0117 checkcast Class(Shape)
    0120 areturn
    sub_attr  StackMapTable (17 bytes)
  attr        RuntimeInvisibleAnnotations (6 bytes)
  attr        RuntimeInvisibleParameterAnnotations (7 bytes)
method        main ()V 0x0019
  code        max_stack=4 max_locals=2
    0000 new Class(Square)
    0003 dup
    0004 iconst_2
    0005 invokespecial Method(Square.<init>:(I)V)
    0008 checkcast Class(Shape)
    0011 astore_0
    0012 aload_0
    0013 invokestatic Method(InputKt.grow:(LShape;)LShape;)
    0016 astore_0
    0017 aload_0
    0018 invokeinterface InterfaceMethod(Shape.area:()I)
    0023 istore_1
    0024 getstatic Field(java/lang/System.out:Ljava/io/PrintStream;)
    0027 iload_1
    0028 invokevirtual Method(java/io/PrintStream.println:(I)V)
    0031 new Class(Rect)
    0034 dup
    0035 iconst_3
    0036 iconst_4
    0037 invokespecial Method(Rect.<init>:(II)V)
    0040 checkcast Class(Shape)
    0043 astore_0
    0044 aload_0
    0045 invokestatic Method(InputKt.grow:(LShape;)LShape;)
    0048 astore_0
    0049 aload_0
    0050 invokeinterface InterfaceMethod(Shape.area:()I)
    0055 istore_1
    0056 getstatic Field(java/lang/System.out:Ljava/io/PrintStream;)
    0059 iload_1
    0060 invokevirtual Method(java/io/PrintStream.println:(I)V)
    0063 new Class(Empty)
    0066 dup
    0067 invokespecial Method(Empty.<init>:()V)
    0070 checkcast Class(Shape)
    0073 astore_0
    0074 aload_0
    0075 invokestatic Method(InputKt.grow:(LShape;)LShape;)
    0078 astore_0
    0079 aload_0
    0080 invokeinterface InterfaceMethod(Shape.area:()I)
    0085 istore_1
    0086 getstatic Field(java/lang/System.out:Ljava/io/PrintStream;)
    0089 iload_1
    0090 invokevirtual Method(java/io/PrintStream.println:(I)V)
    0093 return
method        main ([Ljava/lang/String;)V 0x1009
  code        max_stack=0 max_locals=1
    0000 invokestatic Method(InputKt.main:()V)
    0003 return
