--- ./gradle/com.example.compose.jetchat.profile.ProfileViewModel.javap	2026-05-24 23:07:52
+++ ./skotch/com.example.compose.jetchat.profile.ProfileViewModel.javap	2026-05-24 23:07:52
@@ -1,76 +1,112 @@
-Compiled from "ProfileViewModel.kt"
+Compiled from "com/example/compose/jetchat/profile/ProfileViewModel.kt"
 public final class com.example.compose.jetchat.profile.ProfileViewModel extends androidx.lifecycle.ViewModel {
-  private java.lang.String userId;
+  public java.lang.String userId;
 
-  private final androidx.lifecycle.MutableLiveData<com.example.compose.jetchat.profile.ProfileScreenState> _userData;
+  public androidx.lifecycle.MutableLiveData _userData;
 
-  private final androidx.lifecycle.LiveData<com.example.compose.jetchat.profile.ProfileScreenState> userData;
+  public androidx.lifecycle.LiveData userData;
 
   public static final int $stable;
 
   public com.example.compose.jetchat.profile.ProfileViewModel();
     Code:
          0: aload_0
-         1: invokespecial #8                  // Method androidx/lifecycle/ViewModel."<init>":()V
-         4: aload_0
-         5: ldc           #10                 // String
-         7: putfield      #14                 // Field userId:Ljava/lang/String;
-        10: aload_0
-        11: new           #16                 // class androidx/lifecycle/MutableLiveData
+         1: invokespecial #19                 // Method androidx/lifecycle/ViewModel."<init>":()V
+         4: ldc           #21                 // String
+         6: aload_0
+         7: swap
+         8: putfield      #23                 // Field userId:Ljava/lang/String;
+        11: new           #25                 // class androidx/lifecycle/MutableLiveData
         14: dup
-        15: invokespecial #17                 // Method androidx/lifecycle/MutableLiveData."<init>":()V
-        18: putfield      #21                 // Field _userData:Landroidx/lifecycle/MutableLiveData;
-        21: aload_0
-        22: aload_0
-        23: getfield      #21                 // Field _userData:Landroidx/lifecycle/MutableLiveData;
-        26: checkcast     #23                 // class androidx/lifecycle/LiveData
-        29: putfield      #27                 // Field userData:Landroidx/lifecycle/LiveData;
-        32: return
+        15: invokespecial #26                 // Method androidx/lifecycle/MutableLiveData."<init>":()V
+        18: aload_0
+        19: swap
+        20: putfield      #28                 // Field _userData:Landroidx/lifecycle/MutableLiveData;
+        23: aconst_null
+        24: aload_0
+        25: swap
+        26: putfield      #30                 // Field userData:Landroidx/lifecycle/LiveData;
+        29: return
 
-  public final void setUserId(java.lang.String);
+  public void setUserId(java.lang.String);
     Code:
-         0: aload_1
-         1: aload_0
-         2: getfield      #14                 // Field userId:Ljava/lang/String;
-         5: invokestatic  #38                 // Method kotlin/jvm/internal/Intrinsics.areEqual:(Ljava/lang/Object;Ljava/lang/Object;)Z
-         8: ifne          27
-        11: aload_0
-        12: aload_1
-        13: dup
-        14: ifnonnull     24
-        17: pop
-        18: invokestatic  #44                 // Method com/example/compose/jetchat/data/FakeDataKt.getMeProfile:()Lcom/example/compose/jetchat/profile/ProfileScreenState;
-        21: invokevirtual #50                 // Method com/example/compose/jetchat/profile/ProfileScreenState.getUserId:()Ljava/lang/String;
-        24: putfield      #14                 // Field userId:Ljava/lang/String;
-        27: aload_0
-        28: getfield      #21                 // Field _userData:Landroidx/lifecycle/MutableLiveData;
-        31: aload_0
-        32: getfield      #14                 // Field userId:Ljava/lang/String;
-        35: invokestatic  #44                 // Method com/example/compose/jetchat/data/FakeDataKt.getMeProfile:()Lcom/example/compose/jetchat/profile/ProfileScreenState;
-        38: invokevirtual #50                 // Method com/example/compose/jetchat/profile/ProfileScreenState.getUserId:()Ljava/lang/String;
-        41: invokestatic  #38                 // Method kotlin/jvm/internal/Intrinsics.areEqual:(Ljava/lang/Object;Ljava/lang/Object;)Z
-        44: ifne          63
-        47: aload_0
-        48: getfield      #14                 // Field userId:Ljava/lang/String;
-        51: invokestatic  #44                 // Method com/example/compose/jetchat/data/FakeDataKt.getMeProfile:()Lcom/example/compose/jetchat/profile/ProfileScreenState;
-        54: invokevirtual #53                 // Method com/example/compose/jetchat/profile/ProfileScreenState.getDisplayName:()Ljava/lang/String;
-        57: invokestatic  #38                 // Method kotlin/jvm/internal/Intrinsics.areEqual:(Ljava/lang/Object;Ljava/lang/Object;)Z
-        60: ifeq          69
-        63: invokestatic  #44                 // Method com/example/compose/jetchat/data/FakeDataKt.getMeProfile:()Lcom/example/compose/jetchat/profile/ProfileScreenState;
-        66: goto          72
-        69: invokestatic  #56                 // Method com/example/compose/jetchat/data/FakeDataKt.getColleagueProfile:()Lcom/example/compose/jetchat/profile/ProfileScreenState;
-        72: invokevirtual #60                 // Method androidx/lifecycle/MutableLiveData.setValue:(Ljava/lang/Object;)V
-        75: return
+         0: aload_0
+         1: getfield      #23                 // Field userId:Ljava/lang/String;
+         4: astore_2
+         5: aload_0
+         6: getfield      #28                 // Field _userData:Landroidx/lifecycle/MutableLiveData;
+         9: astore_3
+        10: aload_0
+        11: getfield      #30                 // Field userData:Landroidx/lifecycle/LiveData;
+        14: astore        4
+        16: aload_1
+        17: aload_2
+        18: if_acmpeq     28
+        21: aload_1
+        22: ifnull        58
+        25: goto          52
+        28: invokestatic  #38                 // Method com/example/compose/jetchat/data/FakeDataKt.getMeProfile:()Lcom/example/compose/jetchat/profile/ProfileScreenState;
+        31: getfield      #41                 // Field com/example/compose/jetchat/profile/ProfileScreenState.userId:Ljava/lang/String;
+        34: aload_2
+        35: swap
+        36: invokestatic  #47                 // Method kotlin/jvm/internal/Intrinsics.areEqual:(Ljava/lang/Object;Ljava/lang/Object;)Z
+        39: istore        5
+        41: iconst_1
+        42: istore        6
+        44: iload         5
+        46: ifeq          72
+        49: goto          85
+        52: aload_1
+        53: astore        7
+        55: goto          66
+        58: invokestatic  #38                 // Method com/example/compose/jetchat/data/FakeDataKt.getMeProfile:()Lcom/example/compose/jetchat/profile/ProfileScreenState;
+        61: getfield      #41                 // Field com/example/compose/jetchat/profile/ProfileScreenState.userId:Ljava/lang/String;
+        64: astore        7
+        66: aload         7
+        68: astore_2
+        69: goto          28
+        72: invokestatic  #38                 // Method com/example/compose/jetchat/data/FakeDataKt.getMeProfile:()Lcom/example/compose/jetchat/profile/ProfileScreenState;
+        75: getfield      #50                 // Field com/example/compose/jetchat/profile/ProfileScreenState.displayName:Ljava/lang/String;
+        78: aload_2
+        79: swap
+        80: invokestatic  #47                 // Method kotlin/jvm/internal/Intrinsics.areEqual:(Ljava/lang/Object;Ljava/lang/Object;)Z
+        83: istore        6
+        85: iload         6
+        87: ifeq          98
+        90: invokestatic  #38                 // Method com/example/compose/jetchat/data/FakeDataKt.getMeProfile:()Lcom/example/compose/jetchat/profile/ProfileScreenState;
+        93: astore        8
+        95: goto          103
+        98: invokestatic  #53                 // Method com/example/compose/jetchat/data/FakeDataKt.getColleagueProfile:()Lcom/example/compose/jetchat/profile/ProfileScreenState;
+       101: astore        8
+       103: aload_3
+       104: aload         8
+       106: invokevirtual #57                 // Method androidx/lifecycle/MutableLiveData.setValue:(Ljava/lang/Object;)V
+       109: aload_0
+       110: aload_2
+       111: putfield      #23                 // Field userId:Ljava/lang/String;
+       114: aload_0
+       115: aload_3
+       116: putfield      #28                 // Field _userData:Landroidx/lifecycle/MutableLiveData;
+       119: aload_0
+       120: aload         4
+       122: putfield      #30                 // Field userData:Landroidx/lifecycle/LiveData;
+       125: return
 
-  public final androidx.lifecycle.LiveData<com.example.compose.jetchat.profile.ProfileScreenState> getUserData();
+  public java.lang.String getUserId();
     Code:
          0: aload_0
-         1: getfield      #27                 // Field userData:Landroidx/lifecycle/LiveData;
+         1: getfield      #23                 // Field userId:Ljava/lang/String;
          4: areturn
 
-  static {};
+  public androidx.lifecycle.MutableLiveData get_userData();
     Code:
-         0: bipush        8
-         2: putstatic     #72                 // Field $stable:I
-         5: return
+         0: aload_0
+         1: getfield      #28                 // Field _userData:Landroidx/lifecycle/MutableLiveData;
+         4: areturn
+
+  public androidx.lifecycle.LiveData getUserData();
+    Code:
+         0: aload_0
+         1: getfield      #30                 // Field userData:Landroidx/lifecycle/LiveData;
+         4: areturn
 }
