--- ./gradle/com.example.compose.jetchat.profile.ProfileScreenState.javap	2026-05-25 11:17:38
+++ ./skotch/com.example.compose.jetchat.profile.ProfileScreenState.javap	2026-05-25 11:17:39
@@ -1,528 +1,549 @@
-Compiled from "ProfileViewModel.kt"
+Compiled from "com/example/compose/jetchat/profile/ProfileScreenState.kt"
 public final class com.example.compose.jetchat.profile.ProfileScreenState {
-  private final java.lang.String userId;
+  public java.lang.String userId;
 
-  private final java.lang.Integer photo;
+  public java.lang.Integer photo;
 
-  private final java.lang.String name;
+  public java.lang.String name;
 
-  private final java.lang.String status;
+  public java.lang.String status;
 
-  private final java.lang.String displayName;
+  public java.lang.String displayName;
 
-  private final java.lang.String position;
+  public java.lang.String position;
 
-  private final java.lang.String twitter;
+  public java.lang.String twitter;
 
-  private final java.lang.String timeZone;
+  public java.lang.String timeZone;
 
-  private final java.lang.String commonChannels;
+  public java.lang.String commonChannels;
 
   public static final int $stable;
 
   public com.example.compose.jetchat.profile.ProfileScreenState(java.lang.String, java.lang.Integer, java.lang.String, java.lang.String, java.lang.String, java.lang.String, java.lang.String, java.lang.String, java.lang.String);
     Code:
-         0: aload_1
-         1: ldc           #11                 // String userId
-         3: invokestatic  #17                 // Method kotlin/jvm/internal/Intrinsics.checkNotNullParameter:(Ljava/lang/Object;Ljava/lang/String;)V
-         6: aload_3
-         7: ldc           #19                 // String name
-         9: invokestatic  #17                 // Method kotlin/jvm/internal/Intrinsics.checkNotNullParameter:(Ljava/lang/Object;Ljava/lang/String;)V
-        12: aload         4
-        14: ldc           #21                 // String status
-        16: invokestatic  #17                 // Method kotlin/jvm/internal/Intrinsics.checkNotNullParameter:(Ljava/lang/Object;Ljava/lang/String;)V
-        19: aload         5
-        21: ldc           #23                 // String displayName
-        23: invokestatic  #17                 // Method kotlin/jvm/internal/Intrinsics.checkNotNullParameter:(Ljava/lang/Object;Ljava/lang/String;)V
-        26: aload         6
-        28: ldc           #25                 // String position
-        30: invokestatic  #17                 // Method kotlin/jvm/internal/Intrinsics.checkNotNullParameter:(Ljava/lang/Object;Ljava/lang/String;)V
-        33: aload         7
-        35: ldc           #27                 // String twitter
-        37: invokestatic  #17                 // Method kotlin/jvm/internal/Intrinsics.checkNotNullParameter:(Ljava/lang/Object;Ljava/lang/String;)V
-        40: aload_0
-        41: invokespecial #30                 // Method java/lang/Object."<init>":()V
-        44: aload_0
-        45: aload_1
-        46: putfield      #33                 // Field userId:Ljava/lang/String;
+         0: aload_0
+         1: invokespecial #25                 // Method java/lang/Object."<init>":()V
+         4: aload_0
+         5: aload_1
+         6: putfield      #27                 // Field userId:Ljava/lang/String;
+         9: aload_0
+        10: aload_2
+        11: putfield      #29                 // Field photo:Ljava/lang/Integer;
+        14: aload_0
+        15: aload_3
+        16: putfield      #31                 // Field name:Ljava/lang/String;
+        19: aload_0
+        20: aload         4
+        22: putfield      #33                 // Field status:Ljava/lang/String;
+        25: aload_0
+        26: aload         5
+        28: putfield      #35                 // Field displayName:Ljava/lang/String;
+        31: aload_0
+        32: aload         6
+        34: putfield      #37                 // Field position:Ljava/lang/String;
+        37: aload_0
+        38: aload         7
+        40: putfield      #39                 // Field twitter:Ljava/lang/String;
+        43: aload_0
+        44: aload         8
+        46: putfield      #41                 // Field timeZone:Ljava/lang/String;
         49: aload_0
-        50: aload_2
-        51: putfield      #37                 // Field photo:Ljava/lang/Integer;
-        54: aload_0
-        55: aload_3
-        56: putfield      #39                 // Field name:Ljava/lang/String;
-        59: aload_0
-        60: aload         4
-        62: putfield      #41                 // Field status:Ljava/lang/String;
-        65: aload_0
-        66: aload         5
-        68: putfield      #43                 // Field displayName:Ljava/lang/String;
-        71: aload_0
-        72: aload         6
-        74: putfield      #45                 // Field position:Ljava/lang/String;
-        77: aload_0
-        78: aload         7
-        80: putfield      #47                 // Field twitter:Ljava/lang/String;
-        83: aload_0
-        84: aload         8
-        86: putfield      #50                 // Field timeZone:Ljava/lang/String;
-        89: aload_0
-        90: aload         9
-        92: putfield      #53                 // Field commonChannels:Ljava/lang/String;
-        95: return
+        50: aload         9
+        52: putfield      #43                 // Field commonChannels:Ljava/lang/String;
+        55: return
 
-  public com.example.compose.jetchat.profile.ProfileScreenState(java.lang.String, java.lang.Integer, java.lang.String, java.lang.String, java.lang.String, java.lang.String, java.lang.String, java.lang.String, java.lang.String, int, kotlin.jvm.internal.DefaultConstructorMarker);
+  public boolean isMe();
     Code:
-         0: iload         10
-         2: bipush        64
-         4: iand
-         5: ifeq          12
-         8: ldc           #58                 // String
-        10: astore        7
-        12: aload_0
-        13: aload_1
-        14: aload_2
-        15: aload_3
-        16: aload         4
-        18: aload         5
-        20: aload         6
-        22: aload         7
-        24: aload         8
-        26: aload         9
-        28: invokespecial #60                 // Method "<init>":(Ljava/lang/String;Ljava/lang/Integer;Ljava/lang/String;Ljava/lang/String;Ljava/lang/String;Ljava/lang/String;Ljava/lang/String;Ljava/lang/String;Ljava/lang/String;)V
-        31: return
+         0: aload_0
+         1: getfield      #27                 // Field userId:Ljava/lang/String;
+         4: astore_1
+         5: aload_0
+         6: getfield      #29                 // Field photo:Ljava/lang/Integer;
+         9: astore_2
+        10: aload_0
+        11: getfield      #31                 // Field name:Ljava/lang/String;
+        14: astore_3
+        15: aload_0
+        16: getfield      #33                 // Field status:Ljava/lang/String;
+        19: astore        4
+        21: aload_0
+        22: getfield      #35                 // Field displayName:Ljava/lang/String;
+        25: astore        5
+        27: aload_0
+        28: getfield      #37                 // Field position:Ljava/lang/String;
+        31: astore        6
+        33: aload_0
+        34: getfield      #39                 // Field twitter:Ljava/lang/String;
+        37: astore        7
+        39: aload_0
+        40: getfield      #41                 // Field timeZone:Ljava/lang/String;
+        43: astore        8
+        45: aload_0
+        46: getfield      #43                 // Field commonChannels:Ljava/lang/String;
+        49: astore        9
+        51: aload_1
+        52: invokestatic  #55                 // Method com/example/compose/jetchat/data/FakeDataKt.getMeProfile:()Lcom/example/compose/jetchat/profile/ProfileScreenState;
+        55: getfield      #27                 // Field userId:Ljava/lang/String;
+        58: invokestatic  #61                 // Method kotlin/jvm/internal/Intrinsics.areEqual:(Ljava/lang/Object;Ljava/lang/Object;)Z
+        61: aload_0
+        62: aload_1
+        63: putfield      #27                 // Field userId:Ljava/lang/String;
+        66: aload_0
+        67: aload_2
+        68: putfield      #29                 // Field photo:Ljava/lang/Integer;
+        71: aload_0
+        72: aload_3
+        73: putfield      #31                 // Field name:Ljava/lang/String;
+        76: aload_0
+        77: aload         4
+        79: putfield      #33                 // Field status:Ljava/lang/String;
+        82: aload_0
+        83: aload         5
+        85: putfield      #35                 // Field displayName:Ljava/lang/String;
+        88: aload_0
+        89: aload         6
+        91: putfield      #37                 // Field position:Ljava/lang/String;
+        94: aload_0
+        95: aload         7
+        97: putfield      #39                 // Field twitter:Ljava/lang/String;
+       100: aload_0
+       101: aload         8
+       103: putfield      #41                 // Field timeZone:Ljava/lang/String;
+       106: aload_0
+       107: aload         9
+       109: putfield      #43                 // Field commonChannels:Ljava/lang/String;
+       112: ireturn
 
-  public final java.lang.String getUserId();
+  public java.lang.String getUserId();
     Code:
          0: aload_0
-         1: getfield      #33                 // Field userId:Ljava/lang/String;
+         1: getfield      #27                 // Field userId:Ljava/lang/String;
          4: areturn
 
-  public final java.lang.Integer getPhoto();
+  public java.lang.Integer getPhoto();
     Code:
          0: aload_0
-         1: getfield      #37                 // Field photo:Ljava/lang/Integer;
+         1: getfield      #29                 // Field photo:Ljava/lang/Integer;
          4: areturn
 
-  public final java.lang.String getName();
+  public java.lang.String getName();
     Code:
          0: aload_0
-         1: getfield      #39                 // Field name:Ljava/lang/String;
+         1: getfield      #31                 // Field name:Ljava/lang/String;
          4: areturn
 
-  public final java.lang.String getStatus();
+  public java.lang.String getStatus();
     Code:
          0: aload_0
-         1: getfield      #41                 // Field status:Ljava/lang/String;
+         1: getfield      #33                 // Field status:Ljava/lang/String;
          4: areturn
 
-  public final java.lang.String getDisplayName();
+  public java.lang.String getDisplayName();
     Code:
          0: aload_0
-         1: getfield      #43                 // Field displayName:Ljava/lang/String;
+         1: getfield      #35                 // Field displayName:Ljava/lang/String;
          4: areturn
 
-  public final java.lang.String getPosition();
+  public java.lang.String getPosition();
     Code:
          0: aload_0
-         1: getfield      #45                 // Field position:Ljava/lang/String;
+         1: getfield      #37                 // Field position:Ljava/lang/String;
          4: areturn
 
-  public final java.lang.String getTwitter();
+  public java.lang.String getTwitter();
     Code:
          0: aload_0
-         1: getfield      #47                 // Field twitter:Ljava/lang/String;
+         1: getfield      #39                 // Field twitter:Ljava/lang/String;
          4: areturn
 
-  public final java.lang.String getTimeZone();
+  public java.lang.String getTimeZone();
     Code:
          0: aload_0
-         1: getfield      #50                 // Field timeZone:Ljava/lang/String;
+         1: getfield      #41                 // Field timeZone:Ljava/lang/String;
          4: areturn
 
-  public final java.lang.String getCommonChannels();
+  public java.lang.String getCommonChannels();
     Code:
          0: aload_0
-         1: getfield      #53                 // Field commonChannels:Ljava/lang/String;
+         1: getfield      #43                 // Field commonChannels:Ljava/lang/String;
          4: areturn
 
-  public final boolean isMe();
+  public java.lang.String toString();
     Code:
-         0: aload_0
-         1: getfield      #33                 // Field userId:Ljava/lang/String;
-         4: invokestatic  #79                 // Method com/example/compose/jetchat/data/FakeDataKt.getMeProfile:()Lcom/example/compose/jetchat/profile/ProfileScreenState;
-         7: getfield      #33                 // Field userId:Ljava/lang/String;
-        10: invokestatic  #83                 // Method kotlin/jvm/internal/Intrinsics.areEqual:(Ljava/lang/Object;Ljava/lang/Object;)Z
-        13: ireturn
+         0: ldc           #78                 // String ProfileScreenState(
+         2: invokedynamic #90,  0             // InvokeDynamic #0:makeConcatWithConstants:(Ljava/lang/String;)Ljava/lang/String;
+         7: astore_1
+         8: aload_1
+         9: aload_0
+        10: getfield      #27                 // Field userId:Ljava/lang/String;
+        13: invokedynamic #95,  0             // InvokeDynamic #1:makeConcatWithConstants:(Ljava/lang/String;Ljava/lang/String;)Ljava/lang/String;
+        18: invokedynamic #98,  0             // InvokeDynamic #2:makeConcatWithConstants:(Ljava/lang/String;)Ljava/lang/String;
+        23: invokedynamic #101,  0            // InvokeDynamic #3:makeConcatWithConstants:(Ljava/lang/String;)Ljava/lang/String;
+        28: aload_0
+        29: getfield      #29                 // Field photo:Ljava/lang/Integer;
+        32: invokestatic  #105                // Method java/lang/String.valueOf:(Ljava/lang/Object;)Ljava/lang/String;
+        35: invokevirtual #108                // Method java/lang/String.concat:(Ljava/lang/String;)Ljava/lang/String;
+        38: invokedynamic #98,  0             // InvokeDynamic #2:makeConcatWithConstants:(Ljava/lang/String;)Ljava/lang/String;
+        43: invokedynamic #111,  0            // InvokeDynamic #4:makeConcatWithConstants:(Ljava/lang/String;)Ljava/lang/String;
+        48: astore_2
+        49: aload_0
+        50: getfield      #31                 // Field name:Ljava/lang/String;
+        53: aload_2
+        54: swap
+        55: invokedynamic #95,  0             // InvokeDynamic #1:makeConcatWithConstants:(Ljava/lang/String;Ljava/lang/String;)Ljava/lang/String;
+        60: invokedynamic #98,  0             // InvokeDynamic #2:makeConcatWithConstants:(Ljava/lang/String;)Ljava/lang/String;
+        65: invokedynamic #114,  0            // InvokeDynamic #5:makeConcatWithConstants:(Ljava/lang/String;)Ljava/lang/String;
+        70: astore_3
+        71: aload_0
+        72: getfield      #33                 // Field status:Ljava/lang/String;
+        75: aload_3
+        76: swap
+        77: invokedynamic #95,  0             // InvokeDynamic #1:makeConcatWithConstants:(Ljava/lang/String;Ljava/lang/String;)Ljava/lang/String;
+        82: invokedynamic #98,  0             // InvokeDynamic #2:makeConcatWithConstants:(Ljava/lang/String;)Ljava/lang/String;
+        87: invokedynamic #117,  0            // InvokeDynamic #6:makeConcatWithConstants:(Ljava/lang/String;)Ljava/lang/String;
+        92: astore        4
+        94: aload_0
+        95: getfield      #35                 // Field displayName:Ljava/lang/String;
+        98: aload         4
+       100: swap
+       101: invokedynamic #95,  0             // InvokeDynamic #1:makeConcatWithConstants:(Ljava/lang/String;Ljava/lang/String;)Ljava/lang/String;
+       106: invokedynamic #98,  0             // InvokeDynamic #2:makeConcatWithConstants:(Ljava/lang/String;)Ljava/lang/String;
+       111: invokedynamic #120,  0            // InvokeDynamic #7:makeConcatWithConstants:(Ljava/lang/String;)Ljava/lang/String;
+       116: astore        5
+       118: aload_0
+       119: getfield      #37                 // Field position:Ljava/lang/String;
+       122: aload         5
+       124: swap
+       125: invokedynamic #95,  0             // InvokeDynamic #1:makeConcatWithConstants:(Ljava/lang/String;Ljava/lang/String;)Ljava/lang/String;
+       130: invokedynamic #98,  0             // InvokeDynamic #2:makeConcatWithConstants:(Ljava/lang/String;)Ljava/lang/String;
+       135: invokedynamic #123,  0            // InvokeDynamic #8:makeConcatWithConstants:(Ljava/lang/String;)Ljava/lang/String;
+       140: astore        6
+       142: aload_0
+       143: getfield      #39                 // Field twitter:Ljava/lang/String;
+       146: aload         6
+       148: swap
+       149: invokedynamic #95,  0             // InvokeDynamic #1:makeConcatWithConstants:(Ljava/lang/String;Ljava/lang/String;)Ljava/lang/String;
+       154: invokedynamic #98,  0             // InvokeDynamic #2:makeConcatWithConstants:(Ljava/lang/String;)Ljava/lang/String;
+       159: invokedynamic #126,  0            // InvokeDynamic #9:makeConcatWithConstants:(Ljava/lang/String;)Ljava/lang/String;
+       164: aload_0
+       165: getfield      #41                 // Field timeZone:Ljava/lang/String;
+       168: invokestatic  #105                // Method java/lang/String.valueOf:(Ljava/lang/Object;)Ljava/lang/String;
+       171: invokevirtual #108                // Method java/lang/String.concat:(Ljava/lang/String;)Ljava/lang/String;
+       174: invokedynamic #98,  0             // InvokeDynamic #2:makeConcatWithConstants:(Ljava/lang/String;)Ljava/lang/String;
+       179: invokedynamic #129,  0            // InvokeDynamic #10:makeConcatWithConstants:(Ljava/lang/String;)Ljava/lang/String;
+       184: aload_0
+       185: getfield      #43                 // Field commonChannels:Ljava/lang/String;
+       188: invokestatic  #105                // Method java/lang/String.valueOf:(Ljava/lang/Object;)Ljava/lang/String;
+       191: invokevirtual #108                // Method java/lang/String.concat:(Ljava/lang/String;)Ljava/lang/String;
+       194: invokedynamic #132,  0            // InvokeDynamic #11:makeConcatWithConstants:(Ljava/lang/String;)Ljava/lang/String;
+       199: areturn
 
-  public final java.lang.String component1();
+  public java.lang.String component1();
     Code:
          0: aload_0
-         1: getfield      #33                 // Field userId:Ljava/lang/String;
+         1: getfield      #27                 // Field userId:Ljava/lang/String;
          4: areturn
 
-  public final java.lang.Integer component2();
+  public java.lang.Integer component2();
     Code:
          0: aload_0
-         1: getfield      #37                 // Field photo:Ljava/lang/Integer;
+         1: getfield      #29                 // Field photo:Ljava/lang/Integer;
          4: areturn
 
-  public final java.lang.String component3();
+  public java.lang.String component3();
     Code:
          0: aload_0
-         1: getfield      #39                 // Field name:Ljava/lang/String;
+         1: getfield      #31                 // Field name:Ljava/lang/String;
          4: areturn
 
-  public final java.lang.String component4();
+  public java.lang.String component4();
     Code:
          0: aload_0
-         1: getfield      #41                 // Field status:Ljava/lang/String;
+         1: getfield      #33                 // Field status:Ljava/lang/String;
          4: areturn
 
-  public final java.lang.String component5();
+  public java.lang.String component5();
     Code:
          0: aload_0
-         1: getfield      #43                 // Field displayName:Ljava/lang/String;
+         1: getfield      #35                 // Field displayName:Ljava/lang/String;
          4: areturn
 
-  public final java.lang.String component6();
+  public java.lang.String component6();
     Code:
          0: aload_0
-         1: getfield      #45                 // Field position:Ljava/lang/String;
+         1: getfield      #37                 // Field position:Ljava/lang/String;
          4: areturn
 
-  public final java.lang.String component7();
+  public java.lang.String component7();
     Code:
          0: aload_0
-         1: getfield      #47                 // Field twitter:Ljava/lang/String;
+         1: getfield      #39                 // Field twitter:Ljava/lang/String;
          4: areturn
 
-  public final java.lang.String component8();
+  public java.lang.String component8();
     Code:
          0: aload_0
-         1: getfield      #50                 // Field timeZone:Ljava/lang/String;
+         1: getfield      #41                 // Field timeZone:Ljava/lang/String;
          4: areturn
 
-  public final java.lang.String component9();
+  public java.lang.String component9();
     Code:
          0: aload_0
-         1: getfield      #53                 // Field commonChannels:Ljava/lang/String;
+         1: getfield      #43                 // Field commonChannels:Ljava/lang/String;
          4: areturn
 
-  public final com.example.compose.jetchat.profile.ProfileScreenState copy(java.lang.String, java.lang.Integer, java.lang.String, java.lang.String, java.lang.String, java.lang.String, java.lang.String, java.lang.String, java.lang.String);
+  public boolean equals(java.lang.Object);
     Code:
-         0: aload_1
-         1: ldc           #11                 // String userId
-         3: invokestatic  #17                 // Method kotlin/jvm/internal/Intrinsics.checkNotNullParameter:(Ljava/lang/Object;Ljava/lang/String;)V
-         6: aload_3
-         7: ldc           #19                 // String name
-         9: invokestatic  #17                 // Method kotlin/jvm/internal/Intrinsics.checkNotNullParameter:(Ljava/lang/Object;Ljava/lang/String;)V
-        12: aload         4
-        14: ldc           #21                 // String status
-        16: invokestatic  #17                 // Method kotlin/jvm/internal/Intrinsics.checkNotNullParameter:(Ljava/lang/Object;Ljava/lang/String;)V
-        19: aload         5
-        21: ldc           #23                 // String displayName
-        23: invokestatic  #17                 // Method kotlin/jvm/internal/Intrinsics.checkNotNullParameter:(Ljava/lang/Object;Ljava/lang/String;)V
-        26: aload         6
-        28: ldc           #25                 // String position
-        30: invokestatic  #17                 // Method kotlin/jvm/internal/Intrinsics.checkNotNullParameter:(Ljava/lang/Object;Ljava/lang/String;)V
-        33: aload         7
-        35: ldc           #27                 // String twitter
-        37: invokestatic  #17                 // Method kotlin/jvm/internal/Intrinsics.checkNotNullParameter:(Ljava/lang/Object;Ljava/lang/String;)V
-        40: new           #2                  // class com/example/compose/jetchat/profile/ProfileScreenState
-        43: dup
-        44: aload_1
-        45: aload_2
-        46: aload_3
-        47: aload         4
-        49: aload         5
-        51: aload         6
-        53: aload         7
-        55: aload         8
-        57: aload         9
-        59: invokespecial #60                 // Method "<init>":(Ljava/lang/String;Ljava/lang/Integer;Ljava/lang/String;Ljava/lang/String;Ljava/lang/String;Ljava/lang/String;Ljava/lang/String;Ljava/lang/String;Ljava/lang/String;)V
-        62: areturn
-
-  public static com.example.compose.jetchat.profile.ProfileScreenState copy$default(com.example.compose.jetchat.profile.ProfileScreenState, java.lang.String, java.lang.Integer, java.lang.String, java.lang.String, java.lang.String, java.lang.String, java.lang.String, java.lang.String, java.lang.String, int, java.lang.Object);
-    Code:
-         0: iload         10
-         2: iconst_1
-         3: iand
-         4: ifeq          12
-         7: aload_0
-         8: getfield      #33                 // Field userId:Ljava/lang/String;
-        11: astore_1
-        12: iload         10
-        14: iconst_2
-        15: iand
-        16: ifeq          24
-        19: aload_0
-        20: getfield      #37                 // Field photo:Ljava/lang/Integer;
-        23: astore_2
-        24: iload         10
-        26: iconst_4
-        27: iand
-        28: ifeq          36
-        31: aload_0
-        32: getfield      #39                 // Field name:Ljava/lang/String;
-        35: astore_3
-        36: iload         10
-        38: bipush        8
-        40: iand
-        41: ifeq          50
-        44: aload_0
-        45: getfield      #41                 // Field status:Ljava/lang/String;
-        48: astore        4
-        50: iload         10
-        52: bipush        16
-        54: iand
-        55: ifeq          64
-        58: aload_0
-        59: getfield      #43                 // Field displayName:Ljava/lang/String;
-        62: astore        5
-        64: iload         10
-        66: bipush        32
-        68: iand
-        69: ifeq          78
-        72: aload_0
-        73: getfield      #45                 // Field position:Ljava/lang/String;
-        76: astore        6
-        78: iload         10
-        80: bipush        64
-        82: iand
-        83: ifeq          92
-        86: aload_0
-        87: getfield      #47                 // Field twitter:Ljava/lang/String;
-        90: astore        7
-        92: iload         10
-        94: sipush        128
-        97: iand
-        98: ifeq          107
-       101: aload_0
-       102: getfield      #50                 // Field timeZone:Ljava/lang/String;
-       105: astore        8
-       107: iload         10
-       109: sipush        256
-       112: iand
-       113: ifeq          122
-       116: aload_0
-       117: getfield      #53                 // Field commonChannels:Ljava/lang/String;
-       120: astore        9
-       122: aload_0
-       123: aload_1
-       124: aload_2
-       125: aload_3
-       126: aload         4
-       128: aload         5
-       130: aload         6
-       132: aload         7
-       134: aload         8
-       136: aload         9
-       138: invokevirtual #98                 // Method copy:(Ljava/lang/String;Ljava/lang/Integer;Ljava/lang/String;Ljava/lang/String;Ljava/lang/String;Ljava/lang/String;Ljava/lang/String;Ljava/lang/String;Ljava/lang/String;)Lcom/example/compose/jetchat/profile/ProfileScreenState;
-       141: areturn
-
-  public java.lang.String toString();
-    Code:
          0: aload_0
-         1: getfield      #33                 // Field userId:Ljava/lang/String;
-         4: aload_0
-         5: getfield      #37                 // Field photo:Ljava/lang/Integer;
-         8: aload_0
-         9: getfield      #39                 // Field name:Ljava/lang/String;
-        12: aload_0
-        13: getfield      #41                 // Field status:Ljava/lang/String;
-        16: aload_0
-        17: getfield      #43                 // Field displayName:Ljava/lang/String;
-        20: aload_0
-        21: getfield      #45                 // Field position:Ljava/lang/String;
-        24: aload_0
-        25: getfield      #47                 // Field twitter:Ljava/lang/String;
-        28: aload_0
-        29: getfield      #50                 // Field timeZone:Ljava/lang/String;
-        32: aload_0
-        33: getfield      #53                 // Field commonChannels:Ljava/lang/String;
-        36: invokedynamic #111,  0            // InvokeDynamic #0:makeConcatWithConstants:(Ljava/lang/String;Ljava/lang/Integer;Ljava/lang/String;Ljava/lang/String;Ljava/lang/String;Ljava/lang/String;Ljava/lang/String;Ljava/lang/String;Ljava/lang/String;)Ljava/lang/String;
-        41: areturn
+         1: astore_2
+         2: aload_2
+         3: aload_1
+         4: if_acmpne     13
+         7: iconst_1
+         8: istore        4
+        10: iload         4
+        12: ireturn
+        13: aload_1
+        14: instanceof    #2                  // class com/example/compose/jetchat/profile/ProfileScreenState
+        17: istore        5
+        19: iload         5
+        21: ifne          30
+        24: iconst_0
+        25: istore        6
+        27: iload         6
+        29: ireturn
+        30: aload_1
+        31: checkcast     #2                  // class com/example/compose/jetchat/profile/ProfileScreenState
+        34: astore        7
+        36: aload_0
+        37: getfield      #27                 // Field userId:Ljava/lang/String;
+        40: astore        8
+        42: aload         7
+        44: getfield      #27                 // Field userId:Ljava/lang/String;
+        47: astore        9
+        49: aload         8
+        51: aload         9
+        53: invokevirtual #145                // Method java/lang/String.equals:(Ljava/lang/Object;)Z
+        56: istore        10
+        58: aload_0
+        59: getfield      #29                 // Field photo:Ljava/lang/Integer;
+        62: astore        11
+        64: aload         7
+        66: getfield      #29                 // Field photo:Ljava/lang/Integer;
+        69: astore        12
+        71: aload         11
+        73: aload         12
+        75: invokevirtual #146                // Method java/lang/Object.equals:(Ljava/lang/Object;)Z
+        78: istore        13
+        80: iload         10
+        82: iload         13
+        84: imul
+        85: istore        14
+        87: aload_0
+        88: getfield      #31                 // Field name:Ljava/lang/String;
+        91: astore        15
+        93: aload         7
+        95: getfield      #31                 // Field name:Ljava/lang/String;
+        98: astore        16
+       100: aload         15
+       102: aload         16
+       104: invokevirtual #145                // Method java/lang/String.equals:(Ljava/lang/Object;)Z
+       107: istore        17
+       109: iload         14
+       111: iload         17
+       113: imul
+       114: istore        18
+       116: aload_0
+       117: getfield      #33                 // Field status:Ljava/lang/String;
+       120: astore        19
+       122: aload         7
+       124: getfield      #33                 // Field status:Ljava/lang/String;
+       127: astore        20
+       129: aload         19
+       131: aload         20
+       133: invokevirtual #145                // Method java/lang/String.equals:(Ljava/lang/Object;)Z
+       136: istore        21
+       138: iload         18
+       140: iload         21
+       142: imul
+       143: istore        22
+       145: aload_0
+       146: getfield      #35                 // Field displayName:Ljava/lang/String;
+       149: astore        23
+       151: aload         7
+       153: getfield      #35                 // Field displayName:Ljava/lang/String;
+       156: astore        24
+       158: aload         23
+       160: aload         24
+       162: invokevirtual #145                // Method java/lang/String.equals:(Ljava/lang/Object;)Z
+       165: istore        25
+       167: iload         22
+       169: iload         25
+       171: imul
+       172: istore        26
+       174: aload_0
+       175: getfield      #37                 // Field position:Ljava/lang/String;
+       178: astore        27
+       180: aload         7
+       182: getfield      #37                 // Field position:Ljava/lang/String;
+       185: astore        28
+       187: aload         27
+       189: aload         28
+       191: invokevirtual #145                // Method java/lang/String.equals:(Ljava/lang/Object;)Z
+       194: istore        29
+       196: iload         26
+       198: iload         29
+       200: imul
+       201: istore        30
+       203: aload_0
+       204: getfield      #39                 // Field twitter:Ljava/lang/String;
+       207: astore        31
+       209: aload         7
+       211: getfield      #39                 // Field twitter:Ljava/lang/String;
+       214: astore        32
+       216: aload         31
+       218: aload         32
+       220: invokevirtual #145                // Method java/lang/String.equals:(Ljava/lang/Object;)Z
+       223: istore        33
+       225: iload         30
+       227: iload         33
+       229: imul
+       230: istore        34
+       232: aload_0
+       233: getfield      #41                 // Field timeZone:Ljava/lang/String;
+       236: astore        35
+       238: aload         7
+       240: getfield      #41                 // Field timeZone:Ljava/lang/String;
+       243: astore        36
+       245: aload         35
+       247: aload         36
+       249: invokevirtual #146                // Method java/lang/Object.equals:(Ljava/lang/Object;)Z
+       252: istore        37
+       254: iload         34
+       256: iload         37
+       258: imul
+       259: istore        38
+       261: aload_0
+       262: getfield      #43                 // Field commonChannels:Ljava/lang/String;
+       265: astore        39
+       267: aload         7
+       269: getfield      #43                 // Field commonChannels:Ljava/lang/String;
+       272: astore        40
+       274: aload         39
+       276: aload         40
+       278: invokevirtual #146                // Method java/lang/Object.equals:(Ljava/lang/Object;)Z
+       281: istore        41
+       283: iload         38
+       285: iload         41
+       287: imul
+       288: istore        42
+       290: iload         42
+       292: ireturn
 
   public int hashCode();
     Code:
          0: aload_0
-         1: getfield      #33                 // Field userId:Ljava/lang/String;
-         4: invokevirtual #117                // Method java/lang/String.hashCode:()I
+         1: getfield      #27                 // Field userId:Ljava/lang/String;
+         4: invokevirtual #151                // Method java/lang/String.hashCode:()I
          7: istore_1
-         8: iload_1
-         9: bipush        31
-        11: imul
-        12: aload_0
-        13: getfield      #37                 // Field photo:Ljava/lang/Integer;
-        16: ifnonnull     23
-        19: iconst_0
-        20: goto          30
-        23: aload_0
-        24: getfield      #37                 // Field photo:Ljava/lang/Integer;
-        27: invokevirtual #118                // Method java/lang/Object.hashCode:()I
-        30: iadd
-        31: istore_1
-        32: iload_1
-        33: bipush        31
-        35: imul
-        36: aload_0
-        37: getfield      #39                 // Field name:Ljava/lang/String;
-        40: invokevirtual #117                // Method java/lang/String.hashCode:()I
-        43: iadd
-        44: istore_1
-        45: iload_1
-        46: bipush        31
-        48: imul
-        49: aload_0
-        50: getfield      #41                 // Field status:Ljava/lang/String;
-        53: invokevirtual #117                // Method java/lang/String.hashCode:()I
-        56: iadd
-        57: istore_1
-        58: iload_1
-        59: bipush        31
-        61: imul
-        62: aload_0
-        63: getfield      #43                 // Field displayName:Ljava/lang/String;
-        66: invokevirtual #117                // Method java/lang/String.hashCode:()I
-        69: iadd
-        70: istore_1
-        71: iload_1
+         8: aload_0
+         9: getfield      #29                 // Field photo:Ljava/lang/Integer;
+        12: checkcast     #4                  // class java/lang/Object
+        15: invokevirtual #152                // Method java/lang/Object.hashCode:()I
+        18: istore_2
+        19: bipush        31
+        21: iload_1
+        22: imul
+        23: iload_2
+        24: iadd
+        25: istore_3
+        26: aload_0
+        27: getfield      #31                 // Field name:Ljava/lang/String;
+        30: invokevirtual #151                // Method java/lang/String.hashCode:()I
+        33: istore        4
+        35: bipush        31
+        37: iload_3
+        38: imul
+        39: iload         4
+        41: iadd
+        42: istore        5
+        44: aload_0
+        45: getfield      #33                 // Field status:Ljava/lang/String;
+        48: invokevirtual #151                // Method java/lang/String.hashCode:()I
+        51: istore        6
+        53: bipush        31
+        55: iload         5
+        57: imul
+        58: iload         6
+        60: iadd
+        61: istore        7
+        63: aload_0
+        64: getfield      #35                 // Field displayName:Ljava/lang/String;
+        67: invokevirtual #151                // Method java/lang/String.hashCode:()I
+        70: istore        8
         72: bipush        31
-        74: imul
-        75: aload_0
-        76: getfield      #45                 // Field position:Ljava/lang/String;
-        79: invokevirtual #117                // Method java/lang/String.hashCode:()I
-        82: iadd
-        83: istore_1
-        84: iload_1
-        85: bipush        31
-        87: imul
-        88: aload_0
-        89: getfield      #47                 // Field twitter:Ljava/lang/String;
-        92: invokevirtual #117                // Method java/lang/String.hashCode:()I
-        95: iadd
-        96: istore_1
-        97: iload_1
-        98: bipush        31
-       100: imul
+        74: iload         7
+        76: imul
+        77: iload         8
+        79: iadd
+        80: istore        9
+        82: aload_0
+        83: getfield      #37                 // Field position:Ljava/lang/String;
+        86: invokevirtual #151                // Method java/lang/String.hashCode:()I
+        89: istore        10
+        91: bipush        31
+        93: iload         9
+        95: imul
+        96: iload         10
+        98: iadd
+        99: istore        11
        101: aload_0
-       102: getfield      #50                 // Field timeZone:Ljava/lang/String;
-       105: ifnonnull     112
-       108: iconst_0
-       109: goto          119
-       112: aload_0
-       113: getfield      #50                 // Field timeZone:Ljava/lang/String;
-       116: invokevirtual #117                // Method java/lang/String.hashCode:()I
-       119: iadd
-       120: istore_1
-       121: iload_1
-       122: bipush        31
-       124: imul
-       125: aload_0
-       126: getfield      #53                 // Field commonChannels:Ljava/lang/String;
-       129: ifnonnull     136
-       132: iconst_0
-       133: goto          143
-       136: aload_0
-       137: getfield      #53                 // Field commonChannels:Ljava/lang/String;
-       140: invokevirtual #117                // Method java/lang/String.hashCode:()I
-       143: iadd
-       144: istore_1
-       145: iload_1
-       146: ireturn
+       102: getfield      #39                 // Field twitter:Ljava/lang/String;
+       105: invokevirtual #151                // Method java/lang/String.hashCode:()I
+       108: istore        12
+       110: bipush        31
+       112: iload         11
+       114: imul
+       115: iload         12
+       117: iadd
+       118: istore        13
+       120: aload_0
+       121: getfield      #41                 // Field timeZone:Ljava/lang/String;
+       124: checkcast     #4                  // class java/lang/Object
+       127: invokevirtual #152                // Method java/lang/Object.hashCode:()I
+       130: istore        14
+       132: bipush        31
+       134: iload         13
+       136: imul
+       137: iload         14
+       139: iadd
+       140: istore        15
+       142: aload_0
+       143: getfield      #43                 // Field commonChannels:Ljava/lang/String;
+       146: checkcast     #4                  // class java/lang/Object
+       149: invokevirtual #152                // Method java/lang/Object.hashCode:()I
+       152: istore        16
+       154: bipush        31
+       156: iload         15
+       158: imul
+       159: iload         16
+       161: iadd
+       162: ireturn
 
-  public boolean equals(java.lang.Object);
+  public com.example.compose.jetchat.profile.ProfileScreenState copy(java.lang.String, java.lang.Integer, java.lang.String, java.lang.String, java.lang.String, java.lang.String, java.lang.String, java.lang.String, java.lang.String);
     Code:
-         0: aload_0
-         1: aload_1
-         2: if_acmpne     7
-         5: iconst_1
-         6: ireturn
-         7: aload_1
-         8: instanceof    #2                  // class com/example/compose/jetchat/profile/ProfileScreenState
-        11: ifne          16
-        14: iconst_0
-        15: ireturn
-        16: aload_1
-        17: checkcast     #2                  // class com/example/compose/jetchat/profile/ProfileScreenState
-        20: astore_2
-        21: aload_0
-        22: getfield      #33                 // Field userId:Ljava/lang/String;
-        25: aload_2
-        26: getfield      #33                 // Field userId:Ljava/lang/String;
-        29: invokestatic  #83                 // Method kotlin/jvm/internal/Intrinsics.areEqual:(Ljava/lang/Object;Ljava/lang/Object;)Z
-        32: ifne          37
-        35: iconst_0
-        36: ireturn
-        37: aload_0
-        38: getfield      #37                 // Field photo:Ljava/lang/Integer;
-        41: aload_2
-        42: getfield      #37                 // Field photo:Ljava/lang/Integer;
-        45: invokestatic  #83                 // Method kotlin/jvm/internal/Intrinsics.areEqual:(Ljava/lang/Object;Ljava/lang/Object;)Z
-        48: ifne          53
-        51: iconst_0
-        52: ireturn
-        53: aload_0
-        54: getfield      #39                 // Field name:Ljava/lang/String;
-        57: aload_2
-        58: getfield      #39                 // Field name:Ljava/lang/String;
-        61: invokestatic  #83                 // Method kotlin/jvm/internal/Intrinsics.areEqual:(Ljava/lang/Object;Ljava/lang/Object;)Z
-        64: ifne          69
-        67: iconst_0
-        68: ireturn
-        69: aload_0
-        70: getfield      #41                 // Field status:Ljava/lang/String;
-        73: aload_2
-        74: getfield      #41                 // Field status:Ljava/lang/String;
-        77: invokestatic  #83                 // Method kotlin/jvm/internal/Intrinsics.areEqual:(Ljava/lang/Object;Ljava/lang/Object;)Z
-        80: ifne          85
-        83: iconst_0
-        84: ireturn
-        85: aload_0
-        86: getfield      #43                 // Field displayName:Ljava/lang/String;
-        89: aload_2
-        90: getfield      #43                 // Field displayName:Ljava/lang/String;
-        93: invokestatic  #83                 // Method kotlin/jvm/internal/Intrinsics.areEqual:(Ljava/lang/Object;Ljava/lang/Object;)Z
-        96: ifne          101
-        99: iconst_0
-       100: ireturn
-       101: aload_0
-       102: getfield      #45                 // Field position:Ljava/lang/String;
-       105: aload_2
-       106: getfield      #45                 // Field position:Ljava/lang/String;
-       109: invokestatic  #83                 // Method kotlin/jvm/internal/Intrinsics.areEqual:(Ljava/lang/Object;Ljava/lang/Object;)Z
-       112: ifne          117
-       115: iconst_0
-       116: ireturn
-       117: aload_0
-       118: getfield      #47                 // Field twitter:Ljava/lang/String;
-       121: aload_2
-       122: getfield      #47                 // Field twitter:Ljava/lang/String;
-       125: invokestatic  #83                 // Method kotlin/jvm/internal/Intrinsics.areEqual:(Ljava/lang/Object;Ljava/lang/Object;)Z
-       128: ifne          133
-       131: iconst_0
-       132: ireturn
-       133: aload_0
-       134: getfield      #50                 // Field timeZone:Ljava/lang/String;
-       137: aload_2
-       138: getfield      #50                 // Field timeZone:Ljava/lang/String;
-       141: invokestatic  #83                 // Method kotlin/jvm/internal/Intrinsics.areEqual:(Ljava/lang/Object;Ljava/lang/Object;)Z
-       144: ifne          149
-       147: iconst_0
-       148: ireturn
-       149: aload_0
-       150: getfield      #53                 // Field commonChannels:Ljava/lang/String;
-       153: aload_2
-       154: getfield      #53                 // Field commonChannels:Ljava/lang/String;
-       157: invokestatic  #83                 // Method kotlin/jvm/internal/Intrinsics.areEqual:(Ljava/lang/Object;Ljava/lang/Object;)Z
-       160: ifne          165
-       163: iconst_0
-       164: ireturn
-       165: iconst_1
-       166: ireturn
-
-  static {};
-    Code:
-         0: return
+         0: new           #2                  // class com/example/compose/jetchat/profile/ProfileScreenState
+         3: dup
+         4: aload_1
+         5: aload_2
+         6: aload_3
+         7: aload         4
+         9: aload         5
+        11: aload         6
+        13: aload         7
+        15: aload         8
+        17: aload         9
+        19: invokespecial #156                // Method "<init>":(Ljava/lang/String;Ljava/lang/Integer;Ljava/lang/String;Ljava/lang/String;Ljava/lang/String;Ljava/lang/String;Ljava/lang/String;Ljava/lang/String;Ljava/lang/String;)V
+        22: areturn
 }
