--- ./gradle/com.example.compose.jetchat.widget.theme.JetChatGlanceTextStyles.javap	2026-05-25 11:17:41
+++ ./skotch/com.example.compose.jetchat.widget.theme.JetChatGlanceTextStyles.javap	2026-05-25 11:17:41
@@ -1,84 +1,18 @@
-Compiled from "Type.kt"
+Compiled from "com/example/compose/jetchat/widget/theme/JetChatGlanceTextStyles.kt"
 public final class com.example.compose.jetchat.widget.theme.JetChatGlanceTextStyles {
   public static final com.example.compose.jetchat.widget.theme.JetChatGlanceTextStyles INSTANCE;
 
-  private static final androidx.glance.text.TextStyle titleMedium;
-
-  private static final androidx.glance.text.TextStyle bodyMedium;
-
-  public static final int $stable;
-
-  private com.example.compose.jetchat.widget.theme.JetChatGlanceTextStyles();
-    Code:
-         0: aload_0
-         1: invokespecial #8                  // Method java/lang/Object."<init>":()V
-         4: return
-
-  public final androidx.glance.text.TextStyle getTitleMedium();
-    Code:
-         0: getstatic     #17                 // Field titleMedium:Landroidx/glance/text/TextStyle;
-         3: areturn
-
-  public final androidx.glance.text.TextStyle getBodyMedium();
-    Code:
-         0: getstatic     #21                 // Field bodyMedium:Landroidx/glance/text/TextStyle;
-         3: areturn
-
   static {};
     Code:
          0: new           #2                  // class com/example/compose/jetchat/widget/theme/JetChatGlanceTextStyles
          3: dup
-         4: invokespecial #23                 // Method "<init>":()V
-         7: putstatic     #26                 // Field INSTANCE:Lcom/example/compose/jetchat/widget/theme/JetChatGlanceTextStyles;
-        10: bipush        16
-        12: invokestatic  #32                 // Method androidx/compose/ui/unit/TextUnitKt.getSp:(I)J
-        15: lstore_0
-        16: getstatic     #37                 // Field com/example/compose/jetchat/widget/theme/JetchatGlanceColorScheme.INSTANCE:Lcom/example/compose/jetchat/widget/theme/JetchatGlanceColorScheme;
-        19: invokevirtual #41                 // Method com/example/compose/jetchat/widget/theme/JetchatGlanceColorScheme.getColors:()Landroidx/glance/color/ColorProviders;
-        22: invokevirtual #47                 // Method androidx/glance/color/ColorProviders.getOnSurfaceVariant:()Landroidx/glance/unit/ColorProvider;
-        25: astore_2
-        26: getstatic     #53                 // Field androidx/glance/text/FontWeight.Companion:Landroidx/glance/text/FontWeight$Companion;
-        29: invokevirtual #59                 // Method androidx/glance/text/FontWeight$Companion."getBold-WjrlUT0":()I
-        32: istore_3
-        33: new           #61                 // class androidx/glance/text/TextStyle
-        36: dup
-        37: aload_2
-        38: lload_0
-        39: invokestatic  #67                 // Method androidx/compose/ui/unit/TextUnit."box-impl":(J)Landroidx/compose/ui/unit/TextUnit;
-        42: iload_3
-        43: invokestatic  #70                 // Method androidx/glance/text/FontWeight."box-impl":(I)Landroidx/glance/text/FontWeight;
-        46: aconst_null
-        47: aconst_null
-        48: aconst_null
-        49: aconst_null
-        50: bipush        120
-        52: aconst_null
-        53: invokespecial #73                 // Method androidx/glance/text/TextStyle."<init>":(Landroidx/glance/unit/ColorProvider;Landroidx/compose/ui/unit/TextUnit;Landroidx/glance/text/FontWeight;Landroidx/glance/text/FontStyle;Landroidx/glance/text/TextAlign;Landroidx/glance/text/TextDecoration;Landroidx/glance/text/FontFamily;ILkotlin/jvm/internal/DefaultConstructorMarker;)V
-        56: putstatic     #17                 // Field titleMedium:Landroidx/glance/text/TextStyle;
-        59: bipush        16
-        61: invokestatic  #32                 // Method androidx/compose/ui/unit/TextUnitKt.getSp:(I)J
-        64: lstore_0
-        65: getstatic     #37                 // Field com/example/compose/jetchat/widget/theme/JetchatGlanceColorScheme.INSTANCE:Lcom/example/compose/jetchat/widget/theme/JetchatGlanceColorScheme;
-        68: invokevirtual #41                 // Method com/example/compose/jetchat/widget/theme/JetchatGlanceColorScheme.getColors:()Landroidx/glance/color/ColorProviders;
-        71: invokevirtual #47                 // Method androidx/glance/color/ColorProviders.getOnSurfaceVariant:()Landroidx/glance/unit/ColorProvider;
-        74: astore_2
-        75: getstatic     #53                 // Field androidx/glance/text/FontWeight.Companion:Landroidx/glance/text/FontWeight$Companion;
-        78: invokevirtual #76                 // Method androidx/glance/text/FontWeight$Companion."getNormal-WjrlUT0":()I
-        81: istore_3
-        82: new           #61                 // class androidx/glance/text/TextStyle
-        85: dup
-        86: aload_2
-        87: lload_0
-        88: invokestatic  #67                 // Method androidx/compose/ui/unit/TextUnit."box-impl":(J)Landroidx/compose/ui/unit/TextUnit;
-        91: iload_3
-        92: invokestatic  #70                 // Method androidx/glance/text/FontWeight."box-impl":(I)Landroidx/glance/text/FontWeight;
-        95: aconst_null
-        96: aconst_null
-        97: aconst_null
-        98: aconst_null
-        99: bipush        120
-       101: aconst_null
-       102: invokespecial #73                 // Method androidx/glance/text/TextStyle."<init>":(Landroidx/glance/unit/ColorProvider;Landroidx/compose/ui/unit/TextUnit;Landroidx/glance/text/FontWeight;Landroidx/glance/text/FontStyle;Landroidx/glance/text/TextAlign;Landroidx/glance/text/TextDecoration;Landroidx/glance/text/FontFamily;ILkotlin/jvm/internal/DefaultConstructorMarker;)V
-       105: putstatic     #21                 // Field bodyMedium:Landroidx/glance/text/TextStyle;
-       108: return
+         4: invokespecial #14                 // Method "<init>":()V
+         7: putstatic     #16                 // Field INSTANCE:Lcom/example/compose/jetchat/widget/theme/JetChatGlanceTextStyles;
+        10: return
+
+  public com.example.compose.jetchat.widget.theme.JetChatGlanceTextStyles();
+    Code:
+         0: aload_0
+         1: invokespecial #17                 // Method java/lang/Object."<init>":()V
+         4: return
 }
