--- ./gradle/com.example.compose.jetchat.conversation.ConversationUiState.javap	2026-05-25 11:17:33
+++ ./skotch/com.example.compose.jetchat.conversation.ConversationUiState.javap	2026-05-25 11:17:33
@@ -1,76 +1,94 @@
-Compiled from "ConversationUiState.kt"
+Compiled from "com/example/compose/jetchat/conversation/ConversationUiState.kt"
 public final class com.example.compose.jetchat.conversation.ConversationUiState {
-  private final java.lang.String channelName;
+  public java.lang.String channelName;
 
-  private final int channelMembers;
+  public int channelMembers;
 
-  private final java.util.List<com.example.compose.jetchat.conversation.Message> _messages;
+  public java.util.List _messages;
 
-  private final java.util.List<com.example.compose.jetchat.conversation.Message> messages;
+  public java.util.List messages;
 
   public static final int $stable;
 
-  public com.example.compose.jetchat.conversation.ConversationUiState(java.lang.String, int, java.util.List<com.example.compose.jetchat.conversation.Message>);
+  public com.example.compose.jetchat.conversation.ConversationUiState(java.lang.String, int, java.util.List);
     Code:
-         0: aload_1
-         1: ldc           #10                 // String channelName
-         3: invokestatic  #16                 // Method kotlin/jvm/internal/Intrinsics.checkNotNullParameter:(Ljava/lang/Object;Ljava/lang/String;)V
-         6: aload_3
-         7: ldc           #18                 // String initialMessages
-         9: invokestatic  #16                 // Method kotlin/jvm/internal/Intrinsics.checkNotNullParameter:(Ljava/lang/Object;Ljava/lang/String;)V
-        12: aload_0
-        13: invokespecial #21                 // Method java/lang/Object."<init>":()V
-        16: aload_0
-        17: aload_1
-        18: putfield      #24                 // Field channelName:Ljava/lang/String;
-        21: aload_0
-        22: iload_2
-        23: putfield      #28                 // Field channelMembers:I
+         0: aload_0
+         1: invokespecial #20                 // Method java/lang/Object."<init>":()V
+         4: aload_0
+         5: aload_1
+         6: putfield      #22                 // Field channelName:Ljava/lang/String;
+         9: aload_0
+        10: iload_2
+        11: putfield      #24                 // Field channelMembers:I
+        14: aload_0
+        15: aload_3
+        16: putfield      #27                 // Field initialMessages:Ljava/util/List;
+        19: aload_3
+        20: checkcast     #29                 // class java/util/Collection
+        23: invokestatic  #35                 // Method androidx/compose/runtime/SnapshotStateKt.toMutableStateList:(Ljava/util/Collection;)Landroidx/compose/runtime/snapshots/SnapshotStateList;
         26: aload_0
-        27: aload_3
-        28: checkcast     #30                 // class java/util/Collection
-        31: invokestatic  #36                 // Method androidx/compose/runtime/SnapshotStateKt.toMutableStateList:(Ljava/util/Collection;)Landroidx/compose/runtime/snapshots/SnapshotStateList;
-        34: checkcast     #38                 // class java/util/List
-        37: putfield      #42                 // Field _messages:Ljava/util/List;
-        40: aload_0
+        27: swap
+        28: putfield      #37                 // Field _messages:Ljava/util/List;
+        31: aload_0
+        32: getfield      #37                 // Field _messages:Ljava/util/List;
+        35: aload_0
+        36: swap
+        37: putfield      #39                 // Field messages:Ljava/util/List;
+        40: return
+
+  public void addMessage(com.example.compose.jetchat.conversation.Message);
+    Code:
+         0: aload_0
+         1: getfield      #22                 // Field channelName:Ljava/lang/String;
+         4: astore_2
+         5: aload_0
+         6: getfield      #24                 // Field channelMembers:I
+         9: istore_3
+        10: aload_0
+        11: getfield      #37                 // Field _messages:Ljava/util/List;
+        14: astore        4
+        16: aload_0
+        17: getfield      #39                 // Field messages:Ljava/util/List;
+        20: astore        5
+        22: aload         4
+        24: iconst_0
+        25: aload_1
+        26: invokeinterface #49,  3           // InterfaceMethod java/util/List.add:(ILjava/lang/Object;)V
+        31: aload_0
+        32: aload_2
+        33: putfield      #22                 // Field channelName:Ljava/lang/String;
+        36: aload_0
+        37: iload_3
+        38: putfield      #24                 // Field channelMembers:I
         41: aload_0
-        42: getfield      #42                 // Field _messages:Ljava/util/List;
-        45: putfield      #45                 // Field messages:Ljava/util/List;
-        48: return
+        42: aload         4
+        44: putfield      #37                 // Field _messages:Ljava/util/List;
+        47: aload_0
+        48: aload         5
+        50: putfield      #39                 // Field messages:Ljava/util/List;
+        53: return
 
-  public final java.lang.String getChannelName();
+  public java.lang.String getChannelName();
     Code:
          0: aload_0
-         1: getfield      #24                 // Field channelName:Ljava/lang/String;
+         1: getfield      #22                 // Field channelName:Ljava/lang/String;
          4: areturn
 
-  public final int getChannelMembers();
+  public int getChannelMembers();
     Code:
          0: aload_0
-         1: getfield      #28                 // Field channelMembers:I
+         1: getfield      #24                 // Field channelMembers:I
          4: ireturn
 
-  public final java.util.List<com.example.compose.jetchat.conversation.Message> getMessages();
+  public <T> java.util.List get_messages();
     Code:
          0: aload_0
-         1: getfield      #45                 // Field messages:Ljava/util/List;
+         1: getfield      #37                 // Field _messages:Ljava/util/List;
          4: areturn
 
-  public final void addMessage(com.example.compose.jetchat.conversation.Message);
+  public <T> java.util.List getMessages();
     Code:
-         0: aload_1
-         1: ldc           #58                 // String msg
-         3: invokestatic  #16                 // Method kotlin/jvm/internal/Intrinsics.checkNotNullParameter:(Ljava/lang/Object;Ljava/lang/String;)V
-         6: aload_0
-         7: getfield      #42                 // Field _messages:Ljava/util/List;
-        10: iconst_0
-        11: aload_1
-        12: invokeinterface #62,  3           // InterfaceMethod java/util/List.add:(ILjava/lang/Object;)V
-        17: return
-
-  static {};
-    Code:
-         0: bipush        8
-         2: putstatic     #67                 // Field $stable:I
-         5: return
+         0: aload_0
+         1: getfield      #39                 // Field messages:Ljava/util/List;
+         4: areturn
 }
