--- ./gradle/com.example.compose.jetchat.data.FakeDataKt.javap	2026-05-25 11:17:37
+++ ./skotch/com.example.compose.jetchat.data.FakeDataKt.javap	2026-05-25 11:17:37
@@ -1,8 +1,8 @@
-Compiled from "FakeData.kt"
+Compiled from "com/example/compose/jetchat/data/FakeData.kt"
 public final class com.example.compose.jetchat.data.FakeDataKt {
-  private static final java.util.List<com.example.compose.jetchat.conversation.Message> initialMessages;
+  private static final java.lang.Object initialMessages;
 
-  private static final java.util.List<com.example.compose.jetchat.conversation.Message> unreadMessages;
+  private static final java.lang.Object unreadMessages;
 
   private static final com.example.compose.jetchat.conversation.ConversationUiState exampleUiState;
 
@@ -10,24 +10,24 @@
 
   private static final com.example.compose.jetchat.profile.ProfileScreenState meProfile;
 
-  public static final java.util.List<com.example.compose.jetchat.conversation.Message> getInitialMessages();
+  public static final java.lang.Object getInitialMessages();
     Code:
-         0: getstatic     #12                 // Field initialMessages:Ljava/util/List;
+         0: getstatic     #16                 // Field initialMessages:Ljava/lang/Object;
          3: areturn
 
-  public static final java.util.List<com.example.compose.jetchat.conversation.Message> getUnreadMessages();
+  public static final java.lang.Object getUnreadMessages();
     Code:
-         0: getstatic     #16                 // Field unreadMessages:Ljava/util/List;
+         0: getstatic     #19                 // Field unreadMessages:Ljava/lang/Object;
          3: areturn
 
   public static final com.example.compose.jetchat.conversation.ConversationUiState getExampleUiState();
     Code:
-         0: getstatic     #22                 // Field exampleUiState:Lcom/example/compose/jetchat/conversation/ConversationUiState;
+         0: getstatic     #25                 // Field exampleUiState:Lcom/example/compose/jetchat/conversation/ConversationUiState;
          3: areturn
 
   public static final com.example.compose.jetchat.profile.ProfileScreenState getColleagueProfile();
     Code:
-         0: getstatic     #28                 // Field colleagueProfile:Lcom/example/compose/jetchat/profile/ProfileScreenState;
+         0: getstatic     #29                 // Field colleagueProfile:Lcom/example/compose/jetchat/profile/ProfileScreenState;
          3: areturn
 
   public static final com.example.compose.jetchat.profile.ProfileScreenState getMeProfile();
@@ -35,214 +35,224 @@
          0: getstatic     #32                 // Field meProfile:Lcom/example/compose/jetchat/profile/ProfileScreenState;
          3: areturn
 
-  static {};
+  public static final kotlin.Unit clinit$lambda$0(java.lang.Object);
     Code:
-         0: bipush        9
-         2: anewarray     #36                 // class com/example/compose/jetchat/conversation/Message
-         5: astore_0
+         0: getstatic     #40                 // Field kotlin/Unit.INSTANCE:Lkotlin/Unit;
+         3: areturn
+
+  public static final boolean clinit$lambda$1(com.example.compose.jetchat.conversation.Message);
+    Code:
+         0: aload_0
+         1: ldc           #44                 // String it
+         3: invokestatic  #50                 // Method kotlin/jvm/internal/Intrinsics.checkNotNullParameter:(Ljava/lang/Object;Ljava/lang/String;)V
          6: aload_0
-         7: iconst_0
-         8: new           #36                 // class com/example/compose/jetchat/conversation/Message
-        11: dup
-        12: ldc           #38                 // String me
-        14: ldc           #40                 // String Check it out!
-        16: ldc           #42                 // String 8:07 PM
+         7: getfield      #56                 // Field com/example/compose/jetchat/conversation/Message.author:Ljava/lang/String;
+        10: ldc           #58                 // String me
+        12: invokestatic  #62                 // Method kotlin/jvm/internal/Intrinsics.areEqual:(Ljava/lang/Object;Ljava/lang/Object;)Z
+        15: ifne          22
+        18: iconst_1
+        19: goto          23
+        22: iconst_0
+        23: ireturn
+
+  private static final {};
+    Code:
+         0: new           #52                 // class com/example/compose/jetchat/conversation/Message
+         3: dup
+         4: ldc           #58                 // String me
+         6: ldc           #67                 // String Check it out!
+         8: ldc           #69                 // String 8:07 PM
+        10: aconst_null
+        11: iconst_0
+        12: invokespecial #73                 // Method com/example/compose/jetchat/conversation/Message."<init>":(Ljava/lang/String;Ljava/lang/String;Ljava/lang/String;Ljava/lang/Integer;I)V
+        15: astore_0
+        16: ldc           #75                 // String Thank you!
         18: aconst_null
-        19: iconst_0
-        20: bipush        24
-        22: aconst_null
-        23: invokespecial #46                 // Method com/example/compose/jetchat/conversation/Message."<init>":(Ljava/lang/String;Ljava/lang/String;Ljava/lang/String;Ljava/lang/Integer;IILkotlin/jvm/internal/DefaultConstructorMarker;)V
-        26: aastore
-        27: aload_0
-        28: iconst_1
-        29: new           #36                 // class com/example/compose/jetchat/conversation/Message
-        32: dup
-        33: ldc           #38                 // String me
-        35: ldc           #48                 // String Thank you!🩷
-        37: ldc           #50                 // String 8:06 PM
-        39: getstatic     #56                 // Field com/example/compose/jetchat/R$drawable.sticker:I
-        42: invokestatic  #62                 // Method java/lang/Integer.valueOf:(I)Ljava/lang/Integer;
-        45: iconst_0
-        46: bipush        16
-        48: aconst_null
-        49: invokespecial #46                 // Method com/example/compose/jetchat/conversation/Message."<init>":(Ljava/lang/String;Ljava/lang/String;Ljava/lang/String;Ljava/lang/Integer;IILkotlin/jvm/internal/DefaultConstructorMarker;)V
-        52: aastore
-        53: aload_0
-        54: iconst_2
-        55: new           #36                 // class com/example/compose/jetchat/conversation/Message
-        58: dup
-        59: ldc           #64                 // String Taylor Brooks
-        61: ldc           #66                 // String You can use all the same stuff
-        63: ldc           #68                 // String 8:05 PM
-        65: aconst_null
-        66: iconst_0
-        67: bipush        24
-        69: aconst_null
-        70: invokespecial #46                 // Method com/example/compose/jetchat/conversation/Message."<init>":(Ljava/lang/String;Ljava/lang/String;Ljava/lang/String;Ljava/lang/Integer;IILkotlin/jvm/internal/DefaultConstructorMarker;)V
-        73: aastore
-        74: aload_0
-        75: iconst_3
-        76: new           #36                 // class com/example/compose/jetchat/conversation/Message
-        79: dup
-        80: ldc           #64                 // String Taylor Brooks
-        82: ldc           #70                 // String @aliconors Take a look at the `Flow.collectAsStateWithLifecycle()` APIs
-        84: ldc           #68                 // String 8:05 PM
-        86: aconst_null
-        87: iconst_0
-        88: bipush        24
-        90: aconst_null
-        91: invokespecial #46                 // Method com/example/compose/jetchat/conversation/Message."<init>":(Ljava/lang/String;Ljava/lang/String;Ljava/lang/String;Ljava/lang/Integer;IILkotlin/jvm/internal/DefaultConstructorMarker;)V
-        94: aastore
-        95: aload_0
-        96: iconst_4
-        97: new           #36                 // class com/example/compose/jetchat/conversation/Message
-       100: dup
-       101: ldc           #72                 // String John Glenn
-       103: ldc           #74                 // String Compose newbie as well 🦩, have you looked at the JetNews sample? Most blog posts end up out of date pretty fast but this sample is always up to date and deals with async data loading (it\'s faked but the same idea applies)  👉 https://goo.gle/jetnews
-       105: ldc           #76                 // String 8:04 PM
-       107: aconst_null
-       108: iconst_0
-       109: bipush        24
-       111: aconst_null
-       112: invokespecial #46                 // Method com/example/compose/jetchat/conversation/Message."<init>":(Ljava/lang/String;Ljava/lang/String;Ljava/lang/String;Ljava/lang/Integer;IILkotlin/jvm/internal/DefaultConstructorMarker;)V
-       115: aastore
-       116: aload_0
-       117: iconst_5
-       118: new           #36                 // class com/example/compose/jetchat/conversation/Message
+        19: invokestatic  #81                 // Method java/lang/String.valueOf:(Ljava/lang/Object;)Ljava/lang/String;
+        22: invokevirtual #85                 // Method java/lang/String.concat:(Ljava/lang/String;)Ljava/lang/String;
+        25: astore_1
+        26: new           #52                 // class com/example/compose/jetchat/conversation/Message
+        29: dup
+        30: ldc           #58                 // String me
+        32: aload_1
+        33: ldc           #87                 // String 8:06 PM
+        35: getstatic     #93                 // Field com/example/compose/jetchat/R$drawable.sticker:I
+        38: invokestatic  #98                 // Method java/lang/Integer.valueOf:(I)Ljava/lang/Integer;
+        41: iconst_0
+        42: invokespecial #73                 // Method com/example/compose/jetchat/conversation/Message."<init>":(Ljava/lang/String;Ljava/lang/String;Ljava/lang/String;Ljava/lang/Integer;I)V
+        45: astore_1
+        46: new           #52                 // class com/example/compose/jetchat/conversation/Message
+        49: dup
+        50: ldc           #100                // String Taylor Brooks
+        52: ldc           #102                // String You can use all the same stuff
+        54: ldc           #104                // String 8:05 PM
+        56: aconst_null
+        57: iconst_0
+        58: invokespecial #73                 // Method com/example/compose/jetchat/conversation/Message."<init>":(Ljava/lang/String;Ljava/lang/String;Ljava/lang/String;Ljava/lang/Integer;I)V
+        61: astore_2
+        62: new           #52                 // class com/example/compose/jetchat/conversation/Message
+        65: dup
+        66: ldc           #100                // String Taylor Brooks
+        68: ldc           #106                // String @aliconors Take a look at the `Flow.collectAsStateWithLifecycle()` APIs
+        70: ldc           #104                // String 8:05 PM
+        72: aconst_null
+        73: iconst_0
+        74: invokespecial #73                 // Method com/example/compose/jetchat/conversation/Message."<init>":(Ljava/lang/String;Ljava/lang/String;Ljava/lang/String;Ljava/lang/Integer;I)V
+        77: astore_3
+        78: ldc           #108                // String Compose newbie as well
+        80: aconst_null
+        81: invokestatic  #81                 // Method java/lang/String.valueOf:(Ljava/lang/Object;)Ljava/lang/String;
+        84: invokevirtual #85                 // Method java/lang/String.concat:(Ljava/lang/String;)Ljava/lang/String;
+        87: invokedynamic #119,  0            // InvokeDynamic #0:makeConcatWithConstants:(Ljava/lang/String;)Ljava/lang/String;
+        92: astore        4
+        94: ldc           #121                // String applies)
+        96: aconst_null
+        97: invokestatic  #81                 // Method java/lang/String.valueOf:(Ljava/lang/Object;)Ljava/lang/String;
+       100: invokevirtual #85                 // Method java/lang/String.concat:(Ljava/lang/String;)Ljava/lang/String;
+       103: invokedynamic #124,  0            // InvokeDynamic #1:makeConcatWithConstants:(Ljava/lang/String;)Ljava/lang/String;
+       108: aload         4
+       110: swap
+       111: invokedynamic #129,  0            // InvokeDynamic #2:makeConcatWithConstants:(Ljava/lang/String;Ljava/lang/String;)Ljava/lang/String;
+       116: astore        4
+       118: new           #52                 // class com/example/compose/jetchat/conversation/Message
        121: dup
-       122: ldc           #38                 // String me
-       124: ldc           #78                 // String Compose newbie: I’ve scourged the internet for tutorials about async data loading but haven’t found any good ones 🫠 😶‍🌫️. What’s the recommended way to load async data and emit composable widgets?
-       126: ldc           #80                 // String 8:03 PM
+       122: ldc           #131                // String John Glenn
+       124: aload         4
+       126: ldc           #133                // String 8:04 PM
        128: aconst_null
        129: iconst_0
-       130: bipush        24
-       132: aconst_null
-       133: invokespecial #46                 // Method com/example/compose/jetchat/conversation/Message."<init>":(Ljava/lang/String;Ljava/lang/String;Ljava/lang/String;Ljava/lang/Integer;IILkotlin/jvm/internal/DefaultConstructorMarker;)V
-       136: aastore
-       137: aload_0
-       138: bipush        6
-       140: new           #36                 // class com/example/compose/jetchat/conversation/Message
-       143: dup
-       144: ldc           #82                 // String Shangeeth Sivan
-       146: ldc           #84                 // String Does anyone know about Glance Widgets its the new way to build widgets in Android!
-       148: ldc           #86                 // String 8:08 PM
-       150: aconst_null
-       151: iconst_0
-       152: bipush        24
-       154: aconst_null
-       155: invokespecial #46                 // Method com/example/compose/jetchat/conversation/Message."<init>":(Ljava/lang/String;Ljava/lang/String;Ljava/lang/String;Ljava/lang/Integer;IILkotlin/jvm/internal/DefaultConstructorMarker;)V
-       158: aastore
-       159: aload_0
-       160: bipush        7
-       162: new           #36                 // class com/example/compose/jetchat/conversation/Message
-       165: dup
-       166: ldc           #64                 // String Taylor Brooks
-       168: ldc           #88                 // String Wow! I never knew about Glance Widgets when was this added to the android ecosystem
-       170: ldc           #90                 // String 8:10 PM
-       172: aconst_null
-       173: iconst_0
-       174: bipush        24
-       176: aconst_null
-       177: invokespecial #46                 // Method com/example/compose/jetchat/conversation/Message."<init>":(Ljava/lang/String;Ljava/lang/String;Ljava/lang/String;Ljava/lang/Integer;IILkotlin/jvm/internal/DefaultConstructorMarker;)V
-       180: aastore
-       181: aload_0
-       182: bipush        8
-       184: new           #36                 // class com/example/compose/jetchat/conversation/Message
-       187: dup
-       188: ldc           #72                 // String John Glenn
-       190: ldc           #92                 // String Yeah its seems to be pretty new!
-       192: ldc           #94                 // String 8:12 PM
-       194: aconst_null
-       195: iconst_0
-       196: bipush        24
-       198: aconst_null
-       199: invokespecial #46                 // Method com/example/compose/jetchat/conversation/Message."<init>":(Ljava/lang/String;Ljava/lang/String;Ljava/lang/String;Ljava/lang/Integer;IILkotlin/jvm/internal/DefaultConstructorMarker;)V
-       202: aastore
-       203: aload_0
-       204: invokestatic  #100                // Method kotlin/collections/CollectionsKt.listOf:([Ljava/lang/Object;)Ljava/util/List;
-       207: putstatic     #12                 // Field initialMessages:Ljava/util/List;
-       210: getstatic     #12                 // Field initialMessages:Ljava/util/List;
-       213: checkcast     #102                // class java/lang/Iterable
-       216: astore_0
-       217: iconst_0
-       218: istore_1
-       219: aload_0
-       220: astore_2
-       221: new           #104                // class java/util/ArrayList
-       224: dup
-       225: invokespecial #106                // Method java/util/ArrayList."<init>":()V
-       228: checkcast     #108                // class java/util/Collection
-       231: astore_3
-       232: iconst_0
-       233: istore        4
-       235: aload_2
-       236: invokeinterface #112,  1          // InterfaceMethod java/lang/Iterable.iterator:()Ljava/util/Iterator;
-       241: astore        5
-       243: aload         5
-       245: invokeinterface #118,  1          // InterfaceMethod java/util/Iterator.hasNext:()Z
-       250: ifeq          305
-       253: aload         5
-       255: invokeinterface #122,  1          // InterfaceMethod java/util/Iterator.next:()Ljava/lang/Object;
-       260: astore        6
-       262: aload         6
-       264: checkcast     #36                 // class com/example/compose/jetchat/conversation/Message
-       267: astore        7
-       269: iconst_0
-       270: istore        8
-       272: aload         7
-       274: invokevirtual #126                // Method com/example/compose/jetchat/conversation/Message.getAuthor:()Ljava/lang/String;
-       277: ldc           #38                 // String me
-       279: invokestatic  #132                // Method kotlin/jvm/internal/Intrinsics.areEqual:(Ljava/lang/Object;Ljava/lang/Object;)Z
-       282: ifne          289
-       285: iconst_1
-       286: goto          290
-       289: iconst_0
-       290: ifeq          243
-       293: aload_3
-       294: aload         6
-       296: invokeinterface #136,  2          // InterfaceMethod java/util/Collection.add:(Ljava/lang/Object;)Z
-       301: pop
-       302: goto          243
-       305: aload_3
-       306: checkcast     #138                // class java/util/List
-       309: nop
-       310: putstatic     #16                 // Field unreadMessages:Ljava/util/List;
-       313: getstatic     #12                 // Field initialMessages:Ljava/util/List;
-       316: astore_0
-       317: new           #140                // class com/example/compose/jetchat/conversation/ConversationUiState
-       320: dup
-       321: ldc           #142                // String #composers
-       323: bipush        42
-       325: aload_0
-       326: invokespecial #145                // Method com/example/compose/jetchat/conversation/ConversationUiState."<init>":(Ljava/lang/String;ILjava/util/List;)V
-       329: putstatic     #22                 // Field exampleUiState:Lcom/example/compose/jetchat/conversation/ConversationUiState;
-       332: new           #147                // class com/example/compose/jetchat/profile/ProfileScreenState
-       335: dup
-       336: ldc           #149                // String 12345
-       338: getstatic     #152                // Field com/example/compose/jetchat/R$drawable.someone_else:I
-       341: invokestatic  #62                 // Method java/lang/Integer.valueOf:(I)Ljava/lang/Integer;
-       344: ldc           #64                 // String Taylor Brooks
-       346: ldc           #154                // String Away
-       348: ldc           #156                // String taylor
-       350: ldc           #158                // String Senior Android Dev at Openlane
-       352: ldc           #160                // String twitter.com/taylorbrookscodes
-       354: ldc           #162                // String 12:25 AM local time (Eastern Daylight Time)
-       356: ldc           #164                // String 2
-       358: invokespecial #167                // Method com/example/compose/jetchat/profile/ProfileScreenState."<init>":(Ljava/lang/String;Ljava/lang/Integer;Ljava/lang/String;Ljava/lang/String;Ljava/lang/String;Ljava/lang/String;Ljava/lang/String;Ljava/lang/String;Ljava/lang/String;)V
-       361: putstatic     #28                 // Field colleagueProfile:Lcom/example/compose/jetchat/profile/ProfileScreenState;
-       364: new           #147                // class com/example/compose/jetchat/profile/ProfileScreenState
-       367: dup
-       368: ldc           #38                 // String me
-       370: getstatic     #170                // Field com/example/compose/jetchat/R$drawable.ali:I
-       373: invokestatic  #62                 // Method java/lang/Integer.valueOf:(I)Ljava/lang/Integer;
-       376: ldc           #172                // String Ali Conors
-       378: ldc           #174                // String Online
-       380: ldc           #176                // String aliconors
-       382: ldc           #178                // String Senior Android Dev at Yearin\nGoogle Developer Expert
-       384: ldc           #180                // String twitter.com/aliconors
-       386: ldc           #182                // String In your timezone
-       388: aconst_null
-       389: invokespecial #167                // Method com/example/compose/jetchat/profile/ProfileScreenState."<init>":(Ljava/lang/String;Ljava/lang/Integer;Ljava/lang/String;Ljava/lang/String;Ljava/lang/String;Ljava/lang/String;Ljava/lang/String;Ljava/lang/String;Ljava/lang/String;)V
-       392: putstatic     #32                 // Field meProfile:Lcom/example/compose/jetchat/profile/ProfileScreenState;
-       395: return
+       130: invokespecial #73                 // Method com/example/compose/jetchat/conversation/Message."<init>":(Ljava/lang/String;Ljava/lang/String;Ljava/lang/String;Ljava/lang/Integer;I)V
+       133: astore        4
+       135: ldc           #135                // String loading but haven’t found any good ones
+       137: aconst_null
+       138: invokestatic  #81                 // Method java/lang/String.valueOf:(Ljava/lang/Object;)Ljava/lang/String;
+       141: invokevirtual #85                 // Method java/lang/String.concat:(Ljava/lang/String;)Ljava/lang/String;
+       144: invokedynamic #138,  0            // InvokeDynamic #3:makeConcatWithConstants:(Ljava/lang/String;)Ljava/lang/String;
+       149: aconst_null
+       150: invokestatic  #81                 // Method java/lang/String.valueOf:(Ljava/lang/Object;)Ljava/lang/String;
+       153: invokevirtual #85                 // Method java/lang/String.concat:(Ljava/lang/String;)Ljava/lang/String;
+       156: invokedynamic #141,  0            // InvokeDynamic #4:makeConcatWithConstants:(Ljava/lang/String;)Ljava/lang/String;
+       161: invokedynamic #144,  0            // InvokeDynamic #5:makeConcatWithConstants:(Ljava/lang/String;)Ljava/lang/String;
+       166: astore        5
+       168: new           #52                 // class com/example/compose/jetchat/conversation/Message
+       171: dup
+       172: ldc           #58                 // String me
+       174: aload         5
+       176: ldc           #146                // String 8:03 PM
+       178: aconst_null
+       179: iconst_0
+       180: invokespecial #73                 // Method com/example/compose/jetchat/conversation/Message."<init>":(Ljava/lang/String;Ljava/lang/String;Ljava/lang/String;Ljava/lang/Integer;I)V
+       183: astore        5
+       185: new           #52                 // class com/example/compose/jetchat/conversation/Message
+       188: dup
+       189: ldc           #148                // String Shangeeth Sivan
+       191: ldc           #150                // String Does anyone know about Glance Widgets its the new way to build widgets in Android!
+       193: ldc           #152                // String 8:08 PM
+       195: aconst_null
+       196: iconst_0
+       197: invokespecial #73                 // Method com/example/compose/jetchat/conversation/Message."<init>":(Ljava/lang/String;Ljava/lang/String;Ljava/lang/String;Ljava/lang/Integer;I)V
+       200: astore        6
+       202: new           #52                 // class com/example/compose/jetchat/conversation/Message
+       205: dup
+       206: ldc           #100                // String Taylor Brooks
+       208: ldc           #154                // String Wow! I never knew about Glance Widgets when was this added to the android ecosystem
+       210: ldc           #156                // String 8:10 PM
+       212: aconst_null
+       213: iconst_0
+       214: invokespecial #73                 // Method com/example/compose/jetchat/conversation/Message."<init>":(Ljava/lang/String;Ljava/lang/String;Ljava/lang/String;Ljava/lang/Integer;I)V
+       217: astore        7
+       219: new           #52                 // class com/example/compose/jetchat/conversation/Message
+       222: dup
+       223: ldc           #131                // String John Glenn
+       225: ldc           #158                // String Yeah its seems to be pretty new!
+       227: ldc           #160                // String 8:12 PM
+       229: aconst_null
+       230: iconst_0
+       231: invokespecial #73                 // Method com/example/compose/jetchat/conversation/Message."<init>":(Ljava/lang/String;Ljava/lang/String;Ljava/lang/String;Ljava/lang/Integer;I)V
+       234: astore        8
+       236: bipush        9
+       238: anewarray     #4                  // class java/lang/Object
+       241: astore        9
+       243: aload         9
+       245: iconst_0
+       246: aload_0
+       247: aastore
+       248: aload         9
+       250: iconst_1
+       251: aload_1
+       252: aastore
+       253: aload         9
+       255: iconst_2
+       256: aload_2
+       257: aastore
+       258: aload         9
+       260: iconst_3
+       261: aload_3
+       262: aastore
+       263: aload         9
+       265: iconst_4
+       266: aload         4
+       268: aastore
+       269: aload         9
+       271: iconst_5
+       272: aload         5
+       274: aastore
+       275: aload         9
+       277: bipush        6
+       279: aload         6
+       281: aastore
+       282: aload         9
+       284: bipush        7
+       286: aload         7
+       288: aastore
+       289: aload         9
+       291: bipush        8
+       293: aload         8
+       295: aastore
+       296: aload         9
+       298: invokestatic  #166                // Method kotlin/collections/CollectionsKt.listOf:([Ljava/lang/Object;)Ljava/util/List;
+       301: putstatic     #16                 // Field initialMessages:Ljava/lang/Object;
+       304: invokedynamic #183,  0            // InvokeDynamic #6:invoke:()Lkotlin/jvm/functions/Function1;
+       309: astore_0
+       310: invokedynamic #189,  0            // InvokeDynamic #7:invoke:()Lkotlin/jvm/functions/Function1;
+       315: getstatic     #16                 // Field initialMessages:Ljava/lang/Object;
+       318: swap
+       319: invokestatic  #193                // Method kotlin/collections/CollectionsKt.filter:(Ljava/lang/Iterable;Lkotlin/jvm/functions/Function1;)Ljava/util/List;
+       322: putstatic     #19                 // Field unreadMessages:Ljava/lang/Object;
+       325: new           #195                // class com/example/compose/jetchat/conversation/ConversationUiState
+       328: dup
+       329: ldc           #197                // String #composers
+       331: bipush        42
+       333: getstatic     #16                 // Field initialMessages:Ljava/lang/Object;
+       336: invokespecial #200                // Method com/example/compose/jetchat/conversation/ConversationUiState."<init>":(Ljava/lang/String;ILjava/lang/Object;)V
+       339: putstatic     #25                 // Field exampleUiState:Lcom/example/compose/jetchat/conversation/ConversationUiState;
+       342: new           #202                // class com/example/compose/jetchat/profile/ProfileScreenState
+       345: dup
+       346: ldc           #204                // String 12345
+       348: getstatic     #207                // Field com/example/compose/jetchat/R$drawable.someone_else:I
+       351: invokestatic  #98                 // Method java/lang/Integer.valueOf:(I)Ljava/lang/Integer;
+       354: ldc           #100                // String Taylor Brooks
+       356: ldc           #209                // String Away
+       358: ldc           #211                // String taylor
+       360: ldc           #213                // String Senior Android Dev at Openlane
+       362: ldc           #215                // String twitter.com/taylorbrookscodes
+       364: ldc           #217                // String 12:25 AM local time (Eastern Daylight Time)
+       366: ldc           #219                // String 2
+       368: invokespecial #222                // Method com/example/compose/jetchat/profile/ProfileScreenState."<init>":(Ljava/lang/String;Ljava/lang/Integer;Ljava/lang/String;Ljava/lang/String;Ljava/lang/String;Ljava/lang/String;Ljava/lang/String;Ljava/lang/String;Ljava/lang/String;)V
+       371: putstatic     #29                 // Field colleagueProfile:Lcom/example/compose/jetchat/profile/ProfileScreenState;
+       374: new           #202                // class com/example/compose/jetchat/profile/ProfileScreenState
+       377: dup
+       378: ldc           #58                 // String me
+       380: getstatic     #225                // Field com/example/compose/jetchat/R$drawable.ali:I
+       383: invokestatic  #98                 // Method java/lang/Integer.valueOf:(I)Ljava/lang/Integer;
+       386: ldc           #227                // String Ali Conors
+       388: ldc           #229                // String Online
+       390: ldc           #231                // String aliconors
+       392: ldc           #233                // String Senior Android Dev at Yearin\nGoogle Developer Expert
+       394: ldc           #235                // String twitter.com/aliconors
+       396: ldc           #237                // String In your timezone
+       398: aconst_null
+       399: invokespecial #222                // Method com/example/compose/jetchat/profile/ProfileScreenState."<init>":(Ljava/lang/String;Ljava/lang/Integer;Ljava/lang/String;Ljava/lang/String;Ljava/lang/String;Ljava/lang/String;Ljava/lang/String;Ljava/lang/String;Ljava/lang/String;)V
+       402: putstatic     #32                 // Field meProfile:Lcom/example/compose/jetchat/profile/ProfileScreenState;
+       405: return
 }
