--- ./gradle/com.example.compose.jetchat.components.BaseLineHeightModifierKt.javap	2026-05-21 07:24:24
+++ ./skotch/com.example.compose.jetchat.components.BaseLineHeightModifierKt.javap	2026-05-21 07:24:24
@@ -1,17 +1,25 @@
-Compiled from "BaseLineHeightModifier.kt"
+Compiled from "com/example/compose/jetchat/components/BaseLineHeightModifier.kt"
 public final class com.example.compose.jetchat.components.BaseLineHeightModifierKt {
-  public static final androidx.compose.ui.Modifier baselineHeight-3ABfNKs(androidx.compose.ui.Modifier, float);
+  public static final androidx.compose.ui.Modifier baselineHeight(androidx.compose.ui.Modifier, androidx.compose.ui.unit.Dp);
     Code:
          0: aload_0
-         1: ldc           #9                  // String $this$baselineHeight
+         1: ldc           #9                  // String <this>
          3: invokestatic  #15                 // Method kotlin/jvm/internal/Intrinsics.checkNotNullParameter:(Ljava/lang/Object;Ljava/lang/String;)V
-         6: aload_0
-         7: new           #17                 // class com/example/compose/jetchat/components/BaselineHeightModifier
-        10: dup
-        11: fload_1
-        12: aconst_null
-        13: invokespecial #21                 // Method com/example/compose/jetchat/components/BaselineHeightModifier."<init>":(FLkotlin/jvm/internal/DefaultConstructorMarker;)V
-        16: checkcast     #23                 // class androidx/compose/ui/Modifier
-        19: invokeinterface #27,  2           // InterfaceMethod androidx/compose/ui/Modifier.then:(Landroidx/compose/ui/Modifier;)Landroidx/compose/ui/Modifier;
-        24: areturn
+         6: aload_1
+         7: ldc           #17                 // String heightFromBaseline
+         9: invokestatic  #15                 // Method kotlin/jvm/internal/Intrinsics.checkNotNullParameter:(Ljava/lang/Object;Ljava/lang/String;)V
+        12: new           #19                 // class com/example/compose/jetchat/components/BaselineHeightModifier
+        15: dup
+        16: aload_1
+        17: invokespecial #23                 // Method com/example/compose/jetchat/components/BaselineHeightModifier."<init>":(Landroidx/compose/ui/unit/Dp;)V
+        20: pop
+        21: new           #19                 // class com/example/compose/jetchat/components/BaselineHeightModifier
+        24: dup
+        25: aload_1
+        26: invokespecial #23                 // Method com/example/compose/jetchat/components/BaselineHeightModifier."<init>":(Landroidx/compose/ui/unit/Dp;)V
+        29: aload_0
+        30: swap
+        31: invokeinterface #29,  2           // InterfaceMethod androidx/compose/ui/Modifier.then:(Landroidx/compose/ui/Modifier;)Landroidx/compose/ui/Modifier;
+        36: checkcast     #25                 // class androidx/compose/ui/Modifier
+        39: areturn
 }
