--- ./gradle/com.example.compose.jetchat.components.AnimatingFabContentKt.javap	2026-05-21 07:24:23
+++ ./skotch/com.example.compose.jetchat.components.AnimatingFabContentKt.javap	2026-05-21 07:24:23
@@ -1,1861 +1,300 @@
-Compiled from "AnimatingFabContent.kt"
-public final class com.example.compose.jetchat.components.AnimatingFabContentKt {
-  private static final int transitionDuration;
-
-  public static final void AnimatingFabContent(kotlin.jvm.functions.Function2<? super androidx.compose.runtime.Composer, ? super java.lang.Integer, kotlin.Unit>, kotlin.jvm.functions.Function2<? super androidx.compose.runtime.Composer, ? super java.lang.Integer, kotlin.Unit>, androidx.compose.ui.Modifier, boolean, androidx.compose.runtime.Composer, int, int);
-    Code:
-         0: aload_0
-         1: ldc           #15                 // String icon
-         3: invokestatic  #21                 // Method kotlin/jvm/internal/Intrinsics.checkNotNullParameter:(Ljava/lang/Object;Ljava/lang/String;)V
-         6: aload_1
-         7: ldc           #23                 // String text
-         9: invokestatic  #21                 // Method kotlin/jvm/internal/Intrinsics.checkNotNullParameter:(Ljava/lang/Object;Ljava/lang/String;)V
-        12: aload         4
-        14: ldc           #24                 // int -134210841
-        16: invokeinterface #30,  2           // InterfaceMethod androidx/compose/runtime/Composer.startRestartGroup:(I)Landroidx/compose/runtime/Composer;
-        21: astore        4
-        23: aload         4
-        25: ldc           #32                 // String C(AnimatingFabContent)N(icon,text,modifier,extended)45@1711L48,47@1795L777,70@2610L616,97@3402L15,98@3427L18,94@3350L131:AnimatingFabContent.kt#o9oqao
-        27: invokestatic  #38                 // Method androidx/compose/runtime/ComposerKt.sourceInformation:(Landroidx/compose/runtime/Composer;Ljava/lang/String;)V
-        30: iload         5
-        32: istore        7
-        34: iload         5
-        36: bipush        6
-        38: iand
-        39: ifne          63
-        42: iload         7
-        44: aload         4
-        46: aload_0
-        47: invokeinterface #42,  2           // InterfaceMethod androidx/compose/runtime/Composer.changedInstance:(Ljava/lang/Object;)Z
-        52: ifeq          59
-        55: iconst_4
-        56: goto          60
-        59: iconst_2
-        60: ior
-        61: istore        7
-        63: iload         5
-        65: bipush        48
-        67: iand
-        68: ifne          94
-        71: iload         7
-        73: aload         4
-        75: aload_1
-        76: invokeinterface #42,  2           // InterfaceMethod androidx/compose/runtime/Composer.changedInstance:(Ljava/lang/Object;)Z
-        81: ifeq          89
-        84: bipush        32
-        86: goto          91
-        89: bipush        16
-        91: ior
-        92: istore        7
-        94: iload         6
-        96: iconst_4
-        97: iand
-        98: ifeq          112
-       101: iload         7
-       103: sipush        384
-       106: ior
-       107: istore        7
-       109: goto          146
-       112: iload         5
-       114: sipush        384
-       117: iand
-       118: ifne          146
-       121: iload         7
-       123: aload         4
-       125: aload_2
-       126: invokeinterface #45,  2           // InterfaceMethod androidx/compose/runtime/Composer.changed:(Ljava/lang/Object;)Z
-       131: ifeq          140
-       134: sipush        256
-       137: goto          143
-       140: sipush        128
-       143: ior
-       144: istore        7
-       146: iload         6
-       148: bipush        8
-       150: iand
-       151: ifeq          165
-       154: iload         7
-       156: sipush        3072
-       159: ior
-       160: istore        7
-       162: goto          199
-       165: iload         5
-       167: sipush        3072
-       170: iand
-       171: ifne          199
-       174: iload         7
-       176: aload         4
-       178: iload_3
-       179: invokeinterface #48,  2           // InterfaceMethod androidx/compose/runtime/Composer.changed:(Z)Z
-       184: ifeq          193
-       187: sipush        2048
-       190: goto          196
-       193: sipush        1024
-       196: ior
-       197: istore        7
-       199: aload         4
-       201: iload         7
-       203: sipush        1171
-       206: iand
-       207: sipush        1170
-       210: if_icmpeq     217
-       213: iconst_1
-       214: goto          218
-       217: iconst_0
-       218: iload         7
-       220: iconst_1
-       221: iand
-       222: invokeinterface #52,  3           // InterfaceMethod androidx/compose/runtime/Composer.shouldExecute:(ZI)Z
-       227: ifeq          2418
-       230: iload         6
-       232: iconst_4
-       233: iand
-       234: ifeq          244
-       237: getstatic     #58                 // Field androidx/compose/ui/Modifier.Companion:Landroidx/compose/ui/Modifier$Companion;
-       240: checkcast     #54                 // class androidx/compose/ui/Modifier
-       243: astore_2
-       244: iload         6
-       246: bipush        8
-       248: iand
-       249: ifeq          254
-       252: iconst_1
-       253: istore_3
-       254: invokestatic  #62                 // Method androidx/compose/runtime/ComposerKt.isTraceInProgress:()Z
-       257: ifeq          270
-       260: ldc           #24                 // int -134210841
-       262: iload         7
-       264: iconst_m1
-       265: ldc           #64                 // String com.example.compose.jetchat.components.AnimatingFabContent (AnimatingFabContent.kt:43)
-       267: invokestatic  #68                 // Method androidx/compose/runtime/ComposerKt.traceEventStart:(IIILjava/lang/String;)V
-       270: iload_3
-       271: ifeq          280
-       274: getstatic     #74                 // Field com/example/compose/jetchat/components/ExpandableFabStates.Extended:Lcom/example/compose/jetchat/components/ExpandableFabStates;
-       277: goto          283
-       280: getstatic     #77                 // Field com/example/compose/jetchat/components/ExpandableFabStates.Collapsed:Lcom/example/compose/jetchat/components/ExpandableFabStates;
-       283: astore        8
-       285: aload         8
-       287: ldc           #79                 // String fab_transition
-       289: aload         4
-       291: bipush        48
-       293: iconst_0
-       294: invokestatic  #85                 // Method androidx/compose/animation/core/TransitionKt.updateTransition:(Ljava/lang/Object;Ljava/lang/String;Landroidx/compose/runtime/Composer;II)Landroidx/compose/animation/core/Transition;
-       297: astore        9
-       299: aload         9
-       301: astore        11
-       303: invokedynamic #105,  0            // InvokeDynamic #0:invoke:()Lkotlin/jvm/functions/Function3;
-       308: astore        12
-       310: ldc           #107                // String fab_text_opacity
-       312: astore        13
-       314: aload         4
-       316: astore        14
-       318: sipush        384
-       321: istore        15
-       323: nop
-       324: iconst_0
-       325: istore        16
-       327: aload         14
-       329: ldc           #108                // int 844118987
-       331: ldc           #110                // String CC(animateFloat)N(transitionSpec,label,targetValueByState)1951@83597L78:Transition.kt#pdpnli
-       333: invokestatic  #114                // Method androidx/compose/runtime/ComposerKt.sourceInformationMarkerStart:(Landroidx/compose/runtime/Composer;ILjava/lang/String;)V
-       336: aload         11
-       338: astore        17
-       340: getstatic     #120                // Field kotlin/jvm/internal/FloatCompanionObject.INSTANCE:Lkotlin/jvm/internal/FloatCompanionObject;
-       343: invokestatic  #126                // Method androidx/compose/animation/core/VectorConvertersKt.getVectorConverter:(Lkotlin/jvm/internal/FloatCompanionObject;)Landroidx/compose/animation/core/TwoWayConverter;
-       346: astore        18
-       348: aload         12
-       350: astore        19
-       352: aload         13
-       354: astore        20
-       356: aload         14
-       358: astore        21
-       360: bipush        14
-       362: iload         15
-       364: iand
-       365: sipush        896
-       368: iload         15
-       370: iconst_3
-       371: ishl
-       372: iand
-       373: ior
-       374: sipush        7168
-       377: iload         15
-       379: iconst_3
-       380: ishl
-       381: iand
-       382: ior
-       383: ldc           #127                // int 57344
-       385: iload         15
-       387: iconst_3
-       388: ishl
-       389: iand
-       390: ior
-       391: istore        22
-       393: iconst_0
-       394: istore        23
-       396: aload         21
-       398: ldc           #128                // int 1143035377
-       400: ldc           #130                // String CC(animateValue)N(typeConverter,transitionSpec,label,targetValueByState)1848@78638L32,1855@79111L49,1855@79092L75,1856@79207L45,1856@79192L67,1858@79272L89:Transition.kt#pdpnli
-       402: invokestatic  #114                // Method androidx/compose/runtime/ComposerKt.sourceInformationMarkerStart:(Landroidx/compose/runtime/Composer;ILjava/lang/String;)V
-       405: aload         17
-       407: invokevirtual #135                // Method androidx/compose/animation/core/Transition.isSeeking:()Z
-       410: ifne          643
-       413: aload         21
-       415: ldc           #136                // int 1666573488
-       417: invokeinterface #140,  2          // InterfaceMethod androidx/compose/runtime/Composer.startReplaceGroup:(I)V
-       422: aload         21
-       424: ldc           #142                // String 1844@78495L67
-       426: invokestatic  #38                 // Method androidx/compose/runtime/ComposerKt.sourceInformation:(Landroidx/compose/runtime/Composer;Ljava/lang/String;)V
-       429: aload         21
-       431: ldc           #143                // int -1054612652
-       433: ldc           #145                // String CC(remember):Transition.kt#9igjgp
-       435: invokestatic  #114                // Method androidx/compose/runtime/ComposerKt.sourceInformationMarkerStart:(Landroidx/compose/runtime/Composer;ILjava/lang/String;)V
-       438: aload         21
-       440: astore        24
-       442: iload         22
-       444: bipush        14
-       446: iand
-       447: bipush        6
-       449: ixor
-       450: iconst_4
-       451: if_icmple     466
-       454: aload         21
-       456: aload         17
-       458: invokeinterface #45,  2           // InterfaceMethod androidx/compose/runtime/Composer.changed:(Ljava/lang/Object;)Z
-       463: ifne          475
-       466: iload         22
-       468: bipush        6
-       470: iand
-       471: iconst_4
-       472: if_icmpne     479
-       475: iconst_1
-       476: goto          480
-       479: iconst_0
-       480: istore        25
-       482: iconst_0
-       483: istore        26
-       485: aload         24
-       487: invokeinterface #149,  1          // InterfaceMethod androidx/compose/runtime/Composer.rememberedValue:()Ljava/lang/Object;
-       492: astore        27
-       494: iconst_0
-       495: istore        28
-       497: iload         25
-       499: ifne          513
-       502: aload         27
-       504: getstatic     #152                // Field androidx/compose/runtime/Composer.Companion:Landroidx/compose/runtime/Composer$Companion;
-       507: invokevirtual #157                // Method androidx/compose/runtime/Composer$Companion.getEmpty:()Ljava/lang/Object;
-       510: if_acmpne     616
-       513: iconst_0
-       514: istore        29
-       516: getstatic     #162                // Field androidx/compose/runtime/snapshots/Snapshot.Companion:Landroidx/compose/runtime/snapshots/Snapshot$Companion;
-       519: astore        30
-       521: iconst_0
-       522: istore        31
-       524: aload         30
-       526: invokevirtual #168                // Method androidx/compose/runtime/snapshots/Snapshot$Companion.getCurrentThreadSnapshot:()Landroidx/compose/runtime/snapshots/Snapshot;
-       529: astore        32
-       531: aload         32
-       533: dup
-       534: ifnull        543
-       537: invokevirtual #172                // Method androidx/compose/runtime/snapshots/Snapshot.getReadObserver:()Lkotlin/jvm/functions/Function1;
-       540: goto          545
-       543: pop
-       544: aconst_null
-       545: astore        33
-       547: aload         30
-       549: aload         32
-       551: invokevirtual #176                // Method androidx/compose/runtime/snapshots/Snapshot$Companion.makeCurrentNonObservable:(Landroidx/compose/runtime/snapshots/Snapshot;)Landroidx/compose/runtime/snapshots/Snapshot;
-       554: astore        34
-       556: nop
-       557: iconst_0
-       558: istore        35
-       560: aload         17
-       562: invokevirtual #179                // Method androidx/compose/animation/core/Transition.getCurrentState:()Ljava/lang/Object;
-       565: astore        35
-       567: aload         30
-       569: aload         32
-       571: aload         34
-       573: aload         33
-       575: invokevirtual #183                // Method androidx/compose/runtime/snapshots/Snapshot$Companion.restoreNonObservable:(Landroidx/compose/runtime/snapshots/Snapshot;Landroidx/compose/runtime/snapshots/Snapshot;Lkotlin/jvm/functions/Function1;)V
-       578: aload         35
-       580: goto          599
-       583: astore        36
-       585: aload         30
-       587: aload         32
-       589: aload         34
-       591: aload         33
-       593: invokevirtual #183                // Method androidx/compose/runtime/snapshots/Snapshot$Companion.restoreNonObservable:(Landroidx/compose/runtime/snapshots/Snapshot;Landroidx/compose/runtime/snapshots/Snapshot;Lkotlin/jvm/functions/Function1;)V
-       596: aload         36
-       598: athrow
-       599: nop
-       600: astore        37
-       602: aload         24
-       604: aload         37
-       606: invokeinterface #187,  2          // InterfaceMethod androidx/compose/runtime/Composer.updateRememberedValue:(Ljava/lang/Object;)V
-       611: aload         37
-       613: goto          618
-       616: aload         27
-       618: nop
-       619: nop
-       620: astore        38
-       622: aload         21
-       624: invokestatic  #191                // Method androidx/compose/runtime/ComposerKt.sourceInformationMarkerEnd:(Landroidx/compose/runtime/Composer;)V
-       627: aload         38
-       629: astore        39
-       631: aload         21
-       633: invokeinterface #195,  1          // InterfaceMethod androidx/compose/runtime/Composer.endReplaceGroup:()V
-       638: aload         39
-       640: goto          664
-       643: aload         21
-       645: ldc           #196                // int 1666827533
-       647: invokeinterface #140,  2          // InterfaceMethod androidx/compose/runtime/Composer.startReplaceGroup:(I)V
-       652: aload         21
-       654: invokeinterface #195,  1          // InterfaceMethod androidx/compose/runtime/Composer.endReplaceGroup:()V
-       659: aload         17
-       661: invokevirtual #179                // Method androidx/compose/animation/core/Transition.getCurrentState:()Ljava/lang/Object;
-       664: astore        40
-       666: aload         40
-       668: aload         21
-       670: bipush        112
-       672: iload         22
-       674: bipush        9
-       676: ishr
-       677: iand
-       678: istore        41
-       680: astore        42
-       682: checkcast     #70                 // class com/example/compose/jetchat/components/ExpandableFabStates
-       685: astore        43
-       687: iconst_0
-       688: istore        44
-       690: aload         42
-       692: ldc           #197                // int -1900950268
-       694: invokeinterface #140,  2          // InterfaceMethod androidx/compose/runtime/Composer.startReplaceGroup:(I)V
-       699: aload         42
-       701: ldc           #199                // String CN(state):AnimatingFabContent.kt#o9oqao
-       703: invokestatic  #38                 // Method androidx/compose/runtime/ComposerKt.sourceInformation:(Landroidx/compose/runtime/Composer;Ljava/lang/String;)V
-       706: invokestatic  #62                 // Method androidx/compose/runtime/ComposerKt.isTraceInProgress:()Z
-       709: ifeq          722
-       712: ldc           #197                // int -1900950268
-       714: iload         41
-       716: iconst_m1
-       717: ldc           #201                // String com.example.compose.jetchat.components.AnimatingFabContent.<anonymous> (AnimatingFabContent.kt:64)
-       719: invokestatic  #68                 // Method androidx/compose/runtime/ComposerKt.traceEventStart:(IIILjava/lang/String;)V
-       722: aload         43
-       724: getstatic     #77                 // Field com/example/compose/jetchat/components/ExpandableFabStates.Collapsed:Lcom/example/compose/jetchat/components/ExpandableFabStates;
-       727: if_acmpne     734
-       730: fconst_0
-       731: goto          735
-       734: fconst_1
-       735: fstore        45
-       737: invokestatic  #62                 // Method androidx/compose/runtime/ComposerKt.isTraceInProgress:()Z
-       740: ifeq          746
-       743: invokestatic  #204                // Method androidx/compose/runtime/ComposerKt.traceEventEnd:()V
-       746: aload         42
-       748: invokeinterface #195,  1          // InterfaceMethod androidx/compose/runtime/Composer.endReplaceGroup:()V
-       753: fload         45
-       755: nop
-       756: invokestatic  #210                // Method java/lang/Float.valueOf:(F)Ljava/lang/Float;
-       759: astore        39
-       761: aload         21
-       763: ldc           #211                // int -1054592958
-       765: ldc           #145                // String CC(remember):Transition.kt#9igjgp
-       767: invokestatic  #114                // Method androidx/compose/runtime/ComposerKt.sourceInformationMarkerStart:(Landroidx/compose/runtime/Composer;ILjava/lang/String;)V
-       770: aload         21
-       772: astore        25
-       774: iload         22
-       776: bipush        14
-       778: iand
-       779: bipush        6
-       781: ixor
-       782: iconst_4
-       783: if_icmple     798
-       786: aload         21
-       788: aload         17
-       790: invokeinterface #45,  2           // InterfaceMethod androidx/compose/runtime/Composer.changed:(Ljava/lang/Object;)Z
-       795: ifne          807
-       798: iload         22
-       800: bipush        6
-       802: iand
-       803: iconst_4
-       804: if_icmpne     811
-       807: iconst_1
-       808: goto          812
-       811: iconst_0
-       812: istore        26
-       814: iconst_0
-       815: istore        27
-       817: aload         25
-       819: invokeinterface #149,  1          // InterfaceMethod androidx/compose/runtime/Composer.rememberedValue:()Ljava/lang/Object;
-       824: astore        28
-       826: iconst_0
-       827: istore        29
-       829: iload         26
-       831: ifne          845
-       834: aload         28
-       836: getstatic     #152                // Field androidx/compose/runtime/Composer.Companion:Landroidx/compose/runtime/Composer$Companion;
-       839: invokevirtual #157                // Method androidx/compose/runtime/Composer$Companion.getEmpty:()Ljava/lang/Object;
-       842: if_acmpne     879
-       845: iconst_0
-       846: istore        30
-       848: new           #213                // class com/example/compose/jetchat/components/AnimatingFabContentKt$AnimatingFabContent$$inlined$animateFloat$1
-       851: dup
-       852: aload         17
-       854: invokespecial #217                // Method com/example/compose/jetchat/components/AnimatingFabContentKt$AnimatingFabContent$$inlined$animateFloat$1."<init>":(Landroidx/compose/animation/core/Transition;)V
-       857: checkcast     #219                // class kotlin/jvm/functions/Function0
-       860: invokestatic  #225                // Method androidx/compose/runtime/SnapshotStateKt.derivedStateOf:(Lkotlin/jvm/functions/Function0;)Landroidx/compose/runtime/State;
-       863: astore        31
-       865: aload         25
-       867: aload         31
-       869: invokeinterface #187,  2          // InterfaceMethod androidx/compose/runtime/Composer.updateRememberedValue:(Ljava/lang/Object;)V
-       874: aload         31
-       876: goto          881
-       879: aload         28
-       881: nop
-       882: nop
-       883: checkcast     #227                // class androidx/compose/runtime/State
-       886: astore        24
-       888: aload         21
-       890: invokestatic  #191                // Method androidx/compose/runtime/ComposerKt.sourceInformationMarkerEnd:(Landroidx/compose/runtime/Composer;)V
-       893: aload         24
-       895: invokeinterface #230,  1          // InterfaceMethod androidx/compose/runtime/State.getValue:()Ljava/lang/Object;
-       900: aload         21
-       902: bipush        112
-       904: iload         22
-       906: bipush        9
-       908: ishr
-       909: iand
-       910: istore        41
-       912: astore        42
-       914: checkcast     #70                 // class com/example/compose/jetchat/components/ExpandableFabStates
-       917: astore        43
-       919: iconst_0
-       920: istore        44
-       922: aload         42
-       924: ldc           #197                // int -1900950268
-       926: invokeinterface #140,  2          // InterfaceMethod androidx/compose/runtime/Composer.startReplaceGroup:(I)V
-       931: aload         42
-       933: ldc           #199                // String CN(state):AnimatingFabContent.kt#o9oqao
-       935: invokestatic  #38                 // Method androidx/compose/runtime/ComposerKt.sourceInformation:(Landroidx/compose/runtime/Composer;Ljava/lang/String;)V
-       938: invokestatic  #62                 // Method androidx/compose/runtime/ComposerKt.isTraceInProgress:()Z
-       941: ifeq          954
-       944: ldc           #197                // int -1900950268
-       946: iload         41
-       948: iconst_m1
-       949: ldc           #201                // String com.example.compose.jetchat.components.AnimatingFabContent.<anonymous> (AnimatingFabContent.kt:64)
-       951: invokestatic  #68                 // Method androidx/compose/runtime/ComposerKt.traceEventStart:(IIILjava/lang/String;)V
-       954: aload         43
-       956: getstatic     #77                 // Field com/example/compose/jetchat/components/ExpandableFabStates.Collapsed:Lcom/example/compose/jetchat/components/ExpandableFabStates;
-       959: if_acmpne     966
-       962: fconst_0
-       963: goto          967
-       966: fconst_1
-       967: fstore        45
-       969: invokestatic  #62                 // Method androidx/compose/runtime/ComposerKt.isTraceInProgress:()Z
-       972: ifeq          978
-       975: invokestatic  #204                // Method androidx/compose/runtime/ComposerKt.traceEventEnd:()V
-       978: aload         42
-       980: invokeinterface #195,  1          // InterfaceMethod androidx/compose/runtime/Composer.endReplaceGroup:()V
-       985: fload         45
-       987: nop
-       988: invokestatic  #210                // Method java/lang/Float.valueOf:(F)Ljava/lang/Float;
-       991: astore        38
-       993: aload         19
-       995: aload         21
-       997: ldc           #231                // int -1054589890
-       999: ldc           #145                // String CC(remember):Transition.kt#9igjgp
-      1001: invokestatic  #114                // Method androidx/compose/runtime/ComposerKt.sourceInformationMarkerStart:(Landroidx/compose/runtime/Composer;ILjava/lang/String;)V
-      1004: aload         21
-      1006: astore        26
-      1008: iload         22
-      1010: bipush        14
-      1012: iand
-      1013: bipush        6
-      1015: ixor
-      1016: iconst_4
-      1017: if_icmple     1032
-      1020: aload         21
-      1022: aload         17
-      1024: invokeinterface #45,  2           // InterfaceMethod androidx/compose/runtime/Composer.changed:(Ljava/lang/Object;)Z
-      1029: ifne          1041
-      1032: iload         22
-      1034: bipush        6
-      1036: iand
-      1037: iconst_4
-      1038: if_icmpne     1045
-      1041: iconst_1
-      1042: goto          1046
-      1045: iconst_0
-      1046: istore        27
-      1048: iconst_0
-      1049: istore        28
-      1051: aload         26
-      1053: invokeinterface #149,  1          // InterfaceMethod androidx/compose/runtime/Composer.rememberedValue:()Ljava/lang/Object;
-      1058: astore        29
-      1060: iconst_0
-      1061: istore        30
-      1063: iload         27
-      1065: ifne          1079
-      1068: aload         29
-      1070: getstatic     #152                // Field androidx/compose/runtime/Composer.Companion:Landroidx/compose/runtime/Composer$Companion;
-      1073: invokevirtual #157                // Method androidx/compose/runtime/Composer$Companion.getEmpty:()Ljava/lang/Object;
-      1076: if_acmpne     1118
-      1079: astore        43
-      1081: iconst_0
-      1082: istore        31
-      1084: new           #233                // class com/example/compose/jetchat/components/AnimatingFabContentKt$AnimatingFabContent$$inlined$animateFloat$2
-      1087: dup
-      1088: aload         17
-      1090: invokespecial #234                // Method com/example/compose/jetchat/components/AnimatingFabContentKt$AnimatingFabContent$$inlined$animateFloat$2."<init>":(Landroidx/compose/animation/core/Transition;)V
-      1093: checkcast     #219                // class kotlin/jvm/functions/Function0
-      1096: invokestatic  #225                // Method androidx/compose/runtime/SnapshotStateKt.derivedStateOf:(Lkotlin/jvm/functions/Function0;)Landroidx/compose/runtime/State;
-      1099: aload         43
-      1101: swap
-      1102: astore        32
-      1104: aload         26
-      1106: aload         32
-      1108: invokeinterface #187,  2          // InterfaceMethod androidx/compose/runtime/Composer.updateRememberedValue:(Ljava/lang/Object;)V
-      1113: aload         32
-      1115: goto          1120
-      1118: aload         29
-      1120: nop
-      1121: nop
-      1122: checkcast     #227                // class androidx/compose/runtime/State
-      1125: astore        25
-      1127: aload         21
-      1129: invokestatic  #191                // Method androidx/compose/runtime/ComposerKt.sourceInformationMarkerEnd:(Landroidx/compose/runtime/Composer;)V
-      1132: aload         25
-      1134: invokeinterface #230,  1          // InterfaceMethod androidx/compose/runtime/State.getValue:()Ljava/lang/Object;
-      1139: aload         21
-      1141: bipush        112
-      1143: iload         22
-      1145: iconst_3
-      1146: ishr
-      1147: iand
-      1148: invokestatic  #239                // Method java/lang/Integer.valueOf:(I)Ljava/lang/Integer;
-      1151: invokeinterface #243,  4          // InterfaceMethod kotlin/jvm/functions/Function3.invoke:(Ljava/lang/Object;Ljava/lang/Object;Ljava/lang/Object;)Ljava/lang/Object;
-      1156: checkcast     #245                // class androidx/compose/animation/core/FiniteAnimationSpec
-      1159: astore        24
-      1161: aload         17
-      1163: aload         39
-      1165: aload         38
-      1167: aload         24
-      1169: aload         18
-      1171: aload         20
-      1173: aload         21
-      1175: bipush        14
-      1177: iload         22
-      1179: iand
-      1180: ldc           #127                // int 57344
-      1182: iload         22
-      1184: bipush        9
-      1186: ishl
-      1187: iand
-      1188: ior
-      1189: ldc           #246                // int 458752
-      1191: iload         22
-      1193: bipush        6
-      1195: ishl
-      1196: iand
-      1197: ior
-      1198: invokestatic  #250                // Method androidx/compose/animation/core/TransitionKt.createTransitionAnimation:(Landroidx/compose/animation/core/Transition;Ljava/lang/Object;Ljava/lang/Object;Landroidx/compose/animation/core/FiniteAnimationSpec;Landroidx/compose/animation/core/TwoWayConverter;Ljava/lang/String;Landroidx/compose/runtime/Composer;I)Landroidx/compose/runtime/State;
-      1201: astore        25
-      1203: aload         21
-      1205: invokestatic  #191                // Method androidx/compose/runtime/ComposerKt.sourceInformationMarkerEnd:(Landroidx/compose/runtime/Composer;)V
-      1208: aload         25
-      1210: nop
-      1211: astore        46
-      1213: aload         14
-      1215: invokestatic  #191                // Method androidx/compose/runtime/ComposerKt.sourceInformationMarkerEnd:(Landroidx/compose/runtime/Composer;)V
-      1218: aload         46
-      1220: astore        10
-      1222: aload         9
-      1224: astore        12
-      1226: invokedynamic #255,  0            // InvokeDynamic #1:invoke:()Lkotlin/jvm/functions/Function3;
-      1231: astore        13
-      1233: ldc_w         #257                // String fab_width_factor
-      1236: astore        14
-      1238: aload         4
-      1240: astore        15
-      1242: sipush        384
-      1245: istore        16
-      1247: nop
-      1248: iconst_0
-      1249: istore        17
-      1251: aload         15
-      1253: ldc           #108                // int 844118987
-      1255: ldc           #110                // String CC(animateFloat)N(transitionSpec,label,targetValueByState)1951@83597L78:Transition.kt#pdpnli
-      1257: invokestatic  #114                // Method androidx/compose/runtime/ComposerKt.sourceInformationMarkerStart:(Landroidx/compose/runtime/Composer;ILjava/lang/String;)V
-      1260: aload         12
-      1262: astore        18
-      1264: getstatic     #120                // Field kotlin/jvm/internal/FloatCompanionObject.INSTANCE:Lkotlin/jvm/internal/FloatCompanionObject;
-      1267: invokestatic  #126                // Method androidx/compose/animation/core/VectorConvertersKt.getVectorConverter:(Lkotlin/jvm/internal/FloatCompanionObject;)Landroidx/compose/animation/core/TwoWayConverter;
-      1270: astore        19
-      1272: aload         13
-      1274: astore        20
-      1276: aload         14
-      1278: astore        21
-      1280: aload         15
-      1282: astore        22
-      1284: bipush        14
-      1286: iload         16
-      1288: iand
-      1289: sipush        896
-      1292: iload         16
-      1294: iconst_3
-      1295: ishl
-      1296: iand
-      1297: ior
-      1298: sipush        7168
-      1301: iload         16
-      1303: iconst_3
-      1304: ishl
-      1305: iand
-      1306: ior
-      1307: ldc           #127                // int 57344
-      1309: iload         16
-      1311: iconst_3
-      1312: ishl
-      1313: iand
-      1314: ior
-      1315: istore        23
-      1317: iconst_0
-      1318: istore        24
-      1320: aload         22
-      1322: ldc           #128                // int 1143035377
-      1324: ldc           #130                // String CC(animateValue)N(typeConverter,transitionSpec,label,targetValueByState)1848@78638L32,1855@79111L49,1855@79092L75,1856@79207L45,1856@79192L67,1858@79272L89:Transition.kt#pdpnli
-      1326: invokestatic  #114                // Method androidx/compose/runtime/ComposerKt.sourceInformationMarkerStart:(Landroidx/compose/runtime/Composer;ILjava/lang/String;)V
-      1329: aload         18
-      1331: invokevirtual #135                // Method androidx/compose/animation/core/Transition.isSeeking:()Z
-      1334: ifne          1567
-      1337: aload         22
-      1339: ldc           #136                // int 1666573488
-      1341: invokeinterface #140,  2          // InterfaceMethod androidx/compose/runtime/Composer.startReplaceGroup:(I)V
-      1346: aload         22
-      1348: ldc           #142                // String 1844@78495L67
-      1350: invokestatic  #38                 // Method androidx/compose/runtime/ComposerKt.sourceInformation:(Landroidx/compose/runtime/Composer;Ljava/lang/String;)V
-      1353: aload         22
-      1355: ldc           #143                // int -1054612652
-      1357: ldc           #145                // String CC(remember):Transition.kt#9igjgp
-      1359: invokestatic  #114                // Method androidx/compose/runtime/ComposerKt.sourceInformationMarkerStart:(Landroidx/compose/runtime/Composer;ILjava/lang/String;)V
-      1362: aload         22
-      1364: astore        25
-      1366: iload         23
-      1368: bipush        14
-      1370: iand
-      1371: bipush        6
-      1373: ixor
-      1374: iconst_4
-      1375: if_icmple     1390
-      1378: aload         22
-      1380: aload         18
-      1382: invokeinterface #45,  2           // InterfaceMethod androidx/compose/runtime/Composer.changed:(Ljava/lang/Object;)Z
-      1387: ifne          1399
-      1390: iload         23
-      1392: bipush        6
-      1394: iand
-      1395: iconst_4
-      1396: if_icmpne     1403
-      1399: iconst_1
-      1400: goto          1404
-      1403: iconst_0
-      1404: istore        26
-      1406: iconst_0
-      1407: istore        27
-      1409: aload         25
-      1411: invokeinterface #149,  1          // InterfaceMethod androidx/compose/runtime/Composer.rememberedValue:()Ljava/lang/Object;
-      1416: astore        28
-      1418: iconst_0
-      1419: istore        29
-      1421: iload         26
-      1423: ifne          1437
-      1426: aload         28
-      1428: getstatic     #152                // Field androidx/compose/runtime/Composer.Companion:Landroidx/compose/runtime/Composer$Companion;
-      1431: invokevirtual #157                // Method androidx/compose/runtime/Composer$Companion.getEmpty:()Ljava/lang/Object;
-      1434: if_acmpne     1540
-      1437: iconst_0
-      1438: istore        30
-      1440: getstatic     #162                // Field androidx/compose/runtime/snapshots/Snapshot.Companion:Landroidx/compose/runtime/snapshots/Snapshot$Companion;
-      1443: astore        31
-      1445: iconst_0
-      1446: istore        32
-      1448: aload         31
-      1450: invokevirtual #168                // Method androidx/compose/runtime/snapshots/Snapshot$Companion.getCurrentThreadSnapshot:()Landroidx/compose/runtime/snapshots/Snapshot;
-      1453: astore        33
-      1455: aload         33
-      1457: dup
-      1458: ifnull        1467
-      1461: invokevirtual #172                // Method androidx/compose/runtime/snapshots/Snapshot.getReadObserver:()Lkotlin/jvm/functions/Function1;
-      1464: goto          1469
-      1467: pop
-      1468: aconst_null
-      1469: astore        34
-      1471: aload         31
-      1473: aload         33
-      1475: invokevirtual #176                // Method androidx/compose/runtime/snapshots/Snapshot$Companion.makeCurrentNonObservable:(Landroidx/compose/runtime/snapshots/Snapshot;)Landroidx/compose/runtime/snapshots/Snapshot;
-      1478: astore        35
-      1480: nop
-      1481: iconst_0
-      1482: istore        36
-      1484: aload         18
-      1486: invokevirtual #179                // Method androidx/compose/animation/core/Transition.getCurrentState:()Ljava/lang/Object;
-      1489: astore        36
-      1491: aload         31
-      1493: aload         33
-      1495: aload         35
-      1497: aload         34
-      1499: invokevirtual #183                // Method androidx/compose/runtime/snapshots/Snapshot$Companion.restoreNonObservable:(Landroidx/compose/runtime/snapshots/Snapshot;Landroidx/compose/runtime/snapshots/Snapshot;Lkotlin/jvm/functions/Function1;)V
-      1502: aload         36
-      1504: goto          1523
-      1507: astore        37
-      1509: aload         31
-      1511: aload         33
-      1513: aload         35
-      1515: aload         34
-      1517: invokevirtual #183                // Method androidx/compose/runtime/snapshots/Snapshot$Companion.restoreNonObservable:(Landroidx/compose/runtime/snapshots/Snapshot;Landroidx/compose/runtime/snapshots/Snapshot;Lkotlin/jvm/functions/Function1;)V
-      1520: aload         37
-      1522: athrow
-      1523: nop
-      1524: astore        38
-      1526: aload         25
-      1528: aload         38
-      1530: invokeinterface #187,  2          // InterfaceMethod androidx/compose/runtime/Composer.updateRememberedValue:(Ljava/lang/Object;)V
-      1535: aload         38
-      1537: goto          1542
-      1540: aload         28
-      1542: nop
-      1543: nop
-      1544: astore        39
-      1546: aload         22
-      1548: invokestatic  #191                // Method androidx/compose/runtime/ComposerKt.sourceInformationMarkerEnd:(Landroidx/compose/runtime/Composer;)V
-      1551: aload         39
-      1553: astore        40
-      1555: aload         22
-      1557: invokeinterface #195,  1          // InterfaceMethod androidx/compose/runtime/Composer.endReplaceGroup:()V
-      1562: aload         40
-      1564: goto          1588
-      1567: aload         22
-      1569: ldc           #196                // int 1666827533
-      1571: invokeinterface #140,  2          // InterfaceMethod androidx/compose/runtime/Composer.startReplaceGroup:(I)V
-      1576: aload         22
-      1578: invokeinterface #195,  1          // InterfaceMethod androidx/compose/runtime/Composer.endReplaceGroup:()V
-      1583: aload         18
-      1585: invokevirtual #179                // Method androidx/compose/animation/core/Transition.getCurrentState:()Ljava/lang/Object;
-      1588: astore        41
-      1590: aload         41
-      1592: aload         22
-      1594: bipush        112
-      1596: iload         23
-      1598: bipush        9
-      1600: ishr
-      1601: iand
-      1602: istore        42
-      1604: astore        43
-      1606: checkcast     #70                 // class com/example/compose/jetchat/components/ExpandableFabStates
-      1609: astore        44
-      1611: iconst_0
-      1612: istore        45
-      1614: aload         43
-      1616: ldc_w         #258                // int -1760486974
-      1619: invokeinterface #140,  2          // InterfaceMethod androidx/compose/runtime/Composer.startReplaceGroup:(I)V
-      1624: aload         43
-      1626: ldc           #199                // String CN(state):AnimatingFabContent.kt#o9oqao
-      1628: invokestatic  #38                 // Method androidx/compose/runtime/ComposerKt.sourceInformation:(Landroidx/compose/runtime/Composer;Ljava/lang/String;)V
-      1631: invokestatic  #62                 // Method androidx/compose/runtime/ComposerKt.isTraceInProgress:()Z
-      1634: ifeq          1649
-      1637: ldc_w         #258                // int -1760486974
-      1640: iload         42
-      1642: iconst_m1
-      1643: ldc_w         #260                // String com.example.compose.jetchat.components.AnimatingFabContent.<anonymous> (AnimatingFabContent.kt:86)
-      1646: invokestatic  #68                 // Method androidx/compose/runtime/ComposerKt.traceEventStart:(IIILjava/lang/String;)V
-      1649: aload         44
-      1651: getstatic     #77                 // Field com/example/compose/jetchat/components/ExpandableFabStates.Collapsed:Lcom/example/compose/jetchat/components/ExpandableFabStates;
-      1654: if_acmpne     1661
-      1657: fconst_0
-      1658: goto          1662
-      1661: fconst_1
-      1662: fstore        46
-      1664: invokestatic  #62                 // Method androidx/compose/runtime/ComposerKt.isTraceInProgress:()Z
-      1667: ifeq          1673
-      1670: invokestatic  #204                // Method androidx/compose/runtime/ComposerKt.traceEventEnd:()V
-      1673: aload         43
-      1675: invokeinterface #195,  1          // InterfaceMethod androidx/compose/runtime/Composer.endReplaceGroup:()V
-      1680: fload         46
-      1682: nop
-      1683: invokestatic  #210                // Method java/lang/Float.valueOf:(F)Ljava/lang/Float;
-      1686: astore        40
-      1688: aload         22
-      1690: ldc           #211                // int -1054592958
-      1692: ldc           #145                // String CC(remember):Transition.kt#9igjgp
-      1694: invokestatic  #114                // Method androidx/compose/runtime/ComposerKt.sourceInformationMarkerStart:(Landroidx/compose/runtime/Composer;ILjava/lang/String;)V
-      1697: aload         22
-      1699: astore        26
-      1701: iload         23
-      1703: bipush        14
-      1705: iand
-      1706: bipush        6
-      1708: ixor
-      1709: iconst_4
-      1710: if_icmple     1725
-      1713: aload         22
-      1715: aload         18
-      1717: invokeinterface #45,  2           // InterfaceMethod androidx/compose/runtime/Composer.changed:(Ljava/lang/Object;)Z
-      1722: ifne          1734
-      1725: iload         23
-      1727: bipush        6
-      1729: iand
-      1730: iconst_4
-      1731: if_icmpne     1738
-      1734: iconst_1
-      1735: goto          1739
-      1738: iconst_0
-      1739: istore        27
-      1741: iconst_0
-      1742: istore        28
-      1744: aload         26
-      1746: invokeinterface #149,  1          // InterfaceMethod androidx/compose/runtime/Composer.rememberedValue:()Ljava/lang/Object;
-      1751: astore        29
-      1753: iconst_0
-      1754: istore        30
-      1756: iload         27
-      1758: ifne          1772
-      1761: aload         29
-      1763: getstatic     #152                // Field androidx/compose/runtime/Composer.Companion:Landroidx/compose/runtime/Composer$Companion;
-      1766: invokevirtual #157                // Method androidx/compose/runtime/Composer$Companion.getEmpty:()Ljava/lang/Object;
-      1769: if_acmpne     1806
-      1772: iconst_0
-      1773: istore        31
-      1775: new           #262                // class com/example/compose/jetchat/components/AnimatingFabContentKt$AnimatingFabContent$$inlined$animateFloat$3
-      1778: dup
-      1779: aload         18
-      1781: invokespecial #263                // Method com/example/compose/jetchat/components/AnimatingFabContentKt$AnimatingFabContent$$inlined$animateFloat$3."<init>":(Landroidx/compose/animation/core/Transition;)V
-      1784: checkcast     #219                // class kotlin/jvm/functions/Function0
-      1787: invokestatic  #225                // Method androidx/compose/runtime/SnapshotStateKt.derivedStateOf:(Lkotlin/jvm/functions/Function0;)Landroidx/compose/runtime/State;
-      1790: astore        32
-      1792: aload         26
-      1794: aload         32
-      1796: invokeinterface #187,  2          // InterfaceMethod androidx/compose/runtime/Composer.updateRememberedValue:(Ljava/lang/Object;)V
-      1801: aload         32
-      1803: goto          1808
-      1806: aload         29
-      1808: nop
-      1809: nop
-      1810: checkcast     #227                // class androidx/compose/runtime/State
-      1813: astore        25
-      1815: aload         22
-      1817: invokestatic  #191                // Method androidx/compose/runtime/ComposerKt.sourceInformationMarkerEnd:(Landroidx/compose/runtime/Composer;)V
-      1820: aload         25
-      1822: invokeinterface #230,  1          // InterfaceMethod androidx/compose/runtime/State.getValue:()Ljava/lang/Object;
-      1827: aload         22
-      1829: bipush        112
-      1831: iload         23
-      1833: bipush        9
-      1835: ishr
-      1836: iand
-      1837: istore        42
-      1839: astore        43
-      1841: checkcast     #70                 // class com/example/compose/jetchat/components/ExpandableFabStates
-      1844: astore        44
-      1846: iconst_0
-      1847: istore        45
-      1849: aload         43
-      1851: ldc_w         #258                // int -1760486974
-      1854: invokeinterface #140,  2          // InterfaceMethod androidx/compose/runtime/Composer.startReplaceGroup:(I)V
-      1859: aload         43
-      1861: ldc           #199                // String CN(state):AnimatingFabContent.kt#o9oqao
-      1863: invokestatic  #38                 // Method androidx/compose/runtime/ComposerKt.sourceInformation:(Landroidx/compose/runtime/Composer;Ljava/lang/String;)V
-      1866: invokestatic  #62                 // Method androidx/compose/runtime/ComposerKt.isTraceInProgress:()Z
-      1869: ifeq          1884
-      1872: ldc_w         #258                // int -1760486974
-      1875: iload         42
-      1877: iconst_m1
-      1878: ldc_w         #260                // String com.example.compose.jetchat.components.AnimatingFabContent.<anonymous> (AnimatingFabContent.kt:86)
-      1881: invokestatic  #68                 // Method androidx/compose/runtime/ComposerKt.traceEventStart:(IIILjava/lang/String;)V
-      1884: aload         44
-      1886: getstatic     #77                 // Field com/example/compose/jetchat/components/ExpandableFabStates.Collapsed:Lcom/example/compose/jetchat/components/ExpandableFabStates;
-      1889: if_acmpne     1896
-      1892: fconst_0
-      1893: goto          1897
-      1896: fconst_1
-      1897: fstore        46
-      1899: invokestatic  #62                 // Method androidx/compose/runtime/ComposerKt.isTraceInProgress:()Z
-      1902: ifeq          1908
-      1905: invokestatic  #204                // Method androidx/compose/runtime/ComposerKt.traceEventEnd:()V
-      1908: aload         43
-      1910: invokeinterface #195,  1          // InterfaceMethod androidx/compose/runtime/Composer.endReplaceGroup:()V
-      1915: fload         46
-      1917: nop
-      1918: invokestatic  #210                // Method java/lang/Float.valueOf:(F)Ljava/lang/Float;
-      1921: astore        39
-      1923: aload         20
-      1925: aload         22
-      1927: ldc           #231                // int -1054589890
-      1929: ldc           #145                // String CC(remember):Transition.kt#9igjgp
-      1931: invokestatic  #114                // Method androidx/compose/runtime/ComposerKt.sourceInformationMarkerStart:(Landroidx/compose/runtime/Composer;ILjava/lang/String;)V
-      1934: aload         22
-      1936: astore        27
-      1938: iload         23
-      1940: bipush        14
-      1942: iand
-      1943: bipush        6
-      1945: ixor
-      1946: iconst_4
-      1947: if_icmple     1962
-      1950: aload         22
-      1952: aload         18
-      1954: invokeinterface #45,  2           // InterfaceMethod androidx/compose/runtime/Composer.changed:(Ljava/lang/Object;)Z
-      1959: ifne          1971
-      1962: iload         23
-      1964: bipush        6
-      1966: iand
-      1967: iconst_4
-      1968: if_icmpne     1975
-      1971: iconst_1
-      1972: goto          1976
-      1975: iconst_0
-      1976: istore        28
-      1978: iconst_0
-      1979: istore        29
-      1981: aload         27
-      1983: invokeinterface #149,  1          // InterfaceMethod androidx/compose/runtime/Composer.rememberedValue:()Ljava/lang/Object;
-      1988: astore        30
-      1990: iconst_0
-      1991: istore        31
-      1993: iload         28
-      1995: ifne          2009
-      1998: aload         30
-      2000: getstatic     #152                // Field androidx/compose/runtime/Composer.Companion:Landroidx/compose/runtime/Composer$Companion;
-      2003: invokevirtual #157                // Method androidx/compose/runtime/Composer$Companion.getEmpty:()Ljava/lang/Object;
-      2006: if_acmpne     2048
-      2009: astore        44
-      2011: iconst_0
-      2012: istore        32
-      2014: new           #265                // class com/example/compose/jetchat/components/AnimatingFabContentKt$AnimatingFabContent$$inlined$animateFloat$4
-      2017: dup
-      2018: aload         18
-      2020: invokespecial #266                // Method com/example/compose/jetchat/components/AnimatingFabContentKt$AnimatingFabContent$$inlined$animateFloat$4."<init>":(Landroidx/compose/animation/core/Transition;)V
-      2023: checkcast     #219                // class kotlin/jvm/functions/Function0
-      2026: invokestatic  #225                // Method androidx/compose/runtime/SnapshotStateKt.derivedStateOf:(Lkotlin/jvm/functions/Function0;)Landroidx/compose/runtime/State;
-      2029: aload         44
-      2031: swap
-      2032: astore        33
-      2034: aload         27
-      2036: aload         33
-      2038: invokeinterface #187,  2          // InterfaceMethod androidx/compose/runtime/Composer.updateRememberedValue:(Ljava/lang/Object;)V
-      2043: aload         33
-      2045: goto          2050
-      2048: aload         30
-      2050: nop
-      2051: nop
-      2052: checkcast     #227                // class androidx/compose/runtime/State
-      2055: astore        26
-      2057: aload         22
-      2059: invokestatic  #191                // Method androidx/compose/runtime/ComposerKt.sourceInformationMarkerEnd:(Landroidx/compose/runtime/Composer;)V
-      2062: aload         26
-      2064: invokeinterface #230,  1          // InterfaceMethod androidx/compose/runtime/State.getValue:()Ljava/lang/Object;
-      2069: aload         22
-      2071: bipush        112
-      2073: iload         23
-      2075: iconst_3
-      2076: ishr
-      2077: iand
-      2078: invokestatic  #239                // Method java/lang/Integer.valueOf:(I)Ljava/lang/Integer;
-      2081: invokeinterface #243,  4          // InterfaceMethod kotlin/jvm/functions/Function3.invoke:(Ljava/lang/Object;Ljava/lang/Object;Ljava/lang/Object;)Ljava/lang/Object;
-      2086: checkcast     #245                // class androidx/compose/animation/core/FiniteAnimationSpec
-      2089: astore        25
-      2091: aload         18
-      2093: aload         40
-      2095: aload         39
-      2097: aload         25
-      2099: aload         19
-      2101: aload         21
-      2103: aload         22
-      2105: bipush        14
-      2107: iload         23
-      2109: iand
-      2110: ldc           #127                // int 57344
-      2112: iload         23
-      2114: bipush        9
-      2116: ishl
-      2117: iand
-      2118: ior
-      2119: ldc           #246                // int 458752
-      2121: iload         23
-      2123: bipush        6
-      2125: ishl
-      2126: iand
-      2127: ior
-      2128: invokestatic  #250                // Method androidx/compose/animation/core/TransitionKt.createTransitionAnimation:(Landroidx/compose/animation/core/Transition;Ljava/lang/Object;Ljava/lang/Object;Landroidx/compose/animation/core/FiniteAnimationSpec;Landroidx/compose/animation/core/TwoWayConverter;Ljava/lang/String;Landroidx/compose/runtime/Composer;I)Landroidx/compose/runtime/State;
-      2131: astore        26
-      2133: aload         22
-      2135: invokestatic  #191                // Method androidx/compose/runtime/ComposerKt.sourceInformationMarkerEnd:(Landroidx/compose/runtime/Composer;)V
-      2138: aload         26
-      2140: nop
-      2141: astore        47
-      2143: aload         15
-      2145: invokestatic  #191                // Method androidx/compose/runtime/ComposerKt.sourceInformationMarkerEnd:(Landroidx/compose/runtime/Composer;)V
-      2148: aload         47
-      2150: astore        11
-      2152: aload_0
-      2153: aload_1
-      2154: aload         4
-      2156: ldc_w         #267                // int -127536106
-      2159: ldc_w         #269                // String CC(remember):AnimatingFabContent.kt#9igjgp
-      2162: invokestatic  #114                // Method androidx/compose/runtime/ComposerKt.sourceInformationMarkerStart:(Landroidx/compose/runtime/Composer;ILjava/lang/String;)V
-      2165: aload         4
-      2167: astore        13
-      2169: aload         4
-      2171: aload         10
-      2173: invokeinterface #45,  2           // InterfaceMethod androidx/compose/runtime/Composer.changed:(Ljava/lang/Object;)Z
-      2178: istore        14
-      2180: iconst_0
-      2181: istore        15
-      2183: aload         13
-      2185: invokeinterface #149,  1          // InterfaceMethod androidx/compose/runtime/Composer.rememberedValue:()Ljava/lang/Object;
-      2190: astore        16
-      2192: iconst_0
-      2193: istore        17
-      2195: iload         14
-      2197: ifne          2211
-      2200: aload         16
-      2202: getstatic     #152                // Field androidx/compose/runtime/Composer.Companion:Landroidx/compose/runtime/Composer$Companion;
-      2205: invokevirtual #157                // Method androidx/compose/runtime/Composer$Companion.getEmpty:()Ljava/lang/Object;
-      2208: if_acmpne     2249
-      2211: astore        49
-      2213: astore        48
-      2215: iconst_0
-      2216: istore        18
-      2218: aload         10
-      2220: invokedynamic #280,  0            // InvokeDynamic #2:invoke:(Landroidx/compose/runtime/State;)Lkotlin/jvm/functions/Function0;
-      2225: astore        50
-      2227: aload         48
-      2229: aload         49
-      2231: aload         50
-      2233: astore        19
-      2235: aload         13
-      2237: aload         19
-      2239: invokeinterface #187,  2          // InterfaceMethod androidx/compose/runtime/Composer.updateRememberedValue:(Ljava/lang/Object;)V
-      2244: aload         19
-      2246: goto          2251
-      2249: aload         16
-      2251: nop
-      2252: nop
-      2253: checkcast     #219                // class kotlin/jvm/functions/Function0
-      2256: astore        12
-      2258: aload         4
-      2260: invokestatic  #191                // Method androidx/compose/runtime/ComposerKt.sourceInformationMarkerEnd:(Landroidx/compose/runtime/Composer;)V
-      2263: aload         12
-      2265: aload         4
-      2267: ldc_w         #281                // int -127535303
-      2270: ldc_w         #269                // String CC(remember):AnimatingFabContent.kt#9igjgp
-      2273: invokestatic  #114                // Method androidx/compose/runtime/ComposerKt.sourceInformationMarkerStart:(Landroidx/compose/runtime/Composer;ILjava/lang/String;)V
-      2276: aload         4
-      2278: astore        13
-      2280: aload         4
-      2282: aload         11
-      2284: invokeinterface #45,  2           // InterfaceMethod androidx/compose/runtime/Composer.changed:(Ljava/lang/Object;)Z
-      2289: istore        14
-      2291: iconst_0
-      2292: istore        15
-      2294: aload         13
-      2296: invokeinterface #149,  1          // InterfaceMethod androidx/compose/runtime/Composer.rememberedValue:()Ljava/lang/Object;
-      2301: astore        16
-      2303: iconst_0
-      2304: istore        17
-      2306: iload         14
-      2308: ifne          2322
-      2311: aload         16
-      2313: getstatic     #152                // Field androidx/compose/runtime/Composer.Companion:Landroidx/compose/runtime/Composer$Companion;
-      2316: invokevirtual #157                // Method androidx/compose/runtime/Composer$Companion.getEmpty:()Ljava/lang/Object;
-      2319: if_acmpne     2364
-      2322: astore        50
-      2324: astore        49
-      2326: astore        48
-      2328: iconst_0
-      2329: istore        18
-      2331: aload         11
-      2333: invokedynamic #286,  0            // InvokeDynamic #3:invoke:(Landroidx/compose/runtime/State;)Lkotlin/jvm/functions/Function0;
-      2338: astore        51
-      2340: aload         48
-      2342: aload         49
-      2344: aload         50
-      2346: aload         51
-      2348: astore        19
-      2350: aload         13
-      2352: aload         19
-      2354: invokeinterface #187,  2          // InterfaceMethod androidx/compose/runtime/Composer.updateRememberedValue:(Ljava/lang/Object;)V
-      2359: aload         19
-      2361: goto          2366
-      2364: aload         16
-      2366: nop
-      2367: nop
-      2368: checkcast     #219                // class kotlin/jvm/functions/Function0
-      2371: astore        12
-      2373: aload         4
-      2375: invokestatic  #191                // Method androidx/compose/runtime/ComposerKt.sourceInformationMarkerEnd:(Landroidx/compose/runtime/Composer;)V
-      2378: aload         12
-      2380: aload_2
-      2381: aload         4
-      2383: bipush        14
-      2385: iload         7
-      2387: iand
-      2388: bipush        112
-      2390: iload         7
-      2392: iand
-      2393: ior
-      2394: ldc           #127                // int 57344
-      2396: iload         7
-      2398: bipush        6
-      2400: ishl
-      2401: iand
-      2402: ior
-      2403: invokestatic  #290                // Method IconAndTextRow:(Lkotlin/jvm/functions/Function2;Lkotlin/jvm/functions/Function2;Lkotlin/jvm/functions/Function0;Lkotlin/jvm/functions/Function0;Landroidx/compose/ui/Modifier;Landroidx/compose/runtime/Composer;I)V
-      2406: invokestatic  #62                 // Method androidx/compose/runtime/ComposerKt.isTraceInProgress:()Z
-      2409: ifeq          2425
-      2412: invokestatic  #204                // Method androidx/compose/runtime/ComposerKt.traceEventEnd:()V
-      2415: goto          2425
-      2418: aload         4
-      2420: invokeinterface #293,  1          // InterfaceMethod androidx/compose/runtime/Composer.skipToGroupEnd:()V
-      2425: aload         4
-      2427: invokeinterface #297,  1          // InterfaceMethod androidx/compose/runtime/Composer.endRestartGroup:()Landroidx/compose/runtime/ScopeUpdateScope;
-      2432: dup
-      2433: ifnull        2457
-      2436: aload_0
-      2437: aload_1
-      2438: aload_2
-      2439: iload_3
-      2440: iload         5
-      2442: iload         6
-      2444: invokedynamic #309,  0            // InvokeDynamic #4:invoke:(Lkotlin/jvm/functions/Function2;Lkotlin/jvm/functions/Function2;Landroidx/compose/ui/Modifier;ZII)Lkotlin/jvm/functions/Function2;
-      2449: invokeinterface #315,  2          // InterfaceMethod androidx/compose/runtime/ScopeUpdateScope.updateScope:(Lkotlin/jvm/functions/Function2;)V
-      2454: goto          2458
-      2457: pop
-      2458: return
-      Exception table:
-         from    to  target type
-           556   567   583   any
-           583   585   583   any
-          1480  1491  1507   any
-          1507  1509  1507   any
-
-  private static final void IconAndTextRow(kotlin.jvm.functions.Function2<? super androidx.compose.runtime.Composer, ? super java.lang.Integer, kotlin.Unit>, kotlin.jvm.functions.Function2<? super androidx.compose.runtime.Composer, ? super java.lang.Integer, kotlin.Unit>, kotlin.jvm.functions.Function0<java.lang.Float>, kotlin.jvm.functions.Function0<java.lang.Float>, androidx.compose.ui.Modifier, androidx.compose.runtime.Composer, int);
-    Code:
-         0: aload         5
-         2: ldc_w         #468                // int -965203272
-         5: invokeinterface #30,  2           // InterfaceMethod androidx/compose/runtime/Composer.startRestartGroup:(I)Landroidx/compose/runtime/Composer;
-        10: astore        5
-        12: aload         5
-        14: ldc_w         #470                // String C(IconAndTextRow)N(icon,text,opacityProgress,widthProgress,modifier)119@3948L1150,111@3735L1363:AnimatingFabContent.kt#o9oqao
-        17: invokestatic  #38                 // Method androidx/compose/runtime/ComposerKt.sourceInformation:(Landroidx/compose/runtime/Composer;Ljava/lang/String;)V
-        20: iload         6
-        22: istore        7
-        24: iload         6
-        26: bipush        6
-        28: iand
-        29: ifne          53
-        32: iload         7
-        34: aload         5
-        36: aload_0
-        37: invokeinterface #42,  2           // InterfaceMethod androidx/compose/runtime/Composer.changedInstance:(Ljava/lang/Object;)Z
-        42: ifeq          49
-        45: iconst_4
-        46: goto          50
-        49: iconst_2
-        50: ior
-        51: istore        7
-        53: iload         6
-        55: bipush        48
-        57: iand
-        58: ifne          84
-        61: iload         7
-        63: aload         5
-        65: aload_1
-        66: invokeinterface #42,  2           // InterfaceMethod androidx/compose/runtime/Composer.changedInstance:(Ljava/lang/Object;)Z
-        71: ifeq          79
-        74: bipush        32
-        76: goto          81
-        79: bipush        16
-        81: ior
-        82: istore        7
-        84: iload         6
-        86: sipush        384
-        89: iand
-        90: ifne          118
-        93: iload         7
-        95: aload         5
-        97: aload_2
-        98: invokeinterface #42,  2           // InterfaceMethod androidx/compose/runtime/Composer.changedInstance:(Ljava/lang/Object;)Z
-       103: ifeq          112
-       106: sipush        256
-       109: goto          115
-       112: sipush        128
-       115: ior
-       116: istore        7
-       118: iload         6
-       120: sipush        3072
-       123: iand
-       124: ifne          152
-       127: iload         7
-       129: aload         5
-       131: aload_3
-       132: invokeinterface #42,  2           // InterfaceMethod androidx/compose/runtime/Composer.changedInstance:(Ljava/lang/Object;)Z
-       137: ifeq          146
-       140: sipush        2048
-       143: goto          149
-       146: sipush        1024
-       149: ior
-       150: istore        7
-       152: iload         6
-       154: sipush        24576
-       157: iand
-       158: ifne          187
-       161: iload         7
-       163: aload         5
-       165: aload         4
-       167: invokeinterface #45,  2           // InterfaceMethod androidx/compose/runtime/Composer.changed:(Ljava/lang/Object;)Z
-       172: ifeq          181
-       175: sipush        16384
-       178: goto          184
-       181: sipush        8192
-       184: ior
-       185: istore        7
-       187: aload         5
-       189: iload         7
-       191: sipush        9363
-       194: iand
-       195: sipush        9362
-       198: if_icmpeq     205
-       201: iconst_1
-       202: goto          206
-       205: iconst_0
-       206: iload         7
-       208: iconst_1
-       209: iand
-       210: invokeinterface #52,  3           // InterfaceMethod androidx/compose/runtime/Composer.shouldExecute:(ZI)Z
-       215: ifeq          1189
-       218: invokestatic  #62                 // Method androidx/compose/runtime/ComposerKt.isTraceInProgress:()Z
-       221: ifeq          236
-       224: ldc_w         #468                // int -965203272
-       227: iload         7
-       229: iconst_m1
-       230: ldc_w         #472                // String com.example.compose.jetchat.components.IconAndTextRow (AnimatingFabContent.kt:110)
-       233: invokestatic  #68                 // Method androidx/compose/runtime/ComposerKt.traceEventStart:(IIILjava/lang/String;)V
-       236: aload         5
-       238: ldc_w         #473                // int 152606870
-       241: ldc_w         #269                // String CC(remember):AnimatingFabContent.kt#9igjgp
-       244: invokestatic  #114                // Method androidx/compose/runtime/ComposerKt.sourceInformationMarkerStart:(Landroidx/compose/runtime/Composer;ILjava/lang/String;)V
-       247: aload         5
-       249: astore        10
-       251: iload         7
-       253: sipush        7168
-       256: iand
-       257: sipush        2048
-       260: if_icmpne     267
-       263: iconst_1
-       264: goto          268
-       267: iconst_0
-       268: istore        11
-       270: iconst_0
-       271: istore        12
-       273: aload         10
-       275: invokeinterface #149,  1          // InterfaceMethod androidx/compose/runtime/Composer.rememberedValue:()Ljava/lang/Object;
-       280: astore        13
-       282: iconst_0
-       283: istore        14
-       285: iload         11
-       287: ifne          301
-       290: aload         13
-       292: getstatic     #152                // Field androidx/compose/runtime/Composer.Companion:Landroidx/compose/runtime/Composer$Companion;
-       295: invokevirtual #157                // Method androidx/compose/runtime/Composer$Companion.getEmpty:()Ljava/lang/Object;
-       298: if_acmpne     331
-       301: iconst_0
-       302: istore        15
-       304: new           #475                // class com/example/compose/jetchat/components/AnimatingFabContentKt$IconAndTextRow$1$1
-       307: dup
-       308: aload_3
-       309: invokespecial #478                // Method com/example/compose/jetchat/components/AnimatingFabContentKt$IconAndTextRow$1$1."<init>":(Lkotlin/jvm/functions/Function0;)V
-       312: checkcast     #480                // class androidx/compose/ui/layout/MeasurePolicy
-       315: astore        16
-       317: aload         10
-       319: aload         16
-       321: invokeinterface #187,  2          // InterfaceMethod androidx/compose/runtime/Composer.updateRememberedValue:(Ljava/lang/Object;)V
-       326: aload         16
-       328: goto          333
-       331: aload         13
-       333: nop
-       334: nop
-       335: checkcast     #480                // class androidx/compose/ui/layout/MeasurePolicy
-       338: astore        9
-       340: aload         5
-       342: invokestatic  #191                // Method androidx/compose/runtime/ComposerKt.sourceInformationMarkerEnd:(Landroidx/compose/runtime/Composer;)V
-       345: aload         9
-       347: astore        8
-       349: aload         4
-       351: astore        9
-       353: aload         8
-       355: astore        10
-       357: aload         5
-       359: astore        11
-       361: bipush        112
-       363: iload         7
-       365: bipush        9
-       367: ishr
-       368: iand
-       369: istore        12
-       371: nop
-       372: iconst_0
-       373: istore        13
-       375: aload         11
-       377: ldc_w         #481                // int -1159599143
-       380: ldc_w         #483                // String CC(Layout)P(!1,2)81@3355L27,84@3521L416:Layout.kt#80mrfh
-       383: invokestatic  #114                // Method androidx/compose/runtime/ComposerKt.sourceInformationMarkerStart:(Landroidx/compose/runtime/Composer;ILjava/lang/String;)V
-       386: aload         11
-       388: iconst_0
-       389: invokestatic  #489                // Method androidx/compose/runtime/ComposablesKt.getCurrentCompositeKeyHashCode:(Landroidx/compose/runtime/Composer;I)J
-       392: invokestatic  #495                // Method java/lang/Long.hashCode:(J)I
-       395: istore        14
-       397: aload         11
-       399: invokeinterface #499,  1          // InterfaceMethod androidx/compose/runtime/Composer.getCurrentCompositionLocalMap:()Landroidx/compose/runtime/CompositionLocalMap;
-       404: astore        15
-       406: aload         11
-       408: aload         9
-       410: invokestatic  #505                // Method androidx/compose/ui/ComposedModifierKt.materializeModifier:(Landroidx/compose/runtime/Composer;Landroidx/compose/ui/Modifier;)Landroidx/compose/ui/Modifier;
-       413: astore        16
-       415: getstatic     #510                // Field androidx/compose/ui/node/ComposeUiNode.Companion:Landroidx/compose/ui/node/ComposeUiNode$Companion;
-       418: invokevirtual #516                // Method androidx/compose/ui/node/ComposeUiNode$Companion.getConstructor:()Lkotlin/jvm/functions/Function0;
-       421: astore        17
-       423: aload         11
-       425: astore        18
-       427: bipush        6
-       429: sipush        896
-       432: iload         12
-       434: bipush        6
-       436: ishl
-       437: iand
-       438: ior
-       439: istore        19
-       441: nop
-       442: iconst_0
-       443: istore        20
-       445: aload         18
-       447: ldc_w         #517                // int -553112988
-       450: ldc_w         #519                // String CC(ReusableComposeNode)N(factory,update,content)399@15590L9:Composables.kt#9igjgp
-       453: invokestatic  #114                // Method androidx/compose/runtime/ComposerKt.sourceInformationMarkerStart:(Landroidx/compose/runtime/Composer;ILjava/lang/String;)V
-       456: aload         18
-       458: invokeinterface #523,  1          // InterfaceMethod androidx/compose/runtime/Composer.getApplier:()Landroidx/compose/runtime/Applier;
-       463: instanceof    #525                // class androidx/compose/runtime/Applier
-       466: ifne          472
-       469: invokestatic  #528                // Method androidx/compose/runtime/ComposablesKt.invalidApplier:()V
-       472: aload         18
-       474: invokeinterface #531,  1          // InterfaceMethod androidx/compose/runtime/Composer.startReusableNode:()V
-       479: aload         18
-       481: invokeinterface #534,  1          // InterfaceMethod androidx/compose/runtime/Composer.getInserting:()Z
-       486: ifeq          501
-       489: aload         18
-       491: aload         17
-       493: invokeinterface #537,  2          // InterfaceMethod androidx/compose/runtime/Composer.createNode:(Lkotlin/jvm/functions/Function0;)V
-       498: goto          508
-       501: aload         18
-       503: invokeinterface #540,  1          // InterfaceMethod androidx/compose/runtime/Composer.useNode:()V
-       508: aload         18
-       510: invokestatic  #546                // Method androidx/compose/runtime/Updater."constructor-impl":(Landroidx/compose/runtime/Composer;)Landroidx/compose/runtime/Composer;
-       513: astore        21
-       515: iconst_0
-       516: istore        22
-       518: aload         21
-       520: aload         10
-       522: getstatic     #510                // Field androidx/compose/ui/node/ComposeUiNode.Companion:Landroidx/compose/ui/node/ComposeUiNode$Companion;
-       525: invokevirtual #550                // Method androidx/compose/ui/node/ComposeUiNode$Companion.getSetMeasurePolicy:()Lkotlin/jvm/functions/Function2;
-       528: invokestatic  #554                // Method androidx/compose/runtime/Updater."set-impl":(Landroidx/compose/runtime/Composer;Ljava/lang/Object;Lkotlin/jvm/functions/Function2;)V
-       531: aload         21
-       533: aload         15
-       535: getstatic     #510                // Field androidx/compose/ui/node/ComposeUiNode.Companion:Landroidx/compose/ui/node/ComposeUiNode$Companion;
-       538: invokevirtual #557                // Method androidx/compose/ui/node/ComposeUiNode$Companion.getSetResolvedCompositionLocals:()Lkotlin/jvm/functions/Function2;
-       541: invokestatic  #554                // Method androidx/compose/runtime/Updater."set-impl":(Landroidx/compose/runtime/Composer;Ljava/lang/Object;Lkotlin/jvm/functions/Function2;)V
-       544: aload         21
-       546: iload         14
-       548: invokestatic  #239                // Method java/lang/Integer.valueOf:(I)Ljava/lang/Integer;
-       551: getstatic     #510                // Field androidx/compose/ui/node/ComposeUiNode.Companion:Landroidx/compose/ui/node/ComposeUiNode$Companion;
-       554: invokevirtual #560                // Method androidx/compose/ui/node/ComposeUiNode$Companion.getSetCompositeKeyHash:()Lkotlin/jvm/functions/Function2;
-       557: invokestatic  #563                // Method androidx/compose/runtime/Updater."init-impl":(Landroidx/compose/runtime/Composer;Ljava/lang/Object;Lkotlin/jvm/functions/Function2;)V
-       560: aload         21
-       562: getstatic     #510                // Field androidx/compose/ui/node/ComposeUiNode.Companion:Landroidx/compose/ui/node/ComposeUiNode$Companion;
-       565: invokevirtual #566                // Method androidx/compose/ui/node/ComposeUiNode$Companion.getApplyOnDeactivatedNodeAssertion:()Lkotlin/jvm/functions/Function1;
-       568: invokestatic  #570                // Method androidx/compose/runtime/Updater."reconcile-impl":(Landroidx/compose/runtime/Composer;Lkotlin/jvm/functions/Function1;)V
-       571: aload         21
-       573: aload         16
-       575: getstatic     #510                // Field androidx/compose/ui/node/ComposeUiNode.Companion:Landroidx/compose/ui/node/ComposeUiNode$Companion;
-       578: invokevirtual #573                // Method androidx/compose/ui/node/ComposeUiNode$Companion.getSetModifier:()Lkotlin/jvm/functions/Function2;
-       581: invokestatic  #554                // Method androidx/compose/runtime/Updater."set-impl":(Landroidx/compose/runtime/Composer;Ljava/lang/Object;Lkotlin/jvm/functions/Function2;)V
-       584: nop
-       585: nop
-       586: aload         18
-       588: bipush        14
-       590: iload         19
-       592: bipush        6
-       594: ishr
-       595: iand
-       596: istore        23
-       598: astore        24
-       600: iconst_0
-       601: istore        25
-       603: aload         24
-       605: ldc_w         #574                // int -1511337418
-       608: ldc_w         #576                // String C114@3804L6,115@3861L29,115@3823L107:AnimatingFabContent.kt#o9oqao
-       611: invokestatic  #114                // Method androidx/compose/runtime/ComposerKt.sourceInformationMarkerStart:(Landroidx/compose/runtime/Composer;ILjava/lang/String;)V
-       614: aload_0
-       615: aload         24
-       617: bipush        14
-       619: iload         7
-       621: iand
-       622: invokestatic  #239                // Method java/lang/Integer.valueOf:(I)Ljava/lang/Integer;
-       625: invokeinterface #578,  3          // InterfaceMethod kotlin/jvm/functions/Function2.invoke:(Ljava/lang/Object;Ljava/lang/Object;)Ljava/lang/Object;
-       630: pop
-       631: getstatic     #58                 // Field androidx/compose/ui/Modifier.Companion:Landroidx/compose/ui/Modifier$Companion;
-       634: checkcast     #54                 // class androidx/compose/ui/Modifier
-       637: aload         24
-       639: ldc_w         #579                // int 1059627564
-       642: ldc_w         #269                // String CC(remember):AnimatingFabContent.kt#9igjgp
-       645: invokestatic  #114                // Method androidx/compose/runtime/ComposerKt.sourceInformationMarkerStart:(Landroidx/compose/runtime/Composer;ILjava/lang/String;)V
-       648: aload         24
-       650: astore        26
-       652: iload         7
-       654: sipush        896
-       657: iand
-       658: sipush        256
-       661: if_icmpne     668
-       664: iconst_1
-       665: goto          669
-       668: iconst_0
-       669: istore        27
-       671: iconst_0
-       672: istore        28
-       674: aload         26
-       676: invokeinterface #149,  1          // InterfaceMethod androidx/compose/runtime/Composer.rememberedValue:()Ljava/lang/Object;
-       681: astore        29
-       683: iconst_0
-       684: istore        30
-       686: iload         27
-       688: ifne          702
-       691: aload         29
-       693: getstatic     #152                // Field androidx/compose/runtime/Composer.Companion:Landroidx/compose/runtime/Composer$Companion;
-       696: invokevirtual #157                // Method androidx/compose/runtime/Composer$Companion.getEmpty:()Ljava/lang/Object;
-       699: if_acmpne     732
-       702: astore        31
-       704: iconst_0
-       705: istore        32
-       707: aload_2
-       708: invokedynamic #591,  0            // InvokeDynamic #5:invoke:(Lkotlin/jvm/functions/Function0;)Lkotlin/jvm/functions/Function1;
-       713: aload         31
-       715: swap
-       716: astore        33
-       718: aload         26
-       720: aload         33
-       722: invokeinterface #187,  2          // InterfaceMethod androidx/compose/runtime/Composer.updateRememberedValue:(Ljava/lang/Object;)V
-       727: aload         33
-       729: goto          734
-       732: aload         29
-       734: nop
-       735: nop
-       736: checkcast     #464                // class kotlin/jvm/functions/Function1
-       739: astore        34
-       741: aload         24
-       743: invokestatic  #191                // Method androidx/compose/runtime/ComposerKt.sourceInformationMarkerEnd:(Landroidx/compose/runtime/Composer;)V
-       746: aload         34
-       748: invokestatic  #597                // Method androidx/compose/ui/graphics/GraphicsLayerModifierKt.graphicsLayer:(Landroidx/compose/ui/Modifier;Lkotlin/jvm/functions/Function1;)Landroidx/compose/ui/Modifier;
-       751: astore        34
-       753: aload         24
-       755: astore        28
-       757: iconst_0
-       758: istore        29
-       760: iconst_0
-       761: istore        30
-       763: aload         28
-       765: ldc_w         #598                // int 1042775818
-       768: ldc_w         #600                // String CC(Box)N(modifier,contentAlignment,propagateMinConstraints,content)71@3424L131:Box.kt#2w3rfo
-       771: invokestatic  #114                // Method androidx/compose/runtime/ComposerKt.sourceInformationMarkerStart:(Landroidx/compose/runtime/Composer;ILjava/lang/String;)V
-       774: getstatic     #605                // Field androidx/compose/ui/Alignment.Companion:Landroidx/compose/ui/Alignment$Companion;
-       777: invokevirtual #611                // Method androidx/compose/ui/Alignment$Companion.getTopStart:()Landroidx/compose/ui/Alignment;
-       780: astore        26
-       782: iconst_0
-       783: istore        27
-       785: aload         26
-       787: iload         27
-       789: invokestatic  #617                // Method androidx/compose/foundation/layout/BoxKt.maybeCachedBoxMeasurePolicy:(Landroidx/compose/ui/Alignment;Z)Landroidx/compose/ui/layout/MeasurePolicy;
-       792: astore        32
-       794: aload         34
-       796: astore        33
-       798: aload         32
-       800: astore        35
-       802: aload         28
-       804: astore        36
-       806: bipush        112
-       808: iload         29
-       810: iconst_3
-       811: ishl
-       812: iand
-       813: istore        37
-       815: nop
-       816: iconst_0
-       817: istore        38
-       819: aload         36
-       821: ldc_w         #481                // int -1159599143
-       824: ldc_w         #483                // String CC(Layout)P(!1,2)81@3355L27,84@3521L416:Layout.kt#80mrfh
-       827: invokestatic  #114                // Method androidx/compose/runtime/ComposerKt.sourceInformationMarkerStart:(Landroidx/compose/runtime/Composer;ILjava/lang/String;)V
-       830: aload         36
-       832: iconst_0
-       833: invokestatic  #489                // Method androidx/compose/runtime/ComposablesKt.getCurrentCompositeKeyHashCode:(Landroidx/compose/runtime/Composer;I)J
-       836: invokestatic  #495                // Method java/lang/Long.hashCode:(J)I
-       839: istore        39
-       841: aload         36
-       843: invokeinterface #499,  1          // InterfaceMethod androidx/compose/runtime/Composer.getCurrentCompositionLocalMap:()Landroidx/compose/runtime/CompositionLocalMap;
-       848: astore        40
-       850: aload         36
-       852: aload         33
-       854: invokestatic  #505                // Method androidx/compose/ui/ComposedModifierKt.materializeModifier:(Landroidx/compose/runtime/Composer;Landroidx/compose/ui/Modifier;)Landroidx/compose/ui/Modifier;
-       857: astore        41
-       859: getstatic     #510                // Field androidx/compose/ui/node/ComposeUiNode.Companion:Landroidx/compose/ui/node/ComposeUiNode$Companion;
-       862: invokevirtual #516                // Method androidx/compose/ui/node/ComposeUiNode$Companion.getConstructor:()Lkotlin/jvm/functions/Function0;
-       865: astore        42
-       867: aload         36
-       869: astore        43
-       871: bipush        6
-       873: sipush        896
-       876: iload         37
-       878: bipush        6
-       880: ishl
-       881: iand
-       882: ior
-       883: istore        44
-       885: nop
-       886: iconst_0
-       887: istore        45
-       889: aload         43
-       891: ldc_w         #517                // int -553112988
-       894: ldc_w         #519                // String CC(ReusableComposeNode)N(factory,update,content)399@15590L9:Composables.kt#9igjgp
-       897: invokestatic  #114                // Method androidx/compose/runtime/ComposerKt.sourceInformationMarkerStart:(Landroidx/compose/runtime/Composer;ILjava/lang/String;)V
-       900: aload         43
-       902: invokeinterface #523,  1          // InterfaceMethod androidx/compose/runtime/Composer.getApplier:()Landroidx/compose/runtime/Applier;
-       907: instanceof    #525                // class androidx/compose/runtime/Applier
-       910: ifne          916
-       913: invokestatic  #528                // Method androidx/compose/runtime/ComposablesKt.invalidApplier:()V
-       916: aload         43
-       918: invokeinterface #531,  1          // InterfaceMethod androidx/compose/runtime/Composer.startReusableNode:()V
-       923: aload         43
-       925: invokeinterface #534,  1          // InterfaceMethod androidx/compose/runtime/Composer.getInserting:()Z
-       930: ifeq          945
-       933: aload         43
-       935: aload         42
-       937: invokeinterface #537,  2          // InterfaceMethod androidx/compose/runtime/Composer.createNode:(Lkotlin/jvm/functions/Function0;)V
-       942: goto          952
-       945: aload         43
-       947: invokeinterface #540,  1          // InterfaceMethod androidx/compose/runtime/Composer.useNode:()V
-       952: aload         43
-       954: invokestatic  #546                // Method androidx/compose/runtime/Updater."constructor-impl":(Landroidx/compose/runtime/Composer;)Landroidx/compose/runtime/Composer;
-       957: astore        46
-       959: iconst_0
-       960: istore        47
-       962: aload         46
-       964: aload         35
-       966: getstatic     #510                // Field androidx/compose/ui/node/ComposeUiNode.Companion:Landroidx/compose/ui/node/ComposeUiNode$Companion;
-       969: invokevirtual #550                // Method androidx/compose/ui/node/ComposeUiNode$Companion.getSetMeasurePolicy:()Lkotlin/jvm/functions/Function2;
-       972: invokestatic  #554                // Method androidx/compose/runtime/Updater."set-impl":(Landroidx/compose/runtime/Composer;Ljava/lang/Object;Lkotlin/jvm/functions/Function2;)V
-       975: aload         46
-       977: aload         40
-       979: getstatic     #510                // Field androidx/compose/ui/node/ComposeUiNode.Companion:Landroidx/compose/ui/node/ComposeUiNode$Companion;
-       982: invokevirtual #557                // Method androidx/compose/ui/node/ComposeUiNode$Companion.getSetResolvedCompositionLocals:()Lkotlin/jvm/functions/Function2;
-       985: invokestatic  #554                // Method androidx/compose/runtime/Updater."set-impl":(Landroidx/compose/runtime/Composer;Ljava/lang/Object;Lkotlin/jvm/functions/Function2;)V
-       988: aload         46
-       990: iload         39
-       992: invokestatic  #239                // Method java/lang/Integer.valueOf:(I)Ljava/lang/Integer;
-       995: getstatic     #510                // Field androidx/compose/ui/node/ComposeUiNode.Companion:Landroidx/compose/ui/node/ComposeUiNode$Companion;
-       998: invokevirtual #560                // Method androidx/compose/ui/node/ComposeUiNode$Companion.getSetCompositeKeyHash:()Lkotlin/jvm/functions/Function2;
-      1001: invokestatic  #563                // Method androidx/compose/runtime/Updater."init-impl":(Landroidx/compose/runtime/Composer;Ljava/lang/Object;Lkotlin/jvm/functions/Function2;)V
-      1004: aload         46
-      1006: getstatic     #510                // Field androidx/compose/ui/node/ComposeUiNode.Companion:Landroidx/compose/ui/node/ComposeUiNode$Companion;
-      1009: invokevirtual #566                // Method androidx/compose/ui/node/ComposeUiNode$Companion.getApplyOnDeactivatedNodeAssertion:()Lkotlin/jvm/functions/Function1;
-      1012: invokestatic  #570                // Method androidx/compose/runtime/Updater."reconcile-impl":(Landroidx/compose/runtime/Composer;Lkotlin/jvm/functions/Function1;)V
-      1015: aload         46
-      1017: aload         41
-      1019: getstatic     #510                // Field androidx/compose/ui/node/ComposeUiNode.Companion:Landroidx/compose/ui/node/ComposeUiNode$Companion;
-      1022: invokevirtual #573                // Method androidx/compose/ui/node/ComposeUiNode$Companion.getSetModifier:()Lkotlin/jvm/functions/Function2;
-      1025: invokestatic  #554                // Method androidx/compose/runtime/Updater."set-impl":(Landroidx/compose/runtime/Composer;Ljava/lang/Object;Lkotlin/jvm/functions/Function2;)V
-      1028: nop
-      1029: nop
-      1030: aload         43
-      1032: bipush        14
-      1034: iload         44
-      1036: bipush        6
-      1038: ishr
-      1039: iand
-      1040: istore        48
-      1042: astore        49
-      1044: iconst_0
-      1045: istore        50
-      1047: aload         49
-      1049: ldc_w         #618                // int 1833054614
-      1052: ldc_w         #620                // String C72@3469L9:Box.kt#2w3rfo
-      1055: invokestatic  #114                // Method androidx/compose/runtime/ComposerKt.sourceInformationMarkerStart:(Landroidx/compose/runtime/Composer;ILjava/lang/String;)V
-      1058: getstatic     #625                // Field androidx/compose/foundation/layout/BoxScopeInstance.INSTANCE:Landroidx/compose/foundation/layout/BoxScopeInstance;
-      1061: aload         49
-      1063: bipush        6
-      1065: bipush        112
-      1067: iload         29
-      1069: bipush        6
-      1071: ishr
-      1072: iand
-      1073: ior
-      1074: istore        51
-      1076: astore        52
-      1078: checkcast     #627                // class androidx/compose/foundation/layout/BoxScope
-      1081: astore        53
-      1083: iconst_0
-      1084: istore        54
-      1086: aload         52
-      1088: ldc_w         #628                // int 1997708776
-      1091: ldc_w         #630                // String C116@3910L6:AnimatingFabContent.kt#o9oqao
-      1094: invokestatic  #114                // Method androidx/compose/runtime/ComposerKt.sourceInformationMarkerStart:(Landroidx/compose/runtime/Composer;ILjava/lang/String;)V
-      1097: aload_1
-      1098: aload         52
-      1100: bipush        14
-      1102: iload         7
-      1104: iconst_3
-      1105: ishr
-      1106: iand
-      1107: invokestatic  #239                // Method java/lang/Integer.valueOf:(I)Ljava/lang/Integer;
-      1110: invokeinterface #578,  3          // InterfaceMethod kotlin/jvm/functions/Function2.invoke:(Ljava/lang/Object;Ljava/lang/Object;)Ljava/lang/Object;
-      1115: pop
-      1116: aload         52
-      1118: invokestatic  #191                // Method androidx/compose/runtime/ComposerKt.sourceInformationMarkerEnd:(Landroidx/compose/runtime/Composer;)V
-      1121: nop
-      1122: aload         49
-      1124: invokestatic  #191                // Method androidx/compose/runtime/ComposerKt.sourceInformationMarkerEnd:(Landroidx/compose/runtime/Composer;)V
-      1127: aload         43
-      1129: invokeinterface #633,  1          // InterfaceMethod androidx/compose/runtime/Composer.endNode:()V
-      1134: aload         43
-      1136: invokestatic  #191                // Method androidx/compose/runtime/ComposerKt.sourceInformationMarkerEnd:(Landroidx/compose/runtime/Composer;)V
-      1139: nop
-      1140: aload         36
-      1142: invokestatic  #191                // Method androidx/compose/runtime/ComposerKt.sourceInformationMarkerEnd:(Landroidx/compose/runtime/Composer;)V
-      1145: nop
-      1146: aload         28
-      1148: invokestatic  #191                // Method androidx/compose/runtime/ComposerKt.sourceInformationMarkerEnd:(Landroidx/compose/runtime/Composer;)V
-      1151: nop
-      1152: aload         24
-      1154: invokestatic  #191                // Method androidx/compose/runtime/ComposerKt.sourceInformationMarkerEnd:(Landroidx/compose/runtime/Composer;)V
-      1157: nop
-      1158: aload         18
-      1160: invokeinterface #633,  1          // InterfaceMethod androidx/compose/runtime/Composer.endNode:()V
-      1165: aload         18
-      1167: invokestatic  #191                // Method androidx/compose/runtime/ComposerKt.sourceInformationMarkerEnd:(Landroidx/compose/runtime/Composer;)V
-      1170: nop
-      1171: aload         11
-      1173: invokestatic  #191                // Method androidx/compose/runtime/ComposerKt.sourceInformationMarkerEnd:(Landroidx/compose/runtime/Composer;)V
-      1176: nop
-      1177: invokestatic  #62                 // Method androidx/compose/runtime/ComposerKt.isTraceInProgress:()Z
-      1180: ifeq          1196
-      1183: invokestatic  #204                // Method androidx/compose/runtime/ComposerKt.traceEventEnd:()V
-      1186: goto          1196
-      1189: aload         5
-      1191: invokeinterface #293,  1          // InterfaceMethod androidx/compose/runtime/Composer.skipToGroupEnd:()V
-      1196: aload         5
-      1198: invokeinterface #297,  1          // InterfaceMethod androidx/compose/runtime/Composer.endRestartGroup:()Landroidx/compose/runtime/ScopeUpdateScope;
-      1203: dup
-      1204: ifnull        1228
-      1207: aload_0
-      1208: aload_1
-      1209: aload_2
-      1210: aload_3
-      1211: aload         4
-      1213: iload         6
-      1215: invokedynamic #641,  0            // InvokeDynamic #6:invoke:(Lkotlin/jvm/functions/Function2;Lkotlin/jvm/functions/Function2;Lkotlin/jvm/functions/Function0;Lkotlin/jvm/functions/Function0;Landroidx/compose/ui/Modifier;I)Lkotlin/jvm/functions/Function2;
-      1220: invokeinterface #315,  2          // InterfaceMethod androidx/compose/runtime/ScopeUpdateScope.updateScope:(Lkotlin/jvm/functions/Function2;)V
-      1225: goto          1229
-      1228: pop
-      1229: return
-
-  private static final float AnimatingFabContent$lambda$6$0(androidx.compose.runtime.State);
-    Code:
-         0: aload_0
-         1: invokestatic  #704                // Method AnimatingFabContent$lambda$2:(Landroidx/compose/runtime/State;)F
-         4: freturn
-
-  private static final float AnimatingFabContent$lambda$7$0(androidx.compose.runtime.State);
-    Code:
-         0: aload_0
-         1: invokestatic  #708                // Method AnimatingFabContent$lambda$5:(Landroidx/compose/runtime/State;)F
-         4: freturn
-
-  private static final float AnimatingFabContent$lambda$2(androidx.compose.runtime.State<java.lang.Float>);
-    Code:
-         0: aload_0
-         1: astore_1
-         2: aconst_null
-         3: astore_2
-         4: aconst_null
-         5: astore_3
-         6: iconst_0
-         7: istore        4
-         9: aload_1
-        10: invokeinterface #230,  1          // InterfaceMethod androidx/compose/runtime/State.getValue:()Ljava/lang/Object;
-        15: checkcast     #712                // class java/lang/Number
-        18: invokevirtual #716                // Method java/lang/Number.floatValue:()F
-        21: freturn
-
-  private static final androidx.compose.animation.core.FiniteAnimationSpec AnimatingFabContent$lambda$0(androidx.compose.animation.core.Transition$Segment, androidx.compose.runtime.Composer, int);
-    Code:
-         0: aload_0
-         1: ldc_w         #726                // String $this$animateFloat
-         4: invokestatic  #21                 // Method kotlin/jvm/internal/Intrinsics.checkNotNullParameter:(Ljava/lang/Object;Ljava/lang/String;)V
-         7: aload_1
-         8: ldc_w         #727                // int -1723418446
-        11: invokeinterface #140,  2          // InterfaceMethod androidx/compose/runtime/Composer.startReplaceGroup:(I)V
-        16: invokestatic  #62                 // Method androidx/compose/runtime/ComposerKt.isTraceInProgress:()Z
-        19: ifeq          33
-        22: ldc_w         #727                // int -1723418446
-        25: iload_2
-        26: iconst_m1
-        27: ldc_w         #729                // String com.example.compose.jetchat.components.AnimatingFabContent.<anonymous> (AnimatingFabContent.kt:49)
-        30: invokestatic  #68                 // Method androidx/compose/runtime/ComposerKt.traceEventStart:(IIILjava/lang/String;)V
-        33: aload_0
-        34: invokeinterface #734,  1          // InterfaceMethod androidx/compose/animation/core/Transition$Segment.getTargetState:()Ljava/lang/Object;
-        39: getstatic     #77                 // Field com/example/compose/jetchat/components/ExpandableFabStates.Collapsed:Lcom/example/compose/jetchat/components/ExpandableFabStates;
-        42: if_acmpne     70
-        45: invokestatic  #740                // Method androidx/compose/animation/core/EasingKt.getLinearEasing:()Landroidx/compose/animation/core/Easing;
-        48: astore        4
-        50: ldc_w         #741                // float 83.33333f
-        53: invokestatic  #747                // Method kotlin/math/MathKt.roundToInt:(F)I
-        56: iconst_0
-        57: aload         4
-        59: iconst_2
-        60: aconst_null
-        61: invokestatic  #753                // Method androidx/compose/animation/core/AnimationSpecKt.tween$default:(IILandroidx/compose/animation/core/Easing;ILjava/lang/Object;)Landroidx/compose/animation/core/TweenSpec;
-        64: checkcast     #245                // class androidx/compose/animation/core/FiniteAnimationSpec
-        67: goto          99
-        70: invokestatic  #740                // Method androidx/compose/animation/core/EasingKt.getLinearEasing:()Landroidx/compose/animation/core/Easing;
-        73: astore        4
-        75: ldc_w         #754                // float 66.666664f
-        78: invokestatic  #747                // Method kotlin/math/MathKt.roundToInt:(F)I
-        81: istore        5
-        83: ldc_w         #741                // float 83.33333f
-        86: invokestatic  #747                // Method kotlin/math/MathKt.roundToInt:(F)I
-        89: iload         5
-        91: aload         4
-        93: invokestatic  #758                // Method androidx/compose/animation/core/AnimationSpecKt.tween:(IILandroidx/compose/animation/core/Easing;)Landroidx/compose/animation/core/TweenSpec;
-        96: checkcast     #245                // class androidx/compose/animation/core/FiniteAnimationSpec
-        99: astore_3
-       100: invokestatic  #62                 // Method androidx/compose/runtime/ComposerKt.isTraceInProgress:()Z
-       103: ifeq          109
-       106: invokestatic  #204                // Method androidx/compose/runtime/ComposerKt.traceEventEnd:()V
-       109: aload_1
-       110: invokeinterface #195,  1          // InterfaceMethod androidx/compose/runtime/Composer.endReplaceGroup:()V
-       115: aload_3
-       116: areturn
-
-  private static final float AnimatingFabContent$lambda$5(androidx.compose.runtime.State<java.lang.Float>);
-    Code:
-         0: aload_0
-         1: astore_1
-         2: aconst_null
-         3: astore_2
-         4: aconst_null
-         5: astore_3
-         6: iconst_0
-         7: istore        4
-         9: aload_1
-        10: invokeinterface #230,  1          // InterfaceMethod androidx/compose/runtime/State.getValue:()Ljava/lang/Object;
-        15: checkcast     #712                // class java/lang/Number
-        18: invokevirtual #716                // Method java/lang/Number.floatValue:()F
-        21: freturn
-
-  private static final androidx.compose.animation.core.FiniteAnimationSpec AnimatingFabContent$lambda$3(androidx.compose.animation.core.Transition$Segment, androidx.compose.runtime.Composer, int);
-    Code:
-         0: aload_0
-         1: ldc_w         #726                // String $this$animateFloat
-         4: invokestatic  #21                 // Method kotlin/jvm/internal/Intrinsics.checkNotNullParameter:(Ljava/lang/Object;Ljava/lang/String;)V
-         7: aload_1
-         8: ldc_w         #763                // int -14719148
-        11: invokeinterface #140,  2          // InterfaceMethod androidx/compose/runtime/Composer.startReplaceGroup:(I)V
-        16: invokestatic  #62                 // Method androidx/compose/runtime/ComposerKt.isTraceInProgress:()Z
-        19: ifeq          33
-        22: ldc_w         #763                // int -14719148
-        25: iload_2
-        26: iconst_m1
-        27: ldc_w         #765                // String com.example.compose.jetchat.components.AnimatingFabContent.<anonymous> (AnimatingFabContent.kt:72)
-        30: invokestatic  #68                 // Method androidx/compose/runtime/ComposerKt.traceEventStart:(IIILjava/lang/String;)V
-        33: aload_0
-        34: invokeinterface #734,  1          // InterfaceMethod androidx/compose/animation/core/Transition$Segment.getTargetState:()Ljava/lang/Object;
-        39: getstatic     #77                 // Field com/example/compose/jetchat/components/ExpandableFabStates.Collapsed:Lcom/example/compose/jetchat/components/ExpandableFabStates;
-        42: if_acmpne     67
-        45: invokestatic  #768                // Method androidx/compose/animation/core/EasingKt.getFastOutSlowInEasing:()Landroidx/compose/animation/core/Easing;
-        48: astore        4
-        50: sipush        200
-        53: iconst_0
-        54: aload         4
-        56: iconst_2
-        57: aconst_null
-        58: invokestatic  #753                // Method androidx/compose/animation/core/AnimationSpecKt.tween$default:(IILandroidx/compose/animation/core/Easing;ILjava/lang/Object;)Landroidx/compose/animation/core/TweenSpec;
-        61: checkcast     #245                // class androidx/compose/animation/core/FiniteAnimationSpec
-        64: goto          86
-        67: invokestatic  #768                // Method androidx/compose/animation/core/EasingKt.getFastOutSlowInEasing:()Landroidx/compose/animation/core/Easing;
-        70: astore        4
-        72: sipush        200
-        75: iconst_0
-        76: aload         4
-        78: iconst_2
-        79: aconst_null
-        80: invokestatic  #753                // Method androidx/compose/animation/core/AnimationSpecKt.tween$default:(IILandroidx/compose/animation/core/Easing;ILjava/lang/Object;)Landroidx/compose/animation/core/TweenSpec;
-        83: checkcast     #245                // class androidx/compose/animation/core/FiniteAnimationSpec
-        86: astore_3
-        87: invokestatic  #62                 // Method androidx/compose/runtime/ComposerKt.isTraceInProgress:()Z
-        90: ifeq          96
-        93: invokestatic  #204                // Method androidx/compose/runtime/ComposerKt.traceEventEnd:()V
-        96: aload_1
-        97: invokeinterface #195,  1          // InterfaceMethod androidx/compose/runtime/Composer.endReplaceGroup:()V
-       102: aload_3
-       103: areturn
-
-  private static final kotlin.Unit AnimatingFabContent$lambda$8(kotlin.jvm.functions.Function2, kotlin.jvm.functions.Function2, androidx.compose.ui.Modifier, boolean, int, int, androidx.compose.runtime.Composer, int);
-    Code:
-         0: aload_0
-         1: aload_1
-         2: aload_2
-         3: iload_3
-         4: aload         6
-         6: iload         4
-         8: iconst_1
-         9: ior
-        10: invokestatic  #774                // Method androidx/compose/runtime/RecomposeScopeImplKt.updateChangedFlags:(I)I
-        13: iload         5
-        15: invokestatic  #776                // Method AnimatingFabContent:(Lkotlin/jvm/functions/Function2;Lkotlin/jvm/functions/Function2;Landroidx/compose/ui/Modifier;ZLandroidx/compose/runtime/Composer;II)V
-        18: getstatic     #781                // Field kotlin/Unit.INSTANCE:Lkotlin/Unit;
-        21: areturn
-
-  private static final kotlin.Unit IconAndTextRow$lambda$1$0$0(kotlin.jvm.functions.Function0, androidx.compose.ui.graphics.GraphicsLayerScope);
-    Code:
-         0: aload_1
-         1: ldc_w         #790                // String $this$graphicsLayer
-         4: invokestatic  #21                 // Method kotlin/jvm/internal/Intrinsics.checkNotNullParameter:(Ljava/lang/Object;Ljava/lang/String;)V
-         7: aload_1
-         8: aload_0
-         9: invokeinterface #792,  1          // InterfaceMethod kotlin/jvm/functions/Function0.invoke:()Ljava/lang/Object;
-        14: checkcast     #712                // class java/lang/Number
-        17: invokevirtual #716                // Method java/lang/Number.floatValue:()F
-        20: invokeinterface #798,  2          // InterfaceMethod androidx/compose/ui/graphics/GraphicsLayerScope.setAlpha:(F)V
-        25: getstatic     #781                // Field kotlin/Unit.INSTANCE:Lkotlin/Unit;
-        28: areturn
-
-  private static final kotlin.Unit IconAndTextRow$lambda$2(kotlin.jvm.functions.Function2, kotlin.jvm.functions.Function2, kotlin.jvm.functions.Function0, kotlin.jvm.functions.Function0, androidx.compose.ui.Modifier, int, androidx.compose.runtime.Composer, int);
-    Code:
-         0: aload_0
-         1: aload_1
-         2: aload_2
-         3: aload_3
-         4: aload         4
-         6: aload         6
-         8: iload         5
-        10: iconst_1
-        11: ior
-        12: invokestatic  #774                // Method androidx/compose/runtime/RecomposeScopeImplKt.updateChangedFlags:(I)I
-        15: invokestatic  #290                // Method IconAndTextRow:(Lkotlin/jvm/functions/Function2;Lkotlin/jvm/functions/Function2;Lkotlin/jvm/functions/Function0;Lkotlin/jvm/functions/Function0;Landroidx/compose/ui/Modifier;Landroidx/compose/runtime/Composer;I)V
-        18: getstatic     #781                // Field kotlin/Unit.INSTANCE:Lkotlin/Unit;
-        21: areturn
+Compiled from "com/example/compose/jetchat/components/AnimatingFabContent.kt"
+public final class com.example.compose.jetchat.components.AnimatingFabContentKt {
+  public static final int transitionDuration;
+
+  public static final <T> void AnimatingFabContent(kotlin.jvm.functions.Function2, kotlin.jvm.functions.Function2, androidx.compose.ui.Modifier, boolean, androidx.compose.runtime.Composer, int);
+    Code:
+         0: aload_0
+         1: ldc           #13                 // String icon
+         3: invokestatic  #19                 // Method kotlin/jvm/internal/Intrinsics.checkNotNullParameter:(Ljava/lang/Object;Ljava/lang/String;)V
+         6: aload_1
+         7: ldc           #21                 // String text
+         9: invokestatic  #19                 // Method kotlin/jvm/internal/Intrinsics.checkNotNullParameter:(Ljava/lang/Object;Ljava/lang/String;)V
+        12: aload_2
+        13: ldc           #23                 // String modifier
+        15: invokestatic  #19                 // Method kotlin/jvm/internal/Intrinsics.checkNotNullParameter:(Ljava/lang/Object;Ljava/lang/String;)V
+        18: iload_3
+        19: ifeq          31
+        22: aconst_null
+        23: getfield      #29                 // Field com/example/compose/jetchat/components/ExpandableFabStates.Extended:Ljava/lang/Object;
+        26: astore        6
+        28: goto          37
+        31: aconst_null
+        32: getfield      #32                 // Field com/example/compose/jetchat/components/ExpandableFabStates.Collapsed:Ljava/lang/Object;
+        35: astore        6
+        37: aload         6
+        39: checkcast     #34                 // class androidx/compose/animation/core/MutableTransitionState
+        42: ldc           #36                 // String fab_transition
+        44: aload         4
+        46: iload         5
+        48: iconst_0
+        49: invokestatic  #42                 // Method androidx/compose/animation/core/TransitionKt.updateTransition:(Landroidx/compose/animation/core/MutableTransitionState;Ljava/lang/String;Landroidx/compose/runtime/Composer;II)Landroidx/compose/animation/core/Transition;
+        52: astore        7
+        54: new           #44                 // class com/example/compose/jetchat/components/AnimatingFabContentKt$Lambda$23
+        57: dup
+        58: invokespecial #48                 // Method com/example/compose/jetchat/components/AnimatingFabContentKt$Lambda$23."<init>":()V
+        61: pop
+        62: invokedynamic #68,  0             // InvokeDynamic #0:invoke:()Lkotlin/jvm/functions/Function1;
+        67: astore        8
+        69: new           #70                 // class com/example/compose/jetchat/components/AnimatingFabContentKt$Lambda$24
+        72: dup
+        73: invokespecial #71                 // Method com/example/compose/jetchat/components/AnimatingFabContentKt$Lambda$24."<init>":()V
+        76: pop
+        77: invokedynamic #76,  0             // InvokeDynamic #1:invoke:()Lkotlin/jvm/functions/Function1;
+        82: astore        9
+        84: aconst_null
+        85: astore        10
+        87: new           #78                 // class com/example/compose/jetchat/components/AnimatingFabContentKt$Lambda$25
+        90: dup
+        91: invokespecial #79                 // Method com/example/compose/jetchat/components/AnimatingFabContentKt$Lambda$25."<init>":()V
+        94: pop
+        95: invokedynamic #84,  0             // InvokeDynamic #2:invoke:()Lkotlin/jvm/functions/Function1;
+       100: astore        11
+       102: new           #86                 // class com/example/compose/jetchat/components/AnimatingFabContentKt$Lambda$26
+       105: dup
+       106: invokespecial #87                 // Method com/example/compose/jetchat/components/AnimatingFabContentKt$Lambda$26."<init>":()V
+       109: pop
+       110: invokedynamic #92,  0             // InvokeDynamic #3:invoke:()Lkotlin/jvm/functions/Function1;
+       115: astore        12
+       117: aconst_null
+       118: astore        13
+       120: new           #94                 // class com/example/compose/jetchat/components/AnimatingFabContentKt$Lambda$27
+       123: dup
+       124: aload         10
+       126: invokespecial #97                 // Method com/example/compose/jetchat/components/AnimatingFabContentKt$Lambda$27."<init>":(Ljava/lang/Object;)V
+       129: astore        14
+       131: new           #99                 // class com/example/compose/jetchat/components/AnimatingFabContentKt$Lambda$28
+       134: dup
+       135: aload         13
+       137: invokespecial #100                // Method com/example/compose/jetchat/components/AnimatingFabContentKt$Lambda$28."<init>":(Ljava/lang/Object;)V
+       140: astore        15
+       142: aload_0
+       143: aload_1
+       144: aload         14
+       146: checkcast     #102                // class kotlin/jvm/functions/Function0
+       149: aload         15
+       151: checkcast     #102                // class kotlin/jvm/functions/Function0
+       154: aload_2
+       155: aload         4
+       157: iconst_0
+       158: invokestatic  #106                // Method IconAndTextRow:(Lkotlin/jvm/functions/Function2;Lkotlin/jvm/functions/Function2;Lkotlin/jvm/functions/Function0;Lkotlin/jvm/functions/Function0;Landroidx/compose/ui/Modifier;Landroidx/compose/runtime/Composer;I)V
+       161: return
+
+  private static final kotlin.Unit AnimatingFabContent$lambda$0(kotlin.jvm.functions.Function2, kotlin.jvm.functions.Function2, androidx.compose.ui.Modifier, boolean, int, androidx.compose.runtime.Composer, int);
+    Code:
+         0: aload_0
+         1: aload_1
+         2: aload_2
+         3: iload_3
+         4: aload         5
+         6: iload         4
+         8: iconst_1
+         9: ior
+        10: invokestatic  #125                // Method androidx/compose/runtime/RecomposeScopeImplKt.updateChangedFlags:(I)I
+        13: invokestatic  #127                // Method AnimatingFabContent:(Lkotlin/jvm/functions/Function2;Lkotlin/jvm/functions/Function2;Landroidx/compose/ui/Modifier;ZLandroidx/compose/runtime/Composer;I)V
+        16: getstatic     #133                // Field kotlin/Unit.INSTANCE:Lkotlin/Unit;
+        19: areturn
+
+  public static void AnimatingFabContent$default(kotlin.jvm.functions.Function2, kotlin.jvm.functions.Function2, androidx.compose.ui.Modifier, boolean, androidx.compose.runtime.Composer, int, int, java.lang.Object);
+    Code:
+         0: iload         6
+         2: bipush        8
+         4: iand
+         5: ifeq          10
+         8: iconst_1
+         9: istore_3
+        10: aload_0
+        11: aload_1
+        12: aload_2
+        13: iload_3
+        14: aload         4
+        16: iload         5
+        18: invokestatic  #127                // Method AnimatingFabContent:(Lkotlin/jvm/functions/Function2;Lkotlin/jvm/functions/Function2;Landroidx/compose/ui/Modifier;ZLandroidx/compose/runtime/Composer;I)V
+        21: return
+
+  public static final <T> void IconAndTextRow(kotlin.jvm.functions.Function2, kotlin.jvm.functions.Function2, kotlin.jvm.functions.Function0, kotlin.jvm.functions.Function0, androidx.compose.ui.Modifier, androidx.compose.runtime.Composer, int);
+    Code:
+         0: aload         5
+         2: ldc           #159                // int -2022106602
+         4: invokeinterface #143,  2          // InterfaceMethod androidx/compose/runtime/Composer.startRestartGroup:(I)Landroidx/compose/runtime/Composer;
+         9: astore        5
+        11: aload         5
+        13: iload         6
+        15: ifeq          22
+        18: iconst_1
+        19: goto          23
+        22: iconst_0
+        23: iload         6
+        25: iconst_1
+        26: iand
+        27: invokeinterface #147,  3          // InterfaceMethod androidx/compose/runtime/Composer.shouldExecute:(ZI)Z
+        32: ifne          45
+        35: aload         5
+        37: invokeinterface #150,  1          // InterfaceMethod androidx/compose/runtime/Composer.skipToGroupEnd:()V
+        42: goto          85
+        45: new           #161                // class com/example/compose/jetchat/components/AnimatingFabContentKt$Lambda$29
+        48: dup
+        49: aload_0
+        50: aload_2
+        51: aload_1
+        52: invokespecial #164                // Method com/example/compose/jetchat/components/AnimatingFabContentKt$Lambda$29."<init>":(Lkotlin/jvm/functions/Function2;Lkotlin/jvm/functions/Function0;Lkotlin/jvm/functions/Function2;)V
+        55: astore        7
+        57: new           #166                // class com/example/compose/jetchat/components/AnimatingFabContentKt$Lambda$33
+        60: dup
+        61: aload_3
+        62: invokespecial #169                // Method com/example/compose/jetchat/components/AnimatingFabContentKt$Lambda$33."<init>":(Lkotlin/jvm/functions/Function0;)V
+        65: astore        8
+        67: aload         4
+        69: aload         7
+        71: checkcast     #171                // class androidx/compose/ui/layout/MeasurePolicy
+        74: aload         8
+        76: checkcast     #112                // class androidx/compose/runtime/Composer
+        79: iload         6
+        81: iconst_0
+        82: invokestatic  #177                // Method androidx/compose/ui/layout/LayoutKt.Layout:(Landroidx/compose/ui/Modifier;Landroidx/compose/ui/layout/MeasurePolicy;Landroidx/compose/runtime/Composer;II)V
+        85: aload         5
+        87: invokeinterface #154,  1          // InterfaceMethod androidx/compose/runtime/Composer.endRestartGroup:()Landroidx/compose/runtime/ScopeUpdateScope;
+        92: dup
+        93: ifnull        117
+        96: aload_0
+        97: aload_1
+        98: aload_2
+        99: aload_3
+       100: aload         4
+       102: iload         6
+       104: invokedynamic #189,  0            // InvokeDynamic #4:invoke:(Lkotlin/jvm/functions/Function2;Lkotlin/jvm/functions/Function2;Lkotlin/jvm/functions/Function0;Lkotlin/jvm/functions/Function0;Landroidx/compose/ui/Modifier;I)Lkotlin/jvm/functions/Function2;
+       109: invokeinterface #158,  2          // InterfaceMethod androidx/compose/runtime/ScopeUpdateScope.updateScope:(Lkotlin/jvm/functions/Function2;)V
+       114: goto          118
+       117: pop
+       118: return
+
+  private static final kotlin.Unit IconAndTextRow$lambda$0(kotlin.jvm.functions.Function2, kotlin.jvm.functions.Function2, kotlin.jvm.functions.Function0, kotlin.jvm.functions.Function0, androidx.compose.ui.Modifier, int, androidx.compose.runtime.Composer, int);
+    Code:
+         0: aload_0
+         1: aload_1
+         2: aload_2
+         3: aload_3
+         4: aload         4
+         6: aload         6
+         8: iload         5
+        10: iconst_1
+        11: ior
+        12: invokestatic  #125                // Method androidx/compose/runtime/RecomposeScopeImplKt.updateChangedFlags:(I)I
+        15: invokestatic  #106                // Method IconAndTextRow:(Lkotlin/jvm/functions/Function2;Lkotlin/jvm/functions/Function2;Lkotlin/jvm/functions/Function0;Lkotlin/jvm/functions/Function0;Landroidx/compose/ui/Modifier;Landroidx/compose/runtime/Composer;I)V
+        18: getstatic     #133                // Field kotlin/Unit.INSTANCE:Lkotlin/Unit;
+        21: areturn
+
+  public static final float AnimatingFabContent$lambda$0(java.lang.Object);
+    Code:
+         0: aconst_null
+         1: getfield      #32                 // Field com/example/compose/jetchat/components/ExpandableFabStates.Collapsed:Ljava/lang/Object;
+         4: aload_0
+         5: swap
+         6: if_acmpne     14
+         9: fconst_0
+        10: fstore_1
+        11: goto          16
+        14: fconst_1
+        15: fstore_1
+        16: fload_1
+        17: freturn
+
+  public static final float AnimatingFabContent$lambda$1(java.lang.Object);
+    Code:
+         0: aconst_null
+         1: getfield      #32                 // Field com/example/compose/jetchat/components/ExpandableFabStates.Collapsed:Ljava/lang/Object;
+         4: aload_0
+         5: swap
+         6: if_acmpne     14
+         9: fconst_0
+        10: fstore_1
+        11: goto          16
+        14: fconst_1
+        15: fstore_1
+        16: fload_1
+        17: freturn
+
+  public static final float AnimatingFabContent$lambda$2(java.lang.Object);
+    Code:
+         0: aconst_null
+         1: getfield      #32                 // Field com/example/compose/jetchat/components/ExpandableFabStates.Collapsed:Ljava/lang/Object;
+         4: aload_0
+         5: swap
+         6: if_acmpne     14
+         9: fconst_0
+        10: fstore_1
+        11: goto          16
+        14: fconst_1
+        15: fstore_1
+        16: fload_1
+        17: freturn
+
+  public static final float AnimatingFabContent$lambda$3(java.lang.Object);
+    Code:
+         0: aconst_null
+         1: getfield      #32                 // Field com/example/compose/jetchat/components/ExpandableFabStates.Collapsed:Ljava/lang/Object;
+         4: aload_0
+         5: swap
+         6: if_acmpne     14
+         9: fconst_0
+        10: fstore_1
+        11: goto          16
+        14: fconst_1
+        15: fstore_1
+        16: fload_1
+        17: freturn
+
+  public static final com.example.compose.jetchat.components.ExpandableFabStates Collapsed();
+    Code:
+         0: new           #25                 // class com/example/compose/jetchat/components/ExpandableFabStates
+         3: dup
+         4: ldc           #192                // String Collapsed
+         6: invokespecial #195                // Method com/example/compose/jetchat/components/ExpandableFabStates."<init>":(Ljava/lang/String;)V
+         9: areturn
+
+  public static final com.example.compose.jetchat.components.ExpandableFabStates Extended();
+    Code:
+         0: new           #25                 // class com/example/compose/jetchat/components/ExpandableFabStates
+         3: dup
+         4: ldc           #196                // String Extended
+         6: invokespecial #195                // Method com/example/compose/jetchat/components/ExpandableFabStates."<init>":(Ljava/lang/String;)V
+         9: areturn
+
+  public static final java.util.ArrayList ExpandableFabStates$values();
+    Code:
+         0: new           #200                // class java/util/ArrayList
+         3: dup
+         4: invokespecial #201                // Method java/util/ArrayList."<init>":()V
+         7: astore_0
+         8: aload_0
+         9: invokestatic  #203                // Method Collapsed:()Lcom/example/compose/jetchat/components/ExpandableFabStates;
+        12: invokevirtual #207                // Method java/util/ArrayList.add:(Ljava/lang/Object;)Z
+        15: pop
+        16: aload_0
+        17: invokestatic  #209                // Method Extended:()Lcom/example/compose/jetchat/components/ExpandableFabStates;
+        20: invokevirtual #207                // Method java/util/ArrayList.add:(Ljava/lang/Object;)Z
+        23: pop
+        24: aload_0
+        25: areturn
+
+  public static final com.example.compose.jetchat.components.ExpandableFabStates ExpandableFabStates$valueOf(java.lang.String);
+    Code:
+         0: aload_0
+         1: ldc           #213                // String name
+         3: invokestatic  #19                 // Method kotlin/jvm/internal/Intrinsics.checkNotNullParameter:(Ljava/lang/Object;Ljava/lang/String;)V
+         6: aload_0
+         7: ldc           #192                // String Collapsed
+         9: invokestatic  #217                // Method kotlin/jvm/internal/Intrinsics.areEqual:(Ljava/lang/Object;Ljava/lang/Object;)Z
+        12: ifeq          22
+        15: goto          35
+        18: invokestatic  #203                // Method Collapsed:()Lcom/example/compose/jetchat/components/ExpandableFabStates;
+        21: areturn
+        22: aload_0
+        23: ldc           #196                // String Extended
+        25: invokestatic  #217                // Method kotlin/jvm/internal/Intrinsics.areEqual:(Ljava/lang/Object;Ljava/lang/Object;)Z
+        28: ifeq          18
+        31: invokestatic  #209                // Method Extended:()Lcom/example/compose/jetchat/components/ExpandableFabStates;
+        34: areturn
+        35: invokestatic  #203                // Method Collapsed:()Lcom/example/compose/jetchat/components/ExpandableFabStates;
+        38: areturn
 }
