--- ./gradle/com.example.compose.jetchat.components.JetchatDrawerKt.javap	2026-05-24 23:07:45
+++ ./skotch/com.example.compose.jetchat.components.JetchatDrawerKt.javap	2026-05-24 23:07:45
@@ -1,3051 +1,560 @@
-Compiled from "JetchatDrawer.kt"
-public final class com.example.compose.jetchat.components.JetchatDrawerKt {
-  public static final void JetchatDrawerContent(kotlin.jvm.functions.Function1<? super java.lang.String, kotlin.Unit>, kotlin.jvm.functions.Function1<? super java.lang.String, kotlin.Unit>, java.lang.String, androidx.compose.runtime.Composer, int, int);
-    Code:
-         0: aload_0
-         1: ldc           #15                 // String onProfileClicked
-         3: invokestatic  #21                 // Method kotlin/jvm/internal/Intrinsics.checkNotNullParameter:(Ljava/lang/Object;Ljava/lang/String;)V
-         6: aload_1
-         7: ldc           #23                 // String onChatClicked
-         9: invokestatic  #21                 // Method kotlin/jvm/internal/Intrinsics.checkNotNullParameter:(Ljava/lang/Object;Ljava/lang/String;)V
-        12: aload_3
-        13: ldc           #24                 // int 98085172
-        15: invokeinterface #30,  2           // InterfaceMethod androidx/compose/runtime/Composer.startRestartGroup:(I)Landroidx/compose/runtime/Composer;
-        20: astore_3
-        21: aload_3
-        22: ldc           #32                 // String C(JetchatDrawerContent)N(onProfileClicked,onChatClicked,selectedMenu)67@2981L1116:JetchatDrawer.kt#o9oqao
-        24: invokestatic  #38                 // Method androidx/compose/runtime/ComposerKt.sourceInformation:(Landroidx/compose/runtime/Composer;Ljava/lang/String;)V
-        27: iload         4
-        29: istore        6
-        31: iload         4
-        33: bipush        6
-        35: iand
-        36: ifne          59
-        39: iload         6
-        41: aload_3
-        42: aload_0
-        43: invokeinterface #42,  2           // InterfaceMethod androidx/compose/runtime/Composer.changedInstance:(Ljava/lang/Object;)Z
-        48: ifeq          55
-        51: iconst_4
-        52: goto          56
-        55: iconst_2
-        56: ior
-        57: istore        6
-        59: iload         4
-        61: bipush        48
-        63: iand
-        64: ifne          89
-        67: iload         6
-        69: aload_3
-        70: aload_1
-        71: invokeinterface #42,  2           // InterfaceMethod androidx/compose/runtime/Composer.changedInstance:(Ljava/lang/Object;)Z
-        76: ifeq          84
-        79: bipush        32
-        81: goto          86
-        84: bipush        16
-        86: ior
-        87: istore        6
-        89: iload         5
-        91: iconst_4
-        92: iand
-        93: ifeq          107
-        96: iload         6
-        98: sipush        384
-       101: ior
-       102: istore        6
-       104: goto          140
-       107: iload         4
-       109: sipush        384
-       112: iand
-       113: ifne          140
-       116: iload         6
-       118: aload_3
-       119: aload_2
-       120: invokeinterface #45,  2           // InterfaceMethod androidx/compose/runtime/Composer.changed:(Ljava/lang/Object;)Z
-       125: ifeq          134
-       128: sipush        256
-       131: goto          137
-       134: sipush        128
-       137: ior
-       138: istore        6
-       140: aload_3
-       141: iload         6
-       143: sipush        147
-       146: iand
-       147: sipush        146
-       150: if_icmpeq     157
-       153: iconst_1
-       154: goto          158
-       157: iconst_0
-       158: iload         6
-       160: iconst_1
-       161: iand
-       162: invokeinterface #49,  3           // InterfaceMethod androidx/compose/runtime/Composer.shouldExecute:(ZI)Z
-       167: ifeq          1405
-       170: iload         5
-       172: iconst_4
-       173: iand
-       174: ifeq          180
-       177: ldc           #51                 // String composers
-       179: astore_2
-       180: invokestatic  #55                 // Method androidx/compose/runtime/ComposerKt.isTraceInProgress:()Z
-       183: ifeq          196
-       186: ldc           #24                 // int 98085172
-       188: iload         6
-       190: iconst_m1
-       191: ldc           #57                 // String com.example.compose.jetchat.components.JetchatDrawerContent (JetchatDrawer.kt:64)
-       193: invokestatic  #61                 // Method androidx/compose/runtime/ComposerKt.traceEventStart:(IIILjava/lang/String;)V
-       196: aload_3
-       197: astore        10
-       199: iconst_0
-       200: istore        11
-       202: nop
-       203: iconst_0
-       204: istore        12
-       206: aload         10
-       208: ldc           #62                 // int 1341605231
-       210: ldc           #64                 // String CC(Column)N(modifier,verticalArrangement,horizontalAlignment,content)87@4443L61,88@4509L134:Column.kt#2w3rfo
-       212: invokestatic  #68                 // Method androidx/compose/runtime/ComposerKt.sourceInformationMarkerStart:(Landroidx/compose/runtime/Composer;ILjava/lang/String;)V
-       215: getstatic     #74                 // Field androidx/compose/ui/Modifier.Companion:Landroidx/compose/ui/Modifier$Companion;
-       218: checkcast     #70                 // class androidx/compose/ui/Modifier
-       221: astore        7
-       223: getstatic     #80                 // Field androidx/compose/foundation/layout/Arrangement.INSTANCE:Landroidx/compose/foundation/layout/Arrangement;
-       226: invokevirtual #84                 // Method androidx/compose/foundation/layout/Arrangement.getTop:()Landroidx/compose/foundation/layout/Arrangement$Vertical;
-       229: astore        8
-       231: getstatic     #89                 // Field androidx/compose/ui/Alignment.Companion:Landroidx/compose/ui/Alignment$Companion;
-       234: invokevirtual #95                 // Method androidx/compose/ui/Alignment$Companion.getStart:()Landroidx/compose/ui/Alignment$Horizontal;
-       237: astore        9
-       239: aload         8
-       241: aload         9
-       243: aload         10
-       245: bipush        14
-       247: iload         11
-       249: iconst_3
-       250: ishr
-       251: iand
-       252: bipush        112
-       254: iload         11
-       256: iconst_3
-       257: ishr
-       258: iand
-       259: ior
-       260: invokestatic  #101                // Method androidx/compose/foundation/layout/ColumnKt.columnMeasurePolicy:(Landroidx/compose/foundation/layout/Arrangement$Vertical;Landroidx/compose/ui/Alignment$Horizontal;Landroidx/compose/runtime/Composer;I)Landroidx/compose/ui/layout/MeasurePolicy;
-       263: astore        13
-       265: aload         7
-       267: astore        14
-       269: aload         13
-       271: astore        15
-       273: aload         10
-       275: astore        16
-       277: bipush        112
-       279: iload         11
-       281: iconst_3
-       282: ishl
-       283: iand
-       284: istore        17
-       286: nop
-       287: iconst_0
-       288: istore        18
-       290: aload         16
-       292: ldc           #102                // int -1159599143
-       294: ldc           #104                // String CC(Layout)P(!1,2)81@3355L27,84@3521L416:Layout.kt#80mrfh
-       296: invokestatic  #68                 // Method androidx/compose/runtime/ComposerKt.sourceInformationMarkerStart:(Landroidx/compose/runtime/Composer;ILjava/lang/String;)V
-       299: aload         16
-       301: iconst_0
-       302: invokestatic  #110                // Method androidx/compose/runtime/ComposablesKt.getCurrentCompositeKeyHashCode:(Landroidx/compose/runtime/Composer;I)J
-       305: invokestatic  #116                // Method java/lang/Long.hashCode:(J)I
-       308: istore        19
-       310: aload         16
-       312: invokeinterface #120,  1          // InterfaceMethod androidx/compose/runtime/Composer.getCurrentCompositionLocalMap:()Landroidx/compose/runtime/CompositionLocalMap;
-       317: astore        20
-       319: aload         16
-       321: aload         14
-       323: invokestatic  #126                // Method androidx/compose/ui/ComposedModifierKt.materializeModifier:(Landroidx/compose/runtime/Composer;Landroidx/compose/ui/Modifier;)Landroidx/compose/ui/Modifier;
-       326: astore        21
-       328: getstatic     #131                // Field androidx/compose/ui/node/ComposeUiNode.Companion:Landroidx/compose/ui/node/ComposeUiNode$Companion;
-       331: invokevirtual #137                // Method androidx/compose/ui/node/ComposeUiNode$Companion.getConstructor:()Lkotlin/jvm/functions/Function0;
-       334: astore        22
-       336: aload         16
-       338: astore        23
-       340: bipush        6
-       342: sipush        896
-       345: iload         17
-       347: bipush        6
-       349: ishl
-       350: iand
-       351: ior
-       352: istore        24
-       354: nop
-       355: iconst_0
-       356: istore        25
-       358: aload         23
-       360: ldc           #138                // int -553112988
-       362: ldc           #140                // String CC(ReusableComposeNode)N(factory,update,content)399@15590L9:Composables.kt#9igjgp
-       364: invokestatic  #68                 // Method androidx/compose/runtime/ComposerKt.sourceInformationMarkerStart:(Landroidx/compose/runtime/Composer;ILjava/lang/String;)V
-       367: aload         23
-       369: invokeinterface #144,  1          // InterfaceMethod androidx/compose/runtime/Composer.getApplier:()Landroidx/compose/runtime/Applier;
-       374: instanceof    #146                // class androidx/compose/runtime/Applier
-       377: ifne          383
-       380: invokestatic  #150                // Method androidx/compose/runtime/ComposablesKt.invalidApplier:()V
-       383: aload         23
-       385: invokeinterface #153,  1          // InterfaceMethod androidx/compose/runtime/Composer.startReusableNode:()V
-       390: aload         23
-       392: invokeinterface #156,  1          // InterfaceMethod androidx/compose/runtime/Composer.getInserting:()Z
-       397: ifeq          412
-       400: aload         23
-       402: aload         22
-       404: invokeinterface #160,  2          // InterfaceMethod androidx/compose/runtime/Composer.createNode:(Lkotlin/jvm/functions/Function0;)V
-       409: goto          419
-       412: aload         23
-       414: invokeinterface #163,  1          // InterfaceMethod androidx/compose/runtime/Composer.useNode:()V
-       419: aload         23
-       421: invokestatic  #169                // Method androidx/compose/runtime/Updater."constructor-impl":(Landroidx/compose/runtime/Composer;)Landroidx/compose/runtime/Composer;
-       424: astore        26
-       426: iconst_0
-       427: istore        27
-       429: aload         26
-       431: aload         15
-       433: getstatic     #131                // Field androidx/compose/ui/node/ComposeUiNode.Companion:Landroidx/compose/ui/node/ComposeUiNode$Companion;
-       436: invokevirtual #173                // Method androidx/compose/ui/node/ComposeUiNode$Companion.getSetMeasurePolicy:()Lkotlin/jvm/functions/Function2;
-       439: invokestatic  #177                // Method androidx/compose/runtime/Updater."set-impl":(Landroidx/compose/runtime/Composer;Ljava/lang/Object;Lkotlin/jvm/functions/Function2;)V
-       442: aload         26
-       444: aload         20
-       446: getstatic     #131                // Field androidx/compose/ui/node/ComposeUiNode.Companion:Landroidx/compose/ui/node/ComposeUiNode$Companion;
-       449: invokevirtual #180                // Method androidx/compose/ui/node/ComposeUiNode$Companion.getSetResolvedCompositionLocals:()Lkotlin/jvm/functions/Function2;
-       452: invokestatic  #177                // Method androidx/compose/runtime/Updater."set-impl":(Landroidx/compose/runtime/Composer;Ljava/lang/Object;Lkotlin/jvm/functions/Function2;)V
-       455: aload         26
-       457: iload         19
-       459: invokestatic  #186                // Method java/lang/Integer.valueOf:(I)Ljava/lang/Integer;
-       462: getstatic     #131                // Field androidx/compose/ui/node/ComposeUiNode.Companion:Landroidx/compose/ui/node/ComposeUiNode$Companion;
-       465: invokevirtual #189                // Method androidx/compose/ui/node/ComposeUiNode$Companion.getSetCompositeKeyHash:()Lkotlin/jvm/functions/Function2;
-       468: invokestatic  #192                // Method androidx/compose/runtime/Updater."init-impl":(Landroidx/compose/runtime/Composer;Ljava/lang/Object;Lkotlin/jvm/functions/Function2;)V
-       471: aload         26
-       473: getstatic     #131                // Field androidx/compose/ui/node/ComposeUiNode.Companion:Landroidx/compose/ui/node/ComposeUiNode$Companion;
-       476: invokevirtual #196                // Method androidx/compose/ui/node/ComposeUiNode$Companion.getApplyOnDeactivatedNodeAssertion:()Lkotlin/jvm/functions/Function1;
-       479: invokestatic  #200                // Method androidx/compose/runtime/Updater."reconcile-impl":(Landroidx/compose/runtime/Composer;Lkotlin/jvm/functions/Function1;)V
-       482: aload         26
-       484: aload         21
-       486: getstatic     #131                // Field androidx/compose/ui/node/ComposeUiNode.Companion:Landroidx/compose/ui/node/ComposeUiNode$Companion;
-       489: invokevirtual #203                // Method androidx/compose/ui/node/ComposeUiNode$Companion.getSetModifier:()Lkotlin/jvm/functions/Function2;
-       492: invokestatic  #177                // Method androidx/compose/runtime/Updater."set-impl":(Landroidx/compose/runtime/Composer;Ljava/lang/Object;Lkotlin/jvm/functions/Function2;)V
-       495: nop
-       496: nop
-       497: aload         23
-       499: bipush        14
-       501: iload         24
-       503: bipush        6
-       505: ishr
-       506: iand
-       507: istore        28
-       509: astore        29
-       511: iconst_0
-       512: istore        30
-       514: aload         29
-       516: ldc           #204                // int 2093002350
-       518: ldc           #206                // String C89@4557L9:Column.kt#2w3rfo
-       520: invokestatic  #68                 // Method androidx/compose/runtime/ComposerKt.sourceInformationMarkerStart:(Landroidx/compose/runtime/Composer;ILjava/lang/String;)V
-       523: getstatic     #211                // Field androidx/compose/foundation/layout/ColumnScopeInstance.INSTANCE:Landroidx/compose/foundation/layout/ColumnScopeInstance;
-       526: aload         29
-       528: bipush        6
-       530: bipush        112
-       532: iload         11
-       534: bipush        6
-       536: ishr
-       537: iand
-       538: ior
-       539: istore        31
-       541: astore        32
-       543: checkcast     #213                // class androidx/compose/foundation/layout/ColumnScope
-       546: astore        33
-       548: iconst_0
-       549: istore        34
-       551: aload         32
-       553: ldc           #214                // int -329983948
-       555: ldc           #216                // String C68@3049L10,68@2998L63,69@3070L14,70@3093L13,71@3115L25,72@3200L50,72@3149L101,75@3316L53,75@3259L110,78@3378L60,79@3447L35,83@3609L58,80@3491L176,89@3805L65,86@3676L194,92@3920L7:JetchatDrawer.kt#o9oqao
-       557: invokestatic  #68                 // Method androidx/compose/runtime/ComposerKt.sourceInformationMarkerStart:(Landroidx/compose/runtime/Composer;ILjava/lang/String;)V
-       560: getstatic     #74                 // Field androidx/compose/ui/Modifier.Companion:Landroidx/compose/ui/Modifier$Companion;
-       563: checkcast     #70                 // class androidx/compose/ui/Modifier
-       566: getstatic     #221                // Field androidx/compose/foundation/layout/WindowInsets.Companion:Landroidx/compose/foundation/layout/WindowInsets$Companion;
-       569: aload         32
-       571: bipush        6
-       573: invokestatic  #227                // Method androidx/compose/foundation/layout/WindowInsets_androidKt.getStatusBars:(Landroidx/compose/foundation/layout/WindowInsets$Companion;Landroidx/compose/runtime/Composer;I)Landroidx/compose/foundation/layout/WindowInsets;
-       576: invokestatic  #233                // Method androidx/compose/foundation/layout/WindowInsetsSizeKt.windowInsetsTopHeight:(Landroidx/compose/ui/Modifier;Landroidx/compose/foundation/layout/WindowInsets;)Landroidx/compose/ui/Modifier;
-       579: aload         32
-       581: iconst_0
-       582: invokestatic  #239                // Method androidx/compose/foundation/layout/SpacerKt.Spacer:(Landroidx/compose/ui/Modifier;Landroidx/compose/runtime/Composer;I)V
-       585: aload         32
-       587: iconst_0
-       588: invokestatic  #243                // Method DrawerHeader:(Landroidx/compose/runtime/Composer;I)V
-       591: aconst_null
-       592: aload         32
-       594: iconst_0
-       595: iconst_1
-       596: invokestatic  #247                // Method DividerItem:(Landroidx/compose/ui/Modifier;Landroidx/compose/runtime/Composer;II)V
-       599: ldc           #249                // String Chats
-       601: aload         32
-       603: bipush        6
-       605: invokestatic  #253                // Method DrawerItemHeader:(Ljava/lang/String;Landroidx/compose/runtime/Composer;I)V
-       608: ldc           #51                 // String composers
-       610: aload_2
-       611: ldc           #51                 // String composers
-       613: invokestatic  #257                // Method kotlin/jvm/internal/Intrinsics.areEqual:(Ljava/lang/Object;Ljava/lang/Object;)Z
-       616: aload         32
-       618: ldc_w         #258                // int -1534659876
-       621: ldc_w         #260                // String CC(remember):JetchatDrawer.kt#9igjgp
-       624: invokestatic  #68                 // Method androidx/compose/runtime/ComposerKt.sourceInformationMarkerStart:(Landroidx/compose/runtime/Composer;ILjava/lang/String;)V
-       627: aload         32
-       629: astore        35
-       631: iload         6
-       633: bipush        112
-       635: iand
-       636: bipush        32
-       638: if_icmpne     645
-       641: iconst_1
-       642: goto          646
-       645: iconst_0
-       646: istore        36
-       648: iconst_0
-       649: istore        37
-       651: aload         35
-       653: invokeinterface #264,  1          // InterfaceMethod androidx/compose/runtime/Composer.rememberedValue:()Ljava/lang/Object;
-       658: astore        38
-       660: iconst_0
-       661: istore        39
-       663: iload         36
-       665: ifne          679
-       668: aload         38
-       670: getstatic     #267                // Field androidx/compose/runtime/Composer.Companion:Landroidx/compose/runtime/Composer$Companion;
-       673: invokevirtual #272                // Method androidx/compose/runtime/Composer$Companion.getEmpty:()Ljava/lang/Object;
-       676: if_acmpne     716
-       679: istore        40
-       681: astore        41
-       683: iconst_0
-       684: istore        42
-       686: aload_1
-       687: invokedynamic #291,  0            // InvokeDynamic #0:invoke:(Lkotlin/jvm/functions/Function1;)Lkotlin/jvm/functions/Function0;
-       692: astore        43
-       694: aload         41
-       696: iload         40
-       698: aload         43
-       700: astore        44
-       702: aload         35
-       704: aload         44
-       706: invokeinterface #295,  2          // InterfaceMethod androidx/compose/runtime/Composer.updateRememberedValue:(Ljava/lang/Object;)V
-       711: aload         44
-       713: goto          718
-       716: aload         38
-       718: nop
-       719: nop
-       720: checkcast     #297                // class kotlin/jvm/functions/Function0
-       723: astore        45
-       725: aload         32
-       727: invokestatic  #301                // Method androidx/compose/runtime/ComposerKt.sourceInformationMarkerEnd:(Landroidx/compose/runtime/Composer;)V
-       730: aload         45
-       732: aload         32
-       734: bipush        6
-       736: invokestatic  #305                // Method ChatItem:(Ljava/lang/String;ZLkotlin/jvm/functions/Function0;Landroidx/compose/runtime/Composer;I)V
-       739: ldc_w         #307                // String droidcon-nyc
-       742: aload_2
-       743: ldc_w         #307                // String droidcon-nyc
-       746: invokestatic  #257                // Method kotlin/jvm/internal/Intrinsics.areEqual:(Ljava/lang/Object;Ljava/lang/Object;)Z
-       749: aload         32
-       751: ldc_w         #308                // int -1534656161
-       754: ldc_w         #260                // String CC(remember):JetchatDrawer.kt#9igjgp
-       757: invokestatic  #68                 // Method androidx/compose/runtime/ComposerKt.sourceInformationMarkerStart:(Landroidx/compose/runtime/Composer;ILjava/lang/String;)V
-       760: aload         32
-       762: astore        35
-       764: iload         6
-       766: bipush        112
-       768: iand
-       769: bipush        32
-       771: if_icmpne     778
-       774: iconst_1
-       775: goto          779
-       778: iconst_0
-       779: istore        36
-       781: iconst_0
-       782: istore        37
-       784: aload         35
-       786: invokeinterface #264,  1          // InterfaceMethod androidx/compose/runtime/Composer.rememberedValue:()Ljava/lang/Object;
-       791: astore        38
-       793: iconst_0
-       794: istore        39
-       796: iload         36
-       798: ifne          812
-       801: aload         38
-       803: getstatic     #267                // Field androidx/compose/runtime/Composer.Companion:Landroidx/compose/runtime/Composer$Companion;
-       806: invokevirtual #272                // Method androidx/compose/runtime/Composer$Companion.getEmpty:()Ljava/lang/Object;
-       809: if_acmpne     849
-       812: istore        40
-       814: astore        41
-       816: iconst_0
-       817: istore        42
-       819: aload_1
-       820: invokedynamic #313,  0            // InvokeDynamic #1:invoke:(Lkotlin/jvm/functions/Function1;)Lkotlin/jvm/functions/Function0;
-       825: astore        43
-       827: aload         41
-       829: iload         40
-       831: aload         43
-       833: astore        44
-       835: aload         35
-       837: aload         44
-       839: invokeinterface #295,  2          // InterfaceMethod androidx/compose/runtime/Composer.updateRememberedValue:(Ljava/lang/Object;)V
-       844: aload         44
-       846: goto          851
-       849: aload         38
-       851: nop
-       852: nop
-       853: checkcast     #297                // class kotlin/jvm/functions/Function0
-       856: astore        45
-       858: aload         32
-       860: invokestatic  #301                // Method androidx/compose/runtime/ComposerKt.sourceInformationMarkerEnd:(Landroidx/compose/runtime/Composer;)V
-       863: aload         45
-       865: aload         32
-       867: bipush        6
-       869: invokestatic  #305                // Method ChatItem:(Ljava/lang/String;ZLkotlin/jvm/functions/Function0;Landroidx/compose/runtime/Composer;I)V
-       872: getstatic     #74                 // Field androidx/compose/ui/Modifier.Companion:Landroidx/compose/ui/Modifier$Companion;
-       875: checkcast     #70                 // class androidx/compose/ui/Modifier
-       878: bipush        28
-       880: istore        45
-       882: iconst_0
-       883: istore        35
-       885: iload         45
-       887: i2f
-       888: invokestatic  #318                // Method androidx/compose/ui/unit/Dp."constructor-impl":(F)F
-       891: fconst_0
-       892: iconst_2
-       893: aconst_null
-       894: invokestatic  #324                // Method androidx/compose/foundation/layout/PaddingKt."padding-VpY3zN4$default":(Landroidx/compose/ui/Modifier;FFILjava/lang/Object;)Landroidx/compose/ui/Modifier;
-       897: aload         32
-       899: bipush        6
-       901: iconst_0
-       902: invokestatic  #247                // Method DividerItem:(Landroidx/compose/ui/Modifier;Landroidx/compose/runtime/Composer;II)V
-       905: ldc_w         #326                // String Recent Profiles
-       908: aload         32
-       910: bipush        6
-       912: invokestatic  #253                // Method DrawerItemHeader:(Ljava/lang/String;Landroidx/compose/runtime/Composer;I)V
-       915: ldc_w         #328                // String Ali Conors (you)
-       918: invokestatic  #334                // Method com/example/compose/jetchat/data/FakeDataKt.getMeProfile:()Lcom/example/compose/jetchat/profile/ProfileScreenState;
-       921: invokevirtual #340                // Method com/example/compose/jetchat/profile/ProfileScreenState.getPhoto:()Ljava/lang/Integer;
-       924: aload_2
-       925: invokestatic  #334                // Method com/example/compose/jetchat/data/FakeDataKt.getMeProfile:()Lcom/example/compose/jetchat/profile/ProfileScreenState;
-       928: invokevirtual #344                // Method com/example/compose/jetchat/profile/ProfileScreenState.getUserId:()Ljava/lang/String;
-       931: invokestatic  #257                // Method kotlin/jvm/internal/Intrinsics.areEqual:(Ljava/lang/Object;Ljava/lang/Object;)Z
-       934: aload         32
-       936: ldc_w         #345                // int -1534646780
-       939: ldc_w         #260                // String CC(remember):JetchatDrawer.kt#9igjgp
-       942: invokestatic  #68                 // Method androidx/compose/runtime/ComposerKt.sourceInformationMarkerStart:(Landroidx/compose/runtime/Composer;ILjava/lang/String;)V
-       945: aload         32
-       947: astore        35
-       949: iload         6
-       951: bipush        14
-       953: iand
-       954: iconst_4
-       955: if_icmpne     962
-       958: iconst_1
-       959: goto          963
-       962: iconst_0
-       963: istore        36
-       965: iconst_0
-       966: istore        37
-       968: aload         35
-       970: invokeinterface #264,  1          // InterfaceMethod androidx/compose/runtime/Composer.rememberedValue:()Ljava/lang/Object;
-       975: astore        38
-       977: iconst_0
-       978: istore        39
-       980: iload         36
-       982: ifne          996
-       985: aload         38
-       987: getstatic     #267                // Field androidx/compose/runtime/Composer.Companion:Landroidx/compose/runtime/Composer$Companion;
-       990: invokevirtual #272                // Method androidx/compose/runtime/Composer$Companion.getEmpty:()Ljava/lang/Object;
-       993: if_acmpne     1037
-       996: istore        43
-       998: astore        40
-      1000: astore        41
-      1002: iconst_0
-      1003: istore        42
-      1005: aload_0
-      1006: invokedynamic #350,  0            // InvokeDynamic #2:invoke:(Lkotlin/jvm/functions/Function1;)Lkotlin/jvm/functions/Function0;
-      1011: astore        46
-      1013: aload         41
-      1015: aload         40
-      1017: iload         43
-      1019: aload         46
-      1021: astore        44
-      1023: aload         35
-      1025: aload         44
-      1027: invokeinterface #295,  2          // InterfaceMethod androidx/compose/runtime/Composer.updateRememberedValue:(Ljava/lang/Object;)V
-      1032: aload         44
-      1034: goto          1039
-      1037: aload         38
-      1039: nop
-      1040: nop
-      1041: checkcast     #297                // class kotlin/jvm/functions/Function0
-      1044: astore        45
-      1046: aload         32
-      1048: invokestatic  #301                // Method androidx/compose/runtime/ComposerKt.sourceInformationMarkerEnd:(Landroidx/compose/runtime/Composer;)V
-      1051: aload         45
-      1053: aload         32
-      1055: bipush        54
-      1057: iconst_0
-      1058: invokestatic  #354                // Method ProfileItem:(Ljava/lang/String;Ljava/lang/Integer;ZLkotlin/jvm/functions/Function0;Landroidx/compose/runtime/Composer;II)V
-      1061: ldc_w         #356                // String Taylor Brooks
-      1064: invokestatic  #359                // Method com/example/compose/jetchat/data/FakeDataKt.getColleagueProfile:()Lcom/example/compose/jetchat/profile/ProfileScreenState;
-      1067: invokevirtual #340                // Method com/example/compose/jetchat/profile/ProfileScreenState.getPhoto:()Ljava/lang/Integer;
-      1070: aload_2
-      1071: invokestatic  #359                // Method com/example/compose/jetchat/data/FakeDataKt.getColleagueProfile:()Lcom/example/compose/jetchat/profile/ProfileScreenState;
-      1074: invokevirtual #344                // Method com/example/compose/jetchat/profile/ProfileScreenState.getUserId:()Ljava/lang/String;
-      1077: invokestatic  #257                // Method kotlin/jvm/internal/Intrinsics.areEqual:(Ljava/lang/Object;Ljava/lang/Object;)Z
-      1080: aload         32
-      1082: ldc_w         #360                // int -1534640501
-      1085: ldc_w         #260                // String CC(remember):JetchatDrawer.kt#9igjgp
-      1088: invokestatic  #68                 // Method androidx/compose/runtime/ComposerKt.sourceInformationMarkerStart:(Landroidx/compose/runtime/Composer;ILjava/lang/String;)V
-      1091: aload         32
-      1093: astore        35
-      1095: iload         6
-      1097: bipush        14
-      1099: iand
-      1100: iconst_4
-      1101: if_icmpne     1108
-      1104: iconst_1
-      1105: goto          1109
-      1108: iconst_0
-      1109: istore        36
-      1111: iconst_0
-      1112: istore        37
-      1114: aload         35
-      1116: invokeinterface #264,  1          // InterfaceMethod androidx/compose/runtime/Composer.rememberedValue:()Ljava/lang/Object;
-      1121: astore        38
-      1123: iconst_0
-      1124: istore        39
-      1126: iload         36
-      1128: ifne          1142
-      1131: aload         38
-      1133: getstatic     #267                // Field androidx/compose/runtime/Composer.Companion:Landroidx/compose/runtime/Composer$Companion;
-      1136: invokevirtual #272                // Method androidx/compose/runtime/Composer$Companion.getEmpty:()Ljava/lang/Object;
-      1139: if_acmpne     1183
-      1142: istore        43
-      1144: astore        40
-      1146: astore        41
-      1148: iconst_0
-      1149: istore        42
-      1151: aload_0
-      1152: invokedynamic #365,  0            // InvokeDynamic #3:invoke:(Lkotlin/jvm/functions/Function1;)Lkotlin/jvm/functions/Function0;
-      1157: astore        46
-      1159: aload         41
-      1161: aload         40
-      1163: iload         43
-      1165: aload         46
-      1167: astore        44
-      1169: aload         35
-      1171: aload         44
-      1173: invokeinterface #295,  2          // InterfaceMethod androidx/compose/runtime/Composer.updateRememberedValue:(Ljava/lang/Object;)V
-      1178: aload         44
-      1180: goto          1185
-      1183: aload         38
-      1185: nop
-      1186: nop
-      1187: checkcast     #297                // class kotlin/jvm/functions/Function0
-      1190: astore        45
-      1192: aload         32
-      1194: invokestatic  #301                // Method androidx/compose/runtime/ComposerKt.sourceInformationMarkerEnd:(Landroidx/compose/runtime/Composer;)V
-      1197: aload         45
-      1199: aload         32
-      1201: bipush        54
-      1203: iconst_0
-      1204: invokestatic  #354                // Method ProfileItem:(Ljava/lang/String;Ljava/lang/Integer;ZLkotlin/jvm/functions/Function0;Landroidx/compose/runtime/Composer;II)V
-      1207: invokestatic  #371                // Method androidx/compose/ui/platform/AndroidCompositionLocals_androidKt.getLocalContext:()Landroidx/compose/runtime/ProvidableCompositionLocal;
-      1210: checkcast     #373                // class androidx/compose/runtime/CompositionLocal
-      1213: astore        45
-      1215: aload         32
-      1217: astore        35
-      1219: iconst_0
-      1220: istore        36
-      1222: iconst_0
-      1223: istore        37
-      1225: aload         35
-      1227: ldc_w         #374                // int 2023513938
-      1230: ldc_w         #376                // String CC(<get-current>):CompositionLocal.kt#9igjgp
-      1233: invokestatic  #68                 // Method androidx/compose/runtime/ComposerKt.sourceInformationMarkerStart:(Landroidx/compose/runtime/Composer;ILjava/lang/String;)V
-      1236: aload         35
-      1238: aload         45
-      1240: invokeinterface #380,  2          // InterfaceMethod androidx/compose/runtime/Composer.consume:(Landroidx/compose/runtime/CompositionLocal;)Ljava/lang/Object;
-      1245: astore        38
-      1247: aload         35
-      1249: invokestatic  #301                // Method androidx/compose/runtime/ComposerKt.sourceInformationMarkerEnd:(Landroidx/compose/runtime/Composer;)V
-      1252: aload         38
-      1254: checkcast     #382                // class android/content/Context
-      1257: invokestatic  #386                // Method widgetAddingIsSupported:(Landroid/content/Context;)Z
-      1260: ifeq          1340
-      1263: aload         32
-      1265: ldc_w         #387                // int -329088297
-      1268: invokeinterface #391,  2          // InterfaceMethod androidx/compose/runtime/Composer.startReplaceGroup:(I)V
-      1273: aload         32
-      1275: ldc_w         #393                // String 93@3944L60,94@4017L28,95@4058L23
-      1278: invokestatic  #38                 // Method androidx/compose/runtime/ComposerKt.sourceInformation:(Landroidx/compose/runtime/Composer;Ljava/lang/String;)V
-      1281: getstatic     #74                 // Field androidx/compose/ui/Modifier.Companion:Landroidx/compose/ui/Modifier$Companion;
-      1284: checkcast     #70                 // class androidx/compose/ui/Modifier
-      1287: bipush        28
-      1289: istore        45
-      1291: iconst_0
-      1292: istore        35
-      1294: iload         45
-      1296: i2f
-      1297: invokestatic  #318                // Method androidx/compose/ui/unit/Dp."constructor-impl":(F)F
-      1300: fconst_0
-      1301: iconst_2
-      1302: aconst_null
-      1303: invokestatic  #324                // Method androidx/compose/foundation/layout/PaddingKt."padding-VpY3zN4$default":(Landroidx/compose/ui/Modifier;FFILjava/lang/Object;)Landroidx/compose/ui/Modifier;
-      1306: aload         32
-      1308: bipush        6
-      1310: iconst_0
-      1311: invokestatic  #247                // Method DividerItem:(Landroidx/compose/ui/Modifier;Landroidx/compose/runtime/Composer;II)V
-      1314: ldc_w         #395                // String Settings
-      1317: aload         32
-      1319: bipush        6
-      1321: invokestatic  #253                // Method DrawerItemHeader:(Ljava/lang/String;Landroidx/compose/runtime/Composer;I)V
-      1324: aload         32
-      1326: iconst_0
-      1327: invokestatic  #398                // Method WidgetDiscoverability:(Landroidx/compose/runtime/Composer;I)V
-      1330: aload         32
-      1332: invokeinterface #401,  1          // InterfaceMethod androidx/compose/runtime/Composer.endReplaceGroup:()V
-      1337: goto          1357
-      1340: aload         32
-      1342: ldc_w         #402                // int -328933576
-      1345: invokeinterface #391,  2          // InterfaceMethod androidx/compose/runtime/Composer.startReplaceGroup:(I)V
-      1350: aload         32
-      1352: invokeinterface #401,  1          // InterfaceMethod androidx/compose/runtime/Composer.endReplaceGroup:()V
-      1357: aload         32
-      1359: invokestatic  #301                // Method androidx/compose/runtime/ComposerKt.sourceInformationMarkerEnd:(Landroidx/compose/runtime/Composer;)V
-      1362: nop
-      1363: aload         29
-      1365: invokestatic  #301                // Method androidx/compose/runtime/ComposerKt.sourceInformationMarkerEnd:(Landroidx/compose/runtime/Composer;)V
-      1368: aload         23
-      1370: invokeinterface #405,  1          // InterfaceMethod androidx/compose/runtime/Composer.endNode:()V
-      1375: aload         23
-      1377: invokestatic  #301                // Method androidx/compose/runtime/ComposerKt.sourceInformationMarkerEnd:(Landroidx/compose/runtime/Composer;)V
-      1380: nop
-      1381: aload         16
-      1383: invokestatic  #301                // Method androidx/compose/runtime/ComposerKt.sourceInformationMarkerEnd:(Landroidx/compose/runtime/Composer;)V
-      1386: nop
-      1387: aload         10
-      1389: invokestatic  #301                // Method androidx/compose/runtime/ComposerKt.sourceInformationMarkerEnd:(Landroidx/compose/runtime/Composer;)V
-      1392: nop
-      1393: invokestatic  #55                 // Method androidx/compose/runtime/ComposerKt.isTraceInProgress:()Z
-      1396: ifeq          1411
-      1399: invokestatic  #408                // Method androidx/compose/runtime/ComposerKt.traceEventEnd:()V
-      1402: goto          1411
-      1405: aload_3
-      1406: invokeinterface #411,  1          // InterfaceMethod androidx/compose/runtime/Composer.skipToGroupEnd:()V
-      1411: aload_3
-      1412: invokeinterface #415,  1          // InterfaceMethod androidx/compose/runtime/Composer.endRestartGroup:()Landroidx/compose/runtime/ScopeUpdateScope;
-      1417: dup
-      1418: ifnull        1441
-      1421: aload_0
-      1422: aload_1
-      1423: aload_2
-      1424: iload         4
-      1426: iload         5
-      1428: invokedynamic #427,  0            // InvokeDynamic #4:invoke:(Lkotlin/jvm/functions/Function1;Lkotlin/jvm/functions/Function1;Ljava/lang/String;II)Lkotlin/jvm/functions/Function2;
-      1433: invokeinterface #433,  2          // InterfaceMethod androidx/compose/runtime/ScopeUpdateScope.updateScope:(Lkotlin/jvm/functions/Function2;)V
-      1438: goto          1442
-      1441: pop
-      1442: return
-
-  private static final void DrawerHeader(androidx.compose.runtime.Composer, int);
-    Code:
-         0: aload_0
-         1: ldc_w         #528                // int 1421032886
-         4: invokeinterface #30,  2           // InterfaceMethod androidx/compose/runtime/Composer.startRestartGroup:(I)Landroidx/compose/runtime/Composer;
-         9: astore_0
-        10: aload_0
-        11: ldc_w         #530                // String C(DrawerHeader)102@4146L388:JetchatDrawer.kt#o9oqao
-        14: invokestatic  #38                 // Method androidx/compose/runtime/ComposerKt.sourceInformation:(Landroidx/compose/runtime/Composer;Ljava/lang/String;)V
-        17: aload_0
-        18: iload_1
-        19: ifeq          26
-        22: iconst_1
-        23: goto          27
-        26: iconst_0
-        27: iload_1
-        28: iconst_1
-        29: iand
-        30: invokeinterface #49,  3           // InterfaceMethod androidx/compose/runtime/Composer.shouldExecute:(ZI)Z
-        35: ifeq          570
-        38: invokestatic  #55                 // Method androidx/compose/runtime/ComposerKt.isTraceInProgress:()Z
-        41: ifeq          55
-        44: ldc_w         #528                // int 1421032886
-        47: iload_1
-        48: iconst_m1
-        49: ldc_w         #532                // String com.example.compose.jetchat.components.DrawerHeader (JetchatDrawer.kt:101)
-        52: invokestatic  #61                 // Method androidx/compose/runtime/ComposerKt.traceEventStart:(IIILjava/lang/String;)V
-        55: getstatic     #74                 // Field androidx/compose/ui/Modifier.Companion:Landroidx/compose/ui/Modifier$Companion;
-        58: checkcast     #70                 // class androidx/compose/ui/Modifier
-        61: bipush        16
-        63: istore_2
-        64: iconst_0
-        65: istore_3
-        66: iload_2
-        67: i2f
-        68: invokestatic  #318                // Method androidx/compose/ui/unit/Dp."constructor-impl":(F)F
-        71: invokestatic  #536                // Method androidx/compose/foundation/layout/PaddingKt."padding-3ABfNKs":(Landroidx/compose/ui/Modifier;F)Landroidx/compose/ui/Modifier;
-        74: astore_2
-        75: getstatic     #89                 // Field androidx/compose/ui/Alignment.Companion:Landroidx/compose/ui/Alignment$Companion;
-        78: invokevirtual #540                // Method androidx/compose/ui/Alignment$Companion.getCenterVertically:()Landroidx/compose/ui/Alignment$Vertical;
-        81: astore        4
-        83: aload_0
-        84: astore        5
-        86: sipush        390
-        89: istore        6
-        91: iconst_0
-        92: istore        7
-        94: aload         5
-        96: ldc_w         #541                // int 844473419
-        99: ldc_w         #543                // String CC(Row)N(modifier,horizontalArrangement,verticalAlignment,content)99@5125L58,100@5188L131:Row.kt#2w3rfo
-       102: invokestatic  #68                 // Method androidx/compose/runtime/ComposerKt.sourceInformationMarkerStart:(Landroidx/compose/runtime/Composer;ILjava/lang/String;)V
-       105: getstatic     #80                 // Field androidx/compose/foundation/layout/Arrangement.INSTANCE:Landroidx/compose/foundation/layout/Arrangement;
-       108: invokevirtual #546                // Method androidx/compose/foundation/layout/Arrangement.getStart:()Landroidx/compose/foundation/layout/Arrangement$Horizontal;
-       111: astore_3
-       112: aload_3
-       113: aload         4
-       115: aload         5
-       117: bipush        14
-       119: iload         6
-       121: iconst_3
-       122: ishr
-       123: iand
-       124: bipush        112
-       126: iload         6
-       128: iconst_3
-       129: ishr
-       130: iand
-       131: ior
-       132: invokestatic  #552                // Method androidx/compose/foundation/layout/RowKt.rowMeasurePolicy:(Landroidx/compose/foundation/layout/Arrangement$Horizontal;Landroidx/compose/ui/Alignment$Vertical;Landroidx/compose/runtime/Composer;I)Landroidx/compose/ui/layout/MeasurePolicy;
-       135: astore        8
-       137: aload_2
-       138: astore        9
-       140: aload         8
-       142: astore        10
-       144: aload         5
-       146: astore        11
-       148: bipush        112
-       150: iload         6
-       152: iconst_3
-       153: ishl
-       154: iand
-       155: istore        12
-       157: nop
-       158: iconst_0
-       159: istore        13
-       161: aload         11
-       163: ldc           #102                // int -1159599143
-       165: ldc           #104                // String CC(Layout)P(!1,2)81@3355L27,84@3521L416:Layout.kt#80mrfh
-       167: invokestatic  #68                 // Method androidx/compose/runtime/ComposerKt.sourceInformationMarkerStart:(Landroidx/compose/runtime/Composer;ILjava/lang/String;)V
-       170: aload         11
-       172: iconst_0
-       173: invokestatic  #110                // Method androidx/compose/runtime/ComposablesKt.getCurrentCompositeKeyHashCode:(Landroidx/compose/runtime/Composer;I)J
-       176: invokestatic  #116                // Method java/lang/Long.hashCode:(J)I
-       179: istore        14
-       181: aload         11
-       183: invokeinterface #120,  1          // InterfaceMethod androidx/compose/runtime/Composer.getCurrentCompositionLocalMap:()Landroidx/compose/runtime/CompositionLocalMap;
-       188: astore        15
-       190: aload         11
-       192: aload         9
-       194: invokestatic  #126                // Method androidx/compose/ui/ComposedModifierKt.materializeModifier:(Landroidx/compose/runtime/Composer;Landroidx/compose/ui/Modifier;)Landroidx/compose/ui/Modifier;
-       197: astore        16
-       199: getstatic     #131                // Field androidx/compose/ui/node/ComposeUiNode.Companion:Landroidx/compose/ui/node/ComposeUiNode$Companion;
-       202: invokevirtual #137                // Method androidx/compose/ui/node/ComposeUiNode$Companion.getConstructor:()Lkotlin/jvm/functions/Function0;
-       205: astore        17
-       207: aload         11
-       209: astore        18
-       211: bipush        6
-       213: sipush        896
-       216: iload         12
-       218: bipush        6
-       220: ishl
-       221: iand
-       222: ior
-       223: istore        19
-       225: nop
-       226: iconst_0
-       227: istore        20
-       229: aload         18
-       231: ldc           #138                // int -553112988
-       233: ldc           #140                // String CC(ReusableComposeNode)N(factory,update,content)399@15590L9:Composables.kt#9igjgp
-       235: invokestatic  #68                 // Method androidx/compose/runtime/ComposerKt.sourceInformationMarkerStart:(Landroidx/compose/runtime/Composer;ILjava/lang/String;)V
-       238: aload         18
-       240: invokeinterface #144,  1          // InterfaceMethod androidx/compose/runtime/Composer.getApplier:()Landroidx/compose/runtime/Applier;
-       245: instanceof    #146                // class androidx/compose/runtime/Applier
-       248: ifne          254
-       251: invokestatic  #150                // Method androidx/compose/runtime/ComposablesKt.invalidApplier:()V
-       254: aload         18
-       256: invokeinterface #153,  1          // InterfaceMethod androidx/compose/runtime/Composer.startReusableNode:()V
-       261: aload         18
-       263: invokeinterface #156,  1          // InterfaceMethod androidx/compose/runtime/Composer.getInserting:()Z
-       268: ifeq          283
-       271: aload         18
-       273: aload         17
-       275: invokeinterface #160,  2          // InterfaceMethod androidx/compose/runtime/Composer.createNode:(Lkotlin/jvm/functions/Function0;)V
-       280: goto          290
-       283: aload         18
-       285: invokeinterface #163,  1          // InterfaceMethod androidx/compose/runtime/Composer.useNode:()V
-       290: aload         18
-       292: invokestatic  #169                // Method androidx/compose/runtime/Updater."constructor-impl":(Landroidx/compose/runtime/Composer;)Landroidx/compose/runtime/Composer;
-       295: astore        21
-       297: iconst_0
-       298: istore        22
-       300: aload         21
-       302: aload         10
-       304: getstatic     #131                // Field androidx/compose/ui/node/ComposeUiNode.Companion:Landroidx/compose/ui/node/ComposeUiNode$Companion;
-       307: invokevirtual #173                // Method androidx/compose/ui/node/ComposeUiNode$Companion.getSetMeasurePolicy:()Lkotlin/jvm/functions/Function2;
-       310: invokestatic  #177                // Method androidx/compose/runtime/Updater."set-impl":(Landroidx/compose/runtime/Composer;Ljava/lang/Object;Lkotlin/jvm/functions/Function2;)V
-       313: aload         21
-       315: aload         15
-       317: getstatic     #131                // Field androidx/compose/ui/node/ComposeUiNode.Companion:Landroidx/compose/ui/node/ComposeUiNode$Companion;
-       320: invokevirtual #180                // Method androidx/compose/ui/node/ComposeUiNode$Companion.getSetResolvedCompositionLocals:()Lkotlin/jvm/functions/Function2;
-       323: invokestatic  #177                // Method androidx/compose/runtime/Updater."set-impl":(Landroidx/compose/runtime/Composer;Ljava/lang/Object;Lkotlin/jvm/functions/Function2;)V
-       326: aload         21
-       328: iload         14
-       330: invokestatic  #186                // Method java/lang/Integer.valueOf:(I)Ljava/lang/Integer;
-       333: getstatic     #131                // Field androidx/compose/ui/node/ComposeUiNode.Companion:Landroidx/compose/ui/node/ComposeUiNode$Companion;
-       336: invokevirtual #189                // Method androidx/compose/ui/node/ComposeUiNode$Companion.getSetCompositeKeyHash:()Lkotlin/jvm/functions/Function2;
-       339: invokestatic  #192                // Method androidx/compose/runtime/Updater."init-impl":(Landroidx/compose/runtime/Composer;Ljava/lang/Object;Lkotlin/jvm/functions/Function2;)V
-       342: aload         21
-       344: getstatic     #131                // Field androidx/compose/ui/node/ComposeUiNode.Companion:Landroidx/compose/ui/node/ComposeUiNode$Companion;
-       347: invokevirtual #196                // Method androidx/compose/ui/node/ComposeUiNode$Companion.getApplyOnDeactivatedNodeAssertion:()Lkotlin/jvm/functions/Function1;
-       350: invokestatic  #200                // Method androidx/compose/runtime/Updater."reconcile-impl":(Landroidx/compose/runtime/Composer;Lkotlin/jvm/functions/Function1;)V
-       353: aload         21
-       355: aload         16
-       357: getstatic     #131                // Field androidx/compose/ui/node/ComposeUiNode.Companion:Landroidx/compose/ui/node/ComposeUiNode$Companion;
-       360: invokevirtual #203                // Method androidx/compose/ui/node/ComposeUiNode$Companion.getSetModifier:()Lkotlin/jvm/functions/Function2;
-       363: invokestatic  #177                // Method androidx/compose/runtime/Updater."set-impl":(Landroidx/compose/runtime/Composer;Ljava/lang/Object;Lkotlin/jvm/functions/Function2;)V
-       366: nop
-       367: nop
-       368: aload         18
-       370: bipush        14
-       372: iload         19
-       374: bipush        6
-       376: ishr
-       377: iand
-       378: istore        23
-       380: astore        24
-       382: iconst_0
-       383: istore        25
-       385: aload         24
-       387: ldc_w         #553                // int 1456264949
-       390: ldc_w         #555                // String C101@5233L9:Row.kt#2w3rfo
-       393: invokestatic  #68                 // Method androidx/compose/runtime/ComposerKt.sourceInformationMarkerStart:(Landroidx/compose/runtime/Composer;ILjava/lang/String;)V
-       396: getstatic     #560                // Field androidx/compose/foundation/layout/RowScopeInstance.INSTANCE:Landroidx/compose/foundation/layout/RowScopeInstance;
-       399: aload         24
-       401: bipush        6
-       403: bipush        112
-       405: iload         6
-       407: bipush        6
-       409: ishr
-       410: iand
-       411: ior
-       412: istore        26
-       414: astore        27
-       416: checkcast     #562                // class androidx/compose/foundation/layout/RowScope
-       419: astore        28
-       421: iconst_0
-       422: istore        29
-       424: aload         27
-       426: ldc_w         #563                // int 308391171
-       429: ldc_w         #565                // String C103@4234L106,108@4378L45,107@4349L179:JetchatDrawer.kt#o9oqao
-       432: invokestatic  #68                 // Method androidx/compose/runtime/ComposerKt.sourceInformationMarkerStart:(Landroidx/compose/runtime/Composer;ILjava/lang/String;)V
-       435: aconst_null
-       436: getstatic     #74                 // Field androidx/compose/ui/Modifier.Companion:Landroidx/compose/ui/Modifier$Companion;
-       439: checkcast     #70                 // class androidx/compose/ui/Modifier
-       442: bipush        24
-       444: istore        30
-       446: iconst_0
-       447: istore        31
-       449: iload         30
-       451: i2f
-       452: invokestatic  #318                // Method androidx/compose/ui/unit/Dp."constructor-impl":(F)F
-       455: invokestatic  #570                // Method androidx/compose/foundation/layout/SizeKt."size-3ABfNKs":(Landroidx/compose/ui/Modifier;F)Landroidx/compose/ui/Modifier;
-       458: aload         27
-       460: bipush        54
-       462: iconst_0
-       463: invokestatic  #576                // Method com/example/compose/jetchat/components/JetchatIconKt.JetchatIcon:(Ljava/lang/String;Landroidx/compose/ui/Modifier;Landroidx/compose/runtime/Composer;II)V
-       466: getstatic     #581                // Field com/example/compose/jetchat/R$drawable.jetchat_logo:I
-       469: aload         27
-       471: iconst_0
-       472: invokestatic  #587                // Method androidx/compose/ui/res/PainterResources_androidKt.painterResource:(ILandroidx/compose/runtime/Composer;I)Landroidx/compose/ui/graphics/painter/Painter;
-       475: aconst_null
-       476: getstatic     #74                 // Field androidx/compose/ui/Modifier.Companion:Landroidx/compose/ui/Modifier$Companion;
-       479: checkcast     #70                 // class androidx/compose/ui/Modifier
-       482: bipush        8
-       484: istore        30
-       486: iconst_0
-       487: istore        31
-       489: iload         30
-       491: i2f
-       492: invokestatic  #318                // Method androidx/compose/ui/unit/Dp."constructor-impl":(F)F
-       495: fconst_0
-       496: fconst_0
-       497: fconst_0
-       498: bipush        14
-       500: aconst_null
-       501: invokestatic  #591                // Method androidx/compose/foundation/layout/PaddingKt."padding-qDBjuR0$default":(Landroidx/compose/ui/Modifier;FFFFILjava/lang/Object;)Landroidx/compose/ui/Modifier;
-       504: aconst_null
-       505: aconst_null
-       506: fconst_0
-       507: aconst_null
-       508: aload         27
-       510: sipush        432
-       513: getstatic     #596                // Field androidx/compose/ui/graphics/painter/Painter.$stable:I
-       516: ior
-       517: bipush        120
-       519: invokestatic  #602                // Method androidx/compose/foundation/ImageKt.Image:(Landroidx/compose/ui/graphics/painter/Painter;Ljava/lang/String;Landroidx/compose/ui/Modifier;Landroidx/compose/ui/Alignment;Landroidx/compose/ui/layout/ContentScale;FLandroidx/compose/ui/graphics/ColorFilter;Landroidx/compose/runtime/Composer;II)V
-       522: aload         27
-       524: invokestatic  #301                // Method androidx/compose/runtime/ComposerKt.sourceInformationMarkerEnd:(Landroidx/compose/runtime/Composer;)V
-       527: nop
-       528: aload         24
-       530: invokestatic  #301                // Method androidx/compose/runtime/ComposerKt.sourceInformationMarkerEnd:(Landroidx/compose/runtime/Composer;)V
-       533: aload         18
-       535: invokeinterface #405,  1          // InterfaceMethod androidx/compose/runtime/Composer.endNode:()V
-       540: aload         18
-       542: invokestatic  #301                // Method androidx/compose/runtime/ComposerKt.sourceInformationMarkerEnd:(Landroidx/compose/runtime/Composer;)V
-       545: nop
-       546: aload         11
-       548: invokestatic  #301                // Method androidx/compose/runtime/ComposerKt.sourceInformationMarkerEnd:(Landroidx/compose/runtime/Composer;)V
-       551: nop
-       552: aload         5
-       554: invokestatic  #301                // Method androidx/compose/runtime/ComposerKt.sourceInformationMarkerEnd:(Landroidx/compose/runtime/Composer;)V
-       557: nop
-       558: invokestatic  #55                 // Method androidx/compose/runtime/ComposerKt.isTraceInProgress:()Z
-       561: ifeq          576
-       564: invokestatic  #408                // Method androidx/compose/runtime/ComposerKt.traceEventEnd:()V
-       567: goto          576
-       570: aload_0
-       571: invokeinterface #411,  1          // InterfaceMethod androidx/compose/runtime/Composer.skipToGroupEnd:()V
-       576: aload_0
-       577: invokeinterface #415,  1          // InterfaceMethod androidx/compose/runtime/Composer.endRestartGroup:()Landroidx/compose/runtime/ScopeUpdateScope;
-       582: dup
-       583: ifnull        600
-       586: iload_1
-       587: invokedynamic #610,  0            // InvokeDynamic #5:invoke:(I)Lkotlin/jvm/functions/Function2;
-       592: invokeinterface #433,  2          // InterfaceMethod androidx/compose/runtime/ScopeUpdateScope.updateScope:(Lkotlin/jvm/functions/Function2;)V
-       597: goto          601
-       600: pop
-       601: return
-
-  private static final void DrawerItemHeader(java.lang.String, androidx.compose.runtime.Composer, int);
-    Code:
-         0: aload_1
-         1: ldc_w         #644                // int 1095084436
-         4: invokeinterface #30,  2           // InterfaceMethod androidx/compose/runtime/Composer.startRestartGroup:(I)Landroidx/compose/runtime/Composer;
-         9: astore_1
-        10: aload_1
-        11: ldc_w         #646                // String C(DrawerItemHeader)N(text)117@4599L325:JetchatDrawer.kt#o9oqao
-        14: invokestatic  #38                 // Method androidx/compose/runtime/ComposerKt.sourceInformation:(Landroidx/compose/runtime/Composer;Ljava/lang/String;)V
-        17: iload_2
-        18: istore_3
-        19: iload_2
-        20: bipush        6
-        22: iand
-        23: ifne          44
-        26: iload_3
-        27: aload_1
-        28: aload_0
-        29: invokeinterface #45,  2           // InterfaceMethod androidx/compose/runtime/Composer.changed:(Ljava/lang/Object;)Z
-        34: ifeq          41
-        37: iconst_4
-        38: goto          42
-        41: iconst_2
-        42: ior
-        43: istore_3
-        44: aload_1
-        45: iload_3
-        46: iconst_3
-        47: iand
-        48: iconst_2
-        49: if_icmpeq     56
-        52: iconst_1
-        53: goto          57
-        56: iconst_0
-        57: iload_3
-        58: iconst_1
-        59: iand
-        60: invokeinterface #49,  3           // InterfaceMethod androidx/compose/runtime/Composer.shouldExecute:(ZI)Z
-        65: ifeq          585
-        68: invokestatic  #55                 // Method androidx/compose/runtime/ComposerKt.isTraceInProgress:()Z
-        71: ifeq          85
-        74: ldc_w         #644                // int 1095084436
-        77: iload_3
-        78: iconst_m1
-        79: ldc_w         #648                // String com.example.compose.jetchat.components.DrawerItemHeader (JetchatDrawer.kt:116)
-        82: invokestatic  #61                 // Method androidx/compose/runtime/ComposerKt.traceEventStart:(IIILjava/lang/String;)V
-        85: getstatic     #74                 // Field androidx/compose/ui/Modifier.Companion:Landroidx/compose/ui/Modifier$Companion;
-        88: checkcast     #70                 // class androidx/compose/ui/Modifier
-        91: bipush        52
-        93: istore        4
-        95: iconst_0
-        96: istore        5
-        98: iload         4
-       100: i2f
-       101: invokestatic  #318                // Method androidx/compose/ui/unit/Dp."constructor-impl":(F)F
-       104: fconst_0
-       105: iconst_2
-       106: aconst_null
-       107: invokestatic  #651                // Method androidx/compose/foundation/layout/SizeKt."heightIn-VpY3zN4$default":(Landroidx/compose/ui/Modifier;FFILjava/lang/Object;)Landroidx/compose/ui/Modifier;
-       110: bipush        28
-       112: istore        4
-       114: iconst_0
-       115: istore        5
-       117: iload         4
-       119: i2f
-       120: invokestatic  #318                // Method androidx/compose/ui/unit/Dp."constructor-impl":(F)F
-       123: fconst_0
-       124: iconst_2
-       125: aconst_null
-       126: invokestatic  #324                // Method androidx/compose/foundation/layout/PaddingKt."padding-VpY3zN4$default":(Landroidx/compose/ui/Modifier;FFILjava/lang/Object;)Landroidx/compose/ui/Modifier;
-       129: astore        4
-       131: getstatic     #89                 // Field androidx/compose/ui/Alignment.Companion:Landroidx/compose/ui/Alignment$Companion;
-       134: invokevirtual #655                // Method androidx/compose/ui/Alignment$Companion.getCenterStart:()Landroidx/compose/ui/Alignment;
-       137: astore        5
-       139: aload_1
-       140: astore        7
-       142: bipush        54
-       144: istore        8
-       146: nop
-       147: iconst_0
-       148: istore        9
-       150: aload         7
-       152: ldc_w         #656                // int 1042775818
-       155: ldc_w         #658                // String CC(Box)N(modifier,contentAlignment,propagateMinConstraints,content)71@3424L131:Box.kt#2w3rfo
-       158: invokestatic  #68                 // Method androidx/compose/runtime/ComposerKt.sourceInformationMarkerStart:(Landroidx/compose/runtime/Composer;ILjava/lang/String;)V
-       161: iconst_0
-       162: istore        6
-       164: aload         5
-       166: iload         6
-       168: invokestatic  #664                // Method androidx/compose/foundation/layout/BoxKt.maybeCachedBoxMeasurePolicy:(Landroidx/compose/ui/Alignment;Z)Landroidx/compose/ui/layout/MeasurePolicy;
-       171: astore        10
-       173: aload         4
-       175: astore        11
-       177: aload         10
-       179: astore        12
-       181: aload         7
-       183: astore        13
-       185: bipush        112
-       187: iload         8
-       189: iconst_3
-       190: ishl
-       191: iand
-       192: istore        14
-       194: nop
-       195: iconst_0
-       196: istore        15
-       198: aload         13
-       200: ldc           #102                // int -1159599143
-       202: ldc           #104                // String CC(Layout)P(!1,2)81@3355L27,84@3521L416:Layout.kt#80mrfh
-       204: invokestatic  #68                 // Method androidx/compose/runtime/ComposerKt.sourceInformationMarkerStart:(Landroidx/compose/runtime/Composer;ILjava/lang/String;)V
-       207: aload         13
-       209: iconst_0
-       210: invokestatic  #110                // Method androidx/compose/runtime/ComposablesKt.getCurrentCompositeKeyHashCode:(Landroidx/compose/runtime/Composer;I)J
-       213: invokestatic  #116                // Method java/lang/Long.hashCode:(J)I
-       216: istore        16
-       218: aload         13
-       220: invokeinterface #120,  1          // InterfaceMethod androidx/compose/runtime/Composer.getCurrentCompositionLocalMap:()Landroidx/compose/runtime/CompositionLocalMap;
-       225: astore        17
-       227: aload         13
-       229: aload         11
-       231: invokestatic  #126                // Method androidx/compose/ui/ComposedModifierKt.materializeModifier:(Landroidx/compose/runtime/Composer;Landroidx/compose/ui/Modifier;)Landroidx/compose/ui/Modifier;
-       234: astore        18
-       236: getstatic     #131                // Field androidx/compose/ui/node/ComposeUiNode.Companion:Landroidx/compose/ui/node/ComposeUiNode$Companion;
-       239: invokevirtual #137                // Method androidx/compose/ui/node/ComposeUiNode$Companion.getConstructor:()Lkotlin/jvm/functions/Function0;
-       242: astore        19
-       244: aload         13
-       246: astore        20
-       248: bipush        6
-       250: sipush        896
-       253: iload         14
-       255: bipush        6
-       257: ishl
-       258: iand
-       259: ior
-       260: istore        21
-       262: nop
-       263: iconst_0
-       264: istore        22
-       266: aload         20
-       268: ldc           #138                // int -553112988
-       270: ldc           #140                // String CC(ReusableComposeNode)N(factory,update,content)399@15590L9:Composables.kt#9igjgp
-       272: invokestatic  #68                 // Method androidx/compose/runtime/ComposerKt.sourceInformationMarkerStart:(Landroidx/compose/runtime/Composer;ILjava/lang/String;)V
-       275: aload         20
-       277: invokeinterface #144,  1          // InterfaceMethod androidx/compose/runtime/Composer.getApplier:()Landroidx/compose/runtime/Applier;
-       282: instanceof    #146                // class androidx/compose/runtime/Applier
-       285: ifne          291
-       288: invokestatic  #150                // Method androidx/compose/runtime/ComposablesKt.invalidApplier:()V
-       291: aload         20
-       293: invokeinterface #153,  1          // InterfaceMethod androidx/compose/runtime/Composer.startReusableNode:()V
-       298: aload         20
-       300: invokeinterface #156,  1          // InterfaceMethod androidx/compose/runtime/Composer.getInserting:()Z
-       305: ifeq          320
-       308: aload         20
-       310: aload         19
-       312: invokeinterface #160,  2          // InterfaceMethod androidx/compose/runtime/Composer.createNode:(Lkotlin/jvm/functions/Function0;)V
-       317: goto          327
-       320: aload         20
-       322: invokeinterface #163,  1          // InterfaceMethod androidx/compose/runtime/Composer.useNode:()V
-       327: aload         20
-       329: invokestatic  #169                // Method androidx/compose/runtime/Updater."constructor-impl":(Landroidx/compose/runtime/Composer;)Landroidx/compose/runtime/Composer;
-       332: astore        23
-       334: iconst_0
-       335: istore        24
-       337: aload         23
-       339: aload         12
-       341: getstatic     #131                // Field androidx/compose/ui/node/ComposeUiNode.Companion:Landroidx/compose/ui/node/ComposeUiNode$Companion;
-       344: invokevirtual #173                // Method androidx/compose/ui/node/ComposeUiNode$Companion.getSetMeasurePolicy:()Lkotlin/jvm/functions/Function2;
-       347: invokestatic  #177                // Method androidx/compose/runtime/Updater."set-impl":(Landroidx/compose/runtime/Composer;Ljava/lang/Object;Lkotlin/jvm/functions/Function2;)V
-       350: aload         23
-       352: aload         17
-       354: getstatic     #131                // Field androidx/compose/ui/node/ComposeUiNode.Companion:Landroidx/compose/ui/node/ComposeUiNode$Companion;
-       357: invokevirtual #180                // Method androidx/compose/ui/node/ComposeUiNode$Companion.getSetResolvedCompositionLocals:()Lkotlin/jvm/functions/Function2;
-       360: invokestatic  #177                // Method androidx/compose/runtime/Updater."set-impl":(Landroidx/compose/runtime/Composer;Ljava/lang/Object;Lkotlin/jvm/functions/Function2;)V
-       363: aload         23
-       365: iload         16
-       367: invokestatic  #186                // Method java/lang/Integer.valueOf:(I)Ljava/lang/Integer;
-       370: getstatic     #131                // Field androidx/compose/ui/node/ComposeUiNode.Companion:Landroidx/compose/ui/node/ComposeUiNode$Companion;
-       373: invokevirtual #189                // Method androidx/compose/ui/node/ComposeUiNode$Companion.getSetCompositeKeyHash:()Lkotlin/jvm/functions/Function2;
-       376: invokestatic  #192                // Method androidx/compose/runtime/Updater."init-impl":(Landroidx/compose/runtime/Composer;Ljava/lang/Object;Lkotlin/jvm/functions/Function2;)V
-       379: aload         23
-       381: getstatic     #131                // Field androidx/compose/ui/node/ComposeUiNode.Companion:Landroidx/compose/ui/node/ComposeUiNode$Companion;
-       384: invokevirtual #196                // Method androidx/compose/ui/node/ComposeUiNode$Companion.getApplyOnDeactivatedNodeAssertion:()Lkotlin/jvm/functions/Function1;
-       387: invokestatic  #200                // Method androidx/compose/runtime/Updater."reconcile-impl":(Landroidx/compose/runtime/Composer;Lkotlin/jvm/functions/Function1;)V
-       390: aload         23
-       392: aload         18
-       394: getstatic     #131                // Field androidx/compose/ui/node/ComposeUiNode.Companion:Landroidx/compose/ui/node/ComposeUiNode$Companion;
-       397: invokevirtual #203                // Method androidx/compose/ui/node/ComposeUiNode$Companion.getSetModifier:()Lkotlin/jvm/functions/Function2;
-       400: invokestatic  #177                // Method androidx/compose/runtime/Updater."set-impl":(Landroidx/compose/runtime/Composer;Ljava/lang/Object;Lkotlin/jvm/functions/Function2;)V
-       403: nop
-       404: nop
-       405: aload         20
-       407: bipush        14
-       409: iload         21
-       411: bipush        6
-       413: ishr
-       414: iand
-       415: istore        25
-       417: astore        26
-       419: iconst_0
-       420: istore        27
-       422: aload         26
-       424: ldc_w         #665                // int 1833054614
-       427: ldc_w         #667                // String C72@3469L9:Box.kt#2w3rfo
-       430: invokestatic  #68                 // Method androidx/compose/runtime/ComposerKt.sourceInformationMarkerStart:(Landroidx/compose/runtime/Composer;ILjava/lang/String;)V
-       433: getstatic     #672                // Field androidx/compose/foundation/layout/BoxScopeInstance.INSTANCE:Landroidx/compose/foundation/layout/BoxScopeInstance;
-       436: aload         26
-       438: bipush        6
-       440: bipush        112
-       442: iload         8
-       444: bipush        6
-       446: ishr
-       447: iand
-       448: ior
-       449: istore        28
-       451: astore        29
-       453: checkcast     #674                // class androidx/compose/foundation/layout/BoxScope
-       456: astore        30
-       458: iconst_0
-       459: istore        31
-       461: aload         29
-       463: ldc_w         #675                // int 1551661680
-       466: ldc_w         #677                // String C125@4823L10,126@4879L11,123@4765L153:JetchatDrawer.kt#o9oqao
-       469: invokestatic  #68                 // Method androidx/compose/runtime/ComposerKt.sourceInformationMarkerStart:(Landroidx/compose/runtime/Composer;ILjava/lang/String;)V
-       472: getstatic     #682                // Field androidx/compose/material3/MaterialTheme.INSTANCE:Landroidx/compose/material3/MaterialTheme;
-       475: aload         29
-       477: getstatic     #683                // Field androidx/compose/material3/MaterialTheme.$stable:I
-       480: invokevirtual #687                // Method androidx/compose/material3/MaterialTheme.getTypography:(Landroidx/compose/runtime/Composer;I)Landroidx/compose/material3/Typography;
-       483: invokevirtual #693                // Method androidx/compose/material3/Typography.getBodySmall:()Landroidx/compose/ui/text/TextStyle;
-       486: astore        32
-       488: getstatic     #682                // Field androidx/compose/material3/MaterialTheme.INSTANCE:Landroidx/compose/material3/MaterialTheme;
-       491: aload         29
-       493: getstatic     #683                // Field androidx/compose/material3/MaterialTheme.$stable:I
-       496: invokevirtual #697                // Method androidx/compose/material3/MaterialTheme.getColorScheme:(Landroidx/compose/runtime/Composer;I)Landroidx/compose/material3/ColorScheme;
-       499: invokevirtual #703                // Method androidx/compose/material3/ColorScheme."getOnSurfaceVariant-0d7_KjU":()J
-       502: lstore        33
-       504: aload_0
-       505: aconst_null
-       506: lload         33
-       508: aconst_null
-       509: lconst_0
-       510: aconst_null
-       511: aconst_null
-       512: aconst_null
-       513: lconst_0
-       514: aconst_null
-       515: aconst_null
-       516: lconst_0
-       517: iconst_0
-       518: iconst_0
-       519: iconst_0
-       520: iconst_0
-       521: aconst_null
-       522: aload         32
-       524: aload         29
-       526: bipush        14
-       528: iload_3
-       529: iand
-       530: iconst_0
-       531: ldc_w         #704                // int 131066
-       534: invokestatic  #710                // Method androidx/compose/material3/TextKt."Text-Nvy7gAk":(Ljava/lang/String;Landroidx/compose/ui/Modifier;JLandroidx/compose/foundation/text/TextAutoSize;JLandroidx/compose/ui/text/font/FontStyle;Landroidx/compose/ui/text/font/FontWeight;Landroidx/compose/ui/text/font/FontFamily;JLandroidx/compose/ui/text/style/TextDecoration;Landroidx/compose/ui/text/style/TextAlign;JIZIILkotlin/jvm/functions/Function1;Landroidx/compose/ui/text/TextStyle;Landroidx/compose/runtime/Composer;III)V
-       537: aload         29
-       539: invokestatic  #301                // Method androidx/compose/runtime/ComposerKt.sourceInformationMarkerEnd:(Landroidx/compose/runtime/Composer;)V
-       542: nop
-       543: aload         26
-       545: invokestatic  #301                // Method androidx/compose/runtime/ComposerKt.sourceInformationMarkerEnd:(Landroidx/compose/runtime/Composer;)V
-       548: aload         20
-       550: invokeinterface #405,  1          // InterfaceMethod androidx/compose/runtime/Composer.endNode:()V
-       555: aload         20
-       557: invokestatic  #301                // Method androidx/compose/runtime/ComposerKt.sourceInformationMarkerEnd:(Landroidx/compose/runtime/Composer;)V
-       560: nop
-       561: aload         13
-       563: invokestatic  #301                // Method androidx/compose/runtime/ComposerKt.sourceInformationMarkerEnd:(Landroidx/compose/runtime/Composer;)V
-       566: nop
-       567: aload         7
-       569: invokestatic  #301                // Method androidx/compose/runtime/ComposerKt.sourceInformationMarkerEnd:(Landroidx/compose/runtime/Composer;)V
-       572: nop
-       573: invokestatic  #55                 // Method androidx/compose/runtime/ComposerKt.isTraceInProgress:()Z
-       576: ifeq          591
-       579: invokestatic  #408                // Method androidx/compose/runtime/ComposerKt.traceEventEnd:()V
-       582: goto          591
-       585: aload_1
-       586: invokeinterface #411,  1          // InterfaceMethod androidx/compose/runtime/Composer.skipToGroupEnd:()V
-       591: aload_1
-       592: invokeinterface #415,  1          // InterfaceMethod androidx/compose/runtime/Composer.endRestartGroup:()Landroidx/compose/runtime/ScopeUpdateScope;
-       597: dup
-       598: ifnull        616
-       601: aload_0
-       602: iload_2
-       603: invokedynamic #718,  0            // InvokeDynamic #6:invoke:(Ljava/lang/String;I)Lkotlin/jvm/functions/Function2;
-       608: invokeinterface #433,  2          // InterfaceMethod androidx/compose/runtime/ScopeUpdateScope.updateScope:(Lkotlin/jvm/functions/Function2;)V
-       613: goto          617
-       616: pop
-       617: return
-
-  private static final void ChatItem(java.lang.String, boolean, kotlin.jvm.functions.Function0<kotlin.Unit>, androidx.compose.runtime.Composer, int);
-    Code:
-         0: aload_3
-         1: ldc_w         #744                // int 878096514
-         4: invokeinterface #30,  2           // InterfaceMethod androidx/compose/runtime/Composer.startRestartGroup:(I)Landroidx/compose/runtime/Composer;
-         9: astore_3
-        10: aload_3
-        11: ldc_w         #746                // String C(ChatItem)N(text,selected,onChatClicked)138@5172L1038:JetchatDrawer.kt#o9oqao
-        14: invokestatic  #38                 // Method androidx/compose/runtime/ComposerKt.sourceInformation:(Landroidx/compose/runtime/Composer;Ljava/lang/String;)V
-        17: iload         4
-        19: istore        5
-        21: iload         4
-        23: bipush        6
-        25: iand
-        26: ifne          49
-        29: iload         5
-        31: aload_3
-        32: aload_0
-        33: invokeinterface #45,  2           // InterfaceMethod androidx/compose/runtime/Composer.changed:(Ljava/lang/Object;)Z
-        38: ifeq          45
-        41: iconst_4
-        42: goto          46
-        45: iconst_2
-        46: ior
-        47: istore        5
-        49: iload         4
-        51: bipush        48
-        53: iand
-        54: ifne          79
-        57: iload         5
-        59: aload_3
-        60: iload_1
-        61: invokeinterface #749,  2          // InterfaceMethod androidx/compose/runtime/Composer.changed:(Z)Z
-        66: ifeq          74
-        69: bipush        32
-        71: goto          76
-        74: bipush        16
-        76: ior
-        77: istore        5
-        79: iload         4
-        81: sipush        384
-        84: iand
-        85: ifne          112
-        88: iload         5
-        90: aload_3
-        91: aload_2
-        92: invokeinterface #42,  2           // InterfaceMethod androidx/compose/runtime/Composer.changedInstance:(Ljava/lang/Object;)Z
-        97: ifeq          106
-       100: sipush        256
-       103: goto          109
-       106: sipush        128
-       109: ior
-       110: istore        5
-       112: aload_3
-       113: iload         5
-       115: sipush        147
-       118: iand
-       119: sipush        146
-       122: if_icmpeq     129
-       125: iconst_1
-       126: goto          130
-       129: iconst_0
-       130: iload         5
-       132: iconst_1
-       133: iand
-       134: invokeinterface #49,  3           // InterfaceMethod androidx/compose/runtime/Composer.shouldExecute:(ZI)Z
-       139: ifeq          1087
-       142: invokestatic  #55                 // Method androidx/compose/runtime/ComposerKt.isTraceInProgress:()Z
-       145: ifeq          160
-       148: ldc_w         #744                // int 878096514
-       151: iload         5
-       153: iconst_m1
-       154: ldc_w         #751                // String com.example.compose.jetchat.components.ChatItem (JetchatDrawer.kt:132)
-       157: invokestatic  #61                 // Method androidx/compose/runtime/ComposerKt.traceEventStart:(IIILjava/lang/String;)V
-       160: iload_1
-       161: ifeq          218
-       164: aload_3
-       165: ldc_w         #752                // int -1272439791
-       168: invokeinterface #391,  2          // InterfaceMethod androidx/compose/runtime/Composer.startReplaceGroup:(I)V
-       173: aload_3
-       174: ldc_w         #754                // String 134@5102L11
-       177: invokestatic  #38                 // Method androidx/compose/runtime/ComposerKt.sourceInformation:(Landroidx/compose/runtime/Composer;Ljava/lang/String;)V
-       180: getstatic     #74                 // Field androidx/compose/ui/Modifier.Companion:Landroidx/compose/ui/Modifier$Companion;
-       183: checkcast     #70                 // class androidx/compose/ui/Modifier
-       186: getstatic     #682                // Field androidx/compose/material3/MaterialTheme.INSTANCE:Landroidx/compose/material3/MaterialTheme;
-       189: aload_3
-       190: getstatic     #683                // Field androidx/compose/material3/MaterialTheme.$stable:I
-       193: invokevirtual #697                // Method androidx/compose/material3/MaterialTheme.getColorScheme:(Landroidx/compose/runtime/Composer;I)Landroidx/compose/material3/ColorScheme;
-       196: invokevirtual #757                // Method androidx/compose/material3/ColorScheme."getPrimaryContainer-0d7_KjU":()J
-       199: aconst_null
-       200: iconst_2
-       201: aconst_null
-       202: invokestatic  #763                // Method androidx/compose/foundation/BackgroundKt."background-bw27NRU$default":(Landroidx/compose/ui/Modifier;JLandroidx/compose/ui/graphics/Shape;ILjava/lang/Object;)Landroidx/compose/ui/Modifier;
-       205: astore        7
-       207: aload_3
-       208: invokeinterface #401,  1          // InterfaceMethod androidx/compose/runtime/Composer.endReplaceGroup:()V
-       213: aload         7
-       215: goto          239
-       218: aload_3
-       219: ldc_w         #764                // int -1272357176
-       222: invokeinterface #391,  2          // InterfaceMethod androidx/compose/runtime/Composer.startReplaceGroup:(I)V
-       227: aload_3
-       228: invokeinterface #401,  1          // InterfaceMethod androidx/compose/runtime/Composer.endReplaceGroup:()V
-       233: getstatic     #74                 // Field androidx/compose/ui/Modifier.Companion:Landroidx/compose/ui/Modifier$Companion;
-       236: checkcast     #70                 // class androidx/compose/ui/Modifier
-       239: astore        6
-       241: getstatic     #74                 // Field androidx/compose/ui/Modifier.Companion:Landroidx/compose/ui/Modifier$Companion;
-       244: checkcast     #70                 // class androidx/compose/ui/Modifier
-       247: bipush        56
-       249: istore        7
-       251: iconst_0
-       252: istore        8
-       254: iload         7
-       256: i2f
-       257: invokestatic  #318                // Method androidx/compose/ui/unit/Dp."constructor-impl":(F)F
-       260: invokestatic  #767                // Method androidx/compose/foundation/layout/SizeKt."height-3ABfNKs":(Landroidx/compose/ui/Modifier;F)Landroidx/compose/ui/Modifier;
-       263: fconst_0
-       264: iconst_1
-       265: aconst_null
-       266: invokestatic  #771                // Method androidx/compose/foundation/layout/SizeKt.fillMaxWidth$default:(Landroidx/compose/ui/Modifier;FILjava/lang/Object;)Landroidx/compose/ui/Modifier;
-       269: bipush        12
-       271: istore        7
-       273: iconst_0
-       274: istore        8
-       276: iload         7
-       278: i2f
-       279: invokestatic  #318                // Method androidx/compose/ui/unit/Dp."constructor-impl":(F)F
-       282: fconst_0
-       283: iconst_2
-       284: aconst_null
-       285: invokestatic  #324                // Method androidx/compose/foundation/layout/PaddingKt."padding-VpY3zN4$default":(Landroidx/compose/ui/Modifier;FFILjava/lang/Object;)Landroidx/compose/ui/Modifier;
-       288: invokestatic  #777                // Method androidx/compose/foundation/shape/RoundedCornerShapeKt.getCircleShape:()Landroidx/compose/foundation/shape/RoundedCornerShape;
-       291: checkcast     #779                // class androidx/compose/ui/graphics/Shape
-       294: invokestatic  #785                // Method androidx/compose/ui/draw/ClipKt.clip:(Landroidx/compose/ui/Modifier;Landroidx/compose/ui/graphics/Shape;)Landroidx/compose/ui/Modifier;
-       297: aload         6
-       299: invokeinterface #789,  2          // InterfaceMethod androidx/compose/ui/Modifier.then:(Landroidx/compose/ui/Modifier;)Landroidx/compose/ui/Modifier;
-       304: iconst_0
-       305: aconst_null
-       306: aconst_null
-       307: aconst_null
-       308: aload_2
-       309: bipush        15
-       311: aconst_null
-       312: invokestatic  #795                // Method androidx/compose/foundation/ClickableKt."clickable-oSLSa3U$default":(Landroidx/compose/ui/Modifier;ZLjava/lang/String;Landroidx/compose/ui/semantics/Role;Landroidx/compose/foundation/interaction/MutableInteractionSource;Lkotlin/jvm/functions/Function0;ILjava/lang/Object;)Landroidx/compose/ui/Modifier;
-       315: astore        7
-       317: getstatic     #89                 // Field androidx/compose/ui/Alignment.Companion:Landroidx/compose/ui/Alignment$Companion;
-       320: invokevirtual #540                // Method androidx/compose/ui/Alignment$Companion.getCenterVertically:()Landroidx/compose/ui/Alignment$Vertical;
-       323: astore        9
-       325: aload_3
-       326: astore        10
-       328: sipush        384
-       331: istore        11
-       333: nop
-       334: iconst_0
-       335: istore        12
-       337: aload         10
-       339: ldc_w         #541                // int 844473419
-       342: ldc_w         #543                // String CC(Row)N(modifier,horizontalArrangement,verticalAlignment,content)99@5125L58,100@5188L131:Row.kt#2w3rfo
-       345: invokestatic  #68                 // Method androidx/compose/runtime/ComposerKt.sourceInformationMarkerStart:(Landroidx/compose/runtime/Composer;ILjava/lang/String;)V
-       348: getstatic     #80                 // Field androidx/compose/foundation/layout/Arrangement.INSTANCE:Landroidx/compose/foundation/layout/Arrangement;
-       351: invokevirtual #546                // Method androidx/compose/foundation/layout/Arrangement.getStart:()Landroidx/compose/foundation/layout/Arrangement$Horizontal;
-       354: astore        8
-       356: aload         8
-       358: aload         9
-       360: aload         10
-       362: bipush        14
-       364: iload         11
-       366: iconst_3
-       367: ishr
-       368: iand
-       369: bipush        112
-       371: iload         11
-       373: iconst_3
-       374: ishr
-       375: iand
-       376: ior
-       377: invokestatic  #552                // Method androidx/compose/foundation/layout/RowKt.rowMeasurePolicy:(Landroidx/compose/foundation/layout/Arrangement$Horizontal;Landroidx/compose/ui/Alignment$Vertical;Landroidx/compose/runtime/Composer;I)Landroidx/compose/ui/layout/MeasurePolicy;
-       380: astore        13
-       382: aload         7
-       384: astore        14
-       386: aload         13
-       388: astore        15
-       390: aload         10
-       392: astore        16
-       394: bipush        112
-       396: iload         11
-       398: iconst_3
-       399: ishl
-       400: iand
-       401: istore        17
-       403: nop
-       404: iconst_0
-       405: istore        18
-       407: aload         16
-       409: ldc           #102                // int -1159599143
-       411: ldc           #104                // String CC(Layout)P(!1,2)81@3355L27,84@3521L416:Layout.kt#80mrfh
-       413: invokestatic  #68                 // Method androidx/compose/runtime/ComposerKt.sourceInformationMarkerStart:(Landroidx/compose/runtime/Composer;ILjava/lang/String;)V
-       416: aload         16
-       418: iconst_0
-       419: invokestatic  #110                // Method androidx/compose/runtime/ComposablesKt.getCurrentCompositeKeyHashCode:(Landroidx/compose/runtime/Composer;I)J
-       422: invokestatic  #116                // Method java/lang/Long.hashCode:(J)I
-       425: istore        19
-       427: aload         16
-       429: invokeinterface #120,  1          // InterfaceMethod androidx/compose/runtime/Composer.getCurrentCompositionLocalMap:()Landroidx/compose/runtime/CompositionLocalMap;
-       434: astore        20
-       436: aload         16
-       438: aload         14
-       440: invokestatic  #126                // Method androidx/compose/ui/ComposedModifierKt.materializeModifier:(Landroidx/compose/runtime/Composer;Landroidx/compose/ui/Modifier;)Landroidx/compose/ui/Modifier;
-       443: astore        21
-       445: getstatic     #131                // Field androidx/compose/ui/node/ComposeUiNode.Companion:Landroidx/compose/ui/node/ComposeUiNode$Companion;
-       448: invokevirtual #137                // Method androidx/compose/ui/node/ComposeUiNode$Companion.getConstructor:()Lkotlin/jvm/functions/Function0;
-       451: astore        22
-       453: aload         16
-       455: astore        23
-       457: bipush        6
-       459: sipush        896
-       462: iload         17
-       464: bipush        6
-       466: ishl
-       467: iand
-       468: ior
-       469: istore        24
-       471: nop
-       472: iconst_0
-       473: istore        25
-       475: aload         23
-       477: ldc           #138                // int -553112988
-       479: ldc           #140                // String CC(ReusableComposeNode)N(factory,update,content)399@15590L9:Composables.kt#9igjgp
-       481: invokestatic  #68                 // Method androidx/compose/runtime/ComposerKt.sourceInformationMarkerStart:(Landroidx/compose/runtime/Composer;ILjava/lang/String;)V
-       484: aload         23
-       486: invokeinterface #144,  1          // InterfaceMethod androidx/compose/runtime/Composer.getApplier:()Landroidx/compose/runtime/Applier;
-       491: instanceof    #146                // class androidx/compose/runtime/Applier
-       494: ifne          500
-       497: invokestatic  #150                // Method androidx/compose/runtime/ComposablesKt.invalidApplier:()V
-       500: aload         23
-       502: invokeinterface #153,  1          // InterfaceMethod androidx/compose/runtime/Composer.startReusableNode:()V
-       507: aload         23
-       509: invokeinterface #156,  1          // InterfaceMethod androidx/compose/runtime/Composer.getInserting:()Z
-       514: ifeq          529
-       517: aload         23
-       519: aload         22
-       521: invokeinterface #160,  2          // InterfaceMethod androidx/compose/runtime/Composer.createNode:(Lkotlin/jvm/functions/Function0;)V
-       526: goto          536
-       529: aload         23
-       531: invokeinterface #163,  1          // InterfaceMethod androidx/compose/runtime/Composer.useNode:()V
-       536: aload         23
-       538: invokestatic  #169                // Method androidx/compose/runtime/Updater."constructor-impl":(Landroidx/compose/runtime/Composer;)Landroidx/compose/runtime/Composer;
-       541: astore        26
-       543: iconst_0
-       544: istore        27
-       546: aload         26
-       548: aload         15
-       550: getstatic     #131                // Field androidx/compose/ui/node/ComposeUiNode.Companion:Landroidx/compose/ui/node/ComposeUiNode$Companion;
-       553: invokevirtual #173                // Method androidx/compose/ui/node/ComposeUiNode$Companion.getSetMeasurePolicy:()Lkotlin/jvm/functions/Function2;
-       556: invokestatic  #177                // Method androidx/compose/runtime/Updater."set-impl":(Landroidx/compose/runtime/Composer;Ljava/lang/Object;Lkotlin/jvm/functions/Function2;)V
-       559: aload         26
-       561: aload         20
-       563: getstatic     #131                // Field androidx/compose/ui/node/ComposeUiNode.Companion:Landroidx/compose/ui/node/ComposeUiNode$Companion;
-       566: invokevirtual #180                // Method androidx/compose/ui/node/ComposeUiNode$Companion.getSetResolvedCompositionLocals:()Lkotlin/jvm/functions/Function2;
-       569: invokestatic  #177                // Method androidx/compose/runtime/Updater."set-impl":(Landroidx/compose/runtime/Composer;Ljava/lang/Object;Lkotlin/jvm/functions/Function2;)V
-       572: aload         26
-       574: iload         19
-       576: invokestatic  #186                // Method java/lang/Integer.valueOf:(I)Ljava/lang/Integer;
-       579: getstatic     #131                // Field androidx/compose/ui/node/ComposeUiNode.Companion:Landroidx/compose/ui/node/ComposeUiNode$Companion;
-       582: invokevirtual #189                // Method androidx/compose/ui/node/ComposeUiNode$Companion.getSetCompositeKeyHash:()Lkotlin/jvm/functions/Function2;
-       585: invokestatic  #192                // Method androidx/compose/runtime/Updater."init-impl":(Landroidx/compose/runtime/Composer;Ljava/lang/Object;Lkotlin/jvm/functions/Function2;)V
-       588: aload         26
-       590: getstatic     #131                // Field androidx/compose/ui/node/ComposeUiNode.Companion:Landroidx/compose/ui/node/ComposeUiNode$Companion;
-       593: invokevirtual #196                // Method androidx/compose/ui/node/ComposeUiNode$Companion.getApplyOnDeactivatedNodeAssertion:()Lkotlin/jvm/functions/Function1;
-       596: invokestatic  #200                // Method androidx/compose/runtime/Updater."reconcile-impl":(Landroidx/compose/runtime/Composer;Lkotlin/jvm/functions/Function1;)V
-       599: aload         26
-       601: aload         21
-       603: getstatic     #131                // Field androidx/compose/ui/node/ComposeUiNode.Companion:Landroidx/compose/ui/node/ComposeUiNode$Companion;
-       606: invokevirtual #203                // Method androidx/compose/ui/node/ComposeUiNode$Companion.getSetModifier:()Lkotlin/jvm/functions/Function2;
-       609: invokestatic  #177                // Method androidx/compose/runtime/Updater."set-impl":(Landroidx/compose/runtime/Composer;Ljava/lang/Object;Lkotlin/jvm/functions/Function2;)V
-       612: nop
-       613: nop
-       614: aload         23
-       616: bipush        14
-       618: iload         24
-       620: bipush        6
-       622: ishr
-       623: iand
-       624: istore        28
-       626: astore        29
-       628: iconst_0
-       629: istore        30
-       631: aload         29
-       633: ldc_w         #553                // int 1456264949
-       636: ldc_w         #555                // String C101@5233L9:Row.kt#2w3rfo
-       639: invokestatic  #68                 // Method androidx/compose/runtime/ComposerKt.sourceInformationMarkerStart:(Landroidx/compose/runtime/Composer;ILjava/lang/String;)V
-       642: getstatic     #560                // Field androidx/compose/foundation/layout/RowScopeInstance.INSTANCE:Landroidx/compose/foundation/layout/RowScopeInstance;
-       645: aload         29
-       647: bipush        6
-       649: bipush        112
-       651: iload         11
-       653: bipush        6
-       655: ishr
-       656: iand
-       657: ior
-       658: istore        31
-       660: astore        32
-       662: checkcast     #562                // class androidx/compose/foundation/layout/RowScope
-       665: astore        33
-       667: iconst_0
-       668: istore        34
-       670: aload         32
-       672: ldc_w         #796                // int -350304862
-       675: ldc_w         #798                // String C154@5668L43,153@5640L235,161@5942L10,159@5884L320:JetchatDrawer.kt#o9oqao
-       678: invokestatic  #68                 // Method androidx/compose/runtime/ComposerKt.sourceInformationMarkerStart:(Landroidx/compose/runtime/Composer;ILjava/lang/String;)V
-       681: iload_1
-       682: ifeq          731
-       685: aload         32
-       687: ldc_w         #799                // int -350296989
-       690: invokeinterface #391,  2          // InterfaceMethod androidx/compose/runtime/Composer.startReplaceGroup:(I)V
-       695: aload         32
-       697: ldc_w         #801                // String 149@5530L11
-       700: invokestatic  #38                 // Method androidx/compose/runtime/ComposerKt.sourceInformation:(Landroidx/compose/runtime/Composer;Ljava/lang/String;)V
-       703: getstatic     #682                // Field androidx/compose/material3/MaterialTheme.INSTANCE:Landroidx/compose/material3/MaterialTheme;
-       706: aload         32
-       708: getstatic     #683                // Field androidx/compose/material3/MaterialTheme.$stable:I
-       711: invokevirtual #697                // Method androidx/compose/material3/MaterialTheme.getColorScheme:(Landroidx/compose/runtime/Composer;I)Landroidx/compose/material3/ColorScheme;
-       714: invokevirtual #804                // Method androidx/compose/material3/ColorScheme."getPrimary-0d7_KjU":()J
-       717: lstore        35
-       719: aload         32
-       721: invokeinterface #401,  1          // InterfaceMethod androidx/compose/runtime/Composer.endReplaceGroup:()V
-       726: lload         35
-       728: goto          774
-       731: aload         32
-       733: ldc_w         #805                // int -350234214
-       736: invokeinterface #391,  2          // InterfaceMethod androidx/compose/runtime/Composer.startReplaceGroup:(I)V
-       741: aload         32
-       743: ldc_w         #807                // String 151@5593L11
-       746: invokestatic  #38                 // Method androidx/compose/runtime/ComposerKt.sourceInformation:(Landroidx/compose/runtime/Composer;Ljava/lang/String;)V
-       749: getstatic     #682                // Field androidx/compose/material3/MaterialTheme.INSTANCE:Landroidx/compose/material3/MaterialTheme;
-       752: aload         32
-       754: getstatic     #683                // Field androidx/compose/material3/MaterialTheme.$stable:I
-       757: invokevirtual #697                // Method androidx/compose/material3/MaterialTheme.getColorScheme:(Landroidx/compose/runtime/Composer;I)Landroidx/compose/material3/ColorScheme;
-       760: invokevirtual #703                // Method androidx/compose/material3/ColorScheme."getOnSurfaceVariant-0d7_KjU":()J
-       763: lstore        35
-       765: aload         32
-       767: invokeinterface #401,  1          // InterfaceMethod androidx/compose/runtime/Composer.endReplaceGroup:()V
-       772: lload         35
-       774: lstore        37
-       776: getstatic     #810                // Field com/example/compose/jetchat/R$drawable.ic_jetchat:I
-       779: aload         32
-       781: iconst_0
-       782: invokestatic  #587                // Method androidx/compose/ui/res/PainterResources_androidKt.painterResource:(ILandroidx/compose/runtime/Composer;I)Landroidx/compose/ui/graphics/painter/Painter;
-       785: astore        39
-       787: getstatic     #74                 // Field androidx/compose/ui/Modifier.Companion:Landroidx/compose/ui/Modifier$Companion;
-       790: checkcast     #70                 // class androidx/compose/ui/Modifier
-       793: bipush        16
-       795: istore        40
-       797: iconst_0
-       798: istore        41
-       800: iload         40
-       802: i2f
-       803: invokestatic  #318                // Method androidx/compose/ui/unit/Dp."constructor-impl":(F)F
-       806: bipush        16
-       808: istore        40
-       810: iconst_0
-       811: istore        41
-       813: iload         40
-       815: i2f
-       816: invokestatic  #318                // Method androidx/compose/ui/unit/Dp."constructor-impl":(F)F
-       819: fconst_0
-       820: bipush        16
-       822: istore        40
-       824: iconst_0
-       825: istore        41
-       827: iload         40
-       829: i2f
-       830: invokestatic  #318                // Method androidx/compose/ui/unit/Dp."constructor-impl":(F)F
-       833: iconst_4
-       834: aconst_null
-       835: invokestatic  #591                // Method androidx/compose/foundation/layout/PaddingKt."padding-qDBjuR0$default":(Landroidx/compose/ui/Modifier;FFFFILjava/lang/Object;)Landroidx/compose/ui/Modifier;
-       838: astore        42
-       840: aload         39
-       842: aconst_null
-       843: aload         42
-       845: lload         37
-       847: aload         32
-       849: sipush        432
-       852: getstatic     #596                // Field androidx/compose/ui/graphics/painter/Painter.$stable:I
-       855: ior
-       856: iconst_0
-       857: invokestatic  #816                // Method androidx/compose/material3/IconKt."Icon-ww6aTOc":(Landroidx/compose/ui/graphics/painter/Painter;Ljava/lang/String;Landroidx/compose/ui/Modifier;JLandroidx/compose/runtime/Composer;II)V
-       860: getstatic     #682                // Field androidx/compose/material3/MaterialTheme.INSTANCE:Landroidx/compose/material3/MaterialTheme;
-       863: aload         32
-       865: getstatic     #683                // Field androidx/compose/material3/MaterialTheme.$stable:I
-       868: invokevirtual #687                // Method androidx/compose/material3/MaterialTheme.getTypography:(Landroidx/compose/runtime/Composer;I)Landroidx/compose/material3/Typography;
-       871: invokevirtual #819                // Method androidx/compose/material3/Typography.getBodyMedium:()Landroidx/compose/ui/text/TextStyle;
-       874: astore        39
-       876: iload_1
-       877: ifeq          926
-       880: aload         32
-       882: ldc_w         #820                // int -349803717
-       885: invokeinterface #391,  2          // InterfaceMethod androidx/compose/runtime/Composer.startReplaceGroup:(I)V
-       890: aload         32
-       892: ldc_w         #822                // String 163@6031L11
-       895: invokestatic  #38                 // Method androidx/compose/runtime/ComposerKt.sourceInformation:(Landroidx/compose/runtime/Composer;Ljava/lang/String;)V
-       898: getstatic     #682                // Field androidx/compose/material3/MaterialTheme.INSTANCE:Landroidx/compose/material3/MaterialTheme;
-       901: aload         32
-       903: getstatic     #683                // Field androidx/compose/material3/MaterialTheme.$stable:I
-       906: invokevirtual #697                // Method androidx/compose/material3/MaterialTheme.getColorScheme:(Landroidx/compose/runtime/Composer;I)Landroidx/compose/material3/ColorScheme;
-       909: invokevirtual #804                // Method androidx/compose/material3/ColorScheme."getPrimary-0d7_KjU":()J
-       912: lstore        43
-       914: aload         32
-       916: invokeinterface #401,  1          // InterfaceMethod androidx/compose/runtime/Composer.endReplaceGroup:()V
-       921: lload         43
-       923: goto          969
-       926: aload         32
-       928: ldc_w         #823                // int -349733223
-       931: invokeinterface #391,  2          // InterfaceMethod androidx/compose/runtime/Composer.startReplaceGroup:(I)V
-       936: aload         32
-       938: ldc_w         #825                // String 165@6102L11
-       941: invokestatic  #38                 // Method androidx/compose/runtime/ComposerKt.sourceInformation:(Landroidx/compose/runtime/Composer;Ljava/lang/String;)V
-       944: getstatic     #682                // Field androidx/compose/material3/MaterialTheme.INSTANCE:Landroidx/compose/material3/MaterialTheme;
-       947: aload         32
-       949: getstatic     #683                // Field androidx/compose/material3/MaterialTheme.$stable:I
-       952: invokevirtual #697                // Method androidx/compose/material3/MaterialTheme.getColorScheme:(Landroidx/compose/runtime/Composer;I)Landroidx/compose/material3/ColorScheme;
-       955: invokevirtual #828                // Method androidx/compose/material3/ColorScheme."getOnSurface-0d7_KjU":()J
-       958: lstore        43
-       960: aload         32
-       962: invokeinterface #401,  1          // InterfaceMethod androidx/compose/runtime/Composer.endReplaceGroup:()V
-       967: lload         43
-       969: lstore        45
-       971: getstatic     #74                 // Field androidx/compose/ui/Modifier.Companion:Landroidx/compose/ui/Modifier$Companion;
-       974: checkcast     #70                 // class androidx/compose/ui/Modifier
-       977: bipush        12
-       979: istore        47
-       981: iconst_0
-       982: istore        48
-       984: iload         47
-       986: i2f
-       987: invokestatic  #318                // Method androidx/compose/ui/unit/Dp."constructor-impl":(F)F
-       990: fconst_0
-       991: fconst_0
-       992: fconst_0
-       993: bipush        14
-       995: aconst_null
-       996: invokestatic  #591                // Method androidx/compose/foundation/layout/PaddingKt."padding-qDBjuR0$default":(Landroidx/compose/ui/Modifier;FFFFILjava/lang/Object;)Landroidx/compose/ui/Modifier;
-       999: astore        41
-      1001: aload_0
-      1002: aload         41
-      1004: lload         45
-      1006: aconst_null
-      1007: lconst_0
-      1008: aconst_null
-      1009: aconst_null
-      1010: aconst_null
-      1011: lconst_0
-      1012: aconst_null
-      1013: aconst_null
-      1014: lconst_0
-      1015: iconst_0
-      1016: iconst_0
-      1017: iconst_0
-      1018: iconst_0
-      1019: aconst_null
-      1020: aload         39
-      1022: aload         32
-      1024: bipush        48
-      1026: bipush        14
-      1028: iload         5
-      1030: iand
-      1031: ior
-      1032: iconst_0
-      1033: ldc_w         #829                // int 131064
-      1036: invokestatic  #710                // Method androidx/compose/material3/TextKt."Text-Nvy7gAk":(Ljava/lang/String;Landroidx/compose/ui/Modifier;JLandroidx/compose/foundation/text/TextAutoSize;JLandroidx/compose/ui/text/font/FontStyle;Landroidx/compose/ui/text/font/FontWeight;Landroidx/compose/ui/text/font/FontFamily;JLandroidx/compose/ui/text/style/TextDecoration;Landroidx/compose/ui/text/style/TextAlign;JIZIILkotlin/jvm/functions/Function1;Landroidx/compose/ui/text/TextStyle;Landroidx/compose/runtime/Composer;III)V
-      1039: aload         32
-      1041: invokestatic  #301                // Method androidx/compose/runtime/ComposerKt.sourceInformationMarkerEnd:(Landroidx/compose/runtime/Composer;)V
-      1044: nop
-      1045: aload         29
-      1047: invokestatic  #301                // Method androidx/compose/runtime/ComposerKt.sourceInformationMarkerEnd:(Landroidx/compose/runtime/Composer;)V
-      1050: aload         23
-      1052: invokeinterface #405,  1          // InterfaceMethod androidx/compose/runtime/Composer.endNode:()V
-      1057: aload         23
-      1059: invokestatic  #301                // Method androidx/compose/runtime/ComposerKt.sourceInformationMarkerEnd:(Landroidx/compose/runtime/Composer;)V
-      1062: nop
-      1063: aload         16
-      1065: invokestatic  #301                // Method androidx/compose/runtime/ComposerKt.sourceInformationMarkerEnd:(Landroidx/compose/runtime/Composer;)V
-      1068: nop
-      1069: aload         10
-      1071: invokestatic  #301                // Method androidx/compose/runtime/ComposerKt.sourceInformationMarkerEnd:(Landroidx/compose/runtime/Composer;)V
-      1074: nop
-      1075: invokestatic  #55                 // Method androidx/compose/runtime/ComposerKt.isTraceInProgress:()Z
-      1078: ifeq          1093
-      1081: invokestatic  #408                // Method androidx/compose/runtime/ComposerKt.traceEventEnd:()V
-      1084: goto          1093
-      1087: aload_3
-      1088: invokeinterface #411,  1          // InterfaceMethod androidx/compose/runtime/Composer.skipToGroupEnd:()V
-      1093: aload_3
-      1094: invokeinterface #415,  1          // InterfaceMethod androidx/compose/runtime/Composer.endRestartGroup:()Landroidx/compose/runtime/ScopeUpdateScope;
-      1099: dup
-      1100: ifnull        1121
-      1103: aload_0
-      1104: iload_1
-      1105: aload_2
-      1106: iload         4
-      1108: invokedynamic #837,  0            // InvokeDynamic #7:invoke:(Ljava/lang/String;ZLkotlin/jvm/functions/Function0;I)Lkotlin/jvm/functions/Function2;
-      1113: invokeinterface #433,  2          // InterfaceMethod androidx/compose/runtime/ScopeUpdateScope.updateScope:(Lkotlin/jvm/functions/Function2;)V
-      1118: goto          1122
-      1121: pop
-      1122: return
-
-  private static final void ProfileItem(java.lang.String, java.lang.Integer, boolean, kotlin.jvm.functions.Function0<kotlin.Unit>, androidx.compose.runtime.Composer, int, int);
-    Code:
-         0: aload         4
-         2: ldc_w         #864                // int -833628720
-         5: invokeinterface #30,  2           // InterfaceMethod androidx/compose/runtime/Composer.startRestartGroup:(I)Landroidx/compose/runtime/Composer;
-        10: astore        4
-        12: aload         4
-        14: ldc_w         #866                // String C(ProfileItem)N(text,profilePic,selected,onProfileClicked)179@6503L1025:JetchatDrawer.kt#o9oqao
-        17: invokestatic  #38                 // Method androidx/compose/runtime/ComposerKt.sourceInformation:(Landroidx/compose/runtime/Composer;Ljava/lang/String;)V
-        20: iload         5
-        22: istore        7
-        24: iload         5
-        26: bipush        6
-        28: iand
-        29: ifne          53
-        32: iload         7
-        34: aload         4
-        36: aload_0
-        37: invokeinterface #45,  2           // InterfaceMethod androidx/compose/runtime/Composer.changed:(Ljava/lang/Object;)Z
-        42: ifeq          49
-        45: iconst_4
-        46: goto          50
-        49: iconst_2
-        50: ior
-        51: istore        7
-        53: iload         5
-        55: bipush        48
-        57: iand
-        58: ifne          84
-        61: iload         7
-        63: aload         4
-        65: aload_1
-        66: invokeinterface #45,  2           // InterfaceMethod androidx/compose/runtime/Composer.changed:(Ljava/lang/Object;)Z
-        71: ifeq          79
-        74: bipush        32
-        76: goto          81
-        79: bipush        16
-        81: ior
-        82: istore        7
-        84: iload         6
-        86: iconst_4
-        87: iand
-        88: ifeq          102
-        91: iload         7
-        93: sipush        384
-        96: ior
-        97: istore        7
-        99: goto          136
-       102: iload         5
-       104: sipush        384
-       107: iand
-       108: ifne          136
-       111: iload         7
-       113: aload         4
-       115: iload_2
-       116: invokeinterface #749,  2          // InterfaceMethod androidx/compose/runtime/Composer.changed:(Z)Z
-       121: ifeq          130
-       124: sipush        256
-       127: goto          133
-       130: sipush        128
-       133: ior
-       134: istore        7
-       136: iload         5
-       138: sipush        3072
-       141: iand
-       142: ifne          170
-       145: iload         7
-       147: aload         4
-       149: aload_3
-       150: invokeinterface #42,  2           // InterfaceMethod androidx/compose/runtime/Composer.changedInstance:(Ljava/lang/Object;)Z
-       155: ifeq          164
-       158: sipush        2048
-       161: goto          167
-       164: sipush        1024
-       167: ior
-       168: istore        7
-       170: aload         4
-       172: iload         7
-       174: sipush        1171
-       177: iand
-       178: sipush        1170
-       181: if_icmpeq     188
-       184: iconst_1
-       185: goto          189
-       188: iconst_0
-       189: iload         7
-       191: iconst_1
-       192: iand
-       193: invokeinterface #49,  3           // InterfaceMethod androidx/compose/runtime/Composer.shouldExecute:(ZI)Z
-       198: ifeq          1113
-       201: iload         6
-       203: iconst_4
-       204: iand
-       205: ifeq          210
-       208: iconst_0
-       209: istore_2
-       210: invokestatic  #55                 // Method androidx/compose/runtime/ComposerKt.isTraceInProgress:()Z
-       213: ifeq          228
-       216: ldc_w         #864                // int -833628720
-       219: iload         7
-       221: iconst_m1
-       222: ldc_w         #868                // String com.example.compose.jetchat.components.ProfileItem (JetchatDrawer.kt:173)
-       225: invokestatic  #61                 // Method androidx/compose/runtime/ComposerKt.traceEventStart:(IIILjava/lang/String;)V
-       228: iload_2
-       229: ifeq          290
-       232: aload         4
-       234: ldc_w         #869                // int -1132135837
-       237: invokeinterface #391,  2          // InterfaceMethod androidx/compose/runtime/Composer.startReplaceGroup:(I)V
-       242: aload         4
-       244: ldc_w         #871                // String 175@6433L11
-       247: invokestatic  #38                 // Method androidx/compose/runtime/ComposerKt.sourceInformation:(Landroidx/compose/runtime/Composer;Ljava/lang/String;)V
-       250: getstatic     #74                 // Field androidx/compose/ui/Modifier.Companion:Landroidx/compose/ui/Modifier$Companion;
-       253: checkcast     #70                 // class androidx/compose/ui/Modifier
-       256: getstatic     #682                // Field androidx/compose/material3/MaterialTheme.INSTANCE:Landroidx/compose/material3/MaterialTheme;
-       259: aload         4
-       261: getstatic     #683                // Field androidx/compose/material3/MaterialTheme.$stable:I
-       264: invokevirtual #697                // Method androidx/compose/material3/MaterialTheme.getColorScheme:(Landroidx/compose/runtime/Composer;I)Landroidx/compose/material3/ColorScheme;
-       267: invokevirtual #757                // Method androidx/compose/material3/ColorScheme."getPrimaryContainer-0d7_KjU":()J
-       270: aconst_null
-       271: iconst_2
-       272: aconst_null
-       273: invokestatic  #763                // Method androidx/compose/foundation/BackgroundKt."background-bw27NRU$default":(Landroidx/compose/ui/Modifier;JLandroidx/compose/ui/graphics/Shape;ILjava/lang/Object;)Landroidx/compose/ui/Modifier;
-       276: astore        9
-       278: aload         4
-       280: invokeinterface #401,  1          // InterfaceMethod androidx/compose/runtime/Composer.endReplaceGroup:()V
-       285: aload         9
-       287: goto          313
-       290: aload         4
-       292: ldc_w         #872                // int -1132053222
-       295: invokeinterface #391,  2          // InterfaceMethod androidx/compose/runtime/Composer.startReplaceGroup:(I)V
-       300: aload         4
-       302: invokeinterface #401,  1          // InterfaceMethod androidx/compose/runtime/Composer.endReplaceGroup:()V
-       307: getstatic     #74                 // Field androidx/compose/ui/Modifier.Companion:Landroidx/compose/ui/Modifier$Companion;
-       310: checkcast     #70                 // class androidx/compose/ui/Modifier
-       313: astore        8
-       315: getstatic     #74                 // Field androidx/compose/ui/Modifier.Companion:Landroidx/compose/ui/Modifier$Companion;
-       318: checkcast     #70                 // class androidx/compose/ui/Modifier
-       321: bipush        56
-       323: istore        9
-       325: iconst_0
-       326: istore        10
-       328: iload         9
-       330: i2f
-       331: invokestatic  #318                // Method androidx/compose/ui/unit/Dp."constructor-impl":(F)F
-       334: invokestatic  #767                // Method androidx/compose/foundation/layout/SizeKt."height-3ABfNKs":(Landroidx/compose/ui/Modifier;F)Landroidx/compose/ui/Modifier;
-       337: fconst_0
-       338: iconst_1
-       339: aconst_null
-       340: invokestatic  #771                // Method androidx/compose/foundation/layout/SizeKt.fillMaxWidth$default:(Landroidx/compose/ui/Modifier;FILjava/lang/Object;)Landroidx/compose/ui/Modifier;
-       343: bipush        12
-       345: istore        9
-       347: iconst_0
-       348: istore        10
-       350: iload         9
-       352: i2f
-       353: invokestatic  #318                // Method androidx/compose/ui/unit/Dp."constructor-impl":(F)F
-       356: fconst_0
-       357: iconst_2
-       358: aconst_null
-       359: invokestatic  #324                // Method androidx/compose/foundation/layout/PaddingKt."padding-VpY3zN4$default":(Landroidx/compose/ui/Modifier;FFILjava/lang/Object;)Landroidx/compose/ui/Modifier;
-       362: invokestatic  #777                // Method androidx/compose/foundation/shape/RoundedCornerShapeKt.getCircleShape:()Landroidx/compose/foundation/shape/RoundedCornerShape;
-       365: checkcast     #779                // class androidx/compose/ui/graphics/Shape
-       368: invokestatic  #785                // Method androidx/compose/ui/draw/ClipKt.clip:(Landroidx/compose/ui/Modifier;Landroidx/compose/ui/graphics/Shape;)Landroidx/compose/ui/Modifier;
-       371: aload         8
-       373: invokeinterface #789,  2          // InterfaceMethod androidx/compose/ui/Modifier.then:(Landroidx/compose/ui/Modifier;)Landroidx/compose/ui/Modifier;
-       378: iconst_0
-       379: aconst_null
-       380: aconst_null
-       381: aconst_null
-       382: aload_3
-       383: bipush        15
-       385: aconst_null
-       386: invokestatic  #795                // Method androidx/compose/foundation/ClickableKt."clickable-oSLSa3U$default":(Landroidx/compose/ui/Modifier;ZLjava/lang/String;Landroidx/compose/ui/semantics/Role;Landroidx/compose/foundation/interaction/MutableInteractionSource;Lkotlin/jvm/functions/Function0;ILjava/lang/Object;)Landroidx/compose/ui/Modifier;
-       389: astore        9
-       391: getstatic     #89                 // Field androidx/compose/ui/Alignment.Companion:Landroidx/compose/ui/Alignment$Companion;
-       394: invokevirtual #540                // Method androidx/compose/ui/Alignment$Companion.getCenterVertically:()Landroidx/compose/ui/Alignment$Vertical;
-       397: astore        11
-       399: aload         4
-       401: astore        12
-       403: sipush        384
-       406: istore        13
-       408: nop
-       409: iconst_0
-       410: istore        14
-       412: aload         12
-       414: ldc_w         #541                // int 844473419
-       417: ldc_w         #543                // String CC(Row)N(modifier,horizontalArrangement,verticalAlignment,content)99@5125L58,100@5188L131:Row.kt#2w3rfo
-       420: invokestatic  #68                 // Method androidx/compose/runtime/ComposerKt.sourceInformationMarkerStart:(Landroidx/compose/runtime/Composer;ILjava/lang/String;)V
-       423: getstatic     #80                 // Field androidx/compose/foundation/layout/Arrangement.INSTANCE:Landroidx/compose/foundation/layout/Arrangement;
-       426: invokevirtual #546                // Method androidx/compose/foundation/layout/Arrangement.getStart:()Landroidx/compose/foundation/layout/Arrangement$Horizontal;
-       429: astore        10
-       431: aload         10
-       433: aload         11
-       435: aload         12
-       437: bipush        14
-       439: iload         13
-       441: iconst_3
-       442: ishr
-       443: iand
-       444: bipush        112
-       446: iload         13
-       448: iconst_3
-       449: ishr
-       450: iand
-       451: ior
-       452: invokestatic  #552                // Method androidx/compose/foundation/layout/RowKt.rowMeasurePolicy:(Landroidx/compose/foundation/layout/Arrangement$Horizontal;Landroidx/compose/ui/Alignment$Vertical;Landroidx/compose/runtime/Composer;I)Landroidx/compose/ui/layout/MeasurePolicy;
-       455: astore        15
-       457: aload         9
-       459: astore        16
-       461: aload         15
-       463: astore        17
-       465: aload         12
-       467: astore        18
-       469: bipush        112
-       471: iload         13
-       473: iconst_3
-       474: ishl
-       475: iand
-       476: istore        19
-       478: nop
-       479: iconst_0
-       480: istore        20
-       482: aload         18
-       484: ldc           #102                // int -1159599143
-       486: ldc           #104                // String CC(Layout)P(!1,2)81@3355L27,84@3521L416:Layout.kt#80mrfh
-       488: invokestatic  #68                 // Method androidx/compose/runtime/ComposerKt.sourceInformationMarkerStart:(Landroidx/compose/runtime/Composer;ILjava/lang/String;)V
-       491: aload         18
-       493: iconst_0
-       494: invokestatic  #110                // Method androidx/compose/runtime/ComposablesKt.getCurrentCompositeKeyHashCode:(Landroidx/compose/runtime/Composer;I)J
-       497: invokestatic  #116                // Method java/lang/Long.hashCode:(J)I
-       500: istore        21
-       502: aload         18
-       504: invokeinterface #120,  1          // InterfaceMethod androidx/compose/runtime/Composer.getCurrentCompositionLocalMap:()Landroidx/compose/runtime/CompositionLocalMap;
-       509: astore        22
-       511: aload         18
-       513: aload         16
-       515: invokestatic  #126                // Method androidx/compose/ui/ComposedModifierKt.materializeModifier:(Landroidx/compose/runtime/Composer;Landroidx/compose/ui/Modifier;)Landroidx/compose/ui/Modifier;
-       518: astore        23
-       520: getstatic     #131                // Field androidx/compose/ui/node/ComposeUiNode.Companion:Landroidx/compose/ui/node/ComposeUiNode$Companion;
-       523: invokevirtual #137                // Method androidx/compose/ui/node/ComposeUiNode$Companion.getConstructor:()Lkotlin/jvm/functions/Function0;
-       526: astore        24
-       528: aload         18
-       530: astore        25
-       532: bipush        6
-       534: sipush        896
-       537: iload         19
-       539: bipush        6
-       541: ishl
-       542: iand
-       543: ior
-       544: istore        26
-       546: nop
-       547: iconst_0
-       548: istore        27
-       550: aload         25
-       552: ldc           #138                // int -553112988
-       554: ldc           #140                // String CC(ReusableComposeNode)N(factory,update,content)399@15590L9:Composables.kt#9igjgp
-       556: invokestatic  #68                 // Method androidx/compose/runtime/ComposerKt.sourceInformationMarkerStart:(Landroidx/compose/runtime/Composer;ILjava/lang/String;)V
-       559: aload         25
-       561: invokeinterface #144,  1          // InterfaceMethod androidx/compose/runtime/Composer.getApplier:()Landroidx/compose/runtime/Applier;
-       566: instanceof    #146                // class androidx/compose/runtime/Applier
-       569: ifne          575
-       572: invokestatic  #150                // Method androidx/compose/runtime/ComposablesKt.invalidApplier:()V
-       575: aload         25
-       577: invokeinterface #153,  1          // InterfaceMethod androidx/compose/runtime/Composer.startReusableNode:()V
-       582: aload         25
-       584: invokeinterface #156,  1          // InterfaceMethod androidx/compose/runtime/Composer.getInserting:()Z
-       589: ifeq          604
-       592: aload         25
-       594: aload         24
-       596: invokeinterface #160,  2          // InterfaceMethod androidx/compose/runtime/Composer.createNode:(Lkotlin/jvm/functions/Function0;)V
-       601: goto          611
-       604: aload         25
-       606: invokeinterface #163,  1          // InterfaceMethod androidx/compose/runtime/Composer.useNode:()V
-       611: aload         25
-       613: invokestatic  #169                // Method androidx/compose/runtime/Updater."constructor-impl":(Landroidx/compose/runtime/Composer;)Landroidx/compose/runtime/Composer;
-       616: astore        28
-       618: iconst_0
-       619: istore        29
-       621: aload         28
-       623: aload         17
-       625: getstatic     #131                // Field androidx/compose/ui/node/ComposeUiNode.Companion:Landroidx/compose/ui/node/ComposeUiNode$Companion;
-       628: invokevirtual #173                // Method androidx/compose/ui/node/ComposeUiNode$Companion.getSetMeasurePolicy:()Lkotlin/jvm/functions/Function2;
-       631: invokestatic  #177                // Method androidx/compose/runtime/Updater."set-impl":(Landroidx/compose/runtime/Composer;Ljava/lang/Object;Lkotlin/jvm/functions/Function2;)V
-       634: aload         28
-       636: aload         22
-       638: getstatic     #131                // Field androidx/compose/ui/node/ComposeUiNode.Companion:Landroidx/compose/ui/node/ComposeUiNode$Companion;
-       641: invokevirtual #180                // Method androidx/compose/ui/node/ComposeUiNode$Companion.getSetResolvedCompositionLocals:()Lkotlin/jvm/functions/Function2;
-       644: invokestatic  #177                // Method androidx/compose/runtime/Updater."set-impl":(Landroidx/compose/runtime/Composer;Ljava/lang/Object;Lkotlin/jvm/functions/Function2;)V
-       647: aload         28
-       649: iload         21
-       651: invokestatic  #186                // Method java/lang/Integer.valueOf:(I)Ljava/lang/Integer;
-       654: getstatic     #131                // Field androidx/compose/ui/node/ComposeUiNode.Companion:Landroidx/compose/ui/node/ComposeUiNode$Companion;
-       657: invokevirtual #189                // Method androidx/compose/ui/node/ComposeUiNode$Companion.getSetCompositeKeyHash:()Lkotlin/jvm/functions/Function2;
-       660: invokestatic  #192                // Method androidx/compose/runtime/Updater."init-impl":(Landroidx/compose/runtime/Composer;Ljava/lang/Object;Lkotlin/jvm/functions/Function2;)V
-       663: aload         28
-       665: getstatic     #131                // Field androidx/compose/ui/node/ComposeUiNode.Companion:Landroidx/compose/ui/node/ComposeUiNode$Companion;
-       668: invokevirtual #196                // Method androidx/compose/ui/node/ComposeUiNode$Companion.getApplyOnDeactivatedNodeAssertion:()Lkotlin/jvm/functions/Function1;
-       671: invokestatic  #200                // Method androidx/compose/runtime/Updater."reconcile-impl":(Landroidx/compose/runtime/Composer;Lkotlin/jvm/functions/Function1;)V
-       674: aload         28
-       676: aload         23
-       678: getstatic     #131                // Field androidx/compose/ui/node/ComposeUiNode.Companion:Landroidx/compose/ui/node/ComposeUiNode$Companion;
-       681: invokevirtual #203                // Method androidx/compose/ui/node/ComposeUiNode$Companion.getSetModifier:()Lkotlin/jvm/functions/Function2;
-       684: invokestatic  #177                // Method androidx/compose/runtime/Updater."set-impl":(Landroidx/compose/runtime/Composer;Ljava/lang/Object;Lkotlin/jvm/functions/Function2;)V
-       687: nop
-       688: nop
-       689: aload         25
-       691: bipush        14
-       693: iload         26
-       695: bipush        6
-       697: ishr
-       698: iand
-       699: istore        30
-       701: astore        31
-       703: iconst_0
-       704: istore        32
-       706: aload         31
-       708: ldc_w         #553                // int 1456264949
-       711: ldc_w         #555                // String C101@5233L9:Row.kt#2w3rfo
-       714: invokestatic  #68                 // Method androidx/compose/runtime/ComposerKt.sourceInformationMarkerStart:(Landroidx/compose/runtime/Composer;ILjava/lang/String;)V
-       717: getstatic     #560                // Field androidx/compose/foundation/layout/RowScopeInstance.INSTANCE:Landroidx/compose/foundation/layout/RowScopeInstance;
-       720: aload         31
-       722: bipush        6
-       724: bipush        112
-       726: iload         13
-       728: bipush        6
-       730: ishr
-       731: iand
-       732: ior
-       733: istore        33
-       735: astore        34
-       737: checkcast     #562                // class androidx/compose/foundation/layout/RowScope
-       740: astore        35
-       742: iconst_0
-       743: istore        36
-       745: aload         34
-       747: ldc_w         #873                // int -1288282132
-       750: ldc_w         #875                // String C204@7377L10,205@7434L11,202@7319L203:JetchatDrawer.kt#o9oqao
-       753: invokestatic  #68                 // Method androidx/compose/runtime/ComposerKt.sourceInformationMarkerStart:(Landroidx/compose/runtime/Composer;ILjava/lang/String;)V
-       756: getstatic     #74                 // Field androidx/compose/ui/Modifier.Companion:Landroidx/compose/ui/Modifier$Companion;
-       759: checkcast     #70                 // class androidx/compose/ui/Modifier
-       762: bipush        16
-       764: istore        37
-       766: iconst_0
-       767: istore        38
-       769: iload         37
-       771: i2f
-       772: invokestatic  #318                // Method androidx/compose/ui/unit/Dp."constructor-impl":(F)F
-       775: bipush        16
-       777: istore        37
-       779: iconst_0
-       780: istore        38
-       782: iload         37
-       784: i2f
-       785: invokestatic  #318                // Method androidx/compose/ui/unit/Dp."constructor-impl":(F)F
-       788: fconst_0
-       789: bipush        16
-       791: istore        37
-       793: iconst_0
-       794: istore        38
-       796: iload         37
-       798: i2f
-       799: invokestatic  #318                // Method androidx/compose/ui/unit/Dp."constructor-impl":(F)F
-       802: iconst_4
-       803: aconst_null
-       804: invokestatic  #591                // Method androidx/compose/foundation/layout/PaddingKt."padding-qDBjuR0$default":(Landroidx/compose/ui/Modifier;FFFFILjava/lang/Object;)Landroidx/compose/ui/Modifier;
-       807: bipush        24
-       809: istore        37
-       811: iconst_0
-       812: istore        38
-       814: iload         37
-       816: i2f
-       817: invokestatic  #318                // Method androidx/compose/ui/unit/Dp."constructor-impl":(F)F
-       820: invokestatic  #570                // Method androidx/compose/foundation/layout/SizeKt."size-3ABfNKs":(Landroidx/compose/ui/Modifier;F)Landroidx/compose/ui/Modifier;
-       823: astore        39
-       825: aload_1
-       826: ifnull        931
-       829: aload         34
-       831: ldc_w         #876                // int -1288126792
-       834: invokeinterface #391,  2          // InterfaceMethod androidx/compose/runtime/Composer.startReplaceGroup:(I)V
-       839: aload         34
-       841: ldc_w         #878                // String 194@7011L32,193@6978L254
-       844: invokestatic  #38                 // Method androidx/compose/runtime/ComposerKt.sourceInformation:(Landroidx/compose/runtime/Composer;Ljava/lang/String;)V
-       847: aload_1
-       848: invokevirtual #882                // Method java/lang/Integer.intValue:()I
-       851: aload         34
-       853: bipush        14
-       855: iload         7
-       857: iconst_3
-       858: ishr
-       859: iand
-       860: invokestatic  #587                // Method androidx/compose/ui/res/PainterResources_androidKt.painterResource:(ILandroidx/compose/runtime/Composer;I)Landroidx/compose/ui/graphics/painter/Painter;
-       863: astore        37
-       865: aload         39
-       867: getstatic     #74                 // Field androidx/compose/ui/Modifier.Companion:Landroidx/compose/ui/Modifier$Companion;
-       870: checkcast     #70                 // class androidx/compose/ui/Modifier
-       873: invokestatic  #777                // Method androidx/compose/foundation/shape/RoundedCornerShapeKt.getCircleShape:()Landroidx/compose/foundation/shape/RoundedCornerShape;
-       876: checkcast     #779                // class androidx/compose/ui/graphics/Shape
-       879: invokestatic  #785                // Method androidx/compose/ui/draw/ClipKt.clip:(Landroidx/compose/ui/Modifier;Landroidx/compose/ui/graphics/Shape;)Landroidx/compose/ui/Modifier;
-       882: invokeinterface #789,  2          // InterfaceMethod androidx/compose/ui/Modifier.then:(Landroidx/compose/ui/Modifier;)Landroidx/compose/ui/Modifier;
-       887: astore        38
-       889: getstatic     #887                // Field androidx/compose/ui/layout/ContentScale.Companion:Landroidx/compose/ui/layout/ContentScale$Companion;
-       892: invokevirtual #893                // Method androidx/compose/ui/layout/ContentScale$Companion.getCrop:()Landroidx/compose/ui/layout/ContentScale;
-       895: astore        40
-       897: aload         37
-       899: aconst_null
-       900: aload         38
-       902: aconst_null
-       903: aload         40
-       905: fconst_0
-       906: aconst_null
-       907: aload         34
-       909: sipush        24624
-       912: getstatic     #596                // Field androidx/compose/ui/graphics/painter/Painter.$stable:I
-       915: ior
-       916: bipush        104
-       918: invokestatic  #602                // Method androidx/compose/foundation/ImageKt.Image:(Landroidx/compose/ui/graphics/painter/Painter;Ljava/lang/String;Landroidx/compose/ui/Modifier;Landroidx/compose/ui/Alignment;Landroidx/compose/ui/layout/ContentScale;FLandroidx/compose/ui/graphics/ColorFilter;Landroidx/compose/runtime/Composer;II)V
-       921: aload         34
-       923: invokeinterface #401,  1          // InterfaceMethod androidx/compose/runtime/Composer.endReplaceGroup:()V
-       928: goto          965
-       931: aload         34
-       933: ldc_w         #894                // int -1287864904
-       936: invokeinterface #391,  2          // InterfaceMethod androidx/compose/runtime/Composer.startReplaceGroup:(I)V
-       941: aload         34
-       943: ldc_w         #896                // String 200@7262L38
-       946: invokestatic  #38                 // Method androidx/compose/runtime/ComposerKt.sourceInformation:(Landroidx/compose/runtime/Composer;Ljava/lang/String;)V
-       949: aload         39
-       951: aload         34
-       953: bipush        6
-       955: invokestatic  #239                // Method androidx/compose/foundation/layout/SpacerKt.Spacer:(Landroidx/compose/ui/Modifier;Landroidx/compose/runtime/Composer;I)V
-       958: aload         34
-       960: invokeinterface #401,  1          // InterfaceMethod androidx/compose/runtime/Composer.endReplaceGroup:()V
-       965: getstatic     #682                // Field androidx/compose/material3/MaterialTheme.INSTANCE:Landroidx/compose/material3/MaterialTheme;
-       968: aload         34
-       970: getstatic     #683                // Field androidx/compose/material3/MaterialTheme.$stable:I
-       973: invokevirtual #687                // Method androidx/compose/material3/MaterialTheme.getTypography:(Landroidx/compose/runtime/Composer;I)Landroidx/compose/material3/Typography;
-       976: invokevirtual #819                // Method androidx/compose/material3/Typography.getBodyMedium:()Landroidx/compose/ui/text/TextStyle;
-       979: astore        37
-       981: getstatic     #682                // Field androidx/compose/material3/MaterialTheme.INSTANCE:Landroidx/compose/material3/MaterialTheme;
-       984: aload         34
-       986: getstatic     #683                // Field androidx/compose/material3/MaterialTheme.$stable:I
-       989: invokevirtual #697                // Method androidx/compose/material3/MaterialTheme.getColorScheme:(Landroidx/compose/runtime/Composer;I)Landroidx/compose/material3/ColorScheme;
-       992: invokevirtual #828                // Method androidx/compose/material3/ColorScheme."getOnSurface-0d7_KjU":()J
-       995: lstore        41
-       997: getstatic     #74                 // Field androidx/compose/ui/Modifier.Companion:Landroidx/compose/ui/Modifier$Companion;
-      1000: checkcast     #70                 // class androidx/compose/ui/Modifier
-      1003: bipush        12
-      1005: istore        43
-      1007: iconst_0
-      1008: istore        44
-      1010: iload         43
-      1012: i2f
-      1013: invokestatic  #318                // Method androidx/compose/ui/unit/Dp."constructor-impl":(F)F
-      1016: fconst_0
-      1017: fconst_0
-      1018: fconst_0
-      1019: bipush        14
-      1021: aconst_null
-      1022: invokestatic  #591                // Method androidx/compose/foundation/layout/PaddingKt."padding-qDBjuR0$default":(Landroidx/compose/ui/Modifier;FFFFILjava/lang/Object;)Landroidx/compose/ui/Modifier;
-      1025: astore        45
-      1027: aload_0
-      1028: aload         45
-      1030: lload         41
-      1032: aconst_null
-      1033: lconst_0
-      1034: aconst_null
-      1035: aconst_null
-      1036: aconst_null
-      1037: lconst_0
-      1038: aconst_null
-      1039: aconst_null
-      1040: lconst_0
-      1041: iconst_0
-      1042: iconst_0
-      1043: iconst_0
-      1044: iconst_0
-      1045: aconst_null
-      1046: aload         37
-      1048: aload         34
-      1050: bipush        48
-      1052: bipush        14
-      1054: iload         7
-      1056: iand
-      1057: ior
-      1058: iconst_0
-      1059: ldc_w         #829                // int 131064
-      1062: invokestatic  #710                // Method androidx/compose/material3/TextKt."Text-Nvy7gAk":(Ljava/lang/String;Landroidx/compose/ui/Modifier;JLandroidx/compose/foundation/text/TextAutoSize;JLandroidx/compose/ui/text/font/FontStyle;Landroidx/compose/ui/text/font/FontWeight;Landroidx/compose/ui/text/font/FontFamily;JLandroidx/compose/ui/text/style/TextDecoration;Landroidx/compose/ui/text/style/TextAlign;JIZIILkotlin/jvm/functions/Function1;Landroidx/compose/ui/text/TextStyle;Landroidx/compose/runtime/Composer;III)V
-      1065: aload         34
-      1067: invokestatic  #301                // Method androidx/compose/runtime/ComposerKt.sourceInformationMarkerEnd:(Landroidx/compose/runtime/Composer;)V
-      1070: nop
-      1071: aload         31
-      1073: invokestatic  #301                // Method androidx/compose/runtime/ComposerKt.sourceInformationMarkerEnd:(Landroidx/compose/runtime/Composer;)V
-      1076: aload         25
-      1078: invokeinterface #405,  1          // InterfaceMethod androidx/compose/runtime/Composer.endNode:()V
-      1083: aload         25
-      1085: invokestatic  #301                // Method androidx/compose/runtime/ComposerKt.sourceInformationMarkerEnd:(Landroidx/compose/runtime/Composer;)V
-      1088: nop
-      1089: aload         18
-      1091: invokestatic  #301                // Method androidx/compose/runtime/ComposerKt.sourceInformationMarkerEnd:(Landroidx/compose/runtime/Composer;)V
-      1094: nop
-      1095: aload         12
-      1097: invokestatic  #301                // Method androidx/compose/runtime/ComposerKt.sourceInformationMarkerEnd:(Landroidx/compose/runtime/Composer;)V
-      1100: nop
-      1101: invokestatic  #55                 // Method androidx/compose/runtime/ComposerKt.isTraceInProgress:()Z
-      1104: ifeq          1120
-      1107: invokestatic  #408                // Method androidx/compose/runtime/ComposerKt.traceEventEnd:()V
-      1110: goto          1120
-      1113: aload         4
-      1115: invokeinterface #411,  1          // InterfaceMethod androidx/compose/runtime/Composer.skipToGroupEnd:()V
-      1120: aload         4
-      1122: invokeinterface #415,  1          // InterfaceMethod androidx/compose/runtime/Composer.endRestartGroup:()Landroidx/compose/runtime/ScopeUpdateScope;
-      1127: dup
-      1128: ifnull        1152
-      1131: aload_0
-      1132: aload_1
-      1133: iload_2
-      1134: aload_3
-      1135: iload         5
-      1137: iload         6
-      1139: invokedynamic #904,  0            // InvokeDynamic #8:invoke:(Ljava/lang/String;Ljava/lang/Integer;ZLkotlin/jvm/functions/Function0;II)Lkotlin/jvm/functions/Function2;
-      1144: invokeinterface #433,  2          // InterfaceMethod androidx/compose/runtime/ScopeUpdateScope.updateScope:(Lkotlin/jvm/functions/Function2;)V
-      1149: goto          1153
-      1152: pop
-      1153: return
-
-  public static final void DividerItem(androidx.compose.ui.Modifier, androidx.compose.runtime.Composer, int, int);
-    Code:
-         0: aload_1
-         1: ldc_w         #922                // int -316014757
-         4: invokeinterface #30,  2           // InterfaceMethod androidx/compose/runtime/Composer.startRestartGroup:(I)Landroidx/compose/runtime/Composer;
-         9: astore_1
-        10: aload_1
-        11: ldc_w         #924                // String C(DividerItem)N(modifier)215@7675L11,213@7597L126:JetchatDrawer.kt#o9oqao
-        14: invokestatic  #38                 // Method androidx/compose/runtime/ComposerKt.sourceInformation:(Landroidx/compose/runtime/Composer;Ljava/lang/String;)V
-        17: iload_2
-        18: istore        4
-        20: iload_3
-        21: iconst_1
-        22: iand
-        23: ifeq          36
-        26: iload         4
-        28: bipush        6
-        30: ior
-        31: istore        4
-        33: goto          63
-        36: iload_2
-        37: bipush        6
-        39: iand
-        40: ifne          63
-        43: iload         4
-        45: aload_1
-        46: aload_0
-        47: invokeinterface #45,  2           // InterfaceMethod androidx/compose/runtime/Composer.changed:(Ljava/lang/Object;)Z
-        52: ifeq          59
-        55: iconst_4
-        56: goto          60
-        59: iconst_2
-        60: ior
-        61: istore        4
-        63: aload_1
-        64: iload         4
-        66: iconst_3
-        67: iand
-        68: iconst_2
-        69: if_icmpeq     76
-        72: iconst_1
-        73: goto          77
-        76: iconst_0
-        77: iload         4
-        79: iconst_1
-        80: iand
-        81: invokeinterface #49,  3           // InterfaceMethod androidx/compose/runtime/Composer.shouldExecute:(ZI)Z
-        86: ifeq          169
-        89: iload_3
-        90: iconst_1
-        91: iand
-        92: ifeq          102
-        95: getstatic     #74                 // Field androidx/compose/ui/Modifier.Companion:Landroidx/compose/ui/Modifier$Companion;
-        98: checkcast     #70                 // class androidx/compose/ui/Modifier
-       101: astore_0
-       102: invokestatic  #55                 // Method androidx/compose/runtime/ComposerKt.isTraceInProgress:()Z
-       105: ifeq          120
-       108: ldc_w         #922                // int -316014757
-       111: iload         4
-       113: iconst_m1
-       114: ldc_w         #926                // String com.example.compose.jetchat.components.DividerItem (JetchatDrawer.kt:212)
-       117: invokestatic  #61                 // Method androidx/compose/runtime/ComposerKt.traceEventStart:(IIILjava/lang/String;)V
-       120: aload_0
-       121: fconst_0
-       122: getstatic     #682                // Field androidx/compose/material3/MaterialTheme.INSTANCE:Landroidx/compose/material3/MaterialTheme;
-       125: aload_1
-       126: getstatic     #683                // Field androidx/compose/material3/MaterialTheme.$stable:I
-       129: invokevirtual #697                // Method androidx/compose/material3/MaterialTheme.getColorScheme:(Landroidx/compose/runtime/Composer;I)Landroidx/compose/material3/ColorScheme;
-       132: invokevirtual #828                // Method androidx/compose/material3/ColorScheme."getOnSurface-0d7_KjU":()J
-       135: ldc_w         #927                // float 0.12f
-       138: fconst_0
-       139: fconst_0
-       140: fconst_0
-       141: bipush        14
-       143: aconst_null
-       144: invokestatic  #933                // Method androidx/compose/ui/graphics/Color."copy-wmQWz5c$default":(JFFFFILjava/lang/Object;)J
-       147: aload_1
-       148: bipush        14
-       150: iload         4
-       152: iand
-       153: iconst_2
-       154: invokestatic  #939                // Method androidx/compose/material3/DividerKt."HorizontalDivider-9IZ8Weo":(Landroidx/compose/ui/Modifier;FJLandroidx/compose/runtime/Composer;II)V
-       157: invokestatic  #55                 // Method androidx/compose/runtime/ComposerKt.isTraceInProgress:()Z
-       160: ifeq          175
-       163: invokestatic  #408                // Method androidx/compose/runtime/ComposerKt.traceEventEnd:()V
-       166: goto          175
-       169: aload_1
-       170: invokeinterface #411,  1          // InterfaceMethod androidx/compose/runtime/Composer.skipToGroupEnd:()V
-       175: aload_1
-       176: invokeinterface #415,  1          // InterfaceMethod androidx/compose/runtime/Composer.endRestartGroup:()Landroidx/compose/runtime/ScopeUpdateScope;
-       181: dup
-       182: ifnull        201
-       185: aload_0
-       186: iload_2
-       187: iload_3
-       188: invokedynamic #947,  0            // InvokeDynamic #9:invoke:(Landroidx/compose/ui/Modifier;II)Lkotlin/jvm/functions/Function2;
-       193: invokeinterface #433,  2          // InterfaceMethod androidx/compose/runtime/ScopeUpdateScope.updateScope:(Lkotlin/jvm/functions/Function2;)V
-       198: goto          202
-       201: pop
-       202: return
-
-  public static final void DrawerPreview(androidx.compose.runtime.Composer, int);
-    Code:
-         0: aload_0
-         1: ldc_w         #951                // int 65918457
-         4: invokeinterface #30,  2           // InterfaceMethod androidx/compose/runtime/Composer.startRestartGroup:(I)Landroidx/compose/runtime/Composer;
-         9: astore_0
-        10: aload_0
-        11: ldc_w         #953                // String C(DrawerPreview)222@7774L128:JetchatDrawer.kt#o9oqao
-        14: invokestatic  #38                 // Method androidx/compose/runtime/ComposerKt.sourceInformation:(Landroidx/compose/runtime/Composer;Ljava/lang/String;)V
-        17: aload_0
-        18: iload_1
-        19: ifeq          26
-        22: iconst_1
-        23: goto          27
-        26: iconst_0
-        27: iload_1
-        28: iconst_1
-        29: iand
-        30: invokeinterface #49,  3           // InterfaceMethod androidx/compose/runtime/Composer.shouldExecute:(ZI)Z
-        35: ifeq          83
-        38: invokestatic  #55                 // Method androidx/compose/runtime/ComposerKt.isTraceInProgress:()Z
-        41: ifeq          55
-        44: ldc_w         #951                // int 65918457
-        47: iload_1
-        48: iconst_m1
-        49: ldc_w         #955                // String com.example.compose.jetchat.components.DrawerPreview (JetchatDrawer.kt:221)
-        52: invokestatic  #61                 // Method androidx/compose/runtime/ComposerKt.traceEventStart:(IIILjava/lang/String;)V
-        55: iconst_0
-        56: iconst_0
-        57: getstatic     #960                // Field com/example/compose/jetchat/components/ComposableSingletons$JetchatDrawerKt.INSTANCE:Lcom/example/compose/jetchat/components/ComposableSingletons$JetchatDrawerKt;
-        60: invokevirtual #963                // Method com/example/compose/jetchat/components/ComposableSingletons$JetchatDrawerKt."getLambda$-210185230$app":()Lkotlin/jvm/functions/Function2;
-        63: aload_0
-        64: sipush        384
-        67: iconst_3
-        68: invokestatic  #969                // Method com/example/compose/jetchat/theme/ThemesKt.JetchatTheme:(ZZLkotlin/jvm/functions/Function2;Landroidx/compose/runtime/Composer;II)V
-        71: invokestatic  #55                 // Method androidx/compose/runtime/ComposerKt.isTraceInProgress:()Z
-        74: ifeq          89
-        77: invokestatic  #408                // Method androidx/compose/runtime/ComposerKt.traceEventEnd:()V
-        80: goto          89
-        83: aload_0
-        84: invokeinterface #411,  1          // InterfaceMethod androidx/compose/runtime/Composer.skipToGroupEnd:()V
-        89: aload_0
-        90: invokeinterface #415,  1          // InterfaceMethod androidx/compose/runtime/Composer.endRestartGroup:()Landroidx/compose/runtime/ScopeUpdateScope;
-        95: dup
-        96: ifnull        113
-        99: iload_1
-       100: invokedynamic #974,  0            // InvokeDynamic #10:invoke:(I)Lkotlin/jvm/functions/Function2;
-       105: invokeinterface #433,  2          // InterfaceMethod androidx/compose/runtime/ScopeUpdateScope.updateScope:(Lkotlin/jvm/functions/Function2;)V
-       110: goto          114
-       113: pop
-       114: return
-
-  public static final void DrawerPreviewDark(androidx.compose.runtime.Composer, int);
-    Code:
-         0: aload_0
-         1: ldc_w         #976                // int -1924392413
-         4: invokeinterface #30,  2           // InterfaceMethod androidx/compose/runtime/Composer.startRestartGroup:(I)Landroidx/compose/runtime/Composer;
-         9: astore_0
-        10: aload_0
-        11: ldc_w         #978                // String C(DrawerPreviewDark)234@7957L148:JetchatDrawer.kt#o9oqao
-        14: invokestatic  #38                 // Method androidx/compose/runtime/ComposerKt.sourceInformation:(Landroidx/compose/runtime/Composer;Ljava/lang/String;)V
-        17: aload_0
-        18: iload_1
-        19: ifeq          26
-        22: iconst_1
-        23: goto          27
-        26: iconst_0
-        27: iload_1
-        28: iconst_1
-        29: iand
-        30: invokeinterface #49,  3           // InterfaceMethod androidx/compose/runtime/Composer.shouldExecute:(ZI)Z
-        35: ifeq          83
-        38: invokestatic  #55                 // Method androidx/compose/runtime/ComposerKt.isTraceInProgress:()Z
-        41: ifeq          55
-        44: ldc_w         #976                // int -1924392413
-        47: iload_1
-        48: iconst_m1
-        49: ldc_w         #980                // String com.example.compose.jetchat.components.DrawerPreviewDark (JetchatDrawer.kt:233)
-        52: invokestatic  #61                 // Method androidx/compose/runtime/ComposerKt.traceEventStart:(IIILjava/lang/String;)V
-        55: iconst_1
-        56: iconst_0
-        57: getstatic     #960                // Field com/example/compose/jetchat/components/ComposableSingletons$JetchatDrawerKt.INSTANCE:Lcom/example/compose/jetchat/components/ComposableSingletons$JetchatDrawerKt;
-        60: invokevirtual #983                // Method com/example/compose/jetchat/components/ComposableSingletons$JetchatDrawerKt."getLambda$-1564118116$app":()Lkotlin/jvm/functions/Function2;
-        63: aload_0
-        64: sipush        390
-        67: iconst_2
-        68: invokestatic  #969                // Method com/example/compose/jetchat/theme/ThemesKt.JetchatTheme:(ZZLkotlin/jvm/functions/Function2;Landroidx/compose/runtime/Composer;II)V
-        71: invokestatic  #55                 // Method androidx/compose/runtime/ComposerKt.isTraceInProgress:()Z
-        74: ifeq          89
-        77: invokestatic  #408                // Method androidx/compose/runtime/ComposerKt.traceEventEnd:()V
-        80: goto          89
-        83: aload_0
-        84: invokeinterface #411,  1          // InterfaceMethod androidx/compose/runtime/Composer.skipToGroupEnd:()V
-        89: aload_0
-        90: invokeinterface #415,  1          // InterfaceMethod androidx/compose/runtime/Composer.endRestartGroup:()Landroidx/compose/runtime/ScopeUpdateScope;
-        95: dup
-        96: ifnull        113
-        99: iload_1
-       100: invokedynamic #988,  0            // InvokeDynamic #11:invoke:(I)Lkotlin/jvm/functions/Function2;
-       105: invokeinterface #433,  2          // InterfaceMethod androidx/compose/runtime/ScopeUpdateScope.updateScope:(Lkotlin/jvm/functions/Function2;)V
-       110: goto          114
-       113: pop
-       114: return
-
-  private static final void WidgetDiscoverability(androidx.compose.runtime.Composer, int);
-    Code:
-         0: aload_0
-         1: ldc_w         #992                // int 1579815059
-         4: invokeinterface #30,  2           // InterfaceMethod androidx/compose/runtime/Composer.startRestartGroup:(I)Landroidx/compose/runtime/Composer;
-         9: astore_0
-        10: aload_0
-        11: ldc_w         #994                // String C(WidgetDiscoverability)246@8226L7,253@8431L62,247@8238L578:JetchatDrawer.kt#o9oqao
-        14: invokestatic  #38                 // Method androidx/compose/runtime/ComposerKt.sourceInformation:(Landroidx/compose/runtime/Composer;Ljava/lang/String;)V
-        17: aload_0
-        18: iload_1
-        19: ifeq          26
-        22: iconst_1
-        23: goto          27
-        26: iconst_0
-        27: iload_1
-        28: iconst_1
-        29: iand
-        30: invokeinterface #49,  3           // InterfaceMethod androidx/compose/runtime/Composer.shouldExecute:(ZI)Z
-        35: ifeq          798
-        38: invokestatic  #55                 // Method androidx/compose/runtime/ComposerKt.isTraceInProgress:()Z
-        41: ifeq          55
-        44: ldc_w         #992                // int 1579815059
-        47: iload_1
-        48: iconst_m1
-        49: ldc_w         #996                // String com.example.compose.jetchat.components.WidgetDiscoverability (JetchatDrawer.kt:245)
-        52: invokestatic  #61                 // Method androidx/compose/runtime/ComposerKt.traceEventStart:(IIILjava/lang/String;)V
-        55: invokestatic  #371                // Method androidx/compose/ui/platform/AndroidCompositionLocals_androidKt.getLocalContext:()Landroidx/compose/runtime/ProvidableCompositionLocal;
-        58: checkcast     #373                // class androidx/compose/runtime/CompositionLocal
-        61: astore_3
-        62: aload_0
-        63: astore        4
-        65: iconst_0
-        66: istore        5
-        68: iconst_0
-        69: istore        6
-        71: aload         4
-        73: ldc_w         #374                // int 2023513938
-        76: ldc_w         #376                // String CC(<get-current>):CompositionLocal.kt#9igjgp
-        79: invokestatic  #68                 // Method androidx/compose/runtime/ComposerKt.sourceInformationMarkerStart:(Landroidx/compose/runtime/Composer;ILjava/lang/String;)V
-        82: aload         4
-        84: aload_3
-        85: invokeinterface #380,  2          // InterfaceMethod androidx/compose/runtime/Composer.consume:(Landroidx/compose/runtime/CompositionLocal;)Ljava/lang/Object;
-        90: astore        7
-        92: aload         4
-        94: invokestatic  #301                // Method androidx/compose/runtime/ComposerKt.sourceInformationMarkerEnd:(Landroidx/compose/runtime/Composer;)V
-        97: aload         7
-        99: checkcast     #382                // class android/content/Context
-       102: astore_2
-       103: getstatic     #74                 // Field androidx/compose/ui/Modifier.Companion:Landroidx/compose/ui/Modifier$Companion;
-       106: checkcast     #70                 // class androidx/compose/ui/Modifier
-       109: bipush        56
-       111: istore_3
-       112: iconst_0
-       113: istore        4
-       115: iload_3
-       116: i2f
-       117: invokestatic  #318                // Method androidx/compose/ui/unit/Dp."constructor-impl":(F)F
-       120: invokestatic  #767                // Method androidx/compose/foundation/layout/SizeKt."height-3ABfNKs":(Landroidx/compose/ui/Modifier;F)Landroidx/compose/ui/Modifier;
-       123: fconst_0
-       124: iconst_1
-       125: aconst_null
-       126: invokestatic  #771                // Method androidx/compose/foundation/layout/SizeKt.fillMaxWidth$default:(Landroidx/compose/ui/Modifier;FILjava/lang/Object;)Landroidx/compose/ui/Modifier;
-       129: bipush        12
-       131: istore_3
-       132: iconst_0
-       133: istore        4
-       135: iload_3
-       136: i2f
-       137: invokestatic  #318                // Method androidx/compose/ui/unit/Dp."constructor-impl":(F)F
-       140: fconst_0
-       141: iconst_2
-       142: aconst_null
-       143: invokestatic  #324                // Method androidx/compose/foundation/layout/PaddingKt."padding-VpY3zN4$default":(Landroidx/compose/ui/Modifier;FFILjava/lang/Object;)Landroidx/compose/ui/Modifier;
-       146: invokestatic  #777                // Method androidx/compose/foundation/shape/RoundedCornerShapeKt.getCircleShape:()Landroidx/compose/foundation/shape/RoundedCornerShape;
-       149: checkcast     #779                // class androidx/compose/ui/graphics/Shape
-       152: invokestatic  #785                // Method androidx/compose/ui/draw/ClipKt.clip:(Landroidx/compose/ui/Modifier;Landroidx/compose/ui/graphics/Shape;)Landroidx/compose/ui/Modifier;
-       155: iconst_0
-       156: aconst_null
-       157: aconst_null
-       158: aconst_null
-       159: aload_0
-       160: ldc_w         #997                // int 2078824785
-       163: ldc_w         #260                // String CC(remember):JetchatDrawer.kt#9igjgp
-       166: invokestatic  #68                 // Method androidx/compose/runtime/ComposerKt.sourceInformationMarkerStart:(Landroidx/compose/runtime/Composer;ILjava/lang/String;)V
-       169: aload_0
-       170: astore        4
-       172: aload_0
-       173: aload_2
-       174: invokeinterface #42,  2           // InterfaceMethod androidx/compose/runtime/Composer.changedInstance:(Ljava/lang/Object;)Z
-       179: istore        5
-       181: iconst_0
-       182: istore        6
-       184: aload         4
-       186: invokeinterface #264,  1          // InterfaceMethod androidx/compose/runtime/Composer.rememberedValue:()Ljava/lang/Object;
-       191: astore        7
-       193: iconst_0
-       194: istore        8
-       196: iload         5
-       198: ifne          212
-       201: aload         7
-       203: getstatic     #267                // Field androidx/compose/runtime/Composer.Companion:Landroidx/compose/runtime/Composer$Companion;
-       206: invokevirtual #272                // Method androidx/compose/runtime/Composer$Companion.getEmpty:()Ljava/lang/Object;
-       209: if_acmpne     261
-       212: astore        42
-       214: astore        41
-       216: astore        40
-       218: istore        39
-       220: astore        38
-       222: iconst_0
-       223: istore        9
-       225: aload_2
-       226: invokedynamic #1005,  0           // InvokeDynamic #12:invoke:(Landroid/content/Context;)Lkotlin/jvm/functions/Function0;
-       231: astore        43
-       233: aload         38
-       235: iload         39
-       237: aload         40
-       239: aload         41
-       241: aload         42
-       243: aload         43
-       245: astore        10
-       247: aload         4
-       249: aload         10
-       251: invokeinterface #295,  2          // InterfaceMethod androidx/compose/runtime/Composer.updateRememberedValue:(Ljava/lang/Object;)V
-       256: aload         10
-       258: goto          263
-       261: aload         7
-       263: nop
-       264: nop
-       265: checkcast     #297                // class kotlin/jvm/functions/Function0
-       268: astore_3
-       269: aload_0
-       270: invokestatic  #301                // Method androidx/compose/runtime/ComposerKt.sourceInformationMarkerEnd:(Landroidx/compose/runtime/Composer;)V
-       273: aload_3
-       274: bipush        15
-       276: aconst_null
-       277: invokestatic  #795                // Method androidx/compose/foundation/ClickableKt."clickable-oSLSa3U$default":(Landroidx/compose/ui/Modifier;ZLjava/lang/String;Landroidx/compose/ui/semantics/Role;Landroidx/compose/foundation/interaction/MutableInteractionSource;Lkotlin/jvm/functions/Function0;ILjava/lang/Object;)Landroidx/compose/ui/Modifier;
-       280: astore_3
-       281: getstatic     #89                 // Field androidx/compose/ui/Alignment.Companion:Landroidx/compose/ui/Alignment$Companion;
-       284: invokevirtual #540                // Method androidx/compose/ui/Alignment$Companion.getCenterVertically:()Landroidx/compose/ui/Alignment$Vertical;
-       287: astore        5
-       289: aload_0
-       290: astore        6
-       292: sipush        384
-       295: istore        7
-       297: nop
-       298: iconst_0
-       299: istore        8
-       301: aload         6
-       303: ldc_w         #541                // int 844473419
-       306: ldc_w         #543                // String CC(Row)N(modifier,horizontalArrangement,verticalAlignment,content)99@5125L58,100@5188L131:Row.kt#2w3rfo
-       309: invokestatic  #68                 // Method androidx/compose/runtime/ComposerKt.sourceInformationMarkerStart:(Landroidx/compose/runtime/Composer;ILjava/lang/String;)V
-       312: getstatic     #80                 // Field androidx/compose/foundation/layout/Arrangement.INSTANCE:Landroidx/compose/foundation/layout/Arrangement;
-       315: invokevirtual #546                // Method androidx/compose/foundation/layout/Arrangement.getStart:()Landroidx/compose/foundation/layout/Arrangement$Horizontal;
-       318: astore        4
-       320: aload         4
-       322: aload         5
-       324: aload         6
-       326: bipush        14
-       328: iload         7
-       330: iconst_3
-       331: ishr
-       332: iand
-       333: bipush        112
-       335: iload         7
-       337: iconst_3
-       338: ishr
-       339: iand
-       340: ior
-       341: invokestatic  #552                // Method androidx/compose/foundation/layout/RowKt.rowMeasurePolicy:(Landroidx/compose/foundation/layout/Arrangement$Horizontal;Landroidx/compose/ui/Alignment$Vertical;Landroidx/compose/runtime/Composer;I)Landroidx/compose/ui/layout/MeasurePolicy;
-       344: astore        9
-       346: aload_3
-       347: astore        10
-       349: aload         9
-       351: astore        11
-       353: aload         6
-       355: astore        12
-       357: bipush        112
-       359: iload         7
-       361: iconst_3
-       362: ishl
-       363: iand
-       364: istore        13
-       366: nop
-       367: iconst_0
-       368: istore        14
-       370: aload         12
-       372: ldc           #102                // int -1159599143
-       374: ldc           #104                // String CC(Layout)P(!1,2)81@3355L27,84@3521L416:Layout.kt#80mrfh
-       376: invokestatic  #68                 // Method androidx/compose/runtime/ComposerKt.sourceInformationMarkerStart:(Landroidx/compose/runtime/Composer;ILjava/lang/String;)V
-       379: aload         12
-       381: iconst_0
-       382: invokestatic  #110                // Method androidx/compose/runtime/ComposablesKt.getCurrentCompositeKeyHashCode:(Landroidx/compose/runtime/Composer;I)J
-       385: invokestatic  #116                // Method java/lang/Long.hashCode:(J)I
-       388: istore        15
-       390: aload         12
-       392: invokeinterface #120,  1          // InterfaceMethod androidx/compose/runtime/Composer.getCurrentCompositionLocalMap:()Landroidx/compose/runtime/CompositionLocalMap;
-       397: astore        16
-       399: aload         12
-       401: aload         10
-       403: invokestatic  #126                // Method androidx/compose/ui/ComposedModifierKt.materializeModifier:(Landroidx/compose/runtime/Composer;Landroidx/compose/ui/Modifier;)Landroidx/compose/ui/Modifier;
-       406: astore        17
-       408: getstatic     #131                // Field androidx/compose/ui/node/ComposeUiNode.Companion:Landroidx/compose/ui/node/ComposeUiNode$Companion;
-       411: invokevirtual #137                // Method androidx/compose/ui/node/ComposeUiNode$Companion.getConstructor:()Lkotlin/jvm/functions/Function0;
-       414: astore        18
-       416: aload         12
-       418: astore        19
-       420: bipush        6
-       422: sipush        896
-       425: iload         13
-       427: bipush        6
-       429: ishl
-       430: iand
-       431: ior
-       432: istore        20
-       434: nop
-       435: iconst_0
-       436: istore        21
-       438: aload         19
-       440: ldc           #138                // int -553112988
-       442: ldc           #140                // String CC(ReusableComposeNode)N(factory,update,content)399@15590L9:Composables.kt#9igjgp
-       444: invokestatic  #68                 // Method androidx/compose/runtime/ComposerKt.sourceInformationMarkerStart:(Landroidx/compose/runtime/Composer;ILjava/lang/String;)V
-       447: aload         19
-       449: invokeinterface #144,  1          // InterfaceMethod androidx/compose/runtime/Composer.getApplier:()Landroidx/compose/runtime/Applier;
-       454: instanceof    #146                // class androidx/compose/runtime/Applier
-       457: ifne          463
-       460: invokestatic  #150                // Method androidx/compose/runtime/ComposablesKt.invalidApplier:()V
-       463: aload         19
-       465: invokeinterface #153,  1          // InterfaceMethod androidx/compose/runtime/Composer.startReusableNode:()V
-       470: aload         19
-       472: invokeinterface #156,  1          // InterfaceMethod androidx/compose/runtime/Composer.getInserting:()Z
-       477: ifeq          492
-       480: aload         19
-       482: aload         18
-       484: invokeinterface #160,  2          // InterfaceMethod androidx/compose/runtime/Composer.createNode:(Lkotlin/jvm/functions/Function0;)V
-       489: goto          499
-       492: aload         19
-       494: invokeinterface #163,  1          // InterfaceMethod androidx/compose/runtime/Composer.useNode:()V
-       499: aload         19
-       501: invokestatic  #169                // Method androidx/compose/runtime/Updater."constructor-impl":(Landroidx/compose/runtime/Composer;)Landroidx/compose/runtime/Composer;
-       504: astore        22
-       506: iconst_0
-       507: istore        23
-       509: aload         22
-       511: aload         11
-       513: getstatic     #131                // Field androidx/compose/ui/node/ComposeUiNode.Companion:Landroidx/compose/ui/node/ComposeUiNode$Companion;
-       516: invokevirtual #173                // Method androidx/compose/ui/node/ComposeUiNode$Companion.getSetMeasurePolicy:()Lkotlin/jvm/functions/Function2;
-       519: invokestatic  #177                // Method androidx/compose/runtime/Updater."set-impl":(Landroidx/compose/runtime/Composer;Ljava/lang/Object;Lkotlin/jvm/functions/Function2;)V
-       522: aload         22
-       524: aload         16
-       526: getstatic     #131                // Field androidx/compose/ui/node/ComposeUiNode.Companion:Landroidx/compose/ui/node/ComposeUiNode$Companion;
-       529: invokevirtual #180                // Method androidx/compose/ui/node/ComposeUiNode$Companion.getSetResolvedCompositionLocals:()Lkotlin/jvm/functions/Function2;
-       532: invokestatic  #177                // Method androidx/compose/runtime/Updater."set-impl":(Landroidx/compose/runtime/Composer;Ljava/lang/Object;Lkotlin/jvm/functions/Function2;)V
-       535: aload         22
-       537: iload         15
-       539: invokestatic  #186                // Method java/lang/Integer.valueOf:(I)Ljava/lang/Integer;
-       542: getstatic     #131                // Field androidx/compose/ui/node/ComposeUiNode.Companion:Landroidx/compose/ui/node/ComposeUiNode$Companion;
-       545: invokevirtual #189                // Method androidx/compose/ui/node/ComposeUiNode$Companion.getSetCompositeKeyHash:()Lkotlin/jvm/functions/Function2;
-       548: invokestatic  #192                // Method androidx/compose/runtime/Updater."init-impl":(Landroidx/compose/runtime/Composer;Ljava/lang/Object;Lkotlin/jvm/functions/Function2;)V
-       551: aload         22
-       553: getstatic     #131                // Field androidx/compose/ui/node/ComposeUiNode.Companion:Landroidx/compose/ui/node/ComposeUiNode$Companion;
-       556: invokevirtual #196                // Method androidx/compose/ui/node/ComposeUiNode$Companion.getApplyOnDeactivatedNodeAssertion:()Lkotlin/jvm/functions/Function1;
-       559: invokestatic  #200                // Method androidx/compose/runtime/Updater."reconcile-impl":(Landroidx/compose/runtime/Composer;Lkotlin/jvm/functions/Function1;)V
-       562: aload         22
-       564: aload         17
-       566: getstatic     #131                // Field androidx/compose/ui/node/ComposeUiNode.Companion:Landroidx/compose/ui/node/ComposeUiNode$Companion;
-       569: invokevirtual #203                // Method androidx/compose/ui/node/ComposeUiNode$Companion.getSetModifier:()Lkotlin/jvm/functions/Function2;
-       572: invokestatic  #177                // Method androidx/compose/runtime/Updater."set-impl":(Landroidx/compose/runtime/Composer;Ljava/lang/Object;Lkotlin/jvm/functions/Function2;)V
-       575: nop
-       576: nop
-       577: aload         19
-       579: bipush        14
-       581: iload         20
-       583: bipush        6
-       585: ishr
-       586: iand
-       587: istore        24
-       589: astore        25
-       591: iconst_0
-       592: istore        26
-       594: aload         25
-       596: ldc_w         #553                // int 1456264949
-       599: ldc_w         #555                // String C101@5233L9:Row.kt#2w3rfo
-       602: invokestatic  #68                 // Method androidx/compose/runtime/ComposerKt.sourceInformationMarkerStart:(Landroidx/compose/runtime/Composer;ILjava/lang/String;)V
-       605: getstatic     #560                // Field androidx/compose/foundation/layout/RowScopeInstance.INSTANCE:Landroidx/compose/foundation/layout/RowScopeInstance;
-       608: aload         25
-       610: bipush        6
-       612: bipush        112
-       614: iload         7
-       616: bipush        6
-       618: ishr
-       619: iand
-       620: ior
-       621: istore        27
-       623: astore        28
-       625: checkcast     #562                // class androidx/compose/foundation/layout/RowScope
-       628: astore        29
-       630: iconst_0
-       631: istore        30
-       633: aload         28
-       635: ldc_w         #1006               // int -421207240
-       638: ldc_w         #1008               // String C259@8576L53,260@8665L10,261@8722L11,258@8558L252:JetchatDrawer.kt#o9oqao
-       641: invokestatic  #68                 // Method androidx/compose/runtime/ComposerKt.sourceInformationMarkerStart:(Landroidx/compose/runtime/Composer;ILjava/lang/String;)V
-       644: getstatic     #1013               // Field com/example/compose/jetchat/R$string.add_widget_to_home_page:I
-       647: aload         28
-       649: iconst_0
-       650: invokestatic  #1019               // Method androidx/compose/ui/res/StringResources_androidKt.stringResource:(ILandroidx/compose/runtime/Composer;I)Ljava/lang/String;
-       653: astore        31
-       655: getstatic     #682                // Field androidx/compose/material3/MaterialTheme.INSTANCE:Landroidx/compose/material3/MaterialTheme;
-       658: aload         28
-       660: getstatic     #683                // Field androidx/compose/material3/MaterialTheme.$stable:I
-       663: invokevirtual #687                // Method androidx/compose/material3/MaterialTheme.getTypography:(Landroidx/compose/runtime/Composer;I)Landroidx/compose/material3/Typography;
-       666: invokevirtual #819                // Method androidx/compose/material3/Typography.getBodyMedium:()Landroidx/compose/ui/text/TextStyle;
-       669: astore        32
-       671: getstatic     #682                // Field androidx/compose/material3/MaterialTheme.INSTANCE:Landroidx/compose/material3/MaterialTheme;
-       674: aload         28
-       676: getstatic     #683                // Field androidx/compose/material3/MaterialTheme.$stable:I
-       679: invokevirtual #697                // Method androidx/compose/material3/MaterialTheme.getColorScheme:(Landroidx/compose/runtime/Composer;I)Landroidx/compose/material3/ColorScheme;
-       682: invokevirtual #828                // Method androidx/compose/material3/ColorScheme."getOnSurface-0d7_KjU":()J
-       685: lstore        33
-       687: getstatic     #74                 // Field androidx/compose/ui/Modifier.Companion:Landroidx/compose/ui/Modifier$Companion;
-       690: checkcast     #70                 // class androidx/compose/ui/Modifier
-       693: bipush        12
-       695: istore        35
-       697: iconst_0
-       698: istore        36
-       700: iload         35
-       702: i2f
-       703: invokestatic  #318                // Method androidx/compose/ui/unit/Dp."constructor-impl":(F)F
-       706: fconst_0
-       707: fconst_0
-       708: fconst_0
-       709: bipush        14
-       711: aconst_null
-       712: invokestatic  #591                // Method androidx/compose/foundation/layout/PaddingKt."padding-qDBjuR0$default":(Landroidx/compose/ui/Modifier;FFFFILjava/lang/Object;)Landroidx/compose/ui/Modifier;
-       715: astore        37
-       717: aload         31
-       719: aload         37
-       721: lload         33
-       723: aconst_null
-       724: lconst_0
-       725: aconst_null
-       726: aconst_null
-       727: aconst_null
-       728: lconst_0
-       729: aconst_null
-       730: aconst_null
-       731: lconst_0
-       732: iconst_0
-       733: iconst_0
-       734: iconst_0
-       735: iconst_0
-       736: aconst_null
-       737: aload         32
-       739: aload         28
-       741: bipush        48
-       743: iconst_0
-       744: ldc_w         #829                // int 131064
-       747: invokestatic  #710                // Method androidx/compose/material3/TextKt."Text-Nvy7gAk":(Ljava/lang/String;Landroidx/compose/ui/Modifier;JLandroidx/compose/foundation/text/TextAutoSize;JLandroidx/compose/ui/text/font/FontStyle;Landroidx/compose/ui/text/font/FontWeight;Landroidx/compose/ui/text/font/FontFamily;JLandroidx/compose/ui/text/style/TextDecoration;Landroidx/compose/ui/text/style/TextAlign;JIZIILkotlin/jvm/functions/Function1;Landroidx/compose/ui/text/TextStyle;Landroidx/compose/runtime/Composer;III)V
-       750: aload         28
-       752: invokestatic  #301                // Method androidx/compose/runtime/ComposerKt.sourceInformationMarkerEnd:(Landroidx/compose/runtime/Composer;)V
-       755: nop
-       756: aload         25
-       758: invokestatic  #301                // Method androidx/compose/runtime/ComposerKt.sourceInformationMarkerEnd:(Landroidx/compose/runtime/Composer;)V
-       761: aload         19
-       763: invokeinterface #405,  1          // InterfaceMethod androidx/compose/runtime/Composer.endNode:()V
-       768: aload         19
-       770: invokestatic  #301                // Method androidx/compose/runtime/ComposerKt.sourceInformationMarkerEnd:(Landroidx/compose/runtime/Composer;)V
-       773: nop
-       774: aload         12
-       776: invokestatic  #301                // Method androidx/compose/runtime/ComposerKt.sourceInformationMarkerEnd:(Landroidx/compose/runtime/Composer;)V
-       779: nop
-       780: aload         6
-       782: invokestatic  #301                // Method androidx/compose/runtime/ComposerKt.sourceInformationMarkerEnd:(Landroidx/compose/runtime/Composer;)V
-       785: nop
-       786: invokestatic  #55                 // Method androidx/compose/runtime/ComposerKt.isTraceInProgress:()Z
-       789: ifeq          804
-       792: invokestatic  #408                // Method androidx/compose/runtime/ComposerKt.traceEventEnd:()V
-       795: goto          804
-       798: aload_0
-       799: invokeinterface #411,  1          // InterfaceMethod androidx/compose/runtime/Composer.skipToGroupEnd:()V
-       804: aload_0
-       805: invokeinterface #415,  1          // InterfaceMethod androidx/compose/runtime/Composer.endRestartGroup:()Landroidx/compose/runtime/ScopeUpdateScope;
-       810: dup
-       811: ifnull        828
-       814: iload_1
-       815: invokedynamic #1024,  0           // InvokeDynamic #13:invoke:(I)Lkotlin/jvm/functions/Function2;
-       820: invokeinterface #433,  2          // InterfaceMethod androidx/compose/runtime/ScopeUpdateScope.updateScope:(Lkotlin/jvm/functions/Function2;)V
-       825: goto          829
-       828: pop
-       829: return
-
-  private static final void addWidgetToHomeScreen(android.content.Context);
-    Code:
-         0: aload_0
-         1: invokestatic  #1071               // Method android/appwidget/AppWidgetManager.getInstance:(Landroid/content/Context;)Landroid/appwidget/AppWidgetManager;
-         4: astore_1
-         5: new           #1073               // class android/content/ComponentName
-         8: dup
-         9: aload_0
-        10: ldc_w         #1075               // class com/example/compose/jetchat/widget/WidgetReceiver
-        13: invokespecial #1079               // Method android/content/ComponentName."<init>":(Landroid/content/Context;Ljava/lang/Class;)V
-        16: astore_2
-        17: aload_0
-        18: invokestatic  #386                // Method widgetAddingIsSupported:(Landroid/content/Context;)Z
-        21: ifeq          32
-        24: aload_1
-        25: aload_2
-        26: aconst_null
-        27: aconst_null
-        28: invokevirtual #1083               // Method android/appwidget/AppWidgetManager.requestPinAppWidget:(Landroid/content/ComponentName;Landroid/os/Bundle;Landroid/app/PendingIntent;)Z
-        31: pop
-        32: return
-
-  private static final boolean widgetAddingIsSupported(android.content.Context);
-    Code:
-         0: getstatic     #1094               // Field android/os/Build$VERSION.SDK_INT:I
-         3: bipush        26
-         5: if_icmplt     22
-         8: aload_0
-         9: invokestatic  #1071               // Method android/appwidget/AppWidgetManager.getInstance:(Landroid/content/Context;)Landroid/appwidget/AppWidgetManager;
-        12: invokevirtual #1097               // Method android/appwidget/AppWidgetManager.isRequestPinAppWidgetSupported:()Z
-        15: ifeq          22
-        18: iconst_1
-        19: goto          23
-        22: iconst_0
-        23: ireturn
-
-  private static final kotlin.Unit JetchatDrawerContent$lambda$0$0$0(kotlin.jvm.functions.Function1);
-    Code:
-         0: aload_0
-         1: ldc           #51                 // String composers
-         3: invokeinterface #1100,  2         // InterfaceMethod kotlin/jvm/functions/Function1.invoke:(Ljava/lang/Object;)Ljava/lang/Object;
-         8: pop
-         9: getstatic     #1105               // Field kotlin/Unit.INSTANCE:Lkotlin/Unit;
-        12: areturn
-
-  private static final kotlin.Unit JetchatDrawerContent$lambda$0$1$0(kotlin.jvm.functions.Function1);
-    Code:
-         0: aload_0
-         1: ldc_w         #307                // String droidcon-nyc
-         4: invokeinterface #1100,  2         // InterfaceMethod kotlin/jvm/functions/Function1.invoke:(Ljava/lang/Object;)Ljava/lang/Object;
-         9: pop
-        10: getstatic     #1105               // Field kotlin/Unit.INSTANCE:Lkotlin/Unit;
-        13: areturn
-
-  private static final kotlin.Unit JetchatDrawerContent$lambda$0$2$0(kotlin.jvm.functions.Function1);
-    Code:
-         0: aload_0
-         1: invokestatic  #334                // Method com/example/compose/jetchat/data/FakeDataKt.getMeProfile:()Lcom/example/compose/jetchat/profile/ProfileScreenState;
-         4: invokevirtual #344                // Method com/example/compose/jetchat/profile/ProfileScreenState.getUserId:()Ljava/lang/String;
-         7: invokeinterface #1100,  2         // InterfaceMethod kotlin/jvm/functions/Function1.invoke:(Ljava/lang/Object;)Ljava/lang/Object;
-        12: pop
-        13: getstatic     #1105               // Field kotlin/Unit.INSTANCE:Lkotlin/Unit;
-        16: areturn
-
-  private static final kotlin.Unit JetchatDrawerContent$lambda$0$3$0(kotlin.jvm.functions.Function1);
-    Code:
-         0: aload_0
-         1: invokestatic  #359                // Method com/example/compose/jetchat/data/FakeDataKt.getColleagueProfile:()Lcom/example/compose/jetchat/profile/ProfileScreenState;
-         4: invokevirtual #344                // Method com/example/compose/jetchat/profile/ProfileScreenState.getUserId:()Ljava/lang/String;
-         7: invokeinterface #1100,  2         // InterfaceMethod kotlin/jvm/functions/Function1.invoke:(Ljava/lang/Object;)Ljava/lang/Object;
-        12: pop
-        13: getstatic     #1105               // Field kotlin/Unit.INSTANCE:Lkotlin/Unit;
-        16: areturn
-
-  private static final kotlin.Unit JetchatDrawerContent$lambda$1(kotlin.jvm.functions.Function1, kotlin.jvm.functions.Function1, java.lang.String, int, int, androidx.compose.runtime.Composer, int);
-    Code:
-         0: aload_0
-         1: aload_1
-         2: aload_2
-         3: aload         5
-         5: iload_3
-         6: iconst_1
-         7: ior
-         8: invokestatic  #1113               // Method androidx/compose/runtime/RecomposeScopeImplKt.updateChangedFlags:(I)I
-        11: iload         4
-        13: invokestatic  #1115               // Method JetchatDrawerContent:(Lkotlin/jvm/functions/Function1;Lkotlin/jvm/functions/Function1;Ljava/lang/String;Landroidx/compose/runtime/Composer;II)V
-        16: getstatic     #1105               // Field kotlin/Unit.INSTANCE:Lkotlin/Unit;
-        19: areturn
-
-  private static final kotlin.Unit DrawerHeader$lambda$1(int, androidx.compose.runtime.Composer, int);
-    Code:
-         0: aload_1
-         1: iload_0
-         2: iconst_1
-         3: ior
-         4: invokestatic  #1113               // Method androidx/compose/runtime/RecomposeScopeImplKt.updateChangedFlags:(I)I
-         7: invokestatic  #243                // Method DrawerHeader:(Landroidx/compose/runtime/Composer;I)V
-        10: getstatic     #1105               // Field kotlin/Unit.INSTANCE:Lkotlin/Unit;
-        13: areturn
-
-  private static final kotlin.Unit DrawerItemHeader$lambda$1(java.lang.String, int, androidx.compose.runtime.Composer, int);
-    Code:
-         0: aload_0
-         1: aload_2
-         2: iload_1
-         3: iconst_1
-         4: ior
-         5: invokestatic  #1113               // Method androidx/compose/runtime/RecomposeScopeImplKt.updateChangedFlags:(I)I
-         8: invokestatic  #253                // Method DrawerItemHeader:(Ljava/lang/String;Landroidx/compose/runtime/Composer;I)V
-        11: getstatic     #1105               // Field kotlin/Unit.INSTANCE:Lkotlin/Unit;
-        14: areturn
-
-  private static final kotlin.Unit ChatItem$lambda$1(java.lang.String, boolean, kotlin.jvm.functions.Function0, int, androidx.compose.runtime.Composer, int);
-    Code:
-         0: aload_0
-         1: iload_1
-         2: aload_2
-         3: aload         4
-         5: iload_3
-         6: iconst_1
-         7: ior
-         8: invokestatic  #1113               // Method androidx/compose/runtime/RecomposeScopeImplKt.updateChangedFlags:(I)I
-        11: invokestatic  #305                // Method ChatItem:(Ljava/lang/String;ZLkotlin/jvm/functions/Function0;Landroidx/compose/runtime/Composer;I)V
-        14: getstatic     #1105               // Field kotlin/Unit.INSTANCE:Lkotlin/Unit;
-        17: areturn
-
-  private static final kotlin.Unit ProfileItem$lambda$1(java.lang.String, java.lang.Integer, boolean, kotlin.jvm.functions.Function0, int, int, androidx.compose.runtime.Composer, int);
-    Code:
-         0: aload_0
-         1: aload_1
-         2: iload_2
-         3: aload_3
-         4: aload         6
-         6: iload         4
-         8: iconst_1
-         9: ior
-        10: invokestatic  #1113               // Method androidx/compose/runtime/RecomposeScopeImplKt.updateChangedFlags:(I)I
-        13: iload         5
-        15: invokestatic  #354                // Method ProfileItem:(Ljava/lang/String;Ljava/lang/Integer;ZLkotlin/jvm/functions/Function0;Landroidx/compose/runtime/Composer;II)V
-        18: getstatic     #1105               // Field kotlin/Unit.INSTANCE:Lkotlin/Unit;
-        21: areturn
-
-  private static final kotlin.Unit DividerItem$lambda$0(androidx.compose.ui.Modifier, int, int, androidx.compose.runtime.Composer, int);
-    Code:
-         0: aload_0
-         1: aload_3
-         2: iload_1
-         3: iconst_1
-         4: ior
-         5: invokestatic  #1113               // Method androidx/compose/runtime/RecomposeScopeImplKt.updateChangedFlags:(I)I
-         8: iload_2
-         9: invokestatic  #247                // Method DividerItem:(Landroidx/compose/ui/Modifier;Landroidx/compose/runtime/Composer;II)V
-        12: getstatic     #1105               // Field kotlin/Unit.INSTANCE:Lkotlin/Unit;
-        15: areturn
-
-  private static final kotlin.Unit DrawerPreview$lambda$0(int, androidx.compose.runtime.Composer, int);
-    Code:
-         0: aload_1
-         1: iload_0
-         2: iconst_1
-         3: ior
-         4: invokestatic  #1113               // Method androidx/compose/runtime/RecomposeScopeImplKt.updateChangedFlags:(I)I
-         7: invokestatic  #1125               // Method DrawerPreview:(Landroidx/compose/runtime/Composer;I)V
-        10: getstatic     #1105               // Field kotlin/Unit.INSTANCE:Lkotlin/Unit;
-        13: areturn
-
-  private static final kotlin.Unit DrawerPreviewDark$lambda$0(int, androidx.compose.runtime.Composer, int);
-    Code:
-         0: aload_1
-         1: iload_0
-         2: iconst_1
-         3: ior
-         4: invokestatic  #1113               // Method androidx/compose/runtime/RecomposeScopeImplKt.updateChangedFlags:(I)I
-         7: invokestatic  #1127               // Method DrawerPreviewDark:(Landroidx/compose/runtime/Composer;I)V
-        10: getstatic     #1105               // Field kotlin/Unit.INSTANCE:Lkotlin/Unit;
-        13: areturn
-
-  private static final kotlin.Unit WidgetDiscoverability$lambda$0$0(android.content.Context);
-    Code:
-         0: aload_0
-         1: invokestatic  #1129               // Method addWidgetToHomeScreen:(Landroid/content/Context;)V
-         4: getstatic     #1105               // Field kotlin/Unit.INSTANCE:Lkotlin/Unit;
-         7: areturn
-
-  private static final kotlin.Unit WidgetDiscoverability$lambda$2(int, androidx.compose.runtime.Composer, int);
-    Code:
-         0: aload_1
-         1: iload_0
-         2: iconst_1
-         3: ior
-         4: invokestatic  #1113               // Method androidx/compose/runtime/RecomposeScopeImplKt.updateChangedFlags:(I)I
-         7: invokestatic  #398                // Method WidgetDiscoverability:(Landroidx/compose/runtime/Composer;I)V
-        10: getstatic     #1105               // Field kotlin/Unit.INSTANCE:Lkotlin/Unit;
-        13: areturn
+Compiled from "com/example/compose/jetchat/components/JetchatDrawer.kt"
+public final class com.example.compose.jetchat.components.JetchatDrawerKt {
+  public static final <T> void JetchatDrawerContent(kotlin.jvm.functions.Function1, kotlin.jvm.functions.Function1, java.lang.String, androidx.compose.runtime.Composer, int);
+    Code:
+         0: aload_3
+         1: ldc           #33                 // int 541299724
+         3: invokeinterface #16,  2           // InterfaceMethod androidx/compose/runtime/Composer.startRestartGroup:(I)Landroidx/compose/runtime/Composer;
+         8: astore_3
+         9: aload_3
+        10: iload         4
+        12: ifeq          19
+        15: iconst_1
+        16: goto          20
+        19: iconst_0
+        20: iload         4
+        22: iconst_1
+        23: iand
+        24: invokeinterface #20,  3           // InterfaceMethod androidx/compose/runtime/Composer.shouldExecute:(ZI)Z
+        29: ifne          41
+        32: aload_3
+        33: invokeinterface #24,  1           // InterfaceMethod androidx/compose/runtime/Composer.skipToGroupEnd:()V
+        38: goto          69
+        41: new           #35                 // class com/example/compose/jetchat/components/JetchatDrawerKt$Lambda$23
+        44: dup
+        45: aload_2
+        46: aload_1
+        47: aload_0
+        48: invokespecial #39                 // Method com/example/compose/jetchat/components/JetchatDrawerKt$Lambda$23."<init>":(Ljava/lang/String;Lkotlin/jvm/functions/Function1;Lkotlin/jvm/functions/Function1;)V
+        51: astore        5
+        53: aconst_null
+        54: aconst_null
+        55: aconst_null
+        56: aload         5
+        58: checkcast     #41                 // class kotlin/jvm/functions/Function3
+        61: aload_3
+        62: iload         4
+        64: bipush        7
+        66: invokestatic  #47                 // Method androidx/compose/foundation/layout/ColumnKt.Column:(Landroidx/compose/ui/Modifier;Landroidx/compose/foundation/layout/Arrangement$Vertical;Landroidx/compose/ui/Alignment$Horizontal;Lkotlin/jvm/functions/Function3;Landroidx/compose/runtime/Composer;II)V
+        69: aload_3
+        70: invokeinterface #28,  1           // InterfaceMethod androidx/compose/runtime/Composer.endRestartGroup:()Landroidx/compose/runtime/ScopeUpdateScope;
+        75: dup
+        76: ifnull        97
+        79: aload_0
+        80: aload_1
+        81: aload_2
+        82: iload         4
+        84: invokedynamic #67,  0             // InvokeDynamic #0:invoke:(Lkotlin/jvm/functions/Function1;Lkotlin/jvm/functions/Function1;Ljava/lang/String;I)Lkotlin/jvm/functions/Function2;
+        89: invokeinterface #32,  2           // InterfaceMethod androidx/compose/runtime/ScopeUpdateScope.updateScope:(Lkotlin/jvm/functions/Function2;)V
+        94: goto          98
+        97: pop
+        98: return
+
+  private static final kotlin.Unit JetchatDrawerContent$lambda$0(kotlin.jvm.functions.Function1, kotlin.jvm.functions.Function1, java.lang.String, int, androidx.compose.runtime.Composer, int);
+    Code:
+         0: aload_0
+         1: aload_1
+         2: aload_2
+         3: aload         4
+         5: iload_3
+         6: iconst_1
+         7: ior
+         8: invokestatic  #82                 // Method androidx/compose/runtime/RecomposeScopeImplKt.updateChangedFlags:(I)I
+        11: invokestatic  #84                 // Method JetchatDrawerContent:(Lkotlin/jvm/functions/Function1;Lkotlin/jvm/functions/Function1;Ljava/lang/String;Landroidx/compose/runtime/Composer;I)V
+        14: getstatic     #90                 // Field kotlin/Unit.INSTANCE:Lkotlin/Unit;
+        17: areturn
+
+  public static void JetchatDrawerContent$default(kotlin.jvm.functions.Function1, kotlin.jvm.functions.Function1, java.lang.String, androidx.compose.runtime.Composer, int, int, java.lang.Object);
+    Code:
+         0: iload         5
+         2: iconst_4
+         3: iand
+         4: ifeq          10
+         7: ldc           #92                 // String composers
+         9: astore_2
+        10: aload_0
+        11: aload_1
+        12: aload_2
+        13: aload_3
+        14: iload         4
+        16: invokestatic  #84                 // Method JetchatDrawerContent:(Lkotlin/jvm/functions/Function1;Lkotlin/jvm/functions/Function1;Ljava/lang/String;Landroidx/compose/runtime/Composer;I)V
+        19: return
+
+  public static final void DrawerHeader(androidx.compose.runtime.Composer, int);
+    Code:
+         0: aload_0
+         1: ldc           #97                 // int -682583163
+         3: invokeinterface #16,  2           // InterfaceMethod androidx/compose/runtime/Composer.startRestartGroup:(I)Landroidx/compose/runtime/Composer;
+         8: astore_0
+         9: aload_0
+        10: iload_1
+        11: ifeq          18
+        14: iconst_1
+        15: goto          19
+        18: iconst_0
+        19: iload_1
+        20: iconst_1
+        21: iand
+        22: invokeinterface #20,  3           // InterfaceMethod androidx/compose/runtime/Composer.shouldExecute:(ZI)Z
+        27: ifne          39
+        30: aload_0
+        31: invokeinterface #24,  1           // InterfaceMethod androidx/compose/runtime/Composer.skipToGroupEnd:()V
+        36: goto          55
+        39: bipush        16
+        41: i2f
+        42: fstore_2
+        43: bipush        16
+        45: i2f
+        46: fstore_3
+        47: new           #99                 // class com/example/compose/jetchat/components/JetchatDrawerKt$Lambda$28
+        50: dup
+        51: invokespecial #101                // Method com/example/compose/jetchat/components/JetchatDrawerKt$Lambda$28."<init>":()V
+        54: pop
+        55: aload_0
+        56: invokeinterface #28,  1           // InterfaceMethod androidx/compose/runtime/Composer.endRestartGroup:()Landroidx/compose/runtime/ScopeUpdateScope;
+        61: dup
+        62: ifnull        79
+        65: iload_1
+        66: invokedynamic #109,  0            // InvokeDynamic #1:invoke:(I)Lkotlin/jvm/functions/Function2;
+        71: invokeinterface #32,  2           // InterfaceMethod androidx/compose/runtime/ScopeUpdateScope.updateScope:(Lkotlin/jvm/functions/Function2;)V
+        76: goto          80
+        79: pop
+        80: return
+
+  private static final kotlin.Unit DrawerHeader$lambda$0(int, androidx.compose.runtime.Composer, int);
+    Code:
+         0: aload_1
+         1: iload_0
+         2: iconst_1
+         3: ior
+         4: invokestatic  #82                 // Method androidx/compose/runtime/RecomposeScopeImplKt.updateChangedFlags:(I)I
+         7: invokestatic  #111                // Method DrawerHeader:(Landroidx/compose/runtime/Composer;I)V
+        10: getstatic     #90                 // Field kotlin/Unit.INSTANCE:Lkotlin/Unit;
+        13: areturn
+
+  public static final void DrawerItemHeader(java.lang.String, androidx.compose.runtime.Composer, int);
+    Code:
+         0: aload_1
+         1: ldc           #114                // int -1158215690
+         3: invokeinterface #16,  2           // InterfaceMethod androidx/compose/runtime/Composer.startRestartGroup:(I)Landroidx/compose/runtime/Composer;
+         8: astore_1
+         9: aload_1
+        10: iload_2
+        11: ifeq          18
+        14: iconst_1
+        15: goto          19
+        18: iconst_0
+        19: iload_2
+        20: iconst_1
+        21: iand
+        22: invokeinterface #20,  3           // InterfaceMethod androidx/compose/runtime/Composer.shouldExecute:(ZI)Z
+        27: ifne          39
+        30: aload_1
+        31: invokeinterface #24,  1           // InterfaceMethod androidx/compose/runtime/Composer.skipToGroupEnd:()V
+        36: goto          62
+        39: bipush        52
+        41: i2f
+        42: fstore_3
+        43: bipush        52
+        45: i2f
+        46: fstore        4
+        48: bipush        28
+        50: i2f
+        51: fstore        5
+        53: new           #116                // class com/example/compose/jetchat/components/JetchatDrawerKt$Lambda$29
+        56: dup
+        57: aload_0
+        58: invokespecial #119                // Method com/example/compose/jetchat/components/JetchatDrawerKt$Lambda$29."<init>":(Ljava/lang/String;)V
+        61: pop
+        62: aload_1
+        63: invokeinterface #28,  1           // InterfaceMethod androidx/compose/runtime/Composer.endRestartGroup:()Landroidx/compose/runtime/ScopeUpdateScope;
+        68: dup
+        69: ifnull        87
+        72: aload_0
+        73: iload_2
+        74: invokedynamic #127,  0            // InvokeDynamic #2:invoke:(Ljava/lang/String;I)Lkotlin/jvm/functions/Function2;
+        79: invokeinterface #32,  2           // InterfaceMethod androidx/compose/runtime/ScopeUpdateScope.updateScope:(Lkotlin/jvm/functions/Function2;)V
+        84: goto          88
+        87: pop
+        88: return
+
+  private static final kotlin.Unit DrawerItemHeader$lambda$0(java.lang.String, int, androidx.compose.runtime.Composer, int);
+    Code:
+         0: aload_0
+         1: aload_2
+         2: iload_1
+         3: iconst_1
+         4: ior
+         5: invokestatic  #82                 // Method androidx/compose/runtime/RecomposeScopeImplKt.updateChangedFlags:(I)I
+         8: invokestatic  #129                // Method DrawerItemHeader:(Ljava/lang/String;Landroidx/compose/runtime/Composer;I)V
+        11: getstatic     #90                 // Field kotlin/Unit.INSTANCE:Lkotlin/Unit;
+        14: areturn
+
+  private static final <T> void ChatItem(java.lang.String, boolean, kotlin.jvm.functions.Function0, androidx.compose.runtime.Composer, int);
+    Code:
+         0: aload_0
+         1: ldc           #133                // String text
+         3: invokestatic  #139                // Method kotlin/jvm/internal/Intrinsics.checkNotNullParameter:(Ljava/lang/Object;Ljava/lang/String;)V
+         6: aload_2
+         7: ldc           #141                // String onChatClicked
+         9: invokestatic  #139                // Method kotlin/jvm/internal/Intrinsics.checkNotNullParameter:(Ljava/lang/Object;Ljava/lang/String;)V
+        12: iload_1
+        13: ifeq          36
+        16: aconst_null
+        17: aload_3
+        18: iconst_0
+        19: invokevirtual #147                // Method androidx/compose/material3/MaterialTheme.getColorScheme:(Landroidx/compose/runtime/Composer;I)Landroidx/compose/material3/ColorScheme;
+        22: pop
+        23: aconst_null
+        24: aload_3
+        25: iconst_0
+        26: invokevirtual #147                // Method androidx/compose/material3/MaterialTheme.getColorScheme:(Landroidx/compose/runtime/Composer;I)Landroidx/compose/material3/ColorScheme;
+        29: pop
+        30: aconst_null
+        31: astore        5
+        33: goto          39
+        36: aconst_null
+        37: astore        5
+        39: bipush        56
+        41: i2f
+        42: fstore        6
+        44: bipush        56
+        46: i2f
+        47: fstore        7
+        49: bipush        12
+        51: i2f
+        52: fstore        8
+        54: new           #149                // class com/example/compose/jetchat/components/JetchatDrawerKt$Lambda$30
+        57: dup
+        58: iload_1
+        59: aload_0
+        60: invokespecial #152                // Method com/example/compose/jetchat/components/JetchatDrawerKt$Lambda$30."<init>":(ZLjava/lang/String;)V
+        63: pop
+        64: return
+
+  private static final kotlin.Unit ChatItem$lambda$0(java.lang.String, boolean, kotlin.jvm.functions.Function0, int, androidx.compose.runtime.Composer, int);
+    Code:
+         0: aload_0
+         1: iload_1
+         2: aload_2
+         3: aload         4
+         5: iload_3
+         6: iconst_1
+         7: ior
+         8: invokestatic  #82                 // Method androidx/compose/runtime/RecomposeScopeImplKt.updateChangedFlags:(I)I
+        11: invokestatic  #161                // Method ChatItem:(Ljava/lang/String;ZLkotlin/jvm/functions/Function0;Landroidx/compose/runtime/Composer;I)V
+        14: getstatic     #90                 // Field kotlin/Unit.INSTANCE:Lkotlin/Unit;
+        17: areturn
+
+  private static final <T> void ProfileItem(java.lang.String, java.lang.Integer, boolean, kotlin.jvm.functions.Function0, androidx.compose.runtime.Composer, int);
+    Code:
+         0: aload_0
+         1: ldc           #133                // String text
+         3: invokestatic  #139                // Method kotlin/jvm/internal/Intrinsics.checkNotNullParameter:(Ljava/lang/Object;Ljava/lang/String;)V
+         6: aload_3
+         7: ldc           #165                // String onProfileClicked
+         9: invokestatic  #139                // Method kotlin/jvm/internal/Intrinsics.checkNotNullParameter:(Ljava/lang/Object;Ljava/lang/String;)V
+        12: iload_2
+        13: ifeq          38
+        16: aconst_null
+        17: aload         4
+        19: iconst_0
+        20: invokevirtual #147                // Method androidx/compose/material3/MaterialTheme.getColorScheme:(Landroidx/compose/runtime/Composer;I)Landroidx/compose/material3/ColorScheme;
+        23: pop
+        24: aconst_null
+        25: aload         4
+        27: iconst_0
+        28: invokevirtual #147                // Method androidx/compose/material3/MaterialTheme.getColorScheme:(Landroidx/compose/runtime/Composer;I)Landroidx/compose/material3/ColorScheme;
+        31: pop
+        32: aconst_null
+        33: astore        6
+        35: goto          41
+        38: aconst_null
+        39: astore        6
+        41: bipush        56
+        43: i2f
+        44: fstore        7
+        46: bipush        56
+        48: i2f
+        49: fstore        8
+        51: bipush        12
+        53: i2f
+        54: fstore        9
+        56: new           #167                // class com/example/compose/jetchat/components/JetchatDrawerKt$Lambda$31
+        59: dup
+        60: aload_1
+        61: aload_0
+        62: invokespecial #170                // Method com/example/compose/jetchat/components/JetchatDrawerKt$Lambda$31."<init>":(Ljava/lang/Integer;Ljava/lang/String;)V
+        65: pop
+        66: return
+
+  private static final kotlin.Unit ProfileItem$lambda$0(java.lang.String, java.lang.Integer, boolean, kotlin.jvm.functions.Function0, int, androidx.compose.runtime.Composer, int);
+    Code:
+         0: aload_0
+         1: aload_1
+         2: iload_2
+         3: aload_3
+         4: aload         5
+         6: iload         4
+         8: iconst_1
+         9: ior
+        10: invokestatic  #82                 // Method androidx/compose/runtime/RecomposeScopeImplKt.updateChangedFlags:(I)I
+        13: invokestatic  #177                // Method ProfileItem:(Ljava/lang/String;Ljava/lang/Integer;ZLkotlin/jvm/functions/Function0;Landroidx/compose/runtime/Composer;I)V
+        16: getstatic     #90                 // Field kotlin/Unit.INSTANCE:Lkotlin/Unit;
+        19: areturn
+
+  public static void ProfileItem$default(java.lang.String, java.lang.Integer, boolean, kotlin.jvm.functions.Function0, androidx.compose.runtime.Composer, int, int, java.lang.Object);
+    Code:
+         0: iload         6
+         2: iconst_4
+         3: iand
+         4: ifeq          9
+         7: iconst_0
+         8: istore_2
+         9: aload_0
+        10: aload_1
+        11: iload_2
+        12: aload_3
+        13: aload         4
+        15: iload         5
+        17: invokestatic  #177                // Method ProfileItem:(Ljava/lang/String;Ljava/lang/Integer;ZLkotlin/jvm/functions/Function0;Landroidx/compose/runtime/Composer;I)V
+        20: return
+
+  public static final void DividerItem(androidx.compose.ui.Modifier, androidx.compose.runtime.Composer, int);
+    Code:
+         0: aload_1
+         1: ldc           #182                // int -1915250427
+         3: invokeinterface #16,  2           // InterfaceMethod androidx/compose/runtime/Composer.startRestartGroup:(I)Landroidx/compose/runtime/Composer;
+         8: astore_1
+         9: aload_1
+        10: iload_2
+        11: ifeq          18
+        14: iconst_1
+        15: goto          19
+        18: iconst_0
+        19: iload_2
+        20: iconst_1
+        21: iand
+        22: invokeinterface #20,  3           // InterfaceMethod androidx/compose/runtime/Composer.shouldExecute:(ZI)Z
+        27: ifne          39
+        30: aload_1
+        31: invokeinterface #24,  1           // InterfaceMethod androidx/compose/runtime/Composer.skipToGroupEnd:()V
+        36: goto          39
+        39: aload_1
+        40: invokeinterface #28,  1           // InterfaceMethod androidx/compose/runtime/Composer.endRestartGroup:()Landroidx/compose/runtime/ScopeUpdateScope;
+        45: dup
+        46: ifnull        64
+        49: aload_0
+        50: iload_2
+        51: invokedynamic #190,  0            // InvokeDynamic #3:invoke:(Landroidx/compose/ui/Modifier;I)Lkotlin/jvm/functions/Function2;
+        56: invokeinterface #32,  2           // InterfaceMethod androidx/compose/runtime/ScopeUpdateScope.updateScope:(Lkotlin/jvm/functions/Function2;)V
+        61: goto          65
+        64: pop
+        65: return
+
+  private static final kotlin.Unit DividerItem$lambda$0(androidx.compose.ui.Modifier, int, androidx.compose.runtime.Composer, int);
+    Code:
+         0: aload_0
+         1: aload_2
+         2: iload_1
+         3: iconst_1
+         4: ior
+         5: invokestatic  #82                 // Method androidx/compose/runtime/RecomposeScopeImplKt.updateChangedFlags:(I)I
+         8: invokestatic  #194                // Method DividerItem:(Landroidx/compose/ui/Modifier;Landroidx/compose/runtime/Composer;I)V
+        11: getstatic     #90                 // Field kotlin/Unit.INSTANCE:Lkotlin/Unit;
+        14: areturn
+
+  public static final void DrawerPreview(androidx.compose.runtime.Composer, int);
+    Code:
+         0: aload_0
+         1: ldc           #196                // int 1515470900
+         3: invokeinterface #16,  2           // InterfaceMethod androidx/compose/runtime/Composer.startRestartGroup:(I)Landroidx/compose/runtime/Composer;
+         8: astore_0
+         9: aload_0
+        10: iload_1
+        11: ifeq          18
+        14: iconst_1
+        15: goto          19
+        18: iconst_0
+        19: iload_1
+        20: iconst_1
+        21: iand
+        22: invokeinterface #20,  3           // InterfaceMethod androidx/compose/runtime/Composer.shouldExecute:(ZI)Z
+        27: ifne          39
+        30: aload_0
+        31: invokeinterface #24,  1           // InterfaceMethod androidx/compose/runtime/Composer.skipToGroupEnd:()V
+        36: goto          58
+        39: new           #198                // class com/example/compose/jetchat/components/JetchatDrawerKt$Lambda$32
+        42: dup
+        43: invokespecial #199                // Method com/example/compose/jetchat/components/JetchatDrawerKt$Lambda$32."<init>":()V
+        46: astore_2
+        47: iconst_0
+        48: iconst_0
+        49: aload_2
+        50: checkcast     #201                // class kotlin/jvm/functions/Function2
+        53: aload_0
+        54: iload_1
+        55: invokestatic  #207                // Method com/example/compose/jetchat/theme/ThemesKt.JetchatTheme:(ZZLkotlin/jvm/functions/Function2;Landroidx/compose/runtime/Composer;I)V
+        58: aload_0
+        59: invokeinterface #28,  1           // InterfaceMethod androidx/compose/runtime/Composer.endRestartGroup:()Landroidx/compose/runtime/ScopeUpdateScope;
+        64: dup
+        65: ifnull        82
+        68: iload_1
+        69: invokedynamic #212,  0            // InvokeDynamic #4:invoke:(I)Lkotlin/jvm/functions/Function2;
+        74: invokeinterface #32,  2           // InterfaceMethod androidx/compose/runtime/ScopeUpdateScope.updateScope:(Lkotlin/jvm/functions/Function2;)V
+        79: goto          83
+        82: pop
+        83: return
+
+  private static final kotlin.Unit DrawerPreview$lambda$0(int, androidx.compose.runtime.Composer, int);
+    Code:
+         0: aload_1
+         1: iload_0
+         2: iconst_1
+         3: ior
+         4: invokestatic  #82                 // Method androidx/compose/runtime/RecomposeScopeImplKt.updateChangedFlags:(I)I
+         7: invokestatic  #216                // Method DrawerPreview:(Landroidx/compose/runtime/Composer;I)V
+        10: getstatic     #90                 // Field kotlin/Unit.INSTANCE:Lkotlin/Unit;
+        13: areturn
+
+  public static final void DrawerPreviewDark(androidx.compose.runtime.Composer, int);
+    Code:
+         0: aload_0
+         1: ldc           #218                // int 1781972792
+         3: invokeinterface #16,  2           // InterfaceMethod androidx/compose/runtime/Composer.startRestartGroup:(I)Landroidx/compose/runtime/Composer;
+         8: astore_0
+         9: aload_0
+        10: iload_1
+        11: ifeq          18
+        14: iconst_1
+        15: goto          19
+        18: iconst_0
+        19: iload_1
+        20: iconst_1
+        21: iand
+        22: invokeinterface #20,  3           // InterfaceMethod androidx/compose/runtime/Composer.shouldExecute:(ZI)Z
+        27: ifne          39
+        30: aload_0
+        31: invokeinterface #24,  1           // InterfaceMethod androidx/compose/runtime/Composer.skipToGroupEnd:()V
+        36: goto          58
+        39: new           #220                // class com/example/compose/jetchat/components/JetchatDrawerKt$Lambda$37
+        42: dup
+        43: invokespecial #221                // Method com/example/compose/jetchat/components/JetchatDrawerKt$Lambda$37."<init>":()V
+        46: astore_2
+        47: iconst_1
+        48: iconst_0
+        49: aload_2
+        50: checkcast     #201                // class kotlin/jvm/functions/Function2
+        53: aload_0
+        54: iload_1
+        55: invokestatic  #207                // Method com/example/compose/jetchat/theme/ThemesKt.JetchatTheme:(ZZLkotlin/jvm/functions/Function2;Landroidx/compose/runtime/Composer;I)V
+        58: aload_0
+        59: invokeinterface #28,  1           // InterfaceMethod androidx/compose/runtime/Composer.endRestartGroup:()Landroidx/compose/runtime/ScopeUpdateScope;
+        64: dup
+        65: ifnull        82
+        68: iload_1
+        69: invokedynamic #226,  0            // InvokeDynamic #5:invoke:(I)Lkotlin/jvm/functions/Function2;
+        74: invokeinterface #32,  2           // InterfaceMethod androidx/compose/runtime/ScopeUpdateScope.updateScope:(Lkotlin/jvm/functions/Function2;)V
+        79: goto          83
+        82: pop
+        83: return
+
+  private static final kotlin.Unit DrawerPreviewDark$lambda$0(int, androidx.compose.runtime.Composer, int);
+    Code:
+         0: aload_1
+         1: iload_0
+         2: iconst_1
+         3: ior
+         4: invokestatic  #82                 // Method androidx/compose/runtime/RecomposeScopeImplKt.updateChangedFlags:(I)I
+         7: invokestatic  #228                // Method DrawerPreviewDark:(Landroidx/compose/runtime/Composer;I)V
+        10: getstatic     #90                 // Field kotlin/Unit.INSTANCE:Lkotlin/Unit;
+        13: areturn
+
+  public static final void WidgetDiscoverability(androidx.compose.runtime.Composer, int);
+    Code:
+         0: aload_0
+         1: ldc           #230                // int -1967475908
+         3: invokeinterface #16,  2           // InterfaceMethod androidx/compose/runtime/Composer.startRestartGroup:(I)Landroidx/compose/runtime/Composer;
+         8: astore_0
+         9: aload_0
+        10: iload_1
+        11: ifeq          18
+        14: iconst_1
+        15: goto          19
+        18: iconst_0
+        19: iload_1
+        20: iconst_1
+        21: iand
+        22: invokeinterface #20,  3           // InterfaceMethod androidx/compose/runtime/Composer.shouldExecute:(ZI)Z
+        27: ifne          39
+        30: aload_0
+        31: invokeinterface #24,  1           // InterfaceMethod androidx/compose/runtime/Composer.skipToGroupEnd:()V
+        36: goto          78
+        39: aconst_null
+        40: astore_2
+        41: aload_2
+        42: getfield      #236                // Field androidx/compose/ui/platform/LocalContext.current:Ljava/lang/Object;
+        45: astore_3
+        46: bipush        56
+        48: i2f
+        49: fstore        4
+        51: bipush        56
+        53: i2f
+        54: fstore        5
+        56: bipush        12
+        58: i2f
+        59: fstore        6
+        61: new           #238                // class com/example/compose/jetchat/components/JetchatDrawerKt$Lambda$42
+        64: dup
+        65: aload_3
+        66: invokespecial #241                // Method com/example/compose/jetchat/components/JetchatDrawerKt$Lambda$42."<init>":(Ljava/lang/Object;)V
+        69: pop
+        70: new           #243                // class com/example/compose/jetchat/components/JetchatDrawerKt$Lambda$43
+        73: dup
+        74: invokespecial #244                // Method com/example/compose/jetchat/components/JetchatDrawerKt$Lambda$43."<init>":()V
+        77: pop
+        78: aload_0
+        79: invokeinterface #28,  1           // InterfaceMethod androidx/compose/runtime/Composer.endRestartGroup:()Landroidx/compose/runtime/ScopeUpdateScope;
+        84: dup
+        85: ifnull        102
+        88: iload_1
+        89: invokedynamic #249,  0            // InvokeDynamic #6:invoke:(I)Lkotlin/jvm/functions/Function2;
+        94: invokeinterface #32,  2           // InterfaceMethod androidx/compose/runtime/ScopeUpdateScope.updateScope:(Lkotlin/jvm/functions/Function2;)V
+        99: goto          103
+       102: pop
+       103: return
+
+  private static final kotlin.Unit WidgetDiscoverability$lambda$0(int, androidx.compose.runtime.Composer, int);
+    Code:
+         0: aload_1
+         1: iload_0
+         2: iconst_1
+         3: ior
+         4: invokestatic  #82                 // Method androidx/compose/runtime/RecomposeScopeImplKt.updateChangedFlags:(I)I
+         7: invokestatic  #254                // Method WidgetDiscoverability:(Landroidx/compose/runtime/Composer;I)V
+        10: getstatic     #90                 // Field kotlin/Unit.INSTANCE:Lkotlin/Unit;
+        13: areturn
+
+  private static final void addWidgetToHomeScreen(com.example.compose.jetchat.components.Context);
+    Code:
+         0: aload_0
+         1: ldc_w         #258                // String context
+         4: invokestatic  #139                // Method kotlin/jvm/internal/Intrinsics.checkNotNullParameter:(Ljava/lang/Object;Ljava/lang/String;)V
+         7: return
+
+  private static final boolean widgetAddingIsSupported(android.content.Context);
+    Code:
+         0: aload_0
+         1: ldc_w         #258                // String context
+         4: invokestatic  #139                // Method kotlin/jvm/internal/Intrinsics.checkNotNullParameter:(Ljava/lang/Object;Ljava/lang/String;)V
+         7: getstatic     #268                // Field android/os/Build$VERSION.SDK_INT:I
+        10: getstatic     #273                // Field android/os/Build$VERSION_CODES.O:I
+        13: if_icmplt     23
+        16: aload_0
+        17: invokestatic  #279                // Method android/appwidget/AppWidgetManager.getInstance:(Landroid/content/Context;)Landroid/appwidget/AppWidgetManager;
+        20: astore_1
+        21: iconst_0
+        22: ireturn
+        23: iconst_0
+        24: ireturn
 }
