--- ./gradle/com.example.compose.jetchat.conversation.Message.javap	2026-05-24 23:07:47
+++ ./skotch/com.example.compose.jetchat.conversation.Message.javap	2026-05-24 23:07:48
@@ -1,322 +1,288 @@
-Compiled from "ConversationUiState.kt"
+Compiled from "com/example/compose/jetchat/conversation/Message.kt"
 public final class com.example.compose.jetchat.conversation.Message {
-  private final java.lang.String author;
+  public java.lang.String author;
 
-  private final java.lang.String content;
+  public java.lang.String content;
 
-  private final java.lang.String timestamp;
+  public java.lang.String timestamp;
 
-  private final java.lang.Integer image;
+  public java.lang.Integer image;
 
-  private final int authorImage;
+  public int authorImage;
 
   public static final int $stable;
 
   public com.example.compose.jetchat.conversation.Message(java.lang.String, java.lang.String, java.lang.String, java.lang.Integer, int);
     Code:
-         0: aload_1
-         1: ldc           #10                 // String author
-         3: invokestatic  #16                 // Method kotlin/jvm/internal/Intrinsics.checkNotNullParameter:(Ljava/lang/Object;Ljava/lang/String;)V
-         6: aload_2
-         7: ldc           #18                 // String content
-         9: invokestatic  #16                 // Method kotlin/jvm/internal/Intrinsics.checkNotNullParameter:(Ljava/lang/Object;Ljava/lang/String;)V
-        12: aload_3
-        13: ldc           #20                 // String timestamp
-        15: invokestatic  #16                 // Method kotlin/jvm/internal/Intrinsics.checkNotNullParameter:(Ljava/lang/Object;Ljava/lang/String;)V
-        18: aload_0
-        19: invokespecial #23                 // Method java/lang/Object."<init>":()V
-        22: aload_0
-        23: aload_1
-        24: putfield      #26                 // Field author:Ljava/lang/String;
-        27: aload_0
-        28: aload_2
-        29: putfield      #28                 // Field content:Ljava/lang/String;
-        32: aload_0
-        33: aload_3
-        34: putfield      #30                 // Field timestamp:Ljava/lang/String;
-        37: aload_0
-        38: aload         4
-        40: putfield      #34                 // Field image:Ljava/lang/Integer;
-        43: aload_0
-        44: iload         5
-        46: putfield      #38                 // Field authorImage:I
-        49: return
+         0: aload_0
+         1: invokespecial #21                 // Method java/lang/Object."<init>":()V
+         4: aload_0
+         5: aload_1
+         6: putfield      #23                 // Field author:Ljava/lang/String;
+         9: aload_0
+        10: aload_2
+        11: putfield      #25                 // Field content:Ljava/lang/String;
+        14: aload_0
+        15: aload_3
+        16: putfield      #27                 // Field timestamp:Ljava/lang/String;
+        19: aload_0
+        20: aload         4
+        22: putfield      #29                 // Field image:Ljava/lang/Integer;
+        25: aload_0
+        26: iload         5
+        28: putfield      #31                 // Field authorImage:I
+        31: return
 
-  public com.example.compose.jetchat.conversation.Message(java.lang.String, java.lang.String, java.lang.String, java.lang.Integer, int, int, kotlin.jvm.internal.DefaultConstructorMarker);
+  public java.lang.String getAuthor();
     Code:
-         0: iload         6
-         2: bipush        8
-         4: iand
-         5: ifeq          11
-         8: aconst_null
-         9: astore        4
-        11: iload         6
-        13: bipush        16
-        15: iand
-        16: ifeq          39
-        19: aload_1
-        20: ldc           #43                 // String me
-        22: invokestatic  #47                 // Method kotlin/jvm/internal/Intrinsics.areEqual:(Ljava/lang/Object;Ljava/lang/Object;)Z
-        25: ifeq          34
-        28: getstatic     #52                 // Field com/example/compose/jetchat/R$drawable.ali:I
-        31: goto          37
-        34: getstatic     #55                 // Field com/example/compose/jetchat/R$drawable.someone_else:I
-        37: istore        5
-        39: aload_0
-        40: aload_1
-        41: aload_2
-        42: aload_3
-        43: aload         4
-        45: iload         5
-        47: invokespecial #57                 // Method "<init>":(Ljava/lang/String;Ljava/lang/String;Ljava/lang/String;Ljava/lang/Integer;I)V
-        50: return
-
-  public final java.lang.String getAuthor();
-    Code:
          0: aload_0
-         1: getfield      #26                 // Field author:Ljava/lang/String;
+         1: getfield      #23                 // Field author:Ljava/lang/String;
          4: areturn
 
-  public final java.lang.String getContent();
+  public java.lang.String getContent();
     Code:
          0: aload_0
-         1: getfield      #28                 // Field content:Ljava/lang/String;
+         1: getfield      #25                 // Field content:Ljava/lang/String;
          4: areturn
 
-  public final java.lang.String getTimestamp();
+  public java.lang.String getTimestamp();
     Code:
          0: aload_0
-         1: getfield      #30                 // Field timestamp:Ljava/lang/String;
+         1: getfield      #27                 // Field timestamp:Ljava/lang/String;
          4: areturn
 
-  public final java.lang.Integer getImage();
+  public java.lang.Integer getImage();
     Code:
          0: aload_0
-         1: getfield      #34                 // Field image:Ljava/lang/Integer;
+         1: getfield      #29                 // Field image:Ljava/lang/Integer;
          4: areturn
 
-  public final int getAuthorImage();
+  public int getAuthorImage();
     Code:
          0: aload_0
-         1: getfield      #38                 // Field authorImage:I
+         1: getfield      #31                 // Field authorImage:I
          4: ireturn
 
-  public final java.lang.String component1();
+  public java.lang.String toString();
     Code:
+         0: ldc           #49                 // String Message(
+         2: invokedynamic #61,  0             // InvokeDynamic #0:makeConcatWithConstants:(Ljava/lang/String;)Ljava/lang/String;
+         7: astore_1
+         8: aload_1
+         9: aload_0
+        10: getfield      #23                 // Field author:Ljava/lang/String;
+        13: invokedynamic #66,  0             // InvokeDynamic #1:makeConcatWithConstants:(Ljava/lang/String;Ljava/lang/String;)Ljava/lang/String;
+        18: invokedynamic #69,  0             // InvokeDynamic #2:makeConcatWithConstants:(Ljava/lang/String;)Ljava/lang/String;
+        23: invokedynamic #72,  0             // InvokeDynamic #3:makeConcatWithConstants:(Ljava/lang/String;)Ljava/lang/String;
+        28: astore_2
+        29: aload_0
+        30: getfield      #25                 // Field content:Ljava/lang/String;
+        33: aload_2
+        34: swap
+        35: invokedynamic #66,  0             // InvokeDynamic #1:makeConcatWithConstants:(Ljava/lang/String;Ljava/lang/String;)Ljava/lang/String;
+        40: invokedynamic #69,  0             // InvokeDynamic #2:makeConcatWithConstants:(Ljava/lang/String;)Ljava/lang/String;
+        45: invokedynamic #75,  0             // InvokeDynamic #4:makeConcatWithConstants:(Ljava/lang/String;)Ljava/lang/String;
+        50: astore_3
+        51: aload_0
+        52: getfield      #27                 // Field timestamp:Ljava/lang/String;
+        55: aload_3
+        56: swap
+        57: invokedynamic #66,  0             // InvokeDynamic #1:makeConcatWithConstants:(Ljava/lang/String;Ljava/lang/String;)Ljava/lang/String;
+        62: invokedynamic #69,  0             // InvokeDynamic #2:makeConcatWithConstants:(Ljava/lang/String;)Ljava/lang/String;
+        67: invokedynamic #78,  0             // InvokeDynamic #5:makeConcatWithConstants:(Ljava/lang/String;)Ljava/lang/String;
+        72: aload_0
+        73: getfield      #29                 // Field image:Ljava/lang/Integer;
+        76: invokestatic  #82                 // Method java/lang/String.valueOf:(Ljava/lang/Object;)Ljava/lang/String;
+        79: invokevirtual #85                 // Method java/lang/String.concat:(Ljava/lang/String;)Ljava/lang/String;
+        82: invokedynamic #69,  0             // InvokeDynamic #2:makeConcatWithConstants:(Ljava/lang/String;)Ljava/lang/String;
+        87: invokedynamic #88,  0             // InvokeDynamic #6:makeConcatWithConstants:(Ljava/lang/String;)Ljava/lang/String;
+        92: aload_0
+        93: getfield      #31                 // Field authorImage:I
+        96: invokedynamic #91,  0             // InvokeDynamic #1:makeConcatWithConstants:(Ljava/lang/String;I)Ljava/lang/String;
+       101: invokedynamic #94,  0             // InvokeDynamic #7:makeConcatWithConstants:(Ljava/lang/String;)Ljava/lang/String;
+       106: areturn
+
+  public java.lang.String component1();
+    Code:
          0: aload_0
-         1: getfield      #26                 // Field author:Ljava/lang/String;
+         1: getfield      #23                 // Field author:Ljava/lang/String;
          4: areturn
 
-  public final java.lang.String component2();
+  public java.lang.String component2();
     Code:
          0: aload_0
-         1: getfield      #28                 // Field content:Ljava/lang/String;
+         1: getfield      #25                 // Field content:Ljava/lang/String;
          4: areturn
 
-  public final java.lang.String component3();
+  public java.lang.String component3();
     Code:
          0: aload_0
-         1: getfield      #30                 // Field timestamp:Ljava/lang/String;
+         1: getfield      #27                 // Field timestamp:Ljava/lang/String;
          4: areturn
 
-  public final java.lang.Integer component4();
+  public java.lang.Integer component4();
     Code:
          0: aload_0
-         1: getfield      #34                 // Field image:Ljava/lang/Integer;
+         1: getfield      #29                 // Field image:Ljava/lang/Integer;
          4: areturn
 
-  public final int component5();
+  public int component5();
     Code:
          0: aload_0
-         1: getfield      #38                 // Field authorImage:I
+         1: getfield      #31                 // Field authorImage:I
          4: ireturn
 
-  public final com.example.compose.jetchat.conversation.Message copy(java.lang.String, java.lang.String, java.lang.String, java.lang.Integer, int);
+  public boolean equals(java.lang.Object);
     Code:
-         0: aload_1
-         1: ldc           #10                 // String author
-         3: invokestatic  #16                 // Method kotlin/jvm/internal/Intrinsics.checkNotNullParameter:(Ljava/lang/Object;Ljava/lang/String;)V
-         6: aload_2
-         7: ldc           #18                 // String content
-         9: invokestatic  #16                 // Method kotlin/jvm/internal/Intrinsics.checkNotNullParameter:(Ljava/lang/Object;Ljava/lang/String;)V
-        12: aload_3
-        13: ldc           #20                 // String timestamp
-        15: invokestatic  #16                 // Method kotlin/jvm/internal/Intrinsics.checkNotNullParameter:(Ljava/lang/Object;Ljava/lang/String;)V
-        18: new           #2                  // class com/example/compose/jetchat/conversation/Message
-        21: dup
-        22: aload_1
-        23: aload_2
-        24: aload_3
-        25: aload         4
-        27: iload         5
-        29: invokespecial #57                 // Method "<init>":(Ljava/lang/String;Ljava/lang/String;Ljava/lang/String;Ljava/lang/Integer;I)V
-        32: areturn
-
-  public static com.example.compose.jetchat.conversation.Message copy$default(com.example.compose.jetchat.conversation.Message, java.lang.String, java.lang.String, java.lang.String, java.lang.Integer, int, int, java.lang.Object);
-    Code:
-         0: iload         6
-         2: iconst_1
-         3: iand
-         4: ifeq          12
-         7: aload_0
-         8: getfield      #26                 // Field author:Ljava/lang/String;
-        11: astore_1
-        12: iload         6
-        14: iconst_2
-        15: iand
-        16: ifeq          24
-        19: aload_0
-        20: getfield      #28                 // Field content:Ljava/lang/String;
-        23: astore_2
-        24: iload         6
-        26: iconst_4
-        27: iand
-        28: ifeq          36
-        31: aload_0
-        32: getfield      #30                 // Field timestamp:Ljava/lang/String;
-        35: astore_3
-        36: iload         6
-        38: bipush        8
-        40: iand
-        41: ifeq          50
-        44: aload_0
-        45: getfield      #34                 // Field image:Ljava/lang/Integer;
-        48: astore        4
-        50: iload         6
-        52: bipush        16
-        54: iand
-        55: ifeq          64
-        58: aload_0
-        59: getfield      #38                 // Field authorImage:I
-        62: istore        5
-        64: aload_0
-        65: aload_1
-        66: aload_2
-        67: aload_3
-        68: aload         4
-        70: iload         5
-        72: invokevirtual #76                 // Method copy:(Ljava/lang/String;Ljava/lang/String;Ljava/lang/String;Ljava/lang/Integer;I)Lcom/example/compose/jetchat/conversation/Message;
-        75: areturn
-
-  public java.lang.String toString();
-    Code:
          0: aload_0
-         1: getfield      #26                 // Field author:Ljava/lang/String;
-         4: aload_0
-         5: getfield      #28                 // Field content:Ljava/lang/String;
-         8: aload_0
-         9: getfield      #30                 // Field timestamp:Ljava/lang/String;
-        12: aload_0
-        13: getfield      #34                 // Field image:Ljava/lang/Integer;
-        16: aload_0
-        17: getfield      #38                 // Field authorImage:I
-        20: invokedynamic #89,  0             // InvokeDynamic #0:makeConcatWithConstants:(Ljava/lang/String;Ljava/lang/String;Ljava/lang/String;Ljava/lang/Integer;I)Ljava/lang/String;
-        25: areturn
+         1: astore_2
+         2: aload_2
+         3: aload_1
+         4: if_acmpne     13
+         7: iconst_1
+         8: istore        4
+        10: iload         4
+        12: ireturn
+        13: aload_1
+        14: instanceof    #2                  // class com/example/compose/jetchat/conversation/Message
+        17: istore        5
+        19: iload         5
+        21: ifne          30
+        24: iconst_0
+        25: istore        6
+        27: iload         6
+        29: ireturn
+        30: aload_1
+        31: checkcast     #2                  // class com/example/compose/jetchat/conversation/Message
+        34: astore        7
+        36: aload_0
+        37: getfield      #23                 // Field author:Ljava/lang/String;
+        40: astore        8
+        42: aload         7
+        44: getfield      #23                 // Field author:Ljava/lang/String;
+        47: astore        9
+        49: aload         8
+        51: aload         9
+        53: invokevirtual #103                // Method java/lang/String.equals:(Ljava/lang/Object;)Z
+        56: istore        10
+        58: aload_0
+        59: getfield      #25                 // Field content:Ljava/lang/String;
+        62: astore        11
+        64: aload         7
+        66: getfield      #25                 // Field content:Ljava/lang/String;
+        69: astore        12
+        71: aload         11
+        73: aload         12
+        75: invokevirtual #103                // Method java/lang/String.equals:(Ljava/lang/Object;)Z
+        78: istore        13
+        80: iload         10
+        82: iload         13
+        84: imul
+        85: istore        14
+        87: aload_0
+        88: getfield      #27                 // Field timestamp:Ljava/lang/String;
+        91: astore        15
+        93: aload         7
+        95: getfield      #27                 // Field timestamp:Ljava/lang/String;
+        98: astore        16
+       100: aload         15
+       102: aload         16
+       104: invokevirtual #103                // Method java/lang/String.equals:(Ljava/lang/Object;)Z
+       107: istore        17
+       109: iload         14
+       111: iload         17
+       113: imul
+       114: istore        18
+       116: aload_0
+       117: getfield      #29                 // Field image:Ljava/lang/Integer;
+       120: astore        19
+       122: aload         7
+       124: getfield      #29                 // Field image:Ljava/lang/Integer;
+       127: astore        20
+       129: aload         19
+       131: aload         20
+       133: invokevirtual #104                // Method java/lang/Object.equals:(Ljava/lang/Object;)Z
+       136: istore        21
+       138: iload         18
+       140: iload         21
+       142: imul
+       143: istore        22
+       145: aload_0
+       146: getfield      #31                 // Field authorImage:I
+       149: istore        23
+       151: aload         7
+       153: getfield      #31                 // Field authorImage:I
+       156: istore        24
+       158: iload         23
+       160: iload         24
+       162: if_icmpne     169
+       165: iconst_1
+       166: goto          170
+       169: iconst_0
+       170: istore        25
+       172: iload         22
+       174: iload         25
+       176: imul
+       177: istore        26
+       179: iload         26
+       181: ireturn
 
   public int hashCode();
     Code:
          0: aload_0
-         1: getfield      #26                 // Field author:Ljava/lang/String;
-         4: invokevirtual #94                 // Method java/lang/String.hashCode:()I
+         1: getfield      #23                 // Field author:Ljava/lang/String;
+         4: invokevirtual #108                // Method java/lang/String.hashCode:()I
          7: istore_1
-         8: iload_1
-         9: bipush        31
-        11: imul
-        12: aload_0
-        13: getfield      #28                 // Field content:Ljava/lang/String;
-        16: invokevirtual #94                 // Method java/lang/String.hashCode:()I
-        19: iadd
-        20: istore_1
-        21: iload_1
-        22: bipush        31
-        24: imul
-        25: aload_0
-        26: getfield      #30                 // Field timestamp:Ljava/lang/String;
-        29: invokevirtual #94                 // Method java/lang/String.hashCode:()I
-        32: iadd
-        33: istore_1
-        34: iload_1
-        35: bipush        31
-        37: imul
-        38: aload_0
-        39: getfield      #34                 // Field image:Ljava/lang/Integer;
-        42: ifnonnull     49
-        45: iconst_0
-        46: goto          56
-        49: aload_0
-        50: getfield      #34                 // Field image:Ljava/lang/Integer;
-        53: invokevirtual #95                 // Method java/lang/Object.hashCode:()I
-        56: iadd
-        57: istore_1
-        58: iload_1
-        59: bipush        31
-        61: imul
-        62: aload_0
-        63: getfield      #38                 // Field authorImage:I
-        66: invokestatic  #100                // Method java/lang/Integer.hashCode:(I)I
-        69: iadd
-        70: istore_1
-        71: iload_1
-        72: ireturn
+         8: aload_0
+         9: getfield      #25                 // Field content:Ljava/lang/String;
+        12: invokevirtual #108                // Method java/lang/String.hashCode:()I
+        15: istore_2
+        16: bipush        31
+        18: iload_1
+        19: imul
+        20: iload_2
+        21: iadd
+        22: istore_3
+        23: aload_0
+        24: getfield      #27                 // Field timestamp:Ljava/lang/String;
+        27: invokevirtual #108                // Method java/lang/String.hashCode:()I
+        30: istore        4
+        32: bipush        31
+        34: iload_3
+        35: imul
+        36: iload         4
+        38: iadd
+        39: istore        5
+        41: aload_0
+        42: getfield      #29                 // Field image:Ljava/lang/Integer;
+        45: checkcast     #4                  // class java/lang/Object
+        48: invokevirtual #109                // Method java/lang/Object.hashCode:()I
+        51: istore        6
+        53: bipush        31
+        55: iload         5
+        57: imul
+        58: iload         6
+        60: iadd
+        61: istore        7
+        63: aload_0
+        64: getfield      #31                 // Field authorImage:I
+        67: istore        8
+        69: bipush        31
+        71: iload         7
+        73: imul
+        74: iload         8
+        76: iadd
+        77: ireturn
 
-  public boolean equals(java.lang.Object);
+  public com.example.compose.jetchat.conversation.Message copy(java.lang.String, java.lang.String, java.lang.String, java.lang.Integer, int);
     Code:
-         0: aload_0
-         1: aload_1
-         2: if_acmpne     7
-         5: iconst_1
-         6: ireturn
-         7: aload_1
-         8: instanceof    #2                  // class com/example/compose/jetchat/conversation/Message
-        11: ifne          16
-        14: iconst_0
-        15: ireturn
-        16: aload_1
-        17: checkcast     #2                  // class com/example/compose/jetchat/conversation/Message
-        20: astore_2
-        21: aload_0
-        22: getfield      #26                 // Field author:Ljava/lang/String;
-        25: aload_2
-        26: getfield      #26                 // Field author:Ljava/lang/String;
-        29: invokestatic  #47                 // Method kotlin/jvm/internal/Intrinsics.areEqual:(Ljava/lang/Object;Ljava/lang/Object;)Z
-        32: ifne          37
-        35: iconst_0
-        36: ireturn
-        37: aload_0
-        38: getfield      #28                 // Field content:Ljava/lang/String;
-        41: aload_2
-        42: getfield      #28                 // Field content:Ljava/lang/String;
-        45: invokestatic  #47                 // Method kotlin/jvm/internal/Intrinsics.areEqual:(Ljava/lang/Object;Ljava/lang/Object;)Z
-        48: ifne          53
-        51: iconst_0
-        52: ireturn
-        53: aload_0
-        54: getfield      #30                 // Field timestamp:Ljava/lang/String;
-        57: aload_2
-        58: getfield      #30                 // Field timestamp:Ljava/lang/String;
-        61: invokestatic  #47                 // Method kotlin/jvm/internal/Intrinsics.areEqual:(Ljava/lang/Object;Ljava/lang/Object;)Z
-        64: ifne          69
-        67: iconst_0
-        68: ireturn
-        69: aload_0
-        70: getfield      #34                 // Field image:Ljava/lang/Integer;
-        73: aload_2
-        74: getfield      #34                 // Field image:Ljava/lang/Integer;
-        77: invokestatic  #47                 // Method kotlin/jvm/internal/Intrinsics.areEqual:(Ljava/lang/Object;Ljava/lang/Object;)Z
-        80: ifne          85
-        83: iconst_0
-        84: ireturn
-        85: aload_0
-        86: getfield      #38                 // Field authorImage:I
-        89: aload_2
-        90: getfield      #38                 // Field authorImage:I
-        93: if_icmpeq     98
-        96: iconst_0
-        97: ireturn
-        98: iconst_1
-        99: ireturn
-
-  static {};
-    Code:
-         0: return
+         0: new           #2                  // class com/example/compose/jetchat/conversation/Message
+         3: dup
+         4: aload_1
+         5: aload_2
+         6: aload_3
+         7: aload         4
+         9: iload         5
+        11: invokespecial #113                // Method "<init>":(Ljava/lang/String;Ljava/lang/String;Ljava/lang/String;Ljava/lang/Integer;I)V
+        14: areturn
 }
