--- ./gradle/com.example.compose.jetchat.widget.composables.MessagesWidgetKt.javap	2026-05-21 07:24:33
+++ ./skotch/com.example.compose.jetchat.widget.composables.MessagesWidgetKt.javap	2026-05-21 07:24:33
@@ -1,593 +1,218 @@
-Compiled from "MessagesWidget.kt"
+Compiled from "com/example/compose/jetchat/widget/composables/MessagesWidget.kt"
 public final class com.example.compose.jetchat.widget.composables.MessagesWidgetKt {
-  public static final void MessagesWidget(java.util.List<com.example.compose.jetchat.conversation.Message>, androidx.compose.runtime.Composer, int);
+  public static final <T> void MessagesWidget(java.util.List, androidx.compose.runtime.Composer, int);
     Code:
-         0: aload_0
-         1: ldc           #15                 // String messages
-         3: invokestatic  #21                 // Method kotlin/jvm/internal/Intrinsics.checkNotNullParameter:(Ljava/lang/Object;Ljava/lang/String;)V
-         6: aload_1
-         7: ldc           #22                 // int -1550874956
-         9: invokeinterface #28,  2           // InterfaceMethod androidx/compose/runtime/Composer.startRestartGroup:(I)Landroidx/compose/runtime/Composer;
-        14: astore_1
-        15: aload_1
-        16: ldc           #30                 // String C(MessagesWidget)N(messages)48@1988L371,42@1693L666:MessagesWidget.kt#nmuova
-        18: invokestatic  #36                 // Method androidx/compose/runtime/ComposerKt.sourceInformation:(Landroidx/compose/runtime/Composer;Ljava/lang/String;)V
-        21: iload_2
-        22: istore_3
-        23: iload_2
-        24: bipush        6
-        26: iand
-        27: ifne          48
-        30: iload_3
-        31: aload_1
-        32: aload_0
-        33: invokeinterface #40,  2           // InterfaceMethod androidx/compose/runtime/Composer.changedInstance:(Ljava/lang/Object;)Z
-        38: ifeq          45
-        41: iconst_4
-        42: goto          46
-        45: iconst_2
-        46: ior
-        47: istore_3
-        48: aload_1
-        49: iload_3
-        50: iconst_3
-        51: iand
-        52: iconst_2
-        53: if_icmpeq     60
-        56: iconst_1
-        57: goto          61
-        60: iconst_0
-        61: iload_3
-        62: iconst_1
-        63: iand
-        64: invokeinterface #44,  3           // InterfaceMethod androidx/compose/runtime/Composer.shouldExecute:(ZI)Z
-        69: ifeq          143
-        72: invokestatic  #48                 // Method androidx/compose/runtime/ComposerKt.isTraceInProgress:()Z
-        75: ifeq          87
-        78: ldc           #22                 // int -1550874956
-        80: iload_3
-        81: iconst_m1
-        82: ldc           #50                 // String com.example.compose.jetchat.widget.composables.MessagesWidget (MessagesWidget.kt:41)
-        84: invokestatic  #54                 // Method androidx/compose/runtime/ComposerKt.traceEventStart:(IIILjava/lang/String;)V
-        87: aconst_null
-        88: getstatic     #60                 // Field com/example/compose/jetchat/widget/composables/ComposableSingletons$MessagesWidgetKt.INSTANCE:Lcom/example/compose/jetchat/widget/composables/ComposableSingletons$MessagesWidgetKt;
-        91: invokevirtual #64                 // Method com/example/compose/jetchat/widget/composables/ComposableSingletons$MessagesWidgetKt."getLambda$-1495958416$app":()Lkotlin/jvm/functions/Function2;
-        94: getstatic     #69                 // Field com/example/compose/jetchat/widget/theme/JetchatGlanceColorScheme.INSTANCE:Lcom/example/compose/jetchat/widget/theme/JetchatGlanceColorScheme;
-        97: invokevirtual #73                 // Method com/example/compose/jetchat/widget/theme/JetchatGlanceColorScheme.getColors:()Landroidx/glance/color/ColorProviders;
-       100: invokevirtual #79                 // Method androidx/glance/color/ColorProviders.getBackground:()Landroidx/glance/unit/ColorProvider;
-       103: fconst_0
-       104: ldc           #80                 // int -2112188339
-       106: iconst_1
-       107: aload_0
-       108: invokedynamic #100,  0            // InvokeDynamic #0:invoke:(Ljava/util/List;)Lkotlin/jvm/functions/Function2;
-       113: aload_1
-       114: bipush        54
-       116: invokestatic  #106                // Method androidx/compose/runtime/internal/ComposableLambdaKt.rememberComposableLambda:(IZLjava/lang/Object;Landroidx/compose/runtime/Composer;I)Landroidx/compose/runtime/internal/ComposableLambda;
-       119: checkcast     #108                // class kotlin/jvm/functions/Function2
-       122: aload_1
-       123: sipush        24624
-       126: bipush        9
-       128: invokestatic  #114                // Method androidx/glance/appwidget/components/ScaffoldKt."Scaffold-hGBTI10":(Landroidx/glance/GlanceModifier;Lkotlin/jvm/functions/Function2;Landroidx/glance/unit/ColorProvider;FLkotlin/jvm/functions/Function2;Landroidx/compose/runtime/Composer;II)V
-       131: invokestatic  #48                 // Method androidx/compose/runtime/ComposerKt.isTraceInProgress:()Z
-       134: ifeq          149
-       137: invokestatic  #118                // Method androidx/compose/runtime/ComposerKt.traceEventEnd:()V
-       140: goto          149
-       143: aload_1
-       144: invokeinterface #121,  1          // InterfaceMethod androidx/compose/runtime/Composer.skipToGroupEnd:()V
-       149: aload_1
-       150: invokeinterface #125,  1          // InterfaceMethod androidx/compose/runtime/Composer.endRestartGroup:()Landroidx/compose/runtime/ScopeUpdateScope;
-       155: dup
-       156: ifnull        174
-       159: aload_0
-       160: iload_2
-       161: invokedynamic #133,  0            // InvokeDynamic #1:invoke:(Ljava/util/List;I)Lkotlin/jvm/functions/Function2;
-       166: invokeinterface #139,  2          // InterfaceMethod androidx/compose/runtime/ScopeUpdateScope.updateScope:(Lkotlin/jvm/functions/Function2;)V
-       171: goto          175
-       174: pop
-       175: return
-
-  public static final void MessageItem(com.example.compose.jetchat.conversation.Message, androidx.compose.runtime.Composer, int);
-    Code:
-         0: aload_0
-         1: ldc           #151                // String message
-         3: invokestatic  #21                 // Method kotlin/jvm/internal/Intrinsics.checkNotNullParameter:(Ljava/lang/Object;Ljava/lang/String;)V
-         6: aload_1
-         7: ldc           #152                // int 1710046225
-         9: invokeinterface #28,  2           // InterfaceMethod androidx/compose/runtime/Composer.startRestartGroup:(I)Landroidx/compose/runtime/Composer;
-        14: astore_1
-        15: aload_1
-        16: ldc           #154                // String C(MessageItem)N(message)64@2510L239,64@2415L334:MessagesWidget.kt#nmuova
-        18: invokestatic  #36                 // Method androidx/compose/runtime/ComposerKt.sourceInformation:(Landroidx/compose/runtime/Composer;Ljava/lang/String;)V
-        21: iload_2
-        22: istore_3
-        23: iload_2
-        24: bipush        6
-        26: iand
-        27: ifne          48
-        30: iload_3
-        31: aload_1
-        32: aload_0
-        33: invokeinterface #157,  2          // InterfaceMethod androidx/compose/runtime/Composer.changed:(Ljava/lang/Object;)Z
-        38: ifeq          45
-        41: iconst_4
-        42: goto          46
-        45: iconst_2
-        46: ior
-        47: istore_3
-        48: aload_1
-        49: iload_3
-        50: iconst_3
-        51: iand
-        52: iconst_2
-        53: if_icmpeq     60
-        56: iconst_1
-        57: goto          61
-        60: iconst_0
-        61: iload_3
-        62: iconst_1
-        63: iand
-        64: invokeinterface #44,  3           // InterfaceMethod androidx/compose/runtime/Composer.shouldExecute:(ZI)Z
-        69: ifeq          159
-        72: invokestatic  #48                 // Method androidx/compose/runtime/ComposerKt.isTraceInProgress:()Z
-        75: ifeq          87
-        78: ldc           #152                // int 1710046225
-        80: iload_3
-        81: iconst_m1
-        82: ldc           #159                // String com.example.compose.jetchat.widget.composables.MessageItem (MessagesWidget.kt:63)
-        84: invokestatic  #54                 // Method androidx/compose/runtime/ComposerKt.traceEventStart:(IIILjava/lang/String;)V
-        87: getstatic     #165                // Field androidx/glance/GlanceModifier.Companion:Landroidx/glance/GlanceModifier$Companion;
-        90: checkcast     #161                // class androidx/glance/GlanceModifier
-        93: iconst_0
-        94: anewarray     #167                // class androidx/glance/action/ActionParameters$Pair
-        97: invokestatic  #173                // Method androidx/glance/action/ActionParametersKt.actionParametersOf:([Landroidx/glance/action/ActionParameters$Pair;)Landroidx/glance/action/ActionParameters;
-       100: astore        4
-       102: iconst_0
-       103: istore        5
-       105: ldc           #175                // class com/example/compose/jetchat/NavActivity
-       107: aload         4
-       109: invokestatic  #181                // Method androidx/glance/action/StartActivityActionKt.actionStartActivity:(Ljava/lang/Class;Landroidx/glance/action/ActionParameters;)Landroidx/glance/action/Action;
-       112: invokestatic  #187                // Method androidx/glance/action/ActionKt.clickable:(Landroidx/glance/GlanceModifier;Landroidx/glance/action/Action;)Landroidx/glance/GlanceModifier;
-       115: invokestatic  #193                // Method androidx/glance/layout/SizeModifiersKt.fillMaxWidth:(Landroidx/glance/GlanceModifier;)Landroidx/glance/GlanceModifier;
-       118: iconst_0
-       119: iconst_0
-       120: ldc           #194                // int 1430340187
-       122: iconst_1
-       123: aload_0
-       124: invokedynamic #206,  0            // InvokeDynamic #2:invoke:(Lcom/example/compose/jetchat/conversation/Message;)Lkotlin/jvm/functions/Function3;
-       129: aload_1
-       130: bipush        54
-       132: invokestatic  #106                // Method androidx/compose/runtime/internal/ComposableLambdaKt.rememberComposableLambda:(IZLjava/lang/Object;Landroidx/compose/runtime/Composer;I)Landroidx/compose/runtime/internal/ComposableLambda;
-       135: checkcast     #208                // class kotlin/jvm/functions/Function3
-       138: aload_1
-       139: sipush        3072
-       142: bipush        6
-       144: invokestatic  #214                // Method androidx/glance/layout/ColumnKt."Column-K4GKKTE":(Landroidx/glance/GlanceModifier;IILkotlin/jvm/functions/Function3;Landroidx/compose/runtime/Composer;II)V
-       147: invokestatic  #48                 // Method androidx/compose/runtime/ComposerKt.isTraceInProgress:()Z
-       150: ifeq          165
-       153: invokestatic  #118                // Method androidx/compose/runtime/ComposerKt.traceEventEnd:()V
-       156: goto          165
-       159: aload_1
-       160: invokeinterface #121,  1          // InterfaceMethod androidx/compose/runtime/Composer.skipToGroupEnd:()V
-       165: aload_1
-       166: invokeinterface #125,  1          // InterfaceMethod androidx/compose/runtime/Composer.endRestartGroup:()Landroidx/compose/runtime/ScopeUpdateScope;
-       171: dup
-       172: ifnull        190
-       175: aload_0
-       176: iload_2
-       177: invokedynamic #222,  0            // InvokeDynamic #3:invoke:(Lcom/example/compose/jetchat/conversation/Message;I)Lkotlin/jvm/functions/Function2;
-       182: invokeinterface #139,  2          // InterfaceMethod androidx/compose/runtime/ScopeUpdateScope.updateScope:(Lkotlin/jvm/functions/Function2;)V
-       187: goto          191
-       190: pop
-       191: return
-
-  public static final void MessageItemPreview(androidx.compose.runtime.Composer, int);
-    Code:
-         0: aload_0
-         1: ldc           #232                // int -405148880
-         3: invokeinterface #28,  2           // InterfaceMethod androidx/compose/runtime/Composer.startRestartGroup:(I)Landroidx/compose/runtime/Composer;
-         8: astore_0
-         9: aload_0
-        10: ldc           #234                // String C(MessageItemPreview)79@2805L79:MessagesWidget.kt#nmuova
-        12: invokestatic  #36                 // Method androidx/compose/runtime/ComposerKt.sourceInformation:(Landroidx/compose/runtime/Composer;Ljava/lang/String;)V
-        15: aload_0
-        16: iload_1
-        17: ifeq          24
-        20: iconst_1
-        21: goto          25
-        24: iconst_0
-        25: iload_1
-        26: iconst_1
-        27: iand
-        28: invokeinterface #44,  3           // InterfaceMethod androidx/compose/runtime/Composer.shouldExecute:(ZI)Z
-        33: ifeq          87
-        36: invokestatic  #48                 // Method androidx/compose/runtime/ComposerKt.isTraceInProgress:()Z
-        39: ifeq          51
-        42: ldc           #232                // int -405148880
-        44: iload_1
-        45: iconst_m1
-        46: ldc           #236                // String com.example.compose.jetchat.widget.composables.MessageItemPreview (MessagesWidget.kt:78)
-        48: invokestatic  #54                 // Method androidx/compose/runtime/ComposerKt.traceEventStart:(IIILjava/lang/String;)V
-        51: new           #228                // class com/example/compose/jetchat/conversation/Message
-        54: dup
-        55: ldc           #238                // String John
-        57: ldc           #240                // String This is a preview of the message Item
-        59: ldc           #242                // String 8:02PM
-        61: aconst_null
-        62: iconst_0
-        63: bipush        24
-        65: aconst_null
-        66: invokespecial #246                // Method com/example/compose/jetchat/conversation/Message."<init>":(Ljava/lang/String;Ljava/lang/String;Ljava/lang/String;Ljava/lang/Integer;IILkotlin/jvm/internal/DefaultConstructorMarker;)V
-        69: aload_0
-        70: bipush        6
-        72: invokestatic  #248                // Method MessageItem:(Lcom/example/compose/jetchat/conversation/Message;Landroidx/compose/runtime/Composer;I)V
-        75: invokestatic  #48                 // Method androidx/compose/runtime/ComposerKt.isTraceInProgress:()Z
-        78: ifeq          93
-        81: invokestatic  #118                // Method androidx/compose/runtime/ComposerKt.traceEventEnd:()V
-        84: goto          93
-        87: aload_0
-        88: invokeinterface #121,  1          // InterfaceMethod androidx/compose/runtime/Composer.skipToGroupEnd:()V
-        93: aload_0
-        94: invokeinterface #125,  1          // InterfaceMethod androidx/compose/runtime/Composer.endRestartGroup:()Landroidx/compose/runtime/ScopeUpdateScope;
-        99: dup
-       100: ifnull        117
-       103: iload_1
-       104: invokedynamic #256,  0            // InvokeDynamic #4:invoke:(I)Lkotlin/jvm/functions/Function2;
-       109: invokeinterface #139,  2          // InterfaceMethod androidx/compose/runtime/ScopeUpdateScope.updateScope:(Lkotlin/jvm/functions/Function2;)V
-       114: goto          118
-       117: pop
-       118: return
-
-  public static final void WidgetPreview(androidx.compose.runtime.Composer, int);
-    Code:
-         0: aload_0
-         1: ldc_w         #258                // int 431087178
-         4: invokeinterface #28,  2           // InterfaceMethod androidx/compose/runtime/Composer.startRestartGroup:(I)Landroidx/compose/runtime/Composer;
-         9: astore_0
-        10: aload_0
-        11: ldc_w         #260                // String C(WidgetPreview)85@2935L90:MessagesWidget.kt#nmuova
-        14: invokestatic  #36                 // Method androidx/compose/runtime/ComposerKt.sourceInformation:(Landroidx/compose/runtime/Composer;Ljava/lang/String;)V
-        17: aload_0
-        18: iload_1
-        19: ifeq          26
-        22: iconst_1
-        23: goto          27
-        26: iconst_0
-        27: iload_1
-        28: iconst_1
-        29: iand
-        30: invokeinterface #44,  3           // InterfaceMethod androidx/compose/runtime/Composer.shouldExecute:(ZI)Z
-        35: ifeq          94
-        38: invokestatic  #48                 // Method androidx/compose/runtime/ComposerKt.isTraceInProgress:()Z
-        41: ifeq          55
-        44: ldc_w         #258                // int 431087178
-        47: iload_1
-        48: iconst_m1
-        49: ldc_w         #262                // String com.example.compose.jetchat.widget.composables.WidgetPreview (MessagesWidget.kt:84)
-        52: invokestatic  #54                 // Method androidx/compose/runtime/ComposerKt.traceEventStart:(IIILjava/lang/String;)V
-        55: new           #228                // class com/example/compose/jetchat/conversation/Message
-        58: dup
-        59: ldc           #238                // String John
-        61: ldc           #240                // String This is a preview of the message Item
-        63: ldc           #242                // String 8:02PM
-        65: aconst_null
-        66: iconst_0
-        67: bipush        24
-        69: aconst_null
-        70: invokespecial #246                // Method com/example/compose/jetchat/conversation/Message."<init>":(Ljava/lang/String;Ljava/lang/String;Ljava/lang/String;Ljava/lang/Integer;IILkotlin/jvm/internal/DefaultConstructorMarker;)V
-        73: invokestatic  #268                // Method kotlin/collections/CollectionsKt.listOf:(Ljava/lang/Object;)Ljava/util/List;
-        76: aload_0
-        77: bipush        6
-        79: invokestatic  #270                // Method MessagesWidget:(Ljava/util/List;Landroidx/compose/runtime/Composer;I)V
-        82: invokestatic  #48                 // Method androidx/compose/runtime/ComposerKt.isTraceInProgress:()Z
-        85: ifeq          100
-        88: invokestatic  #118                // Method androidx/compose/runtime/ComposerKt.traceEventEnd:()V
-        91: goto          100
-        94: aload_0
-        95: invokeinterface #121,  1          // InterfaceMethod androidx/compose/runtime/Composer.skipToGroupEnd:()V
-       100: aload_0
-       101: invokeinterface #125,  1          // InterfaceMethod androidx/compose/runtime/Composer.endRestartGroup:()Landroidx/compose/runtime/ScopeUpdateScope;
-       106: dup
-       107: ifnull        124
-       110: iload_1
-       111: invokedynamic #275,  0            // InvokeDynamic #5:invoke:(I)Lkotlin/jvm/functions/Function2;
-       116: invokeinterface #139,  2          // InterfaceMethod androidx/compose/runtime/ScopeUpdateScope.updateScope:(Lkotlin/jvm/functions/Function2;)V
-       121: goto          125
-       124: pop
-       125: return
-
-  private static final kotlin.Unit MessagesWidget$lambda$0$0$0$0$0$0(com.example.compose.jetchat.conversation.Message, androidx.glance.layout.ColumnScope, androidx.compose.runtime.Composer, int);
-    Code:
          0: aload_1
-         1: ldc_w         #278                // String $this$Column
-         4: invokestatic  #21                 // Method kotlin/jvm/internal/Intrinsics.checkNotNullParameter:(Ljava/lang/Object;Ljava/lang/String;)V
-         7: aload_2
-         8: ldc_w         #280                // String C53@2202L15,54@2242L47:MessagesWidget.kt#nmuova
-        11: invokestatic  #36                 // Method androidx/compose/runtime/ComposerKt.sourceInformation:(Landroidx/compose/runtime/Composer;Ljava/lang/String;)V
-        14: invokestatic  #48                 // Method androidx/compose/runtime/ComposerKt.isTraceInProgress:()Z
-        17: ifeq          31
-        20: ldc_w         #281                // int 1409182074
-        23: iload_3
-        24: iconst_m1
-        25: ldc_w         #283                // String com.example.compose.jetchat.widget.composables.MessagesWidget.<anonymous>.<anonymous>.<anonymous>.<anonymous>.<anonymous>.<anonymous> (MessagesWidget.kt:53)
-        28: invokestatic  #54                 // Method androidx/compose/runtime/ComposerKt.traceEventStart:(IIILjava/lang/String;)V
-        31: aload_0
-        32: aload_2
-        33: iconst_0
-        34: invokestatic  #248                // Method MessageItem:(Lcom/example/compose/jetchat/conversation/Message;Landroidx/compose/runtime/Composer;I)V
-        37: getstatic     #165                // Field androidx/glance/GlanceModifier.Companion:Landroidx/glance/GlanceModifier$Companion;
-        40: checkcast     #161                // class androidx/glance/GlanceModifier
-        43: bipush        10
-        45: istore        4
-        47: iconst_0
-        48: istore        5
-        50: iload         4
-        52: i2f
-        53: invokestatic  #289                // Method androidx/compose/ui/unit/Dp."constructor-impl":(F)F
-        56: invokestatic  #293                // Method androidx/glance/layout/SizeModifiersKt."height-3ABfNKs":(Landroidx/glance/GlanceModifier;F)Landroidx/glance/GlanceModifier;
-        59: aload_2
-        60: iconst_0
-        61: iconst_0
-        62: invokestatic  #299                // Method androidx/glance/layout/SpacerKt.Spacer:(Landroidx/glance/GlanceModifier;Landroidx/compose/runtime/Composer;II)V
-        65: invokestatic  #48                 // Method androidx/compose/runtime/ComposerKt.isTraceInProgress:()Z
-        68: ifeq          74
-        71: invokestatic  #118                // Method androidx/compose/runtime/ComposerKt.traceEventEnd:()V
-        74: getstatic     #304                // Field kotlin/Unit.INSTANCE:Lkotlin/Unit;
-        77: areturn
-
-  private static final kotlin.Unit MessagesWidget$lambda$0$0$0$0$0(com.example.compose.jetchat.conversation.Message, androidx.glance.appwidget.lazy.LazyItemScope, androidx.compose.runtime.Composer, int);
-    Code:
-         0: aload_1
-         1: ldc_w         #312                // String $this$item
-         4: invokestatic  #21                 // Method kotlin/jvm/internal/Intrinsics.checkNotNullParameter:(Ljava/lang/Object;Ljava/lang/String;)V
-         7: aload_2
-         8: ldc_w         #314                // String C52@2176L135,52@2127L184:MessagesWidget.kt#nmuova
-        11: invokestatic  #36                 // Method androidx/compose/runtime/ComposerKt.sourceInformation:(Landroidx/compose/runtime/Composer;Ljava/lang/String;)V
-        14: invokestatic  #48                 // Method androidx/compose/runtime/ComposerKt.isTraceInProgress:()Z
-        17: ifeq          31
-        20: ldc_w         #315                // int -1419887312
-        23: iload_3
-        24: iconst_m1
-        25: ldc_w         #317                // String com.example.compose.jetchat.widget.composables.MessagesWidget.<anonymous>.<anonymous>.<anonymous>.<anonymous>.<anonymous> (MessagesWidget.kt:52)
-        28: invokestatic  #54                 // Method androidx/compose/runtime/ComposerKt.traceEventStart:(IIILjava/lang/String;)V
-        31: getstatic     #165                // Field androidx/glance/GlanceModifier.Companion:Landroidx/glance/GlanceModifier$Companion;
-        34: checkcast     #161                // class androidx/glance/GlanceModifier
-        37: invokestatic  #193                // Method androidx/glance/layout/SizeModifiersKt.fillMaxWidth:(Landroidx/glance/GlanceModifier;)Landroidx/glance/GlanceModifier;
-        40: iconst_0
-        41: iconst_0
-        42: ldc_w         #281                // int 1409182074
-        45: iconst_1
+         1: ldc           #33                 // int -503290507
+         3: invokeinterface #16,  2           // InterfaceMethod androidx/compose/runtime/Composer.startRestartGroup:(I)Landroidx/compose/runtime/Composer;
+         8: astore_1
+         9: aload_1
+        10: iload_2
+        11: ifeq          18
+        14: iconst_1
+        15: goto          19
+        18: iconst_0
+        19: iload_2
+        20: iconst_1
+        21: iand
+        22: invokeinterface #20,  3           // InterfaceMethod androidx/compose/runtime/Composer.shouldExecute:(ZI)Z
+        27: ifne          36
+        30: aload_1
+        31: invokeinterface #24,  1           // InterfaceMethod androidx/compose/runtime/Composer.skipToGroupEnd:()V
+        36: aload_1
+        37: invokeinterface #28,  1           // InterfaceMethod androidx/compose/runtime/Composer.endRestartGroup:()Landroidx/compose/runtime/ScopeUpdateScope;
+        42: dup
+        43: ifnull        61
         46: aload_0
-        47: invokedynamic #321,  0            // InvokeDynamic #6:invoke:(Lcom/example/compose/jetchat/conversation/Message;)Lkotlin/jvm/functions/Function3;
-        52: aload_2
-        53: bipush        54
-        55: invokestatic  #106                // Method androidx/compose/runtime/internal/ComposableLambdaKt.rememberComposableLambda:(IZLjava/lang/Object;Landroidx/compose/runtime/Composer;I)Landroidx/compose/runtime/internal/ComposableLambda;
-        58: checkcast     #208                // class kotlin/jvm/functions/Function3
-        61: aload_2
-        62: sipush        3072
-        65: bipush        6
-        67: invokestatic  #214                // Method androidx/glance/layout/ColumnKt."Column-K4GKKTE":(Landroidx/glance/GlanceModifier;IILkotlin/jvm/functions/Function3;Landroidx/compose/runtime/Composer;II)V
-        70: invokestatic  #48                 // Method androidx/compose/runtime/ComposerKt.isTraceInProgress:()Z
-        73: ifeq          79
-        76: invokestatic  #118                // Method androidx/compose/runtime/ComposerKt.traceEventEnd:()V
-        79: getstatic     #304                // Field kotlin/Unit.INSTANCE:Lkotlin/Unit;
-        82: areturn
+        47: iload_2
+        48: invokedynamic #53,  0             // InvokeDynamic #0:invoke:(Ljava/util/List;I)Lkotlin/jvm/functions/Function2;
+        53: invokeinterface #32,  2           // InterfaceMethod androidx/compose/runtime/ScopeUpdateScope.updateScope:(Lkotlin/jvm/functions/Function2;)V
+        58: goto          62
+        61: pop
+        62: return
 
-  private static final kotlin.Unit MessagesWidget$lambda$0$0$0(java.util.List, androidx.glance.appwidget.lazy.LazyListScope);
+  private static final kotlin.Unit MessagesWidget$lambda$0(java.util.List, int, androidx.compose.runtime.Composer, int);
     Code:
-         0: aload_1
-         1: ldc_w         #326                // String $this$LazyColumn
-         4: invokestatic  #21                 // Method kotlin/jvm/internal/Intrinsics.checkNotNullParameter:(Ljava/lang/Object;Ljava/lang/String;)V
-         7: aload_0
-         8: checkcast     #328                // class java/lang/Iterable
-        11: astore_2
-        12: iconst_0
-        13: istore_3
-        14: aload_2
-        15: invokeinterface #332,  1          // InterfaceMethod java/lang/Iterable.iterator:()Ljava/util/Iterator;
-        20: astore        4
-        22: aload         4
-        24: invokeinterface #337,  1          // InterfaceMethod java/util/Iterator.hasNext:()Z
-        29: ifeq          80
-        32: aload         4
-        34: invokeinterface #341,  1          // InterfaceMethod java/util/Iterator.next:()Ljava/lang/Object;
-        39: astore        5
-        41: aload         5
-        43: checkcast     #228                // class com/example/compose/jetchat/conversation/Message
-        46: astore        6
-        48: iconst_0
-        49: istore        7
-        51: aload_1
-        52: lconst_0
-        53: ldc_w         #315                // int -1419887312
-        56: iconst_1
-        57: aload         6
-        59: invokedynamic #347,  0            // InvokeDynamic #7:invoke:(Lcom/example/compose/jetchat/conversation/Message;)Lkotlin/jvm/functions/Function3;
-        64: invokestatic  #351                // Method androidx/compose/runtime/internal/ComposableLambdaKt.composableLambdaInstance:(IZLjava/lang/Object;)Landroidx/compose/runtime/internal/ComposableLambda;
-        67: checkcast     #208                // class kotlin/jvm/functions/Function3
-        70: iconst_1
-        71: aconst_null
-        72: invokestatic  #357                // InterfaceMethod androidx/glance/appwidget/lazy/LazyListScope.item$default:(Landroidx/glance/appwidget/lazy/LazyListScope;JLkotlin/jvm/functions/Function3;ILjava/lang/Object;)V
-        75: nop
-        76: nop
-        77: goto          22
-        80: nop
-        81: getstatic     #304                // Field kotlin/Unit.INSTANCE:Lkotlin/Unit;
-        84: areturn
-
-  private static final kotlin.Unit MessagesWidget$lambda$0(java.util.List, androidx.compose.runtime.Composer, int);
-    Code:
-         0: aload_1
-         1: ldc_w         #368                // String C49@2051L302,49@1998L355:MessagesWidget.kt#nmuova
-         4: invokestatic  #36                 // Method androidx/compose/runtime/ComposerKt.sourceInformation:(Landroidx/compose/runtime/Composer;Ljava/lang/String;)V
-         7: aload_1
-         8: iload_2
-         9: iconst_3
-        10: iand
-        11: iconst_2
-        12: if_icmpeq     19
-        15: iconst_1
-        16: goto          20
-        19: iconst_0
-        20: iload_2
-        21: iconst_1
-        22: iand
-        23: invokeinterface #44,  3           // InterfaceMethod androidx/compose/runtime/Composer.shouldExecute:(ZI)Z
-        28: ifeq          178
-        31: invokestatic  #48                 // Method androidx/compose/runtime/ComposerKt.isTraceInProgress:()Z
-        34: ifeq          47
-        37: ldc           #80                 // int -2112188339
-        39: iload_2
-        40: iconst_m1
-        41: ldc_w         #370                // String com.example.compose.jetchat.widget.composables.MessagesWidget.<anonymous> (MessagesWidget.kt:49)
-        44: invokestatic  #54                 // Method androidx/compose/runtime/ComposerKt.traceEventStart:(IIILjava/lang/String;)V
-        47: getstatic     #165                // Field androidx/glance/GlanceModifier.Companion:Landroidx/glance/GlanceModifier$Companion;
-        50: checkcast     #161                // class androidx/glance/GlanceModifier
-        53: invokestatic  #193                // Method androidx/glance/layout/SizeModifiersKt.fillMaxWidth:(Landroidx/glance/GlanceModifier;)Landroidx/glance/GlanceModifier;
-        56: iconst_0
-        57: aload_1
-        58: ldc_w         #371                // int 1706539547
-        61: ldc_w         #373                // String CC(remember):MessagesWidget.kt#9igjgp
-        64: invokestatic  #377                // Method androidx/compose/runtime/ComposerKt.sourceInformationMarkerStart:(Landroidx/compose/runtime/Composer;ILjava/lang/String;)V
-        67: aload_1
-        68: astore        4
-        70: aload_1
-        71: aload_0
-        72: invokeinterface #40,  2           // InterfaceMethod androidx/compose/runtime/Composer.changedInstance:(Ljava/lang/Object;)Z
-        77: istore        5
-        79: iconst_0
-        80: istore        6
-        82: aload         4
-        84: invokeinterface #380,  1          // InterfaceMethod androidx/compose/runtime/Composer.rememberedValue:()Ljava/lang/Object;
-        89: astore        7
-        91: iconst_0
-        92: istore        8
-        94: iload         5
-        96: ifne          110
-        99: aload         7
-       101: getstatic     #383                // Field androidx/compose/runtime/Composer.Companion:Landroidx/compose/runtime/Composer$Companion;
-       104: invokevirtual #388                // Method androidx/compose/runtime/Composer$Companion.getEmpty:()Ljava/lang/Object;
-       107: if_acmpne     147
-       110: istore        12
-       112: astore        11
-       114: iconst_0
-       115: istore        9
-       117: aload_0
-       118: invokedynamic #398,  0            // InvokeDynamic #8:invoke:(Ljava/util/List;)Lkotlin/jvm/functions/Function1;
-       123: astore        13
-       125: aload         11
-       127: iload         12
-       129: aload         13
-       131: astore        10
-       133: aload         4
-       135: aload         10
-       137: invokeinterface #402,  2          // InterfaceMethod androidx/compose/runtime/Composer.updateRememberedValue:(Ljava/lang/Object;)V
-       142: aload         10
-       144: goto          149
-       147: aload         7
-       149: nop
-       150: nop
-       151: checkcast     #404                // class kotlin/jvm/functions/Function1
-       154: astore_3
-       155: aload_1
-       156: invokestatic  #408                // Method androidx/compose/runtime/ComposerKt.sourceInformationMarkerEnd:(Landroidx/compose/runtime/Composer;)V
-       159: aload_3
-       160: aload_1
-       161: iconst_0
-       162: iconst_2
-       163: invokestatic  #414                // Method androidx/glance/appwidget/lazy/LazyListKt."LazyColumn-EiNPFjs":(Landroidx/glance/GlanceModifier;ILkotlin/jvm/functions/Function1;Landroidx/compose/runtime/Composer;II)V
-       166: invokestatic  #48                 // Method androidx/compose/runtime/ComposerKt.isTraceInProgress:()Z
-       169: ifeq          184
-       172: invokestatic  #118                // Method androidx/compose/runtime/ComposerKt.traceEventEnd:()V
-       175: goto          184
-       178: aload_1
-       179: invokeinterface #121,  1          // InterfaceMethod androidx/compose/runtime/Composer.skipToGroupEnd:()V
-       184: getstatic     #304                // Field kotlin/Unit.INSTANCE:Lkotlin/Unit;
-       187: areturn
-
-  private static final kotlin.Unit MessagesWidget$lambda$1(java.util.List, int, androidx.compose.runtime.Composer, int);
-    Code:
          0: aload_0
          1: aload_2
          2: iload_1
          3: iconst_1
          4: ior
-         5: invokestatic  #428                // Method androidx/compose/runtime/RecomposeScopeImplKt.updateChangedFlags:(I)I
-         8: invokestatic  #270                // Method MessagesWidget:(Ljava/util/List;Landroidx/compose/runtime/Composer;I)V
-        11: getstatic     #304                // Field kotlin/Unit.INSTANCE:Lkotlin/Unit;
+         5: invokestatic  #68                 // Method androidx/compose/runtime/RecomposeScopeImplKt.updateChangedFlags:(I)I
+         8: invokestatic  #70                 // Method MessagesWidget:(Ljava/util/List;Landroidx/compose/runtime/Composer;I)V
+        11: getstatic     #76                 // Field kotlin/Unit.INSTANCE:Lkotlin/Unit;
         14: areturn
 
-  private static final kotlin.Unit MessageItem$lambda$0(com.example.compose.jetchat.conversation.Message, androidx.glance.layout.ColumnScope, androidx.compose.runtime.Composer, int);
+  public static final void MessageItem(com.example.compose.jetchat.conversation.Message, androidx.compose.runtime.Composer, int);
     Code:
          0: aload_1
-         1: ldc_w         #278                // String $this$Column
-         4: invokestatic  #21                 // Method kotlin/jvm/internal/Intrinsics.checkNotNullParameter:(Ljava/lang/Object;Ljava/lang/String;)V
-         7: aload_2
-         8: ldc_w         #432                // String C65@2520L107,69@2636L107:MessagesWidget.kt#nmuova
-        11: invokestatic  #36                 // Method androidx/compose/runtime/ComposerKt.sourceInformation:(Landroidx/compose/runtime/Composer;Ljava/lang/String;)V
-        14: invokestatic  #48                 // Method androidx/compose/runtime/ComposerKt.isTraceInProgress:()Z
-        17: ifeq          30
-        20: ldc           #194                // int 1430340187
-        22: iload_3
-        23: iconst_m1
-        24: ldc_w         #434                // String com.example.compose.jetchat.widget.composables.MessageItem.<anonymous> (MessagesWidget.kt:65)
-        27: invokestatic  #54                 // Method androidx/compose/runtime/ComposerKt.traceEventStart:(IIILjava/lang/String;)V
-        30: aload_0
-        31: invokevirtual #438                // Method com/example/compose/jetchat/conversation/Message.getAuthor:()Ljava/lang/String;
-        34: aconst_null
-        35: getstatic     #443                // Field com/example/compose/jetchat/widget/theme/JetChatGlanceTextStyles.INSTANCE:Lcom/example/compose/jetchat/widget/theme/JetChatGlanceTextStyles;
-        38: invokevirtual #447                // Method com/example/compose/jetchat/widget/theme/JetChatGlanceTextStyles.getTitleMedium:()Landroidx/glance/text/TextStyle;
-        41: iconst_0
-        42: aload_2
-        43: sipush        384
-        46: bipush        10
-        48: invokestatic  #453                // Method androidx/glance/text/TextKt.Text:(Ljava/lang/String;Landroidx/glance/GlanceModifier;Landroidx/glance/text/TextStyle;ILandroidx/compose/runtime/Composer;II)V
-        51: aload_0
-        52: invokevirtual #456                // Method com/example/compose/jetchat/conversation/Message.getContent:()Ljava/lang/String;
-        55: aconst_null
-        56: getstatic     #443                // Field com/example/compose/jetchat/widget/theme/JetChatGlanceTextStyles.INSTANCE:Lcom/example/compose/jetchat/widget/theme/JetChatGlanceTextStyles;
-        59: invokevirtual #459                // Method com/example/compose/jetchat/widget/theme/JetChatGlanceTextStyles.getBodyMedium:()Landroidx/glance/text/TextStyle;
-        62: iconst_0
-        63: aload_2
-        64: sipush        384
-        67: bipush        10
-        69: invokestatic  #453                // Method androidx/glance/text/TextKt.Text:(Ljava/lang/String;Landroidx/glance/GlanceModifier;Landroidx/glance/text/TextStyle;ILandroidx/compose/runtime/Composer;II)V
-        72: invokestatic  #48                 // Method androidx/compose/runtime/ComposerKt.isTraceInProgress:()Z
-        75: ifeq          81
-        78: invokestatic  #118                // Method androidx/compose/runtime/ComposerKt.traceEventEnd:()V
-        81: getstatic     #304                // Field kotlin/Unit.INSTANCE:Lkotlin/Unit;
-        84: areturn
+         1: ldc           #79                 // int 1052538875
+         3: invokeinterface #16,  2           // InterfaceMethod androidx/compose/runtime/Composer.startRestartGroup:(I)Landroidx/compose/runtime/Composer;
+         8: astore_1
+         9: aload_1
+        10: iload_2
+        11: ifeq          18
+        14: iconst_1
+        15: goto          19
+        18: iconst_0
+        19: iload_2
+        20: iconst_1
+        21: iand
+        22: invokeinterface #20,  3           // InterfaceMethod androidx/compose/runtime/Composer.shouldExecute:(ZI)Z
+        27: ifne          39
+        30: aload_1
+        31: invokeinterface #24,  1           // InterfaceMethod androidx/compose/runtime/Composer.skipToGroupEnd:()V
+        36: goto          59
+        39: aconst_null
+        40: invokestatic  #85                 // Method androidx/glance/action/StartActivityActionKt.actionStartActivity:(Landroidx/glance/action/ActionParameters;)Landroidx/glance/action/Action;
+        43: astore_3
+        44: aconst_null
+        45: invokestatic  #85                 // Method androidx/glance/action/StartActivityActionKt.actionStartActivity:(Landroidx/glance/action/ActionParameters;)Landroidx/glance/action/Action;
+        48: astore        4
+        50: new           #87                 // class com/example/compose/jetchat/widget/composables/MessagesWidgetKt$Lambda$24
+        53: dup
+        54: aload_0
+        55: invokespecial #91                 // Method com/example/compose/jetchat/widget/composables/MessagesWidgetKt$Lambda$24."<init>":(Lcom/example/compose/jetchat/conversation/Message;)V
+        58: pop
+        59: aload_1
+        60: invokeinterface #28,  1           // InterfaceMethod androidx/compose/runtime/Composer.endRestartGroup:()Landroidx/compose/runtime/ScopeUpdateScope;
+        65: dup
+        66: ifnull        84
+        69: aload_0
+        70: iload_2
+        71: invokedynamic #99,  0             // InvokeDynamic #1:invoke:(Lcom/example/compose/jetchat/conversation/Message;I)Lkotlin/jvm/functions/Function2;
+        76: invokeinterface #32,  2           // InterfaceMethod androidx/compose/runtime/ScopeUpdateScope.updateScope:(Lkotlin/jvm/functions/Function2;)V
+        81: goto          85
+        84: pop
+        85: return
 
-  private static final kotlin.Unit MessageItem$lambda$1(com.example.compose.jetchat.conversation.Message, int, androidx.compose.runtime.Composer, int);
+  private static final kotlin.Unit MessageItem$lambda$0(com.example.compose.jetchat.conversation.Message, int, androidx.compose.runtime.Composer, int);
     Code:
          0: aload_0
          1: aload_2
          2: iload_1
          3: iconst_1
          4: ior
-         5: invokestatic  #428                // Method androidx/compose/runtime/RecomposeScopeImplKt.updateChangedFlags:(I)I
-         8: invokestatic  #248                // Method MessageItem:(Lcom/example/compose/jetchat/conversation/Message;Landroidx/compose/runtime/Composer;I)V
-        11: getstatic     #304                // Field kotlin/Unit.INSTANCE:Lkotlin/Unit;
+         5: invokestatic  #68                 // Method androidx/compose/runtime/RecomposeScopeImplKt.updateChangedFlags:(I)I
+         8: invokestatic  #103                // Method MessageItem:(Lcom/example/compose/jetchat/conversation/Message;Landroidx/compose/runtime/Composer;I)V
+        11: getstatic     #76                 // Field kotlin/Unit.INSTANCE:Lkotlin/Unit;
         14: areturn
 
+  public static final void MessageItemPreview(androidx.compose.runtime.Composer, int);
+    Code:
+         0: aload_0
+         1: ldc           #106                // int -2019629011
+         3: invokeinterface #16,  2           // InterfaceMethod androidx/compose/runtime/Composer.startRestartGroup:(I)Landroidx/compose/runtime/Composer;
+         8: astore_0
+         9: aload_0
+        10: iload_1
+        11: ifeq          18
+        14: iconst_1
+        15: goto          19
+        18: iconst_0
+        19: iload_1
+        20: iconst_1
+        21: iand
+        22: invokeinterface #20,  3           // InterfaceMethod androidx/compose/runtime/Composer.shouldExecute:(ZI)Z
+        27: ifne          39
+        30: aload_0
+        31: invokeinterface #24,  1           // InterfaceMethod androidx/compose/runtime/Composer.skipToGroupEnd:()V
+        36: goto          59
+        39: new           #101                // class com/example/compose/jetchat/conversation/Message
+        42: dup
+        43: ldc           #108                // String John
+        45: ldc           #110                // String This is a preview of the message Item
+        47: ldc           #112                // String 8:02PM
+        49: invokespecial #115                // Method com/example/compose/jetchat/conversation/Message."<init>":(Ljava/lang/String;Ljava/lang/String;Ljava/lang/String;)V
+        52: astore_2
+        53: aload_2
+        54: aload_0
+        55: iconst_0
+        56: invokestatic  #103                // Method MessageItem:(Lcom/example/compose/jetchat/conversation/Message;Landroidx/compose/runtime/Composer;I)V
+        59: aload_0
+        60: invokeinterface #28,  1           // InterfaceMethod androidx/compose/runtime/Composer.endRestartGroup:()Landroidx/compose/runtime/ScopeUpdateScope;
+        65: dup
+        66: ifnull        83
+        69: iload_1
+        70: invokedynamic #123,  0            // InvokeDynamic #2:invoke:(I)Lkotlin/jvm/functions/Function2;
+        75: invokeinterface #32,  2           // InterfaceMethod androidx/compose/runtime/ScopeUpdateScope.updateScope:(Lkotlin/jvm/functions/Function2;)V
+        80: goto          84
+        83: pop
+        84: return
+
   private static final kotlin.Unit MessageItemPreview$lambda$0(int, androidx.compose.runtime.Composer, int);
     Code:
          0: aload_1
          1: iload_0
          2: iconst_1
          3: ior
-         4: invokestatic  #428                // Method androidx/compose/runtime/RecomposeScopeImplKt.updateChangedFlags:(I)I
-         7: invokestatic  #462                // Method MessageItemPreview:(Landroidx/compose/runtime/Composer;I)V
-        10: getstatic     #304                // Field kotlin/Unit.INSTANCE:Lkotlin/Unit;
+         4: invokestatic  #68                 // Method androidx/compose/runtime/RecomposeScopeImplKt.updateChangedFlags:(I)I
+         7: invokestatic  #127                // Method MessageItemPreview:(Landroidx/compose/runtime/Composer;I)V
+        10: getstatic     #76                 // Field kotlin/Unit.INSTANCE:Lkotlin/Unit;
         13: areturn
 
+  public static final void WidgetPreview(androidx.compose.runtime.Composer, int);
+    Code:
+         0: aload_0
+         1: ldc           #129                // int -1563054185
+         3: invokeinterface #16,  2           // InterfaceMethod androidx/compose/runtime/Composer.startRestartGroup:(I)Landroidx/compose/runtime/Composer;
+         8: astore_0
+         9: aload_0
+        10: iload_1
+        11: ifeq          18
+        14: iconst_1
+        15: goto          19
+        18: iconst_0
+        19: iload_1
+        20: iconst_1
+        21: iand
+        22: invokeinterface #20,  3           // InterfaceMethod androidx/compose/runtime/Composer.shouldExecute:(ZI)Z
+        27: ifne          39
+        30: aload_0
+        31: invokeinterface #24,  1           // InterfaceMethod androidx/compose/runtime/Composer.skipToGroupEnd:()V
+        36: goto          80
+        39: new           #101                // class com/example/compose/jetchat/conversation/Message
+        42: dup
+        43: ldc           #108                // String John
+        45: ldc           #110                // String This is a preview of the message Item
+        47: ldc           #112                // String 8:02PM
+        49: invokespecial #115                // Method com/example/compose/jetchat/conversation/Message."<init>":(Ljava/lang/String;Ljava/lang/String;Ljava/lang/String;)V
+        52: astore_2
+        53: iconst_1
+        54: istore_3
+        55: iload_3
+        56: anewarray     #4                  // class java/lang/Object
+        59: astore        4
+        61: aload         4
+        63: iconst_0
+        64: aload_2
+        65: aastore
+        66: aload         4
+        68: invokestatic  #135                // Method kotlin/collections/CollectionsKt.listOf:([Ljava/lang/Object;)Ljava/util/List;
+        71: astore        5
+        73: aload         5
+        75: aload_0
+        76: iconst_0
+        77: invokestatic  #70                 // Method MessagesWidget:(Ljava/util/List;Landroidx/compose/runtime/Composer;I)V
+        80: aload_0
+        81: invokeinterface #28,  1           // InterfaceMethod androidx/compose/runtime/Composer.endRestartGroup:()Landroidx/compose/runtime/ScopeUpdateScope;
+        86: dup
+        87: ifnull        104
+        90: iload_1
+        91: invokedynamic #140,  0            // InvokeDynamic #3:invoke:(I)Lkotlin/jvm/functions/Function2;
+        96: invokeinterface #32,  2           // InterfaceMethod androidx/compose/runtime/ScopeUpdateScope.updateScope:(Lkotlin/jvm/functions/Function2;)V
+       101: goto          105
+       104: pop
+       105: return
+
   private static final kotlin.Unit WidgetPreview$lambda$0(int, androidx.compose.runtime.Composer, int);
     Code:
          0: aload_1
          1: iload_0
          2: iconst_1
          3: ior
-         4: invokestatic  #428                // Method androidx/compose/runtime/RecomposeScopeImplKt.updateChangedFlags:(I)I
-         7: invokestatic  #464                // Method WidgetPreview:(Landroidx/compose/runtime/Composer;I)V
-        10: getstatic     #304                // Field kotlin/Unit.INSTANCE:Lkotlin/Unit;
+         4: invokestatic  #68                 // Method androidx/compose/runtime/RecomposeScopeImplKt.updateChangedFlags:(I)I
+         7: invokestatic  #142                // Method WidgetPreview:(Landroidx/compose/runtime/Composer;I)V
+        10: getstatic     #76                 // Field kotlin/Unit.INSTANCE:Lkotlin/Unit;
         13: areturn
 }
