class_version major=61 minor=0
this_class    InputKt
super_class   java/lang/Object
access_flags  0x0031
method        configure (Ljava/lang/String;I)V 0x0019
  code        max_stack=2 max_locals=2
    0000 op_0x2A
    0001 ldc "host"
    0003 invokestatic Method(kotlin/jvm/internal/Intrinsics.checkNotNullParameter:(Ljava/lang/Object;Ljava/lang/String;)V)
    0006 op_0x2A
    0007 op_0x1B
    0008 op_0xBA
    0009 nop
    0010 op_0x1B
    0011 nop
    0012 nop
    0013 getstatic Field(java/lang/System.out:Ljava/io/PrintStream;)
    0016 op_0x5F
    0017 invokevirtual Method(java/io/PrintStream.println:(Ljava/lang/Object;)V)
    0020 return
  attr        RuntimeInvisibleParameterAnnotations (9 bytes)
method        configure$default (Ljava/lang/String;IILjava/lang/Object;)V 0x1009
  code        max_stack=2 max_locals=4
    0000 op_0x1C
    0001 iconst_1
    0002 op_0x7E
    0003 op_0x99
    0004 nop
    0005 iconst_3
    0006 ldc "localhost"
    0008 op_0x4B
    0009 op_0x1C
    0010 iconst_2
    0011 op_0x7E
    0012 op_0x99
    0013 nop
    0014 iconst_4
    0015 sipush 8080
    0018 op_0x3C
    0019 op_0x2A
    0020 op_0x1B
    0021 invokestatic Method(InputKt.configure:(Ljava/lang/String;I)V)
    0024 return
    sub_attr  StackMapTable (4 bytes)
method        main ()V 0x0019
  code        max_stack=4 max_locals=0
    0000 aconst_null
    0001 iconst_0
    0002 iconst_3
    0003 aconst_null
    0004 invokestatic Method(InputKt.configure$default:(Ljava/lang/String;IILjava/lang/Object;)V)
    0007 ldc "example.com"
    0009 iconst_0
    0010 iconst_2
    0011 aconst_null
    0012 invokestatic Method(InputKt.configure$default:(Ljava/lang/String;IILjava/lang/Object;)V)
    0015 ldc "example.com"
    0017 sipush 443
    0020 invokestatic Method(InputKt.configure:(Ljava/lang/String;I)V)
    0023 return
method        main ([Ljava/lang/String;)V 0x1009
  code        max_stack=0 max_locals=1
    0000 invokestatic Method(InputKt.main:()V)
    0003 return
class_attr    BootstrapMethods (8 bytes)
