class_version major=61 minor=0
this_class    RGB
super_class   java/lang/Object
access_flags  0x0031
field         b : I 0x0012
field         g : I 0x0012
field         r : I 0x0012
method        <init> (III)V 0x0001
  code        max_stack=2 max_locals=4
    0000 op_0x2A
    0001 invokespecial Method(java/lang/Object.<init>:()V)
    0004 op_0x2A
    0005 op_0x1B
    0006 op_0xB5
    0007 nop
    0008 op_0x0D
    0009 op_0x2A
    0010 op_0x1C
    0011 op_0xB5
    0012 nop
    0013 bipush 42
    0015 op_0x1D
    0016 op_0xB5
    0017 nop
    0018 op_0x13
    0019 return
method        component1 ()I 0x0011
  code        max_stack=1 max_locals=1
    0000 op_0x2A
    0001 op_0xB4
    0002 nop
    0003 op_0x0D
    0004 op_0xAC
method        component2 ()I 0x0011
  code        max_stack=1 max_locals=1
    0000 op_0x2A
    0001 op_0xB4
    0002 nop
    0003 bipush -84
method        component3 ()I 0x0011
  code        max_stack=1 max_locals=1
    0000 op_0x2A
    0001 op_0xB4
    0002 nop
    0003 op_0x13
    0004 op_0xAC
method        copy (III)LRGB; 0x0011
  code        max_stack=5 max_locals=4
    0000 op_0xBB
    0001 nop
    0002 iconst_m1
    0003 op_0x59
    0004 op_0x1B
    0005 op_0x1C
    0006 op_0x1D
    0007 invokespecial Method(RGB.<init>:(III)V)
    0010 op_0xB0
  attr        RuntimeInvisibleAnnotations (6 bytes)
method        copy$default (LRGB;IIIILjava/lang/Object;)LRGB; 0x1009
  code        max_stack=4 max_locals=6
    0000 iload 4
    0002 iconst_1
    0003 op_0x7E
    0004 op_0x99
    0005 nop
    0006 iconst_5
    0007 op_0x2A
    0008 op_0xB4
    0009 nop
    0010 op_0x0D
    0011 op_0x3C
    0012 iload 4
    0014 iconst_2
    0015 op_0x7E
    0016 op_0x99
    0017 nop
    0018 iconst_5
    0019 op_0x2A
    0020 op_0xB4
    0021 nop
    0022 bipush 61
    0024 iload 4
    0026 iconst_4
    0027 op_0x7E
    0028 op_0x99
    0029 nop
    0030 iconst_5
    0031 op_0x2A
    0032 op_0xB4
    0033 nop
    0034 ldc_w #15914
    0037 op_0x1B
    0038 op_0x1C
    0039 op_0x1D
    0040 invokevirtual Method(RGB.copy:(III)LRGB;)
    0043 op_0xB0
    sub_attr  StackMapTable (5 bytes)
method        equals (Ljava/lang/Object;)Z 0x0001
  code        max_stack=2 max_locals=3
    0000 op_0x2A
    0001 op_0x2B
    0002 op_0xA6
    0003 nop
    0004 iconst_2
    0005 iconst_1
    0006 op_0xAC
    0007 op_0x2B
    0008 op_0xC1
    0009 nop
    0010 iconst_m1
    0011 op_0x9A
    0012 nop
    0013 iconst_2
    0014 iconst_0
    0015 op_0xAC
    0016 op_0x2B
    0017 op_0xC0
    0018 nop
    0019 iconst_m1
    0020 op_0x4D
    0021 op_0x2A
    0022 op_0xB4
    0023 nop
    0024 op_0x0D
    0025 op_0x2C
    0026 op_0xB4
    0027 nop
    0028 op_0x0D
    0029 op_0x9F
    0030 nop
    0031 iconst_2
    0032 iconst_0
    0033 op_0xAC
    0034 op_0x2A
    0035 op_0xB4
    0036 nop
    0037 bipush 44
    0039 op_0xB4
    0040 nop
    0041 bipush -97
    0043 nop
    0044 iconst_2
    0045 iconst_0
    0046 op_0xAC
    0047 op_0x2A
    0048 op_0xB4
    0049 nop
    0050 ldc_w #11444
    0053 nop
    0054 ldc_w #40704
    0057 iconst_2
    0058 iconst_0
    0059 op_0xAC
    0060 iconst_1
    0061 op_0xAC
    sub_attr  StackMapTable (12 bytes)
  attr        RuntimeInvisibleParameterAnnotations (7 bytes)
method        getB ()I 0x0011
  code        max_stack=1 max_locals=1
    0000 op_0x2A
    0001 op_0xB4
    0002 nop
    0003 op_0x13
    0004 op_0xAC
method        getG ()I 0x0011
  code        max_stack=1 max_locals=1
    0000 op_0x2A
    0001 op_0xB4
    0002 nop
    0003 bipush -84
method        getR ()I 0x0011
  code        max_stack=1 max_locals=1
    0000 op_0x2A
    0001 op_0xB4
    0002 nop
    0003 op_0x0D
    0004 op_0xAC
method        hashCode ()I 0x0001
  code        max_stack=2 max_locals=2
    0000 op_0x2A
    0001 op_0xB4
    0002 nop
    0003 op_0x0D
    0004 invokestatic Method(java/lang/Integer.hashCode:(I)I)
    0007 op_0x3C
    0008 op_0x1B
    0009 bipush 31
    0011 imul
    0012 op_0x2A
    0013 op_0xB4
    0014 nop
    0015 bipush -72
    0017 nop
    0018 op_0x39
    0019 iadd
    0020 op_0x3C
    0021 op_0x1B
    0022 bipush 31
    0024 imul
    0025 op_0x2A
    0026 op_0xB4
    0027 nop
    0028 ldc_w #47104
    0031 op_0x39
    0032 iadd
    0033 op_0x3C
    0034 op_0x1B
    0035 op_0xAC
method        toString ()Ljava/lang/String; 0x0001
  code        max_stack=3 max_locals=1
    0000 op_0x2A
    0001 op_0xB4
    0002 nop
    0003 op_0x0D
    0004 op_0x2A
    0005 op_0xB4
    0006 nop
    0007 bipush 42
    0009 op_0xB4
    0010 nop
    0011 ldc_w #47616
    0014 op_0x33
    0015 nop
    0016 nop
    0017 op_0xB0
  attr        RuntimeInvisibleAnnotations (6 bytes)
class_attr    BootstrapMethods (8 bytes)
