class_version major=61 minor=0
this_class    InputKt
super_class   java/lang/Object
access_flags  0x0031
method        describe (LChannel;)Ljava/lang/String; 0x0019
  code        max_stack=2 max_locals=1
    0000 aload_0
    0001 ldc "c"
    0003 invokestatic Method(kotlin/jvm/internal/Intrinsics.checkNotNullParameter:(Ljava/lang/Object;Ljava/lang/String;)V)
    0006 aload_0
    0007 getstatic Field(InputKt$WhenMappings.$EnumSwitchMapping$0:[I)
    0010 swap
    0011 invokevirtual Method(Channel.ordinal:()I)
    0014 iaload
    0015 tableswitch default=55 low=1 high=3 1=40 2=45 3=50
    0040 ldc "alpha"
    0042 goto 63
    0045 ldc "beta"
    0047 goto 63
    0050 ldc "gamma"
    0052 goto 63
    0055 new Class(kotlin/NoWhenBranchMatchedException)
    0058 dup
    0059 invokespecial Method(kotlin/NoWhenBranchMatchedException.<init>:()V)
    0062 athrow
    0063 areturn
    sub_attr  StackMapTable (10 bytes)
  attr        RuntimeInvisibleAnnotations (6 bytes)
  attr        RuntimeInvisibleParameterAnnotations (7 bytes)
method        main ()V 0x0019
  code        max_stack=2 max_locals=0
    0000 getstatic Field(Channel.ALPHA:LChannel;)
    0003 invokestatic Method(InputKt.describe:(LChannel;)Ljava/lang/String;)
    0006 getstatic Field(java/lang/System.out:Ljava/io/PrintStream;)
    0009 swap
    0010 invokevirtual Method(java/io/PrintStream.println:(Ljava/lang/Object;)V)
    0013 getstatic Field(Channel.BETA:LChannel;)
    0016 invokestatic Method(InputKt.describe:(LChannel;)Ljava/lang/String;)
    0019 getstatic Field(java/lang/System.out:Ljava/io/PrintStream;)
    0022 swap
    0023 invokevirtual Method(java/io/PrintStream.println:(Ljava/lang/Object;)V)
    0026 getstatic Field(Channel.GAMMA:LChannel;)
    0029 invokestatic Method(InputKt.describe:(LChannel;)Ljava/lang/String;)
    0032 getstatic Field(java/lang/System.out:Ljava/io/PrintStream;)
    0035 swap
    0036 invokevirtual Method(java/io/PrintStream.println:(Ljava/lang/Object;)V)
    0039 return
method        main ([Ljava/lang/String;)V 0x1009
  code        max_stack=0 max_locals=1
    0000 invokestatic Method(InputKt.main:()V)
    0003 return
class_attr    InnerClasses (10 bytes)
