class_version major=61 minor=0
this_class    test/InputKt
super_class   java/lang/Object
access_flags  0x0031
method        main ()V 0x0019
  code        max_stack=3 max_locals=2
    0000 new Class(test/MyDensity)
    0003 dup
    0004 invokespecial Method(test/MyDensity.<init>:()V)
    0007 astore_0
    0008 new Class(test/Dp)
    0011 dup
    0012 ldc float(10)
    0014 invokespecial Method(test/Dp.<init>:(F)V)
    0017 astore_1
    0018 aload_0
    0019 checkcast Class(test/Density)
    0022 aload_1
    0023 invokestatic Method(test/InputKt.measureIt:(Ltest/Density;Ltest/Dp;)I)
    0026 istore_1
    0027 getstatic Field(java/lang/System.out:Ljava/io/PrintStream;)
    0030 iload_1
    0031 invokevirtual Method(java/io/PrintStream.println:(I)V)
    0034 return
method        main ([Ljava/lang/String;)V 0x1009
  code        max_stack=0 max_locals=1
    0000 invokestatic Method(test/InputKt.main:()V)
    0003 return
method        measureIt (Ltest/Density;Ltest/Dp;)I 0x0019
  code        max_stack=2 max_locals=2
    0000 aload_0
    0001 ldc "<this>"
    0003 invokestatic Method(kotlin/jvm/internal/Intrinsics.checkNotNullParameter:(Ljava/lang/Object;Ljava/lang/String;)V)
    0006 aload_1
    0007 ldc "dp"
    0009 invokestatic Method(kotlin/jvm/internal/Intrinsics.checkNotNullParameter:(Ljava/lang/Object;Ljava/lang/String;)V)
    0012 aload_0
    0013 aload_1
    0014 invokeinterface InterfaceMethod(test/Density.roundToPx:(Ltest/Dp;)I)
    0019 ireturn
  attr        RuntimeInvisibleParameterAnnotations (13 bytes)
