class_version major=61 minor=0
this_class    InputKt
super_class   java/lang/Object
access_flags  0x0031
method        countVowels (Ljava/lang/String;)I 0x0019
  code        max_stack=2 max_locals=10
    0000 aload_0
    0001 ldc "s"
    0003 invokestatic Method(kotlin/jvm/internal/Intrinsics.checkNotNullParameter:(Ljava/lang/Object;Ljava/lang/String;)V)
    0006 iconst_0
    0007 istore_1
    0008 iload_1
    0009 istore_2
<<<<<<< Updated upstream
    0010 aload_0
    0011 ldc "hello"
    0013 invokestatic Method(kotlin/jvm/internal/Intrinsics.areEqual:(Ljava/lang/Object;Ljava/lang/Object;)Z)
    0016 istore_3
    0017 iload_3
    0018 ifeq 27
    0021 iconst_2
    0022 istore 4
    0024 iload 4
    0026 ireturn
    0027 aload_0
    0028 ldc "world"
    0030 invokestatic Method(kotlin/jvm/internal/Intrinsics.areEqual:(Ljava/lang/Object;Ljava/lang/Object;)Z)
    0033 istore 5
    0035 iload 5
    0037 ifeq 46
    0040 iconst_1
    0041 istore 6
    0043 iload 6
    0045 ireturn
    0046 aload_0
    0047 ldc "kotlin"
    0049 invokestatic Method(kotlin/jvm/internal/Intrinsics.areEqual:(Ljava/lang/Object;Ljava/lang/Object;)Z)
    0052 istore 7
    0054 iload 7
    0056 ifeq 65
    0059 iconst_2
    0060 istore 8
    0062 iload 8
    0064 ireturn
    0065 iload_2
    0066 istore 9
    0068 iload 9
    0070 ireturn
    sub_attr  StackMapTable (18 bytes)
=======
    0010 ldc "hello"
    0012 astore_3
    0013 aload_0
    0014 aload_3
    0015 invokestatic Method(kotlin/jvm/internal/Intrinsics.areEqual:(Ljava/lang/Object;Ljava/lang/Object;)Z)
    0018 istore 4
    0020 iload 4
    0022 ifeq 31
    0025 iconst_2
    0026 istore 5
    0028 iload 5
    0030 ireturn
    0031 ldc "world"
    0033 astore 6
    0035 aload_0
    0036 aload 6
    0038 invokestatic Method(kotlin/jvm/internal/Intrinsics.areEqual:(Ljava/lang/Object;Ljava/lang/Object;)Z)
    0041 istore 7
    0043 iload 7
    0045 ifeq 54
    0048 iconst_1
    0049 istore 8
    0051 iload 8
    0053 ireturn
    0054 ldc "kotlin"
    0056 astore 9
    0058 aload_0
    0059 aload 9
    0061 invokestatic Method(kotlin/jvm/internal/Intrinsics.areEqual:(Ljava/lang/Object;Ljava/lang/Object;)Z)
    0064 istore 10
    0066 iload 10
    0068 ifeq 77
    0071 iconst_2
    0072 istore 11
    0074 iload 11
    0076 ireturn
    0077 iload_2
    0078 istore 12
    0080 iload 12
    0082 ireturn
    sub_attr  StackMapTable (34 bytes)
>>>>>>> Stashed changes
  attr        RuntimeInvisibleParameterAnnotations (7 bytes)
method        main ()V 0x0019
  code        max_stack=2 max_locals=1
    0000 ldc "hello"
    0002 invokestatic Method(InputKt.countVowels:(Ljava/lang/String;)I)
    0005 istore_0
    0006 getstatic Field(java/lang/System.out:Ljava/io/PrintStream;)
    0009 iload_0
    0010 invokevirtual Method(java/io/PrintStream.println:(I)V)
    0013 ldc "world"
    0015 invokestatic Method(InputKt.countVowels:(Ljava/lang/String;)I)
    0018 istore_0
    0019 getstatic Field(java/lang/System.out:Ljava/io/PrintStream;)
    0022 iload_0
    0023 invokevirtual Method(java/io/PrintStream.println:(I)V)
    0026 ldc "kotlin"
    0028 invokestatic Method(InputKt.countVowels:(Ljava/lang/String;)I)
    0031 istore_0
    0032 getstatic Field(java/lang/System.out:Ljava/io/PrintStream;)
    0035 iload_0
    0036 invokevirtual Method(java/io/PrintStream.println:(I)V)
    0039 return
method        main ([Ljava/lang/String;)V 0x1009
  code        max_stack=0 max_locals=1
    0000 invokestatic Method(InputKt.main:()V)
    0003 return
