class_version major=61 minor=0
this_class    InputKt
super_class   java/lang/Object
access_flags  0x0031
method        count (Ljava/util/List;I)I 0x0019
  code        max_stack=2 max_locals=4
    0000 aload_0
    0001 ldc "items"
    0003 invokestatic Method(kotlin/jvm/internal/Intrinsics.checkNotNullParameter:(Ljava/lang/Object;Ljava/lang/String;)V)
    0006 iconst_0
    0007 istore_2
    0008 aload_0
    0009 invokeinterface InterfaceMethod(java/lang/Iterable.iterator:()Ljava/util/Iterator;)
    0014 astore_3
    0015 aload_3
    0016 invokeinterface InterfaceMethod(java/util/Iterator.hasNext:()Z)
    0021 ifeq 43
    0024 aload_3
    0025 invokeinterface InterfaceMethod(java/util/Iterator.next:()Ljava/lang/Object;)
    0030 checkcast Class(java/lang/Integer)
    0033 invokevirtual Method(java/lang/Integer.intValue:()I)
    0036 iload_1
    0037 if_icmple 15
    0040 iinc 2 1
    0043 iload_2
    0044 ireturn
    sub_attr  StackMapTable (10 bytes)
  attr        Signature (2 bytes)
  attr        RuntimeInvisibleParameterAnnotations (9 bytes)
method        main ()V 0x0019
  code        max_stack=3 max_locals=14
    0000 bipush 10
    0002 anewarray Class(java/lang/Object)
    0005 astore_0
    0006 iconst_1
    0007 invokestatic Method(java/lang/Integer.valueOf:(I)Ljava/lang/Integer;)
    0010 astore_1
    0011 aload_0
    0012 iconst_0
    0013 aload_1
    0014 aastore
    0015 iconst_2
    0016 invokestatic Method(java/lang/Integer.valueOf:(I)Ljava/lang/Integer;)
    0019 astore_1
    0020 aload_0
    0021 iconst_1
    0022 aload_1
    0023 aastore
    0024 iconst_3
    0025 invokestatic Method(java/lang/Integer.valueOf:(I)Ljava/lang/Integer;)
    0028 astore_1
    0029 aload_0
    0030 iconst_2
    0031 aload_1
    0032 aastore
    0033 iconst_4
    0034 invokestatic Method(java/lang/Integer.valueOf:(I)Ljava/lang/Integer;)
    0037 astore_1
    0038 aload_0
    0039 iconst_3
    0040 aload_1
    0041 aastore
    0042 iconst_5
    0043 invokestatic Method(java/lang/Integer.valueOf:(I)Ljava/lang/Integer;)
    0046 astore_1
    0047 aload_0
    0048 iconst_4
    0049 aload_1
    0050 aastore
    0051 bipush 6
    0053 invokestatic Method(java/lang/Integer.valueOf:(I)Ljava/lang/Integer;)
    0056 astore_1
    0057 aload_0
    0058 iconst_5
    0059 aload_1
    0060 aastore
    0061 bipush 7
    0063 invokestatic Method(java/lang/Integer.valueOf:(I)Ljava/lang/Integer;)
    0066 astore_1
    0067 aload_0
    0068 bipush 6
    0070 aload_1
    0071 aastore
    0072 bipush 8
    0074 invokestatic Method(java/lang/Integer.valueOf:(I)Ljava/lang/Integer;)
    0077 astore_1
    0078 aload_0
    0079 bipush 7
    0081 aload_1
    0082 aastore
    0083 bipush 9
    0085 invokestatic Method(java/lang/Integer.valueOf:(I)Ljava/lang/Integer;)
    0088 astore_1
    0089 aload_0
    0090 bipush 8
    0092 aload_1
    0093 aastore
    0094 bipush 10
    0096 invokestatic Method(java/lang/Integer.valueOf:(I)Ljava/lang/Integer;)
    0099 astore_1
    0100 aload_0
    0101 bipush 9
    0103 aload_1
    0104 aastore
    0105 aload_0
    0106 invokestatic Method(kotlin/collections/CollectionsKt.listOf:([Ljava/lang/Object;)Ljava/util/List;)
    0109 astore 11
    0111 aload 11
    0113 iconst_5
    0114 invokestatic Method(InputKt.count:(Ljava/util/List;I)I)
    0117 istore_0
    0118 getstatic Field(java/lang/System.out:Ljava/io/PrintStream;)
    0121 iload_0
    0122 invokevirtual Method(java/io/PrintStream.println:(I)V)
    0125 new Class(Counter)
    0128 dup
    0129 invokespecial Method(Counter.<init>:()V)
    0132 astore 13
    0134 aload 13
    0136 iconst_5
    0137 invokevirtual Method(Counter.maybeBump:(I)V)
    0140 aload 13
    0142 bipush -3
    0144 invokevirtual Method(Counter.maybeBump:(I)V)
    0147 aload 13
    0149 bipush 10
    0151 invokevirtual Method(Counter.maybeBump:(I)V)
    0154 aload 13
    0156 invokevirtual Method(Counter.getTotal:()I)
    0159 istore_0
    0160 getstatic Field(java/lang/System.out:Ljava/io/PrintStream;)
    0163 iload_0
    0164 invokevirtual Method(java/io/PrintStream.println:(I)V)
    0167 return
method        main ([Ljava/lang/String;)V 0x1009
  code        max_stack=0 max_locals=1
    0000 invokestatic Method(InputKt.main:()V)
    0003 return
