class_version major=61 minor=0
this_class    InputKt
super_class   java/lang/Object
access_flags  0x0031
method        format (ILjava/lang/String;Ljava/lang/String;)Ljava/lang/String; 0x0019
  code        max_stack=3 max_locals=3
    0000 op_0x2B
    0001 ldc "prefix"
    0003 invokestatic Method(kotlin/jvm/internal/Intrinsics.checkNotNullParameter:(Ljava/lang/Object;Ljava/lang/String;)V)
    0006 op_0x2C
    0007 ldc "suffix"
    0009 invokestatic Method(kotlin/jvm/internal/Intrinsics.checkNotNullParameter:(Ljava/lang/Object;Ljava/lang/String;)V)
    0012 op_0x2B
    0013 op_0x1A
    0014 op_0x2C
    0015 op_0xBA
    0016 nop
    0017 op_0x1D
    0018 nop
    0019 nop
    0020 op_0xB0
  attr        RuntimeInvisibleAnnotations (6 bytes)
  attr        RuntimeInvisibleParameterAnnotations (15 bytes)
method        format$default (ILjava/lang/String;Ljava/lang/String;ILjava/lang/Object;)Ljava/lang/String; 0x1009
  code        max_stack=3 max_locals=5
    0000 op_0x1D
    0001 iconst_2
    0002 op_0x7E
    0003 op_0x99
    0004 nop
    0005 iconst_3
    0006 ldc "["
    0008 op_0x4C
    0009 op_0x1D
    0010 iconst_4
    0011 op_0x7E
    0012 op_0x99
    0013 nop
    0014 iconst_3
    0015 ldc "]"
    0017 op_0x4D
    0018 op_0x1A
    0019 op_0x2B
    0020 op_0x2C
    0021 invokestatic Method(InputKt.format:(ILjava/lang/String;Ljava/lang/String;)Ljava/lang/String;)
    0024 op_0xB0
    sub_attr  StackMapTable (4 bytes)
method        main ()V 0x0019
  code        max_stack=5 max_locals=0
    0000 bipush 42
    0002 aconst_null
    0003 aconst_null
    0004 bipush 6
    0006 aconst_null
    0007 invokestatic Method(InputKt.format$default:(ILjava/lang/String;Ljava/lang/String;ILjava/lang/Object;)Ljava/lang/String;)
    0010 getstatic Field(java/lang/System.out:Ljava/io/PrintStream;)
    0013 op_0x5F
    0014 invokevirtual Method(java/io/PrintStream.println:(Ljava/lang/Object;)V)
    0017 bipush 42
    0019 ldc "("
    0021 aconst_null
    0022 iconst_4
    0023 aconst_null
    0024 invokestatic Method(InputKt.format$default:(ILjava/lang/String;Ljava/lang/String;ILjava/lang/Object;)Ljava/lang/String;)
    0027 getstatic Field(java/lang/System.out:Ljava/io/PrintStream;)
    0030 op_0x5F
    0031 invokevirtual Method(java/io/PrintStream.println:(Ljava/lang/Object;)V)
    0034 bipush 42
    0036 ldc "("
    0038 ldc ")"
    0040 invokestatic Method(InputKt.format:(ILjava/lang/String;Ljava/lang/String;)Ljava/lang/String;)
    0043 getstatic Field(java/lang/System.out:Ljava/io/PrintStream;)
    0046 op_0x5F
    0047 invokevirtual Method(java/io/PrintStream.println:(Ljava/lang/Object;)V)
    0050 return
method        main ([Ljava/lang/String;)V 0x1009
  code        max_stack=0 max_locals=1
    0000 invokestatic Method(InputKt.main:()V)
    0003 return
class_attr    BootstrapMethods (8 bytes)
