class_version major=61 minor=0
this_class    Multiplier
super_class   java/lang/Object
access_flags  0x0021
field         factor : I 0x0001
method        <init> (I)V 0x0001
  code        max_stack=2 max_locals=2
    0000 aload_0
    0001 invokespecial Method(java/lang/Object.<init>:()V)
    0004 aload_0
    0005 iload_1
    0006 putfield Field(Multiplier.factor:I)
    0009 return
method        getFactor ()I 0x0001
  code        max_stack=1 max_locals=1
    0000 aload_0
    0001 getfield Field(Multiplier.factor:I)
    0004 ireturn
method        multiply (I)I 0x0001
  code        max_stack=3 max_locals=3
    0000 aload_0
    0001 getfield Field(Multiplier.factor:I)
    0004 istore_2
    0005 iload_1
    0006 iload_2
    0007 imul
    0008 aload_0
    0009 iload_2
    0010 putfield Field(Multiplier.factor:I)
    0013 ireturn
