class_version major=61 minor=0
this_class    InputKt
super_class   java/lang/Object
access_flags  0x0031
method        main ()V 0x0019
  code        max_stack=6 max_locals=2
    0000 ldc "Hello, World!"
    0002 astore_0
    0003 aload_0
    0004 ldc "World"
    0006 ldc "Kotlin"
    0008 iconst_0
    0009 iconst_4
    0010 aconst_null
    0011 invokestatic Method(kotlin/text/StringsKt.replace$default:(Ljava/lang/String;Ljava/lang/String;Ljava/lang/String;ZILjava/lang/Object;)Ljava/lang/String;)
    0014 getstatic Field(java/lang/System.out:Ljava/io/PrintStream;)
    0017 op_0x5F
    0018 invokevirtual Method(java/io/PrintStream.println:(Ljava/lang/Object;)V)
    0021 aload_0
    0022 ldc "!"
    0024 ldc "?"
    0026 iconst_0
    0027 iconst_4
    0028 aconst_null
    0029 invokestatic Method(kotlin/text/StringsKt.replace$default:(Ljava/lang/String;Ljava/lang/String;Ljava/lang/String;ZILjava/lang/Object;)Ljava/lang/String;)
    0032 getstatic Field(java/lang/System.out:Ljava/io/PrintStream;)
    0035 op_0x5F
    0036 invokevirtual Method(java/io/PrintStream.println:(Ljava/lang/Object;)V)
    0039 aload_0
    0040 checkcast Class(java/lang/CharSequence)
    0043 ldc "World"
    0045 iconst_0
    0046 iconst_0
    0047 bipush 6
    0049 aconst_null
    0050 invokestatic Method(kotlin/text/StringsKt.indexOf$default:(Ljava/lang/CharSequence;Ljava/lang/String;IZILjava/lang/Object;)I)
    0053 istore_1
    0054 getstatic Field(java/lang/System.out:Ljava/io/PrintStream;)
    0057 iload_1
    0058 invokevirtual Method(java/io/PrintStream.println:(I)V)
    0061 aload_0
    0062 checkcast Class(java/lang/CharSequence)
    0065 ldc "l"
    0067 iconst_0
    0068 iconst_0
    0069 bipush 6
    0071 aconst_null
    0072 invokestatic Method(kotlin/text/StringsKt.lastIndexOf$default:(Ljava/lang/CharSequence;Ljava/lang/String;IZILjava/lang/Object;)I)
    0075 istore_1
    0076 getstatic Field(java/lang/System.out:Ljava/io/PrintStream;)
    0079 iload_1
    0080 invokevirtual Method(java/io/PrintStream.println:(I)V)
    0083 return
method        main ([Ljava/lang/String;)V 0x1009
  code        max_stack=0 max_locals=1
    0000 invokestatic Method(InputKt.main:()V)
    0003 return
