class_version major=61 minor=0
this_class    InputKt
super_class   java/lang/Object
access_flags  0x0031
method        main ()V 0x0019
  code        max_stack=3 max_locals=22
    0000 ldc "Hello, World!"
    0002 astore_1
    0003 ldc "World"
    0005 astore_2
    0006 ldc "Kotlin"
    0008 astore_3
    0009 aload_1
    0010 astore 4
    0012 ldc "World"
    0014 astore 5
    0016 ldc "Kotlin"
    0018 astore 6
    0020 aload 4
    0022 aload 5
    0024 aload 6
    0026 invokevirtual Method(java/lang/String.replace:(Ljava/lang/CharSequence;Ljava/lang/CharSequence;)Ljava/lang/String;)
    0029 astore 7
    0031 getstatic Field(java/lang/System.out:Ljava/io/PrintStream;)
    0034 aload 7
    0036 invokevirtual Method(java/io/PrintStream.println:(Ljava/lang/String;)V)
    0039 ldc "!"
    0041 astore 8
    0043 ldc "?"
    0045 astore 9
    0047 aload_1
    0048 astore 10
    0050 ldc "!"
    0052 astore 11
    0054 ldc "?"
    0056 astore 12
    0058 aload 10
    0060 aload 11
    0062 aload 12
    0064 invokevirtual Method(java/lang/String.replace:(Ljava/lang/CharSequence;Ljava/lang/CharSequence;)Ljava/lang/String;)
    0067 astore 13
    0069 getstatic Field(java/lang/System.out:Ljava/io/PrintStream;)
    0072 aload 13
    0074 invokevirtual Method(java/io/PrintStream.println:(Ljava/lang/String;)V)
    0077 ldc "World"
    0079 astore 14
    0081 aload_1
    0082 astore 15
    0084 ldc "World"
    0086 astore 16
    0088 aload 15
    0090 aload 16
    0092 invokevirtual Method(java/lang/String.indexOf:(Ljava/lang/String;)I)
    0095 istore 17
    0097 getstatic Field(java/lang/System.out:Ljava/io/PrintStream;)
    0100 iload 17
    0102 invokevirtual Method(java/io/PrintStream.println:(I)V)
    0105 ldc "l"
    0107 astore 18
    0109 aload_1
    0110 astore 19
    0112 ldc "l"
    0114 astore 20
    0116 aload 19
    0118 aload 20
    0120 invokevirtual Method(java/lang/String.lastIndexOf:(Ljava/lang/String;)I)
    0123 istore 21
    0125 getstatic Field(java/lang/System.out:Ljava/io/PrintStream;)
    0128 iload 21
    0130 invokevirtual Method(java/io/PrintStream.println:(I)V)
    0133 return
method        main ([Ljava/lang/String;)V 0x1009
  code        max_stack=0 max_locals=1
    0000 invokestatic Method(InputKt.main:()V)
    0003 return
