class_version major=61 minor=0
this_class    InputKt
super_class   java/lang/Object
access_flags  0x0031
method        applySimpleOp (C[IILjava/lang/StringBuilder;[I)V 0x0019
  code        max_stack=3 max_locals=9
    0000 aload_3
    0001 ldc "out"
    0003 invokestatic Method(kotlin/jvm/internal/Intrinsics.checkNotNullParameter:(Ljava/lang/Object;Ljava/lang/String;)V)
    0006 iload_0
    0007 bipush 62
    0009 if_icmpne 16
    0012 iconst_1
    0013 goto 17
    0016 iconst_0
    0017 istore 5
    0019 iconst_1
    0020 istore 6
    0022 iload 5
    0024 ifne 40
    0027 iload_0
    0028 bipush 60
    0030 if_icmpne 37
    0033 iconst_1
    0034 goto 38
    0037 iconst_0
    0038 istore 6
    0040 iload 6
    0042 ifeq 53
    0045 iload_0
    0046 iload_2
    0047 aload 4
    0049 invokestatic Method(InputKt.movePtr:(CI[I)V)
    0052 return
    0053 iload_0
    0054 bipush 43
    0056 if_icmpne 63
    0059 iconst_1
    0060 goto 64
    0063 iconst_0
    0064 istore 7
    0066 iconst_1
    0067 istore 8
    0069 iload 7
    0071 ifne 87
    0074 iload_0
    0075 bipush 45
    0077 if_icmpne 84
    0080 iconst_1
    0081 goto 85
    0084 iconst_0
    0085 istore 8
    0087 iload 8
    0089 ifeq 99
    0092 iload_0
    0093 aload_1
    0094 iload_2
    0095 invokestatic Method(InputKt.bumpCell:(C[II)V)
    0098 return
    0099 iload_0
    0100 bipush 46
    0102 if_icmpne 114
    0105 aload_3
    0106 aload_1
    0107 iload_2
    0108 iaload
    0109 i2c
    0110 invokevirtual Method(java/lang/StringBuilder.append:(C)Ljava/lang/StringBuilder;)
    0113 pop
    0114 return
    sub_attr  StackMapTable (27 bytes)
  attr        RuntimeInvisibleParameterAnnotations (15 bytes)
method        bracketJump (CLjava/lang/String;II)I 0x0019
  code        max_stack=2 max_locals=8
    0000 aload_1
    0001 ldc "program"
    0003 invokestatic Method(kotlin/jvm/internal/Intrinsics.checkNotNullParameter:(Ljava/lang/Object;Ljava/lang/String;)V)
    0006 iload_0
    0007 bipush 91
    0009 if_icmpne 16
    0012 iconst_1
    0013 goto 17
    0016 iconst_0
    0017 istore 4
    0019 iconst_0
    0020 istore 5
    0022 iload 4
    0024 ifeq 38
    0027 iload_2
    0028 ifne 35
    0031 iconst_1
    0032 goto 36
    0035 iconst_0
    0036 istore 5
    0038 iload 5
    0040 ifeq 49
    0043 aload_1
    0044 iload_3
    0045 invokestatic Method(InputKt.findMatchingClose:(Ljava/lang/String;I)I)
    0048 ireturn
    0049 iload_0
    0050 bipush 93
    0052 if_icmpne 59
    0055 iconst_1
    0056 goto 60
    0059 iconst_0
    0060 istore 6
    0062 iconst_0
    0063 istore 7
    0065 iload 6
    0067 ifeq 81
    0070 iload_2
    0071 ifeq 78
    0074 iconst_1
    0075 goto 79
    0078 iconst_0
    0079 istore 7
    0081 iload 7
    0083 ifeq 92
    0086 aload_1
    0087 iload_3
    0088 invokestatic Method(InputKt.findMatchingOpen:(Ljava/lang/String;I)I)
    0091 ireturn
    0092 iload_3
    0093 ireturn
    sub_attr  StackMapTable (26 bytes)
  attr        RuntimeInvisibleParameterAnnotations (13 bytes)
method        bumpCell (C[II)V 0x0019
  code        max_stack=3 max_locals=5
    0000 iload_0
    0001 bipush 43
    0003 if_icmpne 19
    0006 aload_1
    0007 iload_2
    0008 iaload
    0009 iconst_1
    0010 iadd
    0011 istore_3
    0012 aload_1
    0013 iload_2
    0014 iload_3
    0015 iastore
    0016 goto 31
    0019 aload_1
    0020 iload_2
    0021 iaload
    0022 iconst_1
    0023 isub
    0024 istore 4
    0026 aload_1
    0027 iload_2
    0028 iload 4
    0030 iastore
    0031 return
    sub_attr  StackMapTable (4 bytes)
method        deltaBackwardScan (C)I 0x0019
  code        max_stack=2 max_locals=1
    0000 iload_0
    0001 bipush 93
    0003 if_icmpne 8
    0006 iconst_1
    0007 ireturn
    0008 iload_0
    0009 bipush 91
    0011 if_icmpne 16
    0014 iconst_m1
    0015 ireturn
    0016 iconst_0
    0017 ireturn
    sub_attr  StackMapTable (4 bytes)
method        deltaForwardScan (C)I 0x0019
  code        max_stack=2 max_locals=1
    0000 iload_0
    0001 bipush 91
    0003 if_icmpne 8
    0006 iconst_1
    0007 ireturn
    0008 iload_0
    0009 bipush 93
    0011 if_icmpne 16
    0014 iconst_m1
    0015 ireturn
    0016 iconst_0
    0017 ireturn
    sub_attr  StackMapTable (4 bytes)
method        findMatchingClose (Ljava/lang/String;I)I 0x0019
  code        max_stack=3 max_locals=4
    0000 aload_0
    0001 ldc "program"
    0003 invokestatic Method(kotlin/jvm/internal/Intrinsics.checkNotNullParameter:(Ljava/lang/Object;Ljava/lang/String;)V)
    0006 iconst_1
    0007 istore_2
    0008 iload_1
    0009 istore_3
    0010 iload_2
    0011 ifle 31
    0014 iinc 3 1
    0017 iload_2
    0018 aload_0
    0019 iload_3
    0020 invokevirtual Method(java/lang/String.charAt:(I)C)
    0023 invokestatic Method(InputKt.deltaForwardScan:(C)I)
    0026 iadd
    0027 istore_2
    0028 goto 10
    0031 iload_3
    0032 ireturn
    sub_attr  StackMapTable (8 bytes)
  attr        RuntimeInvisibleParameterAnnotations (9 bytes)
method        findMatchingOpen (Ljava/lang/String;I)I 0x0019
  code        max_stack=3 max_locals=4
    0000 aload_0
    0001 ldc "program"
    0003 invokestatic Method(kotlin/jvm/internal/Intrinsics.checkNotNullParameter:(Ljava/lang/Object;Ljava/lang/String;)V)
    0006 iconst_1
    0007 istore_2
    0008 iload_1
    0009 istore_3
    0010 iload_2
    0011 ifle 31
    0014 iinc 3 -1
    0017 iload_2
    0018 aload_0
    0019 iload_3
    0020 invokevirtual Method(java/lang/String.charAt:(I)C)
    0023 invokestatic Method(InputKt.deltaBackwardScan:(C)I)
    0026 iadd
    0027 istore_2
    0028 goto 10
    0031 iload_3
    0032 ireturn
    sub_attr  StackMapTable (8 bytes)
  attr        RuntimeInvisibleParameterAnnotations (9 bytes)
method        main ()V 0x0019
  code        max_stack=2 max_locals=2
    0000 ldc "+++++++++++++++++++++++++++++++++++++++++++++++++++++++++++++++++."
    0002 ldc ""
    0004 invokestatic Method(InputKt.runBrainfuck:(Ljava/lang/String;Ljava/lang/String;)Ljava/lang/String;)
    0007 getstatic Field(java/lang/System.out:Ljava/io/PrintStream;)
    0010 swap
    0011 invokevirtual Method(java/io/PrintStream.println:(Ljava/lang/Object;)V)
    0014 ldc "++++++++[>++++[>++>+++>+++>+<<<<-]>+>+>->>+[<]<-]>>.>---.+++++++..+++.>>.<-.<.+++.------.--------.>>+.>++."
    0016 astore_0
    0017 aload_0
    0018 ldc ""
    0020 invokestatic Method(InputKt.runBrainfuck:(Ljava/lang/String;Ljava/lang/String;)Ljava/lang/String;)
    0023 getstatic Field(java/lang/System.out:Ljava/io/PrintStream;)
    0026 swap
    0027 invokevirtual Method(java/io/PrintStream.print:(Ljava/lang/Object;)V)
    0030 getstatic Field(java/lang/System.out:Ljava/io/PrintStream;)
    0033 invokevirtual Method(java/io/PrintStream.println:()V)
    0036 ldc ",.."
    0038 ldc "Z"
    0040 invokestatic Method(InputKt.runBrainfuck:(Ljava/lang/String;Ljava/lang/String;)Ljava/lang/String;)
    0043 getstatic Field(java/lang/System.out:Ljava/io/PrintStream;)
    0046 swap
    0047 invokevirtual Method(java/io/PrintStream.println:(Ljava/lang/Object;)V)
    0050 ldc ",>,[<+>-]<------------------------------------------------."
    0052 astore_1
    0053 aload_1
    0054 ldc "34"
    0056 invokestatic Method(InputKt.runBrainfuck:(Ljava/lang/String;Ljava/lang/String;)Ljava/lang/String;)
    0059 getstatic Field(java/lang/System.out:Ljava/io/PrintStream;)
    0062 swap
    0063 invokevirtual Method(java/io/PrintStream.println:(Ljava/lang/Object;)V)
    0066 return
method        main ([Ljava/lang/String;)V 0x1009
  code        max_stack=0 max_locals=1
    0000 invokestatic Method(InputKt.main:()V)
    0003 return
method        movePtr (CI[I)V 0x0019
  code        max_stack=3 max_locals=7
    0000 iload_0
    0001 bipush 62
    0003 if_icmpne 21
    0006 iconst_0
    0007 istore_3
    0008 iload_1
    0009 iconst_1
    0010 iadd
    0011 istore 4
    0013 aload_2
    0014 iload_3
    0015 iload 4
    0017 iastore
    0018 goto 35
    0021 iconst_0
    0022 istore 5
    0024 iload_1
    0025 iconst_1
    0026 isub
    0027 istore 6
    0029 aload_2
    0030 iload 5
    0032 iload 6
    0034 iastore
    0035 return
    sub_attr  StackMapTable (4 bytes)
method        readByte (Ljava/lang/String;[II[I)V 0x0019
  code        max_stack=3 max_locals=11
    0000 aload_0
    0001 ldc "input"
    0003 invokestatic Method(kotlin/jvm/internal/Intrinsics.checkNotNullParameter:(Ljava/lang/Object;Ljava/lang/String;)V)
    0006 iconst_2
    0007 istore 4
    0009 aload_3
    0010 iload 4
    0012 iaload
    0013 istore 5
    0015 aload_0
    0016 invokevirtual Method(java/lang/String.length:()I)
    0019 istore 6
    0021 iload 5
    0023 iload 6
    0025 if_icmpge 59
    0028 aload_0
    0029 iload 5
    0031 invokevirtual Method(java/lang/String.charAt:(I)C)
    0034 istore 7
    0036 aload_1
    0037 iload_2
    0038 iload 7
    0040 iastore
    0041 iconst_2
    0042 istore 8
    0044 iload 5
    0046 iconst_1
    0047 iadd
    0048 istore 9
    0050 aload_3
    0051 iload 8
    0053 iload 9
    0055 iastore
    0056 goto 67
    0059 iconst_0
    0060 istore 10
    0062 aload_1
    0063 iload_2
    0064 iload 10
    0066 iastore
    0067 return
    sub_attr  StackMapTable (9 bytes)
  attr        RuntimeInvisibleParameterAnnotations (13 bytes)
method        runBrainfuck (Ljava/lang/String;Ljava/lang/String;)Ljava/lang/String; 0x0019
  code        max_stack=5 max_locals=8
    0000 aload_0
    0001 ldc "program"
    0003 invokestatic Method(kotlin/jvm/internal/Intrinsics.checkNotNullParameter:(Ljava/lang/Object;Ljava/lang/String;)V)
    0006 aload_1
    0007 ldc "input"
    0009 invokestatic Method(kotlin/jvm/internal/Intrinsics.checkNotNullParameter:(Ljava/lang/Object;Ljava/lang/String;)V)
    0012 sipush 30000
    0015 newarray int
    0017 astore_2
    0018 iconst_3
    0019 newarray int
    0021 astore_3
    0022 new Class(java/lang/StringBuilder)
    0025 dup
    0026 invokespecial Method(java/lang/StringBuilder.<init>:()V)
    0029 astore 4
    0031 iconst_1
    0032 istore 5
    0034 aload_3
    0035 iload 5
    0037 iaload
    0038 istore 6
    0040 aload_0
    0041 invokevirtual Method(java/lang/String.length:()I)
    0044 istore 7
    0046 iload 6
    0048 iload 7
    0050 if_icmpge 65
    0053 aload_0
    0054 aload_1
    0055 aload_2
    0056 aload_3
    0057 aload 4
    0059 invokestatic Method(InputKt.stepBf:(Ljava/lang/String;Ljava/lang/String;[I[ILjava/lang/StringBuilder;)V)
    0062 goto 31
    0065 aload 4
    0067 invokevirtual Method(java/lang/StringBuilder.toString:()Ljava/lang/String;)
    0070 dup
    0071 ldc "toString(...)"
    0073 invokestatic Method(kotlin/jvm/internal/Intrinsics.checkNotNullExpressionValue:(Ljava/lang/Object;Ljava/lang/String;)V)
    0076 areturn
    sub_attr  StackMapTable (20 bytes)
  attr        RuntimeInvisibleAnnotations (6 bytes)
  attr        RuntimeInvisibleParameterAnnotations (13 bytes)
method        stepBf (Ljava/lang/String;Ljava/lang/String;[I[ILjava/lang/StringBuilder;)V 0x0019
  code        max_stack=5 max_locals=17
    0000 aload_0
    0001 ldc "program"
    0003 invokestatic Method(kotlin/jvm/internal/Intrinsics.checkNotNullParameter:(Ljava/lang/Object;Ljava/lang/String;)V)
    0006 aload_1
    0007 ldc "input"
    0009 invokestatic Method(kotlin/jvm/internal/Intrinsics.checkNotNullParameter:(Ljava/lang/Object;Ljava/lang/String;)V)
    0012 aload 4
    0014 ldc "out"
    0016 invokestatic Method(kotlin/jvm/internal/Intrinsics.checkNotNullParameter:(Ljava/lang/Object;Ljava/lang/String;)V)
    0019 iconst_1
    0020 istore 5
    0022 aload_3
    0023 iload 5
    0025 iaload
    0026 istore 6
    0028 iconst_0
    0029 istore 7
    0031 aload_3
    0032 iload 7
    0034 iaload
    0035 istore 8
    0037 aload_0
    0038 iload 6
    0040 invokevirtual Method(java/lang/String.charAt:(I)C)
    0043 istore 9
    0045 iload 9
    0047 bipush 44
    0049 if_icmpne 63
    0052 aload_1
    0053 aload_2
    0054 iload 8
    0056 aload_3
    0057 invokestatic Method(InputKt.readByte:(Ljava/lang/String;[II[I)V)
    0060 goto 74
    0063 iload 9
    0065 aload_2
    0066 iload 8
    0068 aload 4
    0070 aload_3
    0071 invokestatic Method(InputKt.applySimpleOp:(C[IILjava/lang/StringBuilder;[I)V)
    0074 iconst_1
    0075 istore 10
    0077 iconst_0
    0078 istore 11
    0080 aload_3
    0081 iload 11
    0083 iaload
    0084 istore 12
    0086 aload_2
    0087 iload 12
    0089 iaload
    0090 istore 13
    0092 iconst_1
    0093 istore 14
    0095 aload_3
    0096 iload 14
    0098 iaload
    0099 istore 15
    0101 iload 9
    0103 aload_0
    0104 iload 13
    0106 iload 15
    0108 invokestatic Method(InputKt.bracketJump:(CLjava/lang/String;II)I)
    0111 iconst_1
    0112 iadd
    0113 istore 16
    0115 aload_3
    0116 iload 10
    0118 iload 16
    0120 iastore
    0121 return
    sub_attr  StackMapTable (30 bytes)
  attr        RuntimeInvisibleParameterAnnotations (23 bytes)
