class_version major=61 minor=0
this_class    InputKt
super_class   java/lang/Object
access_flags  0x0031
method        main ()V 0x0019
  code        max_stack=2 max_locals=16
    0000 ldc "hello"
    0002 astore_0
<<<<<<< Updated upstream
    0003 aload_0
    0004 aconst_null
    0005 if_acmpeq 12
    0008 iconst_1
    0009 goto 13
    0012 iconst_0
    0013 istore_1
    0014 iload_1
    0015 ifeq 41
    0018 aload_0
    0019 checkcast Class(java/lang/String)
    0022 astore_2
    0023 aload_2
    0024 invokevirtual Method(java/lang/String.length:()I)
    0027 istore_3
    0028 iload_3
    0029 invokestatic Method(java/lang/Integer.valueOf:(I)Ljava/lang/Integer;)
    0032 astore 4
    0034 aload 4
    0036 astore 5
    0038 goto 44
    0041 aconst_null
    0042 astore 5
    0044 getstatic Field(java/lang/System.out:Ljava/io/PrintStream;)
    0047 aload 5
    0049 invokevirtual Method(java/io/PrintStream.println:(Ljava/lang/Object;)V)
    0052 aload_0
    0053 aconst_null
    0054 if_acmpne 61
    0057 iconst_1
    0058 goto 62
    0061 iconst_0
    0062 istore 6
    0064 iload 6
    0066 ifeq 81
    0069 new Class(java/lang/NullPointerException)
    0072 dup
    0073 invokespecial Method(java/lang/NullPointerException.<init>:()V)
    0076 astore 7
    0078 aload 7
    0080 athrow
    0081 aload_0
    0082 checkcast Class(java/lang/String)
    0085 astore 8
    0087 aload 8
    0089 invokevirtual Method(java/lang/String.toUpperCase:()Ljava/lang/String;)
    0092 astore 9
    0094 getstatic Field(java/lang/System.out:Ljava/io/PrintStream;)
    0097 aload 9
    0099 invokevirtual Method(java/io/PrintStream.println:(Ljava/lang/Object;)V)
    0102 aconst_null
    0103 astore 10
    0105 aload 10
    0107 aconst_null
    0108 if_acmpeq 115
    0111 iconst_1
    0112 goto 116
    0115 iconst_0
    0116 istore 11
    0118 iload 11
    0120 ifeq 151
    0123 aload 10
    0125 checkcast Class(java/lang/String)
    0128 astore 12
    0130 aload 12
    0132 invokevirtual Method(java/lang/String.length:()I)
    0135 istore 13
    0137 iload 13
    0139 invokestatic Method(java/lang/Integer.valueOf:(I)Ljava/lang/Integer;)
    0142 astore 14
    0144 aload 14
    0146 astore 15
    0148 goto 154
    0151 aconst_null
    0152 astore 15
    0154 getstatic Field(java/lang/System.out:Ljava/io/PrintStream;)
    0157 aload 15
    0159 invokevirtual Method(java/io/PrintStream.println:(Ljava/lang/Object;)V)
    0162 return
    sub_attr  StackMapTable (107 bytes)
=======
    0003 aconst_null
    0004 astore_1
    0005 aload_0
    0006 aload_1
    0007 if_acmpeq 35
    0010 aload_0
    0011 checkcast Class(java/lang/String)
    0014 astore_3
    0015 aload_3
    0016 invokevirtual Method(java/lang/String.length:()I)
    0019 istore 4
    0021 iload 4
    0023 invokestatic Method(java/lang/Integer.valueOf:(I)Ljava/lang/Integer;)
    0026 astore 5
    0028 aload 5
    0030 astore 6
    0032 goto 38
    0035 aconst_null
    0036 astore 6
    0038 getstatic Field(java/lang/System.out:Ljava/io/PrintStream;)
    0041 aload 6
    0043 invokevirtual Method(java/io/PrintStream.println:(Ljava/lang/Object;)V)
    0046 aconst_null
    0047 astore 7
    0049 aload_0
    0050 aload 7
    0052 if_acmpne 67
    0055 new Class(java/lang/NullPointerException)
    0058 dup
    0059 invokespecial Method(java/lang/NullPointerException.<init>:()V)
    0062 astore 9
    0064 aload 9
    0066 athrow
    0067 aload_0
    0068 checkcast Class(java/lang/String)
    0071 astore 10
    0073 aload 10
    0075 invokevirtual Method(java/lang/String.toUpperCase:()Ljava/lang/String;)
    0078 astore 11
    0080 getstatic Field(java/lang/System.out:Ljava/io/PrintStream;)
    0083 aload 11
    0085 invokevirtual Method(java/io/PrintStream.println:(Ljava/lang/Object;)V)
    0088 aconst_null
    0089 astore 12
    0091 aconst_null
    0092 astore 13
    0094 aload 12
    0096 aload 13
    0098 if_acmpeq 129
    0101 aload 12
    0103 checkcast Class(java/lang/String)
    0106 astore 15
    0108 aload 15
    0110 invokevirtual Method(java/lang/String.length:()I)
    0113 istore 16
    0115 iload 16
    0117 invokestatic Method(java/lang/Integer.valueOf:(I)Ljava/lang/Integer;)
    0120 astore 17
    0122 aload 17
    0124 astore 18
    0126 goto 132
    0129 aconst_null
    0130 astore 18
    0132 getstatic Field(java/lang/System.out:Ljava/io/PrintStream;)
    0135 aload 18
    0137 invokevirtual Method(java/io/PrintStream.println:(Ljava/lang/Object;)V)
    0140 return
    sub_attr  StackMapTable (118 bytes)
>>>>>>> Stashed changes
method        main ([Ljava/lang/String;)V 0x1009
  code        max_stack=0 max_locals=1
    0000 invokestatic Method(InputKt.main:()V)
    0003 return
