class_version major=61 minor=0
this_class    InputKt
super_class   java/lang/Object
access_flags  0x0031
method        A ()LV; 0x0019
  code        max_stack=1 max_locals=0
    0000 getstatic Field(V.A:LV;)
    0003 areturn
  attr        RuntimeInvisibleAnnotations (6 bytes)
method        B ()LV; 0x0019
  code        max_stack=1 max_locals=0
    0000 getstatic Field(V.B:LV;)
    0003 areturn
  attr        RuntimeInvisibleAnnotations (6 bytes)
method        V$valueOf (Ljava/lang/String;)LV; 0x0019
  code        max_stack=2 max_locals=1
    0000 aload_0
    0001 ldc "name"
    0003 invokestatic Method(kotlin/jvm/internal/Intrinsics.checkNotNullParameter:(Ljava/lang/Object;Ljava/lang/String;)V)
    0006 aload_0
    0007 ldc "A"
    0009 invokestatic Method(kotlin/jvm/internal/Intrinsics.areEqual:(Ljava/lang/Object;Ljava/lang/Object;)Z)
    0012 ifeq 22
    0015 goto 35
    0018 invokestatic Method(InputKt.A:()LV;)
    0021 areturn
    0022 aload_0
    0023 ldc "B"
    0025 invokestatic Method(kotlin/jvm/internal/Intrinsics.areEqual:(Ljava/lang/Object;Ljava/lang/Object;)Z)
    0028 ifeq 18
    0031 invokestatic Method(InputKt.B:()LV;)
    0034 areturn
    0035 invokestatic Method(InputKt.A:()LV;)
    0038 areturn
    sub_attr  StackMapTable (5 bytes)
  attr        RuntimeInvisibleAnnotations (6 bytes)
  attr        RuntimeInvisibleParameterAnnotations (7 bytes)
method        V$values ()Ljava/util/ArrayList; 0x0019
  code        max_stack=2 max_locals=1
    0000 new Class(java/util/ArrayList)
    0003 dup
    0004 invokespecial Method(java/util/ArrayList.<init>:()V)
    0007 astore_0
    0008 aload_0
    0009 invokestatic Method(InputKt.A:()LV;)
    0012 invokevirtual Method(java/util/ArrayList.add:(Ljava/lang/Object;)Z)
    0015 pop
    0016 aload_0
    0017 invokestatic Method(InputKt.B:()LV;)
    0020 invokevirtual Method(java/util/ArrayList.add:(Ljava/lang/Object;)Z)
    0023 pop
    0024 aload_0
    0025 areturn
  attr        RuntimeInvisibleAnnotations (6 bytes)
method        main ()V 0x0019
  code        max_stack=3 max_locals=2
    0000 invokestatic Method(InputKt.A:()LV;)
    0003 astore_0
    0004 new Class(Holder)
    0007 dup
    0008 aload_0
    0009 invokespecial Method(Holder.<init>:(LV;)V)
    0012 astore_1
    0013 aload_1
    0014 invokedynamic InvokeDynamic(invoke:()Lkotlin/jvm/functions/Function1;)
    0019 invokestatic Method(InputKt.pickIt:(LHolder;Lkotlin/jvm/functions/Function1;)I)
    0022 istore_1
    0023 getstatic Field(java/lang/System.out:Ljava/io/PrintStream;)
    0026 iload_1
    0027 invokevirtual Method(java/io/PrintStream.println:(I)V)
    0030 return
method        main ([Ljava/lang/String;)V 0x1009
  code        max_stack=0 max_locals=1
    0000 invokestatic Method(InputKt.main:()V)
    0003 return
method        main$lambda$0 (LHolder;)I 0x001A
  code        max_stack=2 max_locals=2
    0000 aload_0
    0001 ldc "it"
    0003 invokestatic Method(kotlin/jvm/internal/Intrinsics.checkNotNullParameter:(Ljava/lang/Object;Ljava/lang/String;)V)
    0006 aload_0
    0007 invokevirtual Method(Holder.getS:()LV;)
    0010 astore_1
    0011 invokestatic Method(InputKt.A:()LV;)
    0014 aload_1
    0015 swap
    0016 swap
    0017 invokevirtual Method(java/lang/Object.toString:()Ljava/lang/String;)
    0020 swap
    0021 invokevirtual Method(java/lang/Object.toString:()Ljava/lang/String;)
    0024 invokevirtual Method(java/lang/String.equals:(Ljava/lang/Object;)Z)
    0027 ifeq 34
    0030 iconst_1
    0031 goto 35
    0034 iconst_2
    0035 ireturn
    sub_attr  StackMapTable (10 bytes)
method        pickIt (LHolder;Lkotlin/jvm/functions/Function1;)I 0x0019
  code        max_stack=2 max_locals=2
    0000 aload_0
    0001 ldc "h"
    0003 invokestatic Method(kotlin/jvm/internal/Intrinsics.checkNotNullParameter:(Ljava/lang/Object;Ljava/lang/String;)V)
    0006 aload_1
    0007 ldc "fn"
    0009 invokestatic Method(kotlin/jvm/internal/Intrinsics.checkNotNullParameter:(Ljava/lang/Object;Ljava/lang/String;)V)
    0012 aload_1
    0013 aload_0
    0014 invokeinterface InterfaceMethod(kotlin/jvm/functions/Function1.invoke:(Ljava/lang/Object;)Ljava/lang/Object;)
    0019 checkcast Class(java/lang/Number)
    0022 invokevirtual Method(java/lang/Number.intValue:()I)
    0025 ireturn
  attr        Signature (2 bytes)
  attr        RuntimeInvisibleParameterAnnotations (13 bytes)
class_attr    BootstrapMethods (12 bytes)
