class_version major=61 minor=0
this_class    B
super_class   A
access_flags  0x0021
field         y : I 0x0001
method        <init> (I)V 0x0001
  code        max_stack=2 max_locals=3
    0000 iload_1
    0001 iconst_1
    0002 iadd
    0003 istore_2
    0004 aload_0
    0005 iload_2
    0006 invokespecial Method(A.<init>:(I)V)
    0009 aload_0
    0010 iload_1
    0011 putfield Field(B.y:I)
    0014 return
method        f ()I 0x0001
  code        max_stack=3 max_locals=2
    0000 aload_0
    0001 getfield Field(B.y:I)
    0004 istore_1
    0005 aload_0
    0006 getfield Field(A.x:I)
    0009 iload_1
    0010 iadd
    0011 aload_0
    0012 iload_1
    0013 putfield Field(B.y:I)
    0016 ireturn
method        getY ()I 0x0001
  code        max_stack=1 max_locals=1
    0000 aload_0
    0001 getfield Field(B.y:I)
    0004 ireturn
