class_version major=61 minor=0
this_class    InputKt
super_class   java/lang/Object
access_flags  0x0031
method        area (LShape;)I 0x0019
  code        max_stack=2 max_locals=13
    0000 aload_0
    0001 ldc "s"
    0003 invokestatic Method(kotlin/jvm/internal/Intrinsics.checkNotNullParameter:(Ljava/lang/Object;Ljava/lang/String;)V)
    0006 aload_0
    0007 instanceof Class(Circle)
    0010 istore_1
    0011 iload_1
<<<<<<< Updated upstream
    0012 ifeq 50
=======
    0012 ifeq 54
>>>>>>> Stashed changes
    0015 aload_0
    0016 checkcast Class(Circle)
    0019 astore_2
    0020 aload_2
    0021 invokevirtual Method(Circle.getR:()I)
    0024 istore_3
    0025 aload_2
    0026 invokevirtual Method(Circle.getR:()I)
    0029 istore 4
    0031 iload_3
    0032 iload 4
    0034 imul
    0035 istore 5
<<<<<<< Updated upstream
    0037 iload 5
    0039 iconst_3
    0040 imul
    0041 istore 6
    0043 iload 6
    0045 istore 7
    0047 goto 98
    0050 aload_0
    0051 instanceof Class(Rect)
    0054 istore 8
    0056 iload 8
    0058 ifeq 95
    0061 aload_0
    0062 checkcast Class(Rect)
    0065 astore 9
    0067 aload 9
    0069 invokevirtual Method(Rect.getW:()I)
    0072 istore 10
    0074 aload 9
    0076 invokevirtual Method(Rect.getH:()I)
    0079 istore 11
    0081 iload 10
    0083 iload 11
    0085 imul
    0086 istore 12
    0088 iload 12
    0090 istore 7
    0092 goto 98
    0095 iconst_0
    0096 istore 7
    0098 iload 7
    0100 ireturn
    sub_attr  StackMapTable (21 bytes)
=======
    0037 iconst_3
    0038 istore 6
    0040 iload 5
    0042 iload 6
    0044 imul
    0045 istore 7
    0047 iload 7
    0049 istore 8
    0051 goto 102
    0054 aload_0
    0055 instanceof Class(Rect)
    0058 istore 9
    0060 iload 9
    0062 ifeq 99
    0065 aload_0
    0066 checkcast Class(Rect)
    0069 astore 10
    0071 aload 10
    0073 invokevirtual Method(Rect.getW:()I)
    0076 istore 11
    0078 aload 10
    0080 invokevirtual Method(Rect.getH:()I)
    0083 istore 12
    0085 iload 11
    0087 iload 12
    0089 imul
    0090 istore 13
    0092 iload 13
    0094 istore 8
    0096 goto 102
    0099 iconst_0
    0100 istore 8
    0102 iload 8
    0104 ireturn
    sub_attr  StackMapTable (22 bytes)
>>>>>>> Stashed changes
  attr        RuntimeInvisibleParameterAnnotations (7 bytes)
method        main ()V 0x0019
  code        max_stack=4 max_locals=1
    0000 new Class(Circle)
    0003 dup
    0004 iconst_5
    0005 invokespecial Method(Circle.<init>:(I)V)
    0008 checkcast Class(Shape)
    0011 invokestatic Method(InputKt.area:(LShape;)I)
    0014 istore_0
    0015 getstatic Field(java/lang/System.out:Ljava/io/PrintStream;)
    0018 iload_0
    0019 invokevirtual Method(java/io/PrintStream.println:(I)V)
    0022 new Class(Rect)
    0025 dup
    0026 iconst_3
    0027 iconst_4
    0028 invokespecial Method(Rect.<init>:(II)V)
    0031 checkcast Class(Shape)
    0034 invokestatic Method(InputKt.area:(LShape;)I)
    0037 istore_0
    0038 getstatic Field(java/lang/System.out:Ljava/io/PrintStream;)
    0041 iload_0
    0042 invokevirtual Method(java/io/PrintStream.println:(I)V)
    0045 return
method        main ([Ljava/lang/String;)V 0x1009
  code        max_stack=0 max_locals=1
    0000 invokestatic Method(InputKt.main:()V)
    0003 return
